Workbook
Name BD: 輸入頁!$E$7
Name BGP: OP!$C$30
Name CV: P_DATA!$V$273:$EC$539
Name DIE: P_DATA!$EI$2:$IP$268
Name EXP: P_DATA!$V$2:$EC$268
Name GP: P_DATA!$J:$K
Name IN: 輸入頁!$E$5
Name MGP: OP!$C$35
Name PA: P_DATA!$EI$273:$IP$539
Name PI: OP!$AK$4:$AL$90
Name PM: 輸入頁!$E$16
Name PVal: P_DATA!$O:$P
Name SEX: 輸入頁!$K$5
Name WORDING: OP!$P$2:$Q$20
Name WORDINGP: OP!$AD$2:$AE$41
Name YPN: 輸入頁!$D$24
Name 主約1: OP!$H$43:$H$45
Name 保額倍數: OP!$B$87:$C$197
Name 繳: OP!$H$17:$H$21
Name 繳別首: OP!$L$31:$L$35
Name 繳別續: OP!$M$31:$M$35

Sheet 揭露
B1: =OP!$C$56 -> CLX20 | C1: ←帶OP | D1: =IF(OP!$E$16=1,"足歲",IF(OP!$E$16=2,"保險年齡","錯誤")) -> 足歲 | E1: ←帶OP | Q1: 6 | R1: 7 | S1: 8 | T1: 9 | U1: 10 | V1: 11 | W1: 12
L2: 以下3欄要注意最下方要和右側揭露拉齊 | O2: 以下COPY-DB | Q2: 109
C3: 代表年齡第?小→ | D3: 1 | E3: 2 | F3: 3 | G3: 1 | H3: 2 | I3: 3 | K3: 年齡代號轉換 | L3: KEY | M3: 年齡 | N3: 年度 | O3: 險種大類 | P3: 年期險種 | Q3: 性別 | R3: 年齡 | S3: 繳費方式 | T3: 宣告利率 | U3: 繳費金額 | V3: 保單年度 | W3: 揭露利率
C4: 性別男=1，女=2→ | D4: 1 | E4: 1 | F4: 1 | G4: 2 | H4: 2 | I4: 2 | K4: =IF($D$1="足歲","15足歲","15") -> 15足歲 | L4: =IF(P4<>$B$1,"",P4&Q4&R4&V4) | M4: =IF(L4="","-",IF(ISERROR($R4*1),LEFT($R4,2)*1,$R4*1)) -> - | N4: =IF(L4="","",V4*1)
B5: 取第?欄→ | C5: 12 | D5: =IF(SMALL($M:$M,D$3)=15,$K$4,SMALL($M:$M,D$3)) -> #NUM! | E5: =IF(SMALL($M:$M,E$3)=15,$K$4,SMALL($M:$M,E$3)) -> #NUM! | F5: =IF(SMALL($M:$M,F$3)=15,$K$4,SMALL($M:$M,F$3)) -> #NUM! | G5: =IF(SMALL($M:$M,G$3)=15,$K$4,SMALL($M:$M,G$3)) -> #NUM! | H5: =IF(SMALL($M:$M,H$3)=15,$K$4,SMALL($M:$M,H$3)) -> #NUM! | I5: =IF(SMALL($M:$M,I$3)=15,$K$4,SMALL($M:$M,I$3)) -> #NUM! | L5: =IF(P5<>$B$1,"",P5&Q5&R5&V5) | M5: =IF(OR(L5="",COUNTIF($M$4:M4,IF(ISERROR($R5*1),LEFT($R5,2)*1,$R5*1))>=1),"-",IF(ISERROR($R5*1),LEFT($R5,2)*1,$R5*1)) -> - | N5: =IF(OR(L5="",COUNTIF($N$4:N4,V5*1)>=1),"-",V5*1) -> -
B6: 第?小↓ | C6: 保單年度 | D6: =IF(OR(ISERROR($D5)),"",IF(N(D$5)=0,D$5&"歲"&IF(D$4=1,"男性",IF(D$4=2,"女性","")),D$5&"歲"&IF(D$4=1,"男性",IF(D$4=2,"女性","")))) | E6: =IF(OR(ISERROR($D5)),"",IF(N(E$5)=0,E$5&"歲"&IF(E$4=1,"男性",IF(E$4=2,"女性","")),E$5&"歲"&IF(E$4=1,"男性",IF(E$4=2,"女性","")))) | F6: =IF(OR(ISERROR($D5)),"",IF(N(F$5)=0,F$5&"歲"&IF(F$4=1,"男性",IF(F$4=2,"女性","")),F$5&"歲"&IF(F$4=1,"男性",IF(F$4=2,"女性","")))) | G6: =IF(OR(ISERROR($D5)),"",IF(N(G$5)=0,G$5&"歲"&IF(G$4=1,"男性",IF(G$4=2,"女性","")),G$5&"歲"&IF(G$4=1,"男性",IF(G$4=2,"女性","")))) | H6: =IF(OR(ISERROR($D5)),"",IF(N(H$5)=0,H$5&"歲"&IF(H$4=1,"男性",IF(H$4=2,"女性","")),H$5&"歲"&IF(H$4=1,"男性",IF(H$4=2,"女性","")))) | I6: =IF(OR(ISERROR($D5)),"",IF(N(I$5)=0,I$5&"歲"&IF(I$4=1,"男性",IF(I$4=2,"女性","")),I$5&"歲"&IF(I$4=1,"男性",IF(I$4=2,"女性","")))) | L6: =IF(P6<>$B$1,"",P6&Q6&R6&V6) | M6: =IF(OR(L6="",COUNTIF($M$4:M5,IF(ISERROR($R6*1),LEFT($R6,2)*1,$R6*1))>=1),"-",IF(ISERROR($R6*1),LEFT($R6,2)*1,$R6*1)) -> - | N6: =IF(OR(L6="",COUNTIF($N$4:N5,V6*1)>=1),"-",V6*1) -> -
B7: 1 | C7: =IF(ISERROR(SMALL($N:$N,$B7)),"",SMALL($N:$N,$B7)) | D7: =IF(ISERROR(VLOOKUP($B$1&D$4&D$5&$C7,$L:$W,$C$5,0)),"",VLOOKUP($B$1&D$4&D$5&$C7,$L:$W,$C$5,0)) | E7: =IF(ISERROR(VLOOKUP($B$1&E$4&E$5&$C7,$L:$W,$C$5,0)),"",VLOOKUP($B$1&E$4&E$5&$C7,$L:$W,$C$5,0)) | F7: =IF(ISERROR(VLOOKUP($B$1&F$4&F$5&$C7,$L:$W,$C$5,0)),"",VLOOKUP($B$1&F$4&F$5&$C7,$L:$W,$C$5,0)) | G7: =IF(ISERROR(VLOOKUP($B$1&G$4&G$5&$C7,$L:$W,$C$5,0)),"",VLOOKUP($B$1&G$4&G$5&$C7,$L:$W,$C$5,0)) | H7: =IF(ISERROR(VLOOKUP($B$1&H$4&H$5&$C7,$L:$W,$C$5,0)),"",VLOOKUP($B$1&H$4&H$5&$C7,$L:$W,$C$5,0)) | I7: =IF(ISERROR(VLOOKUP($B$1&I$4&I$5&$C7,$L:$W,$C$5,0)),"",VLOOKUP($B$1&I$4&I$5&$C7,$L:$W,$C$5,0)) | L7: =IF(P7<>$B$1,"",P7&Q7&R7&V7) | M7: =IF(OR(L7="",COUNTIF($M$4:M6,IF(ISERROR($R7*1),LEFT($R7,2)*1,$R7*1))>=1),"-",IF(ISERROR($R7*1),LEFT($R7,2)*1,$R7*1)) -> - | N7: =IF(OR(L7="",COUNTIF($N$4:N6,V7*1)>=1),"-",V7*1) -> -
B8: 2 | C8: =IF(ISERROR(SMALL($N:$N,$B8)),"",SMALL($N:$N,$B8)) | D8: =IF(ISERROR(VLOOKUP($B$1&D$4&D$5&$C8,$L:$W,$C$5,0)),"",VLOOKUP($B$1&D$4&D$5&$C8,$L:$W,$C$5,0)) | E8: =IF(ISERROR(VLOOKUP($B$1&E$4&E$5&$C8,$L:$W,$C$5,0)),"",VLOOKUP($B$1&E$4&E$5&$C8,$L:$W,$C$5,0)) | F8: =IF(ISERROR(VLOOKUP($B$1&F$4&F$5&$C8,$L:$W,$C$5,0)),"",VLOOKUP($B$1&F$4&F$5&$C8,$L:$W,$C$5,0)) | G8: =IF(ISERROR(VLOOKUP($B$1&G$4&G$5&$C8,$L:$W,$C$5,0)),"",VLOOKUP($B$1&G$4&G$5&$C8,$L:$W,$C$5,0)) | H8: =IF(ISERROR(VLOOKUP($B$1&H$4&H$5&$C8,$L:$W,$C$5,0)),"",VLOOKUP($B$1&H$4&H$5&$C8,$L:$W,$C$5,0)) | I8: =IF(ISERROR(VLOOKUP($B$1&I$4&I$5&$C8,$L:$W,$C$5,0)),"",VLOOKUP($B$1&I$4&I$5&$C8,$L:$W,$C$5,0)) | L8: =IF(P8<>$B$1,"",P8&Q8&R8&V8) | M8: =IF(OR(L8="",COUNTIF($M$4:M7,IF(ISERROR($R8*1),LEFT($R8,2)*1,$R8*1))>=1),"-",IF(ISERROR($R8*1),LEFT($R8,2)*1,$R8*1)) -> - | N8: =IF(OR(L8="",COUNTIF($N$4:N7,V8*1)>=1),"-",V8*1) -> -
B9: 3 | C9: =IF(ISERROR(SMALL($N:$N,$B9)),"",SMALL($N:$N,$B9)) | D9: =IF(ISERROR(VLOOKUP($B$1&D$4&D$5&$C9,$L:$W,$C$5,0)),"",VLOOKUP($B$1&D$4&D$5&$C9,$L:$W,$C$5,0)) | E9: =IF(ISERROR(VLOOKUP($B$1&E$4&E$5&$C9,$L:$W,$C$5,0)),"",VLOOKUP($B$1&E$4&E$5&$C9,$L:$W,$C$5,0)) | F9: =IF(ISERROR(VLOOKUP($B$1&F$4&F$5&$C9,$L:$W,$C$5,0)),"",VLOOKUP($B$1&F$4&F$5&$C9,$L:$W,$C$5,0)) | G9: =IF(ISERROR(VLOOKUP($B$1&G$4&G$5&$C9,$L:$W,$C$5,0)),"",VLOOKUP($B$1&G$4&G$5&$C9,$L:$W,$C$5,0)) | H9: =IF(ISERROR(VLOOKUP($B$1&H$4&H$5&$C9,$L:$W,$C$5,0)),"",VLOOKUP($B$1&H$4&H$5&$C9,$L:$W,$C$5,0)) | I9: =IF(ISERROR(VLOOKUP($B$1&I$4&I$5&$C9,$L:$W,$C$5,0)),"",VLOOKUP($B$1&I$4&I$5&$C9,$L:$W,$C$5,0)) | L9: =IF(P9<>$B$1,"",P9&Q9&R9&V9) | M9: =IF(OR(L9="",COUNTIF($M$4:M8,IF(ISERROR($R9*1),LEFT($R9,2)*1,$R9*1))>=1),"-",IF(ISERROR($R9*1),LEFT($R9,2)*1,$R9*1)) -> - | N9: =IF(OR(L9="",COUNTIF($N$4:N8,V9*1)>=1),"-",V9*1) -> -
B10: 4 | C10: =IF(ISERROR(SMALL($N:$N,$B10)),"",SMALL($N:$N,$B10)) | D10: =IF(ISERROR(VLOOKUP($B$1&D$4&D$5&$C10,$L:$W,$C$5,0)),"",VLOOKUP($B$1&D$4&D$5&$C10,$L:$W,$C$5,0)) | E10: =IF(ISERROR(VLOOKUP($B$1&E$4&E$5&$C10,$L:$W,$C$5,0)),"",VLOOKUP($B$1&E$4&E$5&$C10,$L:$W,$C$5,0)) | F10: =IF(ISERROR(VLOOKUP($B$1&F$4&F$5&$C10,$L:$W,$C$5,0)),"",VLOOKUP($B$1&F$4&F$5&$C10,$L:$W,$C$5,0)) | G10: =IF(ISERROR(VLOOKUP($B$1&G$4&G$5&$C10,$L:$W,$C$5,0)),"",VLOOKUP($B$1&G$4&G$5&$C10,$L:$W,$C$5,0)) | H10: =IF(ISERROR(VLOOKUP($B$1&H$4&H$5&$C10,$L:$W,$C$5,0)),"",VLOOKUP($B$1&H$4&H$5&$C10,$L:$W,$C$5,0)) | I10: =IF(ISERROR(VLOOKUP($B$1&I$4&I$5&$C10,$L:$W,$C$5,0)),"",VLOOKUP($B$1&I$4&I$5&$C10,$L:$W,$C$5,0)) | L10: =IF(P10<>$B$1,"",P10&Q10&R10&V10) | M10: =IF(OR(L10="",COUNTIF($M$4:M9,IF(ISERROR($R10*1),LEFT($R10,2)*1,$R10*1))>=1),"-",IF(ISERROR($R10*1),LEFT($R10,2)*1,$R10*1)) -> - | N10: =IF(OR(L10="",COUNTIF($N$4:N9,V10*1)>=1),"-",V10*1) -> -
B11: 5 | C11: =IF(ISERROR(SMALL($N:$N,$B11)),"",SMALL($N:$N,$B11)) | D11: =IF(ISERROR(VLOOKUP($B$1&D$4&D$5&$C11,$L:$W,$C$5,0)),"",VLOOKUP($B$1&D$4&D$5&$C11,$L:$W,$C$5,0)) | E11: =IF(ISERROR(VLOOKUP($B$1&E$4&E$5&$C11,$L:$W,$C$5,0)),"",VLOOKUP($B$1&E$4&E$5&$C11,$L:$W,$C$5,0)) | F11: =IF(ISERROR(VLOOKUP($B$1&F$4&F$5&$C11,$L:$W,$C$5,0)),"",VLOOKUP($B$1&F$4&F$5&$C11,$L:$W,$C$5,0)) | G11: =IF(ISERROR(VLOOKUP($B$1&G$4&G$5&$C11,$L:$W,$C$5,0)),"",VLOOKUP($B$1&G$4&G$5&$C11,$L:$W,$C$5,0)) | H11: =IF(ISERROR(VLOOKUP($B$1&H$4&H$5&$C11,$L:$W,$C$5,0)),"",VLOOKUP($B$1&H$4&H$5&$C11,$L:$W,$C$5,0)) | I11: =IF(ISERROR(VLOOKUP($B$1&I$4&I$5&$C11,$L:$W,$C$5,0)),"",VLOOKUP($B$1&I$4&I$5&$C11,$L:$W,$C$5,0)) | L11: =IF(P11<>$B$1,"",P11&Q11&R11&V11) | M11: =IF(OR(L11="",COUNTIF($M$4:M10,IF(ISERROR($R11*1),LEFT($R11,2)*1,$R11*1))>=1),"-",IF(ISERROR($R11*1),LEFT($R11,2)*1,$R11*1)) -> - | N11: =IF(OR(L11="",COUNTIF($N$4:N10,V11*1)>=1),"-",V11*1) -> -
B12: 6 | C12: =IF(ISERROR(SMALL($N:$N,$B12)),"",SMALL($N:$N,$B12)) | D12: =IF(ISERROR(VLOOKUP($B$1&D$4&D$5&$C12,$L:$W,$C$5,0)),"",VLOOKUP($B$1&D$4&D$5&$C12,$L:$W,$C$5,0)) | E12: =IF(ISERROR(VLOOKUP($B$1&E$4&E$5&$C12,$L:$W,$C$5,0)),"",VLOOKUP($B$1&E$4&E$5&$C12,$L:$W,$C$5,0)) | F12: =IF(ISERROR(VLOOKUP($B$1&F$4&F$5&$C12,$L:$W,$C$5,0)),"",VLOOKUP($B$1&F$4&F$5&$C12,$L:$W,$C$5,0)) | G12: =IF(ISERROR(VLOOKUP($B$1&G$4&G$5&$C12,$L:$W,$C$5,0)),"",VLOOKUP($B$1&G$4&G$5&$C12,$L:$W,$C$5,0)) | H12: =IF(ISERROR(VLOOKUP($B$1&H$4&H$5&$C12,$L:$W,$C$5,0)),"",VLOOKUP($B$1&H$4&H$5&$C12,$L:$W,$C$5,0)) | I12: =IF(ISERROR(VLOOKUP($B$1&I$4&I$5&$C12,$L:$W,$C$5,0)),"",VLOOKUP($B$1&I$4&I$5&$C12,$L:$W,$C$5,0)) | L12: =IF(P12<>$B$1,"",P12&Q12&R12&V12) | M12: =IF(OR(L12="",COUNTIF($M$4:M11,IF(ISERROR($R12*1),LEFT($R12,2)*1,$R12*1))>=1),"-",IF(ISERROR($R12*1),LEFT($R12,2)*1,$R12*1)) -> - | N12: =IF(OR(L12="",COUNTIF($N$4:N11,V12*1)>=1),"-",V12*1) -> -
B13: 7 | C13: =IF(ISERROR(SMALL($N:$N,$B13)),"",SMALL($N:$N,$B13)) | D13: =IF(ISERROR(VLOOKUP($B$1&D$4&D$5&$C13,$L:$W,$C$5,0)),"",VLOOKUP($B$1&D$4&D$5&$C13,$L:$W,$C$5,0)) | E13: =IF(ISERROR(VLOOKUP($B$1&E$4&E$5&$C13,$L:$W,$C$5,0)),"",VLOOKUP($B$1&E$4&E$5&$C13,$L:$W,$C$5,0)) | F13: =IF(ISERROR(VLOOKUP($B$1&F$4&F$5&$C13,$L:$W,$C$5,0)),"",VLOOKUP($B$1&F$4&F$5&$C13,$L:$W,$C$5,0)) | G13: =IF(ISERROR(VLOOKUP($B$1&G$4&G$5&$C13,$L:$W,$C$5,0)),"",VLOOKUP($B$1&G$4&G$5&$C13,$L:$W,$C$5,0)) | H13: =IF(ISERROR(VLOOKUP($B$1&H$4&H$5&$C13,$L:$W,$C$5,0)),"",VLOOKUP($B$1&H$4&H$5&$C13,$L:$W,$C$5,0)) | I13: =IF(ISERROR(VLOOKUP($B$1&I$4&I$5&$C13,$L:$W,$C$5,0)),"",VLOOKUP($B$1&I$4&I$5&$C13,$L:$W,$C$5,0)) | L13: =IF(P13<>$B$1,"",P13&Q13&R13&V13) | M13: =IF(OR(L13="",COUNTIF($M$4:M12,IF(ISERROR($R13*1),LEFT($R13,2)*1,$R13*1))>=1),"-",IF(ISERROR($R13*1),LEFT($R13,2)*1,$R13*1)) -> - | N13: =IF(OR(L13="",COUNTIF($N$4:N12,V13*1)>=1),"-",V13*1) -> -
B14: 8 | C14: =IF(ISERROR(SMALL($N:$N,$B14)),"",SMALL($N:$N,$B14)) | D14: =IF(ISERROR(VLOOKUP($B$1&D$4&D$5&$C14,$L:$W,$C$5,0)),"",VLOOKUP($B$1&D$4&D$5&$C14,$L:$W,$C$5,0)) | E14: =IF(ISERROR(VLOOKUP($B$1&E$4&E$5&$C14,$L:$W,$C$5,0)),"",VLOOKUP($B$1&E$4&E$5&$C14,$L:$W,$C$5,0)) | F14: =IF(ISERROR(VLOOKUP($B$1&F$4&F$5&$C14,$L:$W,$C$5,0)),"",VLOOKUP($B$1&F$4&F$5&$C14,$L:$W,$C$5,0)) | G14: =IF(ISERROR(VLOOKUP($B$1&G$4&G$5&$C14,$L:$W,$C$5,0)),"",VLOOKUP($B$1&G$4&G$5&$C14,$L:$W,$C$5,0)) | H14: =IF(ISERROR(VLOOKUP($B$1&H$4&H$5&$C14,$L:$W,$C$5,0)),"",VLOOKUP($B$1&H$4&H$5&$C14,$L:$W,$C$5,0)) | I14: =IF(ISERROR(VLOOKUP($B$1&I$4&I$5&$C14,$L:$W,$C$5,0)),"",VLOOKUP($B$1&I$4&I$5&$C14,$L:$W,$C$5,0)) | L14: =IF(P14<>$B$1,"",P14&Q14&R14&V14) | M14: =IF(OR(L14="",COUNTIF($M$4:M13,IF(ISERROR($R14*1),LEFT($R14,2)*1,$R14*1))>=1),"-",IF(ISERROR($R14*1),LEFT($R14,2)*1,$R14*1)) -> - | N14: =IF(OR(L14="",COUNTIF($N$4:N13,V14*1)>=1),"-",V14*1) -> -
C15: 以上區域為帶入列印頁範圍 | L15: =IF(P15<>$B$1,"",P15&Q15&R15&V15) | M15: =IF(OR(L15="",COUNTIF($M$4:M14,IF(ISERROR($R15*1),LEFT($R15,2)*1,$R15*1))>=1),"-",IF(ISERROR($R15*1),LEFT($R15,2)*1,$R15*1)) -> - | N15: =IF(OR(L15="",COUNTIF($N$4:N14,V15*1)>=1),"-",V15*1) -> -
L16: =IF(P16<>$B$1,"",P16&Q16&R16&V16) | M16: =IF(OR(L16="",COUNTIF($M$4:M15,IF(ISERROR($R16*1),LEFT($R16,2)*1,$R16*1))>=1),"-",IF(ISERROR($R16*1),LEFT($R16,2)*1,$R16*1)) -> - | N16: =IF(OR(L16="",COUNTIF($N$4:N15,V16*1)>=1),"-",V16*1) -> -
L17: =IF(P17<>$B$1,"",P17&Q17&R17&V17) | M17: =IF(OR(L17="",COUNTIF($M$4:M16,IF(ISERROR($R17*1),LEFT($R17,2)*1,$R17*1))>=1),"-",IF(ISERROR($R17*1),LEFT($R17,2)*1,$R17*1)) -> - | N17: =IF(OR(L17="",COUNTIF($N$4:N16,V17*1)>=1),"-",V17*1) -> -
L18: =IF(P18<>$B$1,"",P18&Q18&R18&V18) | M18: =IF(OR(L18="",COUNTIF($M$4:M17,IF(ISERROR($R18*1),LEFT($R18,2)*1,$R18*1))>=1),"-",IF(ISERROR($R18*1),LEFT($R18,2)*1,$R18*1)) -> - | N18: =IF(OR(L18="",COUNTIF($N$4:N17,V18*1)>=1),"-",V18*1) -> -
L19: =IF(P19<>$B$1,"",P19&Q19&R19&V19) | M19: =IF(OR(L19="",COUNTIF($M$4:M18,IF(ISERROR($R19*1),LEFT($R19,2)*1,$R19*1))>=1),"-",IF(ISERROR($R19*1),LEFT($R19,2)*1,$R19*1)) -> - | N19: =IF(OR(L19="",COUNTIF($N$4:N18,V19*1)>=1),"-",V19*1) -> -
L20: =IF(P20<>$B$1,"",P20&Q20&R20&V20) | M20: =IF(OR(L20="",COUNTIF($M$4:M19,IF(ISERROR($R20*1),LEFT($R20,2)*1,$R20*1))>=1),"-",IF(ISERROR($R20*1),LEFT($R20,2)*1,$R20*1)) -> - | N20: =IF(OR(L20="",COUNTIF($N$4:N19,V20*1)>=1),"-",V20*1) -> -
L21: =IF(P21<>$B$1,"",P21&Q21&R21&V21) | M21: =IF(OR(L21="",COUNTIF($M$4:M20,IF(ISERROR($R21*1),LEFT($R21,2)*1,$R21*1))>=1),"-",IF(ISERROR($R21*1),LEFT($R21,2)*1,$R21*1)) -> - | N21: =IF(OR(L21="",COUNTIF($N$4:N20,V21*1)>=1),"-",V21*1) -> -
L22: =IF(P22<>$B$1,"",P22&Q22&R22&V22) | M22: =IF(OR(L22="",COUNTIF($M$4:M21,IF(ISERROR($R22*1),LEFT($R22,2)*1,$R22*1))>=1),"-",IF(ISERROR($R22*1),LEFT($R22,2)*1,$R22*1)) -> - | N22: =IF(OR(L22="",COUNTIF($N$4:N21,V22*1)>=1),"-",V22*1) -> -
L23: =IF(P23<>$B$1,"",P23&Q23&R23&V23) | M23: =IF(OR(L23="",COUNTIF($M$4:M22,IF(ISERROR($R23*1),LEFT($R23,2)*1,$R23*1))>=1),"-",IF(ISERROR($R23*1),LEFT($R23,2)*1,$R23*1)) -> - | N23: =IF(OR(L23="",COUNTIF($N$4:N22,V23*1)>=1),"-",V23*1) -> -
L24: =IF(P24<>$B$1,"",P24&Q24&R24&V24) | M24: =IF(OR(L24="",COUNTIF($M$4:M23,IF(ISERROR($R24*1),LEFT($R24,2)*1,$R24*1))>=1),"-",IF(ISERROR($R24*1),LEFT($R24,2)*1,$R24*1)) -> - | N24: =IF(OR(L24="",COUNTIF($N$4:N23,V24*1)>=1),"-",V24*1) -> -
L25: =IF(P25<>$B$1,"",P25&Q25&R25&V25) | M25: =IF(OR(L25="",COUNTIF($M$4:M24,IF(ISERROR($R25*1),LEFT($R25,2)*1,$R25*1))>=1),"-",IF(ISERROR($R25*1),LEFT($R25,2)*1,$R25*1)) -> - | N25: =IF(OR(L25="",COUNTIF($N$4:N24,V25*1)>=1),"-",V25*1) -> -
L26: =IF(P26<>$B$1,"",P26&Q26&R26&V26) | M26: =IF(OR(L26="",COUNTIF($M$4:M25,IF(ISERROR($R26*1),LEFT($R26,2)*1,$R26*1))>=1),"-",IF(ISERROR($R26*1),LEFT($R26,2)*1,$R26*1)) -> - | N26: =IF(OR(L26="",COUNTIF($N$4:N25,V26*1)>=1),"-",V26*1) -> -
L27: =IF(P27<>$B$1,"",P27&Q27&R27&V27) | M27: =IF(OR(L27="",COUNTIF($M$4:M26,IF(ISERROR($R27*1),LEFT($R27,2)*1,$R27*1))>=1),"-",IF(ISERROR($R27*1),LEFT($R27,2)*1,$R27*1)) -> - | N27: =IF(OR(L27="",COUNTIF($N$4:N26,V27*1)>=1),"-",V27*1) -> -
... L339: =IF(P339<>$B$1,"",P339&Q339&R339&V339) | M339: =IF(OR(L339="",COUNTIF($M$4:M338,IF(ISERROR($R339*1),LEFT($R339,2)*1,$R339*1))>=1),"-",IF(ISERROR($R339*1),LEFT($R339,2)*1,$R339*1)) -> - | N339: =IF(OR(L339="",COUNTIF($N$4:N338,V339*1)>=1),"-",V339*1) -> -

Sheet P_DATA
A1: GP | B1: CLX | C1: 1150109 | J1: =B1&TEXT(F1,"00")&TEXT(H1,"00") -> CLX0000 | O1: =M1&TEXT(N1,"00") -> 00 | R1: EXP | S1: 1150109 | V1: =S1&TEXT(T1,"00")&TEXT(U1,"00") -> 11501090000 | EE1: DIE | EF1: 1150109 | EI1: =EF1&TEXT(EG1,"00")&TEXT(EH1,"00") -> 11501090000
A2: 版次 | B2: 商品代號 | C2: 職業等級 | D2: 年期 | E2: 保額代碼 | F2: 性別 | G2: 投保金額 | H2: 年齡 | I2: 繳費年度 | J2: =B2&TEXT(F2,"00")&TEXT(H2,"00") -> 商品代號性別年齡 | K2: 保費 | M2: 商品代號 | N2: 累計給付年度 | O2: =M2&TEXT(N2,"00") -> 商品代號累計給付年度 | P2: 給付數值 | R2: 版次 | S2: 商品代號 | T2: 性別 | U2: 年齡 | V2: =S2&TEXT(T2,"00")&TEXT(U2,"00") -> 商品代號性別年齡 | W2: 第1年祝壽保險金 | X2: 第2年祝壽保險金 | Y2: 第3年祝壽保險金 | Z2: 第4年祝壽保險金 | AA2: 第5年祝壽保險金 | AB2: 第6年祝壽保險金 | AC2: 第7年祝壽保險金 | AD2: 第8年祝壽保險金 | AE2: 第9年祝壽保險金 | AF2: 第10年祝壽保險金 | AG2: 第11年祝壽保險金 | AH2: 第12年祝壽保險金 | AI2: 第13年祝壽保險金 | AJ2: 第14年祝壽保險金 | AK2: 第15年祝壽保險金 | AL2: 第16年祝壽保險金 | AM2: 第17年祝壽保險金 | AN2: 第18年祝壽保險金 | AO2: 第19年祝壽保險金 | AP2: 第20年祝壽保險金 | AQ2: 第21年祝壽保險金 | AR2: 第22年祝壽保險金 | AS2: 第23年祝壽保險金 | AT2: 第24年祝壽保險金 | AU2: 第25年祝壽保險金 | AV2: 第26年祝壽保險金 | AW2: 第27年祝壽保險金 | AX2: 第28年祝壽保險金 | AY2: 第29年祝壽保險金 | AZ2: 第30年祝壽保險金 | BA2: 第31年祝壽保險金 | BB2: 第32年祝壽保險金 | BC2: 第33年祝壽保險金 | BD2: 第34年祝壽保險金 | BE2: 第35年祝壽保險金 | BF2: 第36年祝壽保險金 | BG2: 第37年祝壽保險金 | BH2: 第38年祝壽保險金 | BI2: 第39年祝壽保險金 | BJ2: 第40年祝壽保險金 | BK2: 第41年祝壽保險金 | BL2: 第42年祝壽保險金 | BM2: 第43年祝壽保險金 | BN2: 第44年祝壽保險金 | BO2: 第45年祝壽保險金 | BP2: 第46年祝壽保險金 | BQ2: 第47年祝壽保險金 | BR2: 第48年祝壽保險金 | BS2: 第49年祝壽保險金 | BT2: 第50年祝壽保險金 | BU2: 第51年祝壽保險金 | BV2: 第52年祝壽保險金 | BW2: 第53年祝壽保險金 | BX2: 第54年祝壽保險金 | BY2: 第55年祝壽保險金 | BZ2: 第56年祝壽保險金 | CA2: 第57年祝壽保險金 | CB2: 第58年祝壽保險金 | CC2: 第59年祝壽保險金 | CD2: 第60年祝壽保險金 | CE2: 第61年祝壽保險金 | CF2: 第62年祝壽保險金 | CG2: 第63年祝壽保險金 | CH2: 第64年祝壽保險金 | CI2: 第65年祝壽保險金 | CJ2: 第66年祝壽保險金 | CK2: 第67年祝壽保險金 | CL2: 第68年祝壽保險金 | CM2: 第69年祝壽保險金 | CN2: 第70年祝壽保險金 | CO2: 第71年祝壽保險金 | CP2: 第72年祝壽保險金 | CQ2: 第73年祝壽保險金 | CR2: 第74年祝壽保險金 | CS2: 第75年祝壽保險金 | CT2: 第76年祝壽保險金 | CU2: 第77年祝壽保險金 | CV2: 第78年祝壽保險金 | CW2: 第79年祝壽保險金 | CX2: 第80年祝壽保險金 | CY2: 第81年祝壽保險金 | CZ2: 第82年祝壽保險金 | DA2: 第83年祝壽保險金 | DB2: 第84年祝壽保險金 | DC2: 第85年祝壽保險金 | DD2: 第86年祝壽保險金 | DE2: 第87年祝壽保險金 | DF2: 第88年祝壽保險金 | DG2: 第89年祝壽保險金 | DH2: 第90年祝壽保險金 | DI2: 第91年祝壽保險金 | DJ2: 第92年祝壽保險金 | DK2: 第93年祝壽保險金 | DL2: 第94年祝壽保險金 | DM2: 第95年祝壽保險金 | DN2: 第96年祝壽保險金 | DO2: 第97年祝壽保險金 | DP2: 第98年祝壽保險金 | DQ2: 第99年祝壽保險金 | DR2: 第100年祝壽保險金 | DS2: 第101年祝壽保險金 | DT2: 第102年祝壽保險金 | DU2: 第103年祝壽保險金 | DV2: 第104年祝壽保險金 | DW2: 第105年祝壽保險金 | DX2: 第106年祝壽保險金 | DY2: 第107年祝壽保險金 | DZ2: 第108年祝壽保險金 | EA2: 第109年祝壽保險金 | EB2: 第110年祝壽保險金 | EC2: 第111年祝壽保險金 | EE2: 版次 | EF2: 商品代號 | EG2: 性別 | EH2: 年齡 | EI2: =EF2&TEXT(EG2,"00")&TEXT(EH2,"00") -> 商品代號性別年齡 | EJ2: 第1年身故保險金 | EK2: 第2年身故保險金 | EL2: 第3年身故保險金 | EM2: 第4年身故保險金 | EN2: 第5年身故保險金 | EO2: 第6年身故保險金 | EP2: 第7年身故保險金 | EQ2: 第8年身故保險金 | ER2: 第9年身故保險金 | ES2: 第10年身故保險金 | ET2: 第11年身故保險金 | EU2: 第12年身故保險金 | EV2: 第13年身故保險金 | EW2: 第14年身故保險金 | EX2: 第15年身故保險金 | EY2: 第16年身故保險金 | EZ2: 第17年身故保險金 | FA2: 第18年身故保險金 | FB2: 第19年身故保險金 | FC2: 第20年身故保險金 | FD2: 第21年身故保險金 | FE2: 第22年身故保險金 | FF2: 第23年身故保險金 | FG2: 第24年身故保險金 | FH2: 第25年身故保險金 | FI2: 第26年身故保險金 | FJ2: 第27年身故保險金 | FK2: 第28年身故保險金 | FL2: 第29年身故保險金 | FM2: 第30年身故保險金 | FN2: 第31年身故保險金 | FO2: 第32年身故保險金 | FP2: 第33年身故保險金 | FQ2: 第34年身故保險金 | FR2: 第35年身故保險金 | FS2: 第36年身故保險金 | FT2: 第37年身故保險金 | FU2: 第38年身故保險金 | FV2: 第39年身故保險金 | FW2: 第40年身故保險金 | FX2: 第41年身故保險金 | FY2: 第42年身故保險金 | FZ2: 第43年身故保險金 | GA2: 第44年身故保險金 | GB2: 第45年身故保險金 | GC2: 第46年身故保險金 | GD2: 第47年身故保險金 | GE2: 第48年身故保險金 | GF2: 第49年身故保險金 | GG2: 第50年身故保險金 | GH2: 第51年身故保險金 | GI2: 第52年身故保險金 | GJ2: 第53年身故保險金 | GK2: 第54年身故保險金 | GL2: 第55年身故保險金 | GM2: 第56年身故保險金 | GN2: 第57年身故保險金 | GO2: 第58年身故保險金 | GP2: 第59年身故保險金 | GQ2: 第60年身故保險金 | GR2: 第61年身故保險金 | GS2: 第62年身故保險金 | GT2: 第63年身故保險金 | GU2: 第64年身故保險金 | GV2: 第65年身故保險金 | GW2: 第66年身故保險金 | GX2: 第67年身故保險金 | GY2: 第68年身故保險金 | GZ2: 第69年身故保險金 | HA2: 第70年身故保險金 | HB2: 第71年身故保險金 | HC2: 第72年身故保險金 | HD2: 第73年身故保險金 | HE2: 第74年身故保險金額 | HF2: 第75年身故保險金 | HG2: 第76年身故保險金 | HH2: 第77年身故保險金 | HI2: 第78年身故保險金 | HJ2: 第79年身故保險金 | HK2: 第80年身故保險金 | HL2: 第81年身故保險金 | HM2: 第82年身故保險金 | HN2: 第83年身故保險金 | HO2: 第84年身故保險金 | HP2: 第85年身故保險金 | HQ2: 第86年身故保險金 | HR2: 第87年身故保險金 | HS2: 第88年身故保險金 | HT2: 第89年身故保險金 | HU2: 第90年身故保險金 | HV2: 第91年身故保險金 | HW2: 第92年身故保險金 | HX2: 第93年身故保險金 | HY2: 第94年身故保險金 | HZ2: 第95年身故保險金 | IA2: 第96年身故保險金 | IB2: 第97年身故保險金 | IC2: 第98年身故保險金 | ID2: 第99年身故保險金 | IE2: 第100年身故保險金 | IF2: 第101年身故保險金 | IG2: 第102年身故保險金 | IH2: 第103年身故保險金 | II2: 第104年身故保險金 | IJ2: 第105年身故保險金 | IK2: 第106年身故保險金 | IL2: 第107年身故保險金 | IM2: 第108年身故保險金 | IN2: 第109年身故保險金 | IO2: 第110年身故保險金 | IP2: 第111年身故保險金
A3: 55 | B3: CLX10 | F3: 2 | H3: 18 | J3: =B3&TEXT(F3,"00")&TEXT(H3,"00") -> CLX100218 | K3: 435 | R3: 55 | S3: CLX10 | T3: 2 | U3: 18 | V3: =S3&TEXT(T3,"00")&TEXT(U3,"00") -> CLX100218 | W3: 0 | X3: 0 | Y3: 0 | Z3: 0 | AA3: 0 | AB3: 0 | AC3: 0 | AD3: 0 | AE3: 0 | AF3: 0 | AG3: 0 | AH3: 0 | AI3: 0 | AJ3: 0 | AK3: 0 | AL3: 0 | AM3: 0 | AN3: 0 | AO3: 0 | AP3: 0 | AQ3: 0 | AR3: 0 | AS3: 0 | AT3: 0 | AU3: 0 | AV3: 0 | AW3: 0 | AX3: 0 | AY3: 0 | AZ3: 0 | BA3: 0 | BB3: 0 | BC3: 0 | BD3: 0 | BE3: 0 | BF3: 0 | BG3: 0 | BH3: 0 | BI3: 0 | BJ3: 0 | BK3: 0 | BL3: 0 | BM3: 0 | BN3: 0 | BO3: 0 | BP3: 0 | BQ3: 0 | BR3: 0 | BS3: 0 | BT3: 0 | BU3: 0 | BV3: 0 | BW3: 0 | BX3: 0 | BY3: 0 | BZ3: 0 | CA3: 0 | CB3: 0 | CC3: 0 | CD3: 0 | CE3: 0 | CF3: 0 | CG3: 0 | CH3: 0 | CI3: 0 | CJ3: 0 | CK3: 0 | CL3: 0 | CM3: 0 | CN3: 0 | CO3: 0 | CP3: 4611 | CQ3: 0 | CR3: 0 | CS3: 0 | CT3: 0 | CU3: 0 | CV3: 0 | CW3: 0 | CX3: 0 | CY3: 0 | CZ3: 0 | DA3: 0 | DB3: 0 | DC3: 0 | DD3: 0 | DE3: 0 | DF3: 0 | DG3: 0 | DH3: 0 | DI3: 0 | DJ3: 0 | DK3: 0 | DL3: 0 | DM3: 0 | DN3: 0 | DO3: 0 | DP3: 0 | DQ3: 0 | DR3: 0 | DS3: 0 | DT3: 0 | DU3: 0 | DV3: 0 | EE3: 55 | EF3: CLX10 | EG3: 2 | EH3: 18 | EI3: =EF3&TEXT(EG3,"00")&TEXT(EH3,"00") -> CLX100218 | EJ3: 461.1 | EK3: 922.2 | EL3: 1383.3 | EM3: 1844.4 | EN3: 2305.5 | EO3: 2766.6 | EP3: 3227.7 | EQ3: 3688.8 | ER3: 4149.9 | ES3: 4611 | ET3: 4611 | EU3: 4611 | EV3: 4611 | EW3: 4611 | EX3: 4611 | EY3: 4611 | EZ3: 4611 | FA3: 4611 | FB3: 4611 | FC3: 4611 | FD3: 4611 | FE3: 4611 | FF3: 4611 | FG3: 4611 | FH3: 4611 | FI3: 4611 | FJ3: 4611 | FK3: 4611 | FL3: 4611 | FM3: 4611 | FN3: 4611 | FO3: 4611 | FP3: 4611 | FQ3: 4611 | FR3: 4611 | FS3: 4611 | FT3: 4611 | FU3: 4611 | FV3: 4611 | FW3: 4611 | FX3: 4611 | FY3: 4611 | FZ3: 4611 | GA3: 4611 | GB3: 4611 | GC3: 4611 | GD3: 4611 | GE3: 4611 | GF3: 4611 | GG3: 4611 | GH3: 4611 | GI3: 4611 | GJ3: 4611 | GK3: 4611 | GL3: 4611 | GM3: 4611 | GN3: 4611 | GO3: 4611 | GP3: 4611 | GQ3: 4611 | GR3: 4611 | GS3: 4611 | GT3: 4611 | GU3: 4611 | GV3: 4611 | GW3: 4611 | GX3: 4611 | GY3: 4611 | GZ3: 4611 | HA3: 4611 | HB3: 4611 | HC3: 4611 | HD3: 0 | HE3: 0 | HF3: 0 | HG3: 0 | HH3: 0 | HI3: 0 | HJ3: 0 | HK3: 0 | HL3: 0 | HM3: 0 | HN3: 0 | HO3: 0 | HP3: 0 | HQ3: 0 | HR3: 0 | HS3: 0 | HT3: 0 | HU3: 0 | HV3: 0 | HW3: 0 | HX3: 0 | HY3: 0 | HZ3: 0 | IA3: 0 | IB3: 0 | IC3: 0 | ID3: 0 | IE3: 0 | IF3: 0 | IG3: 0 | IH3: 0 | II3: 0 | IJ3: 0 | IK3: 0 | IL3: 0 | IM3: 0 | IN3: 0 | IO3: 0 | IP3: 0
A4: 55 | B4: CLX10 | F4: 2 | H4: 19 | J4: =B4&TEXT(F4,"00")&TEXT(H4,"00") -> CLX100219 | K4: 440 | R4: 55 | S4: CLX10 | T4: 2 | U4: 19 | V4: =S4&TEXT(T4,"00")&TEXT(U4,"00") -> CLX100219 | W4: 0 | X4: 0 | Y4: 0 | Z4: 0 | AA4: 0 | AB4: 0 | AC4: 0 | AD4: 0 | AE4: 0 | AF4: 0 | AG4: 0 | AH4: 0 | AI4: 0 | AJ4: 0 | AK4: 0 | AL4: 0 | AM4: 0 | AN4: 0 | AO4: 0 | AP4: 0 | AQ4: 0 | AR4: 0 | AS4: 0 | AT4: 0 | AU4: 0 | AV4: 0 | AW4: 0 | AX4: 0 | AY4: 0 | AZ4: 0 | BA4: 0 | BB4: 0 | BC4: 0 | BD4: 0 | BE4: 0 | BF4: 0 | BG4: 0 | BH4: 0 | BI4: 0 | BJ4: 0 | BK4: 0 | BL4: 0 | BM4: 0 | BN4: 0 | BO4: 0 | BP4: 0 | BQ4: 0 | BR4: 0 | BS4: 0 | BT4: 0 | BU4: 0 | BV4: 0 | BW4: 0 | BX4: 0 | BY4: 0 | BZ4: 0 | CA4: 0 | CB4: 0 | CC4: 0 | CD4: 0 | CE4: 0 | CF4: 0 | CG4: 0 | CH4: 0 | CI4: 0 | CJ4: 0 | CK4: 0 | CL4: 0 | CM4: 0 | CN4: 0 | CO4: 4664 | CP4: 0 | CQ4: 0 | CR4: 0 | CS4: 0 | CT4: 0 | CU4: 0 | CV4: 0 | CW4: 0 | CX4: 0 | CY4: 0 | CZ4: 0 | DA4: 0 | DB4: 0 | DC4: 0 | DD4: 0 | DE4: 0 | DF4: 0 | DG4: 0 | DH4: 0 | DI4: 0 | DJ4: 0 | DK4: 0 | DL4: 0 | DM4: 0 | DN4: 0 | DO4: 0 | DP4: 0 | DQ4: 0 | DR4: 0 | DS4: 0 | DT4: 0 | DU4: 0 | DV4: 0 | EE4: 55 | EF4: CLX10 | EG4: 2 | EH4: 19 | EI4: =EF4&TEXT(EG4,"00")&TEXT(EH4,"00") -> CLX100219 | EJ4: 466.4 | EK4: 932.8 | EL4: 1399.2 | EM4: 1865.6 | EN4: 2332 | EO4: 2798.4 | EP4: 3264.8 | EQ4: 3731.2 | ER4: 4197.6 | ES4: 4664 | ET4: 4664 | EU4: 4664 | EV4: 4664 | EW4: 4664 | EX4: 4664 | EY4: 4664 | EZ4: 4664 | FA4: 4664 | FB4: 4664 | FC4: 4664 | FD4: 4664 | FE4: 4664 | FF4: 4664 | FG4: 4664 | FH4: 4664 | FI4: 4664 | FJ4: 4664 | FK4: 4664 | FL4: 4664 | FM4: 4664 | FN4: 4664 | FO4: 4664 | FP4: 4664 | FQ4: 4664 | FR4: 4664 | FS4: 4664 | FT4: 4664 | FU4: 4664 | FV4: 4664 | FW4: 4664 | FX4: 4664 | FY4: 4664 | FZ4: 4664 | GA4: 4664 | GB4: 4664 | GC4: 4664 | GD4: 4664 | GE4: 4664 | GF4: 4664 | GG4: 4664 | GH4: 4664 | GI4: 4664 | GJ4: 4664 | GK4: 4664 | GL4: 4664 | GM4: 4664 | GN4: 4664 | GO4: 4664 | GP4: 4664 | GQ4: 4664 | GR4: 4664 | GS4: 4664 | GT4: 4664 | GU4: 4664 | GV4: 4664 | GW4: 4664 | GX4: 4664 | GY4: 4664 | GZ4: 4664 | HA4: 4664 | HB4: 4664 | HC4: 0 | HD4: 0 | HE4: 0 | HF4: 0 | HG4: 0 | HH4: 0 | HI4: 0 | HJ4: 0 | HK4: 0 | HL4: 0 | HM4: 0 | HN4: 0 | HO4: 0 | HP4: 0 | HQ4: 0 | HR4: 0 | HS4: 0 | HT4: 0 | HU4: 0 | HV4: 0 | HW4: 0 | HX4: 0 | HY4: 0 | HZ4: 0 | IA4: 0 | IB4: 0 | IC4: 0 | ID4: 0 | IE4: 0 | IF4: 0 | IG4: 0 | IH4: 0 | II4: 0 | IJ4: 0 | IK4: 0 | IL4: 0 | IM4: 0 | IN4: 0 | IO4: 0 | IP4: 0
A5: 55 | B5: CLX10 | F5: 2 | H5: 20 | J5: =B5&TEXT(F5,"00")&TEXT(H5,"00") -> CLX100220 | K5: 445 | R5: 55 | S5: CLX10 | T5: 2 | U5: 20 | V5: =S5&TEXT(T5,"00")&TEXT(U5,"00") -> CLX100220 | W5: 0 | X5: 0 | Y5: 0 | Z5: 0 | AA5: 0 | AB5: 0 | AC5: 0 | AD5: 0 | AE5: 0 | AF5: 0 | AG5: 0 | AH5: 0 | AI5: 0 | AJ5: 0 | AK5: 0 | AL5: 0 | AM5: 0 | AN5: 0 | AO5: 0 | AP5: 0 | AQ5: 0 | AR5: 0 | AS5: 0 | AT5: 0 | AU5: 0 | AV5: 0 | AW5: 0 | AX5: 0 | AY5: 0 | AZ5: 0 | BA5: 0 | BB5: 0 | BC5: 0 | BD5: 0 | BE5: 0 | BF5: 0 | BG5: 0 | BH5: 0 | BI5: 0 | BJ5: 0 | BK5: 0 | BL5: 0 | BM5: 0 | BN5: 0 | BO5: 0 | BP5: 0 | BQ5: 0 | BR5: 0 | BS5: 0 | BT5: 0 | BU5: 0 | BV5: 0 | BW5: 0 | BX5: 0 | BY5: 0 | BZ5: 0 | CA5: 0 | CB5: 0 | CC5: 0 | CD5: 0 | CE5: 0 | CF5: 0 | CG5: 0 | CH5: 0 | CI5: 0 | CJ5: 0 | CK5: 0 | CL5: 0 | CM5: 0 | CN5: 4717 | CO5: 0 | CP5: 0 | CQ5: 0 | CR5: 0 | CS5: 0 | CT5: 0 | CU5: 0 | CV5: 0 | CW5: 0 | CX5: 0 | CY5: 0 | CZ5: 0 | DA5: 0 | DB5: 0 | DC5: 0 | DD5: 0 | DE5: 0 | DF5: 0 | DG5: 0 | DH5: 0 | DI5: 0 | DJ5: 0 | DK5: 0 | DL5: 0 | DM5: 0 | DN5: 0 | DO5: 0 | DP5: 0 | DQ5: 0 | DR5: 0 | DS5: 0 | DT5: 0 | DU5: 0 | DV5: 0 | EE5: 55 | EF5: CLX10 | EG5: 2 | EH5: 20 | EI5: =EF5&TEXT(EG5,"00")&TEXT(EH5,"00") -> CLX100220 | EJ5: 471.7 | EK5: 943.4 | EL5: 1415.1 | EM5: 1886.8 | EN5: 2358.5 | EO5: 2830.2 | EP5: 3301.9 | EQ5: 3773.6 | ER5: 4245.3 | ES5: 4717 | ET5: 4717 | EU5: 4717 | EV5: 4717 | EW5: 4717 | EX5: 4717 | EY5: 4717 | EZ5: 4717 | FA5: 4717 | FB5: 4717 | FC5: 4717 | FD5: 4717 | FE5: 4717 | FF5: 4717 | FG5: 4717 | FH5: 4717 | FI5: 4717 | FJ5: 4717 | FK5: 4717 | FL5: 4717 | FM5: 4717 | FN5: 4717 | FO5: 4717 | FP5: 4717 | FQ5: 4717 | FR5: 4717 | FS5: 4717 | FT5: 4717 | FU5: 4717 | FV5: 4717 | FW5: 4717 | FX5: 4717 | FY5: 4717 | FZ5: 4717 | GA5: 4717 | GB5: 4717 | GC5: 4717 | GD5: 4717 | GE5: 4717 | GF5: 4717 | GG5: 4717 | GH5: 4717 | GI5: 4717 | GJ5: 4717 | GK5: 4717 | GL5: 4717 | GM5: 4717 | GN5: 4717 | GO5: 4717 | GP5: 4717 | GQ5: 4717 | GR5: 4717 | GS5: 4717 | GT5: 4717 | GU5: 4717 | GV5: 4717 | GW5: 4717 | GX5: 4717 | GY5: 4717 | GZ5: 4717 | HA5: 4717 | HB5: 0 | HC5: 0 | HD5: 0 | HE5: 0 | HF5: 0 | HG5: 0 | HH5: 0 | HI5: 0 | HJ5: 0 | HK5: 0 | HL5: 0 | HM5: 0 | HN5: 0 | HO5: 0 | HP5: 0 | HQ5: 0 | HR5: 0 | HS5: 0 | HT5: 0 | HU5: 0 | HV5: 0 | HW5: 0 | HX5: 0 | HY5: 0 | HZ5: 0 | IA5: 0 | IB5: 0 | IC5: 0 | ID5: 0 | IE5: 0 | IF5: 0 | IG5: 0 | IH5: 0 | II5: 0 | IJ5: 0 | IK5: 0 | IL5: 0 | IM5: 0 | IN5: 0 | IO5: 0 | IP5: 0
A6: 55 | B6: CLX10 | F6: 2 | H6: 21 | J6: =B6&TEXT(F6,"00")&TEXT(H6,"00") -> CLX100221 | K6: 450 | R6: 55 | S6: CLX10 | T6: 2 | U6: 21 | V6: =S6&TEXT(T6,"00")&TEXT(U6,"00") -> CLX100221 | W6: 0 | X6: 0 | Y6: 0 | Z6: 0 | AA6: 0 | AB6: 0 | AC6: 0 | AD6: 0 | AE6: 0 | AF6: 0 | AG6: 0 | AH6: 0 | AI6: 0 | AJ6: 0 | AK6: 0 | AL6: 0 | AM6: 0 | AN6: 0 | AO6: 0 | AP6: 0 | AQ6: 0 | AR6: 0 | AS6: 0 | AT6: 0 | AU6: 0 | AV6: 0 | AW6: 0 | AX6: 0 | AY6: 0 | AZ6: 0 | BA6: 0 | BB6: 0 | BC6: 0 | BD6: 0 | BE6: 0 | BF6: 0 | BG6: 0 | BH6: 0 | BI6: 0 | BJ6: 0 | BK6: 0 | BL6: 0 | BM6: 0 | BN6: 0 | BO6: 0 | BP6: 0 | BQ6: 0 | BR6: 0 | BS6: 0 | BT6: 0 | BU6: 0 | BV6: 0 | BW6: 0 | BX6: 0 | BY6: 0 | BZ6: 0 | CA6: 0 | CB6: 0 | CC6: 0 | CD6: 0 | CE6: 0 | CF6: 0 | CG6: 0 | CH6: 0 | CI6: 0 | CJ6: 0 | CK6: 0 | CL6: 0 | CM6: 4770 | CN6: 0 | CO6: 0 | CP6: 0 | CQ6: 0 | CR6: 0 | CS6: 0 | CT6: 0 | CU6: 0 | CV6: 0 | CW6: 0 | CX6: 0 | CY6: 0 | CZ6: 0 | DA6: 0 | DB6: 0 | DC6: 0 | DD6: 0 | DE6: 0 | DF6: 0 | DG6: 0 | DH6: 0 | DI6: 0 | DJ6: 0 | DK6: 0 | DL6: 0 | DM6: 0 | DN6: 0 | DO6: 0 | DP6: 0 | DQ6: 0 | DR6: 0 | DS6: 0 | DT6: 0 | DU6: 0 | DV6: 0 | EE6: 55 | EF6: CLX10 | EG6: 2 | EH6: 21 | EI6: =EF6&TEXT(EG6,"00")&TEXT(EH6,"00") -> CLX100221 | EJ6: 477 | EK6: 954 | EL6: 1431 | EM6: 1908 | EN6: 2385 | EO6: 2862 | EP6: 3339 | EQ6: 3816 | ER6: 4293 | ES6: 4770 | ET6: 4770 | EU6: 4770 | EV6: 4770 | EW6: 4770 | EX6: 4770 | EY6: 4770 | EZ6: 4770 | FA6: 4770 | FB6: 4770 | FC6: 4770 | FD6: 4770 | FE6: 4770 | FF6: 4770 | FG6: 4770 | FH6: 4770 | FI6: 4770 | FJ6: 4770 | FK6: 4770 | FL6: 4770 | FM6: 4770 | FN6: 4770 | FO6: 4770 | FP6: 4770 | FQ6: 4770 | FR6: 4770 | FS6: 4770 | FT6: 4770 | FU6: 4770 | FV6: 4770 | FW6: 4770 | FX6: 4770 | FY6: 4770 | FZ6: 4770 | GA6: 4770 | GB6: 4770 | GC6: 4770 | GD6: 4770 | GE6: 4770 | GF6: 4770 | GG6: 4770 | GH6: 4770 | GI6: 4770 | GJ6: 4770 | GK6: 4770 | GL6: 4770 | GM6: 4770 | GN6: 4770 | GO6: 4770 | GP6: 4770 | GQ6: 4770 | GR6: 4770 | GS6: 4770 | GT6: 4770 | GU6: 4770 | GV6: 4770 | GW6: 4770 | GX6: 4770 | GY6: 4770 | GZ6: 4770 | HA6: 0 | HB6: 0 | HC6: 0 | HD6: 0 | HE6: 0 | HF6: 0 | HG6: 0 | HH6: 0 | HI6: 0 | HJ6: 0 | HK6: 0 | HL6: 0 | HM6: 0 | HN6: 0 | HO6: 0 | HP6: 0 | HQ6: 0 | HR6: 0 | HS6: 0 | HT6: 0 | HU6: 0 | HV6: 0 | HW6: 0 | HX6: 0 | HY6: 0 | HZ6: 0 | IA6: 0 | IB6: 0 | IC6: 0 | ID6: 0 | IE6: 0 | IF6: 0 | IG6: 0 | IH6: 0 | II6: 0 | IJ6: 0 | IK6: 0 | IL6: 0 | IM6: 0 | IN6: 0 | IO6: 0 | IP6: 0
A7: 55 | B7: CLX10 | F7: 2 | H7: 22 | J7: =B7&TEXT(F7,"00")&TEXT(H7,"00") -> CLX100222 | K7: 455 | R7: 55 | S7: CLX10 | T7: 2 | U7: 22 | V7: =S7&TEXT(T7,"00")&TEXT(U7,"00") -> CLX100222 | W7: 0 | X7: 0 | Y7: 0 | Z7: 0 | AA7: 0 | AB7: 0 | AC7: 0 | AD7: 0 | AE7: 0 | AF7: 0 | AG7: 0 | AH7: 0 | AI7: 0 | AJ7: 0 | AK7: 0 | AL7: 0 | AM7: 0 | AN7: 0 | AO7: 0 | AP7: 0 | AQ7: 0 | AR7: 0 | AS7: 0 | AT7: 0 | AU7: 0 | AV7: 0 | AW7: 0 | AX7: 0 | AY7: 0 | AZ7: 0 | BA7: 0 | BB7: 0 | BC7: 0 | BD7: 0 | BE7: 0 | BF7: 0 | BG7: 0 | BH7: 0 | BI7: 0 | BJ7: 0 | BK7: 0 | BL7: 0 | BM7: 0 | BN7: 0 | BO7: 0 | BP7: 0 | BQ7: 0 | BR7: 0 | BS7: 0 | BT7: 0 | BU7: 0 | BV7: 0 | BW7: 0 | BX7: 0 | BY7: 0 | BZ7: 0 | CA7: 0 | CB7: 0 | CC7: 0 | CD7: 0 | CE7: 0 | CF7: 0 | CG7: 0 | CH7: 0 | CI7: 0 | CJ7: 0 | CK7: 0 | CL7: 4823 | CM7: 0 | CN7: 0 | CO7: 0 | CP7: 0 | CQ7: 0 | CR7: 0 | CS7: 0 | CT7: 0 | CU7: 0 | CV7: 0 | CW7: 0 | CX7: 0 | CY7: 0 | CZ7: 0 | DA7: 0 | DB7: 0 | DC7: 0 | DD7: 0 | DE7: 0 | DF7: 0 | DG7: 0 | DH7: 0 | DI7: 0 | DJ7: 0 | DK7: 0 | DL7: 0 | DM7: 0 | DN7: 0 | DO7: 0 | DP7: 0 | DQ7: 0 | DR7: 0 | DS7: 0 | DT7: 0 | DU7: 0 | DV7: 0 | EE7: 55 | EF7: CLX10 | EG7: 2 | EH7: 22 | EI7: =EF7&TEXT(EG7,"00")&TEXT(EH7,"00") -> CLX100222 | EJ7: 482.3 | EK7: 964.6 | EL7: 1446.9 | EM7: 1929.2 | EN7: 2411.5 | EO7: 2893.8 | EP7: 3376.1 | EQ7: 3858.4 | ER7: 4340.7 | ES7: 4823 | ET7: 4823 | EU7: 4823 | EV7: 4823 | EW7: 4823 | EX7: 4823 | EY7: 4823 | EZ7: 4823 | FA7: 4823 | FB7: 4823 | FC7: 4823 | FD7: 4823 | FE7: 4823 | FF7: 4823 | FG7: 4823 | FH7: 4823 | FI7: 4823 | FJ7: 4823 | FK7: 4823 | FL7: 4823 | FM7: 4823 | FN7: 4823 | FO7: 4823 | FP7: 4823 | FQ7: 4823 | FR7: 4823 | FS7: 4823 | FT7: 4823 | FU7: 4823 | FV7: 4823 | FW7: 4823 | FX7: 4823 | FY7: 4823 | FZ7: 4823 | GA7: 4823 | GB7: 4823 | GC7: 4823 | GD7: 4823 | GE7: 4823 | GF7: 4823 | GG7: 4823 | GH7: 4823 | GI7: 4823 | GJ7: 4823 | GK7: 4823 | GL7: 4823 | GM7: 4823 | GN7: 4823 | GO7: 4823 | GP7: 4823 | GQ7: 4823 | GR7: 4823 | GS7: 4823 | GT7: 4823 | GU7: 4823 | GV7: 4823 | GW7: 4823 | GX7: 4823 | GY7: 4823 | GZ7: 0 | HA7: 0 | HB7: 0 | HC7: 0 | HD7: 0 | HE7: 0 | HF7: 0 | HG7: 0 | HH7: 0 | HI7: 0 | HJ7: 0 | HK7: 0 | HL7: 0 | HM7: 0 | HN7: 0 | HO7: 0 | HP7: 0 | HQ7: 0 | HR7: 0 | HS7: 0 | HT7: 0 | HU7: 0 | HV7: 0 | HW7: 0 | HX7: 0 | HY7: 0 | HZ7: 0 | IA7: 0 | IB7: 0 | IC7: 0 | ID7: 0 | IE7: 0 | IF7: 0 | IG7: 0 | IH7: 0 | II7: 0 | IJ7: 0 | IK7: 0 | IL7: 0 | IM7: 0 | IN7: 0 | IO7: 0 | IP7: 0
A8: 55 | B8: CLX10 | F8: 2 | H8: 23 | J8: =B8&TEXT(F8,"00")&TEXT(H8,"00") -> CLX100223 | K8: 460 | R8: 55 | S8: CLX10 | T8: 2 | U8: 23 | V8: =S8&TEXT(T8,"00")&TEXT(U8,"00") -> CLX100223 | W8: 0 | X8: 0 | Y8: 0 | Z8: 0 | AA8: 0 | AB8: 0 | AC8: 0 | AD8: 0 | AE8: 0 | AF8: 0 | AG8: 0 | AH8: 0 | AI8: 0 | AJ8: 0 | AK8: 0 | AL8: 0 | AM8: 0 | AN8: 0 | AO8: 0 | AP8: 0 | AQ8: 0 | AR8: 0 | AS8: 0 | AT8: 0 | AU8: 0 | AV8: 0 | AW8: 0 | AX8: 0 | AY8: 0 | AZ8: 0 | BA8: 0 | BB8: 0 | BC8: 0 | BD8: 0 | BE8: 0 | BF8: 0 | BG8: 0 | BH8: 0 | BI8: 0 | BJ8: 0 | BK8: 0 | BL8: 0 | BM8: 0 | BN8: 0 | BO8: 0 | BP8: 0 | BQ8: 0 | BR8: 0 | BS8: 0 | BT8: 0 | BU8: 0 | BV8: 0 | BW8: 0 | BX8: 0 | BY8: 0 | BZ8: 0 | CA8: 0 | CB8: 0 | CC8: 0 | CD8: 0 | CE8: 0 | CF8: 0 | CG8: 0 | CH8: 0 | CI8: 0 | CJ8: 0 | CK8: 4876 | CL8: 0 | CM8: 0 | CN8: 0 | CO8: 0 | CP8: 0 | CQ8: 0 | CR8: 0 | CS8: 0 | CT8: 0 | CU8: 0 | CV8: 0 | CW8: 0 | CX8: 0 | CY8: 0 | CZ8: 0 | DA8: 0 | DB8: 0 | DC8: 0 | DD8: 0 | DE8: 0 | DF8: 0 | DG8: 0 | DH8: 0 | DI8: 0 | DJ8: 0 | DK8: 0 | DL8: 0 | DM8: 0 | DN8: 0 | DO8: 0 | DP8: 0 | DQ8: 0 | DR8: 0 | DS8: 0 | DT8: 0 | DU8: 0 | DV8: 0 | EE8: 55 | EF8: CLX10 | EG8: 2 | EH8: 23 | EI8: =EF8&TEXT(EG8,"00")&TEXT(EH8,"00") -> CLX100223 | EJ8: 487.6 | EK8: 975.2 | EL8: 1462.8 | EM8: 1950.4 | EN8: 2438 | EO8: 2925.6 | EP8: 3413.2 | EQ8: 3900.8 | ER8: 4388.4 | ES8: 4876 | ET8: 4876 | EU8: 4876 | EV8: 4876 | EW8: 4876 | EX8: 4876 | EY8: 4876 | EZ8: 4876 | FA8: 4876 | FB8: 4876 | FC8: 4876 | FD8: 4876 | FE8: 4876 | FF8: 4876 | FG8: 4876 | FH8: 4876 | FI8: 4876 | FJ8: 4876 | FK8: 4876 | FL8: 4876 | FM8: 4876 | FN8: 4876 | FO8: 4876 | FP8: 4876 | FQ8: 4876 | FR8: 4876 | FS8: 4876 | FT8: 4876 | FU8: 4876 | FV8: 4876 | FW8: 4876 | FX8: 4876 | FY8: 4876 | FZ8: 4876 | GA8: 4876 | GB8: 4876 | GC8: 4876 | GD8: 4876 | GE8: 4876 | GF8: 4876 | GG8: 4876 | GH8: 4876 | GI8: 4876 | GJ8: 4876 | GK8: 4876 | GL8: 4876 | GM8: 4876 | GN8: 4876 | GO8: 4876 | GP8: 4876 | GQ8: 4876 | GR8: 4876 | GS8: 4876 | GT8: 4876 | GU8: 4876 | GV8: 4876 | GW8: 4876 | GX8: 4876 | GY8: 0 | GZ8: 0 | HA8: 0 | HB8: 0 | HC8: 0 | HD8: 0 | HE8: 0 | HF8: 0 | HG8: 0 | HH8: 0 | HI8: 0 | HJ8: 0 | HK8: 0 | HL8: 0 | HM8: 0 | HN8: 0 | HO8: 0 | HP8: 0 | HQ8: 0 | HR8: 0 | HS8: 0 | HT8: 0 | HU8: 0 | HV8: 0 | HW8: 0 | HX8: 0 | HY8: 0 | HZ8: 0 | IA8: 0 | IB8: 0 | IC8: 0 | ID8: 0 | IE8: 0 | IF8: 0 | IG8: 0 | IH8: 0 | II8: 0 | IJ8: 0 | IK8: 0 | IL8: 0 | IM8: 0 | IN8: 0 | IO8: 0 | IP8: 0
A9: 55 | B9: CLX10 | F9: 2 | H9: 24 | J9: =B9&TEXT(F9,"00")&TEXT(H9,"00") -> CLX100224 | K9: 465 | R9: 55 | S9: CLX10 | T9: 2 | U9: 24 | V9: =S9&TEXT(T9,"00")&TEXT(U9,"00") -> CLX100224 | W9: 0 | X9: 0 | Y9: 0 | Z9: 0 | AA9: 0 | AB9: 0 | AC9: 0 | AD9: 0 | AE9: 0 | AF9: 0 | AG9: 0 | AH9: 0 | AI9: 0 | AJ9: 0 | AK9: 0 | AL9: 0 | AM9: 0 | AN9: 0 | AO9: 0 | AP9: 0 | AQ9: 0 | AR9: 0 | AS9: 0 | AT9: 0 | AU9: 0 | AV9: 0 | AW9: 0 | AX9: 0 | AY9: 0 | AZ9: 0 | BA9: 0 | BB9: 0 | BC9: 0 | BD9: 0 | BE9: 0 | BF9: 0 | BG9: 0 | BH9: 0 | BI9: 0 | BJ9: 0 | BK9: 0 | BL9: 0 | BM9: 0 | BN9: 0 | BO9: 0 | BP9: 0 | BQ9: 0 | BR9: 0 | BS9: 0 | BT9: 0 | BU9: 0 | BV9: 0 | BW9: 0 | BX9: 0 | BY9: 0 | BZ9: 0 | CA9: 0 | CB9: 0 | CC9: 0 | CD9: 0 | CE9: 0 | CF9: 0 | CG9: 0 | CH9: 0 | CI9: 0 | CJ9: 4929 | CK9: 0 | CL9: 0 | CM9: 0 | CN9: 0 | CO9: 0 | CP9: 0 | CQ9: 0 | CR9: 0 | CS9: 0 | CT9: 0 | CU9: 0 | CV9: 0 | CW9: 0 | CX9: 0 | CY9: 0 | CZ9: 0 | DA9: 0 | DB9: 0 | DC9: 0 | DD9: 0 | DE9: 0 | DF9: 0 | DG9: 0 | DH9: 0 | DI9: 0 | DJ9: 0 | DK9: 0 | DL9: 0 | DM9: 0 | DN9: 0 | DO9: 0 | DP9: 0 | DQ9: 0 | DR9: 0 | DS9: 0 | DT9: 0 | DU9: 0 | DV9: 0 | EE9: 55 | EF9: CLX10 | EG9: 2 | EH9: 24 | EI9: =EF9&TEXT(EG9,"00")&TEXT(EH9,"00") -> CLX100224 | EJ9: 492.9 | EK9: 985.8 | EL9: 1478.7 | EM9: 1971.6 | EN9: 2464.5 | EO9: 2957.4 | EP9: 3450.3 | EQ9: 3943.2 | ER9: 4436.1 | ES9: 4929 | ET9: 4929 | EU9: 4929 | EV9: 4929 | EW9: 4929 | EX9: 4929 | EY9: 4929 | EZ9: 4929 | FA9: 4929 | FB9: 4929 | FC9: 4929 | FD9: 4929 | FE9: 4929 | FF9: 4929 | FG9: 4929 | FH9: 4929 | FI9: 4929 | FJ9: 4929 | FK9: 4929 | FL9: 4929 | FM9: 4929 | FN9: 4929 | FO9: 4929 | FP9: 4929 | FQ9: 4929 | FR9: 4929 | FS9: 4929 | FT9: 4929 | FU9: 4929 | FV9: 4929 | FW9: 4929 | FX9: 4929 | FY9: 4929 | FZ9: 4929 | GA9: 4929 | GB9: 4929 | GC9: 4929 | GD9: 4929 | GE9: 4929 | GF9: 4929 | GG9: 4929 | GH9: 4929 | GI9: 4929 | GJ9: 4929 | GK9: 4929 | GL9: 4929 | GM9: 4929 | GN9: 4929 | GO9: 4929 | GP9: 4929 | GQ9: 4929 | GR9: 4929 | GS9: 4929 | GT9: 4929 | GU9: 4929 | GV9: 4929 | GW9: 4929 | GX9: 0 | GY9: 0 | GZ9: 0 | HA9: 0 | HB9: 0 | HC9: 0 | HD9: 0 | HE9: 0 | HF9: 0 | HG9: 0 | HH9: 0 | HI9: 0 | HJ9: 0 | HK9: 0 | HL9: 0 | HM9: 0 | HN9: 0 | HO9: 0 | HP9: 0 | HQ9: 0 | HR9: 0 | HS9: 0 | HT9: 0 | HU9: 0 | HV9: 0 | HW9: 0 | HX9: 0 | HY9: 0 | HZ9: 0 | IA9: 0 | IB9: 0 | IC9: 0 | ID9: 0 | IE9: 0 | IF9: 0 | IG9: 0 | IH9: 0 | II9: 0 | IJ9: 0 | IK9: 0 | IL9: 0 | IM9: 0 | IN9: 0 | IO9: 0 | IP9: 0
A10: 55 | B10: CLX10 | F10: 2 | H10: 25 | J10: =B10&TEXT(F10,"00")&TEXT(H10,"00") -> CLX100225 | K10: 470 | R10: 55 | S10: CLX10 | T10: 2 | U10: 25 | V10: =S10&TEXT(T10,"00")&TEXT(U10,"00") -> CLX100225 | W10: 0 | X10: 0 | Y10: 0 | Z10: 0 | AA10: 0 | AB10: 0 | AC10: 0 | AD10: 0 | AE10: 0 | AF10: 0 | AG10: 0 | AH10: 0 | AI10: 0 | AJ10: 0 | AK10: 0 | AL10: 0 | AM10: 0 | AN10: 0 | AO10: 0 | AP10: 0 | AQ10: 0 | AR10: 0 | AS10: 0 | AT10: 0 | AU10: 0 | AV10: 0 | AW10: 0 | AX10: 0 | AY10: 0 | AZ10: 0 | BA10: 0 | BB10: 0 | BC10: 0 | BD10: 0 | BE10: 0 | BF10: 0 | BG10: 0 | BH10: 0 | BI10: 0 | BJ10: 0 | BK10: 0 | BL10: 0 | BM10: 0 | BN10: 0 | BO10: 0 | BP10: 0 | BQ10: 0 | BR10: 0 | BS10: 0 | BT10: 0 | BU10: 0 | BV10: 0 | BW10: 0 | BX10: 0 | BY10: 0 | BZ10: 0 | CA10: 0 | CB10: 0 | CC10: 0 | CD10: 0 | CE10: 0 | CF10: 0 | CG10: 0 | CH10: 0 | CI10: 4982 | CJ10: 0 | CK10: 0 | CL10: 0 | CM10: 0 | CN10: 0 | CO10: 0 | CP10: 0 | CQ10: 0 | CR10: 0 | CS10: 0 | CT10: 0 | CU10: 0 | CV10: 0 | CW10: 0 | CX10: 0 | CY10: 0 | CZ10: 0 | DA10: 0 | DB10: 0 | DC10: 0 | DD10: 0 | DE10: 0 | DF10: 0 | DG10: 0 | DH10: 0 | DI10: 0 | DJ10: 0 | DK10: 0 | DL10: 0 | DM10: 0 | DN10: 0 | DO10: 0 | DP10: 0 | DQ10: 0 | DR10: 0 | DS10: 0 | DT10: 0 | DU10: 0 | DV10: 0 | EE10: 55 | EF10: CLX10 | EG10: 2 | EH10: 25 | EI10: =EF10&TEXT(EG10,"00")&TEXT(EH10,"00") -> CLX100225 | EJ10: 498.2 | EK10: 996.4 | EL10: 1494.6 | EM10: 1992.8 | EN10: 2491 | EO10: 2989.2 | EP10: 3487.4 | EQ10: 3985.6 | ER10: 4483.8 | ES10: 4982 | ET10: 4982 | EU10: 4982 | EV10: 4982 | EW10: 4982 | EX10: 4982 | EY10: 4982 | EZ10: 4982 | FA10: 4982 | FB10: 4982 | FC10: 4982 | FD10: 4982 | FE10: 4982 | FF10: 4982 | FG10: 4982 | FH10: 4982 | FI10: 4982 | FJ10: 4982 | FK10: 4982 | FL10: 4982 | FM10: 4982 | FN10: 4982 | FO10: 4982 | FP10: 4982 | FQ10: 4982 | FR10: 4982 | FS10: 4982 | FT10: 4982 | FU10: 4982 | FV10: 4982 | FW10: 4982 | FX10: 4982 | FY10: 4982 | FZ10: 4982 | GA10: 4982 | GB10: 4982 | GC10: 4982 | GD10: 4982 | GE10: 4982 | GF10: 4982 | GG10: 4982 | GH10: 4982 | GI10: 4982 | GJ10: 4982 | GK10: 4982 | GL10: 4982 | GM10: 4982 | GN10: 4982 | GO10: 4982 | GP10: 4982 | GQ10: 4982 | GR10: 4982 | GS10: 4982 | GT10: 4982 | GU10: 4982 | GV10: 4982 | GW10: 0 | GX10: 0 | GY10: 0 | GZ10: 0 | HA10: 0 | HB10: 0 | HC10: 0 | HD10: 0 | HE10: 0 | HF10: 0 | HG10: 0 | HH10: 0 | HI10: 0 | HJ10: 0 | HK10: 0 | HL10: 0 | HM10: 0 | HN10: 0 | HO10: 0 | HP10: 0 | HQ10: 0 | HR10: 0 | HS10: 0 | HT10: 0 | HU10: 0 | HV10: 0 | HW10: 0 | HX10: 0 | HY10: 0 | HZ10: 0 | IA10: 0 | IB10: 0 | IC10: 0 | ID10: 0 | IE10: 0 | IF10: 0 | IG10: 0 | IH10: 0 | II10: 0 | IJ10: 0 | IK10: 0 | IL10: 0 | IM10: 0 | IN10: 0 | IO10: 0 | IP10: 0
A11: 55 | B11: CLX10 | F11: 2 | H11: 26 | J11: =B11&TEXT(F11,"00")&TEXT(H11,"00") -> CLX100226 | K11: 480 | R11: 55 | S11: CLX10 | T11: 2 | U11: 26 | V11: =S11&TEXT(T11,"00")&TEXT(U11,"00") -> CLX100226 | W11: 0 | X11: 0 | Y11: 0 | Z11: 0 | AA11: 0 | AB11: 0 | AC11: 0 | AD11: 0 | AE11: 0 | AF11: 0 | AG11: 0 | AH11: 0 | AI11: 0 | AJ11: 0 | AK11: 0 | AL11: 0 | AM11: 0 | AN11: 0 | AO11: 0 | AP11: 0 | AQ11: 0 | AR11: 0 | AS11: 0 | AT11: 0 | AU11: 0 | AV11: 0 | AW11: 0 | AX11: 0 | AY11: 0 | AZ11: 0 | BA11: 0 | BB11: 0 | BC11: 0 | BD11: 0 | BE11: 0 | BF11: 0 | BG11: 0 | BH11: 0 | BI11: 0 | BJ11: 0 | BK11: 0 | BL11: 0 | BM11: 0 | BN11: 0 | BO11: 0 | BP11: 0 | BQ11: 0 | BR11: 0 | BS11: 0 | BT11: 0 | BU11: 0 | BV11: 0 | BW11: 0 | BX11: 0 | BY11: 0 | BZ11: 0 | CA11: 0 | CB11: 0 | CC11: 0 | CD11: 0 | CE11: 0 | CF11: 0 | CG11: 0 | CH11: 5088 | CI11: 0 | CJ11: 0 | CK11: 0 | CL11: 0 | CM11: 0 | CN11: 0 | CO11: 0 | CP11: 0 | CQ11: 0 | CR11: 0 | CS11: 0 | CT11: 0 | CU11: 0 | CV11: 0 | CW11: 0 | CX11: 0 | CY11: 0 | CZ11: 0 | DA11: 0 | DB11: 0 | DC11: 0 | DD11: 0 | DE11: 0 | DF11: 0 | DG11: 0 | DH11: 0 | DI11: 0 | DJ11: 0 | DK11: 0 | DL11: 0 | DM11: 0 | DN11: 0 | DO11: 0 | DP11: 0 | DQ11: 0 | DR11: 0 | DS11: 0 | DT11: 0 | DU11: 0 | DV11: 0 | EE11: 55 | EF11: CLX10 | EG11: 2 | EH11: 26 | EI11: =EF11&TEXT(EG11,"00")&TEXT(EH11,"00") -> CLX100226 | EJ11: 508.8 | EK11: 1017.6 | EL11: 1526.4 | EM11: 2035.2 | EN11: 2544 | EO11: 3052.8 | EP11: 3561.6 | EQ11: 4070.4 | ER11: 4579.2 | ES11: 5088 | ET11: 5088 | EU11: 5088 | EV11: 5088 | EW11: 5088 | EX11: 5088 | EY11: 5088 | EZ11: 5088 | FA11: 5088 | FB11: 5088 | FC11: 5088 | FD11: 5088 | FE11: 5088 | FF11: 5088 | FG11: 5088 | FH11: 5088 | FI11: 5088 | FJ11: 5088 | FK11: 5088 | FL11: 5088 | FM11: 5088 | FN11: 5088 | FO11: 5088 | FP11: 5088 | FQ11: 5088 | FR11: 5088 | FS11: 5088 | FT11: 5088 | FU11: 5088 | FV11: 5088 | FW11: 5088 | FX11: 5088 | FY11: 5088 | FZ11: 5088 | GA11: 5088 | GB11: 5088 | GC11: 5088 | GD11: 5088 | GE11: 5088 | GF11: 5088 | GG11: 5088 | GH11: 5088 | GI11: 5088 | GJ11: 5088 | GK11: 5088 | GL11: 5088 | GM11: 5088 | GN11: 5088 | GO11: 5088 | GP11: 5088 | GQ11: 5088 | GR11: 5088 | GS11: 5088 | GT11: 5088 | GU11: 5088 | GV11: 0 | GW11: 0 | GX11: 0 | GY11: 0 | GZ11: 0 | HA11: 0 | HB11: 0 | HC11: 0 | HD11: 0 | HE11: 0 | HF11: 0 | HG11: 0 | HH11: 0 | HI11: 0 | HJ11: 0 | HK11: 0 | HL11: 0 | HM11: 0 | HN11: 0 | HO11: 0 | HP11: 0 | HQ11: 0 | HR11: 0 | HS11: 0 | HT11: 0 | HU11: 0 | HV11: 0 | HW11: 0 | HX11: 0 | HY11: 0 | HZ11: 0 | IA11: 0 | IB11: 0 | IC11: 0 | ID11: 0 | IE11: 0 | IF11: 0 | IG11: 0 | IH11: 0 | II11: 0 | IJ11: 0 | IK11: 0 | IL11: 0 | IM11: 0 | IN11: 0 | IO11: 0 | IP11: 0
A12: 55 | B12: CLX10 | F12: 2 | H12: 27 | J12: =B12&TEXT(F12,"00")&TEXT(H12,"00") -> CLX100227 | K12: 490 | R12: 55 | S12: CLX10 | T12: 2 | U12: 27 | V12: =S12&TEXT(T12,"00")&TEXT(U12,"00") -> CLX100227 | W12: 0 | X12: 0 | Y12: 0 | Z12: 0 | AA12: 0 | AB12: 0 | AC12: 0 | AD12: 0 | AE12: 0 | AF12: 0 | AG12: 0 | AH12: 0 | AI12: 0 | AJ12: 0 | AK12: 0 | AL12: 0 | AM12: 0 | AN12: 0 | AO12: 0 | AP12: 0 | AQ12: 0 | AR12: 0 | AS12: 0 | AT12: 0 | AU12: 0 | AV12: 0 | AW12: 0 | AX12: 0 | AY12: 0 | AZ12: 0 | BA12: 0 | BB12: 0 | BC12: 0 | BD12: 0 | BE12: 0 | BF12: 0 | BG12: 0 | BH12: 0 | BI12: 0 | BJ12: 0 | BK12: 0 | BL12: 0 | BM12: 0 | BN12: 0 | BO12: 0 | BP12: 0 | BQ12: 0 | BR12: 0 | BS12: 0 | BT12: 0 | BU12: 0 | BV12: 0 | BW12: 0 | BX12: 0 | BY12: 0 | BZ12: 0 | CA12: 0 | CB12: 0 | CC12: 0 | CD12: 0 | CE12: 0 | CF12: 0 | CG12: 5194 | CH12: 0 | CI12: 0 | CJ12: 0 | CK12: 0 | CL12: 0 | CM12: 0 | CN12: 0 | CO12: 0 | CP12: 0 | CQ12: 0 | CR12: 0 | CS12: 0 | CT12: 0 | CU12: 0 | CV12: 0 | CW12: 0 | CX12: 0 | CY12: 0 | CZ12: 0 | DA12: 0 | DB12: 0 | DC12: 0 | DD12: 0 | DE12: 0 | DF12: 0 | DG12: 0 | DH12: 0 | DI12: 0 | DJ12: 0 | DK12: 0 | DL12: 0 | DM12: 0 | DN12: 0 | DO12: 0 | DP12: 0 | DQ12: 0 | DR12: 0 | DS12: 0 | DT12: 0 | DU12: 0 | DV12: 0 | EE12: 55 | EF12: CLX10 | EG12: 2 | EH12: 27 | EI12: =EF12&TEXT(EG12,"00")&TEXT(EH12,"00") -> CLX100227 | EJ12: 519.4 | EK12: 1038.8 | EL12: 1558.2 | EM12: 2077.6 | EN12: 2597 | EO12: 3116.4 | EP12: 3635.8 | EQ12: 4155.2 | ER12: 4674.6 | ES12: 5194 | ET12: 5194 | EU12: 5194 | EV12: 5194 | EW12: 5194 | EX12: 5194 | EY12: 5194 | EZ12: 5194 | FA12: 5194 | FB12: 5194 | FC12: 5194 | FD12: 5194 | FE12: 5194 | FF12: 5194 | FG12: 5194 | FH12: 5194 | FI12: 5194 | FJ12: 5194 | FK12: 5194 | FL12: 5194 | FM12: 5194 | FN12: 5194 | FO12: 5194 | FP12: 5194 | FQ12: 5194 | FR12: 5194 | FS12: 5194 | FT12: 5194 | FU12: 5194 | FV12: 5194 | FW12: 5194 | FX12: 5194 | FY12: 5194 | FZ12: 5194 | GA12: 5194 | GB12: 5194 | GC12: 5194 | GD12: 5194 | GE12: 5194 | GF12: 5194 | GG12: 5194 | GH12: 5194 | GI12: 5194 | GJ12: 5194 | GK12: 5194 | GL12: 5194 | GM12: 5194 | GN12: 5194 | GO12: 5194 | GP12: 5194 | GQ12: 5194 | GR12: 5194 | GS12: 5194 | GT12: 5194 | GU12: 0 | GV12: 0 | GW12: 0 | GX12: 0 | GY12: 0 | GZ12: 0 | HA12: 0 | HB12: 0 | HC12: 0 | HD12: 0 | HE12: 0 | HF12: 0 | HG12: 0 | HH12: 0 | HI12: 0 | HJ12: 0 | HK12: 0 | HL12: 0 | HM12: 0 | HN12: 0 | HO12: 0 | HP12: 0 | HQ12: 0 | HR12: 0 | HS12: 0 | HT12: 0 | HU12: 0 | HV12: 0 | HW12: 0 | HX12: 0 | HY12: 0 | HZ12: 0 | IA12: 0 | IB12: 0 | IC12: 0 | ID12: 0 | IE12: 0 | IF12: 0 | IG12: 0 | IH12: 0 | II12: 0 | IJ12: 0 | IK12: 0 | IL12: 0 | IM12: 0 | IN12: 0 | IO12: 0 | IP12: 0
A13: 55 | B13: CLX10 | F13: 2 | H13: 28 | J13: =B13&TEXT(F13,"00")&TEXT(H13,"00") -> CLX100228 | K13: 500 | R13: 55 | S13: CLX10 | T13: 2 | U13: 28 | V13: =S13&TEXT(T13,"00")&TEXT(U13,"00") -> CLX100228 | W13: 0 | X13: 0 | Y13: 0 | Z13: 0 | AA13: 0 | AB13: 0 | AC13: 0 | AD13: 0 | AE13: 0 | AF13: 0 | AG13: 0 | AH13: 0 | AI13: 0 | AJ13: 0 | AK13: 0 | AL13: 0 | AM13: 0 | AN13: 0 | AO13: 0 | AP13: 0 | AQ13: 0 | AR13: 0 | AS13: 0 | AT13: 0 | AU13: 0 | AV13: 0 | AW13: 0 | AX13: 0 | AY13: 0 | AZ13: 0 | BA13: 0 | BB13: 0 | BC13: 0 | BD13: 0 | BE13: 0 | BF13: 0 | BG13: 0 | BH13: 0 | BI13: 0 | BJ13: 0 | BK13: 0 | BL13: 0 | BM13: 0 | BN13: 0 | BO13: 0 | BP13: 0 | BQ13: 0 | BR13: 0 | BS13: 0 | BT13: 0 | BU13: 0 | BV13: 0 | BW13: 0 | BX13: 0 | BY13: 0 | BZ13: 0 | CA13: 0 | CB13: 0 | CC13: 0 | CD13: 0 | CE13: 0 | CF13: 5300 | CG13: 0 | CH13: 0 | CI13: 0 | CJ13: 0 | CK13: 0 | CL13: 0 | CM13: 0 | CN13: 0 | CO13: 0 | CP13: 0 | CQ13: 0 | CR13: 0 | CS13: 0 | CT13: 0 | CU13: 0 | CV13: 0 | CW13: 0 | CX13: 0 | CY13: 0 | CZ13: 0 | DA13: 0 | DB13: 0 | DC13: 0 | DD13: 0 | DE13: 0 | DF13: 0 | DG13: 0 | DH13: 0 | DI13: 0 | DJ13: 0 | DK13: 0 | DL13: 0 | DM13: 0 | DN13: 0 | DO13: 0 | DP13: 0 | DQ13: 0 | DR13: 0 | DS13: 0 | DT13: 0 | DU13: 0 | DV13: 0 | EE13: 55 | EF13: CLX10 | EG13: 2 | EH13: 28 | EI13: =EF13&TEXT(EG13,"00")&TEXT(EH13,"00") -> CLX100228 | EJ13: 530 | EK13: 1060 | EL13: 1590 | EM13: 2120 | EN13: 2650 | EO13: 3180 | EP13: 3710 | EQ13: 4240 | ER13: 4770 | ES13: 5300 | ET13: 5300 | EU13: 5300 | EV13: 5300 | EW13: 5300 | EX13: 5300 | EY13: 5300 | EZ13: 5300 | FA13: 5300 | FB13: 5300 | FC13: 5300 | FD13: 5300 | FE13: 5300 | FF13: 5300 | FG13: 5300 | FH13: 5300 | FI13: 5300 | FJ13: 5300 | FK13: 5300 | FL13: 5300 | FM13: 5300 | FN13: 5300 | FO13: 5300 | FP13: 5300 | FQ13: 5300 | FR13: 5300 | FS13: 5300 | FT13: 5300 | FU13: 5300 | FV13: 5300 | FW13: 5300 | FX13: 5300 | FY13: 5300 | FZ13: 5300 | GA13: 5300 | GB13: 5300 | GC13: 5300 | GD13: 5300 | GE13: 5300 | GF13: 5300 | GG13: 5300 | GH13: 5300 | GI13: 5300 | GJ13: 5300 | GK13: 5300 | GL13: 5300 | GM13: 5300 | GN13: 5300 | GO13: 5300 | GP13: 5300 | GQ13: 5300 | GR13: 5300 | GS13: 5300 | GT13: 0 | GU13: 0 | GV13: 0 | GW13: 0 | GX13: 0 | GY13: 0 | GZ13: 0 | HA13: 0 | HB13: 0 | HC13: 0 | HD13: 0 | HE13: 0 | HF13: 0 | HG13: 0 | HH13: 0 | HI13: 0 | HJ13: 0 | HK13: 0 | HL13: 0 | HM13: 0 | HN13: 0 | HO13: 0 | HP13: 0 | HQ13: 0 | HR13: 0 | HS13: 0 | HT13: 0 | HU13: 0 | HV13: 0 | HW13: 0 | HX13: 0 | HY13: 0 | HZ13: 0 | IA13: 0 | IB13: 0 | IC13: 0 | ID13: 0 | IE13: 0 | IF13: 0 | IG13: 0 | IH13: 0 | II13: 0 | IJ13: 0 | IK13: 0 | IL13: 0 | IM13: 0 | IN13: 0 | IO13: 0 | IP13: 0
A14: 55 | B14: CLX10 | F14: 2 | H14: 29 | J14: =B14&TEXT(F14,"00")&TEXT(H14,"00") -> CLX100229 | K14: 510 | R14: 55 | S14: CLX10 | T14: 2 | U14: 29 | V14: =S14&TEXT(T14,"00")&TEXT(U14,"00") -> CLX100229 | W14: 0 | X14: 0 | Y14: 0 | Z14: 0 | AA14: 0 | AB14: 0 | AC14: 0 | AD14: 0 | AE14: 0 | AF14: 0 | AG14: 0 | AH14: 0 | AI14: 0 | AJ14: 0 | AK14: 0 | AL14: 0 | AM14: 0 | AN14: 0 | AO14: 0 | AP14: 0 | AQ14: 0 | AR14: 0 | AS14: 0 | AT14: 0 | AU14: 0 | AV14: 0 | AW14: 0 | AX14: 0 | AY14: 0 | AZ14: 0 | BA14: 0 | BB14: 0 | BC14: 0 | BD14: 0 | BE14: 0 | BF14: 0 | BG14: 0 | BH14: 0 | BI14: 0 | BJ14: 0 | BK14: 0 | BL14: 0 | BM14: 0 | BN14: 0 | BO14: 0 | BP14: 0 | BQ14: 0 | BR14: 0 | BS14: 0 | BT14: 0 | BU14: 0 | BV14: 0 | BW14: 0 | BX14: 0 | BY14: 0 | BZ14: 0 | CA14: 0 | CB14: 0 | CC14: 0 | CD14: 0 | CE14: 5406 | CF14: 0 | CG14: 0 | CH14: 0 | CI14: 0 | CJ14: 0 | CK14: 0 | CL14: 0 | CM14: 0 | CN14: 0 | CO14: 0 | CP14: 0 | CQ14: 0 | CR14: 0 | CS14: 0 | CT14: 0 | CU14: 0 | CV14: 0 | CW14: 0 | CX14: 0 | CY14: 0 | CZ14: 0 | DA14: 0 | DB14: 0 | DC14: 0 | DD14: 0 | DE14: 0 | DF14: 0 | DG14: 0 | DH14: 0 | DI14: 0 | DJ14: 0 | DK14: 0 | DL14: 0 | DM14: 0 | DN14: 0 | DO14: 0 | DP14: 0 | DQ14: 0 | DR14: 0 | DS14: 0 | DT14: 0 | DU14: 0 | DV14: 0 | EE14: 55 | EF14: CLX10 | EG14: 2 | EH14: 29 | EI14: =EF14&TEXT(EG14,"00")&TEXT(EH14,"00") -> CLX100229 | EJ14: 540.6 | EK14: 1081.2 | EL14: 1621.8 | EM14: 2162.4 | EN14: 2703 | EO14: 3243.6 | EP14: 3784.2 | EQ14: 4324.8 | ER14: 4865.4 | ES14: 5406 | ET14: 5406 | EU14: 5406 | EV14: 5406 | EW14: 5406 | EX14: 5406 | EY14: 5406 | EZ14: 5406 | FA14: 5406 | FB14: 5406 | FC14: 5406 | FD14: 5406 | FE14: 5406 | FF14: 5406 | FG14: 5406 | FH14: 5406 | FI14: 5406 | FJ14: 5406 | FK14: 5406 | FL14: 5406 | FM14: 5406 | FN14: 5406 | FO14: 5406 | FP14: 5406 | FQ14: 5406 | FR14: 5406 | FS14: 5406 | FT14: 5406 | FU14: 5406 | FV14: 5406 | FW14: 5406 | FX14: 5406 | FY14: 5406 | FZ14: 5406 | GA14: 5406 | GB14: 5406 | GC14: 5406 | GD14: 5406 | GE14: 5406 | GF14: 5406 | GG14: 5406 | GH14: 5406 | GI14: 5406 | GJ14: 5406 | GK14: 5406 | GL14: 5406 | GM14: 5406 | GN14: 5406 | GO14: 5406 | GP14: 5406 | GQ14: 5406 | GR14: 5406 | GS14: 0 | GT14: 0 | GU14: 0 | GV14: 0 | GW14: 0 | GX14: 0 | GY14: 0 | GZ14: 0 | HA14: 0 | HB14: 0 | HC14: 0 | HD14: 0 | HE14: 0 | HF14: 0 | HG14: 0 | HH14: 0 | HI14: 0 | HJ14: 0 | HK14: 0 | HL14: 0 | HM14: 0 | HN14: 0 | HO14: 0 | HP14: 0 | HQ14: 0 | HR14: 0 | HS14: 0 | HT14: 0 | HU14: 0 | HV14: 0 | HW14: 0 | HX14: 0 | HY14: 0 | HZ14: 0 | IA14: 0 | IB14: 0 | IC14: 0 | ID14: 0 | IE14: 0 | IF14: 0 | IG14: 0 | IH14: 0 | II14: 0 | IJ14: 0 | IK14: 0 | IL14: 0 | IM14: 0 | IN14: 0 | IO14: 0 | IP14: 0
... A78: 55 | B78: CLX20 | F78: 2 | H78: 50 | J78: =B78&TEXT(F78,"00")&TEXT(H78,"00") -> CLX200250 | K78: 470 | R78: 55 | S78: CLX20 | T78: 2 | U78: 50 | V78: =S78&TEXT(T78,"00")&TEXT(U78,"00") -> CLX200250 | W78: 0 | X78: 0 | Y78: 0 | Z78: 0 | AA78: 0 | AB78: 0 | AC78: 0 | AD78: 0 | AE78: 0 | AF78: 0 | AG78: 0 | AH78: 0 | AI78: 0 | AJ78: 0 | AK78: 0 | AL78: 0 | AM78: 0 | AN78: 0 | AO78: 0 | AP78: 0 | AQ78: 0 | AR78: 0 | AS78: 0 | AT78: 0 | AU78: 0 | AV78: 0 | AW78: 0 | AX78: 0 | AY78: 0 | AZ78: 0 | BA78: 0 | BB78: 0 | BC78: 0 | BD78: 0 | BE78: 0 | BF78: 0 | BG78: 0 | BH78: 0 | BI78: 0 | BJ78: 9964 | BK78: 0 | BL78: 0 | BM78: 0 | BN78: 0 | BO78: 0 | BP78: 0 | BQ78: 0 | BR78: 0 | BS78: 0 | BT78: 0 | BU78: 0 | BV78: 0 | BW78: 0 | BX78: 0 | BY78: 0 | BZ78: 0 | CA78: 0 | CB78: 0 | CC78: 0 | CD78: 0 | CE78: 0 | CF78: 0 | CG78: 0 | CH78: 0 | CI78: 0 | CJ78: 0 | CK78: 0 | CL78: 0 | CM78: 0 | CN78: 0 | CO78: 0 | CP78: 0 | CQ78: 0 | CR78: 0 | CS78: 0 | CT78: 0 | CU78: 0 | CV78: 0 | CW78: 0 | CX78: 0 | CY78: 0 | CZ78: 0 | DA78: 0 | DB78: 0 | DC78: 0 | DD78: 0 | DE78: 0 | DF78: 0 | DG78: 0 | DH78: 0 | DI78: 0 | DJ78: 0 | DK78: 0 | DL78: 0 | DM78: 0 | DN78: 0 | DO78: 0 | DP78: 0 | DQ78: 0 | DR78: 0 | DS78: 0 | DT78: 0 | DU78: 0 | DV78: 0 | EE78: 55 | EF78: CLX20 | EG78: 2 | EH78: 50 | EI78: =EF78&TEXT(EG78,"00")&TEXT(EH78,"00") -> CLX200250 | EJ78: 498.2 | EK78: 996.4 | EL78: 1494.6 | EM78: 1992.8 | EN78: 2491 | EO78: 2989.2 | EP78: 3487.4 | EQ78: 3985.6 | ER78: 4483.8 | ES78: 4982 | ET78: 5480.2 | EU78: 5978.4 | EV78: 6476.6 | EW78: 6974.8 | EX78: 7473 | EY78: 7971.2 | EZ78: 8469.4 | FA78: 8967.6 | FB78: 9465.8 | FC78: 9964 | FD78: 9964 | FE78: 9964 | FF78: 9964 | FG78: 9964 | FH78: 9964 | FI78: 9964 | FJ78: 9964 | FK78: 9964 | FL78: 9964 | FM78: 9964 | FN78: 9964 | FO78: 9964 | FP78: 9964 | FQ78: 9964 | FR78: 9964 | FS78: 9964 | FT78: 9964 | FU78: 9964 | FV78: 9964 | FW78: 9964 | FX78: 0 | FY78: 0 | FZ78: 0 | GA78: 0 | GB78: 0 | GC78: 0 | GD78: 0 | GE78: 0 | GF78: 0 | GG78: 0 | GH78: 0 | GI78: 0 | GJ78: 0 | GK78: 0 | GL78: 0 | GM78: 0 | GN78: 0 | GO78: 0 | GP78: 0 | GQ78: 0 | GR78: 0 | GS78: 0 | GT78: 0 | GU78: 0 | GV78: 0 | GW78: 0 | GX78: 0 | GY78: 0 | GZ78: 0 | HA78: 0 | HB78: 0 | HC78: 0 | HD78: 0 | HE78: 0 | HF78: 0 | HG78: 0 | HH78: 0 | HI78: 0 | HJ78: 0 | HK78: 0 | HL78: 0 | HM78: 0 | HN78: 0 | HO78: 0 | HP78: 0 | HQ78: 0 | HR78: 0 | HS78: 0 | HT78: 0 | HU78: 0 | HV78: 0 | HW78: 0 | HX78: 0 | HY78: 0 | HZ78: 0 | IA78: 0 | IB78: 0 | IC78: 0 | ID78: 0 | IE78: 0 | IF78: 0 | IG78: 0 | IH78: 0 | II78: 0 | IJ78: 0 | IK78: 0 | IL78: 0 | IM78: 0 | IN78: 0 | IO78: 0 | IP78: 0
R272: CV | V272: =S272&TEXT(T272,"00")&TEXT(U272,"00") -> 0000 | EE272: PA | EI272: =EF272&TEXT(EG272,"00")&TEXT(EH272,"00") -> 0000
R273: 版次 | S273: 商品代號 | T273: 性別 | U273: 年齡 | V273: =S273&TEXT(T273,"00")&TEXT(U273,"00") -> 商品代號性別年齡 | W273: 第1年解約金 | X273: 第2年解約金 | Y273: 第3年解約金 | Z273: 第4年解約金 | AA273: 第5年解約金 | AB273: 第6年解約金 | AC273: 第7年解約金 | AD273: 第8年解約金 | AE273: 第9年解約金 | AF273: 第10年解約金 | AG273: 第11年解約金 | AH273: 第12年解約金 | AI273: 第13年解約金 | AJ273: 第14年解約金 | AK273: 第15年解約金 | AL273: 第16年解約金 | AM273: 第17年解約金 | AN273: 第18年解約金 | AO273: 第19年解約金 | AP273: 第20年解約金 | AQ273: 第21年解約金 | AR273: 第22年解約金 | AS273: 第23年解約金 | AT273: 第24年解約金 | AU273: 第25年解約金 | AV273: 第26年解約金 | AW273: 第27年解約金 | AX273: 第28年解約金 | AY273: 第29年解約金 | AZ273: 第30年解約金 | BA273: 第31年解約金 | BB273: 第32年解約金 | BC273: 第33年解約金 | BD273: 第34年解約金 | BE273: 第35年解約金 | BF273: 第36年解約金 | BG273: 第37年解約金 | BH273: 第38年解約金 | BI273: 第39年解約金 | BJ273: 第40年解約金 | BK273: 第41年解約金 | BL273: 第42年解約金 | BM273: 第43年解約金 | BN273: 第44年解約金 | BO273: 第45年解約金 | BP273: 第46年解約金 | BQ273: 第47年解約金 | BR273: 第48年解約金 | BS273: 第49年解約金 | BT273: 第50年解約金 | BU273: 第51年解約金 | BV273: 第52年解約金 | BW273: 第53年解約金 | BX273: 第54年解約金 | BY273: 第55年解約金 | BZ273: 第56年解約金 | CA273: 第57年解約金 | CB273: 第58年解約金 | CC273: 第59年解約金 | CD273: 第60年解約金 | CE273: 第61年解約金 | CF273: 第62年解約金 | CG273: 第63年解約金 | CH273: 第64年解約金 | CI273: 第65年解約金 | CJ273: 第66年解約金 | CK273: 第67年解約金 | CL273: 第68年解約金 | CM273: 第69年解約金 | CN273: 第70年解約金 | CO273: 第71年解約金 | CP273: 第72年解約金 | CQ273: 第73年解約金 | CR273: 第74年解約金 | CS273: 第75年解約金 | CT273: 第76年解約金 | CU273: 第77年解約金 | CV273: 第78年解約金 | CW273: 第79年解約金 | CX273: 第80年解約金 | CY273: 第81年解約金 | CZ273: 第82年解約金 | DA273: 第83年解約金 | DB273: 第84年解約金 | DC273: 第85年解約金 | DD273: 第86年解約金 | DE273: 第87年解約金 | DF273: 第88年解約金 | DG273: 第89年解約金 | DH273: 第90年解約金 | DI273: 第91年解約金 | DJ273: 第92年解約金 | DK273: 第93年解約金 | DL273: 第94年解約金 | DM273: 第95年解約金 | DN273: 第96年解約金 | DO273: 第97年解約金 | DP273: 第98年解約金 | DQ273: 第99年解約金 | DR273: 第100年解約金 | DS273: 第101年解約金 | DT273: 第102年解約金 | DU273: 第103年解約金 | DV273: 第104年解約金 | DW273: 第105年解約金 | DX273: 第106年解約金 | DY273: 第107年解約金 | DZ273: 第108年解約金 | EA273: 第109年解約金 | EB273: 第110年解約金 | EC273: 第111年解約金 | EE273: 版次 | EF273: 商品代號 | EG273: 性別 | EH273: 年齡 | EI273: =EF273&TEXT(EG273,"00")&TEXT(EH273,"00") -> 商品代號性別年齡 | EJ273: 第1年減額繳清保額 | EK273: 第2年減額繳清保額 | EL273: 第3年減額繳清保額 | EM273: 第4年減額繳清保額 | EN273: 第5年減額繳清保額 | EO273: 第6年減額繳清保額 | EP273: 第7年減額繳清保額 | EQ273: 第8年減額繳清保額 | ER273: 第9年減額繳清保額 | ES273: 第10年減額繳清保額 | ET273: 第11年減額繳清保額 | EU273: 第12年減額繳清保額 | EV273: 第13年減額繳清保額 | EW273: 第14年減額繳清保額 | EX273: 第15年減額繳清保額 | EY273: 第16年減額繳清保額 | EZ273: 第17年減額繳清保額 | FA273: 第18年減額繳清保額 | FB273: 第19年減額繳清保額B | FC273: 第20年減額繳清保額 | FD273: 第21年減額繳清保額B | FE273: 第22年減額繳清保額 | FF273: 第23年減額繳清保額 | FG273: 第24年減額繳清保額 | FH273: 第25年減額繳清保額 | FI273: 第26年減額繳清保額B | FJ273: 第27年減額繳清保額 | FK273: 第28年減額繳清保額B | FL273: 第29年減額繳清保額 | FM273: 第30年減額繳清保額B | FN273: 第31年減額繳清保額 | FO273: 第32年減額繳清保額 | FP273: 第33年減額繳清保額 | FQ273: 第34年減額繳清保額 | FR273: 第35年減額繳清保額 | FS273: 第36年減額繳清保額 | FT273: 第37年減額繳清保額 | FU273: 第38年減額繳清保額 | FV273: 第39年減額繳清保額 | FW273: 第40年減額繳清保額 | FX273: 第41年減額繳清保額 | FY273: 第42年減額繳清保額 | FZ273: 第43年減額繳清保額 | GA273: 第44年減額繳清保額 | GB273: 第45年減額繳清保額 | GC273: 第46年減額繳清保額 | GD273: 第47年減額繳清保額 | GE273: 第48年減額繳清保額 | GF273: 第49年減額繳清保額 | GG273: 第50年減額繳清保額 | GH273: 第51年減額繳清保額 | GI273: 第52年減額繳清保額 | GJ273: 第53年減額繳清保額 | GK273: 第54年減額繳清保額 | GL273: 第55年減額繳清保額 | GM273: 第56年減額繳清保額 | GN273: 第57年減額繳清保額 | GO273: 第58年減額繳清保額 | GP273: 第59年減額繳清保額 | GQ273: 第60年減額繳清保額 | GR273: 第61年減額繳清保額 | GS273: 第62年減額繳清保額 | GT273: 第63年減額繳清保額 | GU273: 第64年減額繳清保額 | GV273: 第65年減額繳清保額 | GW273: 第66年減額繳清保額 | GX273: 第67年減額繳清保額 | GY273: 第68年減額繳清保額 | GZ273: 第69年減額繳清保額 | HA273: 第70年減額繳清保額 | HB273: 第71年減額繳清保額 | HC273: 第72年減額繳清保額 | HD273: 第73年減額繳清保額 | HE273: 第74年減額繳清保額 | HF273: 第75年減額繳清保額 | HG273: 第76年減額繳清保額 | HH273: 第77年減額繳清保額 | HI273: 第78年減額繳清保額 | HJ273: 第79年減額繳清保額 | HK273: 第80年減額繳清保額 | HL273: 第81年減額繳清保額 | HM273: 第82年契遾B繳清保額 | HN273: 第83年減額繳清保額 | HO273: 第84年減額繳清保額 | HP273: 第85年減額繳清保額 | HQ273: 第86年減額繳清保額 | HR273: 第87年減額繳清保額 | HS273: 第88年減額繳清保額 | HT273: 第89年減額繳清保額 | HU273: 第90年減額繳清保額 | HV273: 第91年減額繳清保額 | HW273: 第92年減額繳清保額 | HX273: 第93年減額繳清保額 | HY273: 第94年減額繳清保額 | HZ273: 第95年減額繳清保額 | IA273: 第96年減額繳清保額 | IB273: 第97年減額繳清保額 | IC273: 第98年減額繳清保額 | ID273: 第99年減額繳清保額 | IE273: 第100年減額繳清保額 | IF273: 第101年減額繳清保額 | IG273: 第102年減額繳清保額 | IH273: 第103年減額繳清保額 | II273: 第104年減額繳清保額 | IJ273: 第105年減額繳清保額 | IK273: 第106年減額繳清保額 | IL273: 第107年減額繳清保額 | IM273: 第108年減額繳清保額 | IN273: 第109年減額繳清保額 | IO273: 第110年減額繳清保額 | IP273: 第111年減額繳清保額

Sheet OP
P1: 文字區域
B2: fubon | C2: 試算日 | D2: 生日 | E2: 驗證 | H2: 彈性繳 | I2: 1 | J2: 1 | K2: 1 | P2: 0 | Q2: 註： | AD2: =IF(AE2="","",MAX($AD$1:AD1)+1) | AL2: =$C$69 -> 業務、服展、北富銀
B3: =IF(C4=0,0,VALUE(MID(C4,IF(LEN(C4)=7,4,3),2))) -> 5 | C3: =IF(TODAY()<DATE(2026,4,9),DATE(2026,4,9),TODAY()) -> 46239 | D3: =IF(C4=0,0,DATE(LEFT(C4,IF(LEN(C4)=7,3,2))+1911,MID(C4,IF(LEN(C4)=7,4,3),2),RIGHT(C4,2))) -> 31927 | E3: =N(DAY(DATE(LEFT(C4,IF(LEN(C4)=7,3,2))+1911,MID(C4,IF(LEN(C4)=7,4,3),2)+1,0))) -> 31 | H3: 躉繳 | I3: 1 | J3: 1 | K3: 1 | P3: =IF(Q3="","",MAX($P$2:P2)+1) -> 1 | Q3: =IF(AND(C46=0,C47=0),"","‧上表年度實繳保費已扣除保費折扣，繳費期內如不符保費折扣條件，上表將不適用。") -> ‧上表年度實繳保費已扣除保費折扣，繳費期內如不符保費折扣條件，上表將不適用。 | AD3: =IF(AE3="","",MAX($AD$1:AD2)+1) | AL3: 業務、服展、北富銀 | AM3: 業務、服展 | AN3: 北富銀 | AO3: 整銷 | AP3: 多元
B4: 生日 | C4: =IF(C9=1,C10,IF(C9=2,VALUE(C11&TEXT(C12,"00")&TEXT(C13,"00")),"")) -> 760530 | D4: =DATE(YEAR(C3)-$C$15,MONTH(C3)-6,DAY(C3)) -> 27795 | E4: =IF(OR(B3<1,B3>12),1,"") | F4: =YEAR($D$4)-1911 -> 65 | H4: 年繳 | I4: 1 | J4: 1 | K4: 1 | P4: =IF(Q4="","",MAX($P$2:P3)+1) -> 2 | Q4: ‧上表所列之各項數值，係指各保單年度末之數值。本保險契約若辦理減額繳清保險時，上表將不適用。 | AD4: =IF(AE4="","",MAX($AD$1:AD3)+1) | AK4: =IF(OR($AL4="",COUNTIF($AL$3:$AR$3,$AL$2)=0),"",MAX($AK$3:AK3)+1) -> 1 | AL4: 富邦人壽保險股份有限公司履行個人資料保護法告知說明書
B5: 最高承保 | C5: 保險 | D5: =IF(SUM(E6,D10:D13)>=1,"生日格式錯誤",IF(D3>C3,"被保險人未出生",IF(MONTH(C3)<B3,IF(OR(MONTH(C3)+12-B3>6,AND(MONTH(C3)+12-B3=6,DAY(C3)>DAY(D3))),YEAR(C3)-1-YEAR(D3)+1,IF(OR(MONTH(C3)+12-B3<6,AND(MONTH(C3)+12-B3=6,DAY(C3)<=DAY(D3))),YEAR(C3)-1-YEAR(D3))),IF(OR(MONTH(C3)-B3>6,AND(MONTH(C3)-B3=6,DAY(C3)>DAY(D3))),YEAR(C3)-YEAR(D3)+1,IF(OR(MONTH(C3)-B3<=6,AND(MONTH(C3)-B3=6,DAY(C3)<=DAY(D3))),YEAR(C3)-YEAR(D3),))))) -> 39 | E5: =IF(OR(VALUE(RIGHT(C4,2))<1,VALUE(RIGHT(C4,2))>E3),1,"") | F5: =MONTH($D$4) -> 2 | H5: 半年繳 | I5: 0.52 | J5: 0.5 | K5: 2 | P5: =IF(Q5="","",MAX($P$2:P4)+1) -> 3 | Q5: ‧上表數值為從未申領老年住院醫療提前給付保險金之數值，如有申領過老年住院醫療提前給付保險金者上表將不適 | AD5: =IF(AE5="","",MAX($AD$1:AD4)+1) | AK5: =IF(OR($AL5="",COUNTIF($AL$3:$AR$3,$AL$2)=0),"",MAX($AK$3:AK4)+1) -> 2
C6: 足歲 | D6: =IF(SUM(E6,D10:D13)>=1,"生日格式錯誤",IF(D3>C3,"被保險人未出生",DATEDIF(D3,C3,"y"))) -> 39 | E6: =IF(OR(E4=1,E5=1),1,"") | F6: =DAY($D$4) -> 5 | H6: 季繳 | I6: 0.262 | J6: 0.25 | K6: 4 | P6: =IF(Q6="","",MAX($P$2:P5)+1) -> 4 | Q6: 用，老年住院醫療提前給付保險金申領之條件及限制請詳閱保單條款說明。 | AD6: =IF(AE6="","",MAX($AD$1:AD5)+1) | AK6: =IF(OR($AL6="",COUNTIF($AL$3:$AR$3,$AL$2)=0),"",MAX($AK$3:AK5)+1) -> 3 | AL6: 富邦人壽保險股份有限公司（下稱本公司）依據個人資料保護法（以下稱個資法）
F7: =F4&TEXT(F5,"00")&TEXT(F6,"00") -> 650205 | H7: 月繳 | I7: 0.088 | J7: 0.08333333 | K7: 12 | P7: =IF(Q7="","",MAX($P$2:P6)+1) -> 5 | Q7: ‧身故保險金若被保險人未滿十五足歲前身故者，將以「所繳保險費加計利息」退還予要保人。 | AD7: =IF(AE7="","",MAX($AD$1:AD6)+1) | AK7: =IF(OR($AL7="",COUNTIF($AL$3:$AR$3,$AL$2)=0),"",MAX($AK$3:AK6)+1) -> 4 | AL7: 規定，向 台端告知下列事項，請 台端詳閱：
K8: 第一頁說明↓ | L8: 警語↓ | M8: =COUNTA(L11:L12) -> 2 | P8: =IF(Q8="","",MAX($P$2:P7)+1) -> 6 | Q8: ‧上表保險年齡15歲以下(含15歲)之身故/完全失能保障數值，為按年繳計算之所繳保險費總和，不含加計利息的部分， | AD8: =IF(AE8="","",MAX($AD$1:AD7)+1) | AK8: =IF(OR($AL8="",COUNTIF($AL$3:$AR$3,$AL$2)=0),"",MAX($AK$3:AK7)+1) -> 5 | AL8: 一、蒐集之目的：
B9: 輸入格式選項 | C9: 1 | D9: 檢核欄位 | H9: 折扣使用 | I9: 首期 | J9: 續期 | K9: =K10&M10&K11&M11&K12&M12&K13&M13&D47 -> 繳費方式 1.0%折扣 | L9: ="保費折扣" -> 保費折扣 | M9: =L10&M10&L11&M11&L12&M12&L13&"折扣" -> 繳費方式折扣 | P9: =IF(Q9="","",MAX($P$2:P8)+1) -> 7 | Q9: 若有加計利息，則實際理賠金額依條款約定辦理。 | AD9: =IF(AE9="","",MAX($AD$1:AD8)+1) | AK9: =IF(OR($AL9="",COUNTIF($AL$3:$AR$3,$AL$2)=0),"",MAX($AK$3:AK8)+1) -> 6 | AL9: （一）人身保險（００一）
B10: 1.輸入格式1-6或7位數字輸入 | C10: =BD -> 760530 | D10: =IF(AND($C$9=1,OR(C10="",C10=0)),1,"") | G10: 1 | H10: 繳費方式 | I10: =$C$42 -> 0.01 | J10: =$C$44 -> 0.01 | K10: =IF(AND(I10>0,J10>0),""&H10&TEXT(I10," 0.0%")&"折扣",IF(AND(I10>0,J10=0),"首期"&H10&TEXT(I10," 0.0%")&"折扣",IF(AND(I10=0,J10>0),"續期"&H10&TEXT(J10," 0.0%")&"折扣",""))) -> 繳費方式 1.0%折扣 | L10: =IF(SUM(I10:J10)>0,H10,"") -> 繳費方式 | M10: =IF(L10="","",IF(SUM(N11:N13)>=2,"、",IF(SUM(N11:N13)=1,"及",""))) | N10: =IF(L10<>"",1,0) -> 1 | P10: =IF(Q10="","",MAX($P$2:P9)+1) | AD10: =IF(AE10="","",MAX($AD$1:AD9)+1) | AK10: =IF(OR($AL10="",COUNTIF($AL$3:$AR$3,$AL$2)=0),"",MAX($AK$3:AK9)+1) -> 7 | AL10: （二）其他經營合於營業登記項目或組織章程所定之業務（一八一）
B11: 2.輸入格式2-年月日 | D11: =IF(AND($C$9=2,OR(C11="",C11=0)),1,"") | G11: 2 | H11: 高保額 | I11: =$C$37 -> 0 | J11: =$C$37 -> 0 | K11: =IF(AND(I11>0,J11>0),""&H11&TEXT(I11," 0.0%")&"折扣",IF(AND(I11>0,J11=0),"首期"&H11&TEXT(I11," 0.0%")&"折扣",IF(AND(I11=0,J11>0),"續期"&H11&TEXT(J11," 0.0%")&"折扣",""))) | L11: =IF(SUM(I11:J11)>0,H11,"") | M11: =IF(L11="","",IF(SUM(N12:N14)>=2,"、",IF(SUM(N12:N14)=1,"及",""))) | N11: =IF(L11<>"",1,0) -> 0 | P11: =IF(Q11="","",MAX($P$2:P10)+1) | AD11: =IF(AE11="","",MAX($AD$1:AD10)+1) | AK11: =IF(OR($AL11="",COUNTIF($AL$3:$AR$3,$AL$2)=0),"",MAX($AK$3:AK10)+1) -> 8 | AL11: 二、蒐集之個人資料類別：
D12: =IF(AND($C$9=2,OR(C12="",C12<1,C12>12)),1,"") | G12: 3 | H12: 專案集彙件 | I12: =$C$38 -> 0 | J12: =$C$39 -> 0 | K12: =IF(AND(I12>0,J12>0),""&H12&TEXT(I12," 0.0%")&"折扣",IF(AND(I12>0,J12=0),"首期"&H12&TEXT(I12," 0.0%")&"折扣",IF(AND(I12=0,J12>0),"續期"&H12&TEXT(J12," 0.0%")&"折扣",""))) | L12: =IF(SUM(I12:J12)>0,H12,"") | M12: =IF(L12="","",IF(SUM(N13:N15)>=2,"、",IF(SUM(N13:N15)=1,"及",""))) | N12: =IF(L12<>"",1,0) -> 0 | P12: =IF(Q12="","",MAX($P$2:P11)+1) | AD12: =IF(AE12="","",MAX($AD$1:AD11)+1) | AK12: =IF(OR($AL12="",COUNTIF($AL$3:$AR$3,$AL$2)=0),"",MAX($AK$3:AK11)+1) -> 9 | AL12: （一）姓名。
D13: =IF(AND($C$9=2,OR(C13="",C13<1,C13>E3)),1,"") | G13: 4 | H13: 員工轉帳件 | I13: =$C$40 -> 0 | J13: =$C$40 -> 0 | K13: =IF(AND(I13>0,J13>0),""&H13&TEXT(I13," 0.0%")&"折扣",IF(AND(I13>0,J13=0),"首期"&H13&TEXT(I13," 0.0%")&"折扣",IF(AND(I13=0,J13>0),"續期"&H13&TEXT(J13," 0.0%")&"折扣",IF(E38=1,"繳費方式不符合員工折扣保費規定","")))) | L13: =IF(SUM(I13:J13)>0,H13,"") | M13: =IF(L13="","",IF(SUM(N14:N16)>=2,"、",IF(SUM(N14:N16)=1,"及",""))) | N13: =IF(L13<>"",1,0) -> 0 | P13: =IF(Q13="","",MAX($P$2:P12)+1) | AD13: =IF(AE13="","",MAX($AD$1:AD12)+1) | AK13: =IF(OR($AL13="",COUNTIF($AL$3:$AR$3,$AL$2)=0),"",MAX($AK$3:AK12)+1) -> 10 | AL13: （二）身分證統一編號。
B14: 生日檢核 | D14: =IF(SUM(E6,D10:D13)>=1,"*日期空白或格式錯誤*","") | P14: =IF(Q14="","",MAX($P$2:P13)+1) | AD14: =IF(AE14="","",MAX($AD$1:AD13)+1) | AK14: =IF(OR($AL14="",COUNTIF($AL$3:$AR$3,$AL$2)=0),"",MAX($AK$3:AK13)+1) -> 11 | AL14: （三）地址。
B15: 最高承保(保險年齡) | C15: =IF($C$22="",,VLOOKUP($C$24,$H$51:$J$54,3,FALSE)) -> 50 | D15: =IF(D5>C15,1,"") | P15: =IF(Q15="","",MAX($P$2:P14)+1) | AD15: =IF(AE15="","",MAX($AD$1:AD14)+1) | AK15: =IF(OR($AL15="",COUNTIF($AL$3:$AR$3,$AL$2)=0),"",MAX($AK$3:AK14)+1) -> 12 | AL15: （四）病歷、醫療、健康檢查 。
B16: ="最低承保"&IF(E16=1,"(足歲)","(保險年齡)") -> 最低承保(足歲) | C16: =IF($C$22="",,VLOOKUP($C$24,H51:J54,2,FALSE)) -> 18 | D16: =IF(IF(E16=1,D6,IF(E16=2,D5,0))<C16,1,"") | E16: 1 | P16: =IF(Q16="","",MAX($P$2:P15)+1) | AD16: =IF(AE16="","",MAX($AD$1:AD15)+1) | AK16: =IF(OR($AL16="",COUNTIF($AL$3:$AR$3,$AL$2)=0),"",MAX($AK$3:AK15)+1) -> 13 | AL16: （五）要保書、要保文件等其他基於保險契約所提供之個人資料。
B17: 年齡檢核 | D17: =IF(SUM(D15:D16)>=1,"*年齡不符合投保區間*","") | H17: =IF($C$24=1,"躉繳","躉繳") -> 躉繳 | P17: =IF(Q17="","",MAX($P$2:P16)+1) | AD17: =IF(AE17="","",MAX($AD$1:AD16)+1) | AK17: =IF(OR($AL17="",COUNTIF($AL$3:$AR$3,$AL$2)=0),"",MAX($AK$3:AK16)+1) -> 14 | AL17: 三、個人資料利用之期間、地區、對象、方式：
B18: 性別 (1.男 2.女) | C18: =IF(輸入頁!$K$5="男",1,IF(輸入頁!$K$5="女",2,0)) -> 2 | D18: =IF(OR(C18="",C18<=0,C18>=3),1,"") | H18: =IF($C$24=1,"年繳","年繳") -> 年繳 | P18: =IF(Q18="","",MAX($P$2:P17)+1) | AD18: =IF(AE18="","",MAX($AD$1:AD17)+1) | AK18: =IF(OR($AL18="",COUNTIF($AL$3:$AR$3,$AL$2)=0),"",MAX($AK$3:AK17)+1) -> 15 | AL18: （一）期間：因執行業務所必須及依法令規定應為保存之期間。
B19: 性別檢核 | D19: =IF(D18=1,"*性別輸入錯誤*","") | H19: =IF($C$24=1,"半年繳","半年繳") -> 半年繳 | P19: =IF(Q19="","",MAX($P$2:P18)+1) | AD19: =IF(AE19="","",MAX($AD$1:AD18)+1) | AK19: =IF(OR($AL19="",COUNTIF($AL$3:$AR$3,$AL$2)=0),"",MAX($AK$3:AK18)+1) -> 16 | AL19: （二）對象：本公司、中華民國人壽保險商業同業公會、財團法人保險事業發展
B20: 基本資料欄位檢核結果 | D20: =IF(SUM(E6,D10:D13,D18)>=1,1,"") | H20: =IF($C$24=1,"季繳","季繳") -> 季繳 | P20: =IF(Q20="","",MAX($P$2:P19)+1) | AD20: =IF(AE20="","",MAX($AD$1:AD19)+1) | AK20: =IF(OR($AL20="",COUNTIF($AL$3:$AR$3,$AL$2)=0),"",MAX($AK$3:AK19)+1) -> 17 | AL20: 中心、財團法人金融消費評議中心、業務委外機構、臺灣網路認證(股)公司、
B21: 計價幣別(1.台幣 2.外幣) | C21: 1 | D21: =IF(OR(C21="",C21<=0,C21>=3),1,"") | E21: 新臺幣 | H21: =IF($C$24=1,"月繳","月繳") -> 月繳 | P21: =IF(Q21="","",MAX($P$2:P20)+1) | AD21: =IF(AE21="","",MAX($AD$1:AD20)+1) | AK21: =IF(OR($AL21="",COUNTIF($AL$3:$AR$3,$AL$2)=0),"",MAX($AK$3:AK20)+1) -> 18 | AL21: 與本公司有再保業務往來之公司、依法有調查權機關或金融監理機關。
B22: 險種代號 | C22: =IF(YPN<>I55,"",YPN) -> CLX | D22: =IF(OR(C22="",C22=0,AND(C22<>K39,C22<>K40)),1,"") | P22: =IF(Q22="","",MAX($P$2:P21)+1) | AD22: =IF(AE22="","",MAX($AD$1:AD21)+1) | AK22: =IF(OR($AL22="",COUNTIF($AL$3:$AR$3,$AL$2)=0),"",MAX($AK$3:AK21)+1)
B23: 商品中文名稱 | C23: 富邦人壽真馨相守防癌定期健康保險 | E23: 繳費年期 | AD23: =IF(AE23="","",MAX($AD$1:AD22)+1) | AK23: =IF(OR($AL23="",COUNTIF($AL$3:$AR$3,$AL$2)=0),"",MAX($AK$3:AK22)+1) -> 19 | AL23: （三）地區：上述對象所在之地區。
B24: 年期 | C24: =IF($C$22="",,輸入頁!$D$22) -> 20 | D24: =IF(OR(C24="",C24=0,COUNTIF(H39:J41,C24)=0),1,"") | E24: =IF($C$22="",,IF(OP!C24=1,"(躉繳)",IF(OP!$C$24>40,"繳費至"&OP!$C$24&"歲滿期","繳費"&OP!$C$24&"年"))) -> 繳費20年 | AD24: =IF(AE24="","",MAX($AD$1:AD23)+1) | AK24: =IF(OR($AL24="",COUNTIF($AL$3:$AR$3,$AL$2)=0),"",MAX($AK$3:AK23)+1) -> 20 | AL24: （四）方式：合於法令規定之利用方式。
B25: 年期檢核 | D25: =IF(SUM(D24)>=1,"*年期選擇錯誤*","") | E25: =COUNTIF(H39:J41,C24) -> 1 | H25: 折扣選項 | I25: =輸入頁!$E$19 -> 無 | AD25: =IF(AE25="","",MAX($AD$1:AD24)+1) | AK25: =IF(OR($AL25="",COUNTIF($AL$3:$AR$3,$AL$2)=0),"",MAX($AK$3:AK24)+1) -> 21 | AL25: 四、依據個資法第三條規定，台端就本公司保有 台端之個人資料得行使之權利及
B26: 最低保額 | C26: =IF($C$22="",,VLOOKUP($C$24,$H$57:$L$60,$H$55+1,FALSE)) -> 50 | H26: 無 | I26: 0 | AD26: =IF(AE26="","",MAX($AD$1:AD25)+1) | AK26: =IF(OR($AL26="",COUNTIF($AL$3:$AR$3,$AL$2)=0),"",MAX($AK$3:AK25)+1) -> 22 | AL26: 方式：
B27: 最高保額 | C27: =IF($C$22="",,VLOOKUP($C$24,$H$57:$L$60,$H$55+2,FALSE)) -> 300 | E27: 保額小數位數 | H27: 員工轉帳件 | I27: 1 | AD27: =IF(AE27="","",MAX($AD$1:AD26)+1) | AK27: =IF(OR($AL27="",COUNTIF($AL$3:$AR$3,$AL$2)=0),"",MAX($AK$3:AK26)+1) -> 23 | AL27: （一）得向本公司行使之權利：
B28: 保額 | C28: =ROUND(輸入頁!J24,1) -> 100 | D28: =IF(OR(C28="",C28=0,C28<C26,C28>C27),1,"") | E28: 0 | H28: 集體彙繳件 | I28: 2 | AD28: =IF(AE28="","",MAX($AD$1:AD27)+1) | AK28: =IF(OR($AL28="",COUNTIF($AL$3:$AR$3,$AL$2)=0),"",MAX($AK$3:AK27)+1) -> 24 | AL28: 1.向本公司查詢、請求閱覽或請求製給複製本。
B29: 保額檢核 | D29: =IF(SUM(D28)>=1,"*保額錯誤*","") | AD29: =IF(AE29="","",MAX($AD$1:AD28)+1) | AK29: =IF(OR($AL29="",COUNTIF($AL$3:$AR$3,$AL$2)=0),"",MAX($AK$3:AK28)+1) -> 25 | AL29: 2.向本公司請求補充或更正。
B30: 每萬保費 | C30: =IF(OR(C18=0,C22=0,D28=1),0,IF(ISNA(VLOOKUP($C$55,GP,2,0)),0,VLOOKUP($C$55,GP,2,0))) -> 350 | H30: 繳別 | I30: 折扣率 | L30: 首期 | M30: 續期 | AD30: =IF(AE30="","",MAX($AD$1:AD29)+1) | AK30: =IF(OR($AL30="",COUNTIF($AL$3:$AR$3,$AL$2)=0),"",MAX($AK$3:AK29)+1) -> 26 | AL30: 3.向本公司請求停止蒐集、處理或利用及請求刪除。
B31: 原始應繳保費 | C31: =IF($C$21=1,ROUND($C28*BGP,1),IF(C21=2,ROUND($C28*BGP,1),"")) -> 35000 | H31: 匯款 | I31: =IF($C$24=1,0,1%) -> 0.01 | J31: ↓首期 | L31: 匯款 | M31: =IF($C$24=1,"","金融機構轉帳") -> 金融機構轉帳 | AD31: =IF(AE31="","",MAX($AD$1:AD30)+1) | AK31: =IF(OR($AL31="",COUNTIF($AL$3:$AR$3,$AL$2)=0),"",MAX($AK$3:AK30)+1) -> 27 | AL31: （二）行使權利之方式：
B32: 繳別 | C32: =IF(PM="","",PM) -> 年繳 | D32: =IF(OR(C32="",C32=0,COUNTIF(繳,$C$32)<1),1,"") | E32: =IF($D$32=1,"繳別錯誤","") | H32: 金融機構轉帳 | I32: =IF($C$24=1,0,1%) -> 0.01 | J32: 續期↓ | L32: 金融機構轉帳 | M32: =IF($C$24=1,"","富邦信用卡") -> 富邦信用卡 | AD32: =IF(AE32="","",MAX($AD$1:AD31)+1) | AK32: =IF(OR($AL32="",COUNTIF($AL$3:$AR$3,$AL$2)=0),"",MAX($AK$3:AK31)+1) -> 28 | AL32: 您可以透過書面（包含電子郵件、傳真、電子文件）方式行使權利。
B33: 換算格式1.傳統 2.直接除 | C33: 1 | D33: =IF(OR(C33="",C33=0),1,"") | H33: 富邦信用卡 | I33: =IF($C$24=1,0,1%) -> 0.01 | L33: =IF($C$24=1,"支票","富邦信用卡") -> 富邦信用卡 | M33: =IF($C$24=1,"","一般信用卡") -> 一般信用卡 | AD33: =IF(AE33="","",MAX($AD$1:AD32)+1) | AK33: =IF(OR($AL33="",COUNTIF($AL$3:$AR$3,$AL$2)=0),"",MAX($AK$3:AK32)+1)
B34: 繳別換算率 | C34: =IF(D32=1,,VLOOKUP(C32,H2:K7,1+C33,FALSE)) -> 1 | H34: 一般信用卡 | I34: =IF($C$24=1,0,0%) -> 0 | J34: ↑首期 | L34: =IF($C$24=1,"","一般信用卡") -> 一般信用卡 | M34: =IF($C$24=1,"","收費") -> 收費 | AD34: =IF(AE34="","",MAX($AD$1:AD33)+1) | AK34: =IF(OR($AL34="",COUNTIF($AL$3:$AR$3,$AL$2)=0),"",MAX($AK$3:AK33)+1) -> 29 | AL34: 五、台端不提供個人資料所致權益之影響
B35: 應繳保費 | C35: =IF($C$21=1,ROUND(C31*C34,0),IF($C$21=2,ROUNDDOWN(C31*C34,0),"")) -> 35000 | H35: 支票 | I35: =IF($C$24=1,0,0%) -> 0 | L35: =IF($C$24=1,"","支票") -> 支票 | M35: =IF($C$24=1,"","自行繳費") -> 自行繳費 | AD35: =IF(AE35="","",MAX($AD$1:AD34)+1) | AK35: =IF(OR($AL35="",COUNTIF($AL$3:$AR$3,$AL$2)=0),"",MAX($AK$3:AK34)+1) -> 30 | AL35: 台端若未能提供相關個人資料時，本公司將可能延後或無法進行必要之審核
B36: 高保費折扣 | D36: 低<=保費<高 | H36: 自行繳費 | I36: =IF($C$24=1,0,1%) -> 0.01 | J36: 續期↑ | AD36: =IF(AE36="","",MAX($AD$1:AD35)+1) | AK36: =IF(OR($AL36="",COUNTIF($AL$3:$AR$3,$AL$2)=0),"",MAX($AK$3:AK35)+1) -> 31 | AL36: 及處理作業，因此可能婉謝承保、遲延或無法承保。
B37: 高保額折扣 | C37: 0 | H37: 收費 | I37: =IF($C$24=1,0,0%) -> 0 | AD37: =IF(AE37="","",MAX($AD$1:AD36)+1) | AK37: =IF(OR($AL37="",COUNTIF($AL$3:$AR$3,$AL$2)=0),"",MAX($AK$3:AK36)+1)
B38: 集彙折扣-首期 | C38: =IF(AND($C$24<>1,$I$25=2,OR(AND(OR(C41=H31,C41=H35),OR(C43=H32,C43=H33,C43=H34,C43=H36)),$C$41=$H$32,$C$41=$H$33,$C$41=$H$34)),2%,0%) -> 0 | D38: =IF(C38>0,"本主約首期保費享有 "&TEXT(C38,"0%")&" 集體彙繳折扣","") | E38: =VLOOKUP(I25,H26:I28,2,0) -> 0 | H38: 年期 | K38: 險種 | AD38: =IF(AE38="","",MAX($AD$1:AD37)+1) | AK38: =IF(OR($AL38="",COUNTIF($AL$3:$AR$3,$AL$2)=0),"",MAX($AK$3:AK37)+1)
B39: 集彙折扣-續期 | C39: =IF(AND($C$24<>1,$I$25=2,OR($C$43=$H$32,$C$43=$H$33,$C$43=$H$34,$C$43=$H$36)),2%,0%) -> 0 | D39: =IF(C39>0,"本主約續期保費享有 "&TEXT(C39,"0%")&" 集體彙繳折扣","") | H39: 10 | I39: 20 | K39: CLX | AD39: =IF(AE39="","",MAX($AD$1:AD38)+1) | AK39: =IF(OR($AL39="",COUNTIF($AL$3:$AR$3,$AL$2)=0),"",MAX($AK$3:AK38)+1)
B40: 員工折扣 | C40: =IF(AND($C$24=10,$E$38=1,C41=H32,OR(C43=H32,C43=H36)),8%,IF(AND($C$24=20,$E$38=1,C41=H32,OR(C43=H32,C43=H36)),6%,0%)) -> 0 | D40: =IF(C40>0,"本保件享有 "&TEXT(C40,"0%")&" 員工轉帳件折扣","") | AD40: =IF(AE40="","",MAX($AD$1:AD39)+1) | AK40: =IF(OR($AL40="",COUNTIF($AL$3:$AR$3,$AL$2)=0),"",MAX($AK$3:AK39)+1)
B41: 首期繳別 | C41: =輸入頁!Q16 -> 金融機構轉帳 | AD41: =IF(AE41="","",MAX($AD$1:AD40)+1) | AK41: =IF(OR($AL41="",COUNTIF($AL$3:$AR$3,$AL$2)=0),"",MAX($AK$3:AK40)+1)
B42: 自繳折扣-首期 | C42: =IF(OR(ISNA(VLOOKUP(C41,$H$30:$I$37,2,FALSE)),$C$40>0),0,VLOOKUP(C41,$H$30:$I$37,2,FALSE)) -> 0.01 | D42: =IF(C42>0,"-首期享有1%繳別折扣-","") -> -首期享有1%繳別折扣- | H42: 主約選項 | J42: 繳費年期 | AD42: =IF(AE42="","",MAX($AD$1:AD41)+1) | AK42: =IF(OR($AL42="",COUNTIF($AL$3:$AR$3,$AL$2)=0),"",MAX($AK$3:AK41)+1)
B43: 續期繳別 | C43: =輸入頁!Q18 -> 金融機構轉帳 | I43: 1 | J43: 1 | L43: 健康管理保險費折扣項目 | M43: =$C$22&"折扣率" -> CLX折扣率 | N43: =$C$22&"續年度折扣後實繳保費"&IF($C$47>0,"(含續期繳費方式折扣"&TEXT($C$47,"0.0%")&")","") -> CLX續年度折扣後實繳保費(含續期繳費方式折扣1.0%) | AD43: =IF(AE43="","",MAX($AD$1:AD42)+1) | AK43: =IF(OR($AL43="",COUNTIF($AL$3:$AR$3,$AL$2)=0),"",MAX($AK$3:AK42)+1)
B44: 自繳折扣-續期 | C44: =IF(OR(ISNA(VLOOKUP(C43,$H$30:$I$37,2,FALSE)),$C$40>0),0,VLOOKUP(C43,$H$30:$I$37,2,FALSE)) -> 0.01 | D44: =IF(C44>0,"-續期享有1%繳別折扣-","") -> -續期享有1%繳別折扣- | H44: 10 | I44: 10 | J44: 10 | L44: 健康檢查 | M44: 0.01 | N44: =ROUND($C$35*(1-($C$47+$M$44)),0) -> 34300 | AD44: =IF(AE44="","",MAX($AD$1:AD43)+1) | AK44: =IF(OR($AL44="",COUNTIF($AL$3:$AR$3,$AL$2)=0),"",MAX($AK$3:AK43)+1)
B45: 折扣率上限 | C45: =IF(AND(E38=1,C40>0),8%,6%) -> 0.06 | D45: =IF(OR(C45="",),1,"") | H45: 20 | I45: 20 | J45: 20 | AD45: =IF(AE45="","",MAX($AD$1:AD44)+1) | AK45: =IF(OR($AL45="",COUNTIF($AL$3:$AR$3,$AL$2)=0),"",MAX($AK$3:AK44)+1)
B46: 首期總折扣率 | C46: =MIN(SUM(C36:C37,C38,C40,C42),C45) -> 0.01 | D46: =IF(OR(C42>0,C44>0),"繳費方式折扣‧","")&IF(C37>0,"高保額折扣‧","")&IF(OR(C38>0,C39>0),"集體彙繳件折扣‧","")&IF(OR(C40>0),"員工轉帳件折扣‧","") -> 繳費方式折扣‧ | AD46: =IF(AE46="","",MAX($AD$1:AD45)+1) | AL46: 保經代 | AM46: 錠嵂保經 | AN46: 銀保
B47: 續期總折扣率 | C47: =MIN(SUM(C37,C39,C40,C44),C45) -> 0.01 | D47: =IF(OR(C37+C38+C40+C42>C45,C37+C39+C44>C45),"本商品折扣率上限"&TEXT($C$45,"0%。"),"") | AD47: =IF(AE47="","",MAX($AD$1:AD46)+1) | AK47: =IF(OR($AL47="",COUNTIF($AL$46:$AR$46,$AL$2)=0),"",MAX($AK$3:AK46)+1) | AL47: 富邦人壽保險股份有限公司履行個人資料保護法告知說明書
B48: 首期實繳保費 | C48: =ROUND(MGP*(1-C46),0) -> 34650 | AD48: =IF(AE48="","",MAX($AD$1:AD47)+1) | AK48: =IF(OR($AL48="",COUNTIF($AL$46:$AR$46,$AL$2)=0),"",MAX($AK$3:AK47)+1)
B49: 續期實繳保費 | C49: =ROUND(MGP*(1-C47),0) -> 34650 | D49: =IF($C$50=12,"-月繳首期須繳 2個月 "&TEXT($C$48*2,"#,##0 元-"),"") | AD49: =IF(AE49="","",MAX($AD$1:AD48)+1) | AK49: =IF(OR($AL49="",COUNTIF($AL$46:$AR$46,$AL$2)=0),"",MAX($AK$3:AK48)+1) | AL49: 富邦人壽保險股份有限公司（下稱本公司）依據個人資料保護法（以下稱個資法）
B50: 繳別回乘倍數 | C50: =IF(D32=1,,VLOOKUP(C32,H2:K7,4,FALSE)) -> 1 | E50: ←首期保費規則 | H50: 年期 | I50: 最低年齡 | J50: 最高年齡 | AD50: =IF(AE50="","",MAX($AD$1:AD49)+1) | AK50: =IF(OR($AL50="",COUNTIF($AL$46:$AR$46,$AL$2)=0),"",MAX($AK$3:AK49)+1) | AL50: 規定，向 台端告知下列事項，請 台端詳閱：
B51: 首年實繳保費 | C51: =IF(C50=12,C48*2+C49*10,C48*1+C49*(C50-1)) -> 34650 | D51: 40831 | AD51: =IF(AE51="","",MAX($AD$1:AD50)+1) | AK51: =IF(OR($AL51="",COUNTIF($AL$46:$AR$46,$AL$2)=0),"",MAX($AK$3:AK50)+1) | AL51: 一、蒐集之目的：
B52: 續年實繳保費 | C52: =C49*C50 -> 34650 | H52: 10 | I52: 18 | J52: 60 | AD52: =IF(AE52="","",MAX($AD$1:AD51)+1) | AK52: =IF(OR($AL52="",COUNTIF($AL$46:$AR$46,$AL$2)=0),"",MAX($AK$3:AK51)+1) | AL52: （一）人身保險（００一）
B53: 主約1欄位檢核結果 | D53: =IF(SUM(D15:D16,D28,D32:D33,D40:D41,D43,D45,D50,D24,D64)>=1,1,"") | H53: 20 | I53: 18 | J53: 50 | AD53: =IF(AE53="","",MAX($AD$1:AD52)+1) | AK53: =IF(OR($AL53="",COUNTIF($AL$46:$AR$46,$AL$2)=0),"",MAX($AK$3:AK52)+1) | AL53: （二）其他經營合於營業登記項目或組織章程所定之業務（一八一）
B54: 版次 | C54: V1.1-1150409 | AD54: =IF(AE54="","",MAX($AD$1:AD53)+1) | AK54: =IF(OR($AL54="",COUNTIF($AL$46:$AR$46,$AL$2)=0),"",MAX($AK$3:AK53)+1) | AL54: 二、蒐集之個人資料類別：
B55: KEY | C55: =$C$22&$C$24&TEXT($C$18,"00")&TEXT($D$5,"00") -> CLX200239 | D55: A險種+年期(2位)+性別(1位)+年齡(2位) | H55: =IF(C22=I55,1,3) -> 1 | I55: CLX | AD55: =IF(AE55="","",MAX($AD$1:AD54)+1) | AK55: =IF(OR($AL55="",COUNTIF($AL$46:$AR$46,$AL$2)=0),"",MAX($AK$3:AK54)+1) | AL55: （一）姓名。
B56: SUMKEY | C56: =IF($C$24=1,$C$22,C22&TEXT($C$24,"00")) -> CLX20 | D56: F險種+年期(2位)+年齡(2位) | H56: 保額 | I56: 最低保額 | J56: 最高保額 | AD56: =IF(AE56="","",MAX($AD$1:AD55)+1) | AK56: =IF(OR($AL56="",COUNTIF($AL$46:$AR$46,$AL$2)=0),"",MAX($AK$3:AK55)+1) | AL56: （二）身分證統一編號。
B57: MAX-Y | C57: =$F$57+1-D5 -> 51 | E57: 保障至幾歲 | F57: 89 | AD57: =IF(AE57="","",MAX($AD$1:AD56)+1) | AK57: =IF(OR($AL57="",COUNTIF($AL$46:$AR$46,$AL$2)=0),"",MAX($AK$3:AK56)+1) | AL57: （三）地址。
B58: KEY | C58: =$C$22&TEXT($C$24,"00") -> CLX20 | H58: 10 | I58: 50 | J58: =VLOOKUP($D$5,$H$72:$I$132,2,0) -> 300 | AD58: =IF(AE58="","",MAX($AD$1:AD57)+1) | AK58: =IF(OR($AL58="",COUNTIF($AL$46:$AR$46,$AL$2)=0),"",MAX($AK$3:AK57)+1) | AL58: （四）病歷、醫療、健康檢查 。
H59: 20 | I59: 50 | J59: =VLOOKUP($D$5,$H$72:$I$132,2,0) -> 300 | AD59: =IF(AE59="","",MAX($AD$1:AD58)+1) | AK59: =IF(OR($AL59="",COUNTIF($AL$46:$AR$46,$AL$2)=0),"",MAX($AK$3:AK58)+1) | AL59: （五）要保書、要保文件等其他基於保險契約所提供之個人資料。
AD60: =IF(AE60="","",MAX($AD$1:AD59)+1) | AK60: =IF(OR($AL60="",COUNTIF($AL$46:$AR$46,$AL$2)=0),"",MAX($AK$3:AK59)+1) | AL60: 三、個人資料利用之期間、地區、對象、方式：
H61: 公版 | I61: =HLOOKUP(H61,H62:K63,2,0) -> 1 | AD61: =IF(AE61="","",MAX($AD$1:AD60)+1) | AK61: =IF(OR($AL61="",COUNTIF($AL$46:$AR$46,$AL$2)=0),"",MAX($AK$3:AK60)+1) | AL61: （一）期間：因執行業務所必須及依法令規定應為保存之期間。
H62: 公版 | I62: 北富銀 | J62: FAX | K62: ON-LINE | AD62: =IF(AE62="","",MAX($AD$1:AD61)+1) | AK62: =IF(OR($AL62="",COUNTIF($AL$46:$AR$46,$AL$2)=0),"",MAX($AK$3:AK61)+1) | AL62: （二）對象：本公司、中華民國人壽保險商業同業公會、財團法人保險事業發展
H63: 1 | I63: 2 | J63: 3 | K63: 4 | AD63: =IF(AE63="","",MAX($AD$1:AD62)+1) | AK63: =IF(OR($AL63="",COUNTIF($AL$46:$AR$46,$AL$2)=0),"",MAX($AK$3:AK62)+1) | AL63: 中心、財團法人金融消費評議中心、業務委外機構、臺灣網路認證(股)公司、
B64: 保額輸入檢核 | C64: =輸入頁!$J$24 -> 100 | D64: =IF(ROUND($C$64,$E$28)<>$C$64,1,"") | E64: =IF(D64=1,"保額輸入"&C64&"不符投保規則，請重新輸入","") | AD64: =IF(AE64="","",MAX($AD$1:AD63)+1) | AK64: =IF(OR($AL64="",COUNTIF($AL$46:$AR$46,$AL$2)=0),"",MAX($AK$3:AK63)+1) | AL64: 與本公司有再保業務往來之公司、依法有調查權機關或金融監理機關。
AD65: =IF(AE65="","",MAX($AD$1:AD64)+1) | AK65: =IF(OR($AL65="",COUNTIF($AL$46:$AR$46,$AL$2)=0),"",MAX($AK$3:AK64)+1) | AL65: （三）地區：上述對象所在之地區。
AD66: =IF(AE66="","",MAX($AD$1:AD65)+1) | AK66: =IF(OR($AL66="",COUNTIF($AL$46:$AR$46,$AL$2)=0),"",MAX($AK$3:AK65)+1) | AL66: （四）方式：合於法令規定之利用方式。
AD67: =IF(AE67="","",MAX($AD$1:AD66)+1) | AK67: =IF(OR($AL67="",COUNTIF($AL$46:$AR$46,$AL$2)=0),"",MAX($AK$3:AK66)+1) | AL67: 四、依據個資法第三條規定，台端就本公司保有 台端之個人資料得行使之權利及
AD68: =IF(AE68="","",MAX($AD$1:AD67)+1) | AK68: =IF(OR($AL68="",COUNTIF($AL$46:$AR$46,$AL$2)=0),"",MAX($AK$3:AK67)+1) | AL68: 方式：
B69: 適用通路： | C69: 業務、服展、北富銀 | D69: PB | F69: ←銀保通路判別使用 | AD69: =IF(AE69="","",MAX($AD$1:AD68)+1) | AK69: =IF(OR($AL69="",COUNTIF($AL$46:$AR$46,$AL$2)=0),"",MAX($AK$3:AK68)+1) | AL69: （一）得向本公司行使之權利：
AK70: =IF(OR($AL70="",COUNTIF($AL$46:$AR$46,$AL$2)=0),"",MAX($AK$3:AK69)+1) | AL70: 1.向本公司查詢、請求閱覽或請求製給複製本。
B71: 姓名遮蔽用：中/英/數混合：前6碼"*"，中文：倒數第2碼"○" | H71: 年齡-1 | I71: 最高保額-2 | J71: 保留-3 | K71: 保留-4 | L71: 免體檢額度-5 | M71: 通算係數-分期-10 | N71: 通算系數-分期-20 | O71: 通算系數-分期-30 | AK71: =IF(OR($AL71="",COUNTIF($AL$46:$AR$46,$AL$2)=0),"",MAX($AK$3:AK70)+1) | AL71: 2.向本公司請求補充或更正。
B72: 姓名： | C72: =IN -> 客戶 | D72: ←輸入頁資料 | E72: 0 | H72: 0 | I72: 0 | L72: 1000 | M72: 0 | N72: 0 | O72: 0 | AK72: =IF(OR($AL72="",COUNTIF($AL$46:$AR$46,$AL$2)=0),"",MAX($AK$3:AK71)+1) | AL72: 3.向本公司請求停止蒐集、處理或利用及請求刪除。
B73: 帶入資料 | C73: =IF(E72=0,C72,IF(OR(E73=1,C72="",C72=0)," ",IF(AND(E82=0),C74&MID(C72,7,50),IF(LEN(C72)=1,C72,LEFT(C72,LEN(C72)-2)&"○"&RIGHT(C72,1))))) -> 客戶 | D73: 判別不顯示(不判別) | H73: 1 | I73: 0 | L73: 1000 | M73: 0 | N73: 0 | O73: 0 | AK73: =IF(OR($AL73="",COUNTIF($AL$46:$AR$46,$AL$2)=0),"",MAX($AK$3:AK72)+1) | AL73: （二）行使權利之方式：
B74: =IF(OR(E73=1,C72="",C72=0),"",IF(AND(E82=0),LEN(C72),"")) | C74: =IF(OR(B74=""),"",IF(ISERROR(VLOOKUP(B74,B75:C80,2,0)),C80,VLOOKUP(B74,B75:C80,2,0))) | D74: ID-11碼數字 | E74: =IF(AND(ISNUMBER(C72),LEN(C72)=11),1,0) -> 0 | H74: 2 | I74: 0 | L74: 1000 | M74: 0 | N74: 0 | O74: 0 | AK74: =IF(OR($AL74="",COUNTIF($AL$46:$AR$46,$AL$2)=0),"",MAX($AK$3:AK73)+1) | AL74: 您可以透過書面（包含電子郵件、傳真、電子文件）方式行使權利。
B75: 1 | C75: * | D75: ID-10碼 | E75: =IF(AND(LEN(C72)=10,ISTEXT(LEFT(C72,1)),ISNUMBER(RIGHT(C72,1)*1)),1,0) -> 0 | H75: 3 | I75: 0 | L75: 1000 | M75: 0 | N75: 0 | O75: 0 | AK75: =IF(OR($AL75="",COUNTIF($AL$46:$AR$46,$AL$2)=0),"",MAX($AK$3:AK74)+1)
B76: 2 | C76: ** | D76: 護照-9碼 | E76: =IF(AND(ISNUMBER(C72),LEN(C72)=9),1,0) -> 0 | H76: 4 | I76: 0 | L76: 1000 | M76: 0 | N76: 0 | O76: 0 | AK76: =IF(OR($AL76="",COUNTIF($AL$46:$AR$46,$AL$2)=0),"",MAX($AK$3:AK75)+1) | AL76: 五、台端不提供個人資料所致權益之影響
B77: 3 | C77: *** | H77: 5 | I77: 0 | L77: 1000 | M77: 0 | N77: 0 | O77: 0 | AK77: =IF(OR($AL77="",COUNTIF($AL$46:$AR$46,$AL$2)=0),"",MAX($AK$3:AK76)+1) | AL77: 台端若未能提供相關個人資料時，本公司將可能延後或無法進行必要之審核
B78: 4 | C78: **** | H78: 6 | I78: 0 | L78: 1000 | M78: 0 | N78: 0 | O78: 0 | AK78: =IF(OR($AL78="",COUNTIF($AL$46:$AR$46,$AL$2)=0),"",MAX($AK$3:AK77)+1) | AL78: 及處理作業，因此可能婉謝承保、遲延或無法承保。
B79: 5 | C79: ***** | H79: 7 | I79: 0 | L79: 1000 | M79: 0 | N79: 0 | O79: 0 | AK79: =IF(OR($AL79="",COUNTIF($AL$46:$AR$46,$AL$2)=0),"",MAX($AK$3:AK78)+1)
B80: 6 | C80: ****** | H80: 8 | I80: 0 | L80: 1000 | M80: 0 | N80: 0 | O80: 0 | AK80: =IF(OR($AL80="",COUNTIF($AL$46:$AR$46,$AL$2)=0),"",MAX($AK$3:AK79)+1)
B81: 空格位置 | C81: =IF(OR(ISERROR(SEARCH(" ",C72)),CODE(C72)>255),"",SEARCH(" ",C72)) | H81: 9 | I81: 0 | L81: 1000 | M81: 0 | N81: 0 | O81: 0 | AK81: =IF(OR($AL81="",COUNTIF($AL$46:$AR$46,$AL$2)=0),"",MAX($AK$3:AK80)+1)
B82: 簡寫 | C82: =IF(OR(ISERROR(SEARCH(" ",C72)),CODE(C72)>255),"",UPPER(LEFT(C72,1)&"."&MID(C72,C81+1,1))) | D82: 1-中文-0-混合 | E82: =IF(LEN(C72)*2=LENB(C72),1,0) -> 1 | H82: 10 | I82: 0 | L82: 1000 | M82: 0 | N82: 0 | O82: 0 | AK82: =IF(OR($AL82="",COUNTIF($AL$46:$AR$46,$AL$2)=0),"",MAX($AK$3:AK81)+1)
H83: 11 | I83: 0 | L83: 1000 | M83: 0 | N83: 0 | O83: 0 | AK83: =IF(OR($AL83="",COUNTIF($AL$46:$AR$46,$AL$2)=0),"",MAX($AK$3:AK82)+1)
H84: 12 | I84: 0 | L84: 1000 | M84: 0 | N84: 0 | O84: 0 | AK84: =IF(OR($AL84="",COUNTIF($AL$46:$AR$46,$AL$2)=0),"",MAX($AK$3:AK83)+1)
B85: 提醒設定 | C85: 1 | D85: 0 | H85: 13 | I85: 0 | L85: 1000 | M85: 0 | N85: 0 | O85: 0 | AK85: =IF(OR($AL85="",COUNTIF($AL$46:$AR$46,$AL$2)=0),"",MAX($AK$3:AK84)+1)
B86: 跳歲計算 | C86: =IF($D$53=1,"",DATE(YEAR($D$3)+$D$6,MONTH($D$3)+6,MIN(DAY($D$3),$E$86)+1)) -> 46357 | D86: =MONTH($D$3)+IF(MONTH($D$3)<=6,6,-6) -> 11 | E86: =IF(OR($D$86=1,$D$86=3,$D$86=5,$D$86=7,$D$86=8,$D$86=10,$D$86=12),31,IF(OR($D$86=4,$D$86=6,$D$86=9,$D$86=11),30,IF(AND($D$86=2,YEAR($C$3)/4=INT(YEAR($C$3)/4),YEAR($C$3)/400<>INT(YEAR($C$3)/400)),29,28))) -> 30 | H86: 14 | I86: 0 | L86: 1000 | M86: 0 | N86: 0 | O86: 0 | AK86: =IF(OR($AL86="",COUNTIF($AL$46:$AR$46,$AL$2)=0),"",MAX($AK$3:AK85)+1)
C87: =IF($D$53=1,"",IF(C86<$C$3,"",C86-$C$3)) -> 118 | D87: =IF(C85=0,"",IF(OR($D$53=1,C87=""),"",IF(AND(C87>=1,C87<=30),"提醒您：被保險人將於 "&MONTH(C86)&" 月 "&DAY(C86)&" 日 ( "&C87&"天後 ) 保險年齡增加一歲"&IF(D85=0,"。","，"&$C$22&$C$32&"保險費"&IF($C$32="躉繳","","每期")&IF(E88>=0,"增加 ","減少 ")&TEXT(E88,"#,##0 元")&"。"),""))) | H87: 15 | I87: 0 | L87: 1000 | M87: 0 | N87: 0 | O87: 0 | AK87: =IF(OR($AL87="",COUNTIF($AL$46:$AR$46,$AL$2)=0),"",MAX($AK$3:AK86)+1)
B88: 新年齡/保費/差異 | C88: =C22&IF($C$24=1,"",TEXT($C$24,"00"))&TEXT($C$18,"00")&TEXT($D$5+1,"00") -> CLX200240 | D88: =IF(ISNA(VLOOKUP(C88,GP,2,0)),0,IF($C$21=1,ROUND(VLOOKUP(C88,GP,2,0)*$C$28*$C$34,0),IF($C$21=2,ROUNDDOWN(VLOOKUP(C88,GP,2,0)*$C$28*C34,0),""))) -> 35500 | E88: =D88-$C$35 -> 500 | H88: 16 | I88: 0 | L88: 1000 | M88: 0 | N88: 0 | O88: 0 | AK88: =IF(OR($AL88="",COUNTIF($AL$46:$AR$46,$AL$2)=0),"",MAX($AK$3:AK87)+1)
H89: 17 | I89: 0 | L89: 1000 | M89: 0 | N89: 0 | O89: 0 | AK89: =IF(OR($AL89="",COUNTIF($AL$46:$AR$46,$AL$2)=0),"",MAX($AK$3:AK88)+1)
B90: 全列印頁面使用 | C90: 更新區域 | D90: 帶入內容區域 | E90: OLD/說明 | H90: 18 | I90: 300 | L90: 1000 | M90: 0 | N90: 0 | O90: 0 | AK90: =IF(OR($AL90="",COUNTIF($AL$46:$AR$46,$AL$2)=0),"",MAX($AK$3:AK89)+1)
B91: 折扣率： | D91: =IF(OR(OP!$D$53=1,AND(OP!C46=0,OP!C47=0)),"","本保件符合保費折扣條件："&OP!$K$9) -> 本保件符合保費折扣條件：繳費方式 1.0%折扣 | H91: 19 | I91: 300 | L91: 1000 | M91: 0 | N91: 0 | O91: 0
B92: 保費/折扣後保費： | D92: =IF(OR(OP!$D$53=1),"",$C$32&"總保費 "&TEXT($C$35,"#,##0元")&IF(AND($C$46=0,$C$47=0),"","，"&IF($C$24=1,IF(OP!$C$46>0,"躉繳折扣後保費 "&TEXT($C$48,"#,##0 元"),""),IF($C$46>0,"首期折扣後保費 "&TEXT($C$48,"#,##0 元 "),"首期保費 "&TEXT($C$48,"#,##0 元 "))&"，"&IF($C$47>0,"續期折扣後保費 "&TEXT($C$49,"#,##0 元 "),"續期保費 "&TEXT($C$49,"#,##0 元 "))))&$D$49) -> 年繳總保費 35,000元，首期折扣後保費 34,650 元 ，續期折扣後保費 34,650 元 | H92: 20 | I92: 300 | L92: 1000 | M92: 0 | N92: 0 | O92: 0
B93: 表格保險種類 | D93: =IF(OP!$D$53=1,"",OP!$C$23&IF(OP!C24=1,"(躉繳)",IF(OP!$C$24=65,"(繳費至"&OP!$C$24&"歲滿期)","(繳費"&OP!$C$24&"年)"))) -> 富邦人壽真馨相守防癌定期健康保險(繳費20年) | H93: 21 | I93: 300 | L93: 1000 | M93: 0 | N93: 0 | O93: 0
B94: 本保單計價幣別： | C94: =$E$21 -> 新臺幣 | D94: =$B$94&$C$94 -> 本保單計價幣別：新臺幣 | H94: 22 | I94: 300 | L94: 1000 | M94: 0 | N94: 0 | O94: 0
B95: =IF(OP!$C$105="停售","宣告利率：",YEAR(OP!$C$3)-1911&" / "&MONTH(OP!$C$3)&" 宣告利率：") -> 115 / 8 宣告利率： | D95: =$B$95&$C$95 -> 115 / 8 宣告利率： | H95: 23 | I95: 300 | L95: 1000 | M95: 0 | N95: 0 | O95: 0
B96: 增值回饋分享金給付方式： | D96: =$B$96&$C$96 -> 增值回饋分享金給付方式： | H96: 24 | I96: 300 | L96: 1000 | M96: 0 | N96: 0 | O96: 0
B97: 有增值回饋分享金頁首： | D97: =$D$95&"，"&$D$96 -> 115 / 8 宣告利率：，增值回饋分享金給付方式： | E97: 其他頁面用 | H97: 25 | I97: 300 | L97: 1000 | M97: 0 | N97: 0 | O97: 0
B98: 有增值回饋分享金頁首： | D98: =$D$95&"，"&$C$98 -> 115 / 8 宣告利率：， | E98: 彙總版用 | H98: 26 | I98: 300 | L98: 1000 | M98: 0 | N98: 0 | O98: 0
H99: 27 | I99: 300 | L99: 1000 | M99: 0 | N99: 0 | O99: 0
B100: 商品文號： | C100: 105.11.14富壽商精字第 1050003499 號函備查、110.07.26富壽商精字第1100001366號函備查 | D100: =$B$100&$C$100 -> 商品文號：105.11.14富壽商精字第 1050003499 號函備查、110.07.26富壽商精字第1100001366號函備查 | H100: 28 | I100: 300 | L100: 1000 | M100: 0 | N100: 0 | O100: 0
...

Sheet 輸入頁
AS1: 0
A2: =OP!D53 | B2: =OP!$C$23&"建議書" -> 富邦人壽真馨相守防癌定期健康保險建議書
B3: 請注意：如使用非微軟OFFICE-PC版開啟本建議書，本建議書內容可能會因硬體系統升級或軟體更新問題導致數值誤差，業務同仁使用時請確實確認。
B5: 被保險人 | D5: 姓名： | E5: 客戶 | J5: 性別： | K5: 女 | N5: 投保年齡區間： | O5: =IF(OR(K5="",E16="",Q16=""),"",OP!$C$16&" 足歲 ~ "&OP!$C$15&"歲 "&"("&OP!F7&")") -> 18 足歲 ~ 50歲 (650205) | R5: =IF(OP!$C$105="停售","本商品已停售","")
D7: 生日： | E7: 760530 | I7: =IF(OP!$E$6=1,"生日日期錯誤",OP!$D$17) | N7: 保險年齡： | O7: =IF(OR(K5="",E7="",E16="",Q16=""),"",OP!$D$5) -> 39 | Q7: 實際年齡： | R7: =IF(OP!$E$6=1,"",OP!$D$6) -> 39
D12: 要保人： | E12: 與被保險人不同 | N12: 繳款人： | O12: 與要被保人不同
D13: =IF($E$12="同被保險人","","要保人姓名：") -> 要保人姓名： | N13: 繳款人姓名：
D14: 要保人生日(民國)： | I14: =IF(OR($E$14=""),"","保險年齡："&OP!$D$154&"歲") | N14: 繳款人生日(民國)：
E15: =IF(AND($E$14<>"",OP!$E$155=1),"要保人生日日期錯誤","")&OP!$B$155 | O15: =IF(AND($O$14<>"",OP!$D$159=1),"本件需進行錄音","")
A16: =OP!$D$32 | D16: 繳別： | E16: 年繳 | H16: =IF(M24="","",OP!D49&OP!$E$32) | O16: 繳費方式： | P16: =IF(OP!$C$24=1,"","首期") -> 首期 | Q16: 金融機構轉帳 | T16: =IF(COUNTIF(OP!$L$31:$L$37,OP!$C$41)<1,1,"")
P18: =IF(OP!$C$24=1,"","續期") -> 續期 | Q18: 金融機構轉帳 | T18: =IF(AND(OP!$C$24<>1,COUNTIF(OP!$M$31:$M$37,OP!$C$43)<1),1,"")
A19: =IF(AND(OP!I13<=0,OP!J13<=0,OP!E38=1),1,"") | D19: 專案保費折扣： | E19: 無 | N19: =IF($A$2=1,"",IF(OR(OP!$C$42>0,OP!$C$44>0),"本保件如符合本公司保費折扣條件，","")&IF(AND(OP!$C$42>0,OP!$C$44>0),"首、續期享有1%保費折扣",IF(AND(OP!$C$42=0,OP!$C$44>0),"續期享有1%保費折扣",IF(AND(OP!$C$42>0,OP!$C$44=0),"首期享有1%保費折扣","")))) -> 本保件如符合本公司保費折扣條件，首、續期享有1%保費折扣
C20: =IF($A$2=1,"",OP!K12&OP!K13)
A22: =OP!$D$24 | C22: 繳費年期： | D22: 20 | M22: 保額限制(以萬為單位)： | P22: =IF(OR($A$2=1),"",OP!$C$32&"保費：") -> 年繳保費： | R22: =IF($A$2=1,"",OP!$C$35) -> 35000
A24: =IF(OR(OP!$C$28<J25,OP!$C$28>K25),1,"") | B24: 險種代號： | D24: CLX | G24: 保額(萬)： | J24: 100 | M24: =IF(OR(D24="",K25<J25),"",TEXT(J25,IF(OP!$E$28=0,"#,##0 ","#,##0.0 ")&"萬")&" ~ "&TEXT(K25,IF(OP!$E$28=0,"#,##0 ","#,##0.0 ")&"萬")) -> 50 萬 ~ 300 萬 | O24: =IF(OP!$D$64=1,OP!$E$64,IF(OR($A$2=1),"",IF(OP!$C$37>0,"本保件享 "&TEXT(OP!$C$37,"0.0%")&OP!$B$37,"")&IF(OP!I25=3,OP!D40,"")))
J25: =OP!$C$26 -> 50 | K25: =OP!$C$27 -> 300
C26: =IF(OR(O7>O5,D24="",M24="保額超過限制，請修正"),"","保障年期：") -> 保障年期： | D26: =IF(OR(O7>O5,D24="",M24="保額超過限制，請修正"),"","保險年齡屆滿八十九歲") -> 保險年齡屆滿八十九歲 | O26: =IF(OR(OP!$C$24=1,$A$2=1),"",IF(OP!$C$46>0,"折扣後","")&OP!$C$32&"首期保費：") -> 折扣後年繳首期保費： | R26: =IF(OR($A$2=1,OP!$C$24=1),"",OP!$C$48) -> 34650
O28: =IF(OR(OP!$C$24=1,A2=1),"",IF(OP!$C$47>0,"折扣後","")&OP!$C$32&"續期保費：") -> 折扣後年繳續期保費： | R28: =IF(OR($A$2=1,OP!$C$24=1),"",OP!$C$49) -> 34650
B29: ※本契約條款樣張須於訂立契約前提供要保人至少三日審閱期間。 | R29: =OP!D47
B33: =OP!C54 -> V1.1-1150409 | P33: 試算日： | Q33: =TEXT(YEAR(OP!$C$3)-1911,"000")&TEXT(MONTH(OP!$C$3),"00")&TEXT(DAY(OP!$C$3),"00") -> 1150805

Sheet 列印頁
A2: =OP!$D$53 | B2: =輸入頁!B2 -> 富邦人壽真馨相守防癌定期健康保險建議書
B4: 被保險人： | D4: =OP!$C$73 -> 客戶 | I4: 保險年齡： | L4: =OP!$D$5 -> 39 | N4: 性別： | P4: =輸入頁!K5 -> 女 | Q4: =OP!$D$94 -> 本保單計價幣別：新臺幣
B5: 保險種類 | M5: 險種代碼 | O5: 保額 | R5: =OP!$C$32&"應繳保費/元" -> 年繳應繳保費/元
A6: 1 | B6: =OP!$D$93 -> 富邦人壽真馨相守防癌定期健康保險(繳費20年) | M6: =IF($A$2=1,"",OP!$C$22) -> CLX | O6: =IF($A$2=1,"",TEXT(OP!$C$28,IF(OP!$E$28=0,"#,##0 ","#,##0.0 "))&"萬") -> 100 萬 | R6: =IF($A$2=1,"",OP!C35) -> 35000
B7: =OP!$D$91 -> 本保件符合保費折扣條件：繳費方式 1.0%折扣
B8: =OP!$D$92 -> 年繳總保費 35,000元，首期折扣後保費 34,650 元 ，續期折扣後保費 34,650 元
B11: =IF($A$2=1,"",OP!$C$22&"第二保單年度起之續期健康管理保險費折扣") -> CLX第二保單年度起之續期健康管理保險費折扣
B13: =IF($A$2=1,"",OP!$L$43) -> 健康管理保險費折扣項目 | H13: =IF($A$2=1,"",OP!$M$43) -> CLX折扣率 | M13: =IF($A$2=1,"",OP!$N$43) -> CLX續年度折扣後實繳保費(含續期繳費方式折扣1.0%)
B14: =IF($A$2=1,"",OP!$L$44) -> 健康檢查 | H14: =IF($A$2=1,"",OP!$M$44) -> 0.01 | M14: =IF($A$2=1,"",TEXT(OP!$N44,"#,### 元")) -> 34,300 元
B15: ‧上表健康管理折扣後實繳保費，繳費期內如不符折扣條件，上表將不適用，詳細內容以投保當時保單條款規定為準。
B17: 投保利益表
U18: =IF(OP!$C$105="停售","本商品已停售","")
B20: 給付內容 | D20: 保單 年度 | E20: 給付金額 | H20: 說明
B21: 首次罹患癌症(初期)或癌症(輕度)保險金 | D21: 1 | E21: =IF(OR($A$2=1),"",TEXT(OP!$C$31*1.06,"#,##0")&"元") -> 37,100元 | H21: ‧本契約有效期間內，「首次罹患癌症（初期）或癌症（輕度）保險金」以給付一次為限。同時或先後罹患癌症（初期）及癌症（輕度）者亦同。 ‧被保險人已先符合或同時符合「首次罹患癌症（重度）保險金」給付條件者，本公司不負本條保險金給付之責。
D22: 2~ | E22: =IF(OR($A$2=1),"",TEXT(OP!$C$28*10000*0.1,"#,##0")&"元") -> 100,000元
B23: 首次罹患癌症(重度)保險金 | D23: 1 | E23: =IF(OR($A$2=1),"",TEXT(OP!$C$31*1.06,"#,##0")&"元") -> 37,100元 | H23: ‧被保險人如已申領「首次罹患癌症（初期）或癌症（輕度）保險金」者，則改按左列計算之給付金額扣除「首次罹患癌症（初期）或癌症（輕度）保險金」後之餘額，給付「首次罹患癌症（重度）保險金」。 ‧本契約有效期間內，「首次罹患癌症（重度）保險金」以給付一次為限。
D24: 2~ | E24: =IF(OR($A$2=1),"",TEXT(OP!$C$28*10000,"#,##0")&"元") -> 1,000,000元
B25: 首次罹患特定癌症(重度)保險金 | D25: 2 | E25: =IF(OR($A$2=1),"",TEXT(OP!$C$28*10000*0.1,"#,##0")&"元") -> 100,000元 | H25: ‧本契約第二保單年度之有效期間內，符合「首次罹患特定癌症（重度）保險金」給付條件，且該項癌症（重度）亦同時符合保單條款約定之特定癌症（重度）者，依首次診斷確定日之保單年度，給付「首次罹患特定癌症（重度）保險金」。 ‧本契約有效期間內，「首次罹患特定癌症(重度)保險金」以給付一次為限。
D26: 3 | E26: =IF(OR($A$2=1),"",TEXT(OP!$C$28*10000*0.2,"#,##0")&"元") -> 200,000元
D27: 4 | E27: =IF(OR($A$2=1),"",TEXT(OP!$C$28*10000*0.3,"#,##0")&"元") -> 300,000元
D28: 5 | E28: =IF(OR($A$2=1),"",TEXT(OP!$C$28*10000*0.4,"#,##0")&"元") -> 400,000元
D29: 6~ | E29: =IF(OR($A$2=1),"",TEXT(OP!$C$28*10000*0.5,"#,##0")&"元") -> 500,000元
B30: 特定傷病 保險金 | D30: 2~ | E30: =IF(OR($A$2=1),"",TEXT(OP!$C$28*10000*0.1,"#,##0")&"元") -> 100,000元 | H30: ‧被保險人於本契約第二保單年度起之有效期間內，不論同時或先後罹患二項特定傷病，本公司僅對其中一項特定傷病負給付「特定傷病保險金」之責任。若係同項特定傷病發生二次（含）以上者，本公司僅對其中一次特定傷病負給付「特定傷病保險金」之責任。
B32: 特定手術 保險金 | D32: =IF(OR($A$2=1),"",TEXT(OP!$C$28*10000*0.02,"#,##0")&"元") -> 20,000元 | H32: ‧被保險人於本契約有效期間內，不論同時或先後接受二項（含）以上特定手術項目，本公司僅對其中一項特定手術項目負給付「特定手術保險金」之責任。若係同項特定手術項目發生二次（含）以上者，本公司僅對其中一次特定手術項目負給付「特定手術保險金」之責任。
B34: 豁免保險費 | D34: ‧本契約符合下列情形之一者，本公司豁免自診斷確定日後本契約(不含附約)續期應繳之各期保險費，本契約繼續有效： 一、被保險人於等待期間屆滿後或復效日起之本契約有效且繳費期間內，始經病理檢驗確定符合保單條款約定之首 次罹患癌症(重度)，並經醫院醫師診斷確定者。 二、被保險人於本契約有效且繳費期間內遭受保單條款約定之意外傷害事故，自意外傷害事故發生之日起一百八十 日以內致成保單條款附表所列一至六級失能程度之一，並經醫院醫師診斷確定者。但超過一百八十日致成一至 六級失能程度之一者，受益人若能證明被保險人之失能與該意外傷害事故具有因果關係者，不在此限。被保險 人因本次意外傷害事故所致之失能如合併以前(不含本契約訂立前)的失能，符合保單條款附表所列一至六級失 能程度之一者，亦同。 ‧前項情形，不論被保險人同時或先後致成幾項豁免保險費事故，本公司僅就一項豁免保險費事故負豁免保險費之責。經本公司同意豁免保險費後，非經被保險人同意，要保人不得終止本契約。
B36: 滿期保險金 | D36: =IF($A$2=1,"",TEXT(ROUND(VLOOKUP(OP!$C$55,EXP,OP!$C$57+1,0)*OP!$C$28,0),"#,###,##0")&" 元") -> 742,000 元 | H36: ‧被保險人於本契約有效期間內且在保險年齡屆滿八十九歲仍生存者，本公司按當年度保險金額給付滿期保險金後，本契約效力即行終止。 ‧給付時需扣除被保險人已依保單條款約定所應申領之各項保險金累計總額。
B38: 身故保險金或喪葬費用 保險金 | D38: 詳下表身故保障 | H38: ‧被保險人於本契約有效期間內身故者，本公司按當年度保險金額給付身故保險金後，本契約效力即行終止。 ‧給付時需扣除被保險人已依保單條款約定所應申領之各項保險金累計總額。
B40: ‧上表所列各項保險實際給付金額以保單條款規定為準。
A44: 1 | B44: =OP!$D$107 -> 本建議書僅供參考，詳細商品內容及其變更，應以投保當時保單條款內容及本公司核保、保全作業規定為準
D45: =OP!$D$106 -> ※本契約條款樣張須於訂立契約前提供要保人至少三日審閱期間 | U45: =OP!$D$105 -> V1.1-1150409 試算日：1150805
U46: =IF(OP!$C$105="停售","本商品已停售","")
U47: 單位：元
B48: 保單 年度 | C48: 保險 年齡 | D48: 年度 實繳保費 | F48: 累計 實繳保費 | I48: 身故保障 | L48: 保單 年度 | M48: 保險 年齡 | N48: 年度 實繳保費 | P48: 累計 實繳保費 | S48: 身故保障
B49: 1 | C49: =IF($A$2=1,"",OP!$D$5) -> 39 | D49: =IF(OR($A$2=1,$B49>OP!$C$24),"",OP!$C$51) -> 34650 | F49: =IF(OR($A$2=1,$B49=""),"",N($D49)) -> 34650 | I49: =IF(OR($A$2=1,$B49=""),"",VLOOKUP(OP!$C$55,DIE,$B49+1,0)*OP!$C$28) -> 37100 | L49: =IF(OR(C106>=OP!F57,C106=""),"",B106+1) | M49: =IF(L49="","",C106+1) | N49: =IF(OR($A$2=1,$L49>OP!$C$24),"",OP!$C$52) | P49: =IF(OR($A$2=1,$L49=""),"",N($N49)+N($F106)) | S49: =IF(OR($A$2=1,$L49=""),"",VLOOKUP(OP!$C$55,DIE,$L49+1,0)*OP!$C$28)
B50: =IF(OR(C49>=OP!F$57,C49=""),"",IF(C49+1>OP!$F$57,OP!$F$57+1-$C$49,B49+1)) -> 2 | C50: =IF(OR($A$2=1,MAX($C$49:C49)>=OP!$F$57),"",C49+(B50-B49)) -> 40 | D50: =IF(OR($A$2=1,$B50>OP!$C$24),"",OP!$C$52) -> 34650 | F50: =IF(OR($A$2=1,$B50=""),"",N($F49)+N($D50)) -> 69300 | I50: =IF(OR($A$2=1,$B50=""),"",VLOOKUP(OP!$C$55,DIE,$B50+1,0)*OP!$C$28) -> 74200 | L50: =IF(OR(M49>=OP!F57,L49=""),"",L49+1) | M50: =IF(L50="","",M49+1) | N50: =IF(OR($A$2=1,$L50>OP!$C$24),"",OP!$C$52) | P50: =IF(OR($A$2=1,$L50=""),"",N($N49)+N($P49)) | S50: =IF(OR($A$2=1,$L50=""),"",VLOOKUP(OP!$C$55,DIE,$L50+1,0)*OP!$C$28)
B51: =IF(OR(C50>=OP!F$57,C50=""),"",IF(C50+1>OP!$F$57,OP!$F$57+1-$C$49,B50+1)) -> 3 | C51: =IF(OR($A$2=1,MAX($C$49:C50)>=OP!$F$57),"",C50+(B51-B50)) -> 41 | D51: =IF(OR($A$2=1,$B51>OP!$C$24),"",OP!$C$52) -> 34650 | F51: =IF(OR($A$2=1,$B51=""),"",N($F50)+N($D51)) -> 103950 | I51: =IF(OR($A$2=1,$B51=""),"",VLOOKUP(OP!$C$55,DIE,$B51+1,0)*OP!$C$28) -> 111300 | L51: =IF(OR(M50>=OP!F57,L50=""),"",L50+1) | M51: =IF(L51="","",M50+1) | N51: =IF(OR($A$2=1,$L51>OP!$C$24),"",OP!$C$52) | P51: =IF(OR($A$2=1,$L51=""),"",N($N50)+N($P50)) | S51: =IF(OR($A$2=1,$L51=""),"",VLOOKUP(OP!$C$55,DIE,$L51+1,0)*OP!$C$28)
B52: =IF(OR(C51>=OP!F$57,C51=""),"",IF(C51+1>OP!$F$57,OP!$F$57+1-$C$49,B51+1)) -> 4 | C52: =IF(OR($A$2=1,MAX($C$49:C51)>=OP!$F$57),"",C51+(B52-B51)) -> 42 | D52: =IF(OR($A$2=1,$B52>OP!$C$24),"",OP!$C$52) -> 34650 | F52: =IF(OR($A$2=1,$B52=""),"",N($F51)+N($D52)) -> 138600 | I52: =IF(OR($A$2=1,$B52=""),"",VLOOKUP(OP!$C$55,DIE,$B52+1,0)*OP!$C$28) -> 148400 | L52: =IF(OR(M51>=OP!F57,L51=""),"",L51+1) | M52: =IF(L52="","",M51+1) | N52: =IF(OR($A$2=1,$L52>OP!$C$24),"",OP!$C$52) | P52: =IF(OR($A$2=1,$L52=""),"",N($N51)+N($P51)) | S52: =IF(OR($A$2=1,$L52=""),"",VLOOKUP(OP!$C$55,DIE,$L52+1,0)*OP!$C$28)
B53: =IF(OR(C52>=OP!F$57,C52=""),"",IF(C52+1>OP!$F$57,OP!$F$57+1-$C$49,B52+1)) -> 5 | C53: =IF(OR($A$2=1,MAX($C$49:C52)>=OP!$F$57),"",C52+(B53-B52)) -> 43 | D53: =IF(OR($A$2=1,$B53>OP!$C$24),"",OP!$C$52) -> 34650 | F53: =IF(OR($A$2=1,$B53=""),"",N($F52)+N($D53)) -> 173250 | I53: =IF(OR($A$2=1,$B53=""),"",VLOOKUP(OP!$C$55,DIE,$B53+1,0)*OP!$C$28) -> 185500 | L53: =IF(OR(M52>=OP!F57,L52=""),"",L52+1) | M53: =IF(L53="","",M52+1) | N53: =IF(OR($A$2=1,$L53>OP!$C$24),"",OP!$C$52) | P53: =IF(OR($A$2=1,$L53=""),"",N($N52)+N($P52)) | S53: =IF(OR($A$2=1,$L53=""),"",VLOOKUP(OP!$C$55,DIE,$L53+1,0)*OP!$C$28)
B54: =IF(OR(C53>=OP!F$57,C53=""),"",IF(C53+1>OP!$F$57,OP!$F$57+1-$C$49,B53+1)) -> 6 | C54: =IF(OR($A$2=1,MAX($C$49:C53)>=OP!$F$57),"",C53+(B54-B53)) -> 44 | D54: =IF(OR($A$2=1,$B54>OP!$C$24),"",OP!$C$52) -> 34650 | F54: =IF(OR($A$2=1,$B54=""),"",N($F53)+N($D54)) -> 207900 | I54: =IF(OR($A$2=1,$B54=""),"",VLOOKUP(OP!$C$55,DIE,$B54+1,0)*OP!$C$28) -> 222600 | L54: =IF(OR(M53>=OP!F57,L53=""),"",L53+1) | M54: =IF(L54="","",M53+1) | N54: =IF(OR($A$2=1,$L54>OP!$C$24),"",OP!$C$52) | P54: =IF(OR($A$2=1,$L54=""),"",N($N53)+N($P53)) | S54: =IF(OR($A$2=1,$L54=""),"",VLOOKUP(OP!$C$55,DIE,$L54+1,0)*OP!$C$28)
B55: =IF(OR(C54>=OP!F$57,C54=""),"",IF(C54+1>OP!$F$57,OP!$F$57+1-$C$49,B54+1)) -> 7 | C55: =IF(OR($A$2=1,MAX($C$49:C54)>=OP!$F$57),"",C54+(B55-B54)) -> 45 | D55: =IF(OR($A$2=1,$B55>OP!$C$24),"",OP!$C$52) -> 34650 | F55: =IF(OR($A$2=1,$B55=""),"",N($F54)+N($D55)) -> 242550 | I55: =IF(OR($A$2=1,$B55=""),"",VLOOKUP(OP!$C$55,DIE,$B55+1,0)*OP!$C$28) -> 259700 | L55: =IF(OR(M54>=OP!F57,L54=""),"",L54+1) | M55: =IF(L55="","",M54+1) | N55: =IF(OR($A$2=1,$L55>OP!$C$24),"",OP!$C$52) | P55: =IF(OR($A$2=1,$L55=""),"",N($N54)+N($P54)) | S55: =IF(OR($A$2=1,$L55=""),"",VLOOKUP(OP!$C$55,DIE,$L55+1,0)*OP!$C$28)
B56: =IF(OR(C55>=OP!F$57,C55=""),"",IF(C55+1>OP!$F$57,OP!$F$57+1-$C$49,B55+1)) -> 8 | C56: =IF(OR($A$2=1,MAX($C$49:C55)>=OP!$F$57),"",C55+(B56-B55)) -> 46 | D56: =IF(OR($A$2=1,$B56>OP!$C$24),"",OP!$C$52) -> 34650 | F56: =IF(OR($A$2=1,$B56=""),"",N($F55)+N($D56)) -> 277200 | I56: =IF(OR($A$2=1,$B56=""),"",VLOOKUP(OP!$C$55,DIE,$B56+1,0)*OP!$C$28) -> 296800 | L56: =IF(OR(M55>=OP!F57,L55=""),"",L55+1) | M56: =IF(L56="","",M55+1) | N56: =IF(OR($A$2=1,$L56>OP!$C$24),"",OP!$C$52) | P56: =IF(OR($A$2=1,$L56=""),"",N($N55)+N($P55)) | S56: =IF(OR($A$2=1,$L56=""),"",VLOOKUP(OP!$C$55,DIE,$L56+1,0)*OP!$C$28)
B57: =IF(OR(C56>=OP!F$57,C56=""),"",IF(C56+1>OP!$F$57,OP!$F$57+1-$C$49,B56+1)) -> 9 | C57: =IF(OR($A$2=1,MAX($C$49:C56)>=OP!$F$57),"",C56+(B57-B56)) -> 47 | D57: =IF(OR($A$2=1,$B57>OP!$C$24),"",OP!$C$52) -> 34650 | F57: =IF(OR($A$2=1,$B57=""),"",N($F56)+N($D57)) -> 311850 | I57: =IF(OR($A$2=1,$B57=""),"",VLOOKUP(OP!$C$55,DIE,$B57+1,0)*OP!$C$28) -> 333900 | L57: =IF(OR(M56>=OP!F57,L56=""),"",L56+1) | M57: =IF(L57="","",M56+1) | N57: =IF(OR($A$2=1,$L57>OP!$C$24),"",OP!$C$52) | P57: =IF(OR($A$2=1,$L57=""),"",N($N56)+N($P56)) | S57: =IF(OR($A$2=1,$L57=""),"",VLOOKUP(OP!$C$55,DIE,$L57+1,0)*OP!$C$28)
B58: =IF(OR(C57>=OP!F$57,C57=""),"",IF(C57+1>OP!$F$57,OP!$F$57+1-$C$49,B57+1)) -> 10 | C58: =IF(OR($A$2=1,MAX($C$49:C57)>=OP!$F$57),"",C57+(B58-B57)) -> 48 | D58: =IF(OR($A$2=1,$B58>OP!$C$24),"",OP!$C$52) -> 34650 | F58: =IF(OR($A$2=1,$B58=""),"",N($F57)+N($D58)) -> 346500 | I58: =IF(OR($A$2=1,$B58=""),"",VLOOKUP(OP!$C$55,DIE,$B58+1,0)*OP!$C$28) -> 371000 | L58: =IF(OR(M57>=OP!F57,L57=""),"",L57+1) | M58: =IF(L58="","",M57+1) | N58: =IF(OR($A$2=1,$L58>OP!$C$24),"",OP!$C$52) | P58: =IF(OR($A$2=1,$L58=""),"",N($N57)+N($P57)) | S58: =IF(OR($A$2=1,$L58=""),"",VLOOKUP(OP!$C$55,DIE,$L58+1,0)*OP!$C$28)
B59: =IF(OR(C58>=OP!F$57,C58=""),"",IF(C58+1>OP!$F$57,OP!$F$57+1-$C$49,B58+1)) -> 11 | C59: =IF(OR($A$2=1,MAX($C$49:C58)>=OP!$F$57),"",C58+(B59-B58)) -> 49 | D59: =IF(OR($A$2=1,$B59>OP!$C$24),"",OP!$C$52) -> 34650 | F59: =IF(OR($A$2=1,$B59=""),"",N($F58)+N($D59)) -> 381150 | I59: =IF(OR($A$2=1,$B59=""),"",VLOOKUP(OP!$C$55,DIE,$B59+1,0)*OP!$C$28) -> 408100 | L59: =IF(OR(M58>=OP!F57,L58=""),"",L58+1) | M59: =IF(L59="","",M58+1) | N59: =IF(OR($A$2=1,$L59>OP!$C$24),"",OP!$C$52) | P59: =IF(OR($A$2=1,$L59=""),"",N($N58)+N($P58)) | S59: =IF(OR($A$2=1,$L59=""),"",VLOOKUP(OP!$C$55,DIE,$L59+1,0)*OP!$C$28)
B60: =IF(OR(C59>=OP!F$57,C59=""),"",IF(C59+1>OP!$F$57,OP!$F$57+1-$C$49,B59+1)) -> 12 | C60: =IF(OR($A$2=1,MAX($C$49:C59)>=OP!$F$57),"",C59+(B60-B59)) -> 50 | D60: =IF(OR($A$2=1,$B60>OP!$C$24),"",OP!$C$52) -> 34650 | F60: =IF(OR($A$2=1,$B60=""),"",N($F59)+N($D60)) -> 415800 | I60: =IF(OR($A$2=1,$B60=""),"",VLOOKUP(OP!$C$55,DIE,$B60+1,0)*OP!$C$28) -> 445200 | L60: =IF(OR(M59>=OP!F57,L59=""),"",L59+1) | M60: =IF(L60="","",M59+1) | N60: =IF(OR($A$2=1,$L60>OP!$C$24),"",OP!$C$52) | P60: =IF(OR($A$2=1,$L60=""),"",N($N59)+N($P59)) | S60: =IF(OR($A$2=1,$L60=""),"",VLOOKUP(OP!$C$55,DIE,$L60+1,0)*OP!$C$28)
B61: =IF(OR(C60>=OP!F$57,C60=""),"",IF(C60+1>OP!$F$57,OP!$F$57+1-$C$49,B60+1)) -> 13 | C61: =IF(OR($A$2=1,MAX($C$49:C60)>=OP!$F$57),"",C60+(B61-B60)) -> 51 | D61: =IF(OR($A$2=1,$B61>OP!$C$24),"",OP!$C$52) -> 34650 | F61: =IF(OR($A$2=1,$B61=""),"",N($F60)+N($D61)) -> 450450 | I61: =IF(OR($A$2=1,$B61=""),"",VLOOKUP(OP!$C$55,DIE,$B61+1,0)*OP!$C$28) -> 482300 | L61: =IF(OR(M60>=OP!F57,L60=""),"",L60+1) | M61: =IF(L61="","",M60+1) | N61: =IF(OR($A$2=1,$L61>OP!$C$24),"",OP!$C$52) | P61: =IF(OR($A$2=1,$L61=""),"",N($N60)+N($P60)) | S61: =IF(OR($A$2=1,$L61=""),"",VLOOKUP(OP!$C$55,DIE,$L61+1,0)*OP!$C$28)
B62: =IF(OR(C61>=OP!F$57,C61=""),"",IF(C61+1>OP!$F$57,OP!$F$57+1-$C$49,B61+1)) -> 14 | C62: =IF(OR($A$2=1,MAX($C$49:C61)>=OP!$F$57),"",C61+(B62-B61)) -> 52 | D62: =IF(OR($A$2=1,$B62>OP!$C$24),"",OP!$C$52) -> 34650 | F62: =IF(OR($A$2=1,$B62=""),"",N($F61)+N($D62)) -> 485100 | I62: =IF(OR($A$2=1,$B62=""),"",VLOOKUP(OP!$C$55,DIE,$B62+1,0)*OP!$C$28) -> 519400 | L62: =IF(OR(M61>=OP!F57,L61=""),"",L61+1) | M62: =IF(L62="","",M61+1) | N62: =IF(OR($A$2=1,$L62>OP!$C$24),"",OP!$C$52) | P62: =IF(OR($A$2=1,$L62=""),"",N($N61)+N($P61)) | S62: =IF(OR($A$2=1,$L62=""),"",VLOOKUP(OP!$C$55,DIE,$L62+1,0)*OP!$C$28)
B63: =IF(OR(C62>=OP!F$57,C62=""),"",IF(C62+1>OP!$F$57,OP!$F$57+1-$C$49,B62+1)) -> 15 | C63: =IF(OR($A$2=1,MAX($C$49:C62)>=OP!$F$57),"",C62+(B63-B62)) -> 53 | D63: =IF(OR($A$2=1,$B63>OP!$C$24),"",OP!$C$52) -> 34650 | F63: =IF(OR($A$2=1,$B63=""),"",N($F62)+N($D63)) -> 519750 | I63: =IF(OR($A$2=1,$B63=""),"",VLOOKUP(OP!$C$55,DIE,$B63+1,0)*OP!$C$28) -> 556500 | L63: =IF(OR(M62>=OP!F57,L62=""),"",L62+1) | M63: =IF(L63="","",M62+1) | N63: =IF(OR($A$2=1,$L63>OP!$C$24),"",OP!$C$52) | P63: =IF(OR($A$2=1,$L63=""),"",N($N62)+N($P62)) | S63: =IF(OR($A$2=1,$L63=""),"",VLOOKUP(OP!$C$55,DIE,$L63+1,0)*OP!$C$28)
B64: =IF(OR(C63>=OP!F$57,C63=""),"",IF(C63+1>OP!$F$57,OP!$F$57+1-$C$49,B63+1)) -> 16 | C64: =IF(OR($A$2=1,MAX($C$49:C63)>=OP!$F$57),"",C63+(B64-B63)) -> 54 | D64: =IF(OR($A$2=1,$B64>OP!$C$24),"",OP!$C$52) -> 34650 | F64: =IF(OR($A$2=1,$B64=""),"",N($F63)+N($D64)) -> 554400 | I64: =IF(OR($A$2=1,$B64=""),"",VLOOKUP(OP!$C$55,DIE,$B64+1,0)*OP!$C$28) -> 593600 | L64: =IF(OR(M63>=OP!F57,L63=""),"",L63+1) | M64: =IF(L64="","",M63+1) | N64: =IF(OR($A$2=1,$L64>OP!$C$24),"",OP!$C$52) | P64: =IF(OR($A$2=1,$L64=""),"",N($N63)+N($P63)) | S64: =IF(OR($A$2=1,$L64=""),"",VLOOKUP(OP!$C$55,DIE,$L64+1,0)*OP!$C$28)
B65: =IF(OR(C64>=OP!F$57,C64=""),"",IF(C64+1>OP!$F$57,OP!$F$57+1-$C$49,B64+1)) -> 17 | C65: =IF(OR($A$2=1,MAX($C$49:C64)>=OP!$F$57),"",C64+(B65-B64)) -> 55 | D65: =IF(OR($A$2=1,$B65>OP!$C$24),"",OP!$C$52) -> 34650 | F65: =IF(OR($A$2=1,$B65=""),"",N($F64)+N($D65)) -> 589050 | I65: =IF(OR($A$2=1,$B65=""),"",VLOOKUP(OP!$C$55,DIE,$B65+1,0)*OP!$C$28) -> 630700 | L65: =IF(OR(M64>=OP!F57,L64=""),"",L64+1) | M65: =IF(L65="","",M64+1) | N65: =IF(OR($A$2=1,$L65>OP!$C$24),"",OP!$C$52) | P65: =IF(OR($A$2=1,$L65=""),"",N($N64)+N($P64)) | S65: =IF(OR($A$2=1,$L65=""),"",VLOOKUP(OP!$C$55,DIE,$L65+1,0)*OP!$C$28)
B66: =IF(OR(C65>=OP!F$57,C65=""),"",IF(C65+1>OP!$F$57,OP!$F$57+1-$C$49,B65+1)) -> 18 | C66: =IF(OR($A$2=1,MAX($C$49:C65)>=OP!$F$57),"",C65+(B66-B65)) -> 56 | D66: =IF(OR($A$2=1,$B66>OP!$C$24),"",OP!$C$52) -> 34650 | F66: =IF(OR($A$2=1,$B66=""),"",N($F65)+N($D66)) -> 623700 | I66: =IF(OR($A$2=1,$B66=""),"",VLOOKUP(OP!$C$55,DIE,$B66+1,0)*OP!$C$28) -> 667800 | L66: =IF(OR(M65>=OP!F57,L65=""),"",L65+1) | M66: =IF(L66="","",M65+1) | N66: =IF(OR($A$2=1,$L66>OP!$C$24),"",OP!$C$52) | P66: =IF(OR($A$2=1,$L66=""),"",N($N65)+N($P65)) | S66: =IF(OR($A$2=1,$L66=""),"",VLOOKUP(OP!$C$55,DIE,$L66+1,0)*OP!$C$28)
B67: =IF(OR(C66>=OP!F$57,C66=""),"",IF(C66+1>OP!$F$57,OP!$F$57+1-$C$49,B66+1)) -> 19 | C67: =IF(OR($A$2=1,MAX($C$49:C66)>=OP!$F$57),"",C66+(B67-B66)) -> 57 | D67: =IF(OR($A$2=1,$B67>OP!$C$24),"",OP!$C$52) -> 34650 | F67: =IF(OR($A$2=1,$B67=""),"",N($F66)+N($D67)) -> 658350 | I67: =IF(OR($A$2=1,$B67=""),"",VLOOKUP(OP!$C$55,DIE,$B67+1,0)*OP!$C$28) -> 704900 | L67: =IF(OR(M66=OP!F57,L66=""),"",L66+1) | M67: =IF(L67="","",M66+1) | N67: =IF(OR($A$2=1,$L67>OP!$C$24),"",OP!$C$52) | P67: =IF(OR($A$2=1,$L67=""),"",N($N66)+N($P66)) | S67: =IF(OR($A$2=1,$L67=""),"",VLOOKUP(OP!$C$55,DIE,$L67+1,0)*OP!$C$28)
B68: =IF(OR(C67>=OP!F$57,C67=""),"",IF(C67+1>OP!$F$57,OP!$F$57+1-$C$49,B67+1)) -> 20 | C68: =IF(OR($A$2=1,MAX($C$49:C67)>=OP!$F$57),"",C67+(B68-B67)) -> 58 | D68: =IF(OR($A$2=1,$B68>OP!$C$24),"",OP!$C$52) -> 34650 | F68: =IF(OR($A$2=1,$B68=""),"",N($F67)+N($D68)) -> 693000 | I68: =IF(OR($A$2=1,$B68=""),"",VLOOKUP(OP!$C$55,DIE,$B68+1,0)*OP!$C$28) -> 742000
B69: =IF(OR(C68>=OP!F$57,C68=""),"",IF(C68+1>OP!$F$57,OP!$F$57+1-$C$49,B68+1)) -> 21 | C69: =IF(OR($A$2=1,MAX($C$49:C68)>=OP!$F$57),"",C68+(B69-B68)) -> 59 | D69: =IF(OR($A$2=1,$B69>OP!$C$24),"",OP!$C$52) | F69: =IF(OR($A$2=1,$B69=""),"",N($F68)+N($D69)) -> 693000 | I69: =IF(OR($A$2=1,$B69=""),"",VLOOKUP(OP!$C$55,DIE,$B69+1,0)*OP!$C$28) -> 742000
B70: =IF(OR(C69>=OP!F$57,C69=""),"",IF(C69+1>OP!$F$57,OP!$F$57+1-$C$49,B69+1)) -> 22 | C70: =IF(OR($A$2=1,MAX($C$49:C69)>=OP!$F$57),"",C69+(B70-B69)) -> 60 | D70: =IF(OR($A$2=1,$B70>OP!$C$24),"",OP!$C$52) | F70: =IF(OR($A$2=1,$B70=""),"",N($F69)+N($D70)) -> 693000 | I70: =IF(OR($A$2=1,$B70=""),"",VLOOKUP(OP!$C$55,DIE,$B70+1,0)*OP!$C$28) -> 742000
B71: =IF(OR(C70>=OP!F$57,C70=""),"",IF(C70+1>OP!$F$57,OP!$F$57+1-$C$49,B70+1)) -> 23 | C71: =IF(OR($A$2=1,MAX($C$49:C70)>=OP!$F$57),"",C70+(B71-B70)) -> 61 | D71: =IF(OR($A$2=1,$B71>OP!$C$24),"",OP!$C$52) | F71: =IF(OR($A$2=1,$B71=""),"",N($F70)+N($D71)) -> 693000 | I71: =IF(OR($A$2=1,$B71=""),"",VLOOKUP(OP!$C$55,DIE,$B71+1,0)*OP!$C$28) -> 742000
B72: =IF(OR(C71>=OP!F$57,C71=""),"",IF(C71+1>OP!$F$57,OP!$F$57+1-$C$49,B71+1)) -> 24 | C72: =IF(OR($A$2=1,MAX($C$49:C71)>=OP!$F$57),"",C71+(B72-B71)) -> 62 | D72: =IF(OR($A$2=1,$B72>OP!$C$24),"",OP!$C$52) | F72: =IF(OR($A$2=1,$B72=""),"",N($F71)+N($D72)) -> 693000 | I72: =IF(OR($A$2=1,$B72=""),"",VLOOKUP(OP!$C$55,DIE,$B72+1,0)*OP!$C$28) -> 742000
B73: =IF(OR(C72>=OP!F$57,C72=""),"",IF(C72+1>OP!$F$57,OP!$F$57+1-$C$49,B72+1)) -> 25 | C73: =IF(OR($A$2=1,MAX($C$49:C72)>=OP!$F$57),"",C72+(B73-B72)) -> 63 | D73: =IF(OR($A$2=1,$B73>OP!$C$24),"",OP!$C$52) | F73: =IF(OR($A$2=1,$B73=""),"",N($F72)+N($D73)) -> 693000 | I73: =IF(OR($A$2=1,$B73=""),"",VLOOKUP(OP!$C$55,DIE,$B73+1,0)*OP!$C$28) -> 742000
B74: =IF(OR(C73>=OP!F$57,C73=""),"",IF(C73+1>OP!$F$57,OP!$F$57+1-$C$49,B73+1)) -> 26 | C74: =IF(OR($A$2=1,MAX($C$49:C73)>=OP!$F$57),"",C73+(B74-B73)) -> 64 | D74: =IF(OR($A$2=1,$B74>OP!$C$24),"",OP!$C$52) | F74: =IF(OR($A$2=1,$B74=""),"",N($F73)+N($D74)) -> 693000 | I74: =IF(OR($A$2=1,$B74=""),"",VLOOKUP(OP!$C$55,DIE,$B74+1,0)*OP!$C$28) -> 742000
B75: =IF(OR(C74>=OP!F$57,C74=""),"",IF(C74+1>OP!$F$57,OP!$F$57+1-$C$49,B74+1)) -> 27 | C75: =IF(OR($A$2=1,MAX($C$49:C74)>=OP!$F$57),"",C74+(B75-B74)) -> 65 | D75: =IF(OR($A$2=1,$B75>OP!$C$24),"",OP!$C$52) | F75: =IF(OR($A$2=1,$B75=""),"",N($F74)+N($D75)) -> 693000 | I75: =IF(OR($A$2=1,$B75=""),"",VLOOKUP(OP!$C$55,DIE,$B75+1,0)*OP!$C$28) -> 742000
B76: =IF(OR(C75>=OP!F$57,C75=""),"",IF(C75+1>OP!$F$57,OP!$F$57+1-$C$49,B75+1)) -> 28 | C76: =IF(OR($A$2=1,MAX($C$49:C75)>=OP!$F$57),"",C75+(B76-B75)) -> 66 | D76: =IF(OR($A$2=1,$B76>OP!$C$24),"",OP!$C$52) | F76: =IF(OR($A$2=1,$B76=""),"",N($F75)+N($D76)) -> 693000 | I76: =IF(OR($A$2=1,$B76=""),"",VLOOKUP(OP!$C$55,DIE,$B76+1,0)*OP!$C$28) -> 742000
B77: =IF(OR(C76>=OP!F$57,C76=""),"",IF(C76+1>OP!$F$57,OP!$F$57+1-$C$49,B76+1)) -> 29 | C77: =IF(OR($A$2=1,MAX($C$49:C76)>=OP!$F$57),"",C76+(B77-B76)) -> 67 | D77: =IF(OR($A$2=1,$B77>OP!$C$24),"",OP!$C$52) | F77: =IF(OR($A$2=1,$B77=""),"",N($F76)+N($D77)) -> 693000 | I77: =IF(OR($A$2=1,$B77=""),"",VLOOKUP(OP!$C$55,DIE,$B77+1,0)*OP!$C$28) -> 742000
B78: =IF(OR(C77>=OP!F$57,C77=""),"",IF(C77+1>OP!$F$57,OP!$F$57+1-$C$49,B77+1)) -> 30 | C78: =IF(OR($A$2=1,MAX($C$49:C77)>=OP!$F$57),"",C77+(B78-B77)) -> 68 | D78: =IF(OR($A$2=1,$B78>OP!$C$24),"",OP!$C$52) | F78: =IF(OR($A$2=1,$B78=""),"",N($F77)+N($D78)) -> 693000 | I78: =IF(OR($A$2=1,$B78=""),"",VLOOKUP(OP!$C$55,DIE,$B78+1,0)*OP!$C$28) -> 742000
B79: =IF(OR(C78>=OP!F$57,C78=""),"",IF(C78+1>OP!$F$57,OP!$F$57+1-$C$49,B78+1)) -> 31 | C79: =IF(OR($A$2=1,MAX($C$49:C78)>=OP!$F$57),"",C78+(B79-B78)) -> 69 | D79: =IF(OR($A$2=1,$B79>OP!$C$24),"",OP!$C$52) | F79: =IF(OR($A$2=1,$B79=""),"",N($F78)+N($D79)) -> 693000 | I79: =IF(OR($A$2=1,$B79=""),"",VLOOKUP(OP!$C$55,DIE,$B79+1,0)*OP!$C$28) -> 742000
... B106: =IF(OR(C105>=OP!F$57,C105=""),"",IF(C105+1>OP!$F$57,OP!$F$57+1-$C$49,B105+1)) | C106: =IF(OR($A$2=1,MAX($C$49:C105)>=OP!$F$57),"",C105+(B106-B105)) | D106: =IF(OR($A$2=1,$B106>OP!$C$24),"",OP!$C$52) | F106: =IF(OR($A$2=1,$B106=""),"",N($F105)+N($D106)) | I106: =IF(OR($A$2=1,$B106=""),"",VLOOKUP(OP!$C$55,DIE,$B106+1,0)*OP!$C$28)
B107: ‧上表年度/累計實繳保費已扣除繳費方式折扣，繳費期內如不符繳費方式折扣條件，上表將不適用。
B108: ‧上表身故保障數值為假設被保險人於保險期間均未提出任何保險給付之數值，給付時需扣除被保險人已依保單條款約
B109: 定所應申領之各項保險金累計總額，實際保障數值依保單條款約定辦理。
A111: 1 | B111: =OP!$D$107 -> 本建議書僅供參考，詳細商品內容及其變更，應以投保當時保單條款內容及本公司核保、保全作業規定為準
D112: =OP!$D$106 -> ※本契約條款樣張須於訂立契約前提供要保人至少三日審閱期間 | U112: =OP!$D$105 -> V1.1-1150409 試算日：1150805
U113: =IF(OP!$C$105="停售","本商品已停售","")
B114: 商品摘要
A115: 1 | B115: =OP!$C$23&"("&OP!$C$22&")" -> 富邦人壽真馨相守防癌定期健康保險(CLX)
B116: 給付項目：首次罹患癌症(初期)或癌症(輕度)保險金、首次罹患癌症(重度)保險金、首次罹患特定
B117: 癌症(重度)保險金、特定手術保險金、特定傷病保險金、身故保險金或喪葬費用保險金、
B118: 滿期保險金、豁免保險費
B119: 免付費申訴專線：0809-000-550
B120: ‧本保險為不分紅保險單，不參加紅利分配，並無紅利給付項目。
A121: 2 | B121: ‧本保險因費率計算已考慮脫退率，故本保險無解約金
A122: 3 | B122: ‧本商品之身故保險給付，有可能於特定條件下小於年繳保險費總和，請慎選符合需求之保險商品
A123: 4 | B123: ‧等待期間：係指自本契約生效日起持續有效九十日之期間。
A124: 5 | B124: ‧特定傷病：係指被保險人經醫院醫師診斷確定符合下列各目定義之特定傷病之一：
A125: 6 | B125: （一）嚴重全身性紅斑性狼瘡腎病變、（二）嚴重類風濕性關節炎
A126: 7 | B126: ‧疾病：係指被保險人自本契約生效日起持續有效三十日以後或復效日起所發生之疾病。
B127: ‧本商品各項保險金給付詳細內容及其限制請詳閱保單條款內容說明。
B128: ‧健康管理保險費折扣：本契約有效之繳費期間內，被保險人於指定期間內，接受經中央衛生主管機關核准登記並領有開
B129: 業執照之醫療機構或醫事檢驗所之合格醫事人員所作之健康檢查，並將包含被保險人身高、體重、血壓、血糖、血脂肪
B130: （包括膽固醇及三酸甘油脂）等數值之健康檢查報告送達本公司者，本公司將提供本契約次一保單年度續期保險費 1％
B131: 之健康管理保險費折扣（以下簡稱健康折扣）。於同一指定期間內，被保險人無論接受幾次健康檢查，健康折扣均以一
B132: 次計算。
B133: ‧被保險人如未於第一項約定之期限內提供健康檢查報告予本公司者，本契約次一保單年度即不提供健康折扣。
B134: ‧保險給付的限制：本契約被保險人於等待期間屆滿前或停效期間內， 已為病理檢驗確定被保險人罹患保單條款約定之
B135: 癌症，本公司將不負「首次罹患癌症（初期）或癌症（輕度）」、「首次罹患癌症（重度）」、「首次罹患特定癌症（
B136: 重度）」各項保險金給付與保單條款約定豁免保險費之責。
B152: 注意事項：
B153: ‧消費者投保前應審慎瞭解本商品之承保範圍、除外責任、不保事項及商品風險，相關內容均詳列於保單條款及相關銷售
... B169: ‧富邦人壽保險股份有限公司 / 地址：台北市信義區松高路77號8樓 / 電話：(02)8771-6699
B170: ="‧消費者於購買前，應詳閱各種銷售文件內容，本商品之預定附加費用率，"&OP!$D$101&"；如要詳細了解其他" -> ‧消費者於購買前，應詳閱各種銷售文件內容，本商品之預定附加費用率，最高33.61%，最低20.62%；如要詳細了解其他
B171: 相關資訊，請洽本公司業務員、服務據點(免費服務及申訴電話：0809-000-550)或網站(www.fubon.com/life/)，
B172: 以保障您的權益。
...
