Workbook
Name CV: PDATA!$EI$282:$IP$548
Name DIE: PDATA!$V$552:$EC$828
Name En_BFM: OP!$W$4:$W$5
Name En_PayMF: OP!$U$3:$U$6
Name En_PayMR: OP!$V$3:$V$6
Name En_PayT: OP!$T$5:$T$8
Name En_Sex: OP!$S$3:$S$4
Name EXP: PDATA!$EI$552:$IP$828
Name GP: PDATA!$J:$K
Name HL_1: PDATA!$V$1164:$EC$1429
Name HL_2: PDATA!$EI$1164:$IP$1429
Name PA: PDATA!$V$2:$EC$278
Name PDN1_1: OP!$C$23
Name PDSN1: OP!$C$22
Name PDSN1_1: OP!$C$22
Name PI: OP!$AK$4:$AL$90
Name PV: PDATA!$EI$988:$IP$1150
Name PV0: PDATA!$V$988:$ED$1150
Name PVal: PDATA!$O:$P
Name PYO: PY!$D$4
Name PYR: PY!$C$11
Name PYY: PY!$C$4
Name SRV: PDATA!$EI$2:$IP$278
Name TOV: 總表!$B$3:$AI$114
Name 關係: OP!$B$182:$B$186

Sheet PDATA
A1: GP | B1: 1051130 | J1: =B1&TEXT(F1,"00")&TEXT(H1,"00") -> 10511300000 | O1: =M1&TEXT(N1,"00") -> 00 | R1: PA | V1: =S1&TEXT(T1,"00")&TEXT(U1,"00") -> 0000 | EE1: SRV | EI1: =EF1&TEXT(EG1,"00")&TEXT(EH1,"00") -> 0000
A2: 版次 | B2: 商品代號 | C2: 職業等級 | D2: 年期 | E2: 保額代碼 | F2: 性別 | G2: 投保金額 | H2: 年齡 | I2: 繳費年度 | J2: =B2&TEXT(F2,"00")&TEXT(H2,"00") -> 商品代號性別年齡 | K2: 保費 | M2: 商品代號 | N2: 累計給付年度 | O2: =M2&TEXT(N2,"00") -> 商品代號累計給付年度 | P2: 給付數值 | R2: 版次 | S2: 商品代號 | T2: 性別 | U2: 年齡 | V2: =S2&TEXT(T2,"00")&TEXT(U2,"00") -> 商品代號性別年齡 | W2: 第1年減額繳清保額 | X2: 第2年減額繳清保額 | Y2: 第3年減額繳清保額 | Z2: 第4年減額繳清保額 | AA2: 第5年減額繳清保額 | AB2: 第6年減額繳清保額 | AC2: 第7年減額繳清保額 | AD2: 第8年減額繳清保額 | AE2: 第9年減額繳清保額 | AF2: 第10年減額繳清保額 | AG2: 第11年減額繳清保額 | AH2: 第12年減額繳清保額 | AI2: 第13年減額繳清保額 | AJ2: 第14年減額繳清保額 | AK2: 第15年減額繳清保額 | AL2: 第16年減額繳清保額 | AM2: 第17年減額繳清保額 | AN2: 第18年減額繳清保額 | AO2: 第19年減額繳清保額B | AP2: 第20年減額繳清保額 | AQ2: 第21年減額繳清保額B | AR2: 第22年減額繳清保額 | AS2: 第23年減額繳清保額 | AT2: 第24年減額繳清保額 | AU2: 第25年減額繳清保額 | AV2: 第26年減額繳清保額B | AW2: 第27年減額繳清保額 | AX2: 第28年減額繳清保額B | AY2: 第29年減額繳清保額 | AZ2: 第30年減額繳清保額B | BA2: 第31年減額繳清保額 | BB2: 第32年減額繳清保額 | BC2: 第33年減額繳清保額 | BD2: 第34年減額繳清保額 | BE2: 第35年減額繳清保額 | BF2: 第36年減額繳清保額 | BG2: 第37年減額繳清保額 | BH2: 第38年減額繳清保額 | BI2: 第39年減額繳清保額 | BJ2: 第40年減額繳清保額 | BK2: 第41年減額繳清保額 | BL2: 第42年減額繳清保額 | BM2: 第43年減額繳清保額 | BN2: 第44年減額繳清保額 | BO2: 第45年減額繳清保額 | BP2: 第46年減額繳清保額 | BQ2: 第47年減額繳清保額 | BR2: 第48年減額繳清保額 | BS2: 第49年減額繳清保額 | BT2: 第50年減額繳清保額 | BU2: 第51年減額繳清保額 | BV2: 第52年減額繳清保額 | BW2: 第53年減額繳清保額 | BX2: 第54年減額繳清保額 | BY2: 第55年減額繳清保額 | BZ2: 第56年減額繳清保額 | CA2: 第57年減額繳清保額 | CB2: 第58年減額繳清保額 | CC2: 第59年減額繳清保額 | CD2: 第60年減額繳清保額 | CE2: 第61年減額繳清保額 | CF2: 第62年減額繳清保額 | CG2: 第63年減額繳清保額 | CH2: 第64年減額繳清保額 | CI2: 第65年減額繳清保額 | CJ2: 第66年減額繳清保額 | CK2: 第67年減額繳清保額 | CL2: 第68年減額繳清保額 | CM2: 第69年減額繳清保額 | CN2: 第70年減額繳清保額 | CO2: 第71年減額繳清保額 | CP2: 第72年減額繳清保額 | CQ2: 第73年減額繳清保額 | CR2: 第74年減額繳清保額 | CS2: 第75年減額繳清保額 | CT2: 第76年減額繳清保額 | CU2: 第77年減額繳清保額 | CV2: 第78年減額繳清保額 | CW2: 第79年減額繳清保額 | CX2: 第80年減額繳清保額 | CY2: 第81年減額繳清保額 | CZ2: 第82年契遾B繳清保額 | DA2: 第83年減額繳清保額 | DB2: 第84年減額繳清保額 | DC2: 第85年減額繳清保額 | DD2: 第86年減額繳清保額 | DE2: 第87年減額繳清保額 | DF2: 第88年減額繳清保額 | DG2: 第89年減額繳清保額 | DH2: 第90年減額繳清保額 | DI2: 第91年減額繳清保額 | DJ2: 第92年減額繳清保額 | DK2: 第93年減額繳清保額 | DL2: 第94年減額繳清保額 | DM2: 第95年減額繳清保額 | DN2: 第96年減額繳清保額 | DO2: 第97年減額繳清保額 | DP2: 第98年減額繳清保額 | DQ2: 第99年減額繳清保額 | DR2: 第100年減額繳清保額 | DS2: 第101年減額繳清保額 | DT2: 第102年減額繳清保額 | DU2: 第103年減額繳清保額 | DV2: 第104年減額繳清保額 | DW2: 第105年減額繳清保額 | DX2: 第106年減額繳清保額 | DY2: 第107年減額繳清保額 | DZ2: 第108年減額繳清保額 | EA2: 第109年減額繳清保額 | EB2: 第110年減額繳清保額 | EC2: 第111年減額繳清保額 | EE2: 版次 | EF2: 商品代號 | EG2: 性別 | EH2: 年齡
B3: LTQ30 | D3: 30 | F3: 1 | H3: 15 | J3: =B3&TEXT(F3,"00")&TEXT(H3,"00") -> LTQ300115 | K3: 12780 | M3: LTQ10 | N3: 1 | O3: =M3&TEXT(N3,"00") -> LTQ1001 | P3: 20000
B4: LTQ30 | D4: 30 | F4: 1 | H4: 16 | J4: =B4&TEXT(F4,"00")&TEXT(H4,"00") -> LTQ300116 | K4: 12980 | M4: LTQ10 | N4: 2 | O4: =M4&TEXT(N4,"00") -> LTQ1002 | P4: 20400
B5: LTQ30 | D5: 30 | F5: 1 | H5: 17 | J5: =B5&TEXT(F5,"00")&TEXT(H5,"00") -> LTQ300117 | K5: 13290 | M5: LTQ10 | N5: 3 | O5: =M5&TEXT(N5,"00") -> LTQ1003 | P5: 20800
B6: LTQ30 | D6: 30 | F6: 1 | H6: 18 | J6: =B6&TEXT(F6,"00")&TEXT(H6,"00") -> LTQ300118 | K6: 13600 | M6: LTQ10 | N6: 4 | O6: =M6&TEXT(N6,"00") -> LTQ1004 | P6: 21200
B7: LTQ30 | D7: 30 | F7: 1 | H7: 19 | J7: =B7&TEXT(F7,"00")&TEXT(H7,"00") -> LTQ300119 | K7: 13810 | M7: LTQ10 | N7: 5 | O7: =M7&TEXT(N7,"00") -> LTQ1005 | P7: 21600
B8: LTQ30 | D8: 30 | F8: 1 | H8: 20 | J8: =B8&TEXT(F8,"00")&TEXT(H8,"00") -> LTQ300120 | K8: 14320 | M8: LTQ10 | N8: 6 | O8: =M8&TEXT(N8,"00") -> LTQ1006 | P8: 22000
B9: LTQ30 | D9: 30 | F9: 1 | H9: 21 | J9: =B9&TEXT(F9,"00")&TEXT(H9,"00") -> LTQ300121 | K9: 14740 | M9: LTQ10 | N9: 7 | O9: =M9&TEXT(N9,"00") -> LTQ1007 | P9: 22400
B10: LTQ30 | D10: 30 | F10: 1 | H10: 22 | J10: =B10&TEXT(F10,"00")&TEXT(H10,"00") -> LTQ300122 | K10: 15150 | M10: LTQ10 | N10: 8 | O10: =M10&TEXT(N10,"00") -> LTQ1008 | P10: 22800
B11: LTQ30 | D11: 30 | F11: 1 | H11: 23 | J11: =B11&TEXT(F11,"00")&TEXT(H11,"00") -> LTQ300123 | K11: 15560 | M11: LTQ10 | N11: 9 | O11: =M11&TEXT(N11,"00") -> LTQ1009 | P11: 23200
B12: LTQ30 | D12: 30 | F12: 1 | H12: 24 | J12: =B12&TEXT(F12,"00")&TEXT(H12,"00") -> LTQ300124 | K12: 16070 | M12: LTQ10 | N12: 10 | O12: =M12&TEXT(N12,"00") -> LTQ1010 | P12: 23600
B13: LTQ30 | D13: 30 | F13: 1 | H13: 25 | J13: =B13&TEXT(F13,"00")&TEXT(H13,"00") -> LTQ300125 | K13: 16580 | M13: LTQ10 | N13: 11 | O13: =M13&TEXT(N13,"00") -> LTQ1011 | P13: 24000
B14: LTQ30 | D14: 30 | F14: 1 | H14: 26 | J14: =B14&TEXT(F14,"00")&TEXT(H14,"00") -> LTQ300126 | K14: 16990 | M14: LTQ10 | N14: 12 | O14: =M14&TEXT(N14,"00") -> LTQ1012 | P14: 24400
... B50: LTQ30 | D50: 30 | F50: 2 | H50: 26 | J50: =B50&TEXT(F50,"00")&TEXT(H50,"00") -> LTQ300226 | K50: 20970 | M50: LTQ30 | N50: 16 | O50: =M50&TEXT(N50,"00") -> LTQ3016 | P50: 26000
B51: LTQ30 | D51: 30 | F51: 2 | H51: 27 | J51: =B51&TEXT(F51,"00")&TEXT(H51,"00") -> LTQ300227 | K51: 21470
B52: LTQ30 | D52: 30 | F52: 2 | H52: 28 | J52: =B52&TEXT(F52,"00")&TEXT(H52,"00") -> LTQ300228 | K52: 21970
B53: LTQ30 | D53: 30 | F53: 2 | H53: 29 | J53: =B53&TEXT(F53,"00")&TEXT(H53,"00") -> LTQ300229 | K53: 22570
B54: LTQ30 | D54: 30 | F54: 2 | H54: 30 | J54: =B54&TEXT(F54,"00")&TEXT(H54,"00") -> LTQ300230 | K54: 23080
B55: LTQ30 | D55: 30 | F55: 2 | H55: 31 | J55: =B55&TEXT(F55,"00")&TEXT(H55,"00") -> LTQ300231 | K55: 23890
B56: LTQ30 | D56: 30 | F56: 2 | H56: 32 | J56: =B56&TEXT(F56,"00")&TEXT(H56,"00") -> LTQ300232 | K56: 24500
B57: LTQ30 | D57: 30 | F57: 2 | H57: 33 | J57: =B57&TEXT(F57,"00")&TEXT(H57,"00") -> LTQ300233 | K57: 25310
B58: LTQ30 | D58: 30 | F58: 2 | H58: 34 | J58: =B58&TEXT(F58,"00")&TEXT(H58,"00") -> LTQ300234 | K58: 26030
B59: LTQ30 | D59: 30 | F59: 2 | H59: 35 | J59: =B59&TEXT(F59,"00")&TEXT(H59,"00") -> LTQ300235 | K59: 26740
B60: LTQ30 | D60: 30 | F60: 2 | H60: 36 | J60: =B60&TEXT(F60,"00")&TEXT(H60,"00") -> LTQ300236 | K60: 27460
B61: LTQ30 | D61: 30 | F61: 2 | H61: 37 | J61: =B61&TEXT(F61,"00")&TEXT(H61,"00") -> LTQ300237 | K61: 28180
B62: LTQ30 | D62: 30 | F62: 2 | H62: 38 | J62: =B62&TEXT(F62,"00")&TEXT(H62,"00") -> LTQ300238 | K62: 29000
... B278: LTQ10 | D278: 10 | F278: 2 | H278: 70 | J278: =B278&TEXT(F278,"00")&TEXT(H278,"00") -> LTQ100270 | K278: 345100
R281: DIE2 | V281: =S281&TEXT(T281,"00")&TEXT(U281,"00") -> 0000 | EE281: CV | EI281: =EF281&TEXT(EG281,"00")&TEXT(EH281,"00") -> 0000
R282: 版次 | S282: 商品代號 | T282: 性別 | U282: 年齡 | EE282: 版次 | EF282: 商品代號 | EG282: 性別 | EH282: 年齡 | EI282: =EF282&TEXT(EG282,"00")&TEXT(EH282,"00") -> 商品代號性別年齡 | EJ282: 第1年解約金 | EK282: 第2年解約金 | EL282: 第3年解約金 | EM282: 第4年解約金 | EN282: 第5年解約金 | EO282: 第6年解約金 | EP282: 第7年解約金 | EQ282: 第8年解約金 | ER282: 第9年解約金 | ES282: 第10年解約金 | ET282: 第11年解約金 | EU282: 第12年解約金 | EV282: 第13年解約金 | EW282: 第14年解約金 | EX282: 第15年解約金 | EY282: 第16年解約金 | EZ282: 第17年解約金 | FA282: 第18年解約金 | FB282: 第19年解約金 | FC282: 第20年解約金 | FD282: 第21年解約金 | FE282: 第22年解約金 | FF282: 第23年解約金 | FG282: 第24年解約金 | FH282: 第25年解約金 | FI282: 第26年解約金 | FJ282: 第27年解約金 | FK282: 第28年解約金 | FL282: 第29年解約金 | FM282: 第30年解約金 | FN282: 第31年解約金 | FO282: 第32年解約金 | FP282: 第33年解約金 | FQ282: 第34年解約金 | FR282: 第35年解約金 | FS282: 第36年解約金 | FT282: 第37年解約金 | FU282: 第38年解約金 | FV282: 第39年解約金 | FW282: 第40年解約金 | FX282: 第41年解約金 | FY282: 第42年解約金 | FZ282: 第43年解約金 | GA282: 第44年解約金 | GB282: 第45年解約金 | GC282: 第46年解約金 | GD282: 第47年解約金 | GE282: 第48年解約金 | GF282: 第49年解約金 | GG282: 第50年解約金 | GH282: 第51年解約金 | GI282: 第52年解約金 | GJ282: 第53年解約金 | GK282: 第54年解約金 | GL282: 第55年解約金 | GM282: 第56年解約金 | GN282: 第57年解約金 | GO282: 第58年解約金 | GP282: 第59年解約金 | GQ282: 第60年解約金 | GR282: 第61年解約金 | GS282: 第62年解約金 | GT282: 第63年解約金 | GU282: 第64年解約金 | GV282: 第65年解約金 | GW282: 第66年解約金 | GX282: 第67年解約金 | GY282: 第68年解約金 | GZ282: 第69年解約金 | HA282: 第70年解約金 | HB282: 第71年解約金 | HC282: 第72年解約金 | HD282: 第73年解約金 | HE282: 第74年解約金 | HF282: 第75年解約金 | HG282: 第76年解約金 | HH282: 第77年解約金 | HI282: 第78年解約金 | HJ282: 第79年解約金 | HK282: 第80年解約金 | HL282: 第81年解約金 | HM282: 第82年解約金 | HN282: 第83年解約金 | HO282: 第84年解約金 | HP282: 第85年解約金 | HQ282: 第86年解約金 | HR282: 第87年解約金 | HS282: 第88年解約金 | HT282: 第89年解約金 | HU282: 第90年解約金 | HV282: 第91年解約金 | HW282: 第92年解約金 | HX282: 第93年解約金 | HY282: 第94年解約金 | HZ282: 第95年解約金 | IA282: 第96年解約金 | IB282: 第97年解約金 | IC282: 第98年解約金 | ID282: 第99年解約金 | IE282: 第100年解約金 | IF282: 第101年解約金 | IG282: 第102年解約金 | IH282: 第103年解約金 | II282: 第104年解約金 | IJ282: 第105年解約金 | IK282: 第106年解約金 | IL282: 第107年解約金 | IM282: 第108年解約金 | IN282: 第109年解約金 | IO282: 第110年解約金 | IP282: 第111年解約金
R551: DIE | V551: =S551&TEXT(T551,"00")&TEXT(U551,"00") -> 0000 | EE551: EXP | EI551: =EF551&TEXT(EG551,"00")&TEXT(EH551,"00") -> 0000
R552: 版次 | S552: 商品代號 | T552: 性別 | U552: 年齡 | V552: =S552&TEXT(T552,"00")&TEXT(U552,"00") -> 商品代號性別年齡 | W552: 第1年身故保險金 | X552: 第2年身故保險金 | Y552: 第3年身故保險金 | Z552: 第4年身故保險金 | AA552: 第5年身故保險金 | AB552: 第6年身故保險金 | AC552: 第7年身故保險金 | AD552: 第8年身故保險金 | AE552: 第9年身故保險金 | AF552: 第10年身故保險金 | AG552: 第11年身故保險金 | AH552: 第12年身故保險金 | AI552: 第13年身故保險金 | AJ552: 第14年身故保險金 | AK552: 第15年身故保險金 | AL552: 第16年身故保險金 | AM552: 第17年身故保險金 | AN552: 第18年身故保險金 | AO552: 第19年身故保險金 | AP552: 第20年身故保險金 | AQ552: 第21年身故保險金 | AR552: 第22年身故保險金 | AS552: 第23年身故保險金 | AT552: 第24年身故保險金 | AU552: 第25年身故保險金 | AV552: 第26年身故保險金 | AW552: 第27年身故保險金 | AX552: 第28年身故保險金 | AY552: 第29年身故保險金 | AZ552: 第30年身故保險金 | BA552: 第31年身故保險金 | BB552: 第32年身故保險金 | BC552: 第33年身故保險金 | BD552: 第34年身故保險金 | BE552: 第35年身故保險金 | BF552: 第36年身故保險金 | BG552: 第37年身故保險金 | BH552: 第38年身故保險金 | BI552: 第39年身故保險金 | BJ552: 第40年身故保險金 | BK552: 第41年身故保險金 | BL552: 第42年身故保險金 | BM552: 第43年身故保險金 | BN552: 第44年身故保險金 | BO552: 第45年身故保險金 | BP552: 第46年身故保險金 | BQ552: 第47年身故保險金 | BR552: 第48年身故保險金 | BS552: 第49年身故保險金 | BT552: 第50年身故保險金 | BU552: 第51年身故保險金 | BV552: 第52年身故保險金 | BW552: 第53年身故保險金 | BX552: 第54年身故保險金 | BY552: 第55年身故保險金 | BZ552: 第56年身故保險金 | CA552: 第57年身故保險金 | CB552: 第58年身故保險金 | CC552: 第59年身故保險金 | CD552: 第60年身故保險金 | CE552: 第61年身故保險金 | CF552: 第62年身故保險金 | CG552: 第63年身故保險金 | CH552: 第64年身故保險金 | CI552: 第65年身故保險金 | CJ552: 第66年身故保險金 | CK552: 第67年身故保險金 | CL552: 第68年身故保險金 | CM552: 第69年身故保險金 | CN552: 第70年身故保險金 | CO552: 第71年身故保險金 | CP552: 第72年身故保險金 | CQ552: 第73年身故保險金 | CR552: 第74年身故保險金額 | CS552: 第75年身故保險金 | CT552: 第76年身故保險金 | CU552: 第77年身故保險金 | CV552: 第78年身故保險金 | CW552: 第79年身故保險金 | CX552: 第80年身故保險金 | CY552: 第81年身故保險金 | CZ552: 第82年身故保險金 | DA552: 第83年身故保險金 | DB552: 第84年身故保險金 | DC552: 第85年身故保險金 | DD552: 第86年身故保險金 | DE552: 第87年身故保險金 | DF552: 第88年身故保險金 | DG552: 第89年身故保險金 | DH552: 第90年身故保險金 | DI552: 第91年身故保險金 | DJ552: 第92年身故保險金 | DK552: 第93年身故保險金 | DL552: 第94年身故保險金 | DM552: 第95年身故保險金 | DN552: 第96年身故保險金 | DO552: 第97年身故保險金 | DP552: 第98年身故保險金 | DQ552: 第99年身故保險金 | DR552: 第100年身故保險金 | DS552: 第101年身故保險金 | DT552: 第102年身故保險金 | DU552: 第103年身故保險金 | DV552: 第104年身故保險金 | DW552: 第105年身故保險金 | DX552: 第106年身故保險金 | DY552: 第107年身故保險金 | DZ552: 第108年身故保險金 | EA552: 第109年身故保險金 | EB552: 第110年身故保險金 | EC552: 第111年身故保險金 | EE552: 版次 | EF552: 商品代號 | EG552: 性別 | EH552: 年齡 | EI552: =EF552&TEXT(EG552,"00")&TEXT(EH552,"00") -> 商品代號性別年齡 | EJ552: 第1年祝壽保險金 | EK552: 第2年祝壽保險金 | EL552: 第3年祝壽保險金 | EM552: 第4年祝壽保險金 | EN552: 第5年祝壽保險金 | EO552: 第6年祝壽保險金 | EP552: 第7年祝壽保險金 | EQ552: 第8年祝壽保險金 | ER552: 第9年祝壽保險金 | ES552: 第10年祝壽保險金 | ET552: 第11年祝壽保險金 | EU552: 第12年祝壽保險金 | EV552: 第13年祝壽保險金 | EW552: 第14年祝壽保險金 | EX552: 第15年祝壽保險金 | EY552: 第16年祝壽保險金 | EZ552: 第17年祝壽保險金 | FA552: 第18年祝壽保險金 | FB552: 第19年祝壽保險金 | FC552: 第20年祝壽保險金 | FD552: 第21年祝壽保險金 | FE552: 第22年祝壽保險金 | FF552: 第23年祝壽保險金 | FG552: 第24年祝壽保險金 | FH552: 第25年祝壽保險金 | FI552: 第26年祝壽保險金 | FJ552: 第27年祝壽保險金 | FK552: 第28年祝壽保險金 | FL552: 第29年祝壽保險金 | FM552: 第30年祝壽保險金 | FN552: 第31年祝壽保險金 | FO552: 第32年祝壽保險金 | FP552: 第33年祝壽保險金 | FQ552: 第34年祝壽保險金 | FR552: 第35年祝壽保險金 | FS552: 第36年祝壽保險金 | FT552: 第37年祝壽保險金 | FU552: 第38年祝壽保險金 | FV552: 第39年祝壽保險金 | FW552: 第40年祝壽保險金 | FX552: 第41年祝壽保險金 | FY552: 第42年祝壽保險金 | FZ552: 第43年祝壽保險金 | GA552: 第44年祝壽保險金 | GB552: 第45年祝壽保險金 | GC552: 第46年祝壽保險金 | GD552: 第47年祝壽保險金 | GE552: 第48年祝壽保險金 | GF552: 第49年祝壽保險金 | GG552: 第50年祝壽保險金 | GH552: 第51年祝壽保險金 | GI552: 第52年祝壽保險金 | GJ552: 第53年祝壽保險金 | GK552: 第54年祝壽保險金 | GL552: 第55年祝壽保險金 | GM552: 第56年祝壽保險金 | GN552: 第57年祝壽保險金 | GO552: 第58年祝壽保險金 | GP552: 第59年祝壽保險金 | GQ552: 第60年祝壽保險金 | GR552: 第61年祝壽保險金 | GS552: 第62年祝壽保險金 | GT552: 第63年祝壽保險金 | GU552: 第64年祝壽保險金 | GV552: 第65年祝壽保險金 | GW552: 第66年祝壽保險金 | GX552: 第67年祝壽保險金 | GY552: 第68年祝壽保險金 | GZ552: 第69年祝壽保險金 | HA552: 第70年祝壽保險金 | HB552: 第71年祝壽保險金 | HC552: 第72年祝壽保險金 | HD552: 第73年祝壽保險金 | HE552: 第74年祝壽保險金 | HF552: 第75年祝壽保險金 | HG552: 第76年祝壽保險金 | HH552: 第77年祝壽保險金 | HI552: 第78年祝壽保險金 | HJ552: 第79年祝壽保險金 | HK552: 第80年祝壽保險金 | HL552: 第81年祝壽保險金 | HM552: 第82年祝壽保險金 | HN552: 第83年祝壽保險金 | HO552: 第84年祝壽保險金 | HP552: 第85年祝壽保險金 | HQ552: 第86年祝壽保險金 | HR552: 第87年祝壽保險金 | HS552: 第88年祝壽保險金 | HT552: 第89年祝壽保險金 | HU552: 第90年祝壽保險金 | HV552: 第91年祝壽保險金 | HW552: 第92年祝壽保險金 | HX552: 第93年祝壽保險金 | HY552: 第94年祝壽保險金 | HZ552: 第95年祝壽保險金 | IA552: 第96年祝壽保險金 | IB552: 第97年祝壽保險金 | IC552: 第98年祝壽保險金 | ID552: 第99年祝壽保險金 | IE552: 第100年祝壽保險金 | IF552: 第101年祝壽保險金 | IG552: 第102年祝壽保險金 | IH552: 第103年祝壽保險金 | II552: 第104年祝壽保險金 | IJ552: 第105年祝壽保險金 | IK552: 第106年祝壽保險金 | IL552: 第107年祝壽保險金 | IM552: 第108年祝壽保險金 | IN552: 第109年祝壽保險金 | IO552: 第110年祝壽保險金 | IP552: 第111年祝壽保險金
S553: LTQ30 | T553: 1 | U553: 15 | V553: =S553&TEXT(T553,"00")&TEXT(U553,"00") -> LTQ300115 | W553: 13035.6 | X553: 26071.2 | Y553: 39106.8 | Z553: 52142.4 | AA553: 65178 | AB553: 78213.6 | AC553: 91249.2 | AD553: 104284.8 | AE553: 117320.4 | AF553: 130356 | AG553: 143391.6 | AH553: 156427.2 | AI553: 169462.8 | AJ553: 182498.4 | AK553: 195534 | AL553: 208569.6 | AM553: 221605.2 | AN553: 234640.8 | AO553: 247676.4 | AP553: 260712 | AQ553: 273747.6 | AR553: 286783.2 | AS553: 299818.8 | AT553: 312854.4 | AU553: 325890 | AV553: 338925.6 | AW553: 351961.2 | AX553: 364996.8 | AY553: 378032.4 | AZ553: 391068 | BA553: 391068 | BB553: 391068 | BC553: 391068 | BD553: 391068 | BE553: 391068 | BF553: 391068 | BG553: 391068 | BH553: 391068 | BI553: 391068 | BJ553: 391068 | BK553: 391068 | BL553: 391068 | BM553: 391068 | BN553: 391068 | BO553: 391068 | BP553: 391068 | BQ553: 391068 | BR553: 391068 | BS553: 391068 | BT553: 391068 | BU553: 391068 | BV553: 391068 | BW553: 391068 | BX553: 391068 | BY553: 391068 | BZ553: 391068 | CA553: 391068 | CB553: 391068 | CC553: 391068 | CD553: 391068 | CE553: 391068 | CF553: 391068 | CG553: 391068 | CH553: 391068 | CI553: 391068 | CJ553: 391068 | CK553: 391068 | CL553: 391068 | CM553: 391068 | CN553: 391068 | CO553: 391068 | CP553: 391068 | CQ553: 391068 | CR553: 391068 | CS553: 391068 | CT553: 391068 | CU553: 391068 | CV553: 391068 | CW553: 391068 | CX553: 391068 | CY553: 391068 | CZ553: 391068 | DA553: 391068 | DB553: 391068 | DC553: 391068 | DD553: 0 | DE553: 0 | DF553: 0 | DG553: 0 | DH553: 0 | DI553: 0 | DJ553: 0 | DK553: 0 | DL553: 0 | DM553: 0 | DN553: 0 | DO553: 0 | DP553: 0 | DQ553: 0 | DR553: 0 | DS553: 0 | DT553: 0 | DU553: 0 | DV553: 0 | DW553: 0 | DX553: 0 | DY553: 0 | DZ553: 0 | EA553: 0 | EB553: 0 | EC553: 0 | EF553: LTQ30 | EG553: 1 | EH553: 15 | EI553: =EF553&TEXT(EG553,"00")&TEXT(EH553,"00") -> LTQ300115 | EJ553: 0 | EK553: 0 | EL553: 0 | EM553: 0 | EN553: 0 | EO553: 0 | EP553: 0 | EQ553: 0 | ER553: 0 | ES553: 0 | ET553: 0 | EU553: 0 | EV553: 0 | EW553: 0 | EX553: 0 | EY553: 0 | EZ553: 0 | FA553: 0 | FB553: 0 | FC553: 0 | FD553: 0 | FE553: 0 | FF553: 0 | FG553: 0 | FH553: 0 | FI553: 0 | FJ553: 0 | FK553: 0 | FL553: 0 | FM553: 0 | FN553: 0 | FO553: 0 | FP553: 0 | FQ553: 0 | FR553: 0 | FS553: 0 | FT553: 0 | FU553: 0 | FV553: 0 | FW553: 0 | FX553: 0 | FY553: 0 | FZ553: 0 | GA553: 0 | GB553: 0 | GC553: 0 | GD553: 0 | GE553: 0 | GF553: 0 | GG553: 0 | GH553: 0 | GI553: 0 | GJ553: 0 | GK553: 0 | GL553: 0 | GM553: 0 | GN553: 0 | GO553: 0 | GP553: 0 | GQ553: 0 | GR553: 0 | GS553: 0 | GT553: 0 | GU553: 0 | GV553: 0 | GW553: 0 | GX553: 0 | GY553: 0 | GZ553: 0 | HA553: 0 | HB553: 0 | HC553: 0 | HD553: 0 | HE553: 0 | HF553: 0 | HG553: 0 | HH553: 0 | HI553: 0 | HJ553: 0 | HK553: 0 | HL553: 0 | HM553: 0 | HN553: 0 | HO553: 0 | HP553: 391068 | HQ553: 0 | HR553: 0 | HS553: 0 | HT553: 0 | HU553: 0 | HV553: 0 | HW553: 0 | HX553: 0 | HY553: 0 | HZ553: 0 | IA553: 0 | IB553: 0 | IC553: 0 | ID553: 0 | IE553: 0 | IF553: 0 | IG553: 0 | IH553: 0 | II553: 0 | IJ553: 0 | IK553: 0 | IL553: 0 | IM553: 0 | IN553: 0 | IO553: 0 | IP553: 0
S554: LTQ30 | T554: 1 | U554: 16 | V554: =S554&TEXT(T554,"00")&TEXT(U554,"00") -> LTQ300116 | W554: 13239.6 | X554: 26479.2 | Y554: 39718.8 | Z554: 52958.4 | AA554: 66198 | AB554: 79437.6 | AC554: 92677.2 | AD554: 105916.8 | AE554: 119156.4 | AF554: 132396 | AG554: 145635.6 | AH554: 158875.2 | AI554: 172114.8 | AJ554: 185354.4 | AK554: 198594 | AL554: 211833.6 | AM554: 225073.2 | AN554: 238312.8 | AO554: 251552.4 | AP554: 264792 | AQ554: 278031.6 | AR554: 291271.2 | AS554: 304510.8 | AT554: 317750.4 | AU554: 330990 | AV554: 344229.6 | AW554: 357469.2 | AX554: 370708.8 | AY554: 383948.4 | AZ554: 397188 | BA554: 397188 | BB554: 397188 | BC554: 397188 | BD554: 397188 | BE554: 397188 | BF554: 397188 | BG554: 397188 | BH554: 397188 | BI554: 397188 | BJ554: 397188 | BK554: 397188 | BL554: 397188 | BM554: 397188 | BN554: 397188 | BO554: 397188 | BP554: 397188 | BQ554: 397188 | BR554: 397188 | BS554: 397188 | BT554: 397188 | BU554: 397188 | BV554: 397188 | BW554: 397188 | BX554: 397188 | BY554: 397188 | BZ554: 397188 | CA554: 397188 | CB554: 397188 | CC554: 397188 | CD554: 397188 | CE554: 397188 | CF554: 397188 | CG554: 397188 | CH554: 397188 | CI554: 397188 | CJ554: 397188 | CK554: 397188 | CL554: 397188 | CM554: 397188 | CN554: 397188 | CO554: 397188 | CP554: 397188 | CQ554: 397188 | CR554: 397188 | CS554: 397188 | CT554: 397188 | CU554: 397188 | CV554: 397188 | CW554: 397188 | CX554: 397188 | CY554: 397188 | CZ554: 397188 | DA554: 397188 | DB554: 397188 | DC554: 0 | DD554: 0 | DE554: 0 | DF554: 0 | DG554: 0 | DH554: 0 | DI554: 0 | DJ554: 0 | DK554: 0 | DL554: 0 | DM554: 0 | DN554: 0 | DO554: 0 | DP554: 0 | DQ554: 0 | DR554: 0 | DS554: 0 | DT554: 0 | DU554: 0 | DV554: 0 | DW554: 0 | DX554: 0 | DY554: 0 | DZ554: 0 | EA554: 0 | EB554: 0 | EC554: 0 | EF554: LTQ30 | EG554: 1 | EH554: 16 | EI554: =EF554&TEXT(EG554,"00")&TEXT(EH554,"00") -> LTQ300116 | EJ554: 0 | EK554: 0 | EL554: 0 | EM554: 0 | EN554: 0 | EO554: 0 | EP554: 0 | EQ554: 0 | ER554: 0 | ES554: 0 | ET554: 0 | EU554: 0 | EV554: 0 | EW554: 0 | EX554: 0 | EY554: 0 | EZ554: 0 | FA554: 0 | FB554: 0 | FC554: 0 | FD554: 0 | FE554: 0 | FF554: 0 | FG554: 0 | FH554: 0 | FI554: 0 | FJ554: 0 | FK554: 0 | FL554: 0 | FM554: 0 | FN554: 0 | FO554: 0 | FP554: 0 | FQ554: 0 | FR554: 0 | FS554: 0 | FT554: 0 | FU554: 0 | FV554: 0 | FW554: 0 | FX554: 0 | FY554: 0 | FZ554: 0 | GA554: 0 | GB554: 0 | GC554: 0 | GD554: 0 | GE554: 0 | GF554: 0 | GG554: 0 | GH554: 0 | GI554: 0 | GJ554: 0 | GK554: 0 | GL554: 0 | GM554: 0 | GN554: 0 | GO554: 0 | GP554: 0 | GQ554: 0 | GR554: 0 | GS554: 0 | GT554: 0 | GU554: 0 | GV554: 0 | GW554: 0 | GX554: 0 | GY554: 0 | GZ554: 0 | HA554: 0 | HB554: 0 | HC554: 0 | HD554: 0 | HE554: 0 | HF554: 0 | HG554: 0 | HH554: 0 | HI554: 0 | HJ554: 0 | HK554: 0 | HL554: 0 | HM554: 0 | HN554: 0 | HO554: 397188 | HP554: 0 | HQ554: 0 | HR554: 0 | HS554: 0 | HT554: 0 | HU554: 0 | HV554: 0 | HW554: 0 | HX554: 0 | HY554: 0 | HZ554: 0 | IA554: 0 | IB554: 0 | IC554: 0 | ID554: 0 | IE554: 0 | IF554: 0 | IG554: 0 | IH554: 0 | II554: 0 | IJ554: 0 | IK554: 0 | IL554: 0 | IM554: 0 | IN554: 0 | IO554: 0 | IP554: 0
S555: LTQ30 | T555: 1 | U555: 17 | V555: =S555&TEXT(T555,"00")&TEXT(U555,"00") -> LTQ300117 | W555: 13555.8 | X555: 27111.6 | Y555: 40667.4 | Z555: 54223.2 | AA555: 67779 | AB555: 81334.8 | AC555: 94890.6 | AD555: 108446.4 | AE555: 122002.2 | AF555: 135558 | AG555: 149113.8 | AH555: 162669.6 | AI555: 176225.4 | AJ555: 189781.2 | AK555: 203337 | AL555: 216892.8 | AM555: 230448.6 | AN555: 244004.4 | AO555: 257560.2 | AP555: 271116 | AQ555: 284671.8 | AR555: 298227.6 | AS555: 311783.4 | AT555: 325339.2 | AU555: 338895 | AV555: 352450.8 | AW555: 366006.6 | AX555: 379562.4 | AY555: 393118.2 | AZ555: 406674 | BA555: 406674 | BB555: 406674 | BC555: 406674 | BD555: 406674 | BE555: 406674 | BF555: 406674 | BG555: 406674 | BH555: 406674 | BI555: 406674 | BJ555: 406674 | BK555: 406674 | BL555: 406674 | BM555: 406674 | BN555: 406674 | BO555: 406674 | BP555: 406674 | BQ555: 406674 | BR555: 406674 | BS555: 406674 | BT555: 406674 | BU555: 406674 | BV555: 406674 | BW555: 406674 | BX555: 406674 | BY555: 406674 | BZ555: 406674 | CA555: 406674 | CB555: 406674 | CC555: 406674 | CD555: 406674 | CE555: 406674 | CF555: 406674 | CG555: 406674 | CH555: 406674 | CI555: 406674 | CJ555: 406674 | CK555: 406674 | CL555: 406674 | CM555: 406674 | CN555: 406674 | CO555: 406674 | CP555: 406674 | CQ555: 406674 | CR555: 406674 | CS555: 406674 | CT555: 406674 | CU555: 406674 | CV555: 406674 | CW555: 406674 | CX555: 406674 | CY555: 406674 | CZ555: 406674 | DA555: 406674 | DB555: 0 | DC555: 0 | DD555: 0 | DE555: 0 | DF555: 0 | DG555: 0 | DH555: 0 | DI555: 0 | DJ555: 0 | DK555: 0 | DL555: 0 | DM555: 0 | DN555: 0 | DO555: 0 | DP555: 0 | DQ555: 0 | DR555: 0 | DS555: 0 | DT555: 0 | DU555: 0 | DV555: 0 | DW555: 0 | DX555: 0 | DY555: 0 | DZ555: 0 | EA555: 0 | EB555: 0 | EC555: 0 | EF555: LTQ30 | EG555: 1 | EH555: 17 | EI555: =EF555&TEXT(EG555,"00")&TEXT(EH555,"00") -> LTQ300117 | EJ555: 0 | EK555: 0 | EL555: 0 | EM555: 0 | EN555: 0 | EO555: 0 | EP555: 0 | EQ555: 0 | ER555: 0 | ES555: 0 | ET555: 0 | EU555: 0 | EV555: 0 | EW555: 0 | EX555: 0 | EY555: 0 | EZ555: 0 | FA555: 0 | FB555: 0 | FC555: 0 | FD555: 0 | FE555: 0 | FF555: 0 | FG555: 0 | FH555: 0 | FI555: 0 | FJ555: 0 | FK555: 0 | FL555: 0 | FM555: 0 | FN555: 0 | FO555: 0 | FP555: 0 | FQ555: 0 | FR555: 0 | FS555: 0 | FT555: 0 | FU555: 0 | FV555: 0 | FW555: 0 | FX555: 0 | FY555: 0 | FZ555: 0 | GA555: 0 | GB555: 0 | GC555: 0 | GD555: 0 | GE555: 0 | GF555: 0 | GG555: 0 | GH555: 0 | GI555: 0 | GJ555: 0 | GK555: 0 | GL555: 0 | GM555: 0 | GN555: 0 | GO555: 0 | GP555: 0 | GQ555: 0 | GR555: 0 | GS555: 0 | GT555: 0 | GU555: 0 | GV555: 0 | GW555: 0 | GX555: 0 | GY555: 0 | GZ555: 0 | HA555: 0 | HB555: 0 | HC555: 0 | HD555: 0 | HE555: 0 | HF555: 0 | HG555: 0 | HH555: 0 | HI555: 0 | HJ555: 0 | HK555: 0 | HL555: 0 | HM555: 0 | HN555: 406674 | HO555: 0 | HP555: 0 | HQ555: 0 | HR555: 0 | HS555: 0 | HT555: 0 | HU555: 0 | HV555: 0 | HW555: 0 | HX555: 0 | HY555: 0 | HZ555: 0 | IA555: 0 | IB555: 0 | IC555: 0 | ID555: 0 | IE555: 0 | IF555: 0 | IG555: 0 | IH555: 0 | II555: 0 | IJ555: 0 | IK555: 0 | IL555: 0 | IM555: 0 | IN555: 0 | IO555: 0 | IP555: 0
S556: LTQ30 | T556: 1 | U556: 18 | V556: =S556&TEXT(T556,"00")&TEXT(U556,"00") -> LTQ300118 | W556: 13872 | X556: 27744 | Y556: 41616 | Z556: 55488 | AA556: 69360 | AB556: 83232 | AC556: 97104 | AD556: 110976 | AE556: 124848 | AF556: 138720 | AG556: 152592 | AH556: 166464 | AI556: 180336 | AJ556: 194208 | AK556: 208080 | AL556: 221952 | AM556: 235824 | AN556: 249696 | AO556: 263568 | AP556: 277440 | AQ556: 291312 | AR556: 305184 | AS556: 319056 | AT556: 332928 | AU556: 346800 | AV556: 360672 | AW556: 374544 | AX556: 388416 | AY556: 402288 | AZ556: 416160 | BA556: 416160 | BB556: 416160 | BC556: 416160 | BD556: 416160 | BE556: 416160 | BF556: 416160 | BG556: 416160 | BH556: 416160 | BI556: 416160 | BJ556: 416160 | BK556: 416160 | BL556: 416160 | BM556: 416160 | BN556: 416160 | BO556: 416160 | BP556: 416160 | BQ556: 416160 | BR556: 416160 | BS556: 416160 | BT556: 416160 | BU556: 416160 | BV556: 416160 | BW556: 416160 | BX556: 416160 | BY556: 416160 | BZ556: 416160 | CA556: 416160 | CB556: 416160 | CC556: 416160 | CD556: 416160 | CE556: 416160 | CF556: 416160 | CG556: 416160 | CH556: 416160 | CI556: 416160 | CJ556: 416160 | CK556: 416160 | CL556: 416160 | CM556: 416160 | CN556: 416160 | CO556: 416160 | CP556: 416160 | CQ556: 416160 | CR556: 416160 | CS556: 416160 | CT556: 416160 | CU556: 416160 | CV556: 416160 | CW556: 416160 | CX556: 416160 | CY556: 416160 | CZ556: 416160 | DA556: 0 | DB556: 0 | DC556: 0 | DD556: 0 | DE556: 0 | DF556: 0 | DG556: 0 | DH556: 0 | DI556: 0 | DJ556: 0 | DK556: 0 | DL556: 0 | DM556: 0 | DN556: 0 | DO556: 0 | DP556: 0 | DQ556: 0 | DR556: 0 | DS556: 0 | DT556: 0 | DU556: 0 | DV556: 0 | DW556: 0 | DX556: 0 | DY556: 0 | DZ556: 0 | EA556: 0 | EB556: 0 | EC556: 0 | EF556: LTQ30 | EG556: 1 | EH556: 18 | EI556: =EF556&TEXT(EG556,"00")&TEXT(EH556,"00") -> LTQ300118 | EJ556: 0 | EK556: 0 | EL556: 0 | EM556: 0 | EN556: 0 | EO556: 0 | EP556: 0 | EQ556: 0 | ER556: 0 | ES556: 0 | ET556: 0 | EU556: 0 | EV556: 0 | EW556: 0 | EX556: 0 | EY556: 0 | EZ556: 0 | FA556: 0 | FB556: 0 | FC556: 0 | FD556: 0 | FE556: 0 | FF556: 0 | FG556: 0 | FH556: 0 | FI556: 0 | FJ556: 0 | FK556: 0 | FL556: 0 | FM556: 0 | FN556: 0 | FO556: 0 | FP556: 0 | FQ556: 0 | FR556: 0 | FS556: 0 | FT556: 0 | FU556: 0 | FV556: 0 | FW556: 0 | FX556: 0 | FY556: 0 | FZ556: 0 | GA556: 0 | GB556: 0 | GC556: 0 | GD556: 0 | GE556: 0 | GF556: 0 | GG556: 0 | GH556: 0 | GI556: 0 | GJ556: 0 | GK556: 0 | GL556: 0 | GM556: 0 | GN556: 0 | GO556: 0 | GP556: 0 | GQ556: 0 | GR556: 0 | GS556: 0 | GT556: 0 | GU556: 0 | GV556: 0 | GW556: 0 | GX556: 0 | GY556: 0 | GZ556: 0 | HA556: 0 | HB556: 0 | HC556: 0 | HD556: 0 | HE556: 0 | HF556: 0 | HG556: 0 | HH556: 0 | HI556: 0 | HJ556: 0 | HK556: 0 | HL556: 0 | HM556: 416160 | HN556: 0 | HO556: 0 | HP556: 0 | HQ556: 0 | HR556: 0 | HS556: 0 | HT556: 0 | HU556: 0 | HV556: 0 | HW556: 0 | HX556: 0 | HY556: 0 | HZ556: 0 | IA556: 0 | IB556: 0 | IC556: 0 | ID556: 0 | IE556: 0 | IF556: 0 | IG556: 0 | IH556: 0 | II556: 0 | IJ556: 0 | IK556: 0 | IL556: 0 | IM556: 0 | IN556: 0 | IO556: 0 | IP556: 0
S557: LTQ30 | T557: 1 | U557: 19 | V557: =S557&TEXT(T557,"00")&TEXT(U557,"00") -> LTQ300119 | W557: 14086.2 | X557: 28172.4 | Y557: 42258.6 | Z557: 56344.8 | AA557: 70431 | AB557: 84517.2 | AC557: 98603.4 | AD557: 112689.6 | AE557: 126775.8 | AF557: 140862 | AG557: 154948.2 | AH557: 169034.4 | AI557: 183120.6 | AJ557: 197206.8 | AK557: 211293 | AL557: 225379.2 | AM557: 239465.4 | AN557: 253551.6 | AO557: 267637.8 | AP557: 281724 | AQ557: 295810.2 | AR557: 309896.4 | AS557: 323982.6 | AT557: 338068.8 | AU557: 352155 | AV557: 366241.2 | AW557: 380327.4 | AX557: 394413.6 | AY557: 408499.8 | AZ557: 422586 | BA557: 422586 | BB557: 422586 | BC557: 422586 | BD557: 422586 | BE557: 422586 | BF557: 422586 | BG557: 422586 | BH557: 422586 | BI557: 422586 | BJ557: 422586 | BK557: 422586 | BL557: 422586 | BM557: 422586 | BN557: 422586 | BO557: 422586 | BP557: 422586 | BQ557: 422586 | BR557: 422586 | BS557: 422586 | BT557: 422586 | BU557: 422586 | BV557: 422586 | BW557: 422586 | BX557: 422586 | BY557: 422586 | BZ557: 422586 | CA557: 422586 | CB557: 422586 | CC557: 422586 | CD557: 422586 | CE557: 422586 | CF557: 422586 | CG557: 422586 | CH557: 422586 | CI557: 422586 | CJ557: 422586 | CK557: 422586 | CL557: 422586 | CM557: 422586 | CN557: 422586 | CO557: 422586 | CP557: 422586 | CQ557: 422586 | CR557: 422586 | CS557: 422586 | CT557: 422586 | CU557: 422586 | CV557: 422586 | CW557: 422586 | CX557: 422586 | CY557: 422586 | CZ557: 0 | DA557: 0 | DB557: 0 | DC557: 0 | DD557: 0 | DE557: 0 | DF557: 0 | DG557: 0 | DH557: 0 | DI557: 0 | DJ557: 0 | DK557: 0 | DL557: 0 | DM557: 0 | DN557: 0 | DO557: 0 | DP557: 0 | DQ557: 0 | DR557: 0 | DS557: 0 | DT557: 0 | DU557: 0 | DV557: 0 | DW557: 0 | DX557: 0 | DY557: 0 | DZ557: 0 | EA557: 0 | EB557: 0 | EC557: 0 | EF557: LTQ30 | EG557: 1 | EH557: 19 | EI557: =EF557&TEXT(EG557,"00")&TEXT(EH557,"00") -> LTQ300119 | EJ557: 0 | EK557: 0 | EL557: 0 | EM557: 0 | EN557: 0 | EO557: 0 | EP557: 0 | EQ557: 0 | ER557: 0 | ES557: 0 | ET557: 0 | EU557: 0 | EV557: 0 | EW557: 0 | EX557: 0 | EY557: 0 | EZ557: 0 | FA557: 0 | FB557: 0 | FC557: 0 | FD557: 0 | FE557: 0 | FF557: 0 | FG557: 0 | FH557: 0 | FI557: 0 | FJ557: 0 | FK557: 0 | FL557: 0 | FM557: 0 | FN557: 0 | FO557: 0 | FP557: 0 | FQ557: 0 | FR557: 0 | FS557: 0 | FT557: 0 | FU557: 0 | FV557: 0 | FW557: 0 | FX557: 0 | FY557: 0 | FZ557: 0 | GA557: 0 | GB557: 0 | GC557: 0 | GD557: 0 | GE557: 0 | GF557: 0 | GG557: 0 | GH557: 0 | GI557: 0 | GJ557: 0 | GK557: 0 | GL557: 0 | GM557: 0 | GN557: 0 | GO557: 0 | GP557: 0 | GQ557: 0 | GR557: 0 | GS557: 0 | GT557: 0 | GU557: 0 | GV557: 0 | GW557: 0 | GX557: 0 | GY557: 0 | GZ557: 0 | HA557: 0 | HB557: 0 | HC557: 0 | HD557: 0 | HE557: 0 | HF557: 0 | HG557: 0 | HH557: 0 | HI557: 0 | HJ557: 0 | HK557: 0 | HL557: 422586 | HM557: 0 | HN557: 0 | HO557: 0 | HP557: 0 | HQ557: 0 | HR557: 0 | HS557: 0 | HT557: 0 | HU557: 0 | HV557: 0 | HW557: 0 | HX557: 0 | HY557: 0 | HZ557: 0 | IA557: 0 | IB557: 0 | IC557: 0 | ID557: 0 | IE557: 0 | IF557: 0 | IG557: 0 | IH557: 0 | II557: 0 | IJ557: 0 | IK557: 0 | IL557: 0 | IM557: 0 | IN557: 0 | IO557: 0 | IP557: 0
S558: LTQ30 | T558: 1 | U558: 20 | V558: =S558&TEXT(T558,"00")&TEXT(U558,"00") -> LTQ300120 | W558: 14606.4 | X558: 29212.8 | Y558: 43819.2 | Z558: 58425.6 | AA558: 73032 | AB558: 87638.4 | AC558: 102244.8 | AD558: 116851.2 | AE558: 131457.6 | AF558: 146064 | AG558: 160670.4 | AH558: 175276.8 | AI558: 189883.2 | AJ558: 204489.6 | AK558: 219096 | AL558: 233702.4 | AM558: 248308.8 | AN558: 262915.2 | AO558: 277521.6 | AP558: 292128 | AQ558: 306734.4 | AR558: 321340.8 | AS558: 335947.2 | AT558: 350553.6 | AU558: 365160 | AV558: 379766.4 | AW558: 394372.8 | AX558: 408979.2 | AY558: 423585.6 | AZ558: 438192 | BA558: 438192 | BB558: 438192 | BC558: 438192 | BD558: 438192 | BE558: 438192 | BF558: 438192 | BG558: 438192 | BH558: 438192 | BI558: 438192 | BJ558: 438192 | BK558: 438192 | BL558: 438192 | BM558: 438192 | BN558: 438192 | BO558: 438192 | BP558: 438192 | BQ558: 438192 | BR558: 438192 | BS558: 438192 | BT558: 438192 | BU558: 438192 | BV558: 438192 | BW558: 438192 | BX558: 438192 | BY558: 438192 | BZ558: 438192 | CA558: 438192 | CB558: 438192 | CC558: 438192 | CD558: 438192 | CE558: 438192 | CF558: 438192 | CG558: 438192 | CH558: 438192 | CI558: 438192 | CJ558: 438192 | CK558: 438192 | CL558: 438192 | CM558: 438192 | CN558: 438192 | CO558: 438192 | CP558: 438192 | CQ558: 438192 | CR558: 438192 | CS558: 438192 | CT558: 438192 | CU558: 438192 | CV558: 438192 | CW558: 438192 | CX558: 438192 | CY558: 0 | CZ558: 0 | DA558: 0 | DB558: 0 | DC558: 0 | DD558: 0 | DE558: 0 | DF558: 0 | DG558: 0 | DH558: 0 | DI558: 0 | DJ558: 0 | DK558: 0 | DL558: 0 | DM558: 0 | DN558: 0 | DO558: 0 | DP558: 0 | DQ558: 0 | DR558: 0 | DS558: 0 | DT558: 0 | DU558: 0 | DV558: 0 | DW558: 0 | DX558: 0 | DY558: 0 | DZ558: 0 | EA558: 0 | EB558: 0 | EC558: 0 | EF558: LTQ30 | EG558: 1 | EH558: 20 | EI558: =EF558&TEXT(EG558,"00")&TEXT(EH558,"00") -> LTQ300120 | EJ558: 0 | EK558: 0 | EL558: 0 | EM558: 0 | EN558: 0 | EO558: 0 | EP558: 0 | EQ558: 0 | ER558: 0 | ES558: 0 | ET558: 0 | EU558: 0 | EV558: 0 | EW558: 0 | EX558: 0 | EY558: 0 | EZ558: 0 | FA558: 0 | FB558: 0 | FC558: 0 | FD558: 0 | FE558: 0 | FF558: 0 | FG558: 0 | FH558: 0 | FI558: 0 | FJ558: 0 | FK558: 0 | FL558: 0 | FM558: 0 | FN558: 0 | FO558: 0 | FP558: 0 | FQ558: 0 | FR558: 0 | FS558: 0 | FT558: 0 | FU558: 0 | FV558: 0 | FW558: 0 | FX558: 0 | FY558: 0 | FZ558: 0 | GA558: 0 | GB558: 0 | GC558: 0 | GD558: 0 | GE558: 0 | GF558: 0 | GG558: 0 | GH558: 0 | GI558: 0 | GJ558: 0 | GK558: 0 | GL558: 0 | GM558: 0 | GN558: 0 | GO558: 0 | GP558: 0 | GQ558: 0 | GR558: 0 | GS558: 0 | GT558: 0 | GU558: 0 | GV558: 0 | GW558: 0 | GX558: 0 | GY558: 0 | GZ558: 0 | HA558: 0 | HB558: 0 | HC558: 0 | HD558: 0 | HE558: 0 | HF558: 0 | HG558: 0 | HH558: 0 | HI558: 0 | HJ558: 0 | HK558: 438192 | HL558: 0 | HM558: 0 | HN558: 0 | HO558: 0 | HP558: 0 | HQ558: 0 | HR558: 0 | HS558: 0 | HT558: 0 | HU558: 0 | HV558: 0 | HW558: 0 | HX558: 0 | HY558: 0 | HZ558: 0 | IA558: 0 | IB558: 0 | IC558: 0 | ID558: 0 | IE558: 0 | IF558: 0 | IG558: 0 | IH558: 0 | II558: 0 | IJ558: 0 | IK558: 0 | IL558: 0 | IM558: 0 | IN558: 0 | IO558: 0 | IP558: 0
S559: LTQ30 | T559: 1 | U559: 21 | V559: =S559&TEXT(T559,"00")&TEXT(U559,"00") -> LTQ300121 | W559: 15034.8 | X559: 30069.6 | Y559: 45104.4 | Z559: 60139.2 | AA559: 75174 | AB559: 90208.8 | AC559: 105243.6 | AD559: 120278.4 | AE559: 135313.2 | AF559: 150348 | AG559: 165382.8 | AH559: 180417.6 | AI559: 195452.4 | AJ559: 210487.2 | AK559: 225522 | AL559: 240556.8 | AM559: 255591.6 | AN559: 270626.4 | AO559: 285661.2 | AP559: 300696 | AQ559: 315730.8 | AR559: 330765.6 | AS559: 345800.4 | AT559: 360835.2 | AU559: 375870 | AV559: 390904.8 | AW559: 405939.6 | AX559: 420974.4 | AY559: 436009.2 | AZ559: 451044 | BA559: 451044 | BB559: 451044 | BC559: 451044 | BD559: 451044 | BE559: 451044 | BF559: 451044 | BG559: 451044 | BH559: 451044 | BI559: 451044 | BJ559: 451044 | BK559: 451044 | BL559: 451044 | BM559: 451044 | BN559: 451044 | BO559: 451044 | BP559: 451044 | BQ559: 451044 | BR559: 451044 | BS559: 451044 | BT559: 451044 | BU559: 451044 | BV559: 451044 | BW559: 451044 | BX559: 451044 | BY559: 451044 | BZ559: 451044 | CA559: 451044 | CB559: 451044 | CC559: 451044 | CD559: 451044 | CE559: 451044 | CF559: 451044 | CG559: 451044 | CH559: 451044 | CI559: 451044 | CJ559: 451044 | CK559: 451044 | CL559: 451044 | CM559: 451044 | CN559: 451044 | CO559: 451044 | CP559: 451044 | CQ559: 451044 | CR559: 451044 | CS559: 451044 | CT559: 451044 | CU559: 451044 | CV559: 451044 | CW559: 451044 | CX559: 0 | CY559: 0 | CZ559: 0 | DA559: 0 | DB559: 0 | DC559: 0 | DD559: 0 | DE559: 0 | DF559: 0 | DG559: 0 | DH559: 0 | DI559: 0 | DJ559: 0 | DK559: 0 | DL559: 0 | DM559: 0 | DN559: 0 | DO559: 0 | DP559: 0 | DQ559: 0 | DR559: 0 | DS559: 0 | DT559: 0 | DU559: 0 | DV559: 0 | DW559: 0 | DX559: 0 | DY559: 0 | DZ559: 0 | EA559: 0 | EB559: 0 | EC559: 0 | EF559: LTQ30 | EG559: 1 | EH559: 21 | EI559: =EF559&TEXT(EG559,"00")&TEXT(EH559,"00") -> LTQ300121 | EJ559: 0 | EK559: 0 | EL559: 0 | EM559: 0 | EN559: 0 | EO559: 0 | EP559: 0 | EQ559: 0 | ER559: 0 | ES559: 0 | ET559: 0 | EU559: 0 | EV559: 0 | EW559: 0 | EX559: 0 | EY559: 0 | EZ559: 0 | FA559: 0 | FB559: 0 | FC559: 0 | FD559: 0 | FE559: 0 | FF559: 0 | FG559: 0 | FH559: 0 | FI559: 0 | FJ559: 0 | FK559: 0 | FL559: 0 | FM559: 0 | FN559: 0 | FO559: 0 | FP559: 0 | FQ559: 0 | FR559: 0 | FS559: 0 | FT559: 0 | FU559: 0 | FV559: 0 | FW559: 0 | FX559: 0 | FY559: 0 | FZ559: 0 | GA559: 0 | GB559: 0 | GC559: 0 | GD559: 0 | GE559: 0 | GF559: 0 | GG559: 0 | GH559: 0 | GI559: 0 | GJ559: 0 | GK559: 0 | GL559: 0 | GM559: 0 | GN559: 0 | GO559: 0 | GP559: 0 | GQ559: 0 | GR559: 0 | GS559: 0 | GT559: 0 | GU559: 0 | GV559: 0 | GW559: 0 | GX559: 0 | GY559: 0 | GZ559: 0 | HA559: 0 | HB559: 0 | HC559: 0 | HD559: 0 | HE559: 0 | HF559: 0 | HG559: 0 | HH559: 0 | HI559: 0 | HJ559: 451044 | HK559: 0 | HL559: 0 | HM559: 0 | HN559: 0 | HO559: 0 | HP559: 0 | HQ559: 0 | HR559: 0 | HS559: 0 | HT559: 0 | HU559: 0 | HV559: 0 | HW559: 0 | HX559: 0 | HY559: 0 | HZ559: 0 | IA559: 0 | IB559: 0 | IC559: 0 | ID559: 0 | IE559: 0 | IF559: 0 | IG559: 0 | IH559: 0 | II559: 0 | IJ559: 0 | IK559: 0 | IL559: 0 | IM559: 0 | IN559: 0 | IO559: 0 | IP559: 0
S560: LTQ30 | T560: 1 | U560: 22 | V560: =S560&TEXT(T560,"00")&TEXT(U560,"00") -> LTQ300122 | W560: 15453 | X560: 30906 | Y560: 46359 | Z560: 61812 | AA560: 77265 | AB560: 92718 | AC560: 108171 | AD560: 123624 | AE560: 139077 | AF560: 154530 | AG560: 169983 | AH560: 185436 | AI560: 200889 | AJ560: 216342 | AK560: 231795 | AL560: 247248 | AM560: 262701 | AN560: 278154 | AO560: 293607 | AP560: 309060 | AQ560: 324513 | AR560: 339966 | AS560: 355419 | AT560: 370872 | AU560: 386325 | AV560: 401778 | AW560: 417231 | AX560: 432684 | AY560: 448137 | AZ560: 463590 | BA560: 463590 | BB560: 463590 | BC560: 463590 | BD560: 463590 | BE560: 463590 | BF560: 463590 | BG560: 463590 | BH560: 463590 | BI560: 463590 | BJ560: 463590 | BK560: 463590 | BL560: 463590 | BM560: 463590 | BN560: 463590 | BO560: 463590 | BP560: 463590 | BQ560: 463590 | BR560: 463590 | BS560: 463590 | BT560: 463590 | BU560: 463590 | BV560: 463590 | BW560: 463590 | BX560: 463590 | BY560: 463590 | BZ560: 463590 | CA560: 463590 | CB560: 463590 | CC560: 463590 | CD560: 463590 | CE560: 463590 | CF560: 463590 | CG560: 463590 | CH560: 463590 | CI560: 463590 | CJ560: 463590 | CK560: 463590 | CL560: 463590 | CM560: 463590 | CN560: 463590 | CO560: 463590 | CP560: 463590 | CQ560: 463590 | CR560: 463590 | CS560: 463590 | CT560: 463590 | CU560: 463590 | CV560: 463590 | CW560: 0 | CX560: 0 | CY560: 0 | CZ560: 0 | DA560: 0 | DB560: 0 | DC560: 0 | DD560: 0 | DE560: 0 | DF560: 0 | DG560: 0 | DH560: 0 | DI560: 0 | DJ560: 0 | DK560: 0 | DL560: 0 | DM560: 0 | DN560: 0 | DO560: 0 | DP560: 0 | DQ560: 0 | DR560: 0 | DS560: 0 | DT560: 0 | DU560: 0 | DV560: 0 | DW560: 0 | DX560: 0 | DY560: 0 | DZ560: 0 | EA560: 0 | EB560: 0 | EC560: 0 | EF560: LTQ30 | EG560: 1 | EH560: 22 | EI560: =EF560&TEXT(EG560,"00")&TEXT(EH560,"00") -> LTQ300122 | EJ560: 0 | EK560: 0 | EL560: 0 | EM560: 0 | EN560: 0 | EO560: 0 | EP560: 0 | EQ560: 0 | ER560: 0 | ES560: 0 | ET560: 0 | EU560: 0 | EV560: 0 | EW560: 0 | EX560: 0 | EY560: 0 | EZ560: 0 | FA560: 0 | FB560: 0 | FC560: 0 | FD560: 0 | FE560: 0 | FF560: 0 | FG560: 0 | FH560: 0 | FI560: 0 | FJ560: 0 | FK560: 0 | FL560: 0 | FM560: 0 | FN560: 0 | FO560: 0 | FP560: 0 | FQ560: 0 | FR560: 0 | FS560: 0 | FT560: 0 | FU560: 0 | FV560: 0 | FW560: 0 | FX560: 0 | FY560: 0 | FZ560: 0 | GA560: 0 | GB560: 0 | GC560: 0 | GD560: 0 | GE560: 0 | GF560: 0 | GG560: 0 | GH560: 0 | GI560: 0 | GJ560: 0 | GK560: 0 | GL560: 0 | GM560: 0 | GN560: 0 | GO560: 0 | GP560: 0 | GQ560: 0 | GR560: 0 | GS560: 0 | GT560: 0 | GU560: 0 | GV560: 0 | GW560: 0 | GX560: 0 | GY560: 0 | GZ560: 0 | HA560: 0 | HB560: 0 | HC560: 0 | HD560: 0 | HE560: 0 | HF560: 0 | HG560: 0 | HH560: 0 | HI560: 463590 | HJ560: 0 | HK560: 0 | HL560: 0 | HM560: 0 | HN560: 0 | HO560: 0 | HP560: 0 | HQ560: 0 | HR560: 0 | HS560: 0 | HT560: 0 | HU560: 0 | HV560: 0 | HW560: 0 | HX560: 0 | HY560: 0 | HZ560: 0 | IA560: 0 | IB560: 0 | IC560: 0 | ID560: 0 | IE560: 0 | IF560: 0 | IG560: 0 | IH560: 0 | II560: 0 | IJ560: 0 | IK560: 0 | IL560: 0 | IM560: 0 | IN560: 0 | IO560: 0 | IP560: 0
S561: LTQ30 | T561: 1 | U561: 23 | V561: =S561&TEXT(T561,"00")&TEXT(U561,"00") -> LTQ300123 | W561: 15871.2 | X561: 31742.4 | Y561: 47613.6 | Z561: 63484.8 | AA561: 79356 | AB561: 95227.2 | AC561: 111098.4 | AD561: 126969.6 | AE561: 142840.8 | AF561: 158712 | AG561: 174583.2 | AH561: 190454.4 | AI561: 206325.6 | AJ561: 222196.8 | AK561: 238068 | AL561: 253939.2 | AM561: 269810.4 | AN561: 285681.6 | AO561: 301552.8 | AP561: 317424 | AQ561: 333295.2 | AR561: 349166.4 | AS561: 365037.6 | AT561: 380908.8 | AU561: 396780 | AV561: 412651.2 | AW561: 428522.4 | AX561: 444393.6 | AY561: 460264.8 | AZ561: 476136 | BA561: 476136 | BB561: 476136 | BC561: 476136 | BD561: 476136 | BE561: 476136 | BF561: 476136 | BG561: 476136 | BH561: 476136 | BI561: 476136 | BJ561: 476136 | BK561: 476136 | BL561: 476136 | BM561: 476136 | BN561: 476136 | BO561: 476136 | BP561: 476136 | BQ561: 476136 | BR561: 476136 | BS561: 476136 | BT561: 476136 | BU561: 476136 | BV561: 476136 | BW561: 476136 | BX561: 476136 | BY561: 476136 | BZ561: 476136 | CA561: 476136 | CB561: 476136 | CC561: 476136 | CD561: 476136 | CE561: 476136 | CF561: 476136 | CG561: 476136 | CH561: 476136 | CI561: 476136 | CJ561: 476136 | CK561: 476136 | CL561: 476136 | CM561: 476136 | CN561: 476136 | CO561: 476136 | CP561: 476136 | CQ561: 476136 | CR561: 476136 | CS561: 476136 | CT561: 476136 | CU561: 476136 | CV561: 0 | CW561: 0 | CX561: 0 | CY561: 0 | CZ561: 0 | DA561: 0 | DB561: 0 | DC561: 0 | DD561: 0 | DE561: 0 | DF561: 0 | DG561: 0 | DH561: 0 | DI561: 0 | DJ561: 0 | DK561: 0 | DL561: 0 | DM561: 0 | DN561: 0 | DO561: 0 | DP561: 0 | DQ561: 0 | DR561: 0 | DS561: 0 | DT561: 0 | DU561: 0 | DV561: 0 | DW561: 0 | DX561: 0 | DY561: 0 | DZ561: 0 | EA561: 0 | EB561: 0 | EC561: 0 | EF561: LTQ30 | EG561: 1 | EH561: 23 | EI561: =EF561&TEXT(EG561,"00")&TEXT(EH561,"00") -> LTQ300123 | EJ561: 0 | EK561: 0 | EL561: 0 | EM561: 0 | EN561: 0 | EO561: 0 | EP561: 0 | EQ561: 0 | ER561: 0 | ES561: 0 | ET561: 0 | EU561: 0 | EV561: 0 | EW561: 0 | EX561: 0 | EY561: 0 | EZ561: 0 | FA561: 0 | FB561: 0 | FC561: 0 | FD561: 0 | FE561: 0 | FF561: 0 | FG561: 0 | FH561: 0 | FI561: 0 | FJ561: 0 | FK561: 0 | FL561: 0 | FM561: 0 | FN561: 0 | FO561: 0 | FP561: 0 | FQ561: 0 | FR561: 0 | FS561: 0 | FT561: 0 | FU561: 0 | FV561: 0 | FW561: 0 | FX561: 0 | FY561: 0 | FZ561: 0 | GA561: 0 | GB561: 0 | GC561: 0 | GD561: 0 | GE561: 0 | GF561: 0 | GG561: 0 | GH561: 0 | GI561: 0 | GJ561: 0 | GK561: 0 | GL561: 0 | GM561: 0 | GN561: 0 | GO561: 0 | GP561: 0 | GQ561: 0 | GR561: 0 | GS561: 0 | GT561: 0 | GU561: 0 | GV561: 0 | GW561: 0 | GX561: 0 | GY561: 0 | GZ561: 0 | HA561: 0 | HB561: 0 | HC561: 0 | HD561: 0 | HE561: 0 | HF561: 0 | HG561: 0 | HH561: 476136 | HI561: 0 | HJ561: 0 | HK561: 0 | HL561: 0 | HM561: 0 | HN561: 0 | HO561: 0 | HP561: 0 | HQ561: 0 | HR561: 0 | HS561: 0 | HT561: 0 | HU561: 0 | HV561: 0 | HW561: 0 | HX561: 0 | HY561: 0 | HZ561: 0 | IA561: 0 | IB561: 0 | IC561: 0 | ID561: 0 | IE561: 0 | IF561: 0 | IG561: 0 | IH561: 0 | II561: 0 | IJ561: 0 | IK561: 0 | IL561: 0 | IM561: 0 | IN561: 0 | IO561: 0 | IP561: 0
S562: LTQ30 | T562: 1 | U562: 24 | V562: =S562&TEXT(T562,"00")&TEXT(U562,"00") -> LTQ300124 | W562: 16391.4 | X562: 32782.8 | Y562: 49174.2 | Z562: 65565.6 | AA562: 81957 | AB562: 98348.4 | AC562: 114739.8 | AD562: 131131.2 | AE562: 147522.6 | AF562: 163914 | AG562: 180305.4 | AH562: 196696.8 | AI562: 213088.2 | AJ562: 229479.6 | AK562: 245871 | AL562: 262262.4 | AM562: 278653.8 | AN562: 295045.2 | AO562: 311436.6 | AP562: 327828 | AQ562: 344219.4 | AR562: 360610.8 | AS562: 377002.2 | AT562: 393393.6 | AU562: 409785 | AV562: 426176.4 | AW562: 442567.8 | AX562: 458959.2 | AY562: 475350.6 | AZ562: 491742 | BA562: 491742 | BB562: 491742 | BC562: 491742 | BD562: 491742 | BE562: 491742 | BF562: 491742 | BG562: 491742 | BH562: 491742 | BI562: 491742 | BJ562: 491742 | BK562: 491742 | BL562: 491742 | BM562: 491742 | BN562: 491742 | BO562: 491742 | BP562: 491742 | BQ562: 491742 | BR562: 491742 | BS562: 491742 | BT562: 491742 | BU562: 491742 | BV562: 491742 | BW562: 491742 | BX562: 491742 | BY562: 491742 | BZ562: 491742 | CA562: 491742 | CB562: 491742 | CC562: 491742 | CD562: 491742 | CE562: 491742 | CF562: 491742 | CG562: 491742 | CH562: 491742 | CI562: 491742 | CJ562: 491742 | CK562: 491742 | CL562: 491742 | CM562: 491742 | CN562: 491742 | CO562: 491742 | CP562: 491742 | CQ562: 491742 | CR562: 491742 | CS562: 491742 | CT562: 491742 | CU562: 0 | CV562: 0 | CW562: 0 | CX562: 0 | CY562: 0 | CZ562: 0 | DA562: 0 | DB562: 0 | DC562: 0 | DD562: 0 | DE562: 0 | DF562: 0 | DG562: 0 | DH562: 0 | DI562: 0 | DJ562: 0 | DK562: 0 | DL562: 0 | DM562: 0 | DN562: 0 | DO562: 0 | DP562: 0 | DQ562: 0 | DR562: 0 | DS562: 0 | DT562: 0 | DU562: 0 | DV562: 0 | DW562: 0 | DX562: 0 | DY562: 0 | DZ562: 0 | EA562: 0 | EB562: 0 | EC562: 0 | EF562: LTQ30 | EG562: 1 | EH562: 24 | EI562: =EF562&TEXT(EG562,"00")&TEXT(EH562,"00") -> LTQ300124 | EJ562: 0 | EK562: 0 | EL562: 0 | EM562: 0 | EN562: 0 | EO562: 0 | EP562: 0 | EQ562: 0 | ER562: 0 | ES562: 0 | ET562: 0 | EU562: 0 | EV562: 0 | EW562: 0 | EX562: 0 | EY562: 0 | EZ562: 0 | FA562: 0 | FB562: 0 | FC562: 0 | FD562: 0 | FE562: 0 | FF562: 0 | FG562: 0 | FH562: 0 | FI562: 0 | FJ562: 0 | FK562: 0 | FL562: 0 | FM562: 0 | FN562: 0 | FO562: 0 | FP562: 0 | FQ562: 0 | FR562: 0 | FS562: 0 | FT562: 0 | FU562: 0 | FV562: 0 | FW562: 0 | FX562: 0 | FY562: 0 | FZ562: 0 | GA562: 0 | GB562: 0 | GC562: 0 | GD562: 0 | GE562: 0 | GF562: 0 | GG562: 0 | GH562: 0 | GI562: 0 | GJ562: 0 | GK562: 0 | GL562: 0 | GM562: 0 | GN562: 0 | GO562: 0 | GP562: 0 | GQ562: 0 | GR562: 0 | GS562: 0 | GT562: 0 | GU562: 0 | GV562: 0 | GW562: 0 | GX562: 0 | GY562: 0 | GZ562: 0 | HA562: 0 | HB562: 0 | HC562: 0 | HD562: 0 | HE562: 0 | HF562: 0 | HG562: 491742 | HH562: 0 | HI562: 0 | HJ562: 0 | HK562: 0 | HL562: 0 | HM562: 0 | HN562: 0 | HO562: 0 | HP562: 0 | HQ562: 0 | HR562: 0 | HS562: 0 | HT562: 0 | HU562: 0 | HV562: 0 | HW562: 0 | HX562: 0 | HY562: 0 | HZ562: 0 | IA562: 0 | IB562: 0 | IC562: 0 | ID562: 0 | IE562: 0 | IF562: 0 | IG562: 0 | IH562: 0 | II562: 0 | IJ562: 0 | IK562: 0 | IL562: 0 | IM562: 0 | IN562: 0 | IO562: 0 | IP562: 0
S563: LTQ30 | T563: 1 | U563: 25 | V563: =S563&TEXT(T563,"00")&TEXT(U563,"00") -> LTQ300125 | W563: 16911.6 | X563: 33823.2 | Y563: 50734.8 | Z563: 67646.4 | AA563: 84558 | AB563: 101469.6 | AC563: 118381.2 | AD563: 135292.8 | AE563: 152204.4 | AF563: 169116 | AG563: 186027.6 | AH563: 202939.2 | AI563: 219850.8 | AJ563: 236762.4 | AK563: 253674 | AL563: 270585.6 | AM563: 287497.2 | AN563: 304408.8 | AO563: 321320.4 | AP563: 338232 | AQ563: 355143.6 | AR563: 372055.2 | AS563: 388966.8 | AT563: 405878.4 | AU563: 422790 | AV563: 439701.6 | AW563: 456613.2 | AX563: 473524.8 | AY563: 490436.4 | AZ563: 507348 | BA563: 507348 | BB563: 507348 | BC563: 507348 | BD563: 507348 | BE563: 507348 | BF563: 507348 | BG563: 507348 | BH563: 507348 | BI563: 507348 | BJ563: 507348 | BK563: 507348 | BL563: 507348 | BM563: 507348 | BN563: 507348 | BO563: 507348 | BP563: 507348 | BQ563: 507348 | BR563: 507348 | BS563: 507348 | BT563: 507348 | BU563: 507348 | BV563: 507348 | BW563: 507348 | BX563: 507348 | BY563: 507348 | BZ563: 507348 | CA563: 507348 | CB563: 507348 | CC563: 507348 | CD563: 507348 | CE563: 507348 | CF563: 507348 | CG563: 507348 | CH563: 507348 | CI563: 507348 | CJ563: 507348 | CK563: 507348 | CL563: 507348 | CM563: 507348 | CN563: 507348 | CO563: 507348 | CP563: 507348 | CQ563: 507348 | CR563: 507348 | CS563: 507348 | CT563: 0 | CU563: 0 | CV563: 0 | CW563: 0 | CX563: 0 | CY563: 0 | CZ563: 0 | DA563: 0 | DB563: 0 | DC563: 0 | DD563: 0 | DE563: 0 | DF563: 0 | DG563: 0 | DH563: 0 | DI563: 0 | DJ563: 0 | DK563: 0 | DL563: 0 | DM563: 0 | DN563: 0 | DO563: 0 | DP563: 0 | DQ563: 0 | DR563: 0 | DS563: 0 | DT563: 0 | DU563: 0 | DV563: 0 | DW563: 0 | DX563: 0 | DY563: 0 | DZ563: 0 | EA563: 0 | EB563: 0 | EC563: 0 | EF563: LTQ30 | EG563: 1 | EH563: 25 | EI563: =EF563&TEXT(EG563,"00")&TEXT(EH563,"00") -> LTQ300125 | EJ563: 0 | EK563: 0 | EL563: 0 | EM563: 0 | EN563: 0 | EO563: 0 | EP563: 0 | EQ563: 0 | ER563: 0 | ES563: 0 | ET563: 0 | EU563: 0 | EV563: 0 | EW563: 0 | EX563: 0 | EY563: 0 | EZ563: 0 | FA563: 0 | FB563: 0 | FC563: 0 | FD563: 0 | FE563: 0 | FF563: 0 | FG563: 0 | FH563: 0 | FI563: 0 | FJ563: 0 | FK563: 0 | FL563: 0 | FM563: 0 | FN563: 0 | FO563: 0 | FP563: 0 | FQ563: 0 | FR563: 0 | FS563: 0 | FT563: 0 | FU563: 0 | FV563: 0 | FW563: 0 | FX563: 0 | FY563: 0 | FZ563: 0 | GA563: 0 | GB563: 0 | GC563: 0 | GD563: 0 | GE563: 0 | GF563: 0 | GG563: 0 | GH563: 0 | GI563: 0 | GJ563: 0 | GK563: 0 | GL563: 0 | GM563: 0 | GN563: 0 | GO563: 0 | GP563: 0 | GQ563: 0 | GR563: 0 | GS563: 0 | GT563: 0 | GU563: 0 | GV563: 0 | GW563: 0 | GX563: 0 | GY563: 0 | GZ563: 0 | HA563: 0 | HB563: 0 | HC563: 0 | HD563: 0 | HE563: 0 | HF563: 507348 | HG563: 0 | HH563: 0 | HI563: 0 | HJ563: 0 | HK563: 0 | HL563: 0 | HM563: 0 | HN563: 0 | HO563: 0 | HP563: 0 | HQ563: 0 | HR563: 0 | HS563: 0 | HT563: 0 | HU563: 0 | HV563: 0 | HW563: 0 | HX563: 0 | HY563: 0 | HZ563: 0 | IA563: 0 | IB563: 0 | IC563: 0 | ID563: 0 | IE563: 0 | IF563: 0 | IG563: 0 | IH563: 0 | II563: 0 | IJ563: 0 | IK563: 0 | IL563: 0 | IM563: 0 | IN563: 0 | IO563: 0 | IP563: 0
S564: LTQ30 | T564: 1 | U564: 26 | V564: =S564&TEXT(T564,"00")&TEXT(U564,"00") -> LTQ300126 | W564: 17329.8 | X564: 34659.6 | Y564: 51989.4 | Z564: 69319.2 | AA564: 86649 | AB564: 103978.8 | AC564: 121308.6 | AD564: 138638.4 | AE564: 155968.2 | AF564: 173298 | AG564: 190627.8 | AH564: 207957.6 | AI564: 225287.4 | AJ564: 242617.2 | AK564: 259947 | AL564: 277276.8 | AM564: 294606.6 | AN564: 311936.4 | AO564: 329266.2 | AP564: 346596 | AQ564: 363925.8 | AR564: 381255.6 | AS564: 398585.4 | AT564: 415915.2 | AU564: 433245 | AV564: 450574.8 | AW564: 467904.6 | AX564: 485234.4 | AY564: 502564.2 | AZ564: 519894 | BA564: 519894 | BB564: 519894 | BC564: 519894 | BD564: 519894 | BE564: 519894 | BF564: 519894 | BG564: 519894 | BH564: 519894 | BI564: 519894 | BJ564: 519894 | BK564: 519894 | BL564: 519894 | BM564: 519894 | BN564: 519894 | BO564: 519894 | BP564: 519894 | BQ564: 519894 | BR564: 519894 | BS564: 519894 | BT564: 519894 | BU564: 519894 | BV564: 519894 | BW564: 519894 | BX564: 519894 | BY564: 519894 | BZ564: 519894 | CA564: 519894 | CB564: 519894 | CC564: 519894 | CD564: 519894 | CE564: 519894 | CF564: 519894 | CG564: 519894 | CH564: 519894 | CI564: 519894 | CJ564: 519894 | CK564: 519894 | CL564: 519894 | CM564: 519894 | CN564: 519894 | CO564: 519894 | CP564: 519894 | CQ564: 519894 | CR564: 519894 | CS564: 0 | CT564: 0 | CU564: 0 | CV564: 0 | CW564: 0 | CX564: 0 | CY564: 0 | CZ564: 0 | DA564: 0 | DB564: 0 | DC564: 0 | DD564: 0 | DE564: 0 | DF564: 0 | DG564: 0 | DH564: 0 | DI564: 0 | DJ564: 0 | DK564: 0 | DL564: 0 | DM564: 0 | DN564: 0 | DO564: 0 | DP564: 0 | DQ564: 0 | DR564: 0 | DS564: 0 | DT564: 0 | DU564: 0 | DV564: 0 | DW564: 0 | DX564: 0 | DY564: 0 | DZ564: 0 | EA564: 0 | EB564: 0 | EC564: 0 | EF564: LTQ30 | EG564: 1 | EH564: 26 | EI564: =EF564&TEXT(EG564,"00")&TEXT(EH564,"00") -> LTQ300126 | EJ564: 0 | EK564: 0 | EL564: 0 | EM564: 0 | EN564: 0 | EO564: 0 | EP564: 0 | EQ564: 0 | ER564: 0 | ES564: 0 | ET564: 0 | EU564: 0 | EV564: 0 | EW564: 0 | EX564: 0 | EY564: 0 | EZ564: 0 | FA564: 0 | FB564: 0 | FC564: 0 | FD564: 0 | FE564: 0 | FF564: 0 | FG564: 0 | FH564: 0 | FI564: 0 | FJ564: 0 | FK564: 0 | FL564: 0 | FM564: 0 | FN564: 0 | FO564: 0 | FP564: 0 | FQ564: 0 | FR564: 0 | FS564: 0 | FT564: 0 | FU564: 0 | FV564: 0 | FW564: 0 | FX564: 0 | FY564: 0 | FZ564: 0 | GA564: 0 | GB564: 0 | GC564: 0 | GD564: 0 | GE564: 0 | GF564: 0 | GG564: 0 | GH564: 0 | GI564: 0 | GJ564: 0 | GK564: 0 | GL564: 0 | GM564: 0 | GN564: 0 | GO564: 0 | GP564: 0 | GQ564: 0 | GR564: 0 | GS564: 0 | GT564: 0 | GU564: 0 | GV564: 0 | GW564: 0 | GX564: 0 | GY564: 0 | GZ564: 0 | HA564: 0 | HB564: 0 | HC564: 0 | HD564: 0 | HE564: 519894 | HF564: 0 | HG564: 0 | HH564: 0 | HI564: 0 | HJ564: 0 | HK564: 0 | HL564: 0 | HM564: 0 | HN564: 0 | HO564: 0 | HP564: 0 | HQ564: 0 | HR564: 0 | HS564: 0 | HT564: 0 | HU564: 0 | HV564: 0 | HW564: 0 | HX564: 0 | HY564: 0 | HZ564: 0 | IA564: 0 | IB564: 0 | IC564: 0 | ID564: 0 | IE564: 0 | IF564: 0 | IG564: 0 | IH564: 0 | II564: 0 | IJ564: 0 | IK564: 0 | IL564: 0 | IM564: 0 | IN564: 0 | IO564: 0 | IP564: 0
... S828: LTQ10 | T828: 2 | U828: 70 | V828: =S828&TEXT(T828,"00")&TEXT(U828,"00") -> LTQ100270 | W828: 352002 | X828: 704004 | Y828: 1056006 | Z828: 1408008 | AA828: 1760010 | AB828: 2112012 | AC828: 2464014 | AD828: 2816016 | AE828: 3168018 | AF828: 3520020 | AG828: 3520020 | AH828: 3520020 | AI828: 3520020 | AJ828: 3520020 | AK828: 3520020 | AL828: 3520020 | AM828: 3520020 | AN828: 3520020 | AO828: 3520020 | AP828: 3520020 | AQ828: 3520020 | AR828: 3520020 | AS828: 3520020 | AT828: 3520020 | AU828: 3520020 | AV828: 3520020 | AW828: 3520020 | AX828: 3520020 | AY828: 3520020 | AZ828: 3520020 | BA828: 0 | BB828: 0 | BC828: 0 | BD828: 0 | BE828: 0 | BF828: 0 | BG828: 0 | BH828: 0 | BI828: 0 | BJ828: 0 | BK828: 0 | BL828: 0 | BM828: 0 | BN828: 0 | BO828: 0 | BP828: 0 | BQ828: 0 | BR828: 0 | BS828: 0 | BT828: 0 | BU828: 0 | BV828: 0 | BW828: 0 | BX828: 0 | BY828: 0 | BZ828: 0 | CA828: 0 | CB828: 0 | CC828: 0 | CD828: 0 | CE828: 0 | CF828: 0 | CG828: 0 | CH828: 0 | CI828: 0 | CJ828: 0 | CK828: 0 | CL828: 0 | CM828: 0 | CN828: 0 | CO828: 0 | CP828: 0 | CQ828: 0 | CR828: 0 | CS828: 0 | CT828: 0 | CU828: 0 | CV828: 0 | CW828: 0 | CX828: 0 | CY828: 0 | CZ828: 0 | DA828: 0 | DB828: 0 | DC828: 0 | DD828: 0 | DE828: 0 | DF828: 0 | DG828: 0 | DH828: 0 | DI828: 0 | DJ828: 0 | DK828: 0 | DL828: 0 | DM828: 0 | DN828: 0 | DO828: 0 | DP828: 0 | DQ828: 0 | DR828: 0 | DS828: 0 | DT828: 0 | DU828: 0 | DV828: 0 | DW828: 0 | DX828: 0 | DY828: 0 | DZ828: 0 | EA828: 0 | EB828: 0 | EC828: 0 | EF828: LTQ10 | EG828: 2 | EH828: 70 | EI828: =EF828&TEXT(EG828,"00")&TEXT(EH828,"00") -> LTQ100270 | EJ828: 0 | EK828: 0 | EL828: 0 | EM828: 0 | EN828: 0 | EO828: 0 | EP828: 0 | EQ828: 0 | ER828: 0 | ES828: 0 | ET828: 0 | EU828: 0 | EV828: 0 | EW828: 0 | EX828: 0 | EY828: 0 | EZ828: 0 | FA828: 0 | FB828: 0 | FC828: 0 | FD828: 0 | FE828: 0 | FF828: 0 | FG828: 0 | FH828: 0 | FI828: 0 | FJ828: 0 | FK828: 0 | FL828: 0 | FM828: 3520020 | FN828: 0 | FO828: 0 | FP828: 0 | FQ828: 0 | FR828: 0 | FS828: 0 | FT828: 0 | FU828: 0 | FV828: 0 | FW828: 0 | FX828: 0 | FY828: 0 | FZ828: 0 | GA828: 0 | GB828: 0 | GC828: 0 | GD828: 0 | GE828: 0 | GF828: 0 | GG828: 0 | GH828: 0 | GI828: 0 | GJ828: 0 | GK828: 0 | GL828: 0 | GM828: 0 | GN828: 0 | GO828: 0 | GP828: 0 | GQ828: 0 | GR828: 0 | GS828: 0 | GT828: 0 | GU828: 0 | GV828: 0 | GW828: 0 | GX828: 0 | GY828: 0 | GZ828: 0 | HA828: 0 | HB828: 0 | HC828: 0 | HD828: 0 | HE828: 0 | HF828: 0 | HG828: 0 | HH828: 0 | HI828: 0 | HJ828: 0 | HK828: 0 | HL828: 0 | HM828: 0 | HN828: 0 | HO828: 0 | HP828: 0 | HQ828: 0 | HR828: 0 | HS828: 0 | HT828: 0 | HU828: 0 | HV828: 0 | HW828: 0 | HX828: 0 | HY828: 0 | HZ828: 0 | IA828: 0 | IB828: 0 | IC828: 0 | ID828: 0 | IE828: 0 | IF828: 0 | IG828: 0 | IH828: 0 | II828: 0 | IJ828: 0 | IK828: 0 | IL828: 0 | IM828: 0 | IN828: 0 | IO828: 0 | IP828: 0
R831: PVFB | S831: 含 | T831: 1051130 | V831: =S831&TEXT(T831,"00")&TEXT(U831,"00") -> 含105113000 | EE831: PVFB0 | EF831: 領後 | EG831: 1051128 | EI831: =EF831&TEXT(EG831,"00")&TEXT(EH831,"00") -> 領後105112800
R832: 版次 | S832: 商品代號 | T832: 性別 | U832: 年齡 | EE832: 版次 | EF832: 商品代號 | EG832: 性別 | EH832: 年齡
R987: tbPV0(期初保價金)_領後(不含生存金) | V987: =S987&TEXT(T987,"00")&TEXT(U987,"00") -> 0000 | EE987: PV | EI987: =EF987&TEXT(EG987,"00")&TEXT(EH987,"00") -> 0000
EE988: 版次 | EF988: 商品代號 | EG988: 性別 | EH988: 年齡
R1162: tbHEALTH1 | V1162: =S1162&TEXT(T1162,"00")&TEXT(U1162,"00") -> 0000 | EE1162: tbHEALTH2 | EI1162: =EF1162&TEXT(EG1162,"00")&TEXT(EH1162,"00") -> 0000
R1163: 版次 | S1163: InsuranceReverseName | T1163: Gender | U1163: Age | V1163: =S1163&TEXT(T1163,"00")&TEXT(U1163,"00") -> InsuranceReverseNameGenderAge | W1163: HEALTH1 | X1163: HEALTH2 | Y1163: HEALTH3 | Z1163: HEALTH4 | AA1163: HEALTH5 | AB1163: HEALTH6 | AC1163: HEALTH7 | AD1163: HEALTH8 | AE1163: HEALTH9 | AF1163: HEALTH10 | AG1163: HEALTH11 | AH1163: HEALTH12 | AI1163: HEALTH13 | AJ1163: HEALTH14 | AK1163: HEALTH15 | AL1163: HEALTH16 | AM1163: HEALTH17 | AN1163: HEALTH18 | AO1163: HEALTH19 | AP1163: HEALTH20 | AQ1163: HEALTH21 | AR1163: HEALTH22 | AS1163: HEALTH23 | AT1163: HEALTH24 | AU1163: HEALTH25 | AV1163: HEALTH26 | AW1163: HEALTH27 | AX1163: HEALTH28 | AY1163: HEALTH29 | AZ1163: HEALTH30 | BA1163: HEALTH31 | BB1163: HEALTH32 | BC1163: HEALTH33 | BD1163: HEALTH34 | BE1163: HEALTH35 | BF1163: HEALTH36 | BG1163: HEALTH37 | BH1163: HEALTH38 | BI1163: HEALTH39 | BJ1163: HEALTH40 | BK1163: HEALTH41 | BL1163: HEALTH42 | BM1163: HEALTH43 | BN1163: HEALTH44 | BO1163: HEALTH45 | BP1163: HEALTH46 | BQ1163: HEALTH47 | BR1163: HEALTH48 | BS1163: HEALTH49 | BT1163: HEALTH50 | BU1163: HEALTH51 | BV1163: HEALTH52 | BW1163: HEALTH53 | BX1163: HEALTH54 | BY1163: HEALTH55 | BZ1163: HEALTH56 | CA1163: HEALTH57 | CB1163: HEALTH58 | CC1163: HEALTH59 | CD1163: HEALTH60 | CE1163: HEALTH61 | CF1163: HEALTH62 | CG1163: HEALTH63 | CH1163: HEALTH64 | CI1163: HEALTH65 | CJ1163: HEALTH66 | CK1163: HEALTH67 | CL1163: HEALTH68 | CM1163: HEALTH69 | CN1163: HEALTH70 | CO1163: HEALTH71 | CP1163: HEALTH72 | CQ1163: HEALTH73 | CR1163: HEALTH74 | CS1163: HEALTH75 | CT1163: HEALTH76 | CU1163: HEALTH77 | CV1163: HEALTH78 | CW1163: HEALTH79 | CX1163: HEALTH80 | CY1163: HEALTH81 | CZ1163: HEALTH82 | DA1163: HEALTH83 | DB1163: HEALTH84 | DC1163: HEALTH85 | DD1163: HEALTH86 | DE1163: HEALTH87 | DF1163: HEALTH88 | DG1163: HEALTH89 | DH1163: HEALTH90 | DI1163: HEALTH91 | DJ1163: HEALTH92 | DK1163: HEALTH93 | DL1163: HEALTH94 | DM1163: HEALTH95 | DN1163: HEALTH96 | DO1163: HEALTH97 | DP1163: HEALTH98 | DQ1163: HEALTH99 | DR1163: HEALTH100 | DS1163: HEALTH101 | DT1163: HEALTH102 | DU1163: HEALTH103 | DV1163: HEALTH104 | DW1163: HEALTH105 | DX1163: HEALTH106 | DY1163: HEALTH107 | DZ1163: HEALTH108 | EA1163: HEALTH109 | EB1163: HEALTH110 | EC1163: HEALTH111 | EE1163: 版次 | EF1163: InsuranceReverseName | EG1163: Gender | EH1163: Age | EI1163: =EF1163&TEXT(EG1163,"00")&TEXT(EH1163,"00") -> InsuranceReverseNameGenderAge | EJ1163: HEALTH1 | EK1163: HEALTH2 | EL1163: HEALTH3 | EM1163: HEALTH4 | EN1163: HEALTH5 | EO1163: HEALTH6 | EP1163: HEALTH7 | EQ1163: HEALTH8 | ER1163: HEALTH9 | ES1163: HEALTH10 | ET1163: HEALTH11 | EU1163: HEALTH12 | EV1163: HEALTH13 | EW1163: HEALTH14 | EX1163: HEALTH15 | EY1163: HEALTH16 | EZ1163: HEALTH17 | FA1163: HEALTH18 | FB1163: HEALTH19 | FC1163: HEALTH20 | FD1163: HEALTH21 | FE1163: HEALTH22 | FF1163: HEALTH23 | FG1163: HEALTH24 | FH1163: HEALTH25 | FI1163: HEALTH26 | FJ1163: HEALTH27 | FK1163: HEALTH28 | FL1163: HEALTH29 | FM1163: HEALTH30 | FN1163: HEALTH31 | FO1163: HEALTH32 | FP1163: HEALTH33 | FQ1163: HEALTH34 | FR1163: HEALTH35 | FS1163: HEALTH36 | FT1163: HEALTH37 | FU1163: HEALTH38 | FV1163: HEALTH39 | FW1163: HEALTH40 | FX1163: HEALTH41 | FY1163: HEALTH42 | FZ1163: HEALTH43 | GA1163: HEALTH44 | GB1163: HEALTH45 | GC1163: HEALTH46 | GD1163: HEALTH47 | GE1163: HEALTH48 | GF1163: HEALTH49 | GG1163: HEALTH50 | GH1163: HEALTH51 | GI1163: HEALTH52 | GJ1163: HEALTH53 | GK1163: HEALTH54 | GL1163: HEALTH55 | GM1163: HEALTH56 | GN1163: HEALTH57 | GO1163: HEALTH58 | GP1163: HEALTH59 | GQ1163: HEALTH60 | GR1163: HEALTH61 | GS1163: HEALTH62 | GT1163: HEALTH63 | GU1163: HEALTH64 | GV1163: HEALTH65 | GW1163: HEALTH66 | GX1163: HEALTH67 | GY1163: HEALTH68 | GZ1163: HEALTH69 | HA1163: HEALTH70 | HB1163: HEALTH71 | HC1163: HEALTH72 | HD1163: HEALTH73 | HE1163: HEALTH74 | HF1163: HEALTH75 | HG1163: HEALTH76 | HH1163: HEALTH77 | HI1163: HEALTH78 | HJ1163: HEALTH79 | HK1163: HEALTH80 | HL1163: HEALTH81 | HM1163: HEALTH82 | HN1163: HEALTH83 | HO1163: HEALTH84 | HP1163: HEALTH85 | HQ1163: HEALTH86 | HR1163: HEALTH87 | HS1163: HEALTH88 | HT1163: HEALTH89 | HU1163: HEALTH90 | HV1163: HEALTH91 | HW1163: HEALTH92 | HX1163: HEALTH93 | HY1163: HEALTH94 | HZ1163: HEALTH95 | IA1163: HEALTH96 | IB1163: HEALTH97 | IC1163: HEALTH98 | ID1163: HEALTH99 | IE1163: HEALTH100 | IF1163: HEALTH101 | IG1163: HEALTH102 | IH1163: HEALTH103 | II1163: HEALTH104 | IJ1163: HEALTH105 | IK1163: HEALTH106 | IL1163: HEALTH107 | IM1163: HEALTH108 | IN1163: HEALTH109 | IO1163: HEALTH110 | IP1163: HEALTH111

Sheet RDATA
A1: =OP!$C$22 -> LTQ | B1: =IF($F$2>0,1,"") | G1: 1 | H1: =IF(H2<>A2&A1,"富邦人壽官網尚未公告"&A2&"宣告利率，目前使用"&LEFT($H$2,8)&"宣告利率，試算當月宣告利率以富邦人壽官網公告為準。","") -> 富邦人壽官網尚未公告115 / 8 宣告利率，目前使用宣告利率，試算當月宣告利率以富邦人壽官網公告為準。 | I1: =IF(H1="",1,"")
A2: =YEAR(TODAY())-1911&" / "&MONTH(TODAY())&" " -> 115 / 8 | D2: key | E2: 宣告利率 | F2: =SUM($F$3:$F$200) -> 0 | G2: 1 | I2: =IF(OP!$C$3<J2,K2,L2) -> 0.0175 | J2: 46023 | K2: 0.0175 | L2: 0.0175
B3: =IF(OR(D3="",D3=0,RIGHT(D3,LEN($A$1))<>$A$1),,(LEFT($D3,3)*100)+MID($D3,7,IF(OR(AND(LEN($A$1)=3,LEN($D3)=12),AND(LEN($A$1)=4,LEN($D3)=13)),2,1))*1) -> 0 | C3: =IF($B3=0,,RANK($B3,$B$3:$B$78)) -> 0 | F3: =IF(AND(RIGHT($D3,LEN($A$1))<>$A$1,$D3<>""),1,0) -> 0 | G3: 2 | H3: =IF(ISNA(VLOOKUP($G3,$C:$E,2,0)),"",VLOOKUP($G3,$C:$E,2,0)) | I3: =IF(ISNA(VLOOKUP($G3,$C:$E,3,0)),"",VLOOKUP($G3,$C:$E,3,0)) | J3: 45658 | K3: 0.0162 | L3: 0.0175
A4: =COUNTIF($D:$D,$A$3) -> 0 | B4: =IF(OR(D4="",D4=0,RIGHT(D4,LEN($A$1))<>$A$1),,(LEFT($D4,3)*100)+MID($D4,7,IF(OR(AND(LEN($A$1)=3,LEN($D4)=12),AND(LEN($A$1)=4,LEN($D4)=13)),2,1))*1) -> 0 | C4: =IF($B4=0,,RANK($B4,$B$3:$B$78)) -> 0 | F4: =IF(AND(RIGHT($D4,LEN($A$1))<>$A$1,$D4<>""),1,0) -> 0 | G4: 3 | H4: =IF(ISNA(VLOOKUP($G4,$C:$E,2,0)),"",VLOOKUP($G4,$C:$E,2,0)) | I4: =IF(ISNA(VLOOKUP($G4,$C:$E,3,0)),"",VLOOKUP($G4,$C:$E,3,0)) | J4: 45292 | K4: 0.015 | L4: 0.0162
B5: =IF(OR(D5="",D5=0,RIGHT(D5,LEN($A$1))<>$A$1),,(LEFT($D5,3)*100)+MID($D5,7,IF(OR(AND(LEN($A$1)=3,LEN($D5)=12),AND(LEN($A$1)=4,LEN($D5)=13)),2,1))*1) -> 0 | C5: =IF($B5=0,,RANK($B5,$B$3:$B$78)) -> 0 | F5: =IF(AND(RIGHT($D5,LEN($A$1))<>$A$1,$D5<>""),1,0) -> 0 | G5: 4 | H5: =IF(ISNA(VLOOKUP($G5,$C:$E,2,0)),"",VLOOKUP($G5,$C:$E,2,0)) | I5: =IF(ISNA(VLOOKUP($G5,$C:$E,3,0)),"",VLOOKUP($G5,$C:$E,3,0))
B6: =IF(OR(D6="",D6=0,RIGHT(D6,LEN($A$1))<>$A$1),,(LEFT($D6,3)*100)+MID($D6,7,IF(OR(AND(LEN($A$1)=3,LEN($D6)=12),AND(LEN($A$1)=4,LEN($D6)=13)),2,1))*1) -> 0 | C6: =IF($B6=0,,RANK($B6,$B$3:$B$78)) -> 0 | F6: =IF(AND(RIGHT($D6,LEN($A$1))<>$A$1,$D6<>""),1,0) -> 0 | G6: 5 | H6: =IF(ISNA(VLOOKUP($G6,$C:$E,2,0)),"",VLOOKUP($G6,$C:$E,2,0)) | I6: =IF(ISNA(VLOOKUP($G6,$C:$E,3,0)),"",VLOOKUP($G6,$C:$E,3,0))
B7: =IF(OR(D7="",D7=0,RIGHT(D7,LEN($A$1))<>$A$1),,(LEFT($D7,3)*100)+MID($D7,7,IF(OR(AND(LEN($A$1)=3,LEN($D7)=12),AND(LEN($A$1)=4,LEN($D7)=13)),2,1))*1) -> 0 | C7: =IF($B7=0,,RANK($B7,$B$3:$B$78)) -> 0 | F7: =IF(AND(RIGHT($D7,LEN($A$1))<>$A$1,$D7<>""),1,0) -> 0 | G7: 6 | H7: =IF(ISNA(VLOOKUP($G7,$C:$E,2,0)),"",VLOOKUP($G7,$C:$E,2,0)) | I7: =IF(ISNA(VLOOKUP($G7,$C:$E,3,0)),"",VLOOKUP($G7,$C:$E,3,0))
B8: =IF(OR(D8="",D8=0,RIGHT(D8,LEN($A$1))<>$A$1),,(LEFT($D8,3)*100)+MID($D8,7,IF(OR(AND(LEN($A$1)=3,LEN($D8)=12),AND(LEN($A$1)=4,LEN($D8)=13)),2,1))*1) -> 0 | C8: =IF($B8=0,,RANK($B8,$B$3:$B$78)) -> 0 | F8: =IF(AND(RIGHT($D8,LEN($A$1))<>$A$1,$D8<>""),1,0) -> 0 | G8: 7 | H8: =IF(ISNA(VLOOKUP($G8,$C:$E,2,0)),"",VLOOKUP($G8,$C:$E,2,0)) | I8: =IF(ISNA(VLOOKUP($G8,$C:$E,3,0)),"",VLOOKUP($G8,$C:$E,3,0))
B9: =IF(OR(D9="",D9=0,RIGHT(D9,LEN($A$1))<>$A$1),,(LEFT($D9,3)*100)+MID($D9,7,IF(OR(AND(LEN($A$1)=3,LEN($D9)=12),AND(LEN($A$1)=4,LEN($D9)=13)),2,1))*1) -> 0 | C9: =IF($B9=0,,RANK($B9,$B$3:$B$78)) -> 0 | F9: =IF(AND(RIGHT($D9,LEN($A$1))<>$A$1,$D9<>""),1,0) -> 0 | G9: 8 | H9: =IF(ISNA(VLOOKUP($G9,$C:$E,2,0)),"",VLOOKUP($G9,$C:$E,2,0)) | I9: =IF(ISNA(VLOOKUP($G9,$C:$E,3,0)),"",VLOOKUP($G9,$C:$E,3,0))
B10: =IF(OR(D10="",D10=0,RIGHT(D10,LEN($A$1))<>$A$1),,(LEFT($D10,3)*100)+MID($D10,7,IF(OR(AND(LEN($A$1)=3,LEN($D10)=12),AND(LEN($A$1)=4,LEN($D10)=13)),2,1))*1) -> 0 | C10: =IF($B10=0,,RANK($B10,$B$3:$B$78)) -> 0 | F10: =IF(AND(RIGHT($D10,LEN($A$1))<>$A$1,$D10<>""),1,0) -> 0 | G10: 9 | H10: =IF(ISNA(VLOOKUP($G10,$C:$E,2,0)),"",VLOOKUP($G10,$C:$E,2,0)) | I10: =IF(ISNA(VLOOKUP($G10,$C:$E,3,0)),"",VLOOKUP($G10,$C:$E,3,0))
B11: =IF(OR(D11="",D11=0,RIGHT(D11,LEN($A$1))<>$A$1),,(LEFT($D11,3)*100)+MID($D11,7,IF(OR(AND(LEN($A$1)=3,LEN($D11)=12),AND(LEN($A$1)=4,LEN($D11)=13)),2,1))*1) -> 0 | C11: =IF($B11=0,,RANK($B11,$B$3:$B$78)) -> 0 | F11: =IF(AND(RIGHT($D11,LEN($A$1))<>$A$1,$D11<>""),1,0) -> 0 | G11: 10 | H11: =IF(ISNA(VLOOKUP($G11,$C:$E,2,0)),"",VLOOKUP($G11,$C:$E,2,0)) | I11: =IF(ISNA(VLOOKUP($G11,$C:$E,3,0)),"",VLOOKUP($G11,$C:$E,3,0))
B12: =IF(OR(D12="",D12=0,RIGHT(D12,LEN($A$1))<>$A$1),,(LEFT($D12,3)*100)+MID($D12,7,IF(OR(AND(LEN($A$1)=3,LEN($D12)=12),AND(LEN($A$1)=4,LEN($D12)=13)),2,1))*1) -> 0 | C12: =IF($B12=0,,RANK($B12,$B$3:$B$78)) -> 0 | F12: =IF(AND(RIGHT($D12,LEN($A$1))<>$A$1,$D12<>""),1,0) -> 0 | G12: 11 | H12: =IF(ISNA(VLOOKUP($G12,$C:$E,2,0)),"",VLOOKUP($G12,$C:$E,2,0)) | I12: =IF(ISNA(VLOOKUP($G12,$C:$E,3,0)),"",VLOOKUP($G12,$C:$E,3,0))
B13: =IF(OR(D13="",D13=0,RIGHT(D13,LEN($A$1))<>$A$1),,(LEFT($D13,3)*100)+MID($D13,7,IF(OR(AND(LEN($A$1)=3,LEN($D13)=12),AND(LEN($A$1)=4,LEN($D13)=13)),2,1))*1) -> 0 | C13: =IF($B13=0,,RANK($B13,$B$3:$B$78)) -> 0 | F13: =IF(AND(RIGHT($D13,LEN($A$1))<>$A$1,$D13<>""),1,0) -> 0 | G13: 12 | H13: =IF(ISNA(VLOOKUP($G13,$C:$E,2,0)),"",VLOOKUP($G13,$C:$E,2,0)) | I13: =IF(ISNA(VLOOKUP($G13,$C:$E,3,0)),"",VLOOKUP($G13,$C:$E,3,0))
B14: =IF(OR(D14="",D14=0,RIGHT(D14,LEN($A$1))<>$A$1),,(LEFT($D14,3)*100)+MID($D14,7,IF(OR(AND(LEN($A$1)=3,LEN($D14)=12),AND(LEN($A$1)=4,LEN($D14)=13)),2,1))*1) -> 0 | C14: =IF($B14=0,,RANK($B14,$B$3:$B$78)) -> 0 | F14: =IF(AND(RIGHT($D14,LEN($A$1))<>$A$1,$D14<>""),1,0) -> 0 | G14: 13 | H14: =IF(ISNA(VLOOKUP($G14,$C:$E,2,0)),"",VLOOKUP($G14,$C:$E,2,0)) | I14: =IF(ISNA(VLOOKUP($G14,$C:$E,3,0)),"",VLOOKUP($G14,$C:$E,3,0))
B15: =IF(OR(D15="",D15=0,RIGHT(D15,LEN($A$1))<>$A$1),,(LEFT($D15,3)*100)+MID($D15,7,IF(OR(AND(LEN($A$1)=3,LEN($D15)=12),AND(LEN($A$1)=4,LEN($D15)=13)),2,1))*1) -> 0 | C15: =IF($B15=0,,RANK($B15,$B$3:$B$78)) -> 0 | F15: =IF(AND(RIGHT($D15,LEN($A$1))<>$A$1,$D15<>""),1,0) -> 0 | G15: 14 | H15: =IF(ISNA(VLOOKUP($G15,$C:$E,2,0)),"",VLOOKUP($G15,$C:$E,2,0)) | I15: =IF(ISNA(VLOOKUP($G15,$C:$E,3,0)),"",VLOOKUP($G15,$C:$E,3,0))
B16: =IF(OR(D16="",D16=0,RIGHT(D16,LEN($A$1))<>$A$1),,(LEFT($D16,3)*100)+MID($D16,7,IF(OR(AND(LEN($A$1)=3,LEN($D16)=12),AND(LEN($A$1)=4,LEN($D16)=13)),2,1))*1) -> 0 | C16: =IF($B16=0,,RANK($B16,$B$3:$B$78)) -> 0 | F16: =IF(AND(RIGHT($D16,LEN($A$1))<>$A$1,$D16<>""),1,0) -> 0 | G16: 15 | H16: =IF(ISNA(VLOOKUP($G16,$C:$E,2,0)),"",VLOOKUP($G16,$C:$E,2,0)) | I16: =IF(ISNA(VLOOKUP($G16,$C:$E,3,0)),"",VLOOKUP($G16,$C:$E,3,0))
... B25: =IF(OR(D25="",D25=0,RIGHT(D25,LEN($A$1))<>$A$1),,(LEFT($D25,3)*100)+MID($D25,7,IF(OR(AND(LEN($A$1)=3,LEN($D25)=12),AND(LEN($A$1)=4,LEN($D25)=13)),2,1))*1) -> 0 | C25: =IF($B25=0,,RANK($B25,$B$3:$B$78)) -> 0 | F25: =IF(AND(RIGHT($D25,LEN($A$1))<>$A$1,$D25<>""),1,0) -> 0 | G25: 24 | H25: =IF(ISNA(VLOOKUP($G25,$C:$E,2,0)),"",VLOOKUP($G25,$C:$E,2,0)) | I25: =IF(ISNA(VLOOKUP($G25,$C:$E,3,0)),"",VLOOKUP($G25,$C:$E,3,0))
B26: =IF(OR(D26="",D26=0,RIGHT(D26,LEN($A$1))<>$A$1),,(LEFT($D26,3)*100)+MID($D26,7,IF(OR(AND(LEN($A$1)=3,LEN($D26)=12),AND(LEN($A$1)=4,LEN($D26)=13)),2,1))*1) -> 0 | C26: =IF($B26=0,,RANK($B26,$B$3:$B$78)) -> 0 | F26: =IF(AND(RIGHT($D26,LEN($A$1))<>$A$1,$D26<>""),1,0) -> 0
B27: =IF(OR(D27="",D27=0,RIGHT(D27,LEN($A$1))<>$A$1),,(LEFT($D27,3)*100)+MID($D27,7,IF(OR(AND(LEN($A$1)=3,LEN($D27)=12),AND(LEN($A$1)=4,LEN($D27)=13)),2,1))*1) -> 0 | C27: =IF($B27=0,,RANK($B27,$B$3:$B$78)) -> 0 | F27: =IF(AND(RIGHT($D27,LEN($A$1))<>$A$1,$D27<>""),1,0) -> 0 | H27: MAX | I27: =MAX(I2:I26) -> 0.0175
B28: =IF(OR(D28="",D28=0,RIGHT(D28,LEN($A$1))<>$A$1),,(LEFT($D28,3)*100)+MID($D28,7,IF(OR(AND(LEN($A$1)=3,LEN($D28)=12),AND(LEN($A$1)=4,LEN($D28)=13)),2,1))*1) -> 0 | C28: =IF($B28=0,,RANK($B28,$B$3:$B$78)) -> 0 | F28: =IF(AND(RIGHT($D28,LEN($A$1))<>$A$1,$D28<>""),1,0) -> 0
B29: =IF(OR(D29="",D29=0,RIGHT(D29,LEN($A$1))<>$A$1),,(LEFT($D29,3)*100)+MID($D29,7,IF(OR(AND(LEN($A$1)=3,LEN($D29)=12),AND(LEN($A$1)=4,LEN($D29)=13)),2,1))*1) -> 0 | C29: =IF($B29=0,,RANK($B29,$B$3:$B$78)) -> 0 | F29: =IF(AND(RIGHT($D29,LEN($A$1))<>$A$1,$D29<>""),1,0) -> 0
B30: =IF(OR(D30="",D30=0,RIGHT(D30,LEN($A$1))<>$A$1),,(LEFT($D30,3)*100)+MID($D30,7,IF(OR(AND(LEN($A$1)=3,LEN($D30)=12),AND(LEN($A$1)=4,LEN($D30)=13)),2,1))*1) -> 0 | C30: =IF($B30=0,,RANK($B30,$B$3:$B$78)) -> 0 | F30: =IF(AND(RIGHT($D30,LEN($A$1))<>$A$1,$D30<>""),1,0) -> 0
B31: =IF(OR(D31="",D31=0,RIGHT(D31,LEN($A$1))<>$A$1),,(LEFT($D31,3)*100)+MID($D31,7,IF(OR(AND(LEN($A$1)=3,LEN($D31)=12),AND(LEN($A$1)=4,LEN($D31)=13)),2,1))*1) -> 0 | C31: =IF($B31=0,,RANK($B31,$B$3:$B$78)) -> 0 | F31: =IF(AND(RIGHT($D31,LEN($A$1))<>$A$1,$D31<>""),1,0) -> 0
B32: =IF(OR(D32="",D32=0,RIGHT(D32,LEN($A$1))<>$A$1),,(LEFT($D32,3)*100)+MID($D32,7,IF(OR(AND(LEN($A$1)=3,LEN($D32)=12),AND(LEN($A$1)=4,LEN($D32)=13)),2,1))*1) -> 0 | C32: =IF($B32=0,,RANK($B32,$B$3:$B$78)) -> 0 | F32: =IF(AND(RIGHT($D32,LEN($A$1))<>$A$1,$D32<>""),1,0) -> 0
B33: =IF(OR(D33="",D33=0,RIGHT(D33,LEN($A$1))<>$A$1),,(LEFT($D33,3)*100)+MID($D33,7,IF(OR(AND(LEN($A$1)=3,LEN($D33)=12),AND(LEN($A$1)=4,LEN($D33)=13)),2,1))*1) -> 0 | C33: =IF($B33=0,,RANK($B33,$B$3:$B$78)) -> 0 | F33: =IF(AND(RIGHT($D33,LEN($A$1))<>$A$1,$D33<>""),1,0) -> 0
B34: =IF(OR(D34="",D34=0,RIGHT(D34,LEN($A$1))<>$A$1),,(LEFT($D34,3)*100)+MID($D34,7,IF(OR(AND(LEN($A$1)=3,LEN($D34)=12),AND(LEN($A$1)=4,LEN($D34)=13)),2,1))*1) -> 0 | C34: =IF($B34=0,,RANK($B34,$B$3:$B$78)) -> 0 | F34: =IF(AND(RIGHT($D34,LEN($A$1))<>$A$1,$D34<>""),1,0) -> 0
B35: =IF(OR(D35="",D35=0,RIGHT(D35,LEN($A$1))<>$A$1),,(LEFT($D35,3)*100)+MID($D35,7,IF(OR(AND(LEN($A$1)=3,LEN($D35)=12),AND(LEN($A$1)=4,LEN($D35)=13)),2,1))*1) -> 0 | C35: =IF($B35=0,,RANK($B35,$B$3:$B$78)) -> 0 | F35: =IF(AND(RIGHT($D35,LEN($A$1))<>$A$1,$D35<>""),1,0) -> 0
B36: =IF(OR(D36="",D36=0,RIGHT(D36,LEN($A$1))<>$A$1),,(LEFT($D36,3)*100)+MID($D36,7,IF(OR(AND(LEN($A$1)=3,LEN($D36)=12),AND(LEN($A$1)=4,LEN($D36)=13)),2,1))*1) -> 0 | C36: =IF($B36=0,,RANK($B36,$B$3:$B$78)) -> 0 | F36: =IF(AND(RIGHT($D36,LEN($A$1))<>$A$1,$D36<>""),1,0) -> 0
B37: =IF(OR(D37="",D37=0,RIGHT(D37,LEN($A$1))<>$A$1),,(LEFT($D37,3)*100)+MID($D37,7,IF(OR(AND(LEN($A$1)=3,LEN($D37)=12),AND(LEN($A$1)=4,LEN($D37)=13)),2,1))*1) -> 0 | C37: =IF($B37=0,,RANK($B37,$B$3:$B$78)) -> 0 | F37: =IF(AND(RIGHT($D37,LEN($A$1))<>$A$1,$D37<>""),1,0) -> 0
B38: =IF(OR(D38="",D38=0,RIGHT(D38,LEN($A$1))<>$A$1),,(LEFT($D38,3)*100)+MID($D38,7,IF(OR(AND(LEN($A$1)=3,LEN($D38)=12),AND(LEN($A$1)=4,LEN($D38)=13)),2,1))*1) -> 0 | C38: =IF($B38=0,,RANK($B38,$B$3:$B$78)) -> 0 | F38: =IF(AND(RIGHT($D38,LEN($A$1))<>$A$1,$D38<>""),1,0) -> 0
B39: =IF(OR(D39="",D39=0,RIGHT(D39,LEN($A$1))<>$A$1),,(LEFT($D39,3)*100)+MID($D39,7,IF(OR(AND(LEN($A$1)=3,LEN($D39)=12),AND(LEN($A$1)=4,LEN($D39)=13)),2,1))*1) -> 0 | C39: =IF($B39=0,,RANK($B39,$B$3:$B$78)) -> 0 | F39: =IF(AND(RIGHT($D39,LEN($A$1))<>$A$1,$D39<>""),1,0) -> 0
... B200: =IF(OR(D200="",D200=0,RIGHT(D200,LEN($A$1))<>$A$1),,(LEFT($D200,3)*100)+MID($D200,7,IF(OR(AND(LEN($A$1)=3,LEN($D200)=12),AND(LEN($A$1)=4,LEN($D200)=13)),2,1))*1) -> 0 | C200: =IF($B200=0,,RANK($B200,$B$3:$B$78)) -> 0 | F200: =IF(AND(RIGHT($D200,LEN($A$1))<>$A$1,$D200<>""),1,0) -> 0

Sheet PY
B2: 轉換金額 | C2: 10000
C3: 分期 | D3: ㄧ次
B4: 指定保險金比例： | C4: =MIN(1,ROUND(OP!$C$141,2)) -> 0 | D4: =1-C4 -> 1 | F4: 年 | G4: 1
B5: 分期最低金額 | C5: =$C$38 -> 20000 | D5: =$D$38 -> 200000 | F5: 半年 | G5: 2
B6: 分期定期保險金給付期間： | C6: =OP!$C$142 -> 10 | F6: 季 | G6: 4
B7: 假設分期定期保險金預定利率： | C7: =$B$30 -> 0.02 | F7: 月 | G7: 12
B8: 期別 | C8: 年 | D8: =VLOOKUP($C$8,$F$4:$G$7,2,0) -> 1
B10: 精算公式→ | C10: =IF(C6=0,,C2*(C7*(1/(1+C7)))/(1-(1/(1+C7))^C6)) -> 1091.4365 | D10: ←精算換算比例(每萬元)
C11: =C10/10000 -> 0.10914365 | D11: ←帶入換算比例(每元)
B15: 定期定額-本利攤還
B16: 給付金額/每期 | C16: =ROUND(PMT($C$7/$D$8,$C$6*$D$8,-$C$2*$C$4,,1),0) -> 0
B17: 給付總額 | C17: =C16*C6*D8 -> 0
B18: 給付比例 | C18: =PMT($C$7/$D$8,$C$6*$D$8,-$C$2,,1)/C2 -> 0.10914365 | D18: ←自行計算換算比例
B20: 定額不定期
B21: 給付金額/每期 | C21: 550 | D21: ←帶入期付金額
B22: 給付總額 | C22: =C21*(($C$26*$D$8)+$C$27) -> 12100
B23: 給付比例 | C23: =$C$21/($C$2/$C$4) -> #DIV/0!
B24: 給付次數 | C24: =NPER($C$7/$D$8,$C$21,-$C$2,0,1) -> 22.261841
B25: 剩餘金額 | C25: =ROUND(C21*($C$24-ROUNDDOWN($C$24,0)),0) -> 144
B26: 給付年次 | C26: =ROUNDDOWN(ROUNDDOWN($C$24,0)/$D$8,0) -> 22 | D26: ←自行計算給付年月數
B27: ="給付"&C8&"次" -> 給付年次 | C27: =ROUNDDOWN($C$24,0)-($C$26*$D$8) -> 0 | D27: ="EX："&$C$26&" 年 "&IF($C$27=0,"",C27&" "&$C$8) -> EX：22 年
B29: 台幣=1，美元=2，澳幣=3 | C29: =OP!$C$21 -> 1 | D29: 新臺幣 | E29: ←設定幣別
B30: =IF($C$29=1,$C$31,IF($C$29=2,$D$31,$E$31)) -> 0.02 | C30: 台幣(1) | D30: 美元(2) | E30: 澳幣(3)
C31: 0.02 | D31: 0.025 | E31: 0.0275
B37: 分期低額 | C37: 每期 | D37: 指定
B38: =$C$29 -> 1 | C38: =VLOOKUP(B38,$B$39:$D$40,2,0) -> 20000 | D38: =VLOOKUP(B38,$B$39:$D$40,3,0) -> 200000
B39: 2 | C39: 3000 | D39: 30000 | E39: =NUMBERSTRING(IF(C39/10000<1,C39/1000,C39/10000),3)&RIGHT(NUMBERSTRING(C39,1),1) -> 三千 | F39: =NUMBERSTRING(IF(D39/10000<1,D39/1000,D39/10000),1)&RIGHT(NUMBERSTRING(D39,2),1) -> 三萬
B40: 1 | C40: 20000 | D40: 200000 | E40: =NUMBERSTRING(IF(C40/10000<1,C40/1000,C40/10000),3)&RIGHT(NUMBERSTRING(C40,2),1) -> 二萬 | F40: =NUMBERSTRING(IF(D40/10000<1,D40/1000,D40/10000),1)&RIGHT(NUMBERSTRING(D40,2),1) -> 二十萬
B41: 3 | C41: 3000 | D41: 30000 | E41: =NUMBERSTRING(IF(C41/10000<1,C41/1000,C41/10000),3)&RIGHT(NUMBERSTRING(C41,1),1) -> 三千 | F41: =NUMBERSTRING(IF(D41/10000<1,D41/1000,D41/10000),1)&RIGHT(NUMBERSTRING(D41,2),1) -> 三萬
B42: 4 | E42: =NUMBERSTRING(IF(C42/10000<1,C42/1000,C42/10000),3)&RIGHT(NUMBERSTRING(C42,2),1) -> ○零 | F42: =NUMBERSTRING(IF(D42/10000<1,D42/1000,D42/10000),1)&RIGHT(NUMBERSTRING(D42,2),1) -> ○零
B43: =IF(OR(AND($D$29=$B$45,$C$29<>1),ISERROR(VLOOKUP($D$29,$B$45:$D$48,3,0))),"商品幣別設定錯誤",VLOOKUP($D$29,$B$45:$D$48,3,0)) -> 二十萬元或每年給付之分期定期保險金低於二萬元者， | C43: =IF(OR(AND($D$29=$B$45,$C$29<>1),ISERROR(VLOOKUP($D$29,$B$45:$D$48,3,0))),1,0) -> 0
B45: 新臺幣 | C45: 1 | D45: =VLOOKUP($C$45,$B$39:$F$42,5,0)&"元"&"或每年給付之分期定期保險金低於"&VLOOKUP($C$45,$B$39:$F$42,4,0)&"元"&"者，" -> 二十萬元或每年給付之分期定期保險金低於二萬元者，
B46: 美元 | C46: 2 | D46: =VLOOKUP($C$46,$B$39:$F$42,5,0)&$B$46&"或每年給付之分期定期保險金低於"&VLOOKUP($C$46,$B$39:$F$42,4,0)&$B$46&"者，" -> 三萬美元或每年給付之分期定期保險金低於三千美元者，
B47: 澳幣 | C47: 3 | D47: =VLOOKUP($C$47,$B$39:$F$42,5,0)&$B$47&"或每年給付之分期定期保險金低於"&VLOOKUP($C$47,$B$39:$F$42,4,0)&$B$47&"者，" -> 三萬澳幣或每年給付之分期定期保險金低於三千澳幣者，
B48: 人民幣 | C48: 4 | D48: =VLOOKUP($C$48,$B$39:$F$42,5,0)&$B$48&"或每年給付之分期定期保險金低於"&VLOOKUP($C$48,$B$39:$F$42,4,0)&$B$48&"者，" -> ○零人民幣或每年給付之分期定期保險金低於○零人民幣者，

Sheet 揭露
B1: =OP!$C$56 -> LTQ30 | C1: ←帶OP | D1: =IF(OP!$E$16=1,"足歲",IF(OP!$E$16=2,"保險年齡","錯誤")) -> 保險年齡 | E1: ←帶OP | Q1: 6 | R1: 7 | S1: 8 | T1: 9 | U1: 10 | V1: 11 | W1: 12
L2: 以下3欄要注意最下方要和右側揭露拉齊 | O2: 以下COPY-DB | Q2: 1120911
C3: 代表年齡第?小→ | D3: 1 | E3: 2 | F3: 3 | G3: 1 | H3: 2 | I3: 3 | K3: 年齡代號轉換 | L3: KEY | M3: 年齡 | N3: 年度 | O3: 險種大類 | P3: 年期險種 | Q3: 性別 | R3: 年齡 | S3: 繳費方式 | T3: 宣告利率 | U3: 繳費金額 | V3: 保單年度 | W3: 揭露利率
C4: 性別男=1，女=2→ | D4: 1 | E4: 1 | F4: 1 | G4: 2 | H4: 2 | I4: 2 | K4: =IF($D$1="足歲","15足","") | L4: =IF(P4<>$B$1,"",P4&Q4&R4&V4) | M4: =IF(L4="","-",IF(ISERROR($R4*1),LEFT($R4,2)*1,$R4*1)) -> - | N4: =IF(L4="","",V4*1)
B5: 取第?欄→ | C5: 12 | D5: =IF(SMALL($M:$M,D$3)=15,$K$4,SMALL($M:$M,D$3)) -> #NUM! | E5: =IF(SMALL($M:$M,E$3)=15,$K$4,SMALL($M:$M,E$3)) -> #NUM! | F5: =IF(SMALL($M:$M,F$3)=15,$K$4,SMALL($M:$M,F$3)) -> #NUM! | G5: =IF(SMALL($M:$M,G$3)=15,$K$4,SMALL($M:$M,G$3)) -> #NUM! | H5: =IF(SMALL($M:$M,H$3)=15,$K$4,SMALL($M:$M,H$3)) -> #NUM! | I5: =IF(SMALL($M:$M,I$3)=15,$K$4,SMALL($M:$M,I$3)) -> #NUM! | L5: =IF(P5<>$B$1,"",P5&Q5&R5&V5) | M5: =IF(OR(L5="",COUNTIF($M$4:M4,IF(ISERROR($R5*1),LEFT($R5,2)*1,$R5*1))>=1),"-",IF(ISERROR($R5*1),LEFT($R5,2)*1,$R5*1)) -> - | N5: =IF(OR(L5="",COUNTIF($N$4:N4,V5*1)>=1),"-",V5*1) -> -
B6: 第?小↓ | C6: 保單年度 | D6: =IF(OR(ISERROR($D5)),"",IF((D$5)=0,D$5&IF(D$4=1,"男性",IF(D$4=2,"女性","")),D$5&"歲"&IF(D$4=1,"男性",IF(D$4=2,"女性","")))) | E6: =IF(OR(ISERROR($D5)),"",IF((E$5)=0,E$5&IF(E$4=1,"男性",IF(E$4=2,"女性","")),E$5&"歲"&IF(E$4=1,"男性",IF(E$4=2,"女性","")))) | F6: =IF(OR(ISERROR($D5)),"",IF((F$5)=0,F$5&IF(F$4=1,"男性",IF(F$4=2,"女性","")),F$5&"歲"&IF(F$4=1,"男性",IF(F$4=2,"女性","")))) | G6: =IF(OR(ISERROR($D5)),"",IF((G$5)=0,G$5&IF(G$4=1,"男性",IF(G$4=2,"女性","")),G$5&"歲"&IF(G$4=1,"男性",IF(G$4=2,"女性","")))) | H6: =IF(OR(ISERROR($D5)),"",IF((H$5)=0,H$5&IF(H$4=1,"男性",IF(H$4=2,"女性","")),H$5&"歲"&IF(H$4=1,"男性",IF(H$4=2,"女性","")))) | I6: =IF(OR(ISERROR($D5)),"",IF((I$5)=0,I$5&IF(I$4=1,"男性",IF(I$4=2,"女性","")),I$5&"歲"&IF(I$4=1,"男性",IF(I$4=2,"女性","")))) | L6: =IF(P6<>$B$1,"",P6&Q6&R6&V6) | M6: =IF(OR(L6="",COUNTIF($M$4:M5,IF(ISERROR($R6*1),LEFT($R6,2)*1,$R6*1))>=1),"-",IF(ISERROR($R6*1),LEFT($R6,2)*1,$R6*1)) -> - | N6: =IF(OR(L6="",COUNTIF($N$4:N5,V6*1)>=1),"-",V6*1) -> -
B7: 1 | C7: =IF(ISERROR(SMALL($N:$N,$B7)),"",SMALL($N:$N,$B7)) | D7: =IF(ISERROR(VLOOKUP($B$1&D$4&D$5&$C7,$L:$W,$C$5,0)),"",VLOOKUP($B$1&D$4&D$5&$C7,$L:$W,$C$5,0)) | E7: =IF(ISERROR(VLOOKUP($B$1&E$4&E$5&$C7,$L:$W,$C$5,0)),"",VLOOKUP($B$1&E$4&E$5&$C7,$L:$W,$C$5,0)) | F7: =IF(ISERROR(VLOOKUP($B$1&F$4&F$5&$C7,$L:$W,$C$5,0)),"",VLOOKUP($B$1&F$4&F$5&$C7,$L:$W,$C$5,0)) | G7: =IF(ISERROR(VLOOKUP($B$1&G$4&G$5&$C7,$L:$W,$C$5,0)),"",VLOOKUP($B$1&G$4&G$5&$C7,$L:$W,$C$5,0)) | H7: =IF(ISERROR(VLOOKUP($B$1&H$4&H$5&$C7,$L:$W,$C$5,0)),"",VLOOKUP($B$1&H$4&H$5&$C7,$L:$W,$C$5,0)) | I7: =IF(ISERROR(VLOOKUP($B$1&I$4&I$5&$C7,$L:$W,$C$5,0)),"",VLOOKUP($B$1&I$4&I$5&$C7,$L:$W,$C$5,0)) | L7: =IF(P7<>$B$1,"",P7&Q7&R7&V7) | M7: =IF(OR(L7="",COUNTIF($M$4:M6,IF(ISERROR($R7*1),LEFT($R7,2)*1,$R7*1))>=1),"-",IF(ISERROR($R7*1),LEFT($R7,2)*1,$R7*1)) -> - | N7: =IF(OR(L7="",COUNTIF($N$4:N6,V7*1)>=1),"-",V7*1) -> -
B8: 2 | C8: =IF(ISERROR(SMALL($N:$N,$B8)),"",SMALL($N:$N,$B8)) | D8: =IF(ISERROR(VLOOKUP($B$1&D$4&D$5&$C8,$L:$W,$C$5,0)),"",VLOOKUP($B$1&D$4&D$5&$C8,$L:$W,$C$5,0)) | E8: =IF(ISERROR(VLOOKUP($B$1&E$4&E$5&$C8,$L:$W,$C$5,0)),"",VLOOKUP($B$1&E$4&E$5&$C8,$L:$W,$C$5,0)) | F8: =IF(ISERROR(VLOOKUP($B$1&F$4&F$5&$C8,$L:$W,$C$5,0)),"",VLOOKUP($B$1&F$4&F$5&$C8,$L:$W,$C$5,0)) | G8: =IF(ISERROR(VLOOKUP($B$1&G$4&G$5&$C8,$L:$W,$C$5,0)),"",VLOOKUP($B$1&G$4&G$5&$C8,$L:$W,$C$5,0)) | H8: =IF(ISERROR(VLOOKUP($B$1&H$4&H$5&$C8,$L:$W,$C$5,0)),"",VLOOKUP($B$1&H$4&H$5&$C8,$L:$W,$C$5,0)) | I8: =IF(ISERROR(VLOOKUP($B$1&I$4&I$5&$C8,$L:$W,$C$5,0)),"",VLOOKUP($B$1&I$4&I$5&$C8,$L:$W,$C$5,0)) | L8: =IF(P8<>$B$1,"",P8&Q8&R8&V8) | M8: =IF(OR(L8="",COUNTIF($M$4:M7,IF(ISERROR($R8*1),LEFT($R8,2)*1,$R8*1))>=1),"-",IF(ISERROR($R8*1),LEFT($R8,2)*1,$R8*1)) -> - | N8: =IF(OR(L8="",COUNTIF($N$4:N7,V8*1)>=1),"-",V8*1) -> -
B9: 3 | C9: =IF(ISERROR(SMALL($N:$N,$B9)),"",SMALL($N:$N,$B9)) | D9: =IF(ISERROR(VLOOKUP($B$1&D$4&D$5&$C9,$L:$W,$C$5,0)),"",VLOOKUP($B$1&D$4&D$5&$C9,$L:$W,$C$5,0)) | E9: =IF(ISERROR(VLOOKUP($B$1&E$4&E$5&$C9,$L:$W,$C$5,0)),"",VLOOKUP($B$1&E$4&E$5&$C9,$L:$W,$C$5,0)) | F9: =IF(ISERROR(VLOOKUP($B$1&F$4&F$5&$C9,$L:$W,$C$5,0)),"",VLOOKUP($B$1&F$4&F$5&$C9,$L:$W,$C$5,0)) | G9: =IF(ISERROR(VLOOKUP($B$1&G$4&G$5&$C9,$L:$W,$C$5,0)),"",VLOOKUP($B$1&G$4&G$5&$C9,$L:$W,$C$5,0)) | H9: =IF(ISERROR(VLOOKUP($B$1&H$4&H$5&$C9,$L:$W,$C$5,0)),"",VLOOKUP($B$1&H$4&H$5&$C9,$L:$W,$C$5,0)) | I9: =IF(ISERROR(VLOOKUP($B$1&I$4&I$5&$C9,$L:$W,$C$5,0)),"",VLOOKUP($B$1&I$4&I$5&$C9,$L:$W,$C$5,0)) | L9: =IF(P9<>$B$1,"",P9&Q9&R9&V9) | M9: =IF(OR(L9="",COUNTIF($M$4:M8,IF(ISERROR($R9*1),LEFT($R9,2)*1,$R9*1))>=1),"-",IF(ISERROR($R9*1),LEFT($R9,2)*1,$R9*1)) -> - | N9: =IF(OR(L9="",COUNTIF($N$4:N8,V9*1)>=1),"-",V9*1) -> -
B10: 4 | C10: =IF(ISERROR(SMALL($N:$N,$B10)),"",SMALL($N:$N,$B10)) | D10: =IF(ISERROR(VLOOKUP($B$1&D$4&D$5&$C10,$L:$W,$C$5,0)),"",VLOOKUP($B$1&D$4&D$5&$C10,$L:$W,$C$5,0)) | E10: =IF(ISERROR(VLOOKUP($B$1&E$4&E$5&$C10,$L:$W,$C$5,0)),"",VLOOKUP($B$1&E$4&E$5&$C10,$L:$W,$C$5,0)) | F10: =IF(ISERROR(VLOOKUP($B$1&F$4&F$5&$C10,$L:$W,$C$5,0)),"",VLOOKUP($B$1&F$4&F$5&$C10,$L:$W,$C$5,0)) | G10: =IF(ISERROR(VLOOKUP($B$1&G$4&G$5&$C10,$L:$W,$C$5,0)),"",VLOOKUP($B$1&G$4&G$5&$C10,$L:$W,$C$5,0)) | H10: =IF(ISERROR(VLOOKUP($B$1&H$4&H$5&$C10,$L:$W,$C$5,0)),"",VLOOKUP($B$1&H$4&H$5&$C10,$L:$W,$C$5,0)) | I10: =IF(ISERROR(VLOOKUP($B$1&I$4&I$5&$C10,$L:$W,$C$5,0)),"",VLOOKUP($B$1&I$4&I$5&$C10,$L:$W,$C$5,0)) | L10: =IF(P10<>$B$1,"",P10&Q10&R10&V10) | M10: =IF(OR(L10="",COUNTIF($M$4:M9,IF(ISERROR($R10*1),LEFT($R10,2)*1,$R10*1))>=1),"-",IF(ISERROR($R10*1),LEFT($R10,2)*1,$R10*1)) -> - | N10: =IF(OR(L10="",COUNTIF($N$4:N9,V10*1)>=1),"-",V10*1) -> -
B11: 5 | C11: =IF(ISERROR(SMALL($N:$N,$B11)),"",SMALL($N:$N,$B11)) | D11: =IF(ISERROR(VLOOKUP($B$1&D$4&D$5&$C11,$L:$W,$C$5,0)),"",VLOOKUP($B$1&D$4&D$5&$C11,$L:$W,$C$5,0)) | E11: =IF(ISERROR(VLOOKUP($B$1&E$4&E$5&$C11,$L:$W,$C$5,0)),"",VLOOKUP($B$1&E$4&E$5&$C11,$L:$W,$C$5,0)) | F11: =IF(ISERROR(VLOOKUP($B$1&F$4&F$5&$C11,$L:$W,$C$5,0)),"",VLOOKUP($B$1&F$4&F$5&$C11,$L:$W,$C$5,0)) | G11: =IF(ISERROR(VLOOKUP($B$1&G$4&G$5&$C11,$L:$W,$C$5,0)),"",VLOOKUP($B$1&G$4&G$5&$C11,$L:$W,$C$5,0)) | H11: =IF(ISERROR(VLOOKUP($B$1&H$4&H$5&$C11,$L:$W,$C$5,0)),"",VLOOKUP($B$1&H$4&H$5&$C11,$L:$W,$C$5,0)) | I11: =IF(ISERROR(VLOOKUP($B$1&I$4&I$5&$C11,$L:$W,$C$5,0)),"",VLOOKUP($B$1&I$4&I$5&$C11,$L:$W,$C$5,0)) | L11: =IF(P11<>$B$1,"",P11&Q11&R11&V11) | M11: =IF(OR(L11="",COUNTIF($M$4:M10,IF(ISERROR($R11*1),LEFT($R11,2)*1,$R11*1))>=1),"-",IF(ISERROR($R11*1),LEFT($R11,2)*1,$R11*1)) -> - | N11: =IF(OR(L11="",COUNTIF($N$4:N10,V11*1)>=1),"-",V11*1) -> -
B12: 6 | C12: =IF(ISERROR(SMALL($N:$N,$B12)),"",SMALL($N:$N,$B12)) | D12: =IF(ISERROR(VLOOKUP($B$1&D$4&D$5&$C12,$L:$W,$C$5,0)),"",VLOOKUP($B$1&D$4&D$5&$C12,$L:$W,$C$5,0)) | E12: =IF(ISERROR(VLOOKUP($B$1&E$4&E$5&$C12,$L:$W,$C$5,0)),"",VLOOKUP($B$1&E$4&E$5&$C12,$L:$W,$C$5,0)) | F12: =IF(ISERROR(VLOOKUP($B$1&F$4&F$5&$C12,$L:$W,$C$5,0)),"",VLOOKUP($B$1&F$4&F$5&$C12,$L:$W,$C$5,0)) | G12: =IF(ISERROR(VLOOKUP($B$1&G$4&G$5&$C12,$L:$W,$C$5,0)),"",VLOOKUP($B$1&G$4&G$5&$C12,$L:$W,$C$5,0)) | H12: =IF(ISERROR(VLOOKUP($B$1&H$4&H$5&$C12,$L:$W,$C$5,0)),"",VLOOKUP($B$1&H$4&H$5&$C12,$L:$W,$C$5,0)) | I12: =IF(ISERROR(VLOOKUP($B$1&I$4&I$5&$C12,$L:$W,$C$5,0)),"",VLOOKUP($B$1&I$4&I$5&$C12,$L:$W,$C$5,0)) | L12: =IF(P12<>$B$1,"",P12&Q12&R12&V12) | M12: =IF(OR(L12="",COUNTIF($M$4:M11,IF(ISERROR($R12*1),LEFT($R12,2)*1,$R12*1))>=1),"-",IF(ISERROR($R12*1),LEFT($R12,2)*1,$R12*1)) -> - | N12: =IF(OR(L12="",COUNTIF($N$4:N11,V12*1)>=1),"-",V12*1) -> -
B13: 7 | C13: =IF(ISERROR(SMALL($N:$N,$B13)),"",SMALL($N:$N,$B13)) | D13: =IF(ISERROR(VLOOKUP($B$1&D$4&D$5&$C13,$L:$W,$C$5,0)),"",VLOOKUP($B$1&D$4&D$5&$C13,$L:$W,$C$5,0)) | E13: =IF(ISERROR(VLOOKUP($B$1&E$4&E$5&$C13,$L:$W,$C$5,0)),"",VLOOKUP($B$1&E$4&E$5&$C13,$L:$W,$C$5,0)) | F13: =IF(ISERROR(VLOOKUP($B$1&F$4&F$5&$C13,$L:$W,$C$5,0)),"",VLOOKUP($B$1&F$4&F$5&$C13,$L:$W,$C$5,0)) | G13: =IF(ISERROR(VLOOKUP($B$1&G$4&G$5&$C13,$L:$W,$C$5,0)),"",VLOOKUP($B$1&G$4&G$5&$C13,$L:$W,$C$5,0)) | H13: =IF(ISERROR(VLOOKUP($B$1&H$4&H$5&$C13,$L:$W,$C$5,0)),"",VLOOKUP($B$1&H$4&H$5&$C13,$L:$W,$C$5,0)) | I13: =IF(ISERROR(VLOOKUP($B$1&I$4&I$5&$C13,$L:$W,$C$5,0)),"",VLOOKUP($B$1&I$4&I$5&$C13,$L:$W,$C$5,0)) | L13: =IF(P13<>$B$1,"",P13&Q13&R13&V13) | M13: =IF(OR(L13="",COUNTIF($M$4:M12,IF(ISERROR($R13*1),LEFT($R13,2)*1,$R13*1))>=1),"-",IF(ISERROR($R13*1),LEFT($R13,2)*1,$R13*1)) -> - | N13: =IF(OR(L13="",COUNTIF($N$4:N12,V13*1)>=1),"-",V13*1) -> -
B14: 8 | C14: =IF(ISERROR(SMALL($N:$N,$B14)),"",SMALL($N:$N,$B14)) | D14: =IF(ISERROR(VLOOKUP($B$1&D$4&D$5&$C14,$L:$W,$C$5,0)),"",VLOOKUP($B$1&D$4&D$5&$C14,$L:$W,$C$5,0)) | E14: =IF(ISERROR(VLOOKUP($B$1&E$4&E$5&$C14,$L:$W,$C$5,0)),"",VLOOKUP($B$1&E$4&E$5&$C14,$L:$W,$C$5,0)) | F14: =IF(ISERROR(VLOOKUP($B$1&F$4&F$5&$C14,$L:$W,$C$5,0)),"",VLOOKUP($B$1&F$4&F$5&$C14,$L:$W,$C$5,0)) | G14: =IF(ISERROR(VLOOKUP($B$1&G$4&G$5&$C14,$L:$W,$C$5,0)),"",VLOOKUP($B$1&G$4&G$5&$C14,$L:$W,$C$5,0)) | H14: =IF(ISERROR(VLOOKUP($B$1&H$4&H$5&$C14,$L:$W,$C$5,0)),"",VLOOKUP($B$1&H$4&H$5&$C14,$L:$W,$C$5,0)) | I14: =IF(ISERROR(VLOOKUP($B$1&I$4&I$5&$C14,$L:$W,$C$5,0)),"",VLOOKUP($B$1&I$4&I$5&$C14,$L:$W,$C$5,0)) | L14: =IF(P14<>$B$1,"",P14&Q14&R14&V14) | M14: =IF(OR(L14="",COUNTIF($M$4:M13,IF(ISERROR($R14*1),LEFT($R14,2)*1,$R14*1))>=1),"-",IF(ISERROR($R14*1),LEFT($R14,2)*1,$R14*1)) -> - | N14: =IF(OR(L14="",COUNTIF($N$4:N13,V14*1)>=1),"-",V14*1) -> -
C15: 以上區域為帶入列印頁範圍 | L15: =IF(P15<>$B$1,"",P15&Q15&R15&V15) | M15: =IF(OR(L15="",COUNTIF($M$4:M14,IF(ISERROR($R15*1),LEFT($R15,2)*1,$R15*1))>=1),"-",IF(ISERROR($R15*1),LEFT($R15,2)*1,$R15*1)) -> - | N15: =IF(OR(L15="",COUNTIF($N$4:N14,V15*1)>=1),"-",V15*1) -> -
L16: =IF(P16<>$B$1,"",P16&Q16&R16&V16) | M16: =IF(OR(L16="",COUNTIF($M$4:M15,IF(ISERROR($R16*1),LEFT($R16,2)*1,$R16*1))>=1),"-",IF(ISERROR($R16*1),LEFT($R16,2)*1,$R16*1)) -> - | N16: =IF(OR(L16="",COUNTIF($N$4:N15,V16*1)>=1),"-",V16*1) -> -
L17: =IF(P17<>$B$1,"",P17&Q17&R17&V17) | M17: =IF(OR(L17="",COUNTIF($M$4:M16,IF(ISERROR($R17*1),LEFT($R17,2)*1,$R17*1))>=1),"-",IF(ISERROR($R17*1),LEFT($R17,2)*1,$R17*1)) -> - | N17: =IF(OR(L17="",COUNTIF($N$4:N16,V17*1)>=1),"-",V17*1) -> -
L18: =IF(P18<>$B$1,"",P18&Q18&R18&V18) | M18: =IF(OR(L18="",COUNTIF($M$4:M17,IF(ISERROR($R18*1),LEFT($R18,2)*1,$R18*1))>=1),"-",IF(ISERROR($R18*1),LEFT($R18,2)*1,$R18*1)) -> - | N18: =IF(OR(L18="",COUNTIF($N$4:N17,V18*1)>=1),"-",V18*1) -> -
L19: =IF(P19<>$B$1,"",P19&Q19&R19&V19) | M19: =IF(OR(L19="",COUNTIF($M$4:M18,IF(ISERROR($R19*1),LEFT($R19,2)*1,$R19*1))>=1),"-",IF(ISERROR($R19*1),LEFT($R19,2)*1,$R19*1)) -> - | N19: =IF(OR(L19="",COUNTIF($N$4:N18,V19*1)>=1),"-",V19*1) -> -
L20: =IF(P20<>$B$1,"",P20&Q20&R20&V20) | M20: =IF(OR(L20="",COUNTIF($M$4:M19,IF(ISERROR($R20*1),LEFT($R20,2)*1,$R20*1))>=1),"-",IF(ISERROR($R20*1),LEFT($R20,2)*1,$R20*1)) -> - | N20: =IF(OR(L20="",COUNTIF($N$4:N19,V20*1)>=1),"-",V20*1) -> -
L21: =IF(P21<>$B$1,"",P21&Q21&R21&V21) | M21: =IF(OR(L21="",COUNTIF($M$4:M20,IF(ISERROR($R21*1),LEFT($R21,2)*1,$R21*1))>=1),"-",IF(ISERROR($R21*1),LEFT($R21,2)*1,$R21*1)) -> - | N21: =IF(OR(L21="",COUNTIF($N$4:N20,V21*1)>=1),"-",V21*1) -> -
L22: =IF(P22<>$B$1,"",P22&Q22&R22&V22) | M22: =IF(OR(L22="",COUNTIF($M$4:M21,IF(ISERROR($R22*1),LEFT($R22,2)*1,$R22*1))>=1),"-",IF(ISERROR($R22*1),LEFT($R22,2)*1,$R22*1)) -> - | N22: =IF(OR(L22="",COUNTIF($N$4:N21,V22*1)>=1),"-",V22*1) -> -
L23: =IF(P23<>$B$1,"",P23&Q23&R23&V23) | M23: =IF(OR(L23="",COUNTIF($M$4:M22,IF(ISERROR($R23*1),LEFT($R23,2)*1,$R23*1))>=1),"-",IF(ISERROR($R23*1),LEFT($R23,2)*1,$R23*1)) -> - | N23: =IF(OR(L23="",COUNTIF($N$4:N22,V23*1)>=1),"-",V23*1) -> -
L24: =IF(P24<>$B$1,"",P24&Q24&R24&V24) | M24: =IF(OR(L24="",COUNTIF($M$4:M23,IF(ISERROR($R24*1),LEFT($R24,2)*1,$R24*1))>=1),"-",IF(ISERROR($R24*1),LEFT($R24,2)*1,$R24*1)) -> - | N24: =IF(OR(L24="",COUNTIF($N$4:N23,V24*1)>=1),"-",V24*1) -> -
L25: =IF(P25<>$B$1,"",P25&Q25&R25&V25) | M25: =IF(OR(L25="",COUNTIF($M$4:M24,IF(ISERROR($R25*1),LEFT($R25,2)*1,$R25*1))>=1),"-",IF(ISERROR($R25*1),LEFT($R25,2)*1,$R25*1)) -> - | N25: =IF(OR(L25="",COUNTIF($N$4:N24,V25*1)>=1),"-",V25*1) -> -
L26: =IF(P26<>$B$1,"",P26&Q26&R26&V26) | M26: =IF(OR(L26="",COUNTIF($M$4:M25,IF(ISERROR($R26*1),LEFT($R26,2)*1,$R26*1))>=1),"-",IF(ISERROR($R26*1),LEFT($R26,2)*1,$R26*1)) -> - | N26: =IF(OR(L26="",COUNTIF($N$4:N25,V26*1)>=1),"-",V26*1) -> -
L27: =IF(P27<>$B$1,"",P27&Q27&R27&V27) | M27: =IF(OR(L27="",COUNTIF($M$4:M26,IF(ISERROR($R27*1),LEFT($R27,2)*1,$R27*1))>=1),"-",IF(ISERROR($R27*1),LEFT($R27,2)*1,$R27*1)) -> - | N27: =IF(OR(L27="",COUNTIF($N$4:N26,V27*1)>=1),"-",V27*1) -> -
... L147: =IF(P147<>$B$1,"",P147&Q147&R147&V147) | M147: =IF(OR(L147="",COUNTIF($M$4:M146,IF(ISERROR($R147*1),LEFT($R147,2)*1,$R147*1))>=1),"-",IF(ISERROR($R147*1),LEFT($R147,2)*1,$R147*1)) -> - | N147: =IF(OR(L147="",COUNTIF($N$4:N146,V147*1)>=1),"-",V147*1) -> -

Sheet input_s
A1: 回傳資訊
A2: 保費：首期 | B2: =IF($H$8=0,"",IF(ISERROR(OP!$D$53),"資料錯誤_首期保費",OP!$C$48))
A3: 保費：續期 | B3: =IF($H$8=0,"",IF(ISERROR(OP!$D$53),"資料錯誤_續期保費",IF(OP!$C$24=1,0,OP!$C$49)))
A4: 錯誤訊息： | B4: =IF($H$8=0,"",IF(ISERROR(OP!$D$53),"資料錯誤",I15&J15&I16&J16&I17&J17&I19&J19&I20&J20&I21&J21&I22&J22&I24&J24&I26&J26&I27&J27&I32&J32&I34&J34&I35&J35&I40&J40&I45&J45&I53&J53&I59&J59&I61&J61&I62&J62&I63&J63&I64&J64&I71&J71&I79&J79&I81&J81&I82&J82&I84&J84&I86&J86&I92&J92&I93&J93&I94&J94&I95&J95&I106&J106))
A5: 原始保費： | B5: =IF($H$8=0,"",IF(ISERROR(OP!$D$53),"資料錯誤_原始保費",OP!$C$35)) | C5: 1090428新增 | H5: 目前未使用，預留
A6: 保險年齡： | B6: =IF($H$8=0,"",IF(ISERROR(OP!$D$53),"資料錯誤_保險年齡",OP!$D$5)) | C6: 1090428新增 | H6: EXCEL使用
H7: 是否使用：1=系統帶入,0=輸入頁帶入 | I7: 利變：1、分紅：2、其他：3
H8: 0 | I8: 3
A9: 欄位名 | B9: 中文名 | C9: 說明 | D9: 是否必填 | E9: 試算表使用欄位 | H9: excel套用欄位內容 | I9: 錯誤訊息 | J9: 間隔 | L9: 性別
A10: ProposalRequest | L10: 1 | M10: 男
A11: TrnNum | B11: 交易序號 | C11: 系統代號+yyyymmddhhMMssmis(建議保險公司可以接收該欄位並記錄於log中, 到時候追查資料時比較方便) | D11: V | E11: X | J11: =IF(I11="","",IF(COUNTA(I12:$I$138)>0,"|","")) | L11: 2 | M11: 女
A12: data_type | B12: 資料類別 | C12: 1.產生建議書 | D12: V | J12: =IF(I12="","",IF(COUNTA(I13:$I$138)>0,"|",""))
C13: 2.要保書檢核 | J13: =IF(I13="","",IF(COUNTA(I14:$I$138)>0,"|",""))
A14: insco_no | B14: 保險公司代碼 | C14: 018安聯 | D14: V | E14: X | J14: =IF(I14="","",IF(COUNTA(I15:$I$138)>0,"|",""))
A15: proposal_seq | B15: 建議書序號 | C15: data_type為2(要保書檢核)時不傳 | E15: 中信規則 | H15: =IF($H$8=1,$G15,"") | I15: =IF(G15="","","") | J15: =IF(I15="","",IF(COUNTA(I16:$I$138)>0,"|","")) | L15: 被保人身分別 | N15: 1090721-建議書序號不需檢核 | O15: =IF(G15="","無傳入建議書序號","") -> 無傳入建議書序號
A16: owner_name | B16: 要保人姓名 | D16: V | F16: 目前無要保人欄位，預留 | H16: =IF($H$8=1,$G16,"") | J16: =IF(I16="","",IF(COUNTA(I17:$I$138)>0,"|","")) | L16: 1 | M16: 一般
A17: owner_sex | B17: 要保人性別 | C17: 1男 | D17: V | H17: =IF($H$8=1,IF(ISERROR(VLOOKUP($G17,$L$10:$M$13,2,0)),"",VLOOKUP($G17,$L$10:$M$13,2,0)),"") | J17: =IF(I17="","",IF(COUNTA(I18:$I$138)>0,"|","")) | L17: 2 | M17: 學生
C18: 2女 | J18: =IF(I18="","",IF(COUNTA(I19:$I$138)>0,"|","")) | L18: 3 | M18: 家管
A19: owner_birth | B19: 要保人出生年月日 | C19: yyyymmdd | D19: V | H19: =IF($H$8=1,IF(OR($G$19="",LEN($G$19)<>8),"",LEFT($G$19,4)-1911&TEXT(MID($G$19,5,2),"00")&TEXT(RIGHT($G$19,2),"00")),輸入頁!$E$14) -> 0 | J19: =IF(I19="","",IF(COUNTA(I20:$I$138)>0,"|","")) | L19: 4 | M19: 退休人士
A20: is_owner | B20: 要被保人同一人 | C20: Y/N | D20: V | H20: =IF($H$8=1,$G20,"") | J20: =IF(I20="","",IF(COUNTA(I21:$I$138)>0,"|",""))
A21: insure_name | B21: 被保人姓名 | D21: V | H21: =IF($H$8=1,IF($G$21="","",$G21),輸入頁!$E$5) -> 客戶 | I21: =IF($H$21="",$I$10&"被保險人姓名未填寫","") | J21: =IF(I21="","",IF(COUNTA(I22:$I$138)>0,"|",""))
A22: insure_sex | B22: 被保險人性別 | C22: 1男 | D22: V | H22: =IF($H$8=1,IF(ISERROR(VLOOKUP($G22,$L$10:$M$13,2,0)),"",VLOOKUP($G22,$L$10:$M$13,2,0)),輸入頁!$K$5) -> 女 | I22: =IF(OR($H$22="",OP!$D$18=1),$I$10&"被保險人性別錯誤","") | J22: =IF(I22="","",IF(COUNTA(I23:$I$138)>0,"|",""))
C23: 2女 | J23: =IF(I23="","",IF(COUNTA(I24:$I$138)>0,"|","")) | L23: 繳別
A24: insure_birthday | B24: 被保險人出生年月日 | C24: yyyymmdd | D24: V | H24: =IF($H$8=1,IF(OR($G$24="",LEN($G$24)<>8),"",LEFT($G$24,4)-1911&TEXT(MID($G$24,5,2),"00")&TEXT(RIGHT($G$24,2),"00")),輸入頁!$N$5) -> 1010101 | I24: =IF(H24="",$I$10&"被保險人生日錯誤",IF(OP!$E$6=1,"生日日期錯誤",""))&IF(OR(OP!$D$15=1,OP!$D$16=1),"＊年齡不符專案投保區間，請先確認年齡後 重新試算，其他欄位檢核訊息請先忽略＊","") | J24: =IF(I24="","",IF(COUNTA(I25:$I$138)>0,"|","")) | K24: 1150126調整 | L24: 01 | M24: 月繳
J25: =IF(I25="","",IF(COUNTA(I26:$I$138)>0,"|","")) | L25: 03 | M25: 季繳
A26: insure_prof_kind | B26: 被保險人職業等級 | C26: 1~6 | D26: V | F26: 與被保人兼業等級取大 | H26: =IF($H$8=1,MAX($G26,$G32),"") | J26: =IF(I26="","",IF(COUNTA(I27:$I$138)>0,"|","")) | L26: 06 | M26: 半年繳
A27: insure_prof_type | B27: 被保險人職業身分別 | C27: 1.一般 | F27: 試算表無身分判別，預留 | H27: =IF($H$8=1,IF(ISERROR(VLOOKUP($G27,$L$16:$M$21,2,0)),"",VLOOKUP($G27,$L$16:$M$21,2,0)),"") | J27: =IF(I27="","",IF(COUNTA(I28:$I$138)>0,"|","")) | L27: 12 | M27: 年繳
C28: 2.學生 | J28: =IF(I28="","",IF(COUNTA(I29:$I$138)>0,"|","")) | L28: P | M28: 躉繳
C29: 3.家管 | J29: =IF(I29="","",IF(COUNTA(I30:$I$138)>0,"|",""))
C30: 4.退休人士 | J30: =IF(I30="","",IF(COUNTA(I31:$I$138)>0,"|",""))
A31: insure_job_code | B31: 被保險人職業代碼 | E31: X | J31: =IF(I31="","",IF(COUNTA(I32:$I$138)>0,"|","")) | L31: 繳費方式 | M31: 首期 | N31: 續期 | O31: 中信
A32: insure_part_time_prof_kind | B32: 被保險人兼職職業等級 | C32: 1~6 | D32: V | H32: 於H26取大 | J32: =IF(I32="","",IF(COUNTA(I33:$I$138)>0,"|","")) | L32: 1 | M32: =IF(OP!$C$21=1,"匯款","外幣匯款") -> 匯款 | N32: - | O32: 1.帳戶圈存(匯款)
A33: insure_part_time_job_code | B33: 被保險人兼職職業代碼 | E33: X | J33: =IF(I33="","",IF(COUNTA(I34:$I$138)>0,"|","")) | L33: 2 | M33: =IF(OP!$C$21=1,"匯款","外幣匯款") -> 匯款 | N33: - | O33: 2.現金圈存(匯款)
A34: plan_code | B34: 險種代號 | D34: V | H34: =IF($H$8=1,UPPER($G34),輸入頁!$E$39) -> LTQ | I34: =IF(ISERROR(VLOOKUP($H$34,OP!$H$43:$H$62,1,0)),$I$10&"險種錯誤","") | J34: =IF(I34="","",IF(COUNTA(I35:$I$138)>0,"|","")) | L34: 3 | M34: 一般信用卡 | N34: 一般信用卡 | O34: 3.信用卡
A35: paid_period_year | B35: 繳費年期 | D35: V | H35: =IF($H$8=1,$G35,輸入頁!$E$37) -> 30 | I35: =IF(COUNTIF(OP!$J$43:$J$62,$H$35&$H$34)<>1,$I$10&"年期錯誤","") | J35: =IF(I35="","",IF(COUNTA(I36:$I$138)>0,"|","")) | L35: 4 | M35: 金融機構轉帳 | N35: 金融機構轉帳 | O35: 4.本行自扣(轉帳)
A36: coverage_type | B36: 保障類別單位 | C36: 1.保額 2單位 3計畫 | D36: V | E36: X | F36: 試算表無須判別 | J36: =IF(I36="","",IF(COUNTA(I37:$I$138)>0,"|","")) | L36: 5 | M36: =IF(OP!$C$21=1,"匯款","外幣匯款") -> 匯款 | N36: 自行繳費 | O36: 5.臨櫃轉帳(匯款)
A37: cuy_cpo | B37: 保額幣別 | C37: 台幣為TWD | D37: V | E37: X | F37: 試算表無須判別 | J37: =IF(I37="","",IF(COUNTA(I38:$I$138)>0,"|","")) | L37: 6 | M37: =IF(OP!$C$21=1,"匯款","外幣匯款") -> 匯款 | N37: 自行繳費 | O37: 6.臨櫃存入(匯款)
A38: cuy_prem | B38: 保費幣別 | C38: OIU商品時, | D38: V | E38: X | F38: 試算表無須判別 | J38: =IF(I38="","",IF(COUNTA(I39:$I$138)>0,"|","")) | L38: 7 | M38: - | N38: - | O38: 9.其他
C39: 可能保額與保費幣別不同 | J39: =IF(I39="","",IF(COUNTA(I40:$I$138)>0,"|","")) | L39: A | M39: 金融機構轉帳 | N39: 金融機構轉帳 | O39: A.他行自扣(轉帳)
A40: Modx | B40: 繳別 | C40: 01 月繳 | D40: V | H40: =IF($H$8=1,IF(ISERROR(VLOOKUP($G40,$L$24:$M$29,2,0)),"",VLOOKUP($G40,$L$24:$M$29,2,0)),輸入頁!$E$17) -> 年繳 | I40: =IF(OP!$D$32=1,$I$10&"繳別錯誤","") | J40: =IF(I40="","",IF(COUNTA(I41:$I$138)>0,"|",""))
C41: 03 季繳 | J41: =IF(I41="","",IF(COUNTA(I42:$I$138)>0,"|",""))
C42: 06 半年繳 | J42: =IF(I42="","",IF(COUNTA(I43:$I$138)>0,"|",""))
C43: 12 年繳 | J43: =IF(I43="","",IF(COUNTA(I44:$I$138)>0,"|","")) | L43: 增值回饋分享金給付方式 | N43: 中信
C44: P 躉繳 | J44: =IF(I44="","",IF(COUNTA(I45:$I$138)>0,"|","")) | L44: 1 | M44: =IF($I$8=1,OP!$W$3,IF($I$8=2,OP!$W$6,"")) | N44: 1 增購保額
A45: first_pay_way | B45: 首期繳費方式 | C45: 1.帳戶圈存(匯款) | D45: V | H45: =IF($H$8=1,IF(ISERROR(VLOOKUP($G45,$L$31:$N$41,2,0)),"",VLOOKUP($G45,$L$31:$N$41,2,0)),輸入頁!$Q$17) -> 匯款 | I45: =IF(OP!$D$41=1,$I$10&"首期繳費方式錯誤","") | J45: =IF(I45="","",IF(COUNTA(I46:$I$138)>0,"|","")) | N45: 2 抵繳保費
C46: 2.現金圈存(匯款) | J46: =IF(I46="","",IF(COUNTA(I47:$I$138)>0,"|","")) | L46: 3 | M46: 現金給付 | N46: 3 現金給付
C47: 3.信用卡 | J47: =IF(I47="","",IF(COUNTA(I48:$I$138)>0,"|","")) | L47: 4 | M47: 儲存生息 | N47: 4 儲存生息
C48: 4.本行自扣(轉帳) | J48: =IF(I48="","",IF(COUNTA(I49:$I$138)>0,"|",""))
C49: 5.臨櫃轉帳(匯款) | J49: =IF(I49="","",IF(COUNTA(I50:$I$138)>0,"|",""))
C50: 6.臨櫃存入(匯款) | J50: =IF(I50="","",IF(COUNTA(I51:$I$138)>0,"|",""))
C51: 9.其他 | J51: =IF(I51="","",IF(COUNTA(I52:$I$138)>0,"|","")) | L51: 年金給付方式 | N51: 中信
C52: A.他行自扣(轉帳) | J52: =IF(I52="","",IF(COUNTA(I53:$I$138)>0,"|","")) | L52: 1 | M52: 一次年金 | N52: 1 一次給付
A53: cont_pay_way | B53: 續期繳費方式 | C53: 3.信用卡 | H53: =IF($H$8=1,IF(ISERROR(VLOOKUP($G53,$L$31:$N$41,3,0)),"",VLOOKUP($G53,$L$31:$N$41,3,0)),輸入頁!$Q$19) -> 金融機構轉帳 | I53: =IF(OP!$D$43=1,$I$10&"續期繳費方式錯誤","") | J53: =IF(I53="","",IF(COUNTA(I54:$I$138)>0,"|","")) | L53: 2 | M53: 分期年金 | N53: 2 分期給付
C54: 4.本行自扣(轉帳) | J54: =IF(I54="","",IF(COUNTA(I55:$I$138)>0,"|",""))
C55: 5.臨櫃轉帳(匯款) | J55: =IF(I55="","",IF(COUNTA(I56:$I$138)>0,"|",""))
C56: 6.臨櫃存入(匯款) | J56: =IF(I56="","",IF(COUNTA(I57:$I$138)>0,"|",""))
C57: 9.其他 | J57: =IF(I57="","",IF(COUNTA(I58:$I$138)>0,"|","")) | L57: 年金保證期
C58: A.他行自扣(轉帳) | J58: =IF(I58="","",IF(COUNTA(I59:$I$138)>0,"|","")) | M58: 5
A59: group_pay_disc_no | B59: 集彙折扣代碼 | F59: 集彙、員工專案有值=Y | H59: =IF($H$8=1,IF($G59<>"","Y",""),OP!$K$27) -> 0 | J59: =IF(I59="","",IF(COUNTA(I60:$I$138)>0,"|","")) | M59: 10
A60: group_pay_disc | B60: 集體彙繳折扣率 | C60: ex 1%提供 0.01 | E60: X | J60: =IF(I60="","",IF(COUNTA(I61:$I$138)>0,"|","")) | M60: 15
A61: face_amt | B61: 保額(元/計畫/單位) | D61: V | H61: =IF(RIGHT($I$8,2)="年金","",IF($H$8=1,$G61/10000,輸入頁!$J$39)) -> 1 | I61: =IF(OR(OP!$D$28=1,OP!$D$64=1),$I$10&"保額不符投保規則，請再確認","") | J61: =IF(I61="","",IF(COUNTA(I62:$I$138)>0,"|","")) | K61: 1150126調整 | M61: 20
A62: prem_amt | B62: 保費(目標保費、核心保費) | D62: V | F62: 投資型用 | H62: =IF($H$8=1,$G62,"") | J62: =IF(I62="","",IF(COUNTA(I63:$I$138)>0,"|",""))
A63: excess_prmm | B63: 超額保費(衛星保費) | H63: =IF($H$8=1,$G63,"") | J63: =IF(I63="","",IF(COUNTA(I64:$I$138)>0,"|","")) | L63: 年金給付方式
A64: additional_prmm | B64: 增額保費/首期追加繳付 | F64: 需加工計算首期總保費 | H64: =IF($H$8=1,$G64,"") | J64: =IF(I64="","",IF(COUNTA(I65:$I$138)>0,"|","")) | L64: 1 | M64: 年 | N64: 1.年給付
A65: cont_trial_yn | B65: 是否續保試算 | C65: Y/N | E65: X | J65: =IF(I65="","",IF(COUNTA(I66:$I$138)>0,"|","")) | L65: 2 | M65: 月 | N65: 2.月給付
A66: mortgage_year | B66: 房貸年期 | C66: 年 | E66: X | J66: =IF(I66="","",IF(COUNTA(I67:$I$138)>0,"|","")) | L66: 3 | M66: 季 | N66: 3.季給付
A67: mortgage_amt | B67: 房貸金額 | C67: 元 | E67: X | J67: =IF(I67="","",IF(COUNTA(I68:$I$138)>0,"|","")) | L67: 4 | M67: 半年 | N67: 4.半年給付
A68: cont_face_amt | B68: 續保保額 | C68: 元 | E68: X | J68: =IF(I68="","",IF(COUNTA(I69:$I$138)>0,"|",""))
A69: add_feedback_pay_type_6 | B69: 增值回饋金1-6年給付方式 | C69: 1 增購保額 | E69: X | F69: 試算表自行判別 | J69: =IF(I69="","",IF(COUNTA(I70:$I$138)>0,"|",""))
C70: 2 抵繳保費 | J70: =IF(I70="","",IF(COUNTA(I71:$I$138)>0,"|",""))
A71: add_feedback_pay_type_7 | B71: 增值回饋金Y7+給付方式 | C71: 1 增購保額 | H71: =IF($H$8=1,IF(ISERROR(VLOOKUP($G71,$L$44:$N$49,2,0)),"",VLOOKUP($G71,$L$44:$N$49,2,0)),輸入頁!$E$19) -> 現金給付 | I71: =IF(AND($I$8<>3,OR($H$71="",OP!$E$96=1)),$I$10&"給付方式錯誤","") | J71: =IF(I71="","",IF(COUNTA(I72:$I$138)>0,"|","")) | L71: 分期定期年期
C72: 2 抵繳保費 | J72: =IF(I72="","",IF(COUNTA(I73:$I$138)>0,"|","")) | L72: 10 | M72: 20
C73: 3 現金給付 | J73: =IF(I73="","",IF(COUNTA(I74:$I$138)>0,"|",""))
C74: 4 儲存生息 | J74: =IF(I74="","",IF(COUNTA(I75:$I$138)>0,"|",""))
A75: add_feedback_pay_type_m_flag | B75: 增值回饋金Y7+且大於55歲是否月領 | C75: Y/N | E75: X | F75: 試算表無月領設定 | J75: =IF(I75="","",IF(COUNTA(I76:$I$138)>0,"|",""))
A76: designate_insurance_amt | B76: 指定保險金 | C76: 元 | E76: X | F76: 無分期定額保險金 | J76: =IF(I76="","",IF(COUNTA(I77:$I$138)>0,"|",""))
A77: installment_fix_ins_est_rate | B77: 分期定額保險金預定利率 | C77: ex 1%提供 0.01 | E77: X | J77: =IF(I77="","",IF(COUNTA(I78:$I$138)>0,"|",""))
A78: installment_fix_ins_pay_during | B78: 分期定額保險金給付期間 | C78: 年 | E78: X | J78: =IF(I78="","",IF(COUNTA(I79:$I$138)>0,"|",""))
A79: death_ins_pay_pct | B79: 主約身故保障給付設定 | C79: ex 30% 提供30 | G79: 100 | H79: =IF($H$8=1,$G79/100,輸入頁!$G$26/100) -> 0 | I79: =IF(K79=0,"",IF(OR(AND($G$79<>"",$G$79*1<0),$G$79*1>100,AND($G$79<>"",LEN($G$79)<>LEN(ROUND($G$79,0)))),"分期定期保險金比例錯誤","")) | J79: =IF(I79="","",IF(COUNTA(I80:$I$138)>0,"|","")) | K79: 0 | L79: =IF(AND($G$79<>"",OR($H$79<0,$H$79>1)),"約定分期給付比例錯誤","")
B80: (約定分期給付比例) | J80: =IF(I80="","",IF(COUNTA(I81:$I$138)>0,"|",""))
A81: installment_regu_ins_pay_during | B81: 分期定期保險金給付期間 | C81: 年 | F81: 10或20 | H81: =IF($H$8=1,$G81,輸入頁!$G$30) -> 10 | I81: =IF(K81=0,"",IF(OR(AND($G$79>0,$G$79<=100,$G$81="")),"分期定期保險金給付年期未設定",IF($G$81="","",IF(OR($G$81=10,$G$81=20),"",IF($G$79*1=0,"","分期定期保險金給付年期錯誤"))))) | J81: =IF(I81="","",IF(COUNTA(I82:$I$138)>0,"|","")) | K81: 0 | L81: =IF(AND($G$81<>"",COUNTIF($L$72:$N$74,$H$81)<>1),"約定分期年期錯誤","")
A82: annuity_pay_type | B82: 年金給付方式 | C82: 1 一次給付 | H82: =IF($H$8=1,IF(ISERROR(VLOOKUP($G82,$L$52:$N$55,2,0)),"",VLOOKUP($G82,$L$52:$N$55,2,0)),"") | J82: =IF(I82="","",IF(COUNTA(I83:$I$138)>0,"|",""))
C83: 2 分期給付 | J83: =IF(I83="","",IF(COUNTA(I84:$I$138)>0,"|",""))
A84: annuity_guarantee_during | B84: 年金保證期間 | C84: 年 | H84: =IF($H$8=1,$G84,"") | J84: =IF(I84="","",IF(COUNTA(I85:$I$138)>0,"|",""))
A85: annuity_guarantee_amt | B85: 年金保證金額 | C85: 元 | E85: X | J85: =IF(I85="","",IF(COUNTA(I86:$I$138)>0,"|",""))
A86: annuity_guarantee_during_pay_type | B86: 年金分期給付方式/年金保證期間給付方式 | C86: 1.年給付 | H86: =IF($H$8=1,IF(ISERROR(VLOOKUP($G86,$L$64:$M$69,2,0)),"",VLOOKUP($G86,$L$64:$M$69,2,0)),"") | J86: =IF(I86="","",IF(COUNTA(I87:$I$138)>0,"|",""))
C87: 2.月給付 | J87: =IF(I87="","",IF(COUNTA(I88:$I$138)>0,"|",""))
C88: 3.季給付 | J88: =IF(I88="","",IF(COUNTA(I89:$I$138)>0,"|",""))
C89: 4.半年給付 | J89: =IF(I89="","",IF(COUNTA(I90:$I$138)>0,"|",""))
A90: annuity_pay_start_age | B90: 年金開始給付(歲) | C90: 歲 | F90: 系統換算 | J90: =IF(I90="","",IF(COUNTA(I91:$I$138)>0,"|",""))
A91: annuity_guarantee_age | B91: 年金保證提領年齡 | C91: 歲 | E91: X | J91: =IF(I91="","",IF(COUNTA(I92:$I$138)>0,"|",""))
A92: anuuity_accumulated_period | B92: 年金累積期間/年金開始給付(年) | C92: 年 | H92: =IF($H$8=1,$G92,"") | J92: =IF(I92="","",IF(COUNTA(I93:$I$138)>0,"|",""))
A93: annuity_plan_paid_period_year | B93: 計畫繳費年期(年金) | C93: 年 | H93: =IF($H$8=1,$G93,"") | J93: =IF(I93="","",IF(COUNTA(I94:$I$138)>0,"|",""))
A94: inv_plan_paid_period_year | B94: 計畫繳費年期(投資型壽險) | C94: 年 | H94: =IF($H$8=1,$G94,"") | J94: =IF(I94="","",IF(COUNTA(I95:$I$138)>0,"|",""))
A95: inv_rate_1 | B95: 預估投資報酬率1 | C95: ex 1%提供 0.01 | F95: 只會使用單段報酬率，其餘系統自訂 | H95: =IF($H$8=1,$G95,"") | J95: =IF(I95="","",IF(COUNTA(I96:$I$138)>0,"|",""))
C96: 應比預估投資報酬率2高 | J96: =IF(I96="","",IF(COUNTA(I97:$I$138)>0,"|",""))
A97: inv_rate_2 | B97: 預估投資報酬率2 | C97: ex 1%提供 0.01 | E97: X | J97: =IF(I97="","",IF(COUNTA(I98:$I$138)>0,"|",""))
C98: 應比預估投資報酬率1低 | J98: =IF(I98="","",IF(COUNTA(I99:$I$138)>0,"|",""))
A99: inv_pct_nor | B99: 投資比例-一般 | C99: % | E99: X | J99: =IF(I99="","",IF(COUNTA(I100:$I$138)>0,"|",""))
A100: inv_pct_etf | B100: 投資比例-ETF | C100: % | E100: X | J100: =IF(I100="","",IF(COUNTA(I101:$I$138)>0,"|",""))
...

Sheet 總表
B1: 1 | C1: 2 | D1: 3 | E1: 4 | F1: 5 | G1: 6 | H1: 7 | I1: 8 | J1: 9 | K1: 10 | L1: 11 | M1: 12 | N1: 13 | O1: 14 | P1: 15 | Q1: 16 | R1: 17 | S1: 18 | T1: 19 | U1: 20 | V1: 21 | W1: 22 | X1: 23 | Y1: 24 | Z1: 25 | AA1: 26 | AB1: 27 | AC1: 28 | AD1: 29 | AE1: 30 | AF1: 31 | AG1: 32 | AH1: 33 | AI1: 34
D2: 列印頁-簡/銀保/彙總 | F2: 基本保額 | N2: 累計增額繳清保險金額 | S2: 生存保險金 F+O | T2: 累計生存保險金 | U2: 生存保險金(月) round(S/12,0) | V2: 累計生存保險金(月) (U*12)+上期總額 | Y2: 年度末身故/完全失能時可領總金額 | Z2: 身故保障=基本保額+增購保額-最後一年回饋金(增購保額) ㄧ次給付身故=身故保障*比例PYO+紅利+最後一年紅利(增購保額) 分期給付=身故保障*比例PYY | AA2: 列印頁 未扣除增值回饋分享金 | AB2: 列印頁 未扣除增值回饋分享金 | AC2: 保險金額- 大眾運輸工具意外身故保障-28 (不含年度末身故/完全失能時可領總金額) | AD2: 重大燒燙傷保險金-29 | AE2: 保險金額- 大眾運輸工具 意外身故保障-30 (含年度末身故/完全失能保障) | AF2: 意外身故保險金(含身故可領總金額)-31
B3: 保 單 年 度 | C3: 保 險 年 齡 | D3: ="年度實繳保費"&IF(OP!$F$55<15," 已扣除增值回饋分享金 ","") -> 年度實繳保費 | E3: ="累計實繳保費"&IF(OP!$F$55<15," 已扣除增值回饋分享金 ","") -> 累計實繳保費 | F3: 生存保險金 | G3: 累計已領 生存保險金 | H3: 年度末 身故/完全 失能保障 | I3: 年度末 解約金 | J3: 年度末 減額繳清 保險金額 | N3: 年度末 保險金額 ( Z ) | O3: 生存保險金 | P3: 累計已領生存保險金 | Q3: ="年度末 身故/完全失能保障 ( D ) "&OP!$D$114 -> 年度末 身故/完全失能保障 ( D ) | R3: ="年度末 解約金 ( E ) "&OP!$D$115 -> 年度末 解約金 ( E ) | Y3: ㄧ次給付 | Z3: =IF(OR(PYY=0,PY!$C$6=0),"","分期給付(年) 給付"&PY!$C$6&"年") | AA3: 年度 實繳保費 | AB3: 累計 實繳保費 | AE3: 年度末 大眾運輸 交通工具 意外身故保障 | AF3: 年度末 大眾運輸交通工具 意外身故時可領總金額 | AG3: 重大疾病暨 特定傷病保險金 | AH3: 輕度失智 保險金 | AI3: 中重度失智 保險金 (免責期間屆滿 時之保單年度)
B4: 1 | C4: =IF(OP!$D$53=1,"",OP!$F$55) -> 15 | D4: =IF(OR(OP!$D$53=1,AND($B4>OP!$C$24)),"",OP!$C$51) -> 16008 | E4: =IF(OR(OP!$D$53=1,$B4=""),"",N(D4)) -> 16008 | F4: =IF(OR(OP!$D$53=1,$B4="",ISERROR(VLOOKUP(OP!$C$55,SRV,$B4+1,0))),"",ROUND(VLOOKUP(OP!$C$55,SRV,$B4+1,0)*OP!$C$28,0)) | G4: =IF(OR(OP!$D$53=1,$B4="",ISERROR(VLOOKUP(OP!$C$55,SRV,$B4+1,0))),"",N($F4)) | H4: =IF(OR(OP!$D$53=1,$B4=""),"",ROUND(VLOOKUP(OP!$C$55,DIE,$B4+1,0)*OP!$C$28,0)) -> 16493 | I4: =IF(OR(OP!$D$53=1,$B4=""),"",ROUND(VLOOKUP(OP!$C$55,CV,$B4+1,0)*OP!$C$28,0)) -> #N/A | J4: =IF(OR(OP!$D$53=1,$B4=""),"",ROUND(VLOOKUP(OP!$C$55,PA,$B4+1,0)*OP!$C$28,0)) -> #N/A | S4: =IF(OR(OP!$D$53=1,$B4=""),"",N($F4)+N($O4)) -> 0 | T4: =IF(OR(OP!$D$53=1,$B4=""),0,N($S4)) -> 0 | U4: =IF(OR(OP!$D$53=1,$B4=""),"",ROUND($S4/12,0)) -> 0 | V4: =IF(OR(OP!$D$53=1,$B4=""),0,N($U4)*12) -> 0 | Y4: =IF(OR(OP!$D$53=1,$B4=""),"",ROUND(($H4+$Q4)*IF(OR($C4<16,$Z4=0,$Z4=""),1,PYO),0)) -> 16493 | Z4: =IF(OR(OP!$D$53=1,$B4=""),"",ROUND(($H4+Q4)*IF(OR($C4<16,($H4+$Q4)*PY!$C$4<PY!$D$5,($H4+$Q4)*PY!$C$4*PYR<PY!$C$5),0,PYY)*PYR,0)) -> 0 | AA4: =IF(OR(OP!$D$53=1,AND(B4>OP!$C$24)),"",OP!$C$51) -> 16008 | AB4: =IF(OR(OP!$D$53=1,$B4=""),"",N($AA4)) -> 16008 | AH4: =IF(OR(OP!$D$53=1,$B4=""),"",ROUND(VLOOKUP(OP!$C$55,HL_1,$B4+1,0)*OP!$C$28,0)) -> #N/A | AI4: =IF(OR(OP!$D$53=1,$B4=""),"",ROUND(VLOOKUP(OP!$C$55,HL_2,$B4+1,0)*OP!$C$28,0)) -> #N/A
B5: =IF(OR(C4>=OP!$F$57,C4=""),"",IF(C4+1>OP!$F$57,OP!$F$57+1-$C$4,B4+1)) -> 2 | C5: =IF(OR(OP!$D$53=1,MAX($C4:C$4)>=OP!$F$57),"",C4+(B5-B4)) -> 16 | D5: =IF(OR(OP!$D$53=1,AND($B5>OP!$C$24)),"",OP!$C$52-IF($C5<16,$K4,0)) -> 16008 | E5: =IF(OR(OP!$D$53=1,$B5=""),"",N($E4)+N($D5)) -> 32016 | F5: =IF(OR(OP!$D$53=1,$B5="",ISERROR(VLOOKUP(OP!$C$55,SRV,$B5+1,0))),"",ROUND(VLOOKUP(OP!$C$55,SRV,$B5+1,0)*OP!$C$28,0)) | G5: =IF(OR(OP!$D$53=1,$B5="",ISERROR(VLOOKUP(OP!$C$55,SRV,$B5+1,0))),"",N($G4)+N($F5)) | H5: =IF(OR(OP!$D$53=1,$B5=""),"",ROUND(VLOOKUP(OP!$C$55,DIE,$B5+1,0)*OP!$C$28,0)) -> 32987 | I5: =IF(OR(OP!$D$53=1,$B5=""),"",ROUND(VLOOKUP(OP!$C$55,CV,$B5+1,0)*OP!$C$28,0)) -> #N/A | J5: =IF(OR(OP!$D$53=1,$B5=""),"",ROUND(VLOOKUP(OP!$C$55,PA,$B5+1,0)*OP!$C$28,0)) -> #N/A | S5: =IF(OR(OP!$D$53=1,$B5=""),"",N($F5)+N($O5)) -> 0 | T5: =IF(OR(OP!$D$53=1,$B5=""),0,N($T4)+N($S5)) -> 0 | U5: =IF(OR(OP!$D$53=1,$B5=""),"",ROUND($S5/12,0)) -> 0 | V5: =IF(OR(OP!$D$53=1,$B5=""),0,N($V4)+(N($U5)*12)) -> 0 | Y5: =IF(OR(OP!$D$53=1,$B5=""),"",ROUND(($H5+$Q5)*IF(OR($C5<16,$Z5=0,$Z5=""),1,PYO),0)) -> 32987 | Z5: =IF(OR(OP!$D$53=1,$B5=""),"",ROUND(($H5+Q5)*IF(OR($C5<16,($H5+$Q5)*PY!$C$4<PY!$D$5,($H5+$Q5)*PY!$C$4*PYR<PY!$C$5),0,PYY)*PYR,0)) -> 0 | AA5: =IF(OR(OP!$D$53=1,AND(B5>OP!$C$24)),"",OP!$C$52) -> 16008 | AB5: =IF(OR(OP!$D$53=1,$B5=""),"",N($AB4)+N($AA5)) -> 32016 | AH5: =IF(OR(OP!$D$53=1,$B5=""),"",ROUND(VLOOKUP(OP!$C$55,HL_1,$B5+1,0)*OP!$C$28,0)) -> #N/A | AI5: =IF(OR(OP!$D$53=1,$B5=""),"",ROUND(VLOOKUP(OP!$C$55,HL_2,$B5+1,0)*OP!$C$28,0)) -> #N/A
B6: =IF(OR(C5>=OP!$F$57,C5=""),"",IF(C5+1>OP!$F$57,OP!$F$57+1-$C$4,B5+1)) -> 3 | C6: =IF(OR(OP!$D$53=1,MAX($C$4:C5)>=OP!$F$57),"",C5+(B6-B5)) -> 17 | D6: =IF(OR(OP!$D$53=1,AND($B6>OP!$C$24)),"",OP!$C$52-IF($C6<16,$K5,0)) -> 16008 | E6: =IF(OR(OP!$D$53=1,$B6=""),"",N($E5)+N($D6)) -> 48024 | F6: =IF(OR(OP!$D$53=1,$B6="",ISERROR(VLOOKUP(OP!$C$55,SRV,$B6+1,0))),"",ROUND(VLOOKUP(OP!$C$55,SRV,$B6+1,0)*OP!$C$28,0)) | G6: =IF(OR(OP!$D$53=1,$B6="",ISERROR(VLOOKUP(OP!$C$55,SRV,$B6+1,0))),"",N($G5)+N($F6)) | H6: =IF(OR(OP!$D$53=1,$B6=""),"",ROUND(VLOOKUP(OP!$C$55,DIE,$B6+1,0)*OP!$C$28,0)) -> 49480 | I6: =IF(OR(OP!$D$53=1,$B6=""),"",ROUND(VLOOKUP(OP!$C$55,CV,$B6+1,0)*OP!$C$28,0)) -> #N/A | J6: =IF(OR(OP!$D$53=1,$B6=""),"",ROUND(VLOOKUP(OP!$C$55,PA,$B6+1,0)*OP!$C$28,0)) -> #N/A | S6: =IF(OR(OP!$D$53=1,$B6=""),"",N($F6)+N($O6)) -> 0 | T6: =IF(OR(OP!$D$53=1,$B6=""),0,N($T5)+N($S6)) -> 0 | U6: =IF(OR(OP!$D$53=1,$B6=""),"",ROUND($S6/12,0)) -> 0 | V6: =IF(OR(OP!$D$53=1,$B6=""),0,N($V5)+(N($U6)*12)) -> 0 | Y6: =IF(OR(OP!$D$53=1,$B6=""),"",ROUND(($H6+$Q6)*IF(OR($C6<16,$Z6=0,$Z6=""),1,PYO),0)) -> 49480 | Z6: =IF(OR(OP!$D$53=1,$B6=""),"",ROUND(($H6+Q6)*IF(OR($C6<16,($H6+$Q6)*PY!$C$4<PY!$D$5,($H6+$Q6)*PY!$C$4*PYR<PY!$C$5),0,PYY)*PYR,0)) -> 0 | AA6: =IF(OR(OP!$D$53=1,AND(B6>OP!$C$24)),"",OP!$C$52) -> 16008 | AB6: =IF(OR(OP!$D$53=1,$B6=""),"",N($AB5)+N($AA6)) -> 48024 | AH6: =IF(OR(OP!$D$53=1,$B6=""),"",ROUND(VLOOKUP(OP!$C$55,HL_1,$B6+1,0)*OP!$C$28,0)) -> #N/A | AI6: =IF(OR(OP!$D$53=1,$B6=""),"",ROUND(VLOOKUP(OP!$C$55,HL_2,$B6+1,0)*OP!$C$28,0)) -> #N/A
B7: =IF(OR(C6>=OP!$F$57,C6=""),"",IF(C6+1>OP!$F$57,OP!$F$57+1-$C$4,B6+1)) -> 4 | C7: =IF(OR(OP!$D$53=1,MAX($C$4:C6)>=OP!$F$57),"",C6+(B7-B6)) -> 18 | D7: =IF(OR(OP!$D$53=1,AND($B7>OP!$C$24)),"",OP!$C$52-IF($C7<16,$K6,0)) -> 16008 | E7: =IF(OR(OP!$D$53=1,$B7=""),"",N($E6)+N($D7)) -> 64032 | F7: =IF(OR(OP!$D$53=1,$B7="",ISERROR(VLOOKUP(OP!$C$55,SRV,$B7+1,0))),"",ROUND(VLOOKUP(OP!$C$55,SRV,$B7+1,0)*OP!$C$28,0)) | G7: =IF(OR(OP!$D$53=1,$B7="",ISERROR(VLOOKUP(OP!$C$55,SRV,$B7+1,0))),"",N($G6)+N($F7)) | H7: =IF(OR(OP!$D$53=1,$B7=""),"",ROUND(VLOOKUP(OP!$C$55,DIE,$B7+1,0)*OP!$C$28,0)) -> 65974 | I7: =IF(OR(OP!$D$53=1,$B7=""),"",ROUND(VLOOKUP(OP!$C$55,CV,$B7+1,0)*OP!$C$28,0)) -> #N/A | J7: =IF(OR(OP!$D$53=1,$B7=""),"",ROUND(VLOOKUP(OP!$C$55,PA,$B7+1,0)*OP!$C$28,0)) -> #N/A | S7: =IF(OR(OP!$D$53=1,$B7=""),"",N($F7)+N($O7)) -> 0 | T7: =IF(OR(OP!$D$53=1,$B7=""),0,N($T6)+N($S7)) -> 0 | U7: =IF(OR(OP!$D$53=1,$B7=""),"",ROUND($S7/12,0)) -> 0 | V7: =IF(OR(OP!$D$53=1,$B7=""),0,N($V6)+(N($U7)*12)) -> 0 | Y7: =IF(OR(OP!$D$53=1,$B7=""),"",ROUND(($H7+$Q7)*IF(OR($C7<16,$Z7=0,$Z7=""),1,PYO),0)) -> 65974 | Z7: =IF(OR(OP!$D$53=1,$B7=""),"",ROUND(($H7+Q7)*IF(OR($C7<16,($H7+$Q7)*PY!$C$4<PY!$D$5,($H7+$Q7)*PY!$C$4*PYR<PY!$C$5),0,PYY)*PYR,0)) -> 0 | AA7: =IF(OR(OP!$D$53=1,AND(B7>OP!$C$24)),"",OP!$C$52) -> 16008 | AB7: =IF(OR(OP!$D$53=1,$B7=""),"",N($AB6)+N($AA7)) -> 64032 | AH7: =IF(OR(OP!$D$53=1,$B7=""),"",ROUND(VLOOKUP(OP!$C$55,HL_1,$B7+1,0)*OP!$C$28,0)) -> #N/A | AI7: =IF(OR(OP!$D$53=1,$B7=""),"",ROUND(VLOOKUP(OP!$C$55,HL_2,$B7+1,0)*OP!$C$28,0)) -> #N/A
B8: =IF(OR(C7>=OP!$F$57,C7=""),"",IF(C7+1>OP!$F$57,OP!$F$57+1-$C$4,B7+1)) -> 5 | C8: =IF(OR(OP!$D$53=1,MAX($C$4:C7)>=OP!$F$57),"",C7+(B8-B7)) -> 19 | D8: =IF(OR(OP!$D$53=1,AND($B8>OP!$C$24)),"",OP!$C$52-IF($C8<16,$K7,0)) -> 16008 | E8: =IF(OR(OP!$D$53=1,$B8=""),"",N($E7)+N($D8)) -> 80040 | F8: =IF(OR(OP!$D$53=1,$B8="",ISERROR(VLOOKUP(OP!$C$55,SRV,$B8+1,0))),"",ROUND(VLOOKUP(OP!$C$55,SRV,$B8+1,0)*OP!$C$28,0)) | G8: =IF(OR(OP!$D$53=1,$B8="",ISERROR(VLOOKUP(OP!$C$55,SRV,$B8+1,0))),"",N($G7)+N($F8)) | H8: =IF(OR(OP!$D$53=1,$B8=""),"",ROUND(VLOOKUP(OP!$C$55,DIE,$B8+1,0)*OP!$C$28,0)) -> 82467 | I8: =IF(OR(OP!$D$53=1,$B8=""),"",ROUND(VLOOKUP(OP!$C$55,CV,$B8+1,0)*OP!$C$28,0)) -> #N/A | J8: =IF(OR(OP!$D$53=1,$B8=""),"",ROUND(VLOOKUP(OP!$C$55,PA,$B8+1,0)*OP!$C$28,0)) -> #N/A | S8: =IF(OR(OP!$D$53=1,$B8=""),"",N($F8)+N($O8)) -> 0 | T8: =IF(OR(OP!$D$53=1,$B8=""),0,N($T7)+N($S8)) -> 0 | U8: =IF(OR(OP!$D$53=1,$B8=""),"",ROUND($S8/12,0)) -> 0 | V8: =IF(OR(OP!$D$53=1,$B8=""),0,N($V7)+(N($U8)*12)) -> 0 | Y8: =IF(OR(OP!$D$53=1,$B8=""),"",ROUND(($H8+$Q8)*IF(OR($C8<16,$Z8=0,$Z8=""),1,PYO),0)) -> 82467 | Z8: =IF(OR(OP!$D$53=1,$B8=""),"",ROUND(($H8+Q8)*IF(OR($C8<16,($H8+$Q8)*PY!$C$4<PY!$D$5,($H8+$Q8)*PY!$C$4*PYR<PY!$C$5),0,PYY)*PYR,0)) -> 0 | AA8: =IF(OR(OP!$D$53=1,AND(B8>OP!$C$24)),"",OP!$C$52) -> 16008 | AB8: =IF(OR(OP!$D$53=1,$B8=""),"",N($AB7)+N($AA8)) -> 80040 | AH8: =IF(OR(OP!$D$53=1,$B8=""),"",ROUND(VLOOKUP(OP!$C$55,HL_1,$B8+1,0)*OP!$C$28,0)) -> #N/A | AI8: =IF(OR(OP!$D$53=1,$B8=""),"",ROUND(VLOOKUP(OP!$C$55,HL_2,$B8+1,0)*OP!$C$28,0)) -> #N/A
B9: =IF(OR(C8>=OP!$F$57,C8=""),"",IF(C8+1>OP!$F$57,OP!$F$57+1-$C$4,B8+1)) -> 6 | C9: =IF(OR(OP!$D$53=1,MAX($C$4:C8)>=OP!$F$57),"",C8+(B9-B8)) -> 20 | D9: =IF(OR(OP!$D$53=1,AND($B9>OP!$C$24)),"",OP!$C$52-IF($C9<16,$K8,0)) -> 16008 | E9: =IF(OR(OP!$D$53=1,$B9=""),"",N($E8)+N($D9)) -> 96048 | F9: =IF(OR(OP!$D$53=1,$B9="",ISERROR(VLOOKUP(OP!$C$55,SRV,$B9+1,0))),"",ROUND(VLOOKUP(OP!$C$55,SRV,$B9+1,0)*OP!$C$28,0)) | G9: =IF(OR(OP!$D$53=1,$B9="",ISERROR(VLOOKUP(OP!$C$55,SRV,$B9+1,0))),"",N($G8)+N($F9)) | H9: =IF(OR(OP!$D$53=1,$B9=""),"",ROUND(VLOOKUP(OP!$C$55,DIE,$B9+1,0)*OP!$C$28,0)) -> 98960 | I9: =IF(OR(OP!$D$53=1,$B9=""),"",ROUND(VLOOKUP(OP!$C$55,CV,$B9+1,0)*OP!$C$28,0)) -> #N/A | J9: =IF(OR(OP!$D$53=1,$B9=""),"",ROUND(VLOOKUP(OP!$C$55,PA,$B9+1,0)*OP!$C$28,0)) -> #N/A | S9: =IF(OR(OP!$D$53=1,$B9=""),"",N($F9)+N($O9)) -> 0 | T9: =IF(OR(OP!$D$53=1,$B9=""),0,N($T8)+N($S9)) -> 0 | U9: =IF(OR(OP!$D$53=1,$B9=""),"",ROUND($S9/12,0)) -> 0 | V9: =IF(OR(OP!$D$53=1,$B9=""),0,N($V8)+(N($U9)*12)) -> 0 | Y9: =IF(OR(OP!$D$53=1,$B9=""),"",ROUND(($H9+$Q9)*IF(OR($C9<16,$Z9=0,$Z9=""),1,PYO),0)) -> 98960 | Z9: =IF(OR(OP!$D$53=1,$B9=""),"",ROUND(($H9+Q9)*IF(OR($C9<16,($H9+$Q9)*PY!$C$4<PY!$D$5,($H9+$Q9)*PY!$C$4*PYR<PY!$C$5),0,PYY)*PYR,0)) -> 0 | AA9: =IF(OR(OP!$D$53=1,AND(B9>OP!$C$24)),"",OP!$C$52) -> 16008 | AB9: =IF(OR(OP!$D$53=1,$B9=""),"",N($AB8)+N($AA9)) -> 96048 | AH9: =IF(OR(OP!$D$53=1,$B9=""),"",ROUND(VLOOKUP(OP!$C$55,HL_1,$B9+1,0)*OP!$C$28,0)) -> #N/A | AI9: =IF(OR(OP!$D$53=1,$B9=""),"",ROUND(VLOOKUP(OP!$C$55,HL_2,$B9+1,0)*OP!$C$28,0)) -> #N/A
B10: =IF(OR(C9>=OP!$F$57,C9=""),"",IF(C9+1>OP!$F$57,OP!$F$57+1-$C$4,B9+1)) -> 7 | C10: =IF(OR(OP!$D$53=1,MAX($C$4:C9)>=OP!$F$57),"",C9+(B10-B9)) -> 21 | D10: =IF(OR(OP!$D$53=1,AND($B10>OP!$C$24)),"",OP!$C$52-IF($C10<16,$K9,0)) -> 16008 | E10: =IF(OR(OP!$D$53=1,$B10=""),"",N($E9)+N($D10)) -> 112056 | F10: =IF(OR(OP!$D$53=1,$B10="",ISERROR(VLOOKUP(OP!$C$55,SRV,$B10+1,0))),"",ROUND(VLOOKUP(OP!$C$55,SRV,$B10+1,0)*OP!$C$28,0)) | G10: =IF(OR(OP!$D$53=1,$B10="",ISERROR(VLOOKUP(OP!$C$55,SRV,$B10+1,0))),"",N($G9)+N($F10)) | H10: =IF(OR(OP!$D$53=1,$B10=""),"",ROUND(VLOOKUP(OP!$C$55,DIE,$B10+1,0)*OP!$C$28,0)) -> 115454 | I10: =IF(OR(OP!$D$53=1,$B10=""),"",ROUND(VLOOKUP(OP!$C$55,CV,$B10+1,0)*OP!$C$28,0)) -> #N/A | J10: =IF(OR(OP!$D$53=1,$B10=""),"",ROUND(VLOOKUP(OP!$C$55,PA,$B10+1,0)*OP!$C$28,0)) -> #N/A | S10: =IF(OR(OP!$D$53=1,$B10=""),"",N($F10)+N($O10)) -> 0 | T10: =IF(OR(OP!$D$53=1,$B10=""),0,N($T9)+N($S10)) -> 0 | U10: =IF(OR(OP!$D$53=1,$B10=""),"",ROUND($S10/12,0)) -> 0 | V10: =IF(OR(OP!$D$53=1,$B10=""),0,N($V9)+(N($U10)*12)) -> 0 | Y10: =IF(OR(OP!$D$53=1,$B10=""),"",ROUND(($H10+$Q10)*IF(OR($C10<16,$Z10=0,$Z10=""),1,PYO),0)) -> 115454 | Z10: =IF(OR(OP!$D$53=1,$B10=""),"",ROUND(($H10+Q10)*IF(OR($C10<16,($H10+$Q10)*PY!$C$4<PY!$D$5,($H10+$Q10)*PY!$C$4*PYR<PY!$C$5),0,PYY)*PYR,0)) -> 0 | AA10: =IF(OR(OP!$D$53=1,AND(B10>OP!$C$24)),"",OP!$C$52) -> 16008 | AB10: =IF(OR(OP!$D$53=1,$B10=""),"",N($AB9)+N($AA10)) -> 112056 | AH10: =IF(OR(OP!$D$53=1,$B10=""),"",ROUND(VLOOKUP(OP!$C$55,HL_1,$B10+1,0)*OP!$C$28,0)) -> #N/A | AI10: =IF(OR(OP!$D$53=1,$B10=""),"",ROUND(VLOOKUP(OP!$C$55,HL_2,$B10+1,0)*OP!$C$28,0)) -> #N/A
B11: =IF(OR(C10>=OP!$F$57,C10=""),"",IF(C10+1>OP!$F$57,OP!$F$57+1-$C$4,B10+1)) -> 8 | C11: =IF(OR(OP!$D$53=1,MAX($C$4:C10)>=OP!$F$57),"",C10+(B11-B10)) -> 22 | D11: =IF(OR(OP!$D$53=1,AND($B11>OP!$C$24)),"",OP!$C$52-IF($C11<16,$K10,0)) -> 16008 | E11: =IF(OR(OP!$D$53=1,$B11=""),"",N($E10)+N($D11)) -> 128064 | F11: =IF(OR(OP!$D$53=1,$B11="",ISERROR(VLOOKUP(OP!$C$55,SRV,$B11+1,0))),"",ROUND(VLOOKUP(OP!$C$55,SRV,$B11+1,0)*OP!$C$28,0)) | G11: =IF(OR(OP!$D$53=1,$B11="",ISERROR(VLOOKUP(OP!$C$55,SRV,$B11+1,0))),"",N($G10)+N($F11)) | H11: =IF(OR(OP!$D$53=1,$B11=""),"",ROUND(VLOOKUP(OP!$C$55,DIE,$B11+1,0)*OP!$C$28,0)) -> 131947 | I11: =IF(OR(OP!$D$53=1,$B11=""),"",ROUND(VLOOKUP(OP!$C$55,CV,$B11+1,0)*OP!$C$28,0)) -> #N/A | J11: =IF(OR(OP!$D$53=1,$B11=""),"",ROUND(VLOOKUP(OP!$C$55,PA,$B11+1,0)*OP!$C$28,0)) -> #N/A | S11: =IF(OR(OP!$D$53=1,$B11=""),"",N($F11)+N($O11)) -> 0 | T11: =IF(OR(OP!$D$53=1,$B11=""),0,N($T10)+N($S11)) -> 0 | U11: =IF(OR(OP!$D$53=1,$B11=""),"",ROUND($S11/12,0)) -> 0 | V11: =IF(OR(OP!$D$53=1,$B11=""),0,N($V10)+(N($U11)*12)) -> 0 | Y11: =IF(OR(OP!$D$53=1,$B11=""),"",ROUND(($H11+$Q11)*IF(OR($C11<16,$Z11=0,$Z11=""),1,PYO),0)) -> 131947 | Z11: =IF(OR(OP!$D$53=1,$B11=""),"",ROUND(($H11+Q11)*IF(OR($C11<16,($H11+$Q11)*PY!$C$4<PY!$D$5,($H11+$Q11)*PY!$C$4*PYR<PY!$C$5),0,PYY)*PYR,0)) -> 0 | AA11: =IF(OR(OP!$D$53=1,AND(B11>OP!$C$24)),"",OP!$C$52) -> 16008 | AB11: =IF(OR(OP!$D$53=1,$B11=""),"",N($AB10)+N($AA11)) -> 128064 | AH11: =IF(OR(OP!$D$53=1,$B11=""),"",ROUND(VLOOKUP(OP!$C$55,HL_1,$B11+1,0)*OP!$C$28,0)) -> #N/A | AI11: =IF(OR(OP!$D$53=1,$B11=""),"",ROUND(VLOOKUP(OP!$C$55,HL_2,$B11+1,0)*OP!$C$28,0)) -> #N/A
B12: =IF(OR(C11>=OP!$F$57,C11=""),"",IF(C11+1>OP!$F$57,OP!$F$57+1-$C$4,B11+1)) -> 9 | C12: =IF(OR(OP!$D$53=1,MAX($C$4:C11)>=OP!$F$57),"",C11+(B12-B11)) -> 23 | D12: =IF(OR(OP!$D$53=1,AND($B12>OP!$C$24)),"",OP!$C$52-IF($C12<16,$K11,0)) -> 16008 | E12: =IF(OR(OP!$D$53=1,$B12=""),"",N($E11)+N($D12)) -> 144072 | F12: =IF(OR(OP!$D$53=1,$B12="",ISERROR(VLOOKUP(OP!$C$55,SRV,$B12+1,0))),"",ROUND(VLOOKUP(OP!$C$55,SRV,$B12+1,0)*OP!$C$28,0)) | G12: =IF(OR(OP!$D$53=1,$B12="",ISERROR(VLOOKUP(OP!$C$55,SRV,$B12+1,0))),"",N($G11)+N($F12)) | H12: =IF(OR(OP!$D$53=1,$B12=""),"",ROUND(VLOOKUP(OP!$C$55,DIE,$B12+1,0)*OP!$C$28,0)) -> 148441 | I12: =IF(OR(OP!$D$53=1,$B12=""),"",ROUND(VLOOKUP(OP!$C$55,CV,$B12+1,0)*OP!$C$28,0)) -> #N/A | J12: =IF(OR(OP!$D$53=1,$B12=""),"",ROUND(VLOOKUP(OP!$C$55,PA,$B12+1,0)*OP!$C$28,0)) -> #N/A | S12: =IF(OR(OP!$D$53=1,$B12=""),"",N($F12)+N($O12)) -> 0 | T12: =IF(OR(OP!$D$53=1,$B12=""),0,N($T11)+N($S12)) -> 0 | U12: =IF(OR(OP!$D$53=1,$B12=""),"",ROUND($S12/12,0)) -> 0 | V12: =IF(OR(OP!$D$53=1,$B12=""),0,N($V11)+(N($U12)*12)) -> 0 | Y12: =IF(OR(OP!$D$53=1,$B12=""),"",ROUND(($H12+$Q12)*IF(OR($C12<16,$Z12=0,$Z12=""),1,PYO),0)) -> 148441 | Z12: =IF(OR(OP!$D$53=1,$B12=""),"",ROUND(($H12+Q12)*IF(OR($C12<16,($H12+$Q12)*PY!$C$4<PY!$D$5,($H12+$Q12)*PY!$C$4*PYR<PY!$C$5),0,PYY)*PYR,0)) -> 0 | AA12: =IF(OR(OP!$D$53=1,AND(B12>OP!$C$24)),"",OP!$C$52) -> 16008 | AB12: =IF(OR(OP!$D$53=1,$B12=""),"",N($AB11)+N($AA12)) -> 144072 | AH12: =IF(OR(OP!$D$53=1,$B12=""),"",ROUND(VLOOKUP(OP!$C$55,HL_1,$B12+1,0)*OP!$C$28,0)) -> #N/A | AI12: =IF(OR(OP!$D$53=1,$B12=""),"",ROUND(VLOOKUP(OP!$C$55,HL_2,$B12+1,0)*OP!$C$28,0)) -> #N/A
B13: =IF(OR(C12>=OP!$F$57,C12=""),"",IF(C12+1>OP!$F$57,OP!$F$57+1-$C$4,B12+1)) -> 10 | C13: =IF(OR(OP!$D$53=1,MAX($C$4:C12)>=OP!$F$57),"",C12+(B13-B12)) -> 24 | D13: =IF(OR(OP!$D$53=1,AND($B13>OP!$C$24)),"",OP!$C$52-IF($C13<16,$K12,0)) -> 16008 | E13: =IF(OR(OP!$D$53=1,$B13=""),"",N($E12)+N($D13)) -> 160080 | F13: =IF(OR(OP!$D$53=1,$B13="",ISERROR(VLOOKUP(OP!$C$55,SRV,$B13+1,0))),"",ROUND(VLOOKUP(OP!$C$55,SRV,$B13+1,0)*OP!$C$28,0)) | G13: =IF(OR(OP!$D$53=1,$B13="",ISERROR(VLOOKUP(OP!$C$55,SRV,$B13+1,0))),"",N($G12)+N($F13)) | H13: =IF(OR(OP!$D$53=1,$B13=""),"",ROUND(VLOOKUP(OP!$C$55,DIE,$B13+1,0)*OP!$C$28,0)) -> 164934 | I13: =IF(OR(OP!$D$53=1,$B13=""),"",ROUND(VLOOKUP(OP!$C$55,CV,$B13+1,0)*OP!$C$28,0)) -> #N/A | J13: =IF(OR(OP!$D$53=1,$B13=""),"",ROUND(VLOOKUP(OP!$C$55,PA,$B13+1,0)*OP!$C$28,0)) -> #N/A | S13: =IF(OR(OP!$D$53=1,$B13=""),"",N($F13)+N($O13)) -> 0 | T13: =IF(OR(OP!$D$53=1,$B13=""),0,N($T12)+N($S13)) -> 0 | U13: =IF(OR(OP!$D$53=1,$B13=""),"",ROUND($S13/12,0)) -> 0 | V13: =IF(OR(OP!$D$53=1,$B13=""),0,N($V12)+(N($U13)*12)) -> 0 | Y13: =IF(OR(OP!$D$53=1,$B13=""),"",ROUND(($H13+$Q13)*IF(OR($C13<16,$Z13=0,$Z13=""),1,PYO),0)) -> 164934 | Z13: =IF(OR(OP!$D$53=1,$B13=""),"",ROUND(($H13+Q13)*IF(OR($C13<16,($H13+$Q13)*PY!$C$4<PY!$D$5,($H13+$Q13)*PY!$C$4*PYR<PY!$C$5),0,PYY)*PYR,0)) -> 0 | AA13: =IF(OR(OP!$D$53=1,AND(B13>OP!$C$24)),"",OP!$C$52) -> 16008 | AB13: =IF(OR(OP!$D$53=1,$B13=""),"",N($AB12)+N($AA13)) -> 160080 | AH13: =IF(OR(OP!$D$53=1,$B13=""),"",ROUND(VLOOKUP(OP!$C$55,HL_1,$B13+1,0)*OP!$C$28,0)) -> #N/A | AI13: =IF(OR(OP!$D$53=1,$B13=""),"",ROUND(VLOOKUP(OP!$C$55,HL_2,$B13+1,0)*OP!$C$28,0)) -> #N/A
B14: =IF(OR(C13>=OP!$F$57,C13=""),"",IF(C13+1>OP!$F$57,OP!$F$57+1-$C$4,B13+1)) -> 11 | C14: =IF(OR(OP!$D$53=1,MAX($C$4:C13)>=OP!$F$57),"",C13+(B14-B13)) -> 25 | D14: =IF(OR(OP!$D$53=1,AND($B14>OP!$C$24)),"",OP!$C$52-IF($C14<16,$K13,0)) -> 16008 | E14: =IF(OR(OP!$D$53=1,$B14=""),"",N($E13)+N($D14)) -> 176088 | F14: =IF(OR(OP!$D$53=1,$B14="",ISERROR(VLOOKUP(OP!$C$55,SRV,$B14+1,0))),"",ROUND(VLOOKUP(OP!$C$55,SRV,$B14+1,0)*OP!$C$28,0)) | G14: =IF(OR(OP!$D$53=1,$B14="",ISERROR(VLOOKUP(OP!$C$55,SRV,$B14+1,0))),"",N($G13)+N($F14)) | H14: =IF(OR(OP!$D$53=1,$B14=""),"",ROUND(VLOOKUP(OP!$C$55,DIE,$B14+1,0)*OP!$C$28,0)) -> 181427 | I14: =IF(OR(OP!$D$53=1,$B14=""),"",ROUND(VLOOKUP(OP!$C$55,CV,$B14+1,0)*OP!$C$28,0)) -> #N/A | J14: =IF(OR(OP!$D$53=1,$B14=""),"",ROUND(VLOOKUP(OP!$C$55,PA,$B14+1,0)*OP!$C$28,0)) -> #N/A | S14: =IF(OR(OP!$D$53=1,$B14=""),"",N($F14)+N($O14)) -> 0 | T14: =IF(OR(OP!$D$53=1,$B14=""),0,N($T13)+N($S14)) -> 0 | U14: =IF(OR(OP!$D$53=1,$B14=""),"",ROUND($S14/12,0)) -> 0 | V14: =IF(OR(OP!$D$53=1,$B14=""),0,N($V13)+(N($U14)*12)) -> 0 | Y14: =IF(OR(OP!$D$53=1,$B14=""),"",ROUND(($H14+$Q14)*IF(OR($C14<16,$Z14=0,$Z14=""),1,PYO),0)) -> 181427 | Z14: =IF(OR(OP!$D$53=1,$B14=""),"",ROUND(($H14+Q14)*IF(OR($C14<16,($H14+$Q14)*PY!$C$4<PY!$D$5,($H14+$Q14)*PY!$C$4*PYR<PY!$C$5),0,PYY)*PYR,0)) -> 0 | AA14: =IF(OR(OP!$D$53=1,AND(B14>OP!$C$24)),"",OP!$C$52) -> 16008 | AB14: =IF(OR(OP!$D$53=1,$B14=""),"",N($AB13)+N($AA14)) -> 176088 | AH14: =IF(OR(OP!$D$53=1,$B14=""),"",ROUND(VLOOKUP(OP!$C$55,HL_1,$B14+1,0)*OP!$C$28,0)) -> #N/A | AI14: =IF(OR(OP!$D$53=1,$B14=""),"",ROUND(VLOOKUP(OP!$C$55,HL_2,$B14+1,0)*OP!$C$28,0)) -> #N/A
B15: =IF(OR(C14>=OP!$F$57,C14=""),"",IF(C14+1>OP!$F$57,OP!$F$57+1-$C$4,B14+1)) -> 12 | C15: =IF(OR(OP!$D$53=1,MAX($C$4:C14)>=OP!$F$57),"",C14+(B15-B14)) -> 26 | D15: =IF(OR(OP!$D$53=1,AND($B15>OP!$C$24)),"",OP!$C$52-IF($C15<16,$K14,0)) -> 16008 | E15: =IF(OR(OP!$D$53=1,$B15=""),"",N($E14)+N($D15)) -> 192096 | F15: =IF(OR(OP!$D$53=1,$B15="",ISERROR(VLOOKUP(OP!$C$55,SRV,$B15+1,0))),"",ROUND(VLOOKUP(OP!$C$55,SRV,$B15+1,0)*OP!$C$28,0)) | G15: =IF(OR(OP!$D$53=1,$B15="",ISERROR(VLOOKUP(OP!$C$55,SRV,$B15+1,0))),"",N($G14)+N($F15)) | H15: =IF(OR(OP!$D$53=1,$B15=""),"",ROUND(VLOOKUP(OP!$C$55,DIE,$B15+1,0)*OP!$C$28,0)) -> 197921 | I15: =IF(OR(OP!$D$53=1,$B15=""),"",ROUND(VLOOKUP(OP!$C$55,CV,$B15+1,0)*OP!$C$28,0)) -> #N/A | J15: =IF(OR(OP!$D$53=1,$B15=""),"",ROUND(VLOOKUP(OP!$C$55,PA,$B15+1,0)*OP!$C$28,0)) -> #N/A | S15: =IF(OR(OP!$D$53=1,$B15=""),"",N($F15)+N($O15)) -> 0 | T15: =IF(OR(OP!$D$53=1,$B15=""),0,N($T14)+N($S15)) -> 0 | U15: =IF(OR(OP!$D$53=1,$B15=""),"",ROUND($S15/12,0)) -> 0 | V15: =IF(OR(OP!$D$53=1,$B15=""),0,N($V14)+(N($U15)*12)) -> 0 | Y15: =IF(OR(OP!$D$53=1,$B15=""),"",ROUND(($H15+$Q15)*IF(OR($C15<16,$Z15=0,$Z15=""),1,PYO),0)) -> 197921 | Z15: =IF(OR(OP!$D$53=1,$B15=""),"",ROUND(($H15+Q15)*IF(OR($C15<16,($H15+$Q15)*PY!$C$4<PY!$D$5,($H15+$Q15)*PY!$C$4*PYR<PY!$C$5),0,PYY)*PYR,0)) -> 0 | AA15: =IF(OR(OP!$D$53=1,AND(B15>OP!$C$24)),"",OP!$C$52) -> 16008 | AB15: =IF(OR(OP!$D$53=1,$B15=""),"",N($AB14)+N($AA15)) -> 192096 | AH15: =IF(OR(OP!$D$53=1,$B15=""),"",ROUND(VLOOKUP(OP!$C$55,HL_1,$B15+1,0)*OP!$C$28,0)) -> #N/A | AI15: =IF(OR(OP!$D$53=1,$B15=""),"",ROUND(VLOOKUP(OP!$C$55,HL_2,$B15+1,0)*OP!$C$28,0)) -> #N/A
B16: =IF(OR(C15>=OP!$F$57,C15=""),"",IF(C15+1>OP!$F$57,OP!$F$57+1-$C$4,B15+1)) -> 13 | C16: =IF(OR(OP!$D$53=1,MAX($C$4:C15)>=OP!$F$57),"",C15+(B16-B15)) -> 27 | D16: =IF(OR(OP!$D$53=1,AND($B16>OP!$C$24)),"",OP!$C$52-IF($C16<16,$K15,0)) -> 16008 | E16: =IF(OR(OP!$D$53=1,$B16=""),"",N($E15)+N($D16)) -> 208104 | F16: =IF(OR(OP!$D$53=1,$B16="",ISERROR(VLOOKUP(OP!$C$55,SRV,$B16+1,0))),"",ROUND(VLOOKUP(OP!$C$55,SRV,$B16+1,0)*OP!$C$28,0)) | G16: =IF(OR(OP!$D$53=1,$B16="",ISERROR(VLOOKUP(OP!$C$55,SRV,$B16+1,0))),"",N($G15)+N($F16)) | H16: =IF(OR(OP!$D$53=1,$B16=""),"",ROUND(VLOOKUP(OP!$C$55,DIE,$B16+1,0)*OP!$C$28,0)) -> 214414 | I16: =IF(OR(OP!$D$53=1,$B16=""),"",ROUND(VLOOKUP(OP!$C$55,CV,$B16+1,0)*OP!$C$28,0)) -> #N/A | J16: =IF(OR(OP!$D$53=1,$B16=""),"",ROUND(VLOOKUP(OP!$C$55,PA,$B16+1,0)*OP!$C$28,0)) -> #N/A | S16: =IF(OR(OP!$D$53=1,$B16=""),"",N($F16)+N($O16)) -> 0 | T16: =IF(OR(OP!$D$53=1,$B16=""),0,N($T15)+N($S16)) -> 0 | U16: =IF(OR(OP!$D$53=1,$B16=""),"",ROUND($S16/12,0)) -> 0 | V16: =IF(OR(OP!$D$53=1,$B16=""),0,N($V15)+(N($U16)*12)) -> 0 | Y16: =IF(OR(OP!$D$53=1,$B16=""),"",ROUND(($H16+$Q16)*IF(OR($C16<16,$Z16=0,$Z16=""),1,PYO),0)) -> 214414 | Z16: =IF(OR(OP!$D$53=1,$B16=""),"",ROUND(($H16+Q16)*IF(OR($C16<16,($H16+$Q16)*PY!$C$4<PY!$D$5,($H16+$Q16)*PY!$C$4*PYR<PY!$C$5),0,PYY)*PYR,0)) -> 0 | AA16: =IF(OR(OP!$D$53=1,AND(B16>OP!$C$24)),"",OP!$C$52) -> 16008 | AB16: =IF(OR(OP!$D$53=1,$B16=""),"",N($AB15)+N($AA16)) -> 208104 | AH16: =IF(OR(OP!$D$53=1,$B16=""),"",ROUND(VLOOKUP(OP!$C$55,HL_1,$B16+1,0)*OP!$C$28,0)) -> #N/A | AI16: =IF(OR(OP!$D$53=1,$B16=""),"",ROUND(VLOOKUP(OP!$C$55,HL_2,$B16+1,0)*OP!$C$28,0)) -> #N/A
B17: =IF(OR(C16>=OP!$F$57,C16=""),"",IF(C16+1>OP!$F$57,OP!$F$57+1-$C$4,B16+1)) -> 14 | C17: =IF(OR(OP!$D$53=1,MAX($C$4:C16)>=OP!$F$57),"",C16+(B17-B16)) -> 28 | D17: =IF(OR(OP!$D$53=1,AND($B17>OP!$C$24)),"",OP!$C$52-IF($C17<16,$K16,0)) -> 16008 | E17: =IF(OR(OP!$D$53=1,$B17=""),"",N($E16)+N($D17)) -> 224112 | F17: =IF(OR(OP!$D$53=1,$B17="",ISERROR(VLOOKUP(OP!$C$55,SRV,$B17+1,0))),"",ROUND(VLOOKUP(OP!$C$55,SRV,$B17+1,0)*OP!$C$28,0)) | G17: =IF(OR(OP!$D$53=1,$B17="",ISERROR(VLOOKUP(OP!$C$55,SRV,$B17+1,0))),"",N($G16)+N($F17)) | H17: =IF(OR(OP!$D$53=1,$B17=""),"",ROUND(VLOOKUP(OP!$C$55,DIE,$B17+1,0)*OP!$C$28,0)) -> 230908 | I17: =IF(OR(OP!$D$53=1,$B17=""),"",ROUND(VLOOKUP(OP!$C$55,CV,$B17+1,0)*OP!$C$28,0)) -> #N/A | J17: =IF(OR(OP!$D$53=1,$B17=""),"",ROUND(VLOOKUP(OP!$C$55,PA,$B17+1,0)*OP!$C$28,0)) -> #N/A | S17: =IF(OR(OP!$D$53=1,$B17=""),"",N($F17)+N($O17)) -> 0 | T17: =IF(OR(OP!$D$53=1,$B17=""),0,N($T16)+N($S17)) -> 0 | U17: =IF(OR(OP!$D$53=1,$B17=""),"",ROUND($S17/12,0)) -> 0 | V17: =IF(OR(OP!$D$53=1,$B17=""),0,N($V16)+(N($U17)*12)) -> 0 | Y17: =IF(OR(OP!$D$53=1,$B17=""),"",ROUND(($H17+$Q17)*IF(OR($C17<16,$Z17=0,$Z17=""),1,PYO),0)) -> 230908 | Z17: =IF(OR(OP!$D$53=1,$B17=""),"",ROUND(($H17+Q17)*IF(OR($C17<16,($H17+$Q17)*PY!$C$4<PY!$D$5,($H17+$Q17)*PY!$C$4*PYR<PY!$C$5),0,PYY)*PYR,0)) -> 0 | AA17: =IF(OR(OP!$D$53=1,AND(B17>OP!$C$24)),"",OP!$C$52) -> 16008 | AB17: =IF(OR(OP!$D$53=1,$B17=""),"",N($AB16)+N($AA17)) -> 224112 | AH17: =IF(OR(OP!$D$53=1,$B17=""),"",ROUND(VLOOKUP(OP!$C$55,HL_1,$B17+1,0)*OP!$C$28,0)) -> #N/A | AI17: =IF(OR(OP!$D$53=1,$B17=""),"",ROUND(VLOOKUP(OP!$C$55,HL_2,$B17+1,0)*OP!$C$28,0)) -> #N/A
... B113: =IF(OR(C112>=OP!$F$57,C112=""),"",IF(C112+1>OP!$F$57,OP!$F$57+1-$C$4,B112+1)) | C113: =IF(OR(OP!$D$53=1,MAX($C$4:C112)>=OP!$F$57),"",C112+(B113-B112)) | D113: =IF(OR(OP!$D$53=1,AND($B113>OP!$C$24)),"",OP!$C$52-IF($C113<16,$K112,0)) | E113: =IF(OR(OP!$D$53=1,$B113=""),"",N($E112)+N($D113)) | F113: =IF(OR(OP!$D$53=1,$B113="",ISERROR(VLOOKUP(OP!$C$55,SRV,$B113+1,0))),"",ROUND(VLOOKUP(OP!$C$55,SRV,$B113+1,0)*OP!$C$28,0)) | G113: =IF(OR(OP!$D$53=1,$B113="",ISERROR(VLOOKUP(OP!$C$55,SRV,$B113+1,0))),"",N($G112)+N($F113)) | H113: =IF(OR(OP!$D$53=1,$B113=""),"",ROUND(VLOOKUP(OP!$C$55,DIE,$B113+1,0)*OP!$C$28,0)) | I113: =IF(OR(OP!$D$53=1,$B113=""),"",ROUND(VLOOKUP(OP!$C$55,CV,$B113+1,0)*OP!$C$28,0)) | J113: =IF(OR(OP!$D$53=1,$B113=""),"",ROUND(VLOOKUP(OP!$C$55,PA,$B113+1,0)*OP!$C$28,0)) | S113: =IF(OR(OP!$D$53=1,$B113=""),"",N($F113)+N($O113)) | T113: =IF(OR(OP!$D$53=1,$B113=""),0,N($T112)+N($S113)) -> 0 | U113: =IF(OR(OP!$D$53=1,$B113=""),"",ROUND($S113/12,0)) | V113: =IF(OR(OP!$D$53=1,$B113=""),0,N($V112)+(N($U113)*12)) -> 0 | Y113: =IF(OR(OP!$D$53=1,$B113=""),"",ROUND(($H113+$Q113)*IF(OR($C113<16,$Z113=0,$Z113=""),1,PYO),0)) | Z113: =IF(OR(OP!$D$53=1,$B113=""),"",ROUND(($H113+Q113)*IF(OR($C113<16,($H113+$Q113)*PY!$C$4<PY!$D$5,($H113+$Q113)*PY!$C$4*PYR<PY!$C$5),0,PYY)*PYR,0)) | AA113: =IF(OR(OP!$D$53=1,AND(B113>OP!$C$24)),"",OP!$C$52) | AB113: =IF(OR(OP!$D$53=1,$B113=""),"",N($AB112)+N($AA113)) | AH113: =IF(OR(OP!$D$53=1,$B113=""),"",ROUND(VLOOKUP(OP!$C$55,HL_1,$B113+1,0)*OP!$C$28,0)) | AI113: =IF(OR(OP!$D$53=1,$B113=""),"",ROUND(VLOOKUP(OP!$C$55,HL_2,$B113+1,0)*OP!$C$28,0))
B114: =IF(OR(C113>=OP!$F$57,C113=""),"",IF(C113+1>OP!$F$57,OP!$F$57+1-$C$4,B113+1)) | C114: =IF(OR(OP!$D$53=1,MAX($C$4:C113)>=OP!$F$57),"",C113+(B114-B113)) | D114: =IF(OR(OP!$D$53=1,AND($B114>OP!$C$24)),"",OP!$C$52-IF($C114<16,$K113,0)) | E114: =IF(OR(OP!$D$53=1,$B114=""),"",N($E113)+N($D114)) | F114: =IF(OR(OP!$D$53=1,$B114="",ISERROR(VLOOKUP(OP!$C$55,SRV,$B114+1,0))),"",ROUND(VLOOKUP(OP!$C$55,SRV,$B114+1,0)*OP!$C$28,0)) | G114: =IF(OR(OP!$D$53=1,$B114="",ISERROR(VLOOKUP(OP!$C$55,SRV,$B114+1,0))),"",N($G113)+N($F114)) | H114: =IF(OR(OP!$D$53=1,$B114=""),"",ROUND(VLOOKUP(OP!$C$55,DIE,$B114+1,0)*OP!$C$28,0)) | I114: =IF(OR(OP!$D$53=1,$B114=""),"",ROUND(VLOOKUP(OP!$C$55,CV,$B114+1,0)*OP!$C$28,0)) | J114: =IF(OR(OP!$D$53=1,$B114=""),"",ROUND(VLOOKUP(OP!$C$55,PA,$B114+1,0)*OP!$C$28,0)) | K114: =IF(OR(OP!$D$53=1,B114=""),"",VLOOKUP($B114,more1,7,0)) | S114: =IF(OR(OP!$D$53=1,$B114=""),"",N($F114)+N($O114)) | T114: =IF(OR(OP!$D$53=1,$B114=""),0,N($T113)+N($S114)) -> 0 | U114: =IF(OR(OP!$D$53=1,$B114=""),"",ROUND($S114/12,0)) | V114: =IF(OR(OP!$D$53=1,$B114=""),0,N($V113)+(N($U114)*12)) -> 0 | Y114: =IF(OR(OP!$D$53=1,$B114=""),"",ROUND(($H114+$Q114)*IF(OR($C114<16,$Z114=0,$Z114=""),1,PYO),0)) | Z114: =IF(OR(OP!$D$53=1,$B114=""),"",ROUND(($H114+Q114)*IF(OR($C114<16,($H114+$Q114)*PY!$C$4<PY!$D$5,($H114+$Q114)*PY!$C$4*PYR<PY!$C$5),0,PYY)*PYR,0)) | AA114: =IF(OR(OP!$D$53=1,AND(B114>OP!$C$24)),"",OP!$C$52) | AB114: =IF(OR(OP!$D$53=1,$B114=""),"",N($AB113)+N($AA114)) | AH114: =IF(OR(OP!$D$53=1,$B114=""),"",ROUND(VLOOKUP(OP!$C$55,HL_1,$B114+1,0)*OP!$C$28,0)) | AI114: =IF(OR(OP!$D$53=1,$B114=""),"",ROUND(VLOOKUP(OP!$C$55,HL_2,$B114+1,0)*OP!$C$28,0))
B115: 祝壽保險金 | G115: =IF(OR(OP!$D$53=1,$B115="",ISERROR(VLOOKUP(OP!$C$55,SRV,$B115+1,0))),"",N($G114)+N($F115)) | H115: =IF(OR(OP!$D$53=1),"",ROUND(VLOOKUP(OP!$C$55,EXP,OP!$D$57+1,0)*OP!$C$28,0)) -> 494802 | P115: EXP
C130: 2 | D130: 7 | E130: 8 | F130: 18 | G130: 13 | H130: 16 | I130: 17 | J130: 0 | K130: 0 | L130: 0 | M130: 0 | N130: 0 | O130: 0 | P130: 0 | Q130: 0 | R130: 0 | S130: 0 | T130: 0
B131: 年度 | C131: =VLOOKUP($B131,TOV,C$130,0) -> #N/A | D131: =IF(ISERROR(VLOOKUP($B131,TOV,D$130,0)),"",VLOOKUP($B131,TOV,D$130,0)) | E131: =IF(ISERROR(VLOOKUP($B131,TOV,E$130,0)),"",VLOOKUP($B131,TOV,E$130,0)) | F131: =IF(ISERROR(VLOOKUP($B131,TOV,F$130,0)),"",VLOOKUP($B131,TOV,F$130,0)) | G131: =IF(ISERROR(VLOOKUP($B131,TOV,G$130,0)),"",VLOOKUP($B131,TOV,G$130,0)) | H131: =IF(ISERROR(VLOOKUP($B131,TOV,H$130,0)),"",VLOOKUP($B131,TOV,H$130,0)) | I131: =IF(ISERROR(VLOOKUP($B131,TOV,I$130,0)),"",VLOOKUP($B131,TOV,I$130,0)) | J131: =IF(ISERROR(VLOOKUP($B131,TOV,J$130,0)),"",VLOOKUP($B131,TOV,J$130,0)) | K131: =IF(ISERROR(VLOOKUP($B131,TOV,K$130,0)),"",VLOOKUP($B131,TOV,K$130,0)) | ... T131: =IF(ISERROR(VLOOKUP($B131,TOV,T$130,0)),"",VLOOKUP($B131,TOV,T$130,0))
B132: 1 | C132: =VLOOKUP($B132,TOV,C$130,0) -> 15 | D132: =IF(ISERROR(VLOOKUP($B132,TOV,D$130,0)),"",VLOOKUP($B132,TOV,D$130,0)) -> 16493 | E132: =IF(ISERROR(VLOOKUP($B132,TOV,E$130,0)),"",VLOOKUP($B132,TOV,E$130,0)) | F132: =IF(ISERROR(VLOOKUP($B132,TOV,F$130,0)),"",VLOOKUP($B132,TOV,F$130,0)) -> 0 | G132: =IF(ISERROR(VLOOKUP($B132,TOV,G$130,0)),"",VLOOKUP($B132,TOV,G$130,0)) -> 0 | H132: =IF(ISERROR(VLOOKUP($B132,TOV,H$130,0)),"",VLOOKUP($B132,TOV,H$130,0)) -> 0 | I132: =IF(ISERROR(VLOOKUP($B132,TOV,I$130,0)),"",VLOOKUP($B132,TOV,I$130,0)) -> 0 | J132: =IF(ISERROR(VLOOKUP($B132,TOV,J$130,0)),"",VLOOKUP($B132,TOV,J$130,0)) | K132: =IF(ISERROR(VLOOKUP($B132,TOV,K$130,0)),"",VLOOKUP($B132,TOV,K$130,0)) | ... T132: =IF(ISERROR(VLOOKUP($B132,TOV,T$130,0)),"",VLOOKUP($B132,TOV,T$130,0))
B133: 2 | C133: =VLOOKUP($B133,TOV,C$130,0) -> 16 | D133: =IF(ISERROR(VLOOKUP($B133,TOV,D$130,0)),"",VLOOKUP($B133,TOV,D$130,0)) -> 32987 | E133: =IF(ISERROR(VLOOKUP($B133,TOV,E$130,0)),"",VLOOKUP($B133,TOV,E$130,0)) | F133: =IF(ISERROR(VLOOKUP($B133,TOV,F$130,0)),"",VLOOKUP($B133,TOV,F$130,0)) -> 0 | G133: =IF(ISERROR(VLOOKUP($B133,TOV,G$130,0)),"",VLOOKUP($B133,TOV,G$130,0)) -> 0 | H133: =IF(ISERROR(VLOOKUP($B133,TOV,H$130,0)),"",VLOOKUP($B133,TOV,H$130,0)) -> 0 | I133: =IF(ISERROR(VLOOKUP($B133,TOV,I$130,0)),"",VLOOKUP($B133,TOV,I$130,0)) -> 0 | J133: =IF(ISERROR(VLOOKUP($B133,TOV,J$130,0)),"",VLOOKUP($B133,TOV,J$130,0)) | K133: =IF(ISERROR(VLOOKUP($B133,TOV,K$130,0)),"",VLOOKUP($B133,TOV,K$130,0)) | ... T133: =IF(ISERROR(VLOOKUP($B133,TOV,T$130,0)),"",VLOOKUP($B133,TOV,T$130,0))
B134: 3 | C134: =VLOOKUP($B134,TOV,C$130,0) -> 17 | D134: =IF(ISERROR(VLOOKUP($B134,TOV,D$130,0)),"",VLOOKUP($B134,TOV,D$130,0)) -> 49480 | E134: =IF(ISERROR(VLOOKUP($B134,TOV,E$130,0)),"",VLOOKUP($B134,TOV,E$130,0)) | F134: =IF(ISERROR(VLOOKUP($B134,TOV,F$130,0)),"",VLOOKUP($B134,TOV,F$130,0)) -> 0 | G134: =IF(ISERROR(VLOOKUP($B134,TOV,G$130,0)),"",VLOOKUP($B134,TOV,G$130,0)) -> 0 | H134: =IF(ISERROR(VLOOKUP($B134,TOV,H$130,0)),"",VLOOKUP($B134,TOV,H$130,0)) -> 0 | I134: =IF(ISERROR(VLOOKUP($B134,TOV,I$130,0)),"",VLOOKUP($B134,TOV,I$130,0)) -> 0 | J134: =IF(ISERROR(VLOOKUP($B134,TOV,J$130,0)),"",VLOOKUP($B134,TOV,J$130,0)) | K134: =IF(ISERROR(VLOOKUP($B134,TOV,K$130,0)),"",VLOOKUP($B134,TOV,K$130,0)) | ... T134: =IF(ISERROR(VLOOKUP($B134,TOV,T$130,0)),"",VLOOKUP($B134,TOV,T$130,0))
B135: 4 | C135: =VLOOKUP($B135,TOV,C$130,0) -> 18 | D135: =IF(ISERROR(VLOOKUP($B135,TOV,D$130,0)),"",VLOOKUP($B135,TOV,D$130,0)) -> 65974 | E135: =IF(ISERROR(VLOOKUP($B135,TOV,E$130,0)),"",VLOOKUP($B135,TOV,E$130,0)) | F135: =IF(ISERROR(VLOOKUP($B135,TOV,F$130,0)),"",VLOOKUP($B135,TOV,F$130,0)) -> 0 | G135: =IF(ISERROR(VLOOKUP($B135,TOV,G$130,0)),"",VLOOKUP($B135,TOV,G$130,0)) -> 0 | H135: =IF(ISERROR(VLOOKUP($B135,TOV,H$130,0)),"",VLOOKUP($B135,TOV,H$130,0)) -> 0 | I135: =IF(ISERROR(VLOOKUP($B135,TOV,I$130,0)),"",VLOOKUP($B135,TOV,I$130,0)) -> 0 | J135: =IF(ISERROR(VLOOKUP($B135,TOV,J$130,0)),"",VLOOKUP($B135,TOV,J$130,0)) | K135: =IF(ISERROR(VLOOKUP($B135,TOV,K$130,0)),"",VLOOKUP($B135,TOV,K$130,0)) | ... T135: =IF(ISERROR(VLOOKUP($B135,TOV,T$130,0)),"",VLOOKUP($B135,TOV,T$130,0))
B136: 5 | C136: =VLOOKUP($B136,TOV,C$130,0) -> 19 | D136: =IF(ISERROR(VLOOKUP($B136,TOV,D$130,0)),"",VLOOKUP($B136,TOV,D$130,0)) -> 82467 | E136: =IF(ISERROR(VLOOKUP($B136,TOV,E$130,0)),"",VLOOKUP($B136,TOV,E$130,0)) | F136: =IF(ISERROR(VLOOKUP($B136,TOV,F$130,0)),"",VLOOKUP($B136,TOV,F$130,0)) -> 0 | G136: =IF(ISERROR(VLOOKUP($B136,TOV,G$130,0)),"",VLOOKUP($B136,TOV,G$130,0)) -> 0 | H136: =IF(ISERROR(VLOOKUP($B136,TOV,H$130,0)),"",VLOOKUP($B136,TOV,H$130,0)) -> 0 | I136: =IF(ISERROR(VLOOKUP($B136,TOV,I$130,0)),"",VLOOKUP($B136,TOV,I$130,0)) -> 0 | J136: =IF(ISERROR(VLOOKUP($B136,TOV,J$130,0)),"",VLOOKUP($B136,TOV,J$130,0)) | K136: =IF(ISERROR(VLOOKUP($B136,TOV,K$130,0)),"",VLOOKUP($B136,TOV,K$130,0)) | ... T136: =IF(ISERROR(VLOOKUP($B136,TOV,T$130,0)),"",VLOOKUP($B136,TOV,T$130,0))
B137: 6 | C137: =VLOOKUP($B137,TOV,C$130,0) -> 20 | D137: =IF(ISERROR(VLOOKUP($B137,TOV,D$130,0)),"",VLOOKUP($B137,TOV,D$130,0)) -> 98960 | E137: =IF(ISERROR(VLOOKUP($B137,TOV,E$130,0)),"",VLOOKUP($B137,TOV,E$130,0)) | F137: =IF(ISERROR(VLOOKUP($B137,TOV,F$130,0)),"",VLOOKUP($B137,TOV,F$130,0)) -> 0 | G137: =IF(ISERROR(VLOOKUP($B137,TOV,G$130,0)),"",VLOOKUP($B137,TOV,G$130,0)) -> 0 | H137: =IF(ISERROR(VLOOKUP($B137,TOV,H$130,0)),"",VLOOKUP($B137,TOV,H$130,0)) -> 0 | I137: =IF(ISERROR(VLOOKUP($B137,TOV,I$130,0)),"",VLOOKUP($B137,TOV,I$130,0)) -> 0 | J137: =IF(ISERROR(VLOOKUP($B137,TOV,J$130,0)),"",VLOOKUP($B137,TOV,J$130,0)) | K137: =IF(ISERROR(VLOOKUP($B137,TOV,K$130,0)),"",VLOOKUP($B137,TOV,K$130,0)) | ... T137: =IF(ISERROR(VLOOKUP($B137,TOV,T$130,0)),"",VLOOKUP($B137,TOV,T$130,0))
B138: 7 | C138: =VLOOKUP($B138,TOV,C$130,0) -> 21 | D138: =IF(ISERROR(VLOOKUP($B138,TOV,D$130,0)),"",VLOOKUP($B138,TOV,D$130,0)) -> 115454 | E138: =IF(ISERROR(VLOOKUP($B138,TOV,E$130,0)),"",VLOOKUP($B138,TOV,E$130,0)) | F138: =IF(ISERROR(VLOOKUP($B138,TOV,F$130,0)),"",VLOOKUP($B138,TOV,F$130,0)) -> 0 | G138: =IF(ISERROR(VLOOKUP($B138,TOV,G$130,0)),"",VLOOKUP($B138,TOV,G$130,0)) -> 0 | H138: =IF(ISERROR(VLOOKUP($B138,TOV,H$130,0)),"",VLOOKUP($B138,TOV,H$130,0)) -> 0 | I138: =IF(ISERROR(VLOOKUP($B138,TOV,I$130,0)),"",VLOOKUP($B138,TOV,I$130,0)) -> 0 | J138: =IF(ISERROR(VLOOKUP($B138,TOV,J$130,0)),"",VLOOKUP($B138,TOV,J$130,0)) | K138: =IF(ISERROR(VLOOKUP($B138,TOV,K$130,0)),"",VLOOKUP($B138,TOV,K$130,0)) | ... T138: =IF(ISERROR(VLOOKUP($B138,TOV,T$130,0)),"",VLOOKUP($B138,TOV,T$130,0))
B139: 8 | C139: =VLOOKUP($B139,TOV,C$130,0) -> 22 | D139: =IF(ISERROR(VLOOKUP($B139,TOV,D$130,0)),"",VLOOKUP($B139,TOV,D$130,0)) -> 131947 | E139: =IF(ISERROR(VLOOKUP($B139,TOV,E$130,0)),"",VLOOKUP($B139,TOV,E$130,0)) | F139: =IF(ISERROR(VLOOKUP($B139,TOV,F$130,0)),"",VLOOKUP($B139,TOV,F$130,0)) -> 0 | G139: =IF(ISERROR(VLOOKUP($B139,TOV,G$130,0)),"",VLOOKUP($B139,TOV,G$130,0)) -> 0 | H139: =IF(ISERROR(VLOOKUP($B139,TOV,H$130,0)),"",VLOOKUP($B139,TOV,H$130,0)) -> 0 | I139: =IF(ISERROR(VLOOKUP($B139,TOV,I$130,0)),"",VLOOKUP($B139,TOV,I$130,0)) -> 0 | J139: =IF(ISERROR(VLOOKUP($B139,TOV,J$130,0)),"",VLOOKUP($B139,TOV,J$130,0)) | K139: =IF(ISERROR(VLOOKUP($B139,TOV,K$130,0)),"",VLOOKUP($B139,TOV,K$130,0)) | ... T139: =IF(ISERROR(VLOOKUP($B139,TOV,T$130,0)),"",VLOOKUP($B139,TOV,T$130,0))
B140: 9 | C140: =VLOOKUP($B140,TOV,C$130,0) -> 23 | D140: =IF(ISERROR(VLOOKUP($B140,TOV,D$130,0)),"",VLOOKUP($B140,TOV,D$130,0)) -> 148441 | E140: =IF(ISERROR(VLOOKUP($B140,TOV,E$130,0)),"",VLOOKUP($B140,TOV,E$130,0)) | F140: =IF(ISERROR(VLOOKUP($B140,TOV,F$130,0)),"",VLOOKUP($B140,TOV,F$130,0)) -> 0 | G140: =IF(ISERROR(VLOOKUP($B140,TOV,G$130,0)),"",VLOOKUP($B140,TOV,G$130,0)) -> 0 | H140: =IF(ISERROR(VLOOKUP($B140,TOV,H$130,0)),"",VLOOKUP($B140,TOV,H$130,0)) -> 0 | I140: =IF(ISERROR(VLOOKUP($B140,TOV,I$130,0)),"",VLOOKUP($B140,TOV,I$130,0)) -> 0 | J140: =IF(ISERROR(VLOOKUP($B140,TOV,J$130,0)),"",VLOOKUP($B140,TOV,J$130,0)) | K140: =IF(ISERROR(VLOOKUP($B140,TOV,K$130,0)),"",VLOOKUP($B140,TOV,K$130,0)) | ... T140: =IF(ISERROR(VLOOKUP($B140,TOV,T$130,0)),"",VLOOKUP($B140,TOV,T$130,0))
B141: 10 | C141: =VLOOKUP($B141,TOV,C$130,0) -> 24 | D141: =IF(ISERROR(VLOOKUP($B141,TOV,D$130,0)),"",VLOOKUP($B141,TOV,D$130,0)) -> 164934 | E141: =IF(ISERROR(VLOOKUP($B141,TOV,E$130,0)),"",VLOOKUP($B141,TOV,E$130,0)) | F141: =IF(ISERROR(VLOOKUP($B141,TOV,F$130,0)),"",VLOOKUP($B141,TOV,F$130,0)) -> 0 | G141: =IF(ISERROR(VLOOKUP($B141,TOV,G$130,0)),"",VLOOKUP($B141,TOV,G$130,0)) -> 0 | H141: =IF(ISERROR(VLOOKUP($B141,TOV,H$130,0)),"",VLOOKUP($B141,TOV,H$130,0)) -> 0 | I141: =IF(ISERROR(VLOOKUP($B141,TOV,I$130,0)),"",VLOOKUP($B141,TOV,I$130,0)) -> 0 | J141: =IF(ISERROR(VLOOKUP($B141,TOV,J$130,0)),"",VLOOKUP($B141,TOV,J$130,0)) | K141: =IF(ISERROR(VLOOKUP($B141,TOV,K$130,0)),"",VLOOKUP($B141,TOV,K$130,0)) | ... T141: =IF(ISERROR(VLOOKUP($B141,TOV,T$130,0)),"",VLOOKUP($B141,TOV,T$130,0))
B142: 20 | C142: =VLOOKUP($B142,TOV,C$130,0) -> 34 | D142: =IF(ISERROR(VLOOKUP($B142,TOV,D$130,0)),"",VLOOKUP($B142,TOV,D$130,0)) -> 329868 | E142: =IF(ISERROR(VLOOKUP($B142,TOV,E$130,0)),"",VLOOKUP($B142,TOV,E$130,0)) | F142: =IF(ISERROR(VLOOKUP($B142,TOV,F$130,0)),"",VLOOKUP($B142,TOV,F$130,0)) -> 0 | G142: =IF(ISERROR(VLOOKUP($B142,TOV,G$130,0)),"",VLOOKUP($B142,TOV,G$130,0)) -> 0 | H142: =IF(ISERROR(VLOOKUP($B142,TOV,H$130,0)),"",VLOOKUP($B142,TOV,H$130,0)) -> 0 | I142: =IF(ISERROR(VLOOKUP($B142,TOV,I$130,0)),"",VLOOKUP($B142,TOV,I$130,0)) -> 0 | J142: =IF(ISERROR(VLOOKUP($B142,TOV,J$130,0)),"",VLOOKUP($B142,TOV,J$130,0)) | K142: =IF(ISERROR(VLOOKUP($B142,TOV,K$130,0)),"",VLOOKUP($B142,TOV,K$130,0)) | ... T142: =IF(ISERROR(VLOOKUP($B142,TOV,T$130,0)),"",VLOOKUP($B142,TOV,T$130,0))
B143: 30 | C143: =VLOOKUP($B143,TOV,C$130,0) -> 44 | D143: =IF(ISERROR(VLOOKUP($B143,TOV,D$130,0)),"",VLOOKUP($B143,TOV,D$130,0)) -> 494802 | E143: =IF(ISERROR(VLOOKUP($B143,TOV,E$130,0)),"",VLOOKUP($B143,TOV,E$130,0)) | F143: =IF(ISERROR(VLOOKUP($B143,TOV,F$130,0)),"",VLOOKUP($B143,TOV,F$130,0)) -> 0 | G143: =IF(ISERROR(VLOOKUP($B143,TOV,G$130,0)),"",VLOOKUP($B143,TOV,G$130,0)) -> 0 | H143: =IF(ISERROR(VLOOKUP($B143,TOV,H$130,0)),"",VLOOKUP($B143,TOV,H$130,0)) -> 0 | I143: =IF(ISERROR(VLOOKUP($B143,TOV,I$130,0)),"",VLOOKUP($B143,TOV,I$130,0)) -> 0 | J143: =IF(ISERROR(VLOOKUP($B143,TOV,J$130,0)),"",VLOOKUP($B143,TOV,J$130,0)) | K143: =IF(ISERROR(VLOOKUP($B143,TOV,K$130,0)),"",VLOOKUP($B143,TOV,K$130,0)) | ... T143: =IF(ISERROR(VLOOKUP($B143,TOV,T$130,0)),"",VLOOKUP($B143,TOV,T$130,0))
... B148: 76 | C148: =VLOOKUP($B148,TOV,C$130,0) -> 90 | D148: =IF(ISERROR(VLOOKUP($B148,TOV,D$130,0)),"",VLOOKUP($B148,TOV,D$130,0)) -> 494802 | E148: =IF(ISERROR(VLOOKUP($B148,TOV,E$130,0)),"",VLOOKUP($B148,TOV,E$130,0)) | F148: =IF(ISERROR(VLOOKUP($B148,TOV,F$130,0)),"",VLOOKUP($B148,TOV,F$130,0)) -> 0 | G148: =IF(ISERROR(VLOOKUP($B148,TOV,G$130,0)),"",VLOOKUP($B148,TOV,G$130,0)) -> 0 | H148: =IF(ISERROR(VLOOKUP($B148,TOV,H$130,0)),"",VLOOKUP($B148,TOV,H$130,0)) -> 0 | I148: =IF(ISERROR(VLOOKUP($B148,TOV,I$130,0)),"",VLOOKUP($B148,TOV,I$130,0)) -> 0 | J148: =IF(ISERROR(VLOOKUP($B148,TOV,J$130,0)),"",VLOOKUP($B148,TOV,J$130,0)) | K148: =IF(ISERROR(VLOOKUP($B148,TOV,K$130,0)),"",VLOOKUP($B148,TOV,K$130,0)) | ... T148: =IF(ISERROR(VLOOKUP($B148,TOV,T$130,0)),"",VLOOKUP($B148,TOV,T$130,0))

Sheet OP
B1: 非連生：1、連生：2 | S1: 控制項目 | AA1: 被保險人2 | AB1: 姓名 | AC1: =輸入頁!$E$8 -> 客戶 | BA1: 一銀 | BH1: 上銀
B2: 1 | C2: 試算日 | D2: 生日 | E2: 驗證 | H2: 彈性繳 | I2: 1 | J2: 1 | K2: 1 | S2: 性別：En_Sex | T2: 繳別：En_PayT | U2: 繳費方式-首期：En_PayMF | V2: 繳費方式-續期：En_PayMR | W2: 給付方式：En_BFM | AB2: fubon | AC2: 試算日 | AD2: 生日 | AE2: 驗證 | AL2: =$C$69 -> 銀保 | BA2: 險種 | BB2: 最低年齡 | BC2: 最高年齡 | BD2: 最長年期 | BE2: 通算保額係數 | BF2: 通算保額係數欄位判定 | BH2: 商品別： | BI2: =$C$21 -> 1
B3: =IF(C4=0,0,VALUE(MID(C4,IF(LEN(C4)=7,4,3),2))) -> 1 | C3: =IF(input_s!H8=1,TODAY(),IF(TODAY()<DATE(2026,7,20),DATE(2026,7,20),TODAY())) -> 46259 | D3: =IF(C4=0,0,DATE(LEFT(C4,IF(LEN(C4)=7,3,2))+1911,MID(C4,IF(LEN(C4)=7,4,3),2),RIGHT(C4,2))) -> 40909 | E3: =IF(E4=1,0,IF(OR(B3=1,B3=3,B3=5,B3=7,B3=8,B3=10,B3=12),31,IF(OR(B3=4,B3=6,B3=9,B3=11),30,IF(OR(AND(B3=2,YEAR(D3)=2000),AND(B3=2,YEAR(D3)/4=INT(YEAR(D3)/4),YEAR(D3)/400<>INT(YEAR(D3)/400))),29,28)))) -> 31 | F3: =YEAR(TODAY())-1911 -> 115 | H3: 躉繳 | I3: 1 | J3: 1 | K3: 1 | S3: 男 | T3: 彈性繳 | U3: =IF($C$21=1,"匯款","外幣匯款") -> 匯款 | V3: 金融機構轉帳 | W3: 購買增額繳清保險金額 | AB3: =IF(AC4=0,0,VALUE(MID(AC4,IF(LEN(AC4)=7,4,3),2))) -> 11 | AD3: =IF(AC4=0,0,DATE(LEFT(AC4,IF(LEN(AC4)=7,3,2))+1911,MID(AC4,IF(LEN(AC4)=7,4,3),2),RIGHT(AC4,2))) -> 40118 | AE3: =IF(AE4=1,0,IF(OR(AB3=1,AB3=3,AB3=5,AB3=7,AB3=8,AB3=10,AB3=12),31,IF(OR(AB3=4,AB3=6,AB3=9,AB3=11),30,IF(OR(AND(AB3=2,YEAR(AD3)=2000),AND(AB3=2,YEAR(AD3)/4=INT(YEAR(AD3)/4),YEAR(AD3)/400<>INT(YEAR(AD3)/400))),29,28)))) -> 30 | AL3: 業務、服展、北富銀 | AM3: 業務、服展 | AN3: 北富銀 | AO3: 整銷 | AP3: 多元 | BA3: =PDSN1_1 -> LTQ | BB3: =C16 -> 15 | BC3: =C15 -> 50 | BD3: =D57 -> 85 | BE3: =VLOOKUP($D$5,$H$75:$O$161,$BF$3,0) -> 0.5 | BF3: =IF($C$18=1,6,7) -> 7 | BH3: 保險年齡： | BI3: =$D$5 -> 15
B4: 生日 | C4: =C10 -> 1010101 | D4: =DATE(YEAR(C3)-$C$15,MONTH(C3)-6,DAY(C3)) -> 27815 | E4: =IF(C4="",1,IF(OR(B3<1,B3>12),1,"")) | F4: =YEAR(D4)-1911 -> 65 | H4: 年繳 | I4: 1 | J4: 1 | K4: 1 | S4: 女 | T4: 躉繳 | U4: 金融機構轉帳 | V4: 自行繳費 | W4: 儲存生息 | AB4: 生日 | AC4: =AC10 -> 981101 | AE4: =IF(AC4="",1,IF(OR(AB3<1,AB3>12),1,"")) | AK4: =IF(OR($AL4="",COUNTIF($AL$3:$AR$3,$AL$2)=0),"",MAX($AK$3:AK3)+1) | AL4: 富邦人壽保險股份有限公司履行個人資料保護法告知說明書 | BA4: 免體減額度 | BB4: =VLOOKUP($D$5,$H$72:$N$161,5,0) -> 1000 | BC4: 匯率 | BD4: =C58 -> 1 | BH4: 保費： | BI4: =$C$31 -> 16170
B5: 最高承保 | C5: 保險 | D5: =IF(SUM(E6,D10:D13)>=1,"生日格式錯誤",IF(D3>C3,"被保險人未出生",IF(MONTH(C3)<B3,IF(OR(MONTH(C3)+12-B3>6,AND(MONTH(C3)+12-B3=6,DAY(C3)>DAY(D3))),YEAR(C3)-1-YEAR(D3)+1,IF(OR(MONTH(C3)+12-B3<6,AND(MONTH(C3)+12-B3=6,DAY(C3)<=DAY(D3))),YEAR(C3)-1-YEAR(D3))),IF(OR(MONTH(C3)-B3>6,AND(MONTH(C3)-B3=6,DAY(C3)>DAY(D3))),YEAR(C3)-YEAR(D3)+1,IF(OR(MONTH(C3)-B3<=6,AND(MONTH(C3)-B3=6,DAY(C3)<=DAY(D3))),YEAR(C3)-YEAR(D3),))))) -> 15 | E5: =IF(C4="",1,IF(OR(VALUE(RIGHT(C4,2))<1,VALUE(RIGHT(C4,2))>E3),1,"")) | F5: =MONTH(D4) -> 2 | H5: 半年繳 | I5: 0.52 | J5: 0.5 | K5: 2 | T5: 年繳 | U5: 富邦信用卡 | V5: 富邦信用卡 | W5: 現金給付 | AB5: 最高承保 | AC5: 保險 | AD5: =IF(SUM(AE6,AD10:AD13)>=1,"生日格式錯誤",IF(AD3>C3,"被保險人未出生",IF(MONTH(C3)<AB3,IF(OR(MONTH(C3)+12-AB3>6,AND(MONTH(C3)+12-AB3=6,DAY(C3)>DAY(AD3))),YEAR(C3)-1-YEAR(AD3)+1,IF(OR(MONTH(C3)+12-AB3<6,AND(MONTH(C3)+12-AB3=6,DAY(C3)<=DAY(AD3))),YEAR(C3)-1-YEAR(AD3))),IF(OR(MONTH(C3)-AB3>6,AND(MONTH(C3)-AB3=6,DAY(C3)>DAY(AD3))),YEAR(C3)-YEAR(AD3)+1,IF(OR(MONTH(C3)-AB3<=6,AND(MONTH(C3)-AB3=6,DAY(C3)<=DAY(AD3))),YEAR(C3)-YEAR(AD3),))))) -> 17 | AE5: =IF(AC4="",1,IF(OR(VALUE(RIGHT(AC4,2))<1,VALUE(RIGHT(AC4,2))>AE3),1,"")) | AK5: =IF(OR($AL5="",COUNTIF($AL$3:$AR$3,$AL$2)=0),"",MAX($AK$3:AK4)+1) | BA5: =IF($BA$8=1,IF($D$5>70,"本保件可能需要體檢。",IF($BB$5>$BB$4,"免體檢額度:新臺幣："&TEXT($BB$4,"#,##0萬")&"，本保件體檢保額:【投保金額*匯率*通算保額係數】=新臺幣："&TEXT($BB$5,IF(OP!$E$28=0,"#,##0","#,##0.0"))&"萬，本保件投保保額超過免體檢額度，可能需要體檢。","")),"") | BB5: =$C$28*$BE$3*BD4 -> 0.5 | BH5: 換算匯率： | BI5: =IF($BI$2=2,$C$58,1) -> 1
C6: 足歲 | D6: =IF(SUM(E6,D10:D13)>=1,"生日格式錯誤",IF(D3>C3,"被保險人未出生", YEAR($C$3)-YEAR($D$3)-1+IF(OR(MONTH($D$3)<MONTH($C$3),AND(MONTH($D$3)=MONTH($C$3),DAY($D$3)<=DAY($C$3))),1,0))) -> 14 | E6: =IF(OR(E4=1,E5=1),1,"") | F6: =DAY(D4) -> 25 | H6: 季繳 | I6: 0.262 | J6: 0.25 | K6: 4 | T6: 半年繳 | U6: 一般信用卡 | V6: 一般信用卡 | W6: 繳清保險金額 | AC6: 足歲 | AD6: =IF(SUM(AE6,AD10:AD13)>=1,"生日格式錯誤",IF(AD3>C3,"被保險人未出生",ROUNDDOWN(YEARFRAC(AD3,C3,1),0))) -> 16 | AE6: =IF(OR(AE4=1,AE5=1),1,"") | AK6: =IF(OR($AL6="",COUNTIF($AL$3:$AR$3,$AL$2)=0),"",MAX($AK$3:AK5)+1) | AL6: 富邦人壽保險股份有限公司（下稱本公司）依據個人資料保護法（以下稱個資法） | BH6: 繳別： | BI6: =IF($C$32="躉繳",1,2) -> 2 | BJ6: =$C$32 -> 年繳
B7: 1MAX | C7: =(F4&TEXT(F5,"00")&TEXT(F6,"00"))*1 -> 650225 | D7: 1MIN | E7: =(YEAR(TODAY())-1911&TEXT(MONTH(TODAY()),"00")&TEXT(DAY(TODAY()),"00"))*1 -> 1150825 | H7: 月繳 | I7: 0.088 | J7: 0.08333333 | K7: 12 | T7: 季繳 | AK7: =IF(OR($AL7="",COUNTIF($AL$3:$AR$3,$AL$2)=0),"",MAX($AK$3:AK6)+1) | AL7: 規定，向 台端告知下列事項，請 台端詳閱： | BA7: 顯示體檢(1：顯示，空：不顯示) | BH7: 發單後是否需要電訪： | BI7: =IF($BI$8="","否","是") -> 否
K8: 第一頁說明↓ | L8: 102警語↓ | M8: =COUNTA(L11:L12) -> 2 | T8: 月繳 | AK8: =IF(OR($AL8="",COUNTIF($AL$3:$AR$3,$AL$2)=0),"",MAX($AK$3:AK7)+1) | AL8: 一、蒐集之目的： | BH8: 電訪原因： | BI8: =IF(ISERROR(VLOOKUP(1,$BH$11:$BI$13,2,0)),"",VLOOKUP(1,$BH$11:$BI$13,2,0))
B9: 輸入格式選項 | C9: 1 | D9: 檢核欄位 | H9: 折扣使用 | I9: 首期 | J9: 續期 | K9: =K10&M10&K11&M11&K12&M12&K13&M13&D47 -> 繳費方式 1.0%折扣。 | L9: ="保費折扣" -> 保費折扣 | M9: =L10&M10&L11&M11&L12&M12&L13&"折扣" -> 繳費方式。折扣 | AD9: 檢核欄位 | AK9: =IF(OR($AL9="",COUNTIF($AL$3:$AR$3,$AL$2)=0),"",MAX($AK$3:AK8)+1) | AL9: （一）人身保險（００一） | BH9: ※請注意！上述的電訪提醒僅針對本試算表所輸入的資料進行初步判斷，實際發單後是否須要電訪本公司將會另行通知。
B10: 1.輸入格式1-6或7位數字輸入 | C10: =input_s!H24 -> 1010101 | D10: =IF(AND($C$9=1,OR(C10="",C10=0,LEN(C10)<6,LEN(C10)>IF(YEAR(TODAY())>2010,7,6))),1,"") | H10: 繳費方式 | I10: =$C$42 -> 0.01 | J10: =$C$44 -> 0.01 | K10: =IF(AND(I10>0,J10>0),""&H10&TEXT(I10," 0.0%")&"折扣",IF(AND(I10>0,J10=0),"首期"&H10&TEXT(I10," 0.0%")&"折扣",IF(AND(I10=0,J10>0),"續期"&H10&TEXT(J10," 0.0%")&"折扣",""))) -> 繳費方式 1.0%折扣 | L10: =IF(SUM(I10:J10)>0,H10,"") -> 繳費方式 | M10: =IF(L10="","",IF(SUM(N11:N13)>=2,"、",IF(SUM(N11:N13)=1,"及","。"))) -> 。 | N10: =IF(L10<>"",1,0) -> 1 | AB10: 1.輸入格式1-6或7位數字輸入 | AC10: =輸入頁!$N$8 -> 981101 | AD10: =IF(AND($C$9=1,OR(AC10="",AC10=0,LEN(AC10)<6,LEN(AC10)>IF(YEAR(TODAY())>2010,7,6))),1,"") | AK10: =IF(OR($AL10="",COUNTIF($AL$3:$AR$3,$AL$2)=0),"",MAX($AK$3:AK9)+1) | AL10: （二）其他經營合於營業登記項目或組織章程所定之業務（一八一）
B11: 2.輸入格式2-年月日 | H11: 高保額 | I11: =$C$37 -> 0 | J11: =$C$37 -> 0 | K11: =IF(AND(I11>0,J11>0),""&H11&TEXT(I11," 0.0%")&"折扣",IF(AND(I11>0,J11=0),"首期"&H11&TEXT(I11," 0.0%")&"折扣",IF(AND(I11=0,J11>0),"續期"&H11&TEXT(J11," 0.0%")&"折扣",""))) | L11: =IF(SUM(I11:J11)>0,H11,"") | M11: =IF(L11="","",IF(SUM(N12:N14)>=2,"、",IF(SUM(N12:N14)=1,"及","。"))) | N11: =IF(L11<>"",1,0) -> 0 | AB11: 2.輸入格式2-年月日 | AK11: =IF(OR($AL11="",COUNTIF($AL$3:$AR$3,$AL$2)=0),"",MAX($AK$3:AK10)+1) | AL11: 二、蒐集之個人資料類別： | BH11: =IF(AND($BI$2=1,$BI$3>=70,$BI$6<>1,$BI$4>=100000),1,"") | BI11: 被保險人達70歲(含)以上且年繳保險費達10萬元(含)以上
H12: 集體彙繳件 | I12: =$C$38 -> 0 | J12: =$C$39 -> 0 | K12: =IF(AND(I12>0,J12>0),""&H12&TEXT(I12," 0.0%")&"折扣",IF(AND(I12>0,J12=0),"首期"&H12&TEXT(I12," 0.0%")&"折扣",IF(AND(I12=0,J12>0),"續期"&H12&TEXT(J12," 0.0%")&"折扣",""))) | L12: =IF(SUM(I12:J12)>0,H12,"") | M12: =IF(L12="","",IF(SUM(N13:N15)>=2,"、",IF(SUM(N13:N15)=1,"及","。"))) | N12: =IF(L12<>"",1,0) -> 0 | AK12: =IF(OR($AL12="",COUNTIF($AL$3:$AR$3,$AL$2)=0),"",MAX($AK$3:AK11)+1) | AL12: （一）姓名。 | BH12: =IF(AND($BI$2=1,$BI$3>=70,$BI$6=1,$BI$4>=1000000),1,"") | BI12: 被保險人達70歲(含)以上且躉繳保險費達100萬(含)以上
H13: 員工轉帳件 | I13: =$C$40 -> 0 | J13: =$C$40 -> 0 | K13: =IF(AND(I13>0,J13>0),""&H13&TEXT(I13," 0.0%")&"折扣",IF(AND(I13>0,J13=0),"首期"&H13&TEXT(I13," 0.0%")&"折扣",IF(AND(I13=0,J13>0),"續期"&H13&TEXT(J13," 0.0%")&"折扣",IF(J27=1,"繳費方式不符合員工折扣保費規定","")))) | L13: =IF(SUM(I13:J13)>0,H13,"") | M13: =IF(L13="","",IF(SUM(N14:N16)>=2,"、",IF(SUM(N14:N16)=1,"及","。"))) | N13: =IF(L13<>"",1,0) -> 0 | AK13: =IF(OR($AL13="",COUNTIF($AL$3:$AR$3,$AL$2)=0),"",MAX($AK$3:AK12)+1) | AL13: （二）身分證統一編號。 | BH13: =IF(AND($BI$13<>""),1,"") | BI13: =IF(AND($BJ$13="",$BK$13=""),"","外幣非投資型商品"&$BJ$13&$BK$13) | BJ13: =IF(ISERROR(VLOOKUP(1,$BH$14:$BJ$16,2,0)),"",VLOOKUP(1,$BH$14:$BJ$16,2,0)&VLOOKUP(1,$BH$14:$BJ$16,3,0)) | BK13: =IF(ISERROR(VLOOKUP(2,$BB$24:$BZ$26,2,0)),"",VLOOKUP(2,$BH$14:$BJ$16,2,0)&VLOOKUP(2,$BH$14:$BJ$16,3,0))
B14: 生日檢核 | D14: =IF(SUM(E6,D10:D13)>=1,"*日期空白或格式錯誤*","") | AB14: 生日檢核 | AD14: =IF(SUM(AE6,AD10:AD13)>=1,"*日期空白或格式錯誤*","") | AK14: =IF(OR($AL14="",COUNTIF($AL$3:$AR$3,$AL$2)=0),"",MAX($AK$3:AK13)+1) | AL14: （三）地址。 | BH14: =IF(AND($BI$2=2,$BI$3>=70),1,"") | BI14: 被保險人年齡達70歲(含)以上 | BJ14: =IF(BH14="","",IF(MAX($BH$14:$BH$16)=1,"。","，"))
B15: 最高承保(保險年齡) | C15: =IF(OR($C$22="",$C$24=""),"",$M$42) -> 50 | D15: =IF(D5>C15,1,"") | E15: =IF(E16=1,"足歲","歲") -> 歲 | K15: 繳費方式、高保額及集體彙繳件折扣 | AB15: 最高承保(保險年齡) | AD15: =IF(AD5>C15,1,"") | AK15: =IF(OR($AL15="",COUNTIF($AL$3:$AR$3,$AL$2)=0),"",MAX($AK$3:AK14)+1) | AL15: （四）病歷、醫療、健康檢查 。 | BH15: =IF(AND($BI$2=2,$BI$6<>1,$BI$4*$BI$5>=300000),MAX($BH$14:$BH$14)+1,"") | BI15: 年繳保險費達新台幣30萬(含)以上 | BJ15: =IF(BH15="","",IF(MAX($BH$14:$BH$15)>=1,"。",""))
B16: ="最低承保"&IF(E16=1,"(足歲)","(保險年齡)") -> 最低承保(保險年齡) | C16: =IF(OR($C$22="",$C$24=""),"",$L$42) -> 15 | D16: =IF(IF(E16=1,D6,IF(E16=2,D5,0))<C16,1,"") | E16: 2 | N16: =IF(O16="","",MAX($N$2:N15)+1) | AB16: ="最低承保"&IF(E16=1,"(足歲)","(保險年齡)") -> 最低承保(保險年齡) | AD16: =IF(IF(E16=1,AD6,IF(E16=2,AD5,0))<C16,1,"") | AK16: =IF(OR($AL16="",COUNTIF($AL$3:$AR$3,$AL$2)=0),"",MAX($AK$3:AK15)+1) | AL16: （五）要保書、要保文件等其他基於保險契約所提供之個人資料。 | BH16: =IF(AND($BI$2=2,$BI$6=1,$BI$4*$BI$5>=1000000),MAX($BH$14:$BH$15)+1,"") | BI16: 躉繳保險費達新台幣100萬(含)以上 | BJ16: =IF(BH16="","",IF(MAX($BH$14:$BH$16)>=1,"。",""))
B17: 年齡檢核 | D17: =IF(SUM(D15:D16)>=1,"*年齡不符專案投保區間*","") | N17: =IF(O17="","",MAX($N$2:N16)+1) | AB17: 年齡檢核 | AD17: =IF(SUM(AD15:AD16)>=1,"*年齡不符專案投保區間*","") | AK17: =IF(OR($AL17="",COUNTIF($AL$3:$AR$3,$AL$2)=0),"",MAX($AK$3:AK16)+1) | AL17: 三、個人資料利用之期間、地區、對象、方式：
B18: 性別 (1.男 2.女) | C18: =IF($E$18="男",1,IF($E$18="女",2,0)) -> 2 | D18: =IF(COUNTIF(En_Sex,$E$18)<>1,1,"") | E18: =input_s!$H$22 -> 女 | N18: =IF(O18="","",MAX($N$2:N17)+1) | AB18: 性別 (1.男 2.女) | AC18: =IF($AE$18="男",1,IF($AE$18="女",2,0)) -> 1 | AD18: =IF(COUNTIF(En_Sex,$AE$18)<>1,1,"") | AE18: =輸入頁!$K$8 -> 男 | AK18: =IF(OR($AL18="",COUNTIF($AL$3:$AR$3,$AL$2)=0),"",MAX($AK$3:AK17)+1) | AL18: （一）期間：因執行業務所必須及依法令規定應為保存之期間。
B19: 性別檢核 | D19: =IF(D18=1,"*性別輸入錯誤*","") | H19: 繳費方式 | I19: 折扣率 | AB19: 性別檢核 | AD19: =IF(AD18=1,"*性別輸入錯誤*","") | AK19: =IF(OR($AL19="",COUNTIF($AL$3:$AR$3,$AL$2)=0),"",MAX($AK$3:AK18)+1) | AL19: （二）對象：本公司、中華民國人壽保險商業同業公會、財團法人保險事業發展
B20: 基本資料欄位檢核結果 | D20: =IF(SUM(E6,D10:D13,D15,D16,D18)>=1,1,"") | H20: =IF($C$21=1,"匯款","外幣匯款") -> 匯款 | I20: =IF($C$21=1,IF($C$24=1,0%,1%),IF($C$24=1,0%,IF($C$43=$H$21,1%,0%))) -> 0.01 | J20: ↓首期 | AB20: 基本資料欄位檢核結果 | AD20: =IF(SUM(AE6,AD10,AD15,AD16,AD18)>=1,1,"") | AK20: =IF(OR($AL20="",COUNTIF($AL$3:$AR$3,$AL$2)=0),"",MAX($AK$3:AK19)+1) | AL20: 中心、財團法人金融消費評議中心、業務委外機構、臺灣網路認證(股)公司、
B21: 計價幣別(1.台幣 2.外幣) | C21: 1 | D21: =IF(OR(C21="",C21<=0,C21>=3),1,"") | E21: 新臺幣 | H21: 金融機構轉帳 | I21: =IF($C$24=1,0%,1%) -> 0.01 | J21: 續期↓ | AB21: MAX-Y | AC21: =$F$57-AD5+1 -> 83 | AK21: =IF(OR($AL21="",COUNTIF($AL$3:$AR$3,$AL$2)=0),"",MAX($AK$3:AK20)+1) | AL21: 與本公司有再保業務往來之公司、依法有調查權機關或金融監理機關。
B22: 險種代號 | C22: =input_s!$H$34 -> LTQ | D22: =IF(OR($C$22="",$C$22=0,ISERROR(VLOOKUP($C$22,$H$43:$H$62,1,0))),1,"") | H22: 富邦信用卡 | I22: =IF($C$21=1,IF($C$24=1,0%,1%),0%) -> 0.01 | AK22: =IF(OR($AL22="",COUNTIF($AL$3:$AR$3,$AL$2)=0),"",MAX($AK$3:AK21)+1)
B23: 商品中文名稱 | C23: 富邦人壽連馨久久長期照顧終身健康保險 | E23: =OP!$C$23&"建議書" -> 富邦人壽連馨久久長期照顧終身健康保險建議書 | H23: 一般信用卡 | I23: 0 | J23: ↑首期 | AK23: =IF(OR($AL23="",COUNTIF($AL$3:$AR$3,$AL$2)=0),"",MAX($AK$3:AK22)+1) | AL23: （三）地區：上述對象所在之地區。
B24: 年期 | C24: =IF(ISERROR(VLOOKUP(input_s!$H$35&$C22,$J$43:$J$62,1,0)),"",input_s!$H$35) -> 30 | D24: =IF(OR($C$24="",$C$24=0,COUNTIF($J$43:$J$62,$C$24&$C$22)<>1),1,"") | E24: =IF(OP!$C$24=1,"躉繳",IF(OP!$C$24>40,OP!$C$24&" 歲滿期",OP!$C$24&" 年期")) -> 30 年期 | H24: 自行繳費 | I24: =IF($C$21=1,IF($C$24=1,0%,1%),0%) -> 0.01 | AK24: =IF(OR($AL24="",COUNTIF($AL$3:$AR$3,$AL$2)=0),"",MAX($AK$3:AK23)+1) | AL24: （四）方式：合於法令規定之利用方式。
B25: 年期檢核 | D25: =IF(SUM(D24)>=1,"*年期選擇錯誤*","") | H25: 支票 | I25: 0 | J25: 續期↑ | AB25: 跳歲計算 | AC25: =DATE(YEAR($AD$3)+$AD$6,MONTH($AD$3)+6,MIN(DAY($AD$3),$AE$25)+1) -> 46144 | AD25: =MONTH($AD$3)+IF(MONTH($AD$3)<=6,6,-6) -> 5 | AE25: =IF(OR($AD$25=1,$AD$25=3,$AD$25=5,$AD$25=7,$AD$25=8,$AD$25=10,$AD$25=12),31,IF(OR($AD$25=4,$AD$25=6,$AD$25=9,$AD$25=11),30,IF(AND($AD$25=2,YEAR($C$3)/4=INT(YEAR($C$3)/4),YEAR($C$3)/400<>INT(YEAR($C$3)/400)),29,28))) -> 31 | AK25: =IF(OR($AL25="",COUNTIF($AL$3:$AR$3,$AL$2)=0),"",MAX($AK$3:AK24)+1) | AL25: 四、依據個資法第三條規定，台端就本公司保有 台端之個人資料得行使之權利及
B26: 最低保額 | C26: =IF(OR($C$22="",$C$24=""),"",$N$42) -> 0.5 | K26: 有折扣：1、2；無折扣：0 | AC26: =IF(AC25<$C$3,"",AC25-$C$3) | AD26: =IF(C85=0,"",IF(OR($D$53=1,AC26=""),"",IF(AND(AC26>=1,AC26<=30),"提醒您：被保險人"&$AC$1&"將於 "&MONTH(AC25)&" 月 "&DAY(AC25)&" 日 ( "&AC26&"天後 ) 保險年齡增加一歲"&IF(D85=0,"。","，"&$C$22&$C$32&"保險費"&IF($C$32="躉繳","","每期")&IF(AE27>=0,"增加 ","減少 ")&TEXT(AE27,"#,##0 元")&"。"),""))) | AK26: =IF(OR($AL26="",COUNTIF($AL$3:$AR$3,$AL$2)=0),"",MAX($AK$3:AK25)+1) | AL26: 方式：
B27: 最高保額 | C27: =IF(OR($C$22="",$C$24="",D20=1),,$O$42) -> 2 | D27: =IF(C28*10<>ROUNDUP(C28,$E$28)*10,1,"") | E27: 保額小數位數 | H27: 折扣選項 | I27: =輸入頁!$E$21 -> 無 | J27: =IF(ISNA(VLOOKUP($I$27,$H$28:$I$30,2,0)),0,VLOOKUP($I$27,$H$28:$I$30,2,0)) -> 0 | K27: =IF(AND($J$27=1,$C$40>0),1,IF(AND($J$27=2,OR($C$38>0,$C$39>0)),2,0)) -> 0 | AB27: 新年齡/保費/差異 | AC27: =C88 -> LTQ300216 | AD27: =IF(ISNA(VLOOKUP(AC27,GP,2,0)),0,IF($C$21=1,ROUND(VLOOKUP(AC27,GP,2,0)*$C$28*$C$34,0),IF($C$21=2,ROUNDDOWN(VLOOKUP(AC27,GP,2,0)*$C$28*$C$34,0),""))) -> 16370 | AE27: =AD27-$C$35 -> 200 | AK27: =IF(OR($AL27="",COUNTIF($AL$3:$AR$3,$AL$2)=0),"",MAX($AK$3:AK26)+1) | AL27: （一）得向本公司行使之權利：
B28: 保額 | C28: =ROUND(input_s!$H$61,$E$28) -> 1 | D28: =IF(OR(C28="",C28=0,C28<C26,C28>C27,D27<>""),1,"") | E28: 1 | H28: 無 | I28: 0 | AK28: =IF(OR($AL28="",COUNTIF($AL$3:$AR$3,$AL$2)=0),"",MAX($AK$3:AK27)+1) | AL28: 1.向本公司查詢、請求閱覽或請求製給複製本。
B29: 保額檢核 | D29: =IF(SUM(D28)>=1,"*保額錯誤*","") | H29: 員工轉帳件 | I29: 1 | AK29: =IF(OR($AL29="",COUNTIF($AL$3:$AR$3,$AL$2)=0),"",MAX($AK$3:AK28)+1) | AL29: 2.向本公司請求補充或更正。
B30: 每萬保費 | C30: =IF(OR(C18=0,C22=0,D28=1),0,IF(ISNA(VLOOKUP($C$55,GP,2,0)),0,VLOOKUP($C$55,GP,2,0))) -> 16170 | H30: 集體彙繳件 | I30: 2 | AK30: =IF(OR($AL30="",COUNTIF($AL$3:$AR$3,$AL$2)=0),"",MAX($AK$3:AK29)+1) | AL30: 3.向本公司請求停止蒐集、處理或利用及請求刪除。
B31: 原始應繳保費 | C31: =IF($C$21=1,ROUND(C28*C30,1),IF(C21=2,ROUND(C28*C30,1),"")) -> 16170 | AK31: =IF(OR($AL31="",COUNTIF($AL$3:$AR$3,$AL$2)=0),"",MAX($AK$3:AK30)+1) | AL31: （二）行使權利之方式：
B32: 繳別 | C32: =IF(input_s!$H$40="","",input_s!$H$40) -> 年繳 | D32: =IF(OR(AND($C$24<>1,$C$32="躉繳"),COUNTIF(En_PayT,$C$32)<>1),1,"") | AK32: =IF(OR($AL32="",COUNTIF($AL$3:$AR$3,$AL$2)=0),"",MAX($AK$3:AK31)+1) | AL32: 您可以透過書面（包含電子郵件、傳真、電子文件）方式行使權利。
B33: 換算格式1.傳統 2.直接除 | C33: 1 | D33: =IF(OR(C33="",C33=0),1,"") | AK33: =IF(OR($AL33="",COUNTIF($AL$3:$AR$3,$AL$2)=0),"",MAX($AK$3:AK32)+1)
B34: 繳別換算率 | C34: =IF(D32=1,,VLOOKUP(C32,H2:K7,1+C33,FALSE)) -> 1 | AK34: =IF(OR($AL34="",COUNTIF($AL$3:$AR$3,$AL$2)=0),"",MAX($AK$3:AK33)+1) | AL34: 五、台端不提供個人資料所致權益之影響
B35: 應繳保費 | C35: =IF($C$21=1,ROUND(C31*C34,0),IF($C$21=2,ROUNDDOWN(C31*C34,0),"")) -> 16170 | D35: =IF($C$50=12,$C$35*2,$C$35*1) -> 16170 | E35: 月繳*2 ←1130126新增月繳倍數(紀錄單用) | AK35: =IF(OR($AL35="",COUNTIF($AL$3:$AR$3,$AL$2)=0),"",MAX($AK$3:AK34)+1) | AL35: 台端若未能提供相關個人資料時，本公司將可能延後或無法進行必要之審核
B36: 高保費折扣 | D36: 低<=保費<高 | AK36: =IF(OR($AL36="",COUNTIF($AL$3:$AR$3,$AL$2)=0),"",MAX($AK$3:AK35)+1) | AL36: 及處理作業，因此可能婉謝承保、遲延或無法承保。
B37: 高保額折扣 | C37: =IF(D64=1,,IF(AND($C$28>=50,$C$28<100),0%,IF(AND($C$28>=100),0%,0%))) -> 0 | D37: =IF(C37>0,"本保件享有 "&TEXT(C37,"0.0%")&" 高保額折扣","") | AK37: =IF(OR($AL37="",COUNTIF($AL$3:$AR$3,$AL$2)=0),"",MAX($AK$3:AK36)+1)
B38: 集彙折扣-首期 | D38: =IF(C38>0,"本主約首期保費享有 "&TEXT(C38,"0%")&" 集體彙繳折扣","") | H38: 預定利率 | I38: 儲存生息-1% | J38: 儲存生息 | AK38: =IF(OR($AL38="",COUNTIF($AL$3:$AR$3,$AL$2)=0),"",MAX($AK$3:AK37)+1)
B39: 集彙折扣-續期 | D39: =IF(C39>0,"本主約續期保費享有 "&TEXT(C39,"0%")&" 集體彙繳折扣","") | H39: =$K$42 -> 0 | I39: =TEXT(RDATA!$I$2-1%,"0.00%") -> 0.75% | J39: =TEXT(RDATA!$I$2,"0.00%") -> 1.75% | AK39: =IF(OR($AL39="",COUNTIF($AL$3:$AR$3,$AL$2)=0),"",MAX($AK$3:AK38)+1)
B40: 員工折扣 | C40: =IF(AND($J$27=1,C41=H21,OR(C43=H21,C43=H24)),IF($C$24=10,5.5%,IF($C$24=20,5%,IF($C$24=30,4%,0%))),0%) -> 0 | D40: =IF(C40>0,"本主約保費享有 "&TEXT(C40,"0.0%")&H29&"折扣","") | AK40: =IF(OR($AL40="",COUNTIF($AL$3:$AR$3,$AL$2)=0),"",MAX($AK$3:AK39)+1)
B41: 首期繳別 | C41: =input_s!$H$45 -> 匯款 | D41: =IF(COUNTIF(En_PayMF,$C$41)<>1,1,"") | H41: 險種代號 | I41: 年期 | J41: 險種代號+年期 | K41: 預定利率-2 | L41: 最低年齡-3 | M41: 最高年齡-4 | N41: 最低保額-5 | O41: 最高保額-6 | AK41: =IF(OR($AL41="",COUNTIF($AL$3:$AR$3,$AL$2)=0),"",MAX($AK$3:AK40)+1)
B42: 自繳折扣-首期 | C42: =IF(OR($K$27<>0,ISNA(VLOOKUP(C41,$H$19:$I$25,2,0))),0,VLOOKUP(C41,$H$19:$I$25,2,0)) -> 0.01 | D42: =IF(C42>0,"-首期享有1%繳別折扣-","") -> -首期享有1%繳別折扣- | H42: =$C$22 -> LTQ | I42: =$C$24 -> 30 | J42: =$I42&$H42 -> 30LTQ | K42: =VLOOKUP($J$42,$J$43:$O$62,2,0) -> 0 | L42: =VLOOKUP($J$42,$J$43:$O$62,3,0) -> 15 | M42: =VLOOKUP($J$42,$J$43:$O$62,4,0) -> 50 | N42: =VLOOKUP($J$42,$J$43:$O$62,5,0) -> 0.5 | O42: =VLOOKUP($J$42,$J$43:$O$62,6,0) -> 2 | AK42: =IF(OR($AL42="",COUNTIF($AL$3:$AR$3,$AL$2)=0),"",MAX($AK$3:AK41)+1)
B43: 續期繳別 | C43: =input_s!H53 -> 金融機構轉帳 | D43: =IF(AND($C$24<>1,COUNTIF(En_PayMR,$C$43)<>1),1,"") | H43: LTQ | I43: 10 | J43: =$I43&$H43 -> 10LTQ | K43: 0 | L43: 15 | M43: 70 | N43: 0.5 | O43: =VLOOKUP($F$55,$H$81:$I$161,2,0) -> 2 | AK43: =IF(OR($AL43="",COUNTIF($AL$3:$AR$3,$AL$2)=0),"",MAX($AK$3:AK42)+1)
B44: 自繳折扣-續期 | C44: =IF(OR($K$27<>0,ISNA(VLOOKUP(C43,$H$21:$I$25,2,FALSE))),0,VLOOKUP(C43,$H$21:$I$25,2,FALSE)) -> 0.01 | D44: =IF(C44>0,"-續期享有1%繳別折扣-","") -> -續期享有1%繳別折扣- | H44: LTQ | I44: 20 | J44: =$I44&$H44 -> 20LTQ | K44: 0 | L44: 15 | M44: 60 | N44: 0.5 | O44: =VLOOKUP($F$55,$H$81:$I$161,2,0) -> 2 | AK44: =IF(OR($AL44="",COUNTIF($AL$3:$AR$3,$AL$2)=0),"",MAX($AK$3:AK43)+1)
B45: 折扣率上限 | C45: =IF($K$27=1,IF($C$24=10,5.5%,IF($C$24=20,5%,IF($C$24=30,4%,1%))),1%) -> 0.01 | D45: =IF(OR(C45="",),1,"") | H45: LTQ | I45: 30 | J45: =$I45&$H45 -> 30LTQ | K45: 0 | L45: 15 | M45: 50 | N45: 0.5 | O45: =VLOOKUP($F$55,$H$81:$I$161,2,0) -> 2 | AK45: =IF(OR($AL45="",COUNTIF($AL$3:$AR$3,$AL$2)=0),"",MAX($AK$3:AK44)+1)
B46: 首期總折扣率 | C46: =MIN(SUM(C36:C40,C42),C45) -> 0.01 | J46: =$I46&$H46 | AL46: 保經代 | AM46: 錠嵂保經 | AN46: 銀保
B47: 續期總折扣率 | C47: =MIN(SUM(C36:C40,C44),C45) -> 0.01 | J47: =$I47&$H47 | AK47: =IF(OR($AL47="",COUNTIF($AL$46:$AR$46,$AL$2)=0),"",MAX($AK$3:AK46)+1) -> 1 | AL47: 富邦人壽保險股份有限公司履行個人資料保護法告知說明書
B48: 首期實繳保費 | C48: =ROUND(C35*(1-C46),0) -> 16008 | J48: =$I48&$H48 | AK48: =IF(OR($AL48="",COUNTIF($AL$46:$AR$46,$AL$2)=0),"",MAX($AK$3:AK47)+1) -> 2
B49: 續期實繳保費 | C49: =ROUND(C35*(1-C47),0) -> 16008 | D49: =IF($C$50=12,"-月繳首期須繳2個月"&TEXT($C$48*2,"#,##0元"),"") | J49: =$I49&$H49 | AK49: =IF(OR($AL49="",COUNTIF($AL$46:$AR$46,$AL$2)=0),"",MAX($AK$3:AK48)+1) -> 3 | AL49: 富邦人壽保險股份有限公司（下稱本公司）依據個人資料保護法（以下稱個資法）
B50: 繳別回乘倍數 | C50: =IF(D32=1,,VLOOKUP(C32,H2:K7,4,FALSE)) -> 1 | E50: ←首期保費規則 | J50: =$I50&$H50 | AK50: =IF(OR($AL50="",COUNTIF($AL$46:$AR$46,$AL$2)=0),"",MAX($AK$3:AK49)+1) -> 4 | AL50: 規定，向 台端告知下列事項，請 台端詳閱：
B51: 首年實繳保費 | C51: =IF(C50=12,C48*2+C49*10,C48*1+C49*(C50-1)) -> 16008 | D51: =IF($C$96=0,1,"") | J51: =$I51&$H51 | AK51: =IF(OR($AL51="",COUNTIF($AL$46:$AR$46,$AL$2)=0),"",MAX($AK$3:AK50)+1) -> 5 | AL51: 一、蒐集之目的：
B52: 續年實繳保費 | C52: =C49*C50 -> 16008 | J52: =$I52&$H52 | AK52: =IF(OR($AL52="",COUNTIF($AL$46:$AR$46,$AL$2)=0),"",MAX($AK$3:AK51)+1) -> 6 | AL52: （一）人身保險（００一）
B53: 主約1欄位檢核結果 | C53: =IF(SUM(D15:D16,D18,D28,D32:D33,D40:D41,D43,D45,D50,D51,D64,E96)>=1,1,"") | D53: =IF($B$2=1,$C$53,IF(SUM(C53,AD20)>=1,1,"")) | J53: =$I53&$H53 | AK53: =IF(OR($AL53="",COUNTIF($AL$46:$AR$46,$AL$2)=0),"",MAX($AK$3:AK52)+1) -> 7 | AL53: （二）其他經營合於營業登記項目或組織章程所定之業務（一八一）
B54: 版次 | C54: V1.0-1150720 | F54: 開始承保保險年齡 | J54: =$I54&$H54 | AK54: =IF(OR($AL54="",COUNTIF($AL$46:$AR$46,$AL$2)=0),"",MAX($AK$3:AK53)+1) -> 8 | AL54: 二、蒐集之個人資料類別：
B55: KEY | C55: =C22&IF($C$24=1,"",TEXT($C$24,"00"))&IF($B$2=1,TEXT($C$18,"00")&TEXT($D$5,"00"),$D$55) -> LTQ300215 | D55: =IF($B$2=2,IF($D$5>$AD$5,TEXT($AC$18,"00")&TEXT($AD$5,"00")&TEXT($C$18,"00")&TEXT($D$5,"00"),TEXT($C$18,"00")&TEXT($D$5,"00")&TEXT($AC$18,"00")&TEXT($AD$5,"00")),"") | E55: A險種+年期(2位)+性別(1位)+年齡(2位) | F55: =IF($B$2=1,$D$5,MIN($D$5,$AD$5)) -> 15 | J55: =$I55&$H55 | AK55: =IF(OR($AL55="",COUNTIF($AL$46:$AR$46,$AL$2)=0),"",MAX($AK$3:AK54)+1) -> 9 | AL55: （一）姓名。
B56: SUMKEY | C56: =C22&IF($C$24=1,"",TEXT($C$24,"00")) -> LTQ30 | D56: F險種+年期(2位) | J56: =$I56&$H56 | AK56: =IF(OR($AL56="",COUNTIF($AL$46:$AR$46,$AL$2)=0),"",MAX($AK$3:AK55)+1) -> 10 | AL56: （二）身分證統一編號。
B57: MAX-Y | C57: =$F$57-D5+1 -> 85 | D57: =IF($B$2=1,$C$57,MAX($C$57,$AC$21)) -> 85 | E57: 保障至幾歲 | F57: 99 | J57: =$I57&$H57 | AK57: =IF(OR($AL57="",COUNTIF($AL$46:$AR$46,$AL$2)=0),"",MAX($AK$3:AK56)+1) -> 11 | AL57: （三）地址。
B58: 換算匯率 | C58: 1 | J58: =$I58&$H58 | AK58: =IF(OR($AL58="",COUNTIF($AL$46:$AR$46,$AL$2)=0),"",MAX($AK$3:AK57)+1) -> 12 | AL58: （四）病歷、醫療、健康檢查 。
B59: 保額上限 | J59: =$I59&$H59 | AK59: =IF(OR($AL59="",COUNTIF($AL$46:$AR$46,$AL$2)=0),"",MAX($AK$3:AK58)+1) -> 13 | AL59: （五）要保書、要保文件等其他基於保險契約所提供之個人資料。
B60: 累積總保額上限 | J60: =$I60&$H60 | AK60: =IF(OR($AL60="",COUNTIF($AL$46:$AR$46,$AL$2)=0),"",MAX($AK$3:AK59)+1) -> 14 | AL60: 三、個人資料利用之期間、地區、對象、方式：
B61: 保費 | C61: =輸入頁!$E$53 -> 100000 | J61: =$I61&$H61 | AK61: =IF(OR($AL61="",COUNTIF($AL$46:$AR$46,$AL$2)=0),"",MAX($AK$3:AK60)+1) -> 15 | AL61: （一）期間：因執行業務所必須及依法令規定應為保存之期間。
B62: 換算1 | C62: =ROUNDDOWN(C61/C30,$E$28) -> 6.1 | J62: =$I62&$H62 | AK62: =IF(OR($AL62="",COUNTIF($AL$46:$AR$46,$AL$2)=0),"",MAX($AK$3:AK61)+1) -> 16 | AL62: （二）對象：本公司、中華民國人壽保險商業同業公會、財團法人保險事業發展
B63: 換算2加計折扣 | C63: =ROUNDDOWN((C61*(1+C46))/C30,$E$28) -> 6.2 | AK63: =IF(OR($AL63="",COUNTIF($AL$46:$AR$46,$AL$2)=0),"",MAX($AK$3:AK62)+1) -> 17 | AL63: 中心、財團法人金融消費評議中心、業務委外機構、臺灣網路認證(股)公司、
B64: 保額輸入檢核 | C64: =input_s!$H$61 -> 1 | D64: =IF(ROUND($C$64,$E$28)<>$C$64,1,"") | E64: =IF(D64=1,"保額輸入"&C64&"不符投保規則，請重新輸入","") | AK64: =IF(OR($AL64="",COUNTIF($AL$46:$AR$46,$AL$2)=0),"",MAX($AK$3:AK63)+1) -> 18 | AL64: 與本公司有再保業務往來之公司、依法有調查權機關或金融監理機關。
AK65: =IF(OR($AL65="",COUNTIF($AL$46:$AR$46,$AL$2)=0),"",MAX($AK$3:AK64)+1) -> 19 | AL65: （三）地區：上述對象所在之地區。
AK66: =IF(OR($AL66="",COUNTIF($AL$46:$AR$46,$AL$2)=0),"",MAX($AK$3:AK65)+1) -> 20 | AL66: （四）方式：合於法令規定之利用方式。
AK67: =IF(OR($AL67="",COUNTIF($AL$46:$AR$46,$AL$2)=0),"",MAX($AK$3:AK66)+1) -> 21 | AL67: 四、依據個資法第三條規定，台端就本公司保有 台端之個人資料得行使之權利及
AK68: =IF(OR($AL68="",COUNTIF($AL$46:$AR$46,$AL$2)=0),"",MAX($AK$3:AK67)+1) -> 22 | AL68: 方式：
B69: 適用通路： | C69: 銀保 | D69: PB | F69: ←銀保通路判別使用 | H69: 健康管理保險費折扣項目 | I69: =$C$22&"折扣率" -> LTQ折扣率 | J69: =$C$22&"續年度折扣後實繳保費"&IF($C$47>0,"(含"&IF($K$27=1,"員工轉帳","續期繳費方式")&"折扣"&TEXT($C$47,"0.0%")&")","") -> LTQ續年度折扣後實繳保費(含續期繳費方式折扣1.0%) | AK69: =IF(OR($AL69="",COUNTIF($AL$46:$AR$46,$AL$2)=0),"",MAX($AK$3:AK68)+1) -> 23 | AL69: （一）得向本公司行使之權利：
H70: 指定疫苗接種或健康檢查 | I70: 0.01 | J70: =ROUND($C$35*(1-($C$47+$I$70)),0) -> 15847 | AK70: =IF(OR($AL70="",COUNTIF($AL$46:$AR$46,$AL$2)=0),"",MAX($AK$3:AK69)+1) -> 24 | AL70: 1.向本公司查詢、請求閱覽或請求製給複製本。
B71: 姓名遮蔽用：中/英/數混合：前6碼"*"，中文：倒數第2碼"○" | AK71: =IF(OR($AL71="",COUNTIF($AL$46:$AR$46,$AL$2)=0),"",MAX($AK$3:AK70)+1) -> 25 | AL71: 2.向本公司請求補充或更正。
B72: 姓名： | C72: =input_s!$H$21 -> 客戶 | D72: ←輸入頁資料 | E72: 0 | AK72: =IF(OR($AL72="",COUNTIF($AL$46:$AR$46,$AL$2)=0),"",MAX($AK$3:AK71)+1) -> 26 | AL72: 3.向本公司請求停止蒐集、處理或利用及請求刪除。
B73: 帶入資料 | C73: =IF(E72=0,C72,IF(OR(E73=1,C72="",C72=0)," ",IF(AND(E82=0),C74&MID(C72,7,50),IF(LEN(C72)=1,C72,LEFT(C72,LEN(C72)-2)&"○"&RIGHT(C72,1))))) -> 客戶 | D73: 判別不顯示(不判別) | AK73: =IF(OR($AL73="",COUNTIF($AL$46:$AR$46,$AL$2)=0),"",MAX($AK$3:AK72)+1) -> 27 | AL73: （二）行使權利之方式：
B74: =IF(OR(E73=1,C72="",C72=0),"",IF(AND(E82=0),LEN(C72),"")) | C74: =IF(OR(B74=""),"",IF(ISERROR(VLOOKUP(B74,B75:C80,2,0)),C80,VLOOKUP(B74,B75:C80,2,0))) | D74: ID-11碼數字 | E74: =IF(AND(ISNUMBER(C72),LEN(C72)=11),1,0) -> 0 | AK74: =IF(OR($AL74="",COUNTIF($AL$46:$AR$46,$AL$2)=0),"",MAX($AK$3:AK73)+1) -> 28 | AL74: 您可以透過書面（包含電子郵件、傳真、電子文件）方式行使權利。
B75: 1 | C75: * | D75: ID-10碼 | E75: =IF(AND(LEN(C72)=10,ISTEXT(LEFT(C72,1)),ISNUMBER(RIGHT(C72,1)*1)),1,0) -> 0 | AK75: =IF(OR($AL75="",COUNTIF($AL$46:$AR$46,$AL$2)=0),"",MAX($AK$3:AK74)+1)
B76: 2 | C76: ** | D76: 護照-9碼 | E76: =IF(AND(ISNUMBER(C72),LEN(C72)=9),1,0) -> 0 | AK76: =IF(OR($AL76="",COUNTIF($AL$46:$AR$46,$AL$2)=0),"",MAX($AK$3:AK75)+1) -> 29 | AL76: 五、台端不提供個人資料所致權益之影響
B77: 3 | C77: *** | AK77: =IF(OR($AL77="",COUNTIF($AL$46:$AR$46,$AL$2)=0),"",MAX($AK$3:AK76)+1) -> 30 | AL77: 台端若未能提供相關個人資料時，本公司將可能延後或無法進行必要之審核
B78: 4 | C78: **** | AK78: =IF(OR($AL78="",COUNTIF($AL$46:$AR$46,$AL$2)=0),"",MAX($AK$3:AK77)+1) -> 31 | AL78: 及處理作業，因此可能婉謝承保、遲延或無法承保。
B79: 5 | C79: ***** | AK79: =IF(OR($AL79="",COUNTIF($AL$46:$AR$46,$AL$2)=0),"",MAX($AK$3:AK78)+1)
B80: 6 | C80: ****** | H80: 年齡-1 | I80: 最高保額-2 | J80: 保留-3 | K80: 保留-4 | L80: 免體檢額度-5 | M80: 通算係數-6-男 | N80: 通算系數-7-女 | AK80: =IF(OR($AL80="",COUNTIF($AL$46:$AR$46,$AL$2)=0),"",MAX($AK$3:AK79)+1)
B81: 空格位置 | C81: =IF(OR(ISERROR(SEARCH(" ",C72)),CODE(C72)>255),"",SEARCH(" ",C72)) | H81: 0 | L81: 1000 | M81: 0.5 | N81: 0.5 | AK81: =IF(OR($AL81="",COUNTIF($AL$46:$AR$46,$AL$2)=0),"",MAX($AK$3:AK80)+1)
B82: 簡寫 | C82: =IF(OR(ISERROR(SEARCH(" ",C72)),CODE(C72)>255),"",UPPER(LEFT(C72,1)&"."&MID(C72,C81+1,1))) | D82: 1-中文-0-混合 | E82: =IF(OR(LEN(C72)*2=LENB(C72),$E$83=1),1,0) -> 1 | H82: 1 | L82: 1000 | M82: 0.5 | N82: 0.5 | AK82: =IF(OR($AL82="",COUNTIF($AL$46:$AR$46,$AL$2)=0),"",MAX($AK$3:AK81)+1)
B83: 富邦人壽 | C83: FBLI | E83: =IF(LENB($B$83)=LEN($C$83),1,0) -> 0 | H83: 2 | L83: 1000 | M83: 0.5 | N83: 0.5 | AK83: =IF(OR($AL83="",COUNTIF($AL$46:$AR$46,$AL$2)=0),"",MAX($AK$3:AK82)+1)
H84: 3 | L84: 1000 | M84: 0.5 | N84: 0.5 | AK84: =IF(OR($AL84="",COUNTIF($AL$46:$AR$46,$AL$2)=0),"",MAX($AK$3:AK83)+1)
B85: 提醒設定 | C85: 1 | D85: 0 | H85: 4 | L85: 1000 | M85: 0.5 | N85: 0.5 | AK85: =IF(OR($AL85="",COUNTIF($AL$46:$AR$46,$AL$2)=0),"",MAX($AK$3:AK84)+1)
B86: 跳歲計算 | C86: =DATE(YEAR($D$3)+$D$6,MONTH($D$3)+6,MIN(DAY($D$3),$E$86)+1) -> 46205 | D86: =MONTH($D$3)+IF(MONTH($D$3)<=6,6,-6) -> 7 | E86: =IF(OR($D$86=1,$D$86=3,$D$86=5,$D$86=7,$D$86=8,$D$86=10,$D$86=12),31,IF(OR($D$86=4,$D$86=6,$D$86=9,$D$86=11),30,IF(AND($D$86=2,YEAR($C$3)/4=INT(YEAR($C$3)/4),YEAR($C$3)/400<>INT(YEAR($C$3)/400)),29,28))) -> 31 | H86: 5 | L86: 1000 | M86: 0.5 | N86: 0.5 | AK86: =IF(OR($AL86="",COUNTIF($AL$46:$AR$46,$AL$2)=0),"",MAX($AK$3:AK85)+1)
C87: =IF(C86<$C$3,"",C86-$C$3) | D87: =IF(C85=0,"",IF(OR($D$53=1,C87=""),"",IF(AND(C87>=1,C87<=30),"提醒您：被保險人"&$C$73&"將於 "&MONTH(C86)&" 月 "&DAY(C86)&" 日 ( "&C87&"天後 ) 保險年齡增加一歲"&IF(D85=0,"。","，"&$C$22&$C$32&"保險費"&IF($C$32="躉繳","","每期")&IF(E88>=0,"增加 ","減少 ")&TEXT(E88,"#,##0 元")&"。"),""))) | H87: 6 | L87: 1000 | M87: 0.5 | N87: 0.5 | AK87: =IF(OR($AL87="",COUNTIF($AL$46:$AR$46,$AL$2)=0),"",MAX($AK$3:AK86)+1)
B88: 新年齡/保費/差異 | C88: =C22&IF($C$24=1,"",TEXT($C$24,"00"))&TEXT($C$18,"00")&TEXT($D$5+1,"00") -> LTQ300216 | D88: =IF(ISNA(VLOOKUP(C88,GP,2,0)),0,IF($C$21=1,ROUND(VLOOKUP(C88,GP,2,0)*$C$28*$C$34,0),IF($C$21=2,ROUNDDOWN(VLOOKUP(C88,GP,2,0)*$C$28*C34,0),""))) -> 16370 | E88: =D88-$C$35 -> 200 | H88: 7 | L88: 1000 | M88: 0.5 | N88: 0.5 | AK88: =IF(OR($AL88="",COUNTIF($AL$46:$AR$46,$AL$2)=0),"",MAX($AK$3:AK87)+1)
H89: 8 | L89: 1000 | M89: 0.5 | N89: 0.5 | AK89: =IF(OR($AL89="",COUNTIF($AL$46:$AR$46,$AL$2)=0),"",MAX($AK$3:AK88)+1)
B90: 全列印頁面使用 | C90: 更新區域 | D90: 帶入內容區域 | E90: OLD/說明/檢核 | H90: 9 | L90: 1000 | M90: 0.5 | N90: 0.5 | AK90: =IF(OR($AL90="",COUNTIF($AL$46:$AR$46,$AL$2)=0),"",MAX($AK$3:AK89)+1)
B91: 折扣率： | D91: =IF(OR(OP!$D$53=1,AND(OP!C46=0,OP!C47=0)),"","本保件符合保費折扣條件："&OP!$K$9&OP!$D$46) -> 本保件符合保費折扣條件：繳費方式 1.0%折扣。 | H91: 10 | L91: 1000 | M91: 0.5 | N91: 0.5
B92: 保費/折扣後保費： | D92: =IF(OR(OP!$D$53=1),"",$C$32&"總保費"&TEXT($C$35,"#,##0元")&IF(AND($C$46=0,$C$47=0),"","，"&IF($C$24=1,IF(OP!$C$46>0,"躉繳折扣後保費"&TEXT($C$48,"#,##0元"),""),IF($C$46>0,"首期折扣後保費"&TEXT($C$48,"#,##0元"),"首期保費"&TEXT($C$48,"#,##0元"))&"，"&IF($C$47>0,"續期折扣後保費"&TEXT($C$49,"#,##0元"),"續期保費"&TEXT($C$49,"#,##0元"))))&$D$49) -> 年繳總保費16,170元，首期折扣後保費16,008元，續期折扣後保費16,008元 | H92: 11 | L92: 1000 | M92: 0.5 | N92: 0.5
B93: 表格保險種類 | D93: =IF(OP!$D$53=1,"",OP!$C$23&IF(OP!C24=1,"(躉繳)",IF(OP!$C$24>=40,"(繳費至"&OP!$C$24&"歲滿期)","(繳費"&OP!$C$24&"年)"))) -> 富邦人壽連馨久久長期照顧終身健康保險(繳費30年) | H93: 12 | L93: 1000 | M93: 0.5 | N93: 0.5
B94: 本保單計價幣別： | C94: =$E$21 -> 新臺幣 | D94: =$B$94&$C$94 -> 本保單計價幣別：新臺幣 | H94: 13 | L94: 1000 | M94: 0.5 | N94: 0.5
B95: 假設儲存生息利率 | C95: =TEXT(RDATA!$I$2,"0.00%") -> 1.75% | D95: =$B$95&$C$95 -> 假設儲存生息利率1.75% | H95: 14 | L95: 1000 | M95: 0.5 | N95: 0.5
B96: 年度保單紅利給付方式： | C96: =input_s!$H$71 -> 現金給付 | D96: =IF($C$96="儲存生息",$B$96&$C$96&"",$B$96&$C$96) -> 年度保單紅利給付方式：現金給付 | E96: =IF(AND(input_s!$I$8<>3,COUNTIF(En_BFM,$C$96)<>1),1,"") | H96: 15 | I96: =IF($D$6<15,2,5) -> 2 | L96: 1000 | M96: 0.5 | N96: 0.5
B97: 有紅利頁首： | D97: =$D$96 -> 年度保單紅利給付方式：現金給付 | E97: 其他頁面用 | H97: 16 | I97: 5 | L97: 1000 | M97: 0.5 | N97: 0.5
B98: 有紅利頁首： | C98: ="本險種預定利率："&TEXT($K$42,"0.00%") -> 本險種預定利率：0.00% | D98: =$C$98&"，"&$D$95 -> 本險種預定利率：0.00%，假設儲存生息利率1.75% | E98: 彙總版用 | H98: 17 | I98: 5 | L98: 1000 | M98: 0.5 | N98: 0.5
H99: 18 | I99: 5 | L99: 1000 | M99: 0.5 | N99: 0.5
B100: 商品文號： | C100: 109.07.01富壽商精字第1090002113號函備查、109.09.01依109.07.08金管保壽字第1090423012號函修正 | D100: =$B$100&$C$100 -> 商品文號：109.07.01富壽商精字第1090002113號函備查、109.09.01依109.07.08金管保壽字第1090423012號函修正 | H100: 19 | I100: 5 | L100: 1000 | M100: 0.5 | N100: 0.5
...

Sheet 輸入頁
A2: =OP!$D$53 | B2: =OP!$E$23 -> 富邦人壽連馨久久長期照顧終身健康保險建議書
B3: 請注意：如使用非微軟OFFICE-PC版開啟本建議書，本建議書內容可能會因硬體系統升級或軟體更新問題導致數值誤差，業務同仁使用時請確實確認。
C4: 被保險人基本資料： | M4: 投保年齡區間： | N4: =OP!$C$16&OP!$E$15&" ~ "&OP!$C$15&"歲 "&"("&IF(OP!$C$9=1,OP!$C$7,OP!F4&" / "&OP!F5&" / "&OP!F6)&")" -> 15歲 ~ 50歲 (650225) | R4: =IF(OP!$C$105="停售","本商品已停售","")
A5: =OP!$E$6 | D5: 姓名： | E5: 客戶 | J5: 性別： | K5: 女 | M5: 生日(民國)： | N5: 1010101 | O5: 保險年齡： | P5: =OP!$D$5 -> 15 | Q5: 實際年齡： | R5: =OP!$D$6 -> 14 | S5: =IF(OR(K5="",E7="",E17="",Q17="",Q19="",E39="",J39="",OR(J39<J40,J39>K40),A2=1),1,"") -> 1
E6: =IF(OP!$E$6=1,"生日日期錯誤",IF($A$2=1,"部分內容空白或錯誤",OP!$D$17))&OP!$B$194&" "&OP!$D$87
A8: =OP!$AE$6 | C8: 被保險人2 | D8: 姓名： | E8: 客戶 | J8: 性別： | K8: 男 | M8: 生日(民國)： | N8: 981101 | O8: 保險年齡： | P8: =OP!$AD$5 -> 17 | Q8: 實際年齡： | R8: =OP!$AD$6 -> 16
E9: =IF(OP!$AE$6=1,"生日日期錯誤",IF($A$2=1,"部分內容空白或錯誤",OP!$AD$17))&OP!$B$194&" "&OP!$AD$26
E10: =IF(OP!$C$9=1,OP!$C$7,OP!$F$4) -> 650225 | F10: =IF(OP!$C$9=1,OP!$E$7,OP!$F$3) -> 1150825 | J10: =OP!E3 -> 31
D12: 要保人/繳款人： | E12: 同被保險人 | I12: =IF(OP!$C$181<10,"",OP!$C$181) | K12: ="請確認右方內容："&IF(OP!$C$181=1,"要保人、被保險人、繳款人皆為 "&OP!$D$182,"要保人："&IF(OR(OP!$C$181=1,OP!$C$181=2),OP!$D$182,OP!$D$181)&" "&"被保險人："&OP!$D$182&" "&"繳款人："&IF(OR(OP!$C$181=1,OP!$C$181=3),OP!$D$182,IF(OR(OP!$C$181=4),OP!$D$181,OP!$D$183))) -> 請確認右方內容：要保人、被保險人、繳款人皆為 客戶
D13: =IF(OR(OP!$C$181=1,OP!$C$181=2),"","要保人姓名：") | N13: =IF(OR(OP!$C$181=1,OP!$C$181=3,OP!$C$181=4),"","繳款人姓名：")
D14: =IF(OR($D$13=""),"","要保人生日(民國)：") | I14: =IF(OR($D$13=""),"","保險年齡："&OP!$D$193&"歲") | N14: =IF(OR($N$13=""),"","繳款人生日(民國)：")
E15: =IF(AND($E$14<>"",OP!$E$194=1),"要保人生日日期錯誤","")&OP!$B$194 | O15: =IF(AND($O$14<>"",OP!$D$198=1),"本件需進行錄音","")
B17: 繳別： | E17: 年繳 | H17: =OP!D49 | O17: 繳費方式： | P17: =IF(OP!$C$24=1,"","首期") -> 首期 | Q17: 匯款
D19: 年度保單紅利給付方式： | E19: 現金給付 | P19: =IF(OP!$C$24=1,"","續期") -> 續期 | Q19: 金融機構轉帳
A21: =IF(AND(OP!I13<=0,OP!J13<=0,OP!J27=1),1,"") | D21: 身份別保費折扣： | E21: 無 | R21: =IF($S$5=1,"",IF(OR(OP!$C$42>0,OP!$C$44>0),"本保件如符合本公司繳費方式折扣條件，","")&IF(AND(OP!$C$42>0,OP!$C$44>0),"首、續期享有1%繳費方式折扣",IF(AND(OP!$C$42=0,OP!$C$44>0),"續期享有1%繳費方式折扣",IF(AND(OP!$C$42>0,OP!$C$44=0),"首期享有1%繳費方式折扣",""))))
E22: =IF($A$2=1,"",OP!K12&OP!K13)
F24: 主約身故保障給付設定：
F26: =PY!$B$4 -> 指定保險金比例： | G26: 0 | J26: % | K26: ="0% ~ 100%"&" 約定分期給付換算比例："&TEXT(PY!$C$4,"0%") -> 0% ~ 100% 約定分期給付換算比例：0%
F28: =IF(OR($G$26<=0,$G$26="",$G$26>100),"",PY!$B$7) | G28: =IF(OR($G$26<=0,$G$26="",$G$26>100),"",PY!$C$7) | J28: =IF(OR($G$26<=0,$G$26="",$G$26>100),""," 計算分期給付金額之利率")
F30: =IF(OR($G$26<=0,$G$26="",$G$26>100),"",PY!$B$6) | G30: 10
S36: =IF(OR(E39="",J39=""),1,"")
D37: 主約繳費年期： | E37: 30 | G37: 保額(以千為單位) | M37: 保額限制： | P37: =OP!$C$32&"保費：" -> 年繳保費： | R37: =IF($A$2=1,"",OP!$C$35) -> 16170
A39: =OP!D28 | D39: 主約險種代號： | E39: LTQ | G39: 保額(萬)： | J39: 1 | M39: =IF(E39="","",TEXT($J$40,IF(OP!$E$28=0,"#,##0","#,##0.0"))&" ~ "&TEXT($K$40,IF(OP!$E$28=0,"#,##0","#,##0.0"))) -> 0.5 ~ 2.0 | N39: =OP!E64&OP!$D$37
J40: =OP!$C$26 -> 0.5 | K40: =OP!$C$27 -> 2
C41: =IF(OR(O7>N4,E39="",M39="保額超過限制，請修正"),"","保障年期：") -> 保障年期： | D41: =IF(OR(O7>N4,E39="",M39="保額超過限制，請修正"),"","終身（保險年齡屆滿"&OP!$F$57&"歲）") -> 終身（保險年齡屆滿99歲） | O41: =IF(OR(AND(OP!$C$24=1,OP!$C$46<=0),A2=1),"",IF(OP!$C$46>0,"折扣後","")&OP!$C$32&IF(OP!$C$24=1,"保費：","首期保費：")) -> 折扣後年繳首期保費： | R41: =IF(OR($A$2=1,AND(OP!$C$24=1,OP!$C$46<=0)),"",OP!C48) -> 16008
O43: =IF(OR(OP!$C$24=1,A2=1),"",IF(OP!$C$47>0,"折扣後","")&OP!$C$32&"續期保費：") -> 折扣後年繳續期保費： | R43: =IF(OR($A$2=1,OP!$C$24=1),"",OP!$C$49) -> 16008
R46: =OP!$D$94 -> 本保單計價幣別：新臺幣
B50: =OP!$C$54 -> V1.0-1150720 | P50: 試算日： | Q50: =OP!$D$121 -> 1150825
B52: 預計第二年度起保單週月日 領取生存保險金/元： | G52: 50000 | J52: =TEXT(J40*10000*1.5%,"#,##0")&"~"&TEXT(K40*10000*1.5%,"#,##0") -> 75~300 | N52: 換算投保保額/萬： | O52: =MAX(J40,MIN(K40,ROUNDUP(G52/1.5%,-4)/10000)) -> 2 | P52: =IF(G52<J40*10000*1.5%,"換算保額低於最低承保保額，顯示最低承保保額。",IF(G52>K40*10000*1.5%,"換算保額高於最高承保保額，顯示最高承保保額。","")) -> 換算保額高於最高承保保額，顯示最高承保保額。
D53: 客戶計畫繳交保費(元)： | E53: 100000 | M53: 換算可購買保額(萬)： | N53: =OP!$C$62 -> 6.1 | O53: 計畫繳交保費換算保額未考慮保費折扣條件
D202: 公司名稱： | O202: 投保本商品的目的及需求： | P202: 其他(請自行填入)
D203: 招攬人： | S203: 「銷售過程紀錄錄音參考範本投保目的及需求須與業務人員報告書一致」
D204: 登錄證：
D205: 共同招攬人：
D206: 共同招攬人登錄證：

Sheet 列印頁
A2: =OP!$D$53 | B2: =OP!$E$23 -> 富邦人壽連馨久久長期照顧終身健康保險建議書
D4: 被保險人： | E4: =OP!$C$73 -> 客戶 | L4: 保險年齡： | M4: =OP!$D$5 -> 15 | P4: 性別： | Q4: =OP!$E$18 -> 女 | R4: =OP!$D$94 -> 本保單計價幣別：新臺幣
B5: 保險種類 | M5: 險種代碼 | P5: 保額 | S5: =OP!$C$32&"應繳保費/元" -> 年繳應繳保費/元
A6: 1 | B6: =OP!$D$93 -> 富邦人壽連馨久久長期照顧終身健康保險(繳費30年) | M6: =IF($A$2=1,"",OP!$C$22) -> LTQ | P6: =IF($A$2=1,"",TEXT(OP!$C$28,IF(OP!$E$28=0,"#,##0 ","#,##0.0 "))&"萬") -> 1.0 萬 | S6: =IF($A$2=1,"",OP!C35) -> 16170
B7: =OP!$D$91 -> 本保件符合保費折扣條件：繳費方式 1.0%折扣。
B8: =OP!$D$92 -> 年繳總保費16,170元，首期折扣後保費16,008元，續期折扣後保費16,008元
B11: =IF($A$2=1,"",OP!$C$22&"第二保單年度起之續期健康管理保險費折扣") -> LTQ第二保單年度起之續期健康管理保險費折扣
B13: =IF($A$2=1,"",OP!$H$69) -> 健康管理保險費折扣項目 | H13: =IF($A$2=1,"",OP!$I$69) -> LTQ折扣率 | K13: =IF($A$2=1,"",OP!$J$69) -> LTQ續年度折扣後實繳保費(含續期繳費方式折扣1.0%)
B14: =IF($A$2=1,"",OP!$H$70) -> 指定疫苗接種或健康檢查 | H14: =IF($A$2=1,"",OP!$I$70) -> 0.01 | K14: =IF($A$2=1,"",TEXT(OP!$J$70,"#,### 元")) -> 15,847 元
B15: ‧上表健康管理折扣後實繳保費，繳費期內如不符折扣條件，上表將不適用，詳細內容以投保當時保單條款規定為準。
B17: 投 保 利 益 表
V18: =IF(OP!$C$105="停售","本商品已停售","")
B20: 老年住院醫療 提前給付 保險金 | E20: =IF(OR($A$2=1),"",TEXT(OP!$C$28*10000*0.1,"#,##0")&"元/日") -> 1,000元/日 | I20: ‧被保險人於本契約有效期間內且於保險年齡八十歲(含)之後因保單條款約定之疾病或意外傷害事故，而於醫院接受住院診療，且被保險人於該次住院之入院日尚未符合保單條款「完全失能關懷保險金」或「長期照顧一次保險金」約定之保險金給付條件者，本公司就該次住院給付保險金。 ‧本條保險金累計給付之住院日數最高以二百日為限。
B21: 完全失能 關懷 保險金 | E21: =IF(OR($A$2=1),"",TEXT(OP!$C$28*10000*15,"#,##0")&"元") -> 150,000元 | I21: ‧被保險人於本契約有效期間內因保單條款約定的疾病或意外傷害事故，經醫院醫師診斷確定符合保單條款附表所列完全失能程度之一，且於完全失能診斷確定日仍生存者依保單條款約定給付，本契約有效期間內以給付一次為限。 ‧若被保險人已先行符合保單條款「長期照顧一次保險金」約定之給付條件，本公司不再負本條保險金給付之責；若被保險人同時符合本條與保單條款「長期照顧一次保險金」約定之給付條件，本公司僅就其中一條約定負給付保險金之責。
B22: 完全失能 生活扶助 保險金 | E22: 累計 給付年度 | G22: 每月 給付金額 (元) | I22: ‧被保險人於本契約有效期間內因保單條款約定的疾病或意外傷害事故，經醫院醫師診斷確定致成保單條款附表所列完全失能程度之一，且於完全失能診斷確定日仍生存者，本公司於完全失能診斷確定日起一年內之每一週月日（不論被保險人生存與否）依保單條款約定給付。 ‧被保險人於完全失能診斷確定日之週年日仍生存者，本公司於各該週年日起一年內之每一週月日（不論被保險人生存與否）依保單條款約定給付。 ‧被保險人於本契約有效期間內，不論同時或先後致成二項以上完全失能者，本公司僅給付一項。若係同項完全失能發生二次以上者，本公司僅給付一次。 ‧本公司於依保單條款約定給付「長期照顧分期保險金」期間，不另給付「完全失能生活扶助保險金」。「完全失能生活扶助保險金」與「長期照顧分期保險金」之給付，合計最高給付上限為一百九十二個月。
E23: 1 | G23: =IF(OR($A$2=1,ISERROR(VLOOKUP(OP!$C$56&TEXT($E23,"00"),PVal,2,0))),"",TEXT(OP!$C$28*VLOOKUP(OP!$C$56&TEXT($E23,"00"),PVal,2,0),"#,##0")) -> 20,000
E24: =$E23+1 -> 2 | G24: =IF(OR($A$2=1,ISERROR(VLOOKUP(OP!$C$56&TEXT($E24,"00"),PVal,2,0))),"",TEXT(OP!$C$28*VLOOKUP(OP!$C$56&TEXT($E24,"00"),PVal,2,0),"#,##0")) -> 20,400
E25: =$E24+1 -> 3 | G25: =IF(OR($A$2=1,ISERROR(VLOOKUP(OP!$C$56&TEXT($E25,"00"),PVal,2,0))),"",TEXT(OP!$C$28*VLOOKUP(OP!$C$56&TEXT($E25,"00"),PVal,2,0),"#,##0")) -> 20,800
E26: =$E25+1 -> 4 | G26: =IF(OR($A$2=1,ISERROR(VLOOKUP(OP!$C$56&TEXT($E26,"00"),PVal,2,0))),"",TEXT(OP!$C$28*VLOOKUP(OP!$C$56&TEXT($E26,"00"),PVal,2,0),"#,##0")) -> 21,200
E27: =$E26+1 -> 5 | G27: =IF(OR($A$2=1,ISERROR(VLOOKUP(OP!$C$56&TEXT($E27,"00"),PVal,2,0))),"",TEXT(OP!$C$28*VLOOKUP(OP!$C$56&TEXT($E27,"00"),PVal,2,0),"#,##0")) -> 21,600
E28: =$E27+1 -> 6 | G28: =IF(OR($A$2=1,ISERROR(VLOOKUP(OP!$C$56&TEXT($E28,"00"),PVal,2,0))),"",TEXT(OP!$C$28*VLOOKUP(OP!$C$56&TEXT($E28,"00"),PVal,2,0),"#,##0")) -> 22,000
E29: =$E28+1 -> 7 | G29: =IF(OR($A$2=1,ISERROR(VLOOKUP(OP!$C$56&TEXT($E29,"00"),PVal,2,0))),"",TEXT(OP!$C$28*VLOOKUP(OP!$C$56&TEXT($E29,"00"),PVal,2,0),"#,##0")) -> 22,400
E30: =$E29+1 -> 8 | G30: =IF(OR($A$2=1,ISERROR(VLOOKUP(OP!$C$56&TEXT($E30,"00"),PVal,2,0))),"",TEXT(OP!$C$28*VLOOKUP(OP!$C$56&TEXT($E30,"00"),PVal,2,0),"#,##0")) -> 22,800
E31: =$E30+1 -> 9 | G31: =IF(OR($A$2=1,ISERROR(VLOOKUP(OP!$C$56&TEXT($E31,"00"),PVal,2,0))),"",TEXT(OP!$C$28*VLOOKUP(OP!$C$56&TEXT($E31,"00"),PVal,2,0),"#,##0")) -> 23,200
E32: =$E31+1 -> 10 | G32: =IF(OR($A$2=1,ISERROR(VLOOKUP(OP!$C$56&TEXT($E32,"00"),PVal,2,0))),"",TEXT(OP!$C$28*VLOOKUP(OP!$C$56&TEXT($E32,"00"),PVal,2,0),"#,##0")) -> 23,600
E33: =$E32+1 -> 11 | G33: =IF(OR($A$2=1,ISERROR(VLOOKUP(OP!$C$56&TEXT($E33,"00"),PVal,2,0))),"",TEXT(OP!$C$28*VLOOKUP(OP!$C$56&TEXT($E33,"00"),PVal,2,0),"#,##0")) -> 24,000
E34: =$E33+1 -> 12 | G34: =IF(OR($A$2=1,ISERROR(VLOOKUP(OP!$C$56&TEXT($E34,"00"),PVal,2,0))),"",TEXT(OP!$C$28*VLOOKUP(OP!$C$56&TEXT($E34,"00"),PVal,2,0),"#,##0")) -> 24,400
E35: =$E34+1 -> 13 | G35: =IF(OR($A$2=1,ISERROR(VLOOKUP(OP!$C$56&TEXT($E35,"00"),PVal,2,0))),"",TEXT(OP!$C$28*VLOOKUP(OP!$C$56&TEXT($E35,"00"),PVal,2,0),"#,##0")) -> 24,800
... E38: =$E37+1 -> 16 | G38: =IF(OR($A$2=1,ISERROR(VLOOKUP(OP!$C$56&TEXT($E38,"00"),PVal,2,0))),"",TEXT(OP!$C$28*VLOOKUP(OP!$C$56&TEXT($E38,"00"),PVal,2,0),"#,##0")) -> 26,000
B39: 長期照顧 一次 保險金 | E39: =IF(OR($A$2=1),"",TEXT(OP!$C$28*10000*15,"#,##0")&"元") -> 150,000元 | I39: ‧被保險人於本契約有效期間內，經醫院專科醫師診斷確定符合保單條款約定之「長期照顧狀態」，並於免責期間屆滿時仍生存且持續符合「長期照顧狀態」者，本公司按免責期間屆滿時之保險金額的十五倍給付。
E40: =IF(OR($A$2=1),"",TEXT(OP!$C$28*10000*10,"#,##0")&"元") -> 100,000元 | I40: ‧前項情形，若被保險人係於保險年齡六十五歲(不含)以前，符合首次經醫院專科醫師診斷確定屬於保單條款約定之認知功能障礙，以及於免責期間屆滿時仍生存且持續符合「長期照顧狀態」之認知功能障礙二項條件者，本公司除依前項約定之金額給付外，另加計免責期間屆滿時之保險金額的十倍給付。但被保險人於符合認知功能障礙以前，已先行經醫院專科醫師診斷確定屬於保單條款約定之生理功能障礙，而符合前項約定給付條件者，無本項約定之適用。
E41: ‧本契約有效期間內以給付一次為限。 ‧若被保險人已先行符合保單條款「完全失能關懷保險金」約定之給付條件，本公司不再負本條保險金給付之責；若被保險人同時符合本條與保單條款「完全失能關懷保險金」約定之給付條件，本公司僅就其中一條約定負給付保險金之責。
A43: 1 | B43: =OP!$D$107 -> 本建議書僅供參考，詳細商品內容及其變更，應以投保當時保單條款內容及本公司核保、保全作業規定為準
D44: =OP!$D$106 -> ※本契約條款樣張須於訂立契約前提供要保人至少三日審閱期間 | V44: =OP!$D$105 -> V1.0-1150720 試算日：1150825
V46: =IF(OP!$C$105="停售","本商品已停售","")
B47: 長期照顧 分期 保險金 | E47: 累計 給付年度 | G47: 每月 給付金額 (元) | I47: ‧被保險人於本契約有效期間內，經醫院專科醫師診斷確定符合保單條款約定之「長期照顧狀態」，並於免責期間屆滿時仍生存且持續符合「長期照顧狀態」者，本公司於免責期間屆滿翌日及一年內之每一週月日（不論被保險人生存與否）依保單條款約定給付。 ‧被保險人於免責期間屆滿翌日的週年日仍生存並持續符合「長期照顧狀態」者，本公司於各該週年日起一年內之每一週月日（不論被保險人生存與否）依保單條款約定給付。 ‧本公司於依保單條款約定給付「完全失能生活扶助保險金」期間，不另給付「長期照顧分期保險金」。「長期照顧分期保險金」與「完全失能生活扶助保險金」之給付，合計最高給付上限為一百九十二個月。
E48: 1 | G48: =IF(OR($A$2=1,ISERROR(VLOOKUP(OP!$C$56&TEXT($E48,"00"),PVal,2,0))),"",TEXT(OP!$C$28*VLOOKUP(OP!$C$56&TEXT($E48,"00"),PVal,2,0),"#,##0")) -> 20,000
E49: =$E48+1 -> 2 | G49: =IF(OR($A$2=1,ISERROR(VLOOKUP(OP!$C$56&TEXT($E49,"00"),PVal,2,0))),"",TEXT(OP!$C$28*VLOOKUP(OP!$C$56&TEXT($E49,"00"),PVal,2,0),"#,##0")) -> 20,400
E50: =$E49+1 -> 3 | G50: =IF(OR($A$2=1,ISERROR(VLOOKUP(OP!$C$56&TEXT($E50,"00"),PVal,2,0))),"",TEXT(OP!$C$28*VLOOKUP(OP!$C$56&TEXT($E50,"00"),PVal,2,0),"#,##0")) -> 20,800
E51: =$E50+1 -> 4 | G51: =IF(OR($A$2=1,ISERROR(VLOOKUP(OP!$C$56&TEXT($E51,"00"),PVal,2,0))),"",TEXT(OP!$C$28*VLOOKUP(OP!$C$56&TEXT($E51,"00"),PVal,2,0),"#,##0")) -> 21,200
E52: =$E51+1 -> 5 | G52: =IF(OR($A$2=1,ISERROR(VLOOKUP(OP!$C$56&TEXT($E52,"00"),PVal,2,0))),"",TEXT(OP!$C$28*VLOOKUP(OP!$C$56&TEXT($E52,"00"),PVal,2,0),"#,##0")) -> 21,600
E53: =$E52+1 -> 6 | G53: =IF(OR($A$2=1,ISERROR(VLOOKUP(OP!$C$56&TEXT($E53,"00"),PVal,2,0))),"",TEXT(OP!$C$28*VLOOKUP(OP!$C$56&TEXT($E53,"00"),PVal,2,0),"#,##0")) -> 22,000
E54: =$E53+1 -> 7 | G54: =IF(OR($A$2=1,ISERROR(VLOOKUP(OP!$C$56&TEXT($E54,"00"),PVal,2,0))),"",TEXT(OP!$C$28*VLOOKUP(OP!$C$56&TEXT($E54,"00"),PVal,2,0),"#,##0")) -> 22,400
E55: =$E54+1 -> 8 | G55: =IF(OR($A$2=1,ISERROR(VLOOKUP(OP!$C$56&TEXT($E55,"00"),PVal,2,0))),"",TEXT(OP!$C$28*VLOOKUP(OP!$C$56&TEXT($E55,"00"),PVal,2,0),"#,##0")) -> 22,800
E56: =$E55+1 -> 9 | G56: =IF(OR($A$2=1,ISERROR(VLOOKUP(OP!$C$56&TEXT($E56,"00"),PVal,2,0))),"",TEXT(OP!$C$28*VLOOKUP(OP!$C$56&TEXT($E56,"00"),PVal,2,0),"#,##0")) -> 23,200
E57: =$E56+1 -> 10 | G57: =IF(OR($A$2=1,ISERROR(VLOOKUP(OP!$C$56&TEXT($E57,"00"),PVal,2,0))),"",TEXT(OP!$C$28*VLOOKUP(OP!$C$56&TEXT($E57,"00"),PVal,2,0),"#,##0")) -> 23,600
E58: =$E57+1 -> 11 | G58: =IF(OR($A$2=1,ISERROR(VLOOKUP(OP!$C$56&TEXT($E58,"00"),PVal,2,0))),"",TEXT(OP!$C$28*VLOOKUP(OP!$C$56&TEXT($E58,"00"),PVal,2,0),"#,##0")) -> 24,000
E59: =$E58+1 -> 12 | G59: =IF(OR($A$2=1,ISERROR(VLOOKUP(OP!$C$56&TEXT($E59,"00"),PVal,2,0))),"",TEXT(OP!$C$28*VLOOKUP(OP!$C$56&TEXT($E59,"00"),PVal,2,0),"#,##0")) -> 24,400
E60: =$E59+1 -> 13 | G60: =IF(OR($A$2=1,ISERROR(VLOOKUP(OP!$C$56&TEXT($E60,"00"),PVal,2,0))),"",TEXT(OP!$C$28*VLOOKUP(OP!$C$56&TEXT($E60,"00"),PVal,2,0),"#,##0")) -> 24,800
... E63: =$E62+1 -> 16 | G63: =IF(OR($A$2=1,ISERROR(VLOOKUP(OP!$C$56&TEXT($E63,"00"),PVal,2,0))),"",TEXT(OP!$C$28*VLOOKUP(OP!$C$56&TEXT($E63,"00"),PVal,2,0),"#,##0")) -> 26,000
B64: 祝壽 保險金 | E64: =IF(OR($A$2=1),"",""&TEXT(OP!$C$133,"#,###元")) -> 494,802元 | I64: 被保險人於本契約有效期間內且在保險年齡屆滿九十九歲仍生存者，本公司按當年度保險金額給付祝壽保險金後，本契約效力即行終止。如被保險人累計已領及應領而未領之各項保險金總額已達年繳保險費總和的一點零二倍者，本公司不再給付祝壽保險金。
B65: 豁免保險費 | E65: ‧被保險人於本契約有效且繳費期間內，經醫院醫師診斷確定致成下列情形之一者，本公司豁免診斷確定日後之本契約（不含附約）續期應繳之各期保險費，本契約繼續有效： 一、依保單條款約定之疾病或意外傷害事故致成保單條款附表所列之完全失能程度之一者。 二、被保險人經醫院專科醫師診斷確定符合保單條款約定之「長期照顧狀態」，並於免責期間屆滿後 仍生存且持續符合「長期照顧狀態」者。 ‧本契約依前項第二款約定豁免保險費期間，若被保險人因保單條款約定之被保險人「長期照顧狀態」已消滅致本公司暫停給付「長期照顧分期保險金」時，本公司自暫停給付「長期照顧分期保險金」之次一應繳日起暫停豁免保險費。要保人應於暫停給付「長期照顧分期保險金」之次一應繳日起繼續交付保險費使本契約繼續有效。
B66: 身故保險金或 喪葬費用 保險金 | E66: 詳下表身故保障 | I66: 被保險人於本契約有效期間內身故者，本公司按當年度保險金額給付身故保險金後，本契約效力即行終止。如被保險人累計已領及應領而未領之各項保險金總額已達年繳保險費總和的一點零二倍者，本公司不再給付身故保險金。
B67: ‧上表所列各項保險實際給付金額以保單條款規定為準。
A91: 1 | B91: =OP!$D$107 -> 本建議書僅供參考，詳細商品內容及其變更，應以投保當時保單條款內容及本公司核保、保全作業規定為準
D92: =OP!$D$106 -> ※本契約條款樣張須於訂立契約前提供要保人至少三日審閱期間 | V92: =OP!$D$105 -> V1.0-1150720 試算日：1150825
V94: =IF(OP!$C$105="停售","本商品已停售","")
V95: 單位：元
B96: 保單年度 | C96: 保險年齡 | D96: 年度 實繳保費 | F96: 累計 實繳保費 | I96: 身故保障 | L96: 保單年度 | M96: 保險年齡 | N96: 年度 實繳保費 | P96: 累計 實繳保費 | S96: 身故保障
B97: =IF(OR($A$2=1),"",1) -> 1 | C97: =IF(OR($A$2=1,ISERROR(VLOOKUP($B97,TOV,2,0))),"",VLOOKUP($B97,TOV,2,0)) -> 15 | D97: =IF(OR($A$2=1,ISERROR(VLOOKUP($B97,TOV,總表!$AA$1,0))),"",VLOOKUP($B97,TOV,總表!$AA$1,0)) -> 16008 | F97: =IF(OR($A$2=1,ISERROR(VLOOKUP($B97,TOV,總表!$AB$1,0))),"",VLOOKUP($B97,TOV,總表!$AB$1,0)) -> 16008 | I97: =IF(OR($A$2=1,ISERROR(VLOOKUP($B97,TOV,總表!$H$1,0))),"",VLOOKUP($B97,TOV,總表!$H$1,0)) -> 16493 | L97: =IF(OR($A$2=1,ISERROR(VLOOKUP($B139+1,TOV,2,0))),"",$B139+1) -> 44 | M97: =IF(OR($A$2=1,ISERROR(VLOOKUP($L97,TOV,2,0))),"",VLOOKUP($L97,TOV,2,0)) -> 58 | N97: =IF(OR($A$2=1,ISERROR(VLOOKUP($L97,TOV,總表!$AA$1,0))),"",VLOOKUP($L97,TOV,總表!$AA$1,0)) | P97: =IF(OR($A$2=1,ISERROR(VLOOKUP($L97,TOV,總表!$AB$1,0))),"",VLOOKUP($L97,TOV,總表!$AB$1,0)) -> 480240 | S97: =IF(OR($A$2=1,ISERROR(VLOOKUP($L97,TOV,總表!$H$1,0))),"",VLOOKUP($L97,TOV,總表!$H$1,0)) -> 494802
B98: =IF(OR($A$2=1,ISERROR(VLOOKUP($B97+1,TOV,2,0))),"",$B97+1) -> 2 | C98: =IF(OR($A$2=1,ISERROR(VLOOKUP($B98,TOV,2,0))),"",VLOOKUP($B98,TOV,2,0)) -> 16 | D98: =IF(OR($A$2=1,ISERROR(VLOOKUP($B98,TOV,總表!$AA$1,0))),"",VLOOKUP($B98,TOV,總表!$AA$1,0)) -> 16008 | F98: =IF(OR($A$2=1,ISERROR(VLOOKUP($B98,TOV,總表!$AB$1,0))),"",VLOOKUP($B98,TOV,總表!$AB$1,0)) -> 32016 | I98: =IF(OR($A$2=1,ISERROR(VLOOKUP($B98,TOV,總表!$H$1,0))),"",VLOOKUP($B98,TOV,總表!$H$1,0)) -> 32987 | L98: =IF(OR($A$2=1,ISERROR(VLOOKUP($L97+1,TOV,2,0))),"",$L97+1) -> 45 | M98: =IF(OR($A$2=1,ISERROR(VLOOKUP($L98,TOV,2,0))),"",VLOOKUP($L98,TOV,2,0)) -> 59 | N98: =IF(OR($A$2=1,ISERROR(VLOOKUP($L98,TOV,總表!$AA$1,0))),"",VLOOKUP($L98,TOV,總表!$AA$1,0)) | P98: =IF(OR($A$2=1,ISERROR(VLOOKUP($L98,TOV,總表!$AB$1,0))),"",VLOOKUP($L98,TOV,總表!$AB$1,0)) -> 480240 | S98: =IF(OR($A$2=1,ISERROR(VLOOKUP($L98,TOV,總表!$H$1,0))),"",VLOOKUP($L98,TOV,總表!$H$1,0)) -> 494802
B99: =IF(OR($A$2=1,ISERROR(VLOOKUP($B98+1,TOV,2,0))),"",$B98+1) -> 3 | C99: =IF(OR($A$2=1,ISERROR(VLOOKUP($B99,TOV,2,0))),"",VLOOKUP($B99,TOV,2,0)) -> 17 | D99: =IF(OR($A$2=1,ISERROR(VLOOKUP($B99,TOV,總表!$AA$1,0))),"",VLOOKUP($B99,TOV,總表!$AA$1,0)) -> 16008 | F99: =IF(OR($A$2=1,ISERROR(VLOOKUP($B99,TOV,總表!$AB$1,0))),"",VLOOKUP($B99,TOV,總表!$AB$1,0)) -> 48024 | I99: =IF(OR($A$2=1,ISERROR(VLOOKUP($B99,TOV,總表!$H$1,0))),"",VLOOKUP($B99,TOV,總表!$H$1,0)) -> 49480 | L99: =IF(OR($A$2=1,ISERROR(VLOOKUP($L98+1,TOV,2,0))),"",$L98+1) -> 46 | M99: =IF(OR($A$2=1,ISERROR(VLOOKUP($L99,TOV,2,0))),"",VLOOKUP($L99,TOV,2,0)) -> 60 | N99: =IF(OR($A$2=1,ISERROR(VLOOKUP($L99,TOV,總表!$AA$1,0))),"",VLOOKUP($L99,TOV,總表!$AA$1,0)) | P99: =IF(OR($A$2=1,ISERROR(VLOOKUP($L99,TOV,總表!$AB$1,0))),"",VLOOKUP($L99,TOV,總表!$AB$1,0)) -> 480240 | S99: =IF(OR($A$2=1,ISERROR(VLOOKUP($L99,TOV,總表!$H$1,0))),"",VLOOKUP($L99,TOV,總表!$H$1,0)) -> 494802
B100: =IF(OR($A$2=1,ISERROR(VLOOKUP($B99+1,TOV,2,0))),"",$B99+1) -> 4 | C100: =IF(OR($A$2=1,ISERROR(VLOOKUP($B100,TOV,2,0))),"",VLOOKUP($B100,TOV,2,0)) -> 18 | D100: =IF(OR($A$2=1,ISERROR(VLOOKUP($B100,TOV,總表!$AA$1,0))),"",VLOOKUP($B100,TOV,總表!$AA$1,0)) -> 16008 | F100: =IF(OR($A$2=1,ISERROR(VLOOKUP($B100,TOV,總表!$AB$1,0))),"",VLOOKUP($B100,TOV,總表!$AB$1,0)) -> 64032 | I100: =IF(OR($A$2=1,ISERROR(VLOOKUP($B100,TOV,總表!$H$1,0))),"",VLOOKUP($B100,TOV,總表!$H$1,0)) -> 65974 | L100: =IF(OR($A$2=1,ISERROR(VLOOKUP($L99+1,TOV,2,0))),"",$L99+1) -> 47 | M100: =IF(OR($A$2=1,ISERROR(VLOOKUP($L100,TOV,2,0))),"",VLOOKUP($L100,TOV,2,0)) -> 61 | N100: =IF(OR($A$2=1,ISERROR(VLOOKUP($L100,TOV,總表!$AA$1,0))),"",VLOOKUP($L100,TOV,總表!$AA$1,0)) | P100: =IF(OR($A$2=1,ISERROR(VLOOKUP($L100,TOV,總表!$AB$1,0))),"",VLOOKUP($L100,TOV,總表!$AB$1,0)) -> 480240 | S100: =IF(OR($A$2=1,ISERROR(VLOOKUP($L100,TOV,總表!$H$1,0))),"",VLOOKUP($L100,TOV,總表!$H$1,0)) -> 494802
B101: =IF(OR($A$2=1,ISERROR(VLOOKUP($B100+1,TOV,2,0))),"",$B100+1) -> 5 | C101: =IF(OR($A$2=1,ISERROR(VLOOKUP($B101,TOV,2,0))),"",VLOOKUP($B101,TOV,2,0)) -> 19 | D101: =IF(OR($A$2=1,ISERROR(VLOOKUP($B101,TOV,總表!$AA$1,0))),"",VLOOKUP($B101,TOV,總表!$AA$1,0)) -> 16008 | F101: =IF(OR($A$2=1,ISERROR(VLOOKUP($B101,TOV,總表!$AB$1,0))),"",VLOOKUP($B101,TOV,總表!$AB$1,0)) -> 80040 | I101: =IF(OR($A$2=1,ISERROR(VLOOKUP($B101,TOV,總表!$H$1,0))),"",VLOOKUP($B101,TOV,總表!$H$1,0)) -> 82467 | L101: =IF(OR($A$2=1,ISERROR(VLOOKUP($L100+1,TOV,2,0))),"",$L100+1) -> 48 | M101: =IF(OR($A$2=1,ISERROR(VLOOKUP($L101,TOV,2,0))),"",VLOOKUP($L101,TOV,2,0)) -> 62 | N101: =IF(OR($A$2=1,ISERROR(VLOOKUP($L101,TOV,總表!$AA$1,0))),"",VLOOKUP($L101,TOV,總表!$AA$1,0)) | P101: =IF(OR($A$2=1,ISERROR(VLOOKUP($L101,TOV,總表!$AB$1,0))),"",VLOOKUP($L101,TOV,總表!$AB$1,0)) -> 480240 | S101: =IF(OR($A$2=1,ISERROR(VLOOKUP($L101,TOV,總表!$H$1,0))),"",VLOOKUP($L101,TOV,總表!$H$1,0)) -> 494802
B102: =IF(OR($A$2=1,ISERROR(VLOOKUP($B101+1,TOV,2,0))),"",$B101+1) -> 6 | C102: =IF(OR($A$2=1,ISERROR(VLOOKUP($B102,TOV,2,0))),"",VLOOKUP($B102,TOV,2,0)) -> 20 | D102: =IF(OR($A$2=1,ISERROR(VLOOKUP($B102,TOV,總表!$AA$1,0))),"",VLOOKUP($B102,TOV,總表!$AA$1,0)) -> 16008 | F102: =IF(OR($A$2=1,ISERROR(VLOOKUP($B102,TOV,總表!$AB$1,0))),"",VLOOKUP($B102,TOV,總表!$AB$1,0)) -> 96048 | I102: =IF(OR($A$2=1,ISERROR(VLOOKUP($B102,TOV,總表!$H$1,0))),"",VLOOKUP($B102,TOV,總表!$H$1,0)) -> 98960 | L102: =IF(OR($A$2=1,ISERROR(VLOOKUP($L101+1,TOV,2,0))),"",$L101+1) -> 49 | M102: =IF(OR($A$2=1,ISERROR(VLOOKUP($L102,TOV,2,0))),"",VLOOKUP($L102,TOV,2,0)) -> 63 | N102: =IF(OR($A$2=1,ISERROR(VLOOKUP($L102,TOV,總表!$AA$1,0))),"",VLOOKUP($L102,TOV,總表!$AA$1,0)) | P102: =IF(OR($A$2=1,ISERROR(VLOOKUP($L102,TOV,總表!$AB$1,0))),"",VLOOKUP($L102,TOV,總表!$AB$1,0)) -> 480240 | S102: =IF(OR($A$2=1,ISERROR(VLOOKUP($L102,TOV,總表!$H$1,0))),"",VLOOKUP($L102,TOV,總表!$H$1,0)) -> 494802
B103: =IF(OR($A$2=1,ISERROR(VLOOKUP($B102+1,TOV,2,0))),"",$B102+1) -> 7 | C103: =IF(OR($A$2=1,ISERROR(VLOOKUP($B103,TOV,2,0))),"",VLOOKUP($B103,TOV,2,0)) -> 21 | D103: =IF(OR($A$2=1,ISERROR(VLOOKUP($B103,TOV,總表!$AA$1,0))),"",VLOOKUP($B103,TOV,總表!$AA$1,0)) -> 16008 | F103: =IF(OR($A$2=1,ISERROR(VLOOKUP($B103,TOV,總表!$AB$1,0))),"",VLOOKUP($B103,TOV,總表!$AB$1,0)) -> 112056 | I103: =IF(OR($A$2=1,ISERROR(VLOOKUP($B103,TOV,總表!$H$1,0))),"",VLOOKUP($B103,TOV,總表!$H$1,0)) -> 115454 | L103: =IF(OR($A$2=1,ISERROR(VLOOKUP($L102+1,TOV,2,0))),"",$L102+1) -> 50 | M103: =IF(OR($A$2=1,ISERROR(VLOOKUP($L103,TOV,2,0))),"",VLOOKUP($L103,TOV,2,0)) -> 64 | N103: =IF(OR($A$2=1,ISERROR(VLOOKUP($L103,TOV,總表!$AA$1,0))),"",VLOOKUP($L103,TOV,總表!$AA$1,0)) | P103: =IF(OR($A$2=1,ISERROR(VLOOKUP($L103,TOV,總表!$AB$1,0))),"",VLOOKUP($L103,TOV,總表!$AB$1,0)) -> 480240 | S103: =IF(OR($A$2=1,ISERROR(VLOOKUP($L103,TOV,總表!$H$1,0))),"",VLOOKUP($L103,TOV,總表!$H$1,0)) -> 494802
B104: =IF(OR($A$2=1,ISERROR(VLOOKUP($B103+1,TOV,2,0))),"",$B103+1) -> 8 | C104: =IF(OR($A$2=1,ISERROR(VLOOKUP($B104,TOV,2,0))),"",VLOOKUP($B104,TOV,2,0)) -> 22 | D104: =IF(OR($A$2=1,ISERROR(VLOOKUP($B104,TOV,總表!$AA$1,0))),"",VLOOKUP($B104,TOV,總表!$AA$1,0)) -> 16008 | F104: =IF(OR($A$2=1,ISERROR(VLOOKUP($B104,TOV,總表!$AB$1,0))),"",VLOOKUP($B104,TOV,總表!$AB$1,0)) -> 128064 | I104: =IF(OR($A$2=1,ISERROR(VLOOKUP($B104,TOV,總表!$H$1,0))),"",VLOOKUP($B104,TOV,總表!$H$1,0)) -> 131947 | L104: =IF(OR($A$2=1,ISERROR(VLOOKUP($L103+1,TOV,2,0))),"",$L103+1) -> 51 | M104: =IF(OR($A$2=1,ISERROR(VLOOKUP($L104,TOV,2,0))),"",VLOOKUP($L104,TOV,2,0)) -> 65 | N104: =IF(OR($A$2=1,ISERROR(VLOOKUP($L104,TOV,總表!$AA$1,0))),"",VLOOKUP($L104,TOV,總表!$AA$1,0)) | P104: =IF(OR($A$2=1,ISERROR(VLOOKUP($L104,TOV,總表!$AB$1,0))),"",VLOOKUP($L104,TOV,總表!$AB$1,0)) -> 480240 | S104: =IF(OR($A$2=1,ISERROR(VLOOKUP($L104,TOV,總表!$H$1,0))),"",VLOOKUP($L104,TOV,總表!$H$1,0)) -> 494802
B105: =IF(OR($A$2=1,ISERROR(VLOOKUP($B104+1,TOV,2,0))),"",$B104+1) -> 9 | C105: =IF(OR($A$2=1,ISERROR(VLOOKUP($B105,TOV,2,0))),"",VLOOKUP($B105,TOV,2,0)) -> 23 | D105: =IF(OR($A$2=1,ISERROR(VLOOKUP($B105,TOV,總表!$AA$1,0))),"",VLOOKUP($B105,TOV,總表!$AA$1,0)) -> 16008 | F105: =IF(OR($A$2=1,ISERROR(VLOOKUP($B105,TOV,總表!$AB$1,0))),"",VLOOKUP($B105,TOV,總表!$AB$1,0)) -> 144072 | I105: =IF(OR($A$2=1,ISERROR(VLOOKUP($B105,TOV,總表!$H$1,0))),"",VLOOKUP($B105,TOV,總表!$H$1,0)) -> 148441 | L105: =IF(OR($A$2=1,ISERROR(VLOOKUP($L104+1,TOV,2,0))),"",$L104+1) -> 52 | M105: =IF(OR($A$2=1,ISERROR(VLOOKUP($L105,TOV,2,0))),"",VLOOKUP($L105,TOV,2,0)) -> 66 | N105: =IF(OR($A$2=1,ISERROR(VLOOKUP($L105,TOV,總表!$AA$1,0))),"",VLOOKUP($L105,TOV,總表!$AA$1,0)) | P105: =IF(OR($A$2=1,ISERROR(VLOOKUP($L105,TOV,總表!$AB$1,0))),"",VLOOKUP($L105,TOV,總表!$AB$1,0)) -> 480240 | S105: =IF(OR($A$2=1,ISERROR(VLOOKUP($L105,TOV,總表!$H$1,0))),"",VLOOKUP($L105,TOV,總表!$H$1,0)) -> 494802
B106: =IF(OR($A$2=1,ISERROR(VLOOKUP($B105+1,TOV,2,0))),"",$B105+1) -> 10 | C106: =IF(OR($A$2=1,ISERROR(VLOOKUP($B106,TOV,2,0))),"",VLOOKUP($B106,TOV,2,0)) -> 24 | D106: =IF(OR($A$2=1,ISERROR(VLOOKUP($B106,TOV,總表!$AA$1,0))),"",VLOOKUP($B106,TOV,總表!$AA$1,0)) -> 16008 | F106: =IF(OR($A$2=1,ISERROR(VLOOKUP($B106,TOV,總表!$AB$1,0))),"",VLOOKUP($B106,TOV,總表!$AB$1,0)) -> 160080 | I106: =IF(OR($A$2=1,ISERROR(VLOOKUP($B106,TOV,總表!$H$1,0))),"",VLOOKUP($B106,TOV,總表!$H$1,0)) -> 164934 | L106: =IF(OR($A$2=1,ISERROR(VLOOKUP($L105+1,TOV,2,0))),"",$L105+1) -> 53 | M106: =IF(OR($A$2=1,ISERROR(VLOOKUP($L106,TOV,2,0))),"",VLOOKUP($L106,TOV,2,0)) -> 67 | N106: =IF(OR($A$2=1,ISERROR(VLOOKUP($L106,TOV,總表!$AA$1,0))),"",VLOOKUP($L106,TOV,總表!$AA$1,0)) | P106: =IF(OR($A$2=1,ISERROR(VLOOKUP($L106,TOV,總表!$AB$1,0))),"",VLOOKUP($L106,TOV,總表!$AB$1,0)) -> 480240 | S106: =IF(OR($A$2=1,ISERROR(VLOOKUP($L106,TOV,總表!$H$1,0))),"",VLOOKUP($L106,TOV,總表!$H$1,0)) -> 494802
B107: =IF(OR($A$2=1,ISERROR(VLOOKUP($B106+1,TOV,2,0))),"",$B106+1) -> 11 | C107: =IF(OR($A$2=1,ISERROR(VLOOKUP($B107,TOV,2,0))),"",VLOOKUP($B107,TOV,2,0)) -> 25 | D107: =IF(OR($A$2=1,ISERROR(VLOOKUP($B107,TOV,總表!$AA$1,0))),"",VLOOKUP($B107,TOV,總表!$AA$1,0)) -> 16008 | F107: =IF(OR($A$2=1,ISERROR(VLOOKUP($B107,TOV,總表!$AB$1,0))),"",VLOOKUP($B107,TOV,總表!$AB$1,0)) -> 176088 | I107: =IF(OR($A$2=1,ISERROR(VLOOKUP($B107,TOV,總表!$H$1,0))),"",VLOOKUP($B107,TOV,總表!$H$1,0)) -> 181427 | L107: =IF(OR($A$2=1,ISERROR(VLOOKUP($L106+1,TOV,2,0))),"",$L106+1) -> 54 | M107: =IF(OR($A$2=1,ISERROR(VLOOKUP($L107,TOV,2,0))),"",VLOOKUP($L107,TOV,2,0)) -> 68 | N107: =IF(OR($A$2=1,ISERROR(VLOOKUP($L107,TOV,總表!$AA$1,0))),"",VLOOKUP($L107,TOV,總表!$AA$1,0)) | P107: =IF(OR($A$2=1,ISERROR(VLOOKUP($L107,TOV,總表!$AB$1,0))),"",VLOOKUP($L107,TOV,總表!$AB$1,0)) -> 480240 | S107: =IF(OR($A$2=1,ISERROR(VLOOKUP($L107,TOV,總表!$H$1,0))),"",VLOOKUP($L107,TOV,總表!$H$1,0)) -> 494802
B108: =IF(OR($A$2=1,ISERROR(VLOOKUP($B107+1,TOV,2,0))),"",$B107+1) -> 12 | C108: =IF(OR($A$2=1,ISERROR(VLOOKUP($B108,TOV,2,0))),"",VLOOKUP($B108,TOV,2,0)) -> 26 | D108: =IF(OR($A$2=1,ISERROR(VLOOKUP($B108,TOV,總表!$AA$1,0))),"",VLOOKUP($B108,TOV,總表!$AA$1,0)) -> 16008 | F108: =IF(OR($A$2=1,ISERROR(VLOOKUP($B108,TOV,總表!$AB$1,0))),"",VLOOKUP($B108,TOV,總表!$AB$1,0)) -> 192096 | I108: =IF(OR($A$2=1,ISERROR(VLOOKUP($B108,TOV,總表!$H$1,0))),"",VLOOKUP($B108,TOV,總表!$H$1,0)) -> 197921 | L108: =IF(OR($A$2=1,ISERROR(VLOOKUP($L107+1,TOV,2,0))),"",$L107+1) -> 55 | M108: =IF(OR($A$2=1,ISERROR(VLOOKUP($L108,TOV,2,0))),"",VLOOKUP($L108,TOV,2,0)) -> 69 | N108: =IF(OR($A$2=1,ISERROR(VLOOKUP($L108,TOV,總表!$AA$1,0))),"",VLOOKUP($L108,TOV,總表!$AA$1,0)) | P108: =IF(OR($A$2=1,ISERROR(VLOOKUP($L108,TOV,總表!$AB$1,0))),"",VLOOKUP($L108,TOV,總表!$AB$1,0)) -> 480240 | S108: =IF(OR($A$2=1,ISERROR(VLOOKUP($L108,TOV,總表!$H$1,0))),"",VLOOKUP($L108,TOV,總表!$H$1,0)) -> 494802
B109: =IF(OR($A$2=1,ISERROR(VLOOKUP($B108+1,TOV,2,0))),"",$B108+1) -> 13 | C109: =IF(OR($A$2=1,ISERROR(VLOOKUP($B109,TOV,2,0))),"",VLOOKUP($B109,TOV,2,0)) -> 27 | D109: =IF(OR($A$2=1,ISERROR(VLOOKUP($B109,TOV,總表!$AA$1,0))),"",VLOOKUP($B109,TOV,總表!$AA$1,0)) -> 16008 | F109: =IF(OR($A$2=1,ISERROR(VLOOKUP($B109,TOV,總表!$AB$1,0))),"",VLOOKUP($B109,TOV,總表!$AB$1,0)) -> 208104 | I109: =IF(OR($A$2=1,ISERROR(VLOOKUP($B109,TOV,總表!$H$1,0))),"",VLOOKUP($B109,TOV,總表!$H$1,0)) -> 214414 | L109: =IF(OR($A$2=1,ISERROR(VLOOKUP($L108+1,TOV,2,0))),"",$L108+1) -> 56 | M109: =IF(OR($A$2=1,ISERROR(VLOOKUP($L109,TOV,2,0))),"",VLOOKUP($L109,TOV,2,0)) -> 70 | N109: =IF(OR($A$2=1,ISERROR(VLOOKUP($L109,TOV,總表!$AA$1,0))),"",VLOOKUP($L109,TOV,總表!$AA$1,0)) | P109: =IF(OR($A$2=1,ISERROR(VLOOKUP($L109,TOV,總表!$AB$1,0))),"",VLOOKUP($L109,TOV,總表!$AB$1,0)) -> 480240 | S109: =IF(OR($A$2=1,ISERROR(VLOOKUP($L109,TOV,總表!$H$1,0))),"",VLOOKUP($L109,TOV,總表!$H$1,0)) -> 494802
... B139: =IF(OR($A$2=1,ISERROR(VLOOKUP($B138+1,TOV,2,0))),"",$B138+1) -> 43 | C139: =IF(OR($A$2=1,ISERROR(VLOOKUP($B139,TOV,2,0))),"",VLOOKUP($B139,TOV,2,0)) -> 57 | D139: =IF(OR($A$2=1,ISERROR(VLOOKUP($B139,TOV,總表!$AA$1,0))),"",VLOOKUP($B139,TOV,總表!$AA$1,0)) | F139: =IF(OR($A$2=1,ISERROR(VLOOKUP($B139,TOV,總表!$AB$1,0))),"",VLOOKUP($B139,TOV,總表!$AB$1,0)) -> 480240 | I139: =IF(OR($A$2=1,ISERROR(VLOOKUP($B139,TOV,總表!$H$1,0))),"",VLOOKUP($B139,TOV,總表!$H$1,0)) -> 494802 | L139: =IF(OR($A$2=1,ISERROR(VLOOKUP($L138+1,TOV,2,0))),"",$L138+1) | M139: =IF(OR($A$2=1,ISERROR(VLOOKUP($L139,TOV,2,0))),"",VLOOKUP($L139,TOV,2,0)) | N139: =IF(OR($A$2=1,ISERROR(VLOOKUP($L139,TOV,總表!$AA$1,0))),"",VLOOKUP($L139,TOV,總表!$AA$1,0)) | P139: =IF(OR($A$2=1,ISERROR(VLOOKUP($L139,TOV,總表!$AB$1,0))),"",VLOOKUP($L139,TOV,總表!$AB$1,0)) | S139: =IF(OR($A$2=1,ISERROR(VLOOKUP($L139,TOV,總表!$H$1,0))),"",VLOOKUP($L139,TOV,總表!$H$1,0))
B140: ‧上表身故保障數值為假設於保險存續期間本保單皆無保險理賠，給付時需扣除被保險人已依保單條款約定所應申領之各
B141: 項保險金累計總額，實際保障數值依保單條款約定辦理。
B142: ‧上表身故保障數值為尚未扣除累計已領及應領而未領之各項保險金總額，如被保險人累計已領及應領而未領之各項保險
B143: 金總額已達年繳保險費總和的一點零二倍者，本公司不再給付身故保險金。
B144: ‧上表年度/累計實繳保費已扣除繳費方式折扣，繳費期內如不符繳費方式折扣條件，上表將不適用。
B145: ‧被保險人實際年齡滿十五足歲前死亡者，其身故保險金變更為喪葬費用保險金。喪葬費用保險金給付總和（包含但不限
B146: 本公司），不得超過投保時遺產及贈與稅法第十七條喪葬費扣除額之一半，超過部分本公司不負給付責任，並依保單條
B147: 款約定無息退還該超過部分之已繳保險費。但被保險人如有於民國99年2月3日之前投保者，其喪葬費用保險金之給付，
B148: 請詳保單條款之約定。有關喪葬費用保險金給付之詳細內容，亦請詳保單條款。
A150: 1 | B150: =OP!$D$107 -> 本建議書僅供參考，詳細商品內容及其變更，應以投保當時保單條款內容及本公司核保、保全作業規定為準
D151: =OP!$D$106 -> ※本契約條款樣張須於訂立契約前提供要保人至少三日審閱期間 | V151: =OP!$D$105 -> V1.0-1150720 試算日：1150825
V153: =IF(OP!$C$105="停售","本商品已停售","")
B154: 商品摘要
A155: 1 | B155: =OP!$C$23&"("&OP!$C$22&")" -> 富邦人壽連馨久久長期照顧終身健康保險(LTQ)
B156: 給付項目：老年住院醫療提前給付保險金、完全失能關懷保險金、完全失能生活扶助保險金、長期照顧一次保險金、
B157: 長期照顧分期保險金、身故保險金或喪葬費用保險金、祝壽保險金、豁免保險費
B158: 免付費申訴專線：0809-000-550
B159: ‧本保險因費率計算已考慮脫退率，故本保險無解約金。
A160: 2 | B160: ‧本商品之身故保險給付，有可能於特定條件下小於年繳保險費總和，請慎選符合需求之保險商品。
A161: 3 | B161: ‧本商品免責期間為九十日。
A162: 4 | B162: ‧免責期間：係指被保險人經專科醫師診斷確定為「長期照顧狀態」之日起算，且持續符合「長期照顧狀態」達九十日之
A163: 5 | B163: 期間。
A164: 6 | B164: ‧疾病：係指被保險人自本契約生效日或復效日（含）起所發生之疾病。
A165: 7 | B165: ‧「住院」：係指被保險人經醫師診斷其疾病或傷害必須入住醫院，且正式辦理住院手續並確實在醫院接受診療者。但
B166: 不包含全民健康保險法所稱之日間住院及精神衛生法所稱之日間留院/日間照護。保險公司辦理理賠作業於需要時會參
B167: 據醫學專業意見審核被保險人住院之必要性。
B168: ‧傷害：係指被保險人於本契約有效期間內，遭受意外傷害事故，因而蒙受之傷害。
...
