Workbook
Name CV: PDATA!$EI$252:$IP$518
Name DIE: PDATA!$V$522:$EC$798
Name En_BFM: OP!$W$4:$W$5
Name En_PayMF: OP!$U$3:$U$6
Name En_PayMR: OP!$V$3:$V$6
Name En_PayT: OP!$T$5:$T$8
Name En_Sex: OP!$S$3:$S$4
Name EXP: PDATA!$EI$522:$IP$798
Name GP: PDATA!$J:$K
Name HL_1: PDATA!$V$1134:$EC$1399
Name HL_2: PDATA!$EI$1134:$IP$1399
Name PA: PDATA!$V$2:$EC$248
Name PDN1_1: OP!$C$23
Name PDSN1: OP!$C$22
Name PDSN1_1: OP!$C$22
Name PI: OP!$AK$4:$AL$90
Name PV: PDATA!$EI$958:$IP$1120
Name PV0: PDATA!$V$958:$ED$1120
Name PVal: PDATA!$O:$P
Name PYO: PY!$D$4
Name PYR: PY!$C$11
Name PYY: PY!$C$4
Name SRV: PDATA!$EI$2:$IP$248
Name TOV: 總表!$B$3:$AI$114
Name 關係: OP!$B$182:$B$186

Sheet PDATA
A1: GP | B1: 1051130 | J1: =B1&TEXT(F1,"00")&TEXT(H1,"00") -> 10511300000 | O1: =M1&TEXT(N1,"00") -> 00 | R1: PA | V1: =S1&TEXT(T1,"00")&TEXT(U1,"00") -> 0000 | EE1: SRV | EI1: =EF1&TEXT(EG1,"00")&TEXT(EH1,"00") -> 0000
A2: 版次 | B2: 商品代號 | C2: 職業等級 | D2: 年期 | E2: 保額代碼 | F2: 性別 | G2: 投保金額 | H2: 年齡 | I2: 繳費年度 | J2: =B2&TEXT(F2,"00")&TEXT(H2,"00") -> 商品代號性別年齡 | K2: 保費 | M2: 商品代號 | N2: 累計給付年度 | O2: =M2&TEXT(N2,"00") -> 商品代號累計給付年度 | P2: 給付數值 | R2: 版次 | S2: 商品代號 | T2: 性別 | U2: 年齡 | V2: =S2&TEXT(T2,"00")&TEXT(U2,"00") -> 商品代號性別年齡 | W2: 第1年減額繳清保額 | X2: 第2年減額繳清保額 | Y2: 第3年減額繳清保額 | Z2: 第4年減額繳清保額 | AA2: 第5年減額繳清保額 | AB2: 第6年減額繳清保額 | AC2: 第7年減額繳清保額 | AD2: 第8年減額繳清保額 | AE2: 第9年減額繳清保額 | AF2: 第10年減額繳清保額 | AG2: 第11年減額繳清保額 | AH2: 第12年減額繳清保額 | AI2: 第13年減額繳清保額 | AJ2: 第14年減額繳清保額 | AK2: 第15年減額繳清保額 | AL2: 第16年減額繳清保額 | AM2: 第17年減額繳清保額 | AN2: 第18年減額繳清保額 | AO2: 第19年減額繳清保額B | AP2: 第20年減額繳清保額 | AQ2: 第21年減額繳清保額B | AR2: 第22年減額繳清保額 | AS2: 第23年減額繳清保額 | AT2: 第24年減額繳清保額 | AU2: 第25年減額繳清保額 | AV2: 第26年減額繳清保額B | AW2: 第27年減額繳清保額 | AX2: 第28年減額繳清保額B | AY2: 第29年減額繳清保額 | AZ2: 第30年減額繳清保額B | BA2: 第31年減額繳清保額 | BB2: 第32年減額繳清保額 | BC2: 第33年減額繳清保額 | BD2: 第34年減額繳清保額 | BE2: 第35年減額繳清保額 | BF2: 第36年減額繳清保額 | BG2: 第37年減額繳清保額 | BH2: 第38年減額繳清保額 | BI2: 第39年減額繳清保額 | BJ2: 第40年減額繳清保額 | BK2: 第41年減額繳清保額 | BL2: 第42年減額繳清保額 | BM2: 第43年減額繳清保額 | BN2: 第44年減額繳清保額 | BO2: 第45年減額繳清保額 | BP2: 第46年減額繳清保額 | BQ2: 第47年減額繳清保額 | BR2: 第48年減額繳清保額 | BS2: 第49年減額繳清保額 | BT2: 第50年減額繳清保額 | BU2: 第51年減額繳清保額 | BV2: 第52年減額繳清保額 | BW2: 第53年減額繳清保額 | BX2: 第54年減額繳清保額 | BY2: 第55年減額繳清保額 | BZ2: 第56年減額繳清保額 | CA2: 第57年減額繳清保額 | CB2: 第58年減額繳清保額 | CC2: 第59年減額繳清保額 | CD2: 第60年減額繳清保額 | CE2: 第61年減額繳清保額 | CF2: 第62年減額繳清保額 | CG2: 第63年減額繳清保額 | CH2: 第64年減額繳清保額 | CI2: 第65年減額繳清保額 | CJ2: 第66年減額繳清保額 | CK2: 第67年減額繳清保額 | CL2: 第68年減額繳清保額 | CM2: 第69年減額繳清保額 | CN2: 第70年減額繳清保額 | CO2: 第71年減額繳清保額 | CP2: 第72年減額繳清保額 | CQ2: 第73年減額繳清保額 | CR2: 第74年減額繳清保額 | CS2: 第75年減額繳清保額 | CT2: 第76年減額繳清保額 | CU2: 第77年減額繳清保額 | CV2: 第78年減額繳清保額 | CW2: 第79年減額繳清保額 | CX2: 第80年減額繳清保額 | CY2: 第81年減額繳清保額 | CZ2: 第82年契遾B繳清保額 | DA2: 第83年減額繳清保額 | DB2: 第84年減額繳清保額 | DC2: 第85年減額繳清保額 | DD2: 第86年減額繳清保額 | DE2: 第87年減額繳清保額 | DF2: 第88年減額繳清保額 | DG2: 第89年減額繳清保額 | DH2: 第90年減額繳清保額 | DI2: 第91年減額繳清保額 | DJ2: 第92年減額繳清保額 | DK2: 第93年減額繳清保額 | DL2: 第94年減額繳清保額 | DM2: 第95年減額繳清保額 | DN2: 第96年減額繳清保額 | DO2: 第97年減額繳清保額 | DP2: 第98年減額繳清保額 | DQ2: 第99年減額繳清保額 | DR2: 第100年減額繳清保額 | DS2: 第101年減額繳清保額 | DT2: 第102年減額繳清保額 | DU2: 第103年減額繳清保額 | DV2: 第104年減額繳清保額 | DW2: 第105年減額繳清保額 | DX2: 第106年減額繳清保額 | DY2: 第107年減額繳清保額 | DZ2: 第108年減額繳清保額 | EA2: 第109年減額繳清保額 | EB2: 第110年減額繳清保額 | EC2: 第111年減額繳清保額 | EE2: 版次 | EF2: 商品代號 | EG2: 性別 | EH2: 年齡
B3: LTT10 | F3: 1 | H3: 15 | J3: =B3&TEXT(F3,"00")&TEXT(H3,"00") -> LTT100115 | K3: 22030 | M3: LTT10 | N3: 1 | O3: =M3&TEXT(N3,"00") -> LTT1001 | P3: 20000
B4: LTT10 | F4: 1 | H4: 16 | J4: =B4&TEXT(F4,"00")&TEXT(H4,"00") -> LTT100116 | K4: 22330 | M4: LTT10 | N4: 2 | O4: =M4&TEXT(N4,"00") -> LTT1002 | P4: 20400
B5: LTT10 | F5: 1 | H5: 17 | J5: =B5&TEXT(F5,"00")&TEXT(H5,"00") -> LTT100117 | K5: 22690 | M5: LTT10 | N5: 3 | O5: =M5&TEXT(N5,"00") -> LTT1003 | P5: 20800
B6: LTT10 | F6: 1 | H6: 18 | J6: =B6&TEXT(F6,"00")&TEXT(H6,"00") -> LTT100118 | K6: 23030 | M6: LTT10 | N6: 4 | O6: =M6&TEXT(N6,"00") -> LTT1004 | P6: 21200
B7: LTT10 | F7: 1 | H7: 19 | J7: =B7&TEXT(F7,"00")&TEXT(H7,"00") -> LTT100119 | K7: 23410 | M7: LTT10 | N7: 5 | O7: =M7&TEXT(N7,"00") -> LTT1005 | P7: 21600
B8: LTT10 | F8: 1 | H8: 20 | J8: =B8&TEXT(F8,"00")&TEXT(H8,"00") -> LTT100120 | K8: 23800 | M8: LTT10 | N8: 6 | O8: =M8&TEXT(N8,"00") -> LTT1006 | P8: 22000
B9: LTT10 | F9: 1 | H9: 21 | J9: =B9&TEXT(F9,"00")&TEXT(H9,"00") -> LTT100121 | K9: 24160 | M9: LTT10 | N9: 7 | O9: =M9&TEXT(N9,"00") -> LTT1007 | P9: 22400
B10: LTT10 | F10: 1 | H10: 22 | J10: =B10&TEXT(F10,"00")&TEXT(H10,"00") -> LTT100122 | K10: 24560 | M10: LTT10 | N10: 8 | O10: =M10&TEXT(N10,"00") -> LTT1008 | P10: 22800
B11: LTT10 | F11: 1 | H11: 23 | J11: =B11&TEXT(F11,"00")&TEXT(H11,"00") -> LTT100123 | K11: 24940 | M11: LTT10 | N11: 9 | O11: =M11&TEXT(N11,"00") -> LTT1009 | P11: 23200
B12: LTT10 | F12: 1 | H12: 24 | J12: =B12&TEXT(F12,"00")&TEXT(H12,"00") -> LTT100124 | K12: 25320 | M12: LTT10 | N12: 10 | O12: =M12&TEXT(N12,"00") -> LTT1010 | P12: 23600
B13: LTT10 | F13: 1 | H13: 25 | J13: =B13&TEXT(F13,"00")&TEXT(H13,"00") -> LTT100125 | K13: 25750 | M13: LTT10 | N13: 11 | O13: =M13&TEXT(N13,"00") -> LTT1011 | P13: 24000
B14: LTT10 | F14: 1 | H14: 26 | J14: =B14&TEXT(F14,"00")&TEXT(H14,"00") -> LTT100126 | K14: 26150 | M14: LTT10 | N14: 12 | O14: =M14&TEXT(N14,"00") -> LTT1012 | P14: 24400
... B47: LTT10 | F47: 1 | H47: 59 | J47: =B47&TEXT(F47,"00")&TEXT(H47,"00") -> LTT100159 | K47: 48180 | M47: LTT30 | N47: 15 | O47: =M47&TEXT(N47,"00") -> LTT3015 | P47: 25600
B48: LTT10 | F48: 1 | H48: 60 | J48: =B48&TEXT(F48,"00")&TEXT(H48,"00") -> LTT100160 | K48: 49210
B49: LTT10 | F49: 1 | H49: 61 | J49: =B49&TEXT(F49,"00")&TEXT(H49,"00") -> LTT100161 | K49: 50250
B50: LTT10 | F50: 1 | H50: 62 | J50: =B50&TEXT(F50,"00")&TEXT(H50,"00") -> LTT100162 | K50: 51390
B51: LTT10 | F51: 1 | H51: 63 | J51: =B51&TEXT(F51,"00")&TEXT(H51,"00") -> LTT100163 | K51: 52640
B52: LTT10 | F52: 1 | H52: 64 | J52: =B52&TEXT(F52,"00")&TEXT(H52,"00") -> LTT100164 | K52: 53910
B53: LTT10 | F53: 1 | H53: 65 | J53: =B53&TEXT(F53,"00")&TEXT(H53,"00") -> LTT100165 | K53: 55220
B54: LTT10 | F54: 2 | H54: 15 | J54: =B54&TEXT(F54,"00")&TEXT(H54,"00") -> LTT100215 | K54: 30890
B55: LTT10 | F55: 2 | H55: 16 | J55: =B55&TEXT(F55,"00")&TEXT(H55,"00") -> LTT100216 | K55: 31430
B56: LTT10 | F56: 2 | H56: 17 | J56: =B56&TEXT(F56,"00")&TEXT(H56,"00") -> LTT100217 | K56: 31910
B57: LTT10 | F57: 2 | H57: 18 | J57: =B57&TEXT(F57,"00")&TEXT(H57,"00") -> LTT100218 | K57: 32430
B58: LTT10 | F58: 2 | H58: 19 | J58: =B58&TEXT(F58,"00")&TEXT(H58,"00") -> LTT100219 | K58: 32920
B59: LTT10 | F59: 2 | H59: 20 | J59: =B59&TEXT(F59,"00")&TEXT(H59,"00") -> LTT100220 | K59: 33420
... B248: LTT30 | F248: 2 | H248: 45 | J248: =B248&TEXT(F248,"00")&TEXT(H248,"00") -> LTT300245 | K248: 20610
R251: DIE2 | V251: =S251&TEXT(T251,"00")&TEXT(U251,"00") -> 0000 | EE251: CV | EI251: =EF251&TEXT(EG251,"00")&TEXT(EH251,"00") -> 0000
R252: 版次 | S252: 商品代號 | T252: 性別 | U252: 年齡 | EE252: 版次 | EF252: 商品代號 | EG252: 性別 | EH252: 年齡 | EI252: =EF252&TEXT(EG252,"00")&TEXT(EH252,"00") -> 商品代號性別年齡 | EJ252: 第1年解約金 | EK252: 第2年解約金 | EL252: 第3年解約金 | EM252: 第4年解約金 | EN252: 第5年解約金 | EO252: 第6年解約金 | EP252: 第7年解約金 | EQ252: 第8年解約金 | ER252: 第9年解約金 | ES252: 第10年解約金 | ET252: 第11年解約金 | EU252: 第12年解約金 | EV252: 第13年解約金 | EW252: 第14年解約金 | EX252: 第15年解約金 | EY252: 第16年解約金 | EZ252: 第17年解約金 | FA252: 第18年解約金 | FB252: 第19年解約金 | FC252: 第20年解約金 | FD252: 第21年解約金 | FE252: 第22年解約金 | FF252: 第23年解約金 | FG252: 第24年解約金 | FH252: 第25年解約金 | FI252: 第26年解約金 | FJ252: 第27年解約金 | FK252: 第28年解約金 | FL252: 第29年解約金 | FM252: 第30年解約金 | FN252: 第31年解約金 | FO252: 第32年解約金 | FP252: 第33年解約金 | FQ252: 第34年解約金 | FR252: 第35年解約金 | FS252: 第36年解約金 | FT252: 第37年解約金 | FU252: 第38年解約金 | FV252: 第39年解約金 | FW252: 第40年解約金 | FX252: 第41年解約金 | FY252: 第42年解約金 | FZ252: 第43年解約金 | GA252: 第44年解約金 | GB252: 第45年解約金 | GC252: 第46年解約金 | GD252: 第47年解約金 | GE252: 第48年解約金 | GF252: 第49年解約金 | GG252: 第50年解約金 | GH252: 第51年解約金 | GI252: 第52年解約金 | GJ252: 第53年解約金 | GK252: 第54年解約金 | GL252: 第55年解約金 | GM252: 第56年解約金 | GN252: 第57年解約金 | GO252: 第58年解約金 | GP252: 第59年解約金 | GQ252: 第60年解約金 | GR252: 第61年解約金 | GS252: 第62年解約金 | GT252: 第63年解約金 | GU252: 第64年解約金 | GV252: 第65年解約金 | GW252: 第66年解約金 | GX252: 第67年解約金 | GY252: 第68年解約金 | GZ252: 第69年解約金 | HA252: 第70年解約金 | HB252: 第71年解約金 | HC252: 第72年解約金 | HD252: 第73年解約金 | HE252: 第74年解約金 | HF252: 第75年解約金 | HG252: 第76年解約金 | HH252: 第77年解約金 | HI252: 第78年解約金 | HJ252: 第79年解約金 | HK252: 第80年解約金 | HL252: 第81年解約金 | HM252: 第82年解約金 | HN252: 第83年解約金 | HO252: 第84年解約金 | HP252: 第85年解約金 | HQ252: 第86年解約金 | HR252: 第87年解約金 | HS252: 第88年解約金 | HT252: 第89年解約金 | HU252: 第90年解約金 | HV252: 第91年解約金 | HW252: 第92年解約金 | HX252: 第93年解約金 | HY252: 第94年解約金 | HZ252: 第95年解約金 | IA252: 第96年解約金 | IB252: 第97年解約金 | IC252: 第98年解約金 | ID252: 第99年解約金 | IE252: 第100年解約金 | IF252: 第101年解約金 | IG252: 第102年解約金 | IH252: 第103年解約金 | II252: 第104年解約金 | IJ252: 第105年解約金 | IK252: 第106年解約金 | IL252: 第107年解約金 | IM252: 第108年解約金 | IN252: 第109年解約金 | IO252: 第110年解約金 | IP252: 第111年解約金
R521: DIE | V521: =S521&TEXT(T521,"00")&TEXT(U521,"00") -> 0000 | EE521: EXP | EI521: =EF521&TEXT(EG521,"00")&TEXT(EH521,"00") -> 0000
R522: 版次 | S522: 商品代號 | T522: 性別 | U522: 年齡 | V522: =S522&TEXT(T522,"00")&TEXT(U522,"00") -> 商品代號性別年齡 | W522: 第1年身故保險金 | X522: 第2年身故保險金 | Y522: 第3年身故保險金 | Z522: 第4年身故保險金 | AA522: 第5年身故保險金 | AB522: 第6年身故保險金 | AC522: 第7年身故保險金 | AD522: 第8年身故保險金 | AE522: 第9年身故保險金 | AF522: 第10年身故保險金 | AG522: 第11年身故保險金 | AH522: 第12年身故保險金 | AI522: 第13年身故保險金 | AJ522: 第14年身故保險金 | AK522: 第15年身故保險金 | AL522: 第16年身故保險金 | AM522: 第17年身故保險金 | AN522: 第18年身故保險金 | AO522: 第19年身故保險金 | AP522: 第20年身故保險金 | AQ522: 第21年身故保險金 | AR522: 第22年身故保險金 | AS522: 第23年身故保險金 | AT522: 第24年身故保險金 | AU522: 第25年身故保險金 | AV522: 第26年身故保險金 | AW522: 第27年身故保險金 | AX522: 第28年身故保險金 | AY522: 第29年身故保險金 | AZ522: 第30年身故保險金 | BA522: 第31年身故保險金 | BB522: 第32年身故保險金 | BC522: 第33年身故保險金 | BD522: 第34年身故保險金 | BE522: 第35年身故保險金 | BF522: 第36年身故保險金 | BG522: 第37年身故保險金 | BH522: 第38年身故保險金 | BI522: 第39年身故保險金 | BJ522: 第40年身故保險金 | BK522: 第41年身故保險金 | BL522: 第42年身故保險金 | BM522: 第43年身故保險金 | BN522: 第44年身故保險金 | BO522: 第45年身故保險金 | BP522: 第46年身故保險金 | BQ522: 第47年身故保險金 | BR522: 第48年身故保險金 | BS522: 第49年身故保險金 | BT522: 第50年身故保險金 | BU522: 第51年身故保險金 | BV522: 第52年身故保險金 | BW522: 第53年身故保險金 | BX522: 第54年身故保險金 | BY522: 第55年身故保險金 | BZ522: 第56年身故保險金 | CA522: 第57年身故保險金 | CB522: 第58年身故保險金 | CC522: 第59年身故保險金 | CD522: 第60年身故保險金 | CE522: 第61年身故保險金 | CF522: 第62年身故保險金 | CG522: 第63年身故保險金 | CH522: 第64年身故保險金 | CI522: 第65年身故保險金 | CJ522: 第66年身故保險金 | CK522: 第67年身故保險金 | CL522: 第68年身故保險金 | CM522: 第69年身故保險金 | CN522: 第70年身故保險金 | CO522: 第71年身故保險金 | CP522: 第72年身故保險金 | CQ522: 第73年身故保險金 | CR522: 第74年身故保險金額 | CS522: 第75年身故保險金 | CT522: 第76年身故保險金 | CU522: 第77年身故保險金 | CV522: 第78年身故保險金 | CW522: 第79年身故保險金 | CX522: 第80年身故保險金 | CY522: 第81年身故保險金 | CZ522: 第82年身故保險金 | DA522: 第83年身故保險金 | DB522: 第84年身故保險金 | DC522: 第85年身故保險金 | DD522: 第86年身故保險金 | DE522: 第87年身故保險金 | DF522: 第88年身故保險金 | DG522: 第89年身故保險金 | DH522: 第90年身故保險金 | DI522: 第91年身故保險金 | DJ522: 第92年身故保險金 | DK522: 第93年身故保險金 | DL522: 第94年身故保險金 | DM522: 第95年身故保險金 | DN522: 第96年身故保險金 | DO522: 第97年身故保險金 | DP522: 第98年身故保險金 | DQ522: 第99年身故保險金 | DR522: 第100年身故保險金 | DS522: 第101年身故保險金 | DT522: 第102年身故保險金 | DU522: 第103年身故保險金 | DV522: 第104年身故保險金 | DW522: 第105年身故保險金 | DX522: 第106年身故保險金 | DY522: 第107年身故保險金 | DZ522: 第108年身故保險金 | EA522: 第109年身故保險金 | EB522: 第110年身故保險金 | EC522: 第111年身故保險金 | EE522: 版次 | EF522: 商品代號 | EG522: 性別 | EH522: 年齡 | EI522: =EF522&TEXT(EG522,"00")&TEXT(EH522,"00") -> 商品代號性別年齡 | EJ522: 第1年祝壽保險金 | EK522: 第2年祝壽保險金 | EL522: 第3年祝壽保險金 | EM522: 第4年祝壽保險金 | EN522: 第5年祝壽保險金 | EO522: 第6年祝壽保險金 | EP522: 第7年祝壽保險金 | EQ522: 第8年祝壽保險金 | ER522: 第9年祝壽保險金 | ES522: 第10年祝壽保險金 | ET522: 第11年祝壽保險金 | EU522: 第12年祝壽保險金 | EV522: 第13年祝壽保險金 | EW522: 第14年祝壽保險金 | EX522: 第15年祝壽保險金 | EY522: 第16年祝壽保險金 | EZ522: 第17年祝壽保險金 | FA522: 第18年祝壽保險金 | FB522: 第19年祝壽保險金 | FC522: 第20年祝壽保險金 | FD522: 第21年祝壽保險金 | FE522: 第22年祝壽保險金 | FF522: 第23年祝壽保險金 | FG522: 第24年祝壽保險金 | FH522: 第25年祝壽保險金 | FI522: 第26年祝壽保險金 | FJ522: 第27年祝壽保險金 | FK522: 第28年祝壽保險金 | FL522: 第29年祝壽保險金 | FM522: 第30年祝壽保險金 | FN522: 第31年祝壽保險金 | FO522: 第32年祝壽保險金 | FP522: 第33年祝壽保險金 | FQ522: 第34年祝壽保險金 | FR522: 第35年祝壽保險金 | FS522: 第36年祝壽保險金 | FT522: 第37年祝壽保險金 | FU522: 第38年祝壽保險金 | FV522: 第39年祝壽保險金 | FW522: 第40年祝壽保險金 | FX522: 第41年祝壽保險金 | FY522: 第42年祝壽保險金 | FZ522: 第43年祝壽保險金 | GA522: 第44年祝壽保險金 | GB522: 第45年祝壽保險金 | GC522: 第46年祝壽保險金 | GD522: 第47年祝壽保險金 | GE522: 第48年祝壽保險金 | GF522: 第49年祝壽保險金 | GG522: 第50年祝壽保險金 | GH522: 第51年祝壽保險金 | GI522: 第52年祝壽保險金 | GJ522: 第53年祝壽保險金 | GK522: 第54年祝壽保險金 | GL522: 第55年祝壽保險金 | GM522: 第56年祝壽保險金 | GN522: 第57年祝壽保險金 | GO522: 第58年祝壽保險金 | GP522: 第59年祝壽保險金 | GQ522: 第60年祝壽保險金 | GR522: 第61年祝壽保險金 | GS522: 第62年祝壽保險金 | GT522: 第63年祝壽保險金 | GU522: 第64年祝壽保險金 | GV522: 第65年祝壽保險金 | GW522: 第66年祝壽保險金 | GX522: 第67年祝壽保險金 | GY522: 第68年祝壽保險金 | GZ522: 第69年祝壽保險金 | HA522: 第70年祝壽保險金 | HB522: 第71年祝壽保險金 | HC522: 第72年祝壽保險金 | HD522: 第73年祝壽保險金 | HE522: 第74年祝壽保險金 | HF522: 第75年祝壽保險金 | HG522: 第76年祝壽保險金 | HH522: 第77年祝壽保險金 | HI522: 第78年祝壽保險金 | HJ522: 第79年祝壽保險金 | HK522: 第80年祝壽保險金 | HL522: 第81年祝壽保險金 | HM522: 第82年祝壽保險金 | HN522: 第83年祝壽保險金 | HO522: 第84年祝壽保險金 | HP522: 第85年祝壽保險金 | HQ522: 第86年祝壽保險金 | HR522: 第87年祝壽保險金 | HS522: 第88年祝壽保險金 | HT522: 第89年祝壽保險金 | HU522: 第90年祝壽保險金 | HV522: 第91年祝壽保險金 | HW522: 第92年祝壽保險金 | HX522: 第93年祝壽保險金 | HY522: 第94年祝壽保險金 | HZ522: 第95年祝壽保險金 | IA522: 第96年祝壽保險金 | IB522: 第97年祝壽保險金 | IC522: 第98年祝壽保險金 | ID522: 第99年祝壽保險金 | IE522: 第100年祝壽保險金 | IF522: 第101年祝壽保險金 | IG522: 第102年祝壽保險金 | IH522: 第103年祝壽保險金 | II522: 第104年祝壽保險金 | IJ522: 第105年祝壽保險金 | IK522: 第106年祝壽保險金 | IL522: 第107年祝壽保險金 | IM522: 第108年祝壽保險金 | IN522: 第109年祝壽保險金 | IO522: 第110年祝壽保險金 | IP522: 第111年祝壽保險金
R801: PVFB | S801: 含 | T801: 1051130 | V801: =S801&TEXT(T801,"00")&TEXT(U801,"00") -> 含105113000 | EE801: PVFB0 | EF801: 領後 | EG801: 1051128 | EI801: =EF801&TEXT(EG801,"00")&TEXT(EH801,"00") -> 領後105112800
R802: 版次 | S802: 商品代號 | T802: 性別 | U802: 年齡 | EE802: 版次 | EF802: 商品代號 | EG802: 性別 | EH802: 年齡
R957: tbPV0(期初保價金)_領後(不含生存金) | V957: =S957&TEXT(T957,"00")&TEXT(U957,"00") -> 0000 | EE957: PV | EI957: =EF957&TEXT(EG957,"00")&TEXT(EH957,"00") -> 0000
EE958: 版次 | EF958: 商品代號 | EG958: 性別 | EH958: 年齡
R1132: tbHEALTH1 | V1132: =S1132&TEXT(T1132,"00")&TEXT(U1132,"00") -> 0000 | EE1132: tbHEALTH2 | EI1132: =EF1132&TEXT(EG1132,"00")&TEXT(EH1132,"00") -> 0000
R1133: 版次 | S1133: InsuranceReverseName | T1133: Gender | U1133: Age | V1133: =S1133&TEXT(T1133,"00")&TEXT(U1133,"00") -> InsuranceReverseNameGenderAge | W1133: HEALTH1 | X1133: HEALTH2 | Y1133: HEALTH3 | Z1133: HEALTH4 | AA1133: HEALTH5 | AB1133: HEALTH6 | AC1133: HEALTH7 | AD1133: HEALTH8 | AE1133: HEALTH9 | AF1133: HEALTH10 | AG1133: HEALTH11 | AH1133: HEALTH12 | AI1133: HEALTH13 | AJ1133: HEALTH14 | AK1133: HEALTH15 | AL1133: HEALTH16 | AM1133: HEALTH17 | AN1133: HEALTH18 | AO1133: HEALTH19 | AP1133: HEALTH20 | AQ1133: HEALTH21 | AR1133: HEALTH22 | AS1133: HEALTH23 | AT1133: HEALTH24 | AU1133: HEALTH25 | AV1133: HEALTH26 | AW1133: HEALTH27 | AX1133: HEALTH28 | AY1133: HEALTH29 | AZ1133: HEALTH30 | BA1133: HEALTH31 | BB1133: HEALTH32 | BC1133: HEALTH33 | BD1133: HEALTH34 | BE1133: HEALTH35 | BF1133: HEALTH36 | BG1133: HEALTH37 | BH1133: HEALTH38 | BI1133: HEALTH39 | BJ1133: HEALTH40 | BK1133: HEALTH41 | BL1133: HEALTH42 | BM1133: HEALTH43 | BN1133: HEALTH44 | BO1133: HEALTH45 | BP1133: HEALTH46 | BQ1133: HEALTH47 | BR1133: HEALTH48 | BS1133: HEALTH49 | BT1133: HEALTH50 | BU1133: HEALTH51 | BV1133: HEALTH52 | BW1133: HEALTH53 | BX1133: HEALTH54 | BY1133: HEALTH55 | BZ1133: HEALTH56 | CA1133: HEALTH57 | CB1133: HEALTH58 | CC1133: HEALTH59 | CD1133: HEALTH60 | CE1133: HEALTH61 | CF1133: HEALTH62 | CG1133: HEALTH63 | CH1133: HEALTH64 | CI1133: HEALTH65 | CJ1133: HEALTH66 | CK1133: HEALTH67 | CL1133: HEALTH68 | CM1133: HEALTH69 | CN1133: HEALTH70 | CO1133: HEALTH71 | CP1133: HEALTH72 | CQ1133: HEALTH73 | CR1133: HEALTH74 | CS1133: HEALTH75 | CT1133: HEALTH76 | CU1133: HEALTH77 | CV1133: HEALTH78 | CW1133: HEALTH79 | CX1133: HEALTH80 | CY1133: HEALTH81 | CZ1133: HEALTH82 | DA1133: HEALTH83 | DB1133: HEALTH84 | DC1133: HEALTH85 | DD1133: HEALTH86 | DE1133: HEALTH87 | DF1133: HEALTH88 | DG1133: HEALTH89 | DH1133: HEALTH90 | DI1133: HEALTH91 | DJ1133: HEALTH92 | DK1133: HEALTH93 | DL1133: HEALTH94 | DM1133: HEALTH95 | DN1133: HEALTH96 | DO1133: HEALTH97 | DP1133: HEALTH98 | DQ1133: HEALTH99 | DR1133: HEALTH100 | DS1133: HEALTH101 | DT1133: HEALTH102 | DU1133: HEALTH103 | DV1133: HEALTH104 | DW1133: HEALTH105 | DX1133: HEALTH106 | DY1133: HEALTH107 | DZ1133: HEALTH108 | EA1133: HEALTH109 | EB1133: HEALTH110 | EC1133: HEALTH111 | EE1133: 版次 | EF1133: InsuranceReverseName | EG1133: Gender | EH1133: Age | EI1133: =EF1133&TEXT(EG1133,"00")&TEXT(EH1133,"00") -> InsuranceReverseNameGenderAge | EJ1133: HEALTH1 | EK1133: HEALTH2 | EL1133: HEALTH3 | EM1133: HEALTH4 | EN1133: HEALTH5 | EO1133: HEALTH6 | EP1133: HEALTH7 | EQ1133: HEALTH8 | ER1133: HEALTH9 | ES1133: HEALTH10 | ET1133: HEALTH11 | EU1133: HEALTH12 | EV1133: HEALTH13 | EW1133: HEALTH14 | EX1133: HEALTH15 | EY1133: HEALTH16 | EZ1133: HEALTH17 | FA1133: HEALTH18 | FB1133: HEALTH19 | FC1133: HEALTH20 | FD1133: HEALTH21 | FE1133: HEALTH22 | FF1133: HEALTH23 | FG1133: HEALTH24 | FH1133: HEALTH25 | FI1133: HEALTH26 | FJ1133: HEALTH27 | FK1133: HEALTH28 | FL1133: HEALTH29 | FM1133: HEALTH30 | FN1133: HEALTH31 | FO1133: HEALTH32 | FP1133: HEALTH33 | FQ1133: HEALTH34 | FR1133: HEALTH35 | FS1133: HEALTH36 | FT1133: HEALTH37 | FU1133: HEALTH38 | FV1133: HEALTH39 | FW1133: HEALTH40 | FX1133: HEALTH41 | FY1133: HEALTH42 | FZ1133: HEALTH43 | GA1133: HEALTH44 | GB1133: HEALTH45 | GC1133: HEALTH46 | GD1133: HEALTH47 | GE1133: HEALTH48 | GF1133: HEALTH49 | GG1133: HEALTH50 | GH1133: HEALTH51 | GI1133: HEALTH52 | GJ1133: HEALTH53 | GK1133: HEALTH54 | GL1133: HEALTH55 | GM1133: HEALTH56 | GN1133: HEALTH57 | GO1133: HEALTH58 | GP1133: HEALTH59 | GQ1133: HEALTH60 | GR1133: HEALTH61 | GS1133: HEALTH62 | GT1133: HEALTH63 | GU1133: HEALTH64 | GV1133: HEALTH65 | GW1133: HEALTH66 | GX1133: HEALTH67 | GY1133: HEALTH68 | GZ1133: HEALTH69 | HA1133: HEALTH70 | HB1133: HEALTH71 | HC1133: HEALTH72 | HD1133: HEALTH73 | HE1133: HEALTH74 | HF1133: HEALTH75 | HG1133: HEALTH76 | HH1133: HEALTH77 | HI1133: HEALTH78 | HJ1133: HEALTH79 | HK1133: HEALTH80 | HL1133: HEALTH81 | HM1133: HEALTH82 | HN1133: HEALTH83 | HO1133: HEALTH84 | HP1133: HEALTH85 | HQ1133: HEALTH86 | HR1133: HEALTH87 | HS1133: HEALTH88 | HT1133: HEALTH89 | HU1133: HEALTH90 | HV1133: HEALTH91 | HW1133: HEALTH92 | HX1133: HEALTH93 | HY1133: HEALTH94 | HZ1133: HEALTH95 | IA1133: HEALTH96 | IB1133: HEALTH97 | IC1133: HEALTH98 | ID1133: HEALTH99 | IE1133: HEALTH100 | IF1133: HEALTH101 | IG1133: HEALTH102 | IH1133: HEALTH103 | II1133: HEALTH104 | IJ1133: HEALTH105 | IK1133: HEALTH106 | IL1133: HEALTH107 | IM1133: HEALTH108 | IN1133: HEALTH109 | IO1133: HEALTH110 | IP1133: HEALTH111

Sheet RDATA
A1: =OP!$C$22 -> LTT | B1: =IF($F$2>0,1,"") | G1: 1 | H1: =IF(H2<>A2&A1,"富邦人壽官網尚未公告"&A2&"宣告利率，目前使用"&LEFT($H$2,8)&"宣告利率，試算當月宣告利率以富邦人壽官網公告為準。","") -> 富邦人壽官網尚未公告115 / 8 宣告利率，目前使用宣告利率，試算當月宣告利率以富邦人壽官網公告為準。 | I1: =IF(H1="",1,"")
A2: =YEAR(TODAY())-1911&" / "&MONTH(TODAY())&" " -> 115 / 8 | D2: key | E2: 宣告利率 | F2: =SUM($F$3:$F$200) -> 0 | G2: 1 | I2: =IF(OP!$C$3<J2,K2,L2) -> 0.0175 | J2: 46023 | K2: 0.0175 | L2: 0.0175
B3: =IF(OR(D3="",D3=0,RIGHT(D3,LEN($A$1))<>$A$1),,(LEFT($D3,3)*100)+MID($D3,7,IF(OR(AND(LEN($A$1)=3,LEN($D3)=12),AND(LEN($A$1)=4,LEN($D3)=13)),2,1))*1) -> 0 | C3: =IF($B3=0,,RANK($B3,$B$3:$B$78)) -> 0 | F3: =IF(AND(RIGHT($D3,LEN($A$1))<>$A$1,$D3<>""),1,0) -> 0 | G3: 2 | H3: =IF(ISNA(VLOOKUP($G3,$C:$E,2,0)),"",VLOOKUP($G3,$C:$E,2,0)) | I3: =IF(ISNA(VLOOKUP($G3,$C:$E,3,0)),"",VLOOKUP($G3,$C:$E,3,0)) | J3: 45658 | K3: 0.0162 | L3: 0.0175
A4: =COUNTIF($D:$D,$A$3) -> 0 | B4: =IF(OR(D4="",D4=0,RIGHT(D4,LEN($A$1))<>$A$1),,(LEFT($D4,3)*100)+MID($D4,7,IF(OR(AND(LEN($A$1)=3,LEN($D4)=12),AND(LEN($A$1)=4,LEN($D4)=13)),2,1))*1) -> 0 | C4: =IF($B4=0,,RANK($B4,$B$3:$B$78)) -> 0 | F4: =IF(AND(RIGHT($D4,LEN($A$1))<>$A$1,$D4<>""),1,0) -> 0 | G4: 3 | H4: =IF(ISNA(VLOOKUP($G4,$C:$E,2,0)),"",VLOOKUP($G4,$C:$E,2,0)) | I4: =IF(ISNA(VLOOKUP($G4,$C:$E,3,0)),"",VLOOKUP($G4,$C:$E,3,0)) | J4: 45292 | K4: 0.015 | L4: 0.0162
B5: =IF(OR(D5="",D5=0,RIGHT(D5,LEN($A$1))<>$A$1),,(LEFT($D5,3)*100)+MID($D5,7,IF(OR(AND(LEN($A$1)=3,LEN($D5)=12),AND(LEN($A$1)=4,LEN($D5)=13)),2,1))*1) -> 0 | C5: =IF($B5=0,,RANK($B5,$B$3:$B$78)) -> 0 | F5: =IF(AND(RIGHT($D5,LEN($A$1))<>$A$1,$D5<>""),1,0) -> 0 | G5: 4 | H5: =IF(ISNA(VLOOKUP($G5,$C:$E,2,0)),"",VLOOKUP($G5,$C:$E,2,0)) | I5: =IF(ISNA(VLOOKUP($G5,$C:$E,3,0)),"",VLOOKUP($G5,$C:$E,3,0))
B6: =IF(OR(D6="",D6=0,RIGHT(D6,LEN($A$1))<>$A$1),,(LEFT($D6,3)*100)+MID($D6,7,IF(OR(AND(LEN($A$1)=3,LEN($D6)=12),AND(LEN($A$1)=4,LEN($D6)=13)),2,1))*1) -> 0 | C6: =IF($B6=0,,RANK($B6,$B$3:$B$78)) -> 0 | F6: =IF(AND(RIGHT($D6,LEN($A$1))<>$A$1,$D6<>""),1,0) -> 0 | G6: 5 | H6: =IF(ISNA(VLOOKUP($G6,$C:$E,2,0)),"",VLOOKUP($G6,$C:$E,2,0)) | I6: =IF(ISNA(VLOOKUP($G6,$C:$E,3,0)),"",VLOOKUP($G6,$C:$E,3,0))
B7: =IF(OR(D7="",D7=0,RIGHT(D7,LEN($A$1))<>$A$1),,(LEFT($D7,3)*100)+MID($D7,7,IF(OR(AND(LEN($A$1)=3,LEN($D7)=12),AND(LEN($A$1)=4,LEN($D7)=13)),2,1))*1) -> 0 | C7: =IF($B7=0,,RANK($B7,$B$3:$B$78)) -> 0 | F7: =IF(AND(RIGHT($D7,LEN($A$1))<>$A$1,$D7<>""),1,0) -> 0 | G7: 6 | H7: =IF(ISNA(VLOOKUP($G7,$C:$E,2,0)),"",VLOOKUP($G7,$C:$E,2,0)) | I7: =IF(ISNA(VLOOKUP($G7,$C:$E,3,0)),"",VLOOKUP($G7,$C:$E,3,0))
B8: =IF(OR(D8="",D8=0,RIGHT(D8,LEN($A$1))<>$A$1),,(LEFT($D8,3)*100)+MID($D8,7,IF(OR(AND(LEN($A$1)=3,LEN($D8)=12),AND(LEN($A$1)=4,LEN($D8)=13)),2,1))*1) -> 0 | C8: =IF($B8=0,,RANK($B8,$B$3:$B$78)) -> 0 | F8: =IF(AND(RIGHT($D8,LEN($A$1))<>$A$1,$D8<>""),1,0) -> 0 | G8: 7 | H8: =IF(ISNA(VLOOKUP($G8,$C:$E,2,0)),"",VLOOKUP($G8,$C:$E,2,0)) | I8: =IF(ISNA(VLOOKUP($G8,$C:$E,3,0)),"",VLOOKUP($G8,$C:$E,3,0))
B9: =IF(OR(D9="",D9=0,RIGHT(D9,LEN($A$1))<>$A$1),,(LEFT($D9,3)*100)+MID($D9,7,IF(OR(AND(LEN($A$1)=3,LEN($D9)=12),AND(LEN($A$1)=4,LEN($D9)=13)),2,1))*1) -> 0 | C9: =IF($B9=0,,RANK($B9,$B$3:$B$78)) -> 0 | F9: =IF(AND(RIGHT($D9,LEN($A$1))<>$A$1,$D9<>""),1,0) -> 0 | G9: 8 | H9: =IF(ISNA(VLOOKUP($G9,$C:$E,2,0)),"",VLOOKUP($G9,$C:$E,2,0)) | I9: =IF(ISNA(VLOOKUP($G9,$C:$E,3,0)),"",VLOOKUP($G9,$C:$E,3,0))
B10: =IF(OR(D10="",D10=0,RIGHT(D10,LEN($A$1))<>$A$1),,(LEFT($D10,3)*100)+MID($D10,7,IF(OR(AND(LEN($A$1)=3,LEN($D10)=12),AND(LEN($A$1)=4,LEN($D10)=13)),2,1))*1) -> 0 | C10: =IF($B10=0,,RANK($B10,$B$3:$B$78)) -> 0 | F10: =IF(AND(RIGHT($D10,LEN($A$1))<>$A$1,$D10<>""),1,0) -> 0 | G10: 9 | H10: =IF(ISNA(VLOOKUP($G10,$C:$E,2,0)),"",VLOOKUP($G10,$C:$E,2,0)) | I10: =IF(ISNA(VLOOKUP($G10,$C:$E,3,0)),"",VLOOKUP($G10,$C:$E,3,0))
B11: =IF(OR(D11="",D11=0,RIGHT(D11,LEN($A$1))<>$A$1),,(LEFT($D11,3)*100)+MID($D11,7,IF(OR(AND(LEN($A$1)=3,LEN($D11)=12),AND(LEN($A$1)=4,LEN($D11)=13)),2,1))*1) -> 0 | C11: =IF($B11=0,,RANK($B11,$B$3:$B$78)) -> 0 | F11: =IF(AND(RIGHT($D11,LEN($A$1))<>$A$1,$D11<>""),1,0) -> 0 | G11: 10 | H11: =IF(ISNA(VLOOKUP($G11,$C:$E,2,0)),"",VLOOKUP($G11,$C:$E,2,0)) | I11: =IF(ISNA(VLOOKUP($G11,$C:$E,3,0)),"",VLOOKUP($G11,$C:$E,3,0))
B12: =IF(OR(D12="",D12=0,RIGHT(D12,LEN($A$1))<>$A$1),,(LEFT($D12,3)*100)+MID($D12,7,IF(OR(AND(LEN($A$1)=3,LEN($D12)=12),AND(LEN($A$1)=4,LEN($D12)=13)),2,1))*1) -> 0 | C12: =IF($B12=0,,RANK($B12,$B$3:$B$78)) -> 0 | F12: =IF(AND(RIGHT($D12,LEN($A$1))<>$A$1,$D12<>""),1,0) -> 0 | G12: 11 | H12: =IF(ISNA(VLOOKUP($G12,$C:$E,2,0)),"",VLOOKUP($G12,$C:$E,2,0)) | I12: =IF(ISNA(VLOOKUP($G12,$C:$E,3,0)),"",VLOOKUP($G12,$C:$E,3,0))
B13: =IF(OR(D13="",D13=0,RIGHT(D13,LEN($A$1))<>$A$1),,(LEFT($D13,3)*100)+MID($D13,7,IF(OR(AND(LEN($A$1)=3,LEN($D13)=12),AND(LEN($A$1)=4,LEN($D13)=13)),2,1))*1) -> 0 | C13: =IF($B13=0,,RANK($B13,$B$3:$B$78)) -> 0 | F13: =IF(AND(RIGHT($D13,LEN($A$1))<>$A$1,$D13<>""),1,0) -> 0 | G13: 12 | H13: =IF(ISNA(VLOOKUP($G13,$C:$E,2,0)),"",VLOOKUP($G13,$C:$E,2,0)) | I13: =IF(ISNA(VLOOKUP($G13,$C:$E,3,0)),"",VLOOKUP($G13,$C:$E,3,0))
B14: =IF(OR(D14="",D14=0,RIGHT(D14,LEN($A$1))<>$A$1),,(LEFT($D14,3)*100)+MID($D14,7,IF(OR(AND(LEN($A$1)=3,LEN($D14)=12),AND(LEN($A$1)=4,LEN($D14)=13)),2,1))*1) -> 0 | C14: =IF($B14=0,,RANK($B14,$B$3:$B$78)) -> 0 | F14: =IF(AND(RIGHT($D14,LEN($A$1))<>$A$1,$D14<>""),1,0) -> 0 | G14: 13 | H14: =IF(ISNA(VLOOKUP($G14,$C:$E,2,0)),"",VLOOKUP($G14,$C:$E,2,0)) | I14: =IF(ISNA(VLOOKUP($G14,$C:$E,3,0)),"",VLOOKUP($G14,$C:$E,3,0))
B15: =IF(OR(D15="",D15=0,RIGHT(D15,LEN($A$1))<>$A$1),,(LEFT($D15,3)*100)+MID($D15,7,IF(OR(AND(LEN($A$1)=3,LEN($D15)=12),AND(LEN($A$1)=4,LEN($D15)=13)),2,1))*1) -> 0 | C15: =IF($B15=0,,RANK($B15,$B$3:$B$78)) -> 0 | F15: =IF(AND(RIGHT($D15,LEN($A$1))<>$A$1,$D15<>""),1,0) -> 0 | G15: 14 | H15: =IF(ISNA(VLOOKUP($G15,$C:$E,2,0)),"",VLOOKUP($G15,$C:$E,2,0)) | I15: =IF(ISNA(VLOOKUP($G15,$C:$E,3,0)),"",VLOOKUP($G15,$C:$E,3,0))
B16: =IF(OR(D16="",D16=0,RIGHT(D16,LEN($A$1))<>$A$1),,(LEFT($D16,3)*100)+MID($D16,7,IF(OR(AND(LEN($A$1)=3,LEN($D16)=12),AND(LEN($A$1)=4,LEN($D16)=13)),2,1))*1) -> 0 | C16: =IF($B16=0,,RANK($B16,$B$3:$B$78)) -> 0 | F16: =IF(AND(RIGHT($D16,LEN($A$1))<>$A$1,$D16<>""),1,0) -> 0 | G16: 15 | H16: =IF(ISNA(VLOOKUP($G16,$C:$E,2,0)),"",VLOOKUP($G16,$C:$E,2,0)) | I16: =IF(ISNA(VLOOKUP($G16,$C:$E,3,0)),"",VLOOKUP($G16,$C:$E,3,0))
... B25: =IF(OR(D25="",D25=0,RIGHT(D25,LEN($A$1))<>$A$1),,(LEFT($D25,3)*100)+MID($D25,7,IF(OR(AND(LEN($A$1)=3,LEN($D25)=12),AND(LEN($A$1)=4,LEN($D25)=13)),2,1))*1) -> 0 | C25: =IF($B25=0,,RANK($B25,$B$3:$B$78)) -> 0 | F25: =IF(AND(RIGHT($D25,LEN($A$1))<>$A$1,$D25<>""),1,0) -> 0 | G25: 24 | H25: =IF(ISNA(VLOOKUP($G25,$C:$E,2,0)),"",VLOOKUP($G25,$C:$E,2,0)) | I25: =IF(ISNA(VLOOKUP($G25,$C:$E,3,0)),"",VLOOKUP($G25,$C:$E,3,0))
B26: =IF(OR(D26="",D26=0,RIGHT(D26,LEN($A$1))<>$A$1),,(LEFT($D26,3)*100)+MID($D26,7,IF(OR(AND(LEN($A$1)=3,LEN($D26)=12),AND(LEN($A$1)=4,LEN($D26)=13)),2,1))*1) -> 0 | C26: =IF($B26=0,,RANK($B26,$B$3:$B$78)) -> 0 | F26: =IF(AND(RIGHT($D26,LEN($A$1))<>$A$1,$D26<>""),1,0) -> 0
B27: =IF(OR(D27="",D27=0,RIGHT(D27,LEN($A$1))<>$A$1),,(LEFT($D27,3)*100)+MID($D27,7,IF(OR(AND(LEN($A$1)=3,LEN($D27)=12),AND(LEN($A$1)=4,LEN($D27)=13)),2,1))*1) -> 0 | C27: =IF($B27=0,,RANK($B27,$B$3:$B$78)) -> 0 | F27: =IF(AND(RIGHT($D27,LEN($A$1))<>$A$1,$D27<>""),1,0) -> 0 | H27: MAX | I27: =MAX(I2:I26) -> 0.0175
B28: =IF(OR(D28="",D28=0,RIGHT(D28,LEN($A$1))<>$A$1),,(LEFT($D28,3)*100)+MID($D28,7,IF(OR(AND(LEN($A$1)=3,LEN($D28)=12),AND(LEN($A$1)=4,LEN($D28)=13)),2,1))*1) -> 0 | C28: =IF($B28=0,,RANK($B28,$B$3:$B$78)) -> 0 | F28: =IF(AND(RIGHT($D28,LEN($A$1))<>$A$1,$D28<>""),1,0) -> 0
B29: =IF(OR(D29="",D29=0,RIGHT(D29,LEN($A$1))<>$A$1),,(LEFT($D29,3)*100)+MID($D29,7,IF(OR(AND(LEN($A$1)=3,LEN($D29)=12),AND(LEN($A$1)=4,LEN($D29)=13)),2,1))*1) -> 0 | C29: =IF($B29=0,,RANK($B29,$B$3:$B$78)) -> 0 | F29: =IF(AND(RIGHT($D29,LEN($A$1))<>$A$1,$D29<>""),1,0) -> 0
B30: =IF(OR(D30="",D30=0,RIGHT(D30,LEN($A$1))<>$A$1),,(LEFT($D30,3)*100)+MID($D30,7,IF(OR(AND(LEN($A$1)=3,LEN($D30)=12),AND(LEN($A$1)=4,LEN($D30)=13)),2,1))*1) -> 0 | C30: =IF($B30=0,,RANK($B30,$B$3:$B$78)) -> 0 | F30: =IF(AND(RIGHT($D30,LEN($A$1))<>$A$1,$D30<>""),1,0) -> 0
B31: =IF(OR(D31="",D31=0,RIGHT(D31,LEN($A$1))<>$A$1),,(LEFT($D31,3)*100)+MID($D31,7,IF(OR(AND(LEN($A$1)=3,LEN($D31)=12),AND(LEN($A$1)=4,LEN($D31)=13)),2,1))*1) -> 0 | C31: =IF($B31=0,,RANK($B31,$B$3:$B$78)) -> 0 | F31: =IF(AND(RIGHT($D31,LEN($A$1))<>$A$1,$D31<>""),1,0) -> 0
B32: =IF(OR(D32="",D32=0,RIGHT(D32,LEN($A$1))<>$A$1),,(LEFT($D32,3)*100)+MID($D32,7,IF(OR(AND(LEN($A$1)=3,LEN($D32)=12),AND(LEN($A$1)=4,LEN($D32)=13)),2,1))*1) -> 0 | C32: =IF($B32=0,,RANK($B32,$B$3:$B$78)) -> 0 | F32: =IF(AND(RIGHT($D32,LEN($A$1))<>$A$1,$D32<>""),1,0) -> 0
B33: =IF(OR(D33="",D33=0,RIGHT(D33,LEN($A$1))<>$A$1),,(LEFT($D33,3)*100)+MID($D33,7,IF(OR(AND(LEN($A$1)=3,LEN($D33)=12),AND(LEN($A$1)=4,LEN($D33)=13)),2,1))*1) -> 0 | C33: =IF($B33=0,,RANK($B33,$B$3:$B$78)) -> 0 | F33: =IF(AND(RIGHT($D33,LEN($A$1))<>$A$1,$D33<>""),1,0) -> 0
B34: =IF(OR(D34="",D34=0,RIGHT(D34,LEN($A$1))<>$A$1),,(LEFT($D34,3)*100)+MID($D34,7,IF(OR(AND(LEN($A$1)=3,LEN($D34)=12),AND(LEN($A$1)=4,LEN($D34)=13)),2,1))*1) -> 0 | C34: =IF($B34=0,,RANK($B34,$B$3:$B$78)) -> 0 | F34: =IF(AND(RIGHT($D34,LEN($A$1))<>$A$1,$D34<>""),1,0) -> 0
B35: =IF(OR(D35="",D35=0,RIGHT(D35,LEN($A$1))<>$A$1),,(LEFT($D35,3)*100)+MID($D35,7,IF(OR(AND(LEN($A$1)=3,LEN($D35)=12),AND(LEN($A$1)=4,LEN($D35)=13)),2,1))*1) -> 0 | C35: =IF($B35=0,,RANK($B35,$B$3:$B$78)) -> 0 | F35: =IF(AND(RIGHT($D35,LEN($A$1))<>$A$1,$D35<>""),1,0) -> 0
B36: =IF(OR(D36="",D36=0,RIGHT(D36,LEN($A$1))<>$A$1),,(LEFT($D36,3)*100)+MID($D36,7,IF(OR(AND(LEN($A$1)=3,LEN($D36)=12),AND(LEN($A$1)=4,LEN($D36)=13)),2,1))*1) -> 0 | C36: =IF($B36=0,,RANK($B36,$B$3:$B$78)) -> 0 | F36: =IF(AND(RIGHT($D36,LEN($A$1))<>$A$1,$D36<>""),1,0) -> 0
B37: =IF(OR(D37="",D37=0,RIGHT(D37,LEN($A$1))<>$A$1),,(LEFT($D37,3)*100)+MID($D37,7,IF(OR(AND(LEN($A$1)=3,LEN($D37)=12),AND(LEN($A$1)=4,LEN($D37)=13)),2,1))*1) -> 0 | C37: =IF($B37=0,,RANK($B37,$B$3:$B$78)) -> 0 | F37: =IF(AND(RIGHT($D37,LEN($A$1))<>$A$1,$D37<>""),1,0) -> 0
B38: =IF(OR(D38="",D38=0,RIGHT(D38,LEN($A$1))<>$A$1),,(LEFT($D38,3)*100)+MID($D38,7,IF(OR(AND(LEN($A$1)=3,LEN($D38)=12),AND(LEN($A$1)=4,LEN($D38)=13)),2,1))*1) -> 0 | C38: =IF($B38=0,,RANK($B38,$B$3:$B$78)) -> 0 | F38: =IF(AND(RIGHT($D38,LEN($A$1))<>$A$1,$D38<>""),1,0) -> 0
B39: =IF(OR(D39="",D39=0,RIGHT(D39,LEN($A$1))<>$A$1),,(LEFT($D39,3)*100)+MID($D39,7,IF(OR(AND(LEN($A$1)=3,LEN($D39)=12),AND(LEN($A$1)=4,LEN($D39)=13)),2,1))*1) -> 0 | C39: =IF($B39=0,,RANK($B39,$B$3:$B$78)) -> 0 | F39: =IF(AND(RIGHT($D39,LEN($A$1))<>$A$1,$D39<>""),1,0) -> 0
... B200: =IF(OR(D200="",D200=0,RIGHT(D200,LEN($A$1))<>$A$1),,(LEFT($D200,3)*100)+MID($D200,7,IF(OR(AND(LEN($A$1)=3,LEN($D200)=12),AND(LEN($A$1)=4,LEN($D200)=13)),2,1))*1) -> 0 | C200: =IF($B200=0,,RANK($B200,$B$3:$B$78)) -> 0 | F200: =IF(AND(RIGHT($D200,LEN($A$1))<>$A$1,$D200<>""),1,0) -> 0

Sheet PY
B2: 轉換金額 | C2: 10000
C3: 分期 | D3: ㄧ次
B4: 指定保險金比例： | C4: =MIN(1,ROUND(OP!$C$141,2)) -> 0 | D4: =1-C4 -> 1 | F4: 年 | G4: 1
B5: 分期最低金額 | C5: =$C$38 -> 20000 | D5: =$D$38 -> 200000 | F5: 半年 | G5: 2
B6: 分期定期保險金給付期間： | C6: =OP!$C$142 -> 10 | F6: 季 | G6: 4
B7: 假設分期定期保險金預定利率： | C7: =$B$30 -> 0.02 | F7: 月 | G7: 12
B8: 期別 | C8: 年 | D8: =VLOOKUP($C$8,$F$4:$G$7,2,0) -> 1
B10: 精算公式→ | C10: =IF(C6=0,,C2*(C7*(1/(1+C7)))/(1-(1/(1+C7))^C6)) -> 1091.4365 | D10: ←精算換算比例(每萬元)
C11: =C10/10000 -> 0.10914365 | D11: ←帶入換算比例(每元)
B15: 定期定額-本利攤還
B16: 給付金額/每期 | C16: =ROUND(PMT($C$7/$D$8,$C$6*$D$8,-$C$2*$C$4,,1),0) -> 0
B17: 給付總額 | C17: =C16*C6*D8 -> 0
B18: 給付比例 | C18: =PMT($C$7/$D$8,$C$6*$D$8,-$C$2,,1)/C2 -> 0.10914365 | D18: ←自行計算換算比例
B20: 定額不定期
B21: 給付金額/每期 | C21: 550 | D21: ←帶入期付金額
B22: 給付總額 | C22: =C21*(($C$26*$D$8)+$C$27) -> 12100
B23: 給付比例 | C23: =$C$21/($C$2/$C$4) -> #DIV/0!
B24: 給付次數 | C24: =NPER($C$7/$D$8,$C$21,-$C$2,0,1) -> 22.261841
B25: 剩餘金額 | C25: =ROUND(C21*($C$24-ROUNDDOWN($C$24,0)),0) -> 144
B26: 給付年次 | C26: =ROUNDDOWN(ROUNDDOWN($C$24,0)/$D$8,0) -> 22 | D26: ←自行計算給付年月數
B27: ="給付"&C8&"次" -> 給付年次 | C27: =ROUNDDOWN($C$24,0)-($C$26*$D$8) -> 0 | D27: ="EX："&$C$26&" 年 "&IF($C$27=0,"",C27&" "&$C$8) -> EX：22 年
B29: 台幣=1，美元=2，澳幣=3 | C29: =OP!$C$21 -> 1 | D29: 新臺幣 | E29: ←設定幣別
B30: =IF($C$29=1,$C$31,IF($C$29=2,$D$31,$E$31)) -> 0.02 | C30: 台幣(1) | D30: 美元(2) | E30: 澳幣(3)
C31: 0.02 | D31: 0.025 | E31: 0.0275
B37: 分期低額 | C37: 每期 | D37: 指定
B38: =$C$29 -> 1 | C38: =VLOOKUP(B38,$B$39:$D$40,2,0) -> 20000 | D38: =VLOOKUP(B38,$B$39:$D$40,3,0) -> 200000
B39: 2 | C39: 3000 | D39: 30000 | E39: =NUMBERSTRING(IF(C39/10000<1,C39/1000,C39/10000),3)&RIGHT(NUMBERSTRING(C39,1),1) -> 三千 | F39: =NUMBERSTRING(IF(D39/10000<1,D39/1000,D39/10000),1)&RIGHT(NUMBERSTRING(D39,2),1) -> 三萬
B40: 1 | C40: 20000 | D40: 200000 | E40: =NUMBERSTRING(IF(C40/10000<1,C40/1000,C40/10000),3)&RIGHT(NUMBERSTRING(C40,2),1) -> 二萬 | F40: =NUMBERSTRING(IF(D40/10000<1,D40/1000,D40/10000),1)&RIGHT(NUMBERSTRING(D40,2),1) -> 二十萬
B41: 3 | C41: 3000 | D41: 30000 | E41: =NUMBERSTRING(IF(C41/10000<1,C41/1000,C41/10000),3)&RIGHT(NUMBERSTRING(C41,1),1) -> 三千 | F41: =NUMBERSTRING(IF(D41/10000<1,D41/1000,D41/10000),1)&RIGHT(NUMBERSTRING(D41,2),1) -> 三萬
B42: 4 | E42: =NUMBERSTRING(IF(C42/10000<1,C42/1000,C42/10000),3)&RIGHT(NUMBERSTRING(C42,2),1) -> ○零 | F42: =NUMBERSTRING(IF(D42/10000<1,D42/1000,D42/10000),1)&RIGHT(NUMBERSTRING(D42,2),1) -> ○零
B43: =IF(OR(AND($D$29=$B$45,$C$29<>1),ISERROR(VLOOKUP($D$29,$B$45:$D$48,3,0))),"商品幣別設定錯誤",VLOOKUP($D$29,$B$45:$D$48,3,0)) -> 二十萬元或每年給付之分期定期保險金低於二萬元者， | C43: =IF(OR(AND($D$29=$B$45,$C$29<>1),ISERROR(VLOOKUP($D$29,$B$45:$D$48,3,0))),1,0) -> 0
B45: 新臺幣 | C45: 1 | D45: =VLOOKUP($C$45,$B$39:$F$42,5,0)&"元"&"或每年給付之分期定期保險金低於"&VLOOKUP($C$45,$B$39:$F$42,4,0)&"元"&"者，" -> 二十萬元或每年給付之分期定期保險金低於二萬元者，
B46: 美元 | C46: 2 | D46: =VLOOKUP($C$46,$B$39:$F$42,5,0)&$B$46&"或每年給付之分期定期保險金低於"&VLOOKUP($C$46,$B$39:$F$42,4,0)&$B$46&"者，" -> 三萬美元或每年給付之分期定期保險金低於三千美元者，
B47: 澳幣 | C47: 3 | D47: =VLOOKUP($C$47,$B$39:$F$42,5,0)&$B$47&"或每年給付之分期定期保險金低於"&VLOOKUP($C$47,$B$39:$F$42,4,0)&$B$47&"者，" -> 三萬澳幣或每年給付之分期定期保險金低於三千澳幣者，
B48: 人民幣 | C48: 4 | D48: =VLOOKUP($C$48,$B$39:$F$42,5,0)&$B$48&"或每年給付之分期定期保險金低於"&VLOOKUP($C$48,$B$39:$F$42,4,0)&$B$48&"者，" -> ○零人民幣或每年給付之分期定期保險金低於○零人民幣者，

Sheet 揭露
B1: =OP!$C$56 -> LTT30 | C1: ←帶OP | D1: =IF(OP!$E$16=1,"足歲",IF(OP!$E$16=2,"保險年齡","錯誤")) -> 保險年齡 | E1: ←帶OP | Q1: 6 | R1: 7 | S1: 8 | T1: 9 | U1: 10 | V1: 11 | W1: 12
L2: 以下3欄要注意最下方要和右側揭露拉齊 | O2: 以下COPY-DB | Q2: 1120911
C3: 代表年齡第?小→ | D3: 1 | E3: 2 | F3: 3 | G3: 1 | H3: 2 | I3: 3 | K3: 年齡代號轉換 | L3: KEY | M3: 年齡 | N3: 年度 | O3: 險種大類 | P3: 年期險種 | Q3: 性別 | R3: 年齡 | S3: 繳費方式 | T3: 宣告利率 | U3: 繳費金額 | V3: 保單年度 | W3: 揭露利率
C4: 性別男=1，女=2→ | D4: 1 | E4: 1 | F4: 1 | G4: 2 | H4: 2 | I4: 2 | K4: =IF($D$1="足歲","15足","") | L4: =IF(P4<>$B$1,"",P4&Q4&R4&V4) | M4: =IF(L4="","-",IF(ISERROR($R4*1),LEFT($R4,2)*1,$R4*1)) -> - | N4: =IF(L4="","",V4*1)
B5: 取第?欄→ | C5: 12 | D5: =IF(SMALL($M:$M,D$3)=15,$K$4,SMALL($M:$M,D$3)) -> #NUM! | E5: =IF(SMALL($M:$M,E$3)=15,$K$4,SMALL($M:$M,E$3)) -> #NUM! | F5: =IF(SMALL($M:$M,F$3)=15,$K$4,SMALL($M:$M,F$3)) -> #NUM! | G5: =IF(SMALL($M:$M,G$3)=15,$K$4,SMALL($M:$M,G$3)) -> #NUM! | H5: =IF(SMALL($M:$M,H$3)=15,$K$4,SMALL($M:$M,H$3)) -> #NUM! | I5: =IF(SMALL($M:$M,I$3)=15,$K$4,SMALL($M:$M,I$3)) -> #NUM! | L5: =IF(P5<>$B$1,"",P5&Q5&R5&V5) | M5: =IF(OR(L5="",COUNTIF($M$4:M4,IF(ISERROR($R5*1),LEFT($R5,2)*1,$R5*1))>=1),"-",IF(ISERROR($R5*1),LEFT($R5,2)*1,$R5*1)) -> - | N5: =IF(OR(L5="",COUNTIF($N$4:N4,V5*1)>=1),"-",V5*1) -> -
B6: 第?小↓ | C6: 保單年度 | D6: =IF(OR(ISERROR($D5)),"",IF((D$5)=0,D$5&IF(D$4=1,"男性",IF(D$4=2,"女性","")),D$5&"歲"&IF(D$4=1,"男性",IF(D$4=2,"女性","")))) | E6: =IF(OR(ISERROR($D5)),"",IF((E$5)=0,E$5&IF(E$4=1,"男性",IF(E$4=2,"女性","")),E$5&"歲"&IF(E$4=1,"男性",IF(E$4=2,"女性","")))) | F6: =IF(OR(ISERROR($D5)),"",IF((F$5)=0,F$5&IF(F$4=1,"男性",IF(F$4=2,"女性","")),F$5&"歲"&IF(F$4=1,"男性",IF(F$4=2,"女性","")))) | G6: =IF(OR(ISERROR($D5)),"",IF((G$5)=0,G$5&IF(G$4=1,"男性",IF(G$4=2,"女性","")),G$5&"歲"&IF(G$4=1,"男性",IF(G$4=2,"女性","")))) | H6: =IF(OR(ISERROR($D5)),"",IF((H$5)=0,H$5&IF(H$4=1,"男性",IF(H$4=2,"女性","")),H$5&"歲"&IF(H$4=1,"男性",IF(H$4=2,"女性","")))) | I6: =IF(OR(ISERROR($D5)),"",IF((I$5)=0,I$5&IF(I$4=1,"男性",IF(I$4=2,"女性","")),I$5&"歲"&IF(I$4=1,"男性",IF(I$4=2,"女性","")))) | L6: =IF(P6<>$B$1,"",P6&Q6&R6&V6) | M6: =IF(OR(L6="",COUNTIF($M$4:M5,IF(ISERROR($R6*1),LEFT($R6,2)*1,$R6*1))>=1),"-",IF(ISERROR($R6*1),LEFT($R6,2)*1,$R6*1)) -> - | N6: =IF(OR(L6="",COUNTIF($N$4:N5,V6*1)>=1),"-",V6*1) -> -
B7: 1 | C7: =IF(ISERROR(SMALL($N:$N,$B7)),"",SMALL($N:$N,$B7)) | D7: =IF(ISERROR(VLOOKUP($B$1&D$4&D$5&$C7,$L:$W,$C$5,0)),"",VLOOKUP($B$1&D$4&D$5&$C7,$L:$W,$C$5,0)) | E7: =IF(ISERROR(VLOOKUP($B$1&E$4&E$5&$C7,$L:$W,$C$5,0)),"",VLOOKUP($B$1&E$4&E$5&$C7,$L:$W,$C$5,0)) | F7: =IF(ISERROR(VLOOKUP($B$1&F$4&F$5&$C7,$L:$W,$C$5,0)),"",VLOOKUP($B$1&F$4&F$5&$C7,$L:$W,$C$5,0)) | G7: =IF(ISERROR(VLOOKUP($B$1&G$4&G$5&$C7,$L:$W,$C$5,0)),"",VLOOKUP($B$1&G$4&G$5&$C7,$L:$W,$C$5,0)) | H7: =IF(ISERROR(VLOOKUP($B$1&H$4&H$5&$C7,$L:$W,$C$5,0)),"",VLOOKUP($B$1&H$4&H$5&$C7,$L:$W,$C$5,0)) | I7: =IF(ISERROR(VLOOKUP($B$1&I$4&I$5&$C7,$L:$W,$C$5,0)),"",VLOOKUP($B$1&I$4&I$5&$C7,$L:$W,$C$5,0)) | L7: =IF(P7<>$B$1,"",P7&Q7&R7&V7) | M7: =IF(OR(L7="",COUNTIF($M$4:M6,IF(ISERROR($R7*1),LEFT($R7,2)*1,$R7*1))>=1),"-",IF(ISERROR($R7*1),LEFT($R7,2)*1,$R7*1)) -> - | N7: =IF(OR(L7="",COUNTIF($N$4:N6,V7*1)>=1),"-",V7*1) -> -
B8: 2 | C8: =IF(ISERROR(SMALL($N:$N,$B8)),"",SMALL($N:$N,$B8)) | D8: =IF(ISERROR(VLOOKUP($B$1&D$4&D$5&$C8,$L:$W,$C$5,0)),"",VLOOKUP($B$1&D$4&D$5&$C8,$L:$W,$C$5,0)) | E8: =IF(ISERROR(VLOOKUP($B$1&E$4&E$5&$C8,$L:$W,$C$5,0)),"",VLOOKUP($B$1&E$4&E$5&$C8,$L:$W,$C$5,0)) | F8: =IF(ISERROR(VLOOKUP($B$1&F$4&F$5&$C8,$L:$W,$C$5,0)),"",VLOOKUP($B$1&F$4&F$5&$C8,$L:$W,$C$5,0)) | G8: =IF(ISERROR(VLOOKUP($B$1&G$4&G$5&$C8,$L:$W,$C$5,0)),"",VLOOKUP($B$1&G$4&G$5&$C8,$L:$W,$C$5,0)) | H8: =IF(ISERROR(VLOOKUP($B$1&H$4&H$5&$C8,$L:$W,$C$5,0)),"",VLOOKUP($B$1&H$4&H$5&$C8,$L:$W,$C$5,0)) | I8: =IF(ISERROR(VLOOKUP($B$1&I$4&I$5&$C8,$L:$W,$C$5,0)),"",VLOOKUP($B$1&I$4&I$5&$C8,$L:$W,$C$5,0)) | L8: =IF(P8<>$B$1,"",P8&Q8&R8&V8) | M8: =IF(OR(L8="",COUNTIF($M$4:M7,IF(ISERROR($R8*1),LEFT($R8,2)*1,$R8*1))>=1),"-",IF(ISERROR($R8*1),LEFT($R8,2)*1,$R8*1)) -> - | N8: =IF(OR(L8="",COUNTIF($N$4:N7,V8*1)>=1),"-",V8*1) -> -
B9: 3 | C9: =IF(ISERROR(SMALL($N:$N,$B9)),"",SMALL($N:$N,$B9)) | D9: =IF(ISERROR(VLOOKUP($B$1&D$4&D$5&$C9,$L:$W,$C$5,0)),"",VLOOKUP($B$1&D$4&D$5&$C9,$L:$W,$C$5,0)) | E9: =IF(ISERROR(VLOOKUP($B$1&E$4&E$5&$C9,$L:$W,$C$5,0)),"",VLOOKUP($B$1&E$4&E$5&$C9,$L:$W,$C$5,0)) | F9: =IF(ISERROR(VLOOKUP($B$1&F$4&F$5&$C9,$L:$W,$C$5,0)),"",VLOOKUP($B$1&F$4&F$5&$C9,$L:$W,$C$5,0)) | G9: =IF(ISERROR(VLOOKUP($B$1&G$4&G$5&$C9,$L:$W,$C$5,0)),"",VLOOKUP($B$1&G$4&G$5&$C9,$L:$W,$C$5,0)) | H9: =IF(ISERROR(VLOOKUP($B$1&H$4&H$5&$C9,$L:$W,$C$5,0)),"",VLOOKUP($B$1&H$4&H$5&$C9,$L:$W,$C$5,0)) | I9: =IF(ISERROR(VLOOKUP($B$1&I$4&I$5&$C9,$L:$W,$C$5,0)),"",VLOOKUP($B$1&I$4&I$5&$C9,$L:$W,$C$5,0)) | L9: =IF(P9<>$B$1,"",P9&Q9&R9&V9) | M9: =IF(OR(L9="",COUNTIF($M$4:M8,IF(ISERROR($R9*1),LEFT($R9,2)*1,$R9*1))>=1),"-",IF(ISERROR($R9*1),LEFT($R9,2)*1,$R9*1)) -> - | N9: =IF(OR(L9="",COUNTIF($N$4:N8,V9*1)>=1),"-",V9*1) -> -
B10: 4 | C10: =IF(ISERROR(SMALL($N:$N,$B10)),"",SMALL($N:$N,$B10)) | D10: =IF(ISERROR(VLOOKUP($B$1&D$4&D$5&$C10,$L:$W,$C$5,0)),"",VLOOKUP($B$1&D$4&D$5&$C10,$L:$W,$C$5,0)) | E10: =IF(ISERROR(VLOOKUP($B$1&E$4&E$5&$C10,$L:$W,$C$5,0)),"",VLOOKUP($B$1&E$4&E$5&$C10,$L:$W,$C$5,0)) | F10: =IF(ISERROR(VLOOKUP($B$1&F$4&F$5&$C10,$L:$W,$C$5,0)),"",VLOOKUP($B$1&F$4&F$5&$C10,$L:$W,$C$5,0)) | G10: =IF(ISERROR(VLOOKUP($B$1&G$4&G$5&$C10,$L:$W,$C$5,0)),"",VLOOKUP($B$1&G$4&G$5&$C10,$L:$W,$C$5,0)) | H10: =IF(ISERROR(VLOOKUP($B$1&H$4&H$5&$C10,$L:$W,$C$5,0)),"",VLOOKUP($B$1&H$4&H$5&$C10,$L:$W,$C$5,0)) | I10: =IF(ISERROR(VLOOKUP($B$1&I$4&I$5&$C10,$L:$W,$C$5,0)),"",VLOOKUP($B$1&I$4&I$5&$C10,$L:$W,$C$5,0)) | L10: =IF(P10<>$B$1,"",P10&Q10&R10&V10) | M10: =IF(OR(L10="",COUNTIF($M$4:M9,IF(ISERROR($R10*1),LEFT($R10,2)*1,$R10*1))>=1),"-",IF(ISERROR($R10*1),LEFT($R10,2)*1,$R10*1)) -> - | N10: =IF(OR(L10="",COUNTIF($N$4:N9,V10*1)>=1),"-",V10*1) -> -
B11: 5 | C11: =IF(ISERROR(SMALL($N:$N,$B11)),"",SMALL($N:$N,$B11)) | D11: =IF(ISERROR(VLOOKUP($B$1&D$4&D$5&$C11,$L:$W,$C$5,0)),"",VLOOKUP($B$1&D$4&D$5&$C11,$L:$W,$C$5,0)) | E11: =IF(ISERROR(VLOOKUP($B$1&E$4&E$5&$C11,$L:$W,$C$5,0)),"",VLOOKUP($B$1&E$4&E$5&$C11,$L:$W,$C$5,0)) | F11: =IF(ISERROR(VLOOKUP($B$1&F$4&F$5&$C11,$L:$W,$C$5,0)),"",VLOOKUP($B$1&F$4&F$5&$C11,$L:$W,$C$5,0)) | G11: =IF(ISERROR(VLOOKUP($B$1&G$4&G$5&$C11,$L:$W,$C$5,0)),"",VLOOKUP($B$1&G$4&G$5&$C11,$L:$W,$C$5,0)) | H11: =IF(ISERROR(VLOOKUP($B$1&H$4&H$5&$C11,$L:$W,$C$5,0)),"",VLOOKUP($B$1&H$4&H$5&$C11,$L:$W,$C$5,0)) | I11: =IF(ISERROR(VLOOKUP($B$1&I$4&I$5&$C11,$L:$W,$C$5,0)),"",VLOOKUP($B$1&I$4&I$5&$C11,$L:$W,$C$5,0)) | L11: =IF(P11<>$B$1,"",P11&Q11&R11&V11) | M11: =IF(OR(L11="",COUNTIF($M$4:M10,IF(ISERROR($R11*1),LEFT($R11,2)*1,$R11*1))>=1),"-",IF(ISERROR($R11*1),LEFT($R11,2)*1,$R11*1)) -> - | N11: =IF(OR(L11="",COUNTIF($N$4:N10,V11*1)>=1),"-",V11*1) -> -
B12: 6 | C12: =IF(ISERROR(SMALL($N:$N,$B12)),"",SMALL($N:$N,$B12)) | D12: =IF(ISERROR(VLOOKUP($B$1&D$4&D$5&$C12,$L:$W,$C$5,0)),"",VLOOKUP($B$1&D$4&D$5&$C12,$L:$W,$C$5,0)) | E12: =IF(ISERROR(VLOOKUP($B$1&E$4&E$5&$C12,$L:$W,$C$5,0)),"",VLOOKUP($B$1&E$4&E$5&$C12,$L:$W,$C$5,0)) | F12: =IF(ISERROR(VLOOKUP($B$1&F$4&F$5&$C12,$L:$W,$C$5,0)),"",VLOOKUP($B$1&F$4&F$5&$C12,$L:$W,$C$5,0)) | G12: =IF(ISERROR(VLOOKUP($B$1&G$4&G$5&$C12,$L:$W,$C$5,0)),"",VLOOKUP($B$1&G$4&G$5&$C12,$L:$W,$C$5,0)) | H12: =IF(ISERROR(VLOOKUP($B$1&H$4&H$5&$C12,$L:$W,$C$5,0)),"",VLOOKUP($B$1&H$4&H$5&$C12,$L:$W,$C$5,0)) | I12: =IF(ISERROR(VLOOKUP($B$1&I$4&I$5&$C12,$L:$W,$C$5,0)),"",VLOOKUP($B$1&I$4&I$5&$C12,$L:$W,$C$5,0)) | L12: =IF(P12<>$B$1,"",P12&Q12&R12&V12) | M12: =IF(OR(L12="",COUNTIF($M$4:M11,IF(ISERROR($R12*1),LEFT($R12,2)*1,$R12*1))>=1),"-",IF(ISERROR($R12*1),LEFT($R12,2)*1,$R12*1)) -> - | N12: =IF(OR(L12="",COUNTIF($N$4:N11,V12*1)>=1),"-",V12*1) -> -
B13: 7 | C13: =IF(ISERROR(SMALL($N:$N,$B13)),"",SMALL($N:$N,$B13)) | D13: =IF(ISERROR(VLOOKUP($B$1&D$4&D$5&$C13,$L:$W,$C$5,0)),"",VLOOKUP($B$1&D$4&D$5&$C13,$L:$W,$C$5,0)) | E13: =IF(ISERROR(VLOOKUP($B$1&E$4&E$5&$C13,$L:$W,$C$5,0)),"",VLOOKUP($B$1&E$4&E$5&$C13,$L:$W,$C$5,0)) | F13: =IF(ISERROR(VLOOKUP($B$1&F$4&F$5&$C13,$L:$W,$C$5,0)),"",VLOOKUP($B$1&F$4&F$5&$C13,$L:$W,$C$5,0)) | G13: =IF(ISERROR(VLOOKUP($B$1&G$4&G$5&$C13,$L:$W,$C$5,0)),"",VLOOKUP($B$1&G$4&G$5&$C13,$L:$W,$C$5,0)) | H13: =IF(ISERROR(VLOOKUP($B$1&H$4&H$5&$C13,$L:$W,$C$5,0)),"",VLOOKUP($B$1&H$4&H$5&$C13,$L:$W,$C$5,0)) | I13: =IF(ISERROR(VLOOKUP($B$1&I$4&I$5&$C13,$L:$W,$C$5,0)),"",VLOOKUP($B$1&I$4&I$5&$C13,$L:$W,$C$5,0)) | L13: =IF(P13<>$B$1,"",P13&Q13&R13&V13) | M13: =IF(OR(L13="",COUNTIF($M$4:M12,IF(ISERROR($R13*1),LEFT($R13,2)*1,$R13*1))>=1),"-",IF(ISERROR($R13*1),LEFT($R13,2)*1,$R13*1)) -> - | N13: =IF(OR(L13="",COUNTIF($N$4:N12,V13*1)>=1),"-",V13*1) -> -
B14: 8 | C14: =IF(ISERROR(SMALL($N:$N,$B14)),"",SMALL($N:$N,$B14)) | D14: =IF(ISERROR(VLOOKUP($B$1&D$4&D$5&$C14,$L:$W,$C$5,0)),"",VLOOKUP($B$1&D$4&D$5&$C14,$L:$W,$C$5,0)) | E14: =IF(ISERROR(VLOOKUP($B$1&E$4&E$5&$C14,$L:$W,$C$5,0)),"",VLOOKUP($B$1&E$4&E$5&$C14,$L:$W,$C$5,0)) | F14: =IF(ISERROR(VLOOKUP($B$1&F$4&F$5&$C14,$L:$W,$C$5,0)),"",VLOOKUP($B$1&F$4&F$5&$C14,$L:$W,$C$5,0)) | G14: =IF(ISERROR(VLOOKUP($B$1&G$4&G$5&$C14,$L:$W,$C$5,0)),"",VLOOKUP($B$1&G$4&G$5&$C14,$L:$W,$C$5,0)) | H14: =IF(ISERROR(VLOOKUP($B$1&H$4&H$5&$C14,$L:$W,$C$5,0)),"",VLOOKUP($B$1&H$4&H$5&$C14,$L:$W,$C$5,0)) | I14: =IF(ISERROR(VLOOKUP($B$1&I$4&I$5&$C14,$L:$W,$C$5,0)),"",VLOOKUP($B$1&I$4&I$5&$C14,$L:$W,$C$5,0)) | L14: =IF(P14<>$B$1,"",P14&Q14&R14&V14) | M14: =IF(OR(L14="",COUNTIF($M$4:M13,IF(ISERROR($R14*1),LEFT($R14,2)*1,$R14*1))>=1),"-",IF(ISERROR($R14*1),LEFT($R14,2)*1,$R14*1)) -> - | N14: =IF(OR(L14="",COUNTIF($N$4:N13,V14*1)>=1),"-",V14*1) -> -
C15: 以上區域為帶入列印頁範圍 | L15: =IF(P15<>$B$1,"",P15&Q15&R15&V15) | M15: =IF(OR(L15="",COUNTIF($M$4:M14,IF(ISERROR($R15*1),LEFT($R15,2)*1,$R15*1))>=1),"-",IF(ISERROR($R15*1),LEFT($R15,2)*1,$R15*1)) -> - | N15: =IF(OR(L15="",COUNTIF($N$4:N14,V15*1)>=1),"-",V15*1) -> -
L16: =IF(P16<>$B$1,"",P16&Q16&R16&V16) | M16: =IF(OR(L16="",COUNTIF($M$4:M15,IF(ISERROR($R16*1),LEFT($R16,2)*1,$R16*1))>=1),"-",IF(ISERROR($R16*1),LEFT($R16,2)*1,$R16*1)) -> - | N16: =IF(OR(L16="",COUNTIF($N$4:N15,V16*1)>=1),"-",V16*1) -> -
L17: =IF(P17<>$B$1,"",P17&Q17&R17&V17) | M17: =IF(OR(L17="",COUNTIF($M$4:M16,IF(ISERROR($R17*1),LEFT($R17,2)*1,$R17*1))>=1),"-",IF(ISERROR($R17*1),LEFT($R17,2)*1,$R17*1)) -> - | N17: =IF(OR(L17="",COUNTIF($N$4:N16,V17*1)>=1),"-",V17*1) -> -
L18: =IF(P18<>$B$1,"",P18&Q18&R18&V18) | M18: =IF(OR(L18="",COUNTIF($M$4:M17,IF(ISERROR($R18*1),LEFT($R18,2)*1,$R18*1))>=1),"-",IF(ISERROR($R18*1),LEFT($R18,2)*1,$R18*1)) -> - | N18: =IF(OR(L18="",COUNTIF($N$4:N17,V18*1)>=1),"-",V18*1) -> -
L19: =IF(P19<>$B$1,"",P19&Q19&R19&V19) | M19: =IF(OR(L19="",COUNTIF($M$4:M18,IF(ISERROR($R19*1),LEFT($R19,2)*1,$R19*1))>=1),"-",IF(ISERROR($R19*1),LEFT($R19,2)*1,$R19*1)) -> - | N19: =IF(OR(L19="",COUNTIF($N$4:N18,V19*1)>=1),"-",V19*1) -> -
L20: =IF(P20<>$B$1,"",P20&Q20&R20&V20) | M20: =IF(OR(L20="",COUNTIF($M$4:M19,IF(ISERROR($R20*1),LEFT($R20,2)*1,$R20*1))>=1),"-",IF(ISERROR($R20*1),LEFT($R20,2)*1,$R20*1)) -> - | N20: =IF(OR(L20="",COUNTIF($N$4:N19,V20*1)>=1),"-",V20*1) -> -
L21: =IF(P21<>$B$1,"",P21&Q21&R21&V21) | M21: =IF(OR(L21="",COUNTIF($M$4:M20,IF(ISERROR($R21*1),LEFT($R21,2)*1,$R21*1))>=1),"-",IF(ISERROR($R21*1),LEFT($R21,2)*1,$R21*1)) -> - | N21: =IF(OR(L21="",COUNTIF($N$4:N20,V21*1)>=1),"-",V21*1) -> -
L22: =IF(P22<>$B$1,"",P22&Q22&R22&V22) | M22: =IF(OR(L22="",COUNTIF($M$4:M21,IF(ISERROR($R22*1),LEFT($R22,2)*1,$R22*1))>=1),"-",IF(ISERROR($R22*1),LEFT($R22,2)*1,$R22*1)) -> - | N22: =IF(OR(L22="",COUNTIF($N$4:N21,V22*1)>=1),"-",V22*1) -> -
L23: =IF(P23<>$B$1,"",P23&Q23&R23&V23) | M23: =IF(OR(L23="",COUNTIF($M$4:M22,IF(ISERROR($R23*1),LEFT($R23,2)*1,$R23*1))>=1),"-",IF(ISERROR($R23*1),LEFT($R23,2)*1,$R23*1)) -> - | N23: =IF(OR(L23="",COUNTIF($N$4:N22,V23*1)>=1),"-",V23*1) -> -
L24: =IF(P24<>$B$1,"",P24&Q24&R24&V24) | M24: =IF(OR(L24="",COUNTIF($M$4:M23,IF(ISERROR($R24*1),LEFT($R24,2)*1,$R24*1))>=1),"-",IF(ISERROR($R24*1),LEFT($R24,2)*1,$R24*1)) -> - | N24: =IF(OR(L24="",COUNTIF($N$4:N23,V24*1)>=1),"-",V24*1) -> -
L25: =IF(P25<>$B$1,"",P25&Q25&R25&V25) | M25: =IF(OR(L25="",COUNTIF($M$4:M24,IF(ISERROR($R25*1),LEFT($R25,2)*1,$R25*1))>=1),"-",IF(ISERROR($R25*1),LEFT($R25,2)*1,$R25*1)) -> - | N25: =IF(OR(L25="",COUNTIF($N$4:N24,V25*1)>=1),"-",V25*1) -> -
L26: =IF(P26<>$B$1,"",P26&Q26&R26&V26) | M26: =IF(OR(L26="",COUNTIF($M$4:M25,IF(ISERROR($R26*1),LEFT($R26,2)*1,$R26*1))>=1),"-",IF(ISERROR($R26*1),LEFT($R26,2)*1,$R26*1)) -> - | N26: =IF(OR(L26="",COUNTIF($N$4:N25,V26*1)>=1),"-",V26*1) -> -
L27: =IF(P27<>$B$1,"",P27&Q27&R27&V27) | M27: =IF(OR(L27="",COUNTIF($M$4:M26,IF(ISERROR($R27*1),LEFT($R27,2)*1,$R27*1))>=1),"-",IF(ISERROR($R27*1),LEFT($R27,2)*1,$R27*1)) -> - | N27: =IF(OR(L27="",COUNTIF($N$4:N26,V27*1)>=1),"-",V27*1) -> -
... L147: =IF(P147<>$B$1,"",P147&Q147&R147&V147) | M147: =IF(OR(L147="",COUNTIF($M$4:M146,IF(ISERROR($R147*1),LEFT($R147,2)*1,$R147*1))>=1),"-",IF(ISERROR($R147*1),LEFT($R147,2)*1,$R147*1)) -> - | N147: =IF(OR(L147="",COUNTIF($N$4:N146,V147*1)>=1),"-",V147*1) -> -

Sheet input_s
A1: 回傳資訊
A2: 保費：首期 | B2: =IF($H$8=0,"",IF(ISERROR(OP!$D$53),"資料錯誤_首期保費",OP!$C$48))
A3: 保費：續期 | B3: =IF($H$8=0,"",IF(ISERROR(OP!$D$53),"資料錯誤_續期保費",IF(OP!$C$24=1,0,OP!$C$49)))
A4: 錯誤訊息： | B4: =IF($H$8=0,"",IF(ISERROR(OP!$D$53),"資料錯誤",I15&J15&I16&J16&I17&J17&I19&J19&I20&J20&I21&J21&I22&J22&I24&J24&I26&J26&I27&J27&I32&J32&I34&J34&I35&J35&I40&J40&I45&J45&I53&J53&I59&J59&I61&J61&I62&J62&I63&J63&I64&J64&I71&J71&I79&J79&I81&J81&I82&J82&I84&J84&I86&J86&I92&J92&I93&J93&I94&J94&I95&J95&I106&J106))
A5: 原始保費： | B5: =IF($H$8=0,"",IF(ISERROR(OP!$D$53),"資料錯誤_原始保費",OP!$C$35)) | C5: 1090428新增 | H5: 目前未使用，預留
A6: 保險年齡： | B6: =IF($H$8=0,"",IF(ISERROR(OP!$D$53),"資料錯誤_保險年齡",OP!$D$5)) | C6: 1090428新增 | H6: EXCEL使用
H7: 是否使用：1=系統帶入,0=輸入頁帶入 | I7: 利變：1、分紅：2、其他：3
H8: 0 | I8: 3
A9: 欄位名 | B9: 中文名 | C9: 說明 | D9: 是否必填 | E9: 試算表使用欄位 | H9: excel套用欄位內容 | I9: 錯誤訊息 | J9: 間隔 | L9: 性別
A10: ProposalRequest | L10: 1 | M10: 男
A11: TrnNum | B11: 交易序號 | C11: 系統代號+yyyymmddhhMMssmis(建議保險公司可以接收該欄位並記錄於log中, 到時候追查資料時比較方便) | D11: V | E11: X | J11: =IF(I11="","",IF(COUNTA(I12:$I$138)>0,"|","")) | L11: 2 | M11: 女
A12: data_type | B12: 資料類別 | C12: 1.產生建議書 | D12: V | J12: =IF(I12="","",IF(COUNTA(I13:$I$138)>0,"|",""))
C13: 2.要保書檢核 | J13: =IF(I13="","",IF(COUNTA(I14:$I$138)>0,"|",""))
A14: insco_no | B14: 保險公司代碼 | C14: 018安聯 | D14: V | E14: X | J14: =IF(I14="","",IF(COUNTA(I15:$I$138)>0,"|",""))
A15: proposal_seq | B15: 建議書序號 | C15: data_type為2(要保書檢核)時不傳 | E15: 中信規則 | H15: =IF($H$8=1,$G15,"") | I15: =IF(G15="","","") | J15: =IF(I15="","",IF(COUNTA(I16:$I$138)>0,"|","")) | L15: 被保人身分別 | N15: 1090721-建議書序號不需檢核 | O15: =IF(G15="","無傳入建議書序號","") -> 無傳入建議書序號
A16: owner_name | B16: 要保人姓名 | D16: V | F16: 目前無要保人欄位，預留 | H16: =IF($H$8=1,$G16,"") | J16: =IF(I16="","",IF(COUNTA(I17:$I$138)>0,"|","")) | L16: 1 | M16: 一般
A17: owner_sex | B17: 要保人性別 | C17: 1男 | D17: V | H17: =IF($H$8=1,IF(ISERROR(VLOOKUP($G17,$L$10:$M$13,2,0)),"",VLOOKUP($G17,$L$10:$M$13,2,0)),"") | J17: =IF(I17="","",IF(COUNTA(I18:$I$138)>0,"|","")) | L17: 2 | M17: 學生
C18: 2女 | J18: =IF(I18="","",IF(COUNTA(I19:$I$138)>0,"|","")) | L18: 3 | M18: 家管
A19: owner_birth | B19: 要保人出生年月日 | C19: yyyymmdd | D19: V | H19: =IF($H$8=1,IF(OR($G$19="",LEN($G$19)<>8),"",LEFT($G$19,4)-1911&TEXT(MID($G$19,5,2),"00")&TEXT(RIGHT($G$19,2),"00")),輸入頁!$E$14) -> 0 | J19: =IF(I19="","",IF(COUNTA(I20:$I$138)>0,"|","")) | L19: 4 | M19: 退休人士
A20: is_owner | B20: 要被保人同一人 | C20: Y/N | D20: V | H20: =IF($H$8=1,$G20,"") | J20: =IF(I20="","",IF(COUNTA(I21:$I$138)>0,"|",""))
A21: insure_name | B21: 被保人姓名 | D21: V | H21: =IF($H$8=1,IF($G$21="","",$G21),輸入頁!$E$5) -> 客戶 | I21: =IF($H$21="",$I$10&"被保險人姓名未填寫","") | J21: =IF(I21="","",IF(COUNTA(I22:$I$138)>0,"|",""))
A22: insure_sex | B22: 被保險人性別 | C22: 1男 | D22: V | H22: =IF($H$8=1,IF(ISERROR(VLOOKUP($G22,$L$10:$M$13,2,0)),"",VLOOKUP($G22,$L$10:$M$13,2,0)),輸入頁!$K$5) -> 女 | I22: =IF(OR($H$22="",OP!$D$18=1),$I$10&"被保險人性別錯誤","") | J22: =IF(I22="","",IF(COUNTA(I23:$I$138)>0,"|",""))
C23: 2女 | J23: =IF(I23="","",IF(COUNTA(I24:$I$138)>0,"|","")) | L23: 繳別
A24: insure_birthday | B24: 被保險人出生年月日 | C24: yyyymmdd | D24: V | H24: =IF($H$8=1,IF(OR($G$24="",LEN($G$24)<>8),"",LEFT($G$24,4)-1911&TEXT(MID($G$24,5,2),"00")&TEXT(RIGHT($G$24,2),"00")),輸入頁!$N$5) -> 1010101 | I24: =IF(H24="",$I$10&"被保險人生日錯誤",IF(OP!$E$6=1,"生日日期錯誤",""))&IF(OR(OP!$D$15=1,OP!$D$16=1),"＊年齡不符專案投保區間，請先確認年齡後 重新試算，其他欄位檢核訊息請先忽略＊","") | J24: =IF(I24="","",IF(COUNTA(I25:$I$138)>0,"|","")) | K24: 1150126調整 | L24: 01 | M24: 月繳
J25: =IF(I25="","",IF(COUNTA(I26:$I$138)>0,"|","")) | L25: 03 | M25: 季繳
A26: insure_prof_kind | B26: 被保險人職業等級 | C26: 1~6 | D26: V | F26: 與被保人兼業等級取大 | H26: =IF($H$8=1,MAX($G26,$G32),"") | J26: =IF(I26="","",IF(COUNTA(I27:$I$138)>0,"|","")) | L26: 06 | M26: 半年繳
A27: insure_prof_type | B27: 被保險人職業身分別 | C27: 1.一般 | F27: 試算表無身分判別，預留 | H27: =IF($H$8=1,IF(ISERROR(VLOOKUP($G27,$L$16:$M$21,2,0)),"",VLOOKUP($G27,$L$16:$M$21,2,0)),"") | J27: =IF(I27="","",IF(COUNTA(I28:$I$138)>0,"|","")) | L27: 12 | M27: 年繳
C28: 2.學生 | J28: =IF(I28="","",IF(COUNTA(I29:$I$138)>0,"|","")) | L28: P | M28: 躉繳
C29: 3.家管 | J29: =IF(I29="","",IF(COUNTA(I30:$I$138)>0,"|",""))
C30: 4.退休人士 | J30: =IF(I30="","",IF(COUNTA(I31:$I$138)>0,"|",""))
A31: insure_job_code | B31: 被保險人職業代碼 | E31: X | J31: =IF(I31="","",IF(COUNTA(I32:$I$138)>0,"|","")) | L31: 繳費方式 | M31: 首期 | N31: 續期 | O31: 中信
A32: insure_part_time_prof_kind | B32: 被保險人兼職職業等級 | C32: 1~6 | D32: V | H32: 於H26取大 | J32: =IF(I32="","",IF(COUNTA(I33:$I$138)>0,"|","")) | L32: 1 | M32: =IF(OP!$C$21=1,"匯款","外幣匯款") -> 匯款 | N32: - | O32: 1.帳戶圈存(匯款)
A33: insure_part_time_job_code | B33: 被保險人兼職職業代碼 | E33: X | J33: =IF(I33="","",IF(COUNTA(I34:$I$138)>0,"|","")) | L33: 2 | M33: =IF(OP!$C$21=1,"匯款","外幣匯款") -> 匯款 | N33: - | O33: 2.現金圈存(匯款)
A34: plan_code | B34: 險種代號 | D34: V | H34: =IF($H$8=1,UPPER($G34),輸入頁!$E$39) -> LTT | I34: =IF(ISERROR(VLOOKUP($H$34,OP!$H$43:$H$62,1,0)),$I$10&"險種錯誤","") | J34: =IF(I34="","",IF(COUNTA(I35:$I$138)>0,"|","")) | L34: 3 | M34: 一般信用卡 | N34: 一般信用卡 | O34: 3.信用卡
A35: paid_period_year | B35: 繳費年期 | D35: V | H35: =IF($H$8=1,$G35,輸入頁!$E$37) -> 30 | I35: =IF(COUNTIF(OP!$J$43:$J$62,$H$35&$H$34)<>1,$I$10&"年期錯誤","") | J35: =IF(I35="","",IF(COUNTA(I36:$I$138)>0,"|","")) | L35: 4 | M35: 金融機構轉帳 | N35: 金融機構轉帳 | O35: 4.本行自扣(轉帳)
A36: coverage_type | B36: 保障類別單位 | C36: 1.保額 2單位 3計畫 | D36: V | E36: X | F36: 試算表無須判別 | J36: =IF(I36="","",IF(COUNTA(I37:$I$138)>0,"|","")) | L36: 5 | M36: =IF(OP!$C$21=1,"匯款","外幣匯款") -> 匯款 | N36: 自行繳費 | O36: 5.臨櫃轉帳(匯款)
A37: cuy_cpo | B37: 保額幣別 | C37: 台幣為TWD | D37: V | E37: X | F37: 試算表無須判別 | J37: =IF(I37="","",IF(COUNTA(I38:$I$138)>0,"|","")) | L37: 6 | M37: =IF(OP!$C$21=1,"匯款","外幣匯款") -> 匯款 | N37: 自行繳費 | O37: 6.臨櫃存入(匯款)
A38: cuy_prem | B38: 保費幣別 | C38: OIU商品時, | D38: V | E38: X | F38: 試算表無須判別 | J38: =IF(I38="","",IF(COUNTA(I39:$I$138)>0,"|","")) | L38: 7 | M38: - | N38: - | O38: 9.其他
C39: 可能保額與保費幣別不同 | J39: =IF(I39="","",IF(COUNTA(I40:$I$138)>0,"|","")) | L39: A | M39: 金融機構轉帳 | N39: 金融機構轉帳 | O39: A.他行自扣(轉帳)
A40: Modx | B40: 繳別 | C40: 01 月繳 | D40: V | H40: =IF($H$8=1,IF(ISERROR(VLOOKUP($G40,$L$24:$M$29,2,0)),"",VLOOKUP($G40,$L$24:$M$29,2,0)),輸入頁!$E$17) -> 年繳 | I40: =IF(OP!$D$32=1,$I$10&"繳別錯誤","") | J40: =IF(I40="","",IF(COUNTA(I41:$I$138)>0,"|",""))
C41: 03 季繳 | J41: =IF(I41="","",IF(COUNTA(I42:$I$138)>0,"|",""))
C42: 06 半年繳 | J42: =IF(I42="","",IF(COUNTA(I43:$I$138)>0,"|",""))
C43: 12 年繳 | J43: =IF(I43="","",IF(COUNTA(I44:$I$138)>0,"|","")) | L43: 增值回饋分享金給付方式 | N43: 中信
C44: P 躉繳 | J44: =IF(I44="","",IF(COUNTA(I45:$I$138)>0,"|","")) | L44: 1 | M44: =IF($I$8=1,OP!$W$3,IF($I$8=2,OP!$W$6,"")) | N44: 1 增購保額
A45: first_pay_way | B45: 首期繳費方式 | C45: 1.帳戶圈存(匯款) | D45: V | H45: =IF($H$8=1,IF(ISERROR(VLOOKUP($G45,$L$31:$N$41,2,0)),"",VLOOKUP($G45,$L$31:$N$41,2,0)),輸入頁!$Q$17) -> 匯款 | I45: =IF(OP!$D$41=1,$I$10&"首期繳費方式錯誤","") | J45: =IF(I45="","",IF(COUNTA(I46:$I$138)>0,"|","")) | N45: 2 抵繳保費
C46: 2.現金圈存(匯款) | J46: =IF(I46="","",IF(COUNTA(I47:$I$138)>0,"|","")) | L46: 3 | M46: 現金給付 | N46: 3 現金給付
C47: 3.信用卡 | J47: =IF(I47="","",IF(COUNTA(I48:$I$138)>0,"|","")) | L47: 4 | M47: 儲存生息 | N47: 4 儲存生息
C48: 4.本行自扣(轉帳) | J48: =IF(I48="","",IF(COUNTA(I49:$I$138)>0,"|",""))
C49: 5.臨櫃轉帳(匯款) | J49: =IF(I49="","",IF(COUNTA(I50:$I$138)>0,"|",""))
C50: 6.臨櫃存入(匯款) | J50: =IF(I50="","",IF(COUNTA(I51:$I$138)>0,"|",""))
C51: 9.其他 | J51: =IF(I51="","",IF(COUNTA(I52:$I$138)>0,"|","")) | L51: 年金給付方式 | N51: 中信
C52: A.他行自扣(轉帳) | J52: =IF(I52="","",IF(COUNTA(I53:$I$138)>0,"|","")) | L52: 1 | M52: 一次年金 | N52: 1 一次給付
A53: cont_pay_way | B53: 續期繳費方式 | C53: 3.信用卡 | H53: =IF($H$8=1,IF(ISERROR(VLOOKUP($G53,$L$31:$N$41,3,0)),"",VLOOKUP($G53,$L$31:$N$41,3,0)),輸入頁!$Q$19) -> 金融機構轉帳 | I53: =IF(OP!$D$43=1,$I$10&"續期繳費方式錯誤","") | J53: =IF(I53="","",IF(COUNTA(I54:$I$138)>0,"|","")) | L53: 2 | M53: 分期年金 | N53: 2 分期給付
C54: 4.本行自扣(轉帳) | J54: =IF(I54="","",IF(COUNTA(I55:$I$138)>0,"|",""))
C55: 5.臨櫃轉帳(匯款) | J55: =IF(I55="","",IF(COUNTA(I56:$I$138)>0,"|",""))
C56: 6.臨櫃存入(匯款) | J56: =IF(I56="","",IF(COUNTA(I57:$I$138)>0,"|",""))
C57: 9.其他 | J57: =IF(I57="","",IF(COUNTA(I58:$I$138)>0,"|","")) | L57: 年金保證期
C58: A.他行自扣(轉帳) | J58: =IF(I58="","",IF(COUNTA(I59:$I$138)>0,"|","")) | M58: 5
A59: group_pay_disc_no | B59: 集彙折扣代碼 | F59: 集彙、員工專案有值=Y | H59: =IF($H$8=1,IF($G59<>"","Y",""),OP!$K$27) -> 0 | J59: =IF(I59="","",IF(COUNTA(I60:$I$138)>0,"|","")) | M59: 10
A60: group_pay_disc | B60: 集體彙繳折扣率 | C60: ex 1%提供 0.01 | E60: X | J60: =IF(I60="","",IF(COUNTA(I61:$I$138)>0,"|","")) | M60: 15
A61: face_amt | B61: 保額(元/計畫/單位) | D61: V | H61: =IF(RIGHT($I$8,2)="年金","",IF($H$8=1,$G61/10000,輸入頁!$J$39)) -> 1 | I61: =IF(OR(OP!$D$28=1,OP!$D$64=1),$I$10&"保額不符投保規則，請再確認","") | J61: =IF(I61="","",IF(COUNTA(I62:$I$138)>0,"|","")) | K61: 1150126調整 | M61: 20
A62: prem_amt | B62: 保費(目標保費、核心保費) | D62: V | F62: 投資型用 | H62: =IF($H$8=1,$G62,"") | J62: =IF(I62="","",IF(COUNTA(I63:$I$138)>0,"|",""))
A63: excess_prmm | B63: 超額保費(衛星保費) | H63: =IF($H$8=1,$G63,"") | J63: =IF(I63="","",IF(COUNTA(I64:$I$138)>0,"|","")) | L63: 年金給付方式
A64: additional_prmm | B64: 增額保費/首期追加繳付 | F64: 需加工計算首期總保費 | H64: =IF($H$8=1,$G64,"") | J64: =IF(I64="","",IF(COUNTA(I65:$I$138)>0,"|","")) | L64: 1 | M64: 年 | N64: 1.年給付
A65: cont_trial_yn | B65: 是否續保試算 | C65: Y/N | E65: X | J65: =IF(I65="","",IF(COUNTA(I66:$I$138)>0,"|","")) | L65: 2 | M65: 月 | N65: 2.月給付
A66: mortgage_year | B66: 房貸年期 | C66: 年 | E66: X | J66: =IF(I66="","",IF(COUNTA(I67:$I$138)>0,"|","")) | L66: 3 | M66: 季 | N66: 3.季給付
A67: mortgage_amt | B67: 房貸金額 | C67: 元 | E67: X | J67: =IF(I67="","",IF(COUNTA(I68:$I$138)>0,"|","")) | L67: 4 | M67: 半年 | N67: 4.半年給付
A68: cont_face_amt | B68: 續保保額 | C68: 元 | E68: X | J68: =IF(I68="","",IF(COUNTA(I69:$I$138)>0,"|",""))
A69: add_feedback_pay_type_6 | B69: 增值回饋金1-6年給付方式 | C69: 1 增購保額 | E69: X | F69: 試算表自行判別 | J69: =IF(I69="","",IF(COUNTA(I70:$I$138)>0,"|",""))
C70: 2 抵繳保費 | J70: =IF(I70="","",IF(COUNTA(I71:$I$138)>0,"|",""))
A71: add_feedback_pay_type_7 | B71: 增值回饋金Y7+給付方式 | C71: 1 增購保額 | H71: =IF($H$8=1,IF(ISERROR(VLOOKUP($G71,$L$44:$N$49,2,0)),"",VLOOKUP($G71,$L$44:$N$49,2,0)),輸入頁!$E$19) -> 現金給付 | I71: =IF(AND($I$8<>3,OR($H$71="",OP!$E$96=1)),$I$10&"給付方式錯誤","") | J71: =IF(I71="","",IF(COUNTA(I72:$I$138)>0,"|","")) | L71: 分期定期年期
C72: 2 抵繳保費 | J72: =IF(I72="","",IF(COUNTA(I73:$I$138)>0,"|","")) | L72: 10 | M72: 20
C73: 3 現金給付 | J73: =IF(I73="","",IF(COUNTA(I74:$I$138)>0,"|",""))
C74: 4 儲存生息 | J74: =IF(I74="","",IF(COUNTA(I75:$I$138)>0,"|",""))
A75: add_feedback_pay_type_m_flag | B75: 增值回饋金Y7+且大於55歲是否月領 | C75: Y/N | E75: X | F75: 試算表無月領設定 | J75: =IF(I75="","",IF(COUNTA(I76:$I$138)>0,"|",""))
A76: designate_insurance_amt | B76: 指定保險金 | C76: 元 | E76: X | F76: 無分期定額保險金 | J76: =IF(I76="","",IF(COUNTA(I77:$I$138)>0,"|",""))
A77: installment_fix_ins_est_rate | B77: 分期定額保險金預定利率 | C77: ex 1%提供 0.01 | E77: X | J77: =IF(I77="","",IF(COUNTA(I78:$I$138)>0,"|",""))
A78: installment_fix_ins_pay_during | B78: 分期定額保險金給付期間 | C78: 年 | E78: X | J78: =IF(I78="","",IF(COUNTA(I79:$I$138)>0,"|",""))
A79: death_ins_pay_pct | B79: 主約身故保障給付設定 | C79: ex 30% 提供30 | G79: 100 | H79: =IF($H$8=1,$G79/100,輸入頁!$G$26/100) -> 0 | I79: =IF(K79=0,"",IF(OR(AND($G$79<>"",$G$79*1<0),$G$79*1>100,AND($G$79<>"",LEN($G$79)<>LEN(ROUND($G$79,0)))),"分期定期保險金比例錯誤","")) | J79: =IF(I79="","",IF(COUNTA(I80:$I$138)>0,"|","")) | K79: 0 | L79: =IF(AND($G$79<>"",OR($H$79<0,$H$79>1)),"約定分期給付比例錯誤","")
B80: (約定分期給付比例) | J80: =IF(I80="","",IF(COUNTA(I81:$I$138)>0,"|",""))
A81: installment_regu_ins_pay_during | B81: 分期定期保險金給付期間 | C81: 年 | F81: 10或20 | H81: =IF($H$8=1,$G81,輸入頁!$G$30) -> 10 | I81: =IF(K81=0,"",IF(OR(AND($G$79>0,$G$79<=100,$G$81="")),"分期定期保險金給付年期未設定",IF($G$81="","",IF(OR($G$81=10,$G$81=20),"",IF($G$79*1=0,"","分期定期保險金給付年期錯誤"))))) | J81: =IF(I81="","",IF(COUNTA(I82:$I$138)>0,"|","")) | K81: 0 | L81: =IF(AND($G$81<>"",COUNTIF($L$72:$N$74,$H$81)<>1),"約定分期年期錯誤","")
A82: annuity_pay_type | B82: 年金給付方式 | C82: 1 一次給付 | H82: =IF($H$8=1,IF(ISERROR(VLOOKUP($G82,$L$52:$N$55,2,0)),"",VLOOKUP($G82,$L$52:$N$55,2,0)),"") | J82: =IF(I82="","",IF(COUNTA(I83:$I$138)>0,"|",""))
C83: 2 分期給付 | J83: =IF(I83="","",IF(COUNTA(I84:$I$138)>0,"|",""))
A84: annuity_guarantee_during | B84: 年金保證期間 | C84: 年 | H84: =IF($H$8=1,$G84,"") | J84: =IF(I84="","",IF(COUNTA(I85:$I$138)>0,"|",""))
A85: annuity_guarantee_amt | B85: 年金保證金額 | C85: 元 | E85: X | J85: =IF(I85="","",IF(COUNTA(I86:$I$138)>0,"|",""))
A86: annuity_guarantee_during_pay_type | B86: 年金分期給付方式/年金保證期間給付方式 | C86: 1.年給付 | H86: =IF($H$8=1,IF(ISERROR(VLOOKUP($G86,$L$64:$M$69,2,0)),"",VLOOKUP($G86,$L$64:$M$69,2,0)),"") | J86: =IF(I86="","",IF(COUNTA(I87:$I$138)>0,"|",""))
C87: 2.月給付 | J87: =IF(I87="","",IF(COUNTA(I88:$I$138)>0,"|",""))
C88: 3.季給付 | J88: =IF(I88="","",IF(COUNTA(I89:$I$138)>0,"|",""))
C89: 4.半年給付 | J89: =IF(I89="","",IF(COUNTA(I90:$I$138)>0,"|",""))
A90: annuity_pay_start_age | B90: 年金開始給付(歲) | C90: 歲 | F90: 系統換算 | J90: =IF(I90="","",IF(COUNTA(I91:$I$138)>0,"|",""))
A91: annuity_guarantee_age | B91: 年金保證提領年齡 | C91: 歲 | E91: X | J91: =IF(I91="","",IF(COUNTA(I92:$I$138)>0,"|",""))
A92: anuuity_accumulated_period | B92: 年金累積期間/年金開始給付(年) | C92: 年 | H92: =IF($H$8=1,$G92,"") | J92: =IF(I92="","",IF(COUNTA(I93:$I$138)>0,"|",""))
A93: annuity_plan_paid_period_year | B93: 計畫繳費年期(年金) | C93: 年 | H93: =IF($H$8=1,$G93,"") | J93: =IF(I93="","",IF(COUNTA(I94:$I$138)>0,"|",""))
A94: inv_plan_paid_period_year | B94: 計畫繳費年期(投資型壽險) | C94: 年 | H94: =IF($H$8=1,$G94,"") | J94: =IF(I94="","",IF(COUNTA(I95:$I$138)>0,"|",""))
A95: inv_rate_1 | B95: 預估投資報酬率1 | C95: ex 1%提供 0.01 | F95: 只會使用單段報酬率，其餘系統自訂 | H95: =IF($H$8=1,$G95,"") | J95: =IF(I95="","",IF(COUNTA(I96:$I$138)>0,"|",""))
C96: 應比預估投資報酬率2高 | J96: =IF(I96="","",IF(COUNTA(I97:$I$138)>0,"|",""))
A97: inv_rate_2 | B97: 預估投資報酬率2 | C97: ex 1%提供 0.01 | E97: X | J97: =IF(I97="","",IF(COUNTA(I98:$I$138)>0,"|",""))
C98: 應比預估投資報酬率1低 | J98: =IF(I98="","",IF(COUNTA(I99:$I$138)>0,"|",""))
A99: inv_pct_nor | B99: 投資比例-一般 | C99: % | E99: X | J99: =IF(I99="","",IF(COUNTA(I100:$I$138)>0,"|",""))
A100: inv_pct_etf | B100: 投資比例-ETF | C100: % | E100: X | J100: =IF(I100="","",IF(COUNTA(I101:$I$138)>0,"|",""))
...

Sheet 總表
B1: 1 | C1: 2 | D1: 3 | E1: 4 | F1: 5 | G1: 6 | H1: 7 | I1: 8 | J1: 9 | K1: 10 | L1: 11 | M1: 12 | N1: 13 | O1: 14 | P1: 15 | Q1: 16 | R1: 17 | S1: 18 | T1: 19 | U1: 20 | V1: 21 | W1: 22 | X1: 23 | Y1: 24 | Z1: 25 | AA1: 26 | AB1: 27 | AC1: 28 | AD1: 29 | AE1: 30 | AF1: 31 | AG1: 32 | AH1: 33 | AI1: 34
D2: 列印頁-簡/銀保/彙總 | F2: 基本保額 | N2: 累計增額繳清保險金額 | S2: 生存保險金 F+O | T2: 累計生存保險金 | U2: 生存保險金(月) round(S/12,0) | V2: 累計生存保險金(月) (U*12)+上期總額 | Y2: 年度末身故/完全失能時可領總金額 | Z2: 身故保障=基本保額+增購保額-最後一年回饋金(增購保額) ㄧ次給付身故=身故保障*比例PYO+紅利+最後一年紅利(增購保額) 分期給付=身故保障*比例PYY | AA2: 列印頁 未扣除增值回饋分享金 | AB2: 列印頁 未扣除增值回饋分享金 | AC2: 保險金額- 大眾運輸工具意外身故保障-28 (不含年度末身故/完全失能時可領總金額) | AD2: 重大燒燙傷保險金-29 | AE2: 保險金額- 大眾運輸工具 意外身故保障-30 (含年度末身故/完全失能保障) | AF2: 意外身故保險金(含身故可領總金額)-31
B3: 保 單 年 度 | C3: 保 險 年 齡 | D3: ="年度實繳保費"&IF(OP!$F$55<15," 已扣除增值回饋分享金 ","") -> 年度實繳保費 | E3: ="累計實繳保費"&IF(OP!$F$55<15," 已扣除增值回饋分享金 ","") -> 累計實繳保費 | F3: 生存保險金 | G3: 累計已領 生存保險金 | H3: 年度末 身故/完全 失能保障 | I3: 年度末 解約金 | J3: 年度末 減額繳清 保險金額 | N3: 年度末 保險金額 ( Z ) | O3: 生存保險金 | P3: 累計已領生存保險金 | Q3: ="年度末 身故/完全失能保障 ( D ) "&OP!$D$114 -> 年度末 身故/完全失能保障 ( D ) | R3: ="年度末 解約金 ( E ) "&OP!$D$115 -> 年度末 解約金 ( E ) | Y3: ㄧ次給付 | Z3: =IF(OR(PYY=0,PY!$C$6=0),"","分期給付(年) 給付"&PY!$C$6&"年") | AA3: 年度 實繳保費 | AB3: 累計 實繳保費 | AE3: 年度末 大眾運輸 交通工具 意外身故保障 | AF3: 年度末 大眾運輸交通工具 意外身故時可領總金額 | AG3: 重大疾病暨 特定傷病保險金 | AH3: 輕度失智 保險金 | AI3: 中重度失智 保險金 (免責期間屆滿 時之保單年度)
B4: 1 | C4: =IF(OP!$D$53=1,"",OP!$F$55) -> 15 | D4: =IF(OR(OP!$D$53=1,AND($B4>OP!$C$24)),"",OP!$C$51) -> 11326 | E4: =IF(OR(OP!$D$53=1,$B4=""),"",N(D4)) -> 11326 | F4: =IF(OR(OP!$D$53=1,$B4="",ISERROR(VLOOKUP(OP!$C$55,SRV,$B4+1,0))),"",ROUND(VLOOKUP(OP!$C$55,SRV,$B4+1,0)*OP!$C$28,0)) | G4: =IF(OR(OP!$D$53=1,$B4="",ISERROR(VLOOKUP(OP!$C$55,SRV,$B4+1,0))),"",N($F4)) | H4: =IF(OR(OP!$D$53=1,$B4=""),"",ROUND(VLOOKUP(OP!$C$55,DIE,$B4+1,0)*OP!$C$28,0)) -> #N/A | I4: =IF(OR(OP!$D$53=1,$B4=""),"",ROUND(VLOOKUP(OP!$C$55,CV,$B4+1,0)*OP!$C$28,0)) -> #N/A | J4: =IF(OR(OP!$D$53=1,$B4=""),"",ROUND(VLOOKUP(OP!$C$55,PA,$B4+1,0)*OP!$C$28,0)) -> #N/A | S4: =IF(OR(OP!$D$53=1,$B4=""),"",N($F4)+N($O4)) -> 0 | T4: =IF(OR(OP!$D$53=1,$B4=""),0,N($S4)) -> 0 | U4: =IF(OR(OP!$D$53=1,$B4=""),"",ROUND($S4/12,0)) -> 0 | V4: =IF(OR(OP!$D$53=1,$B4=""),0,N($U4)*12) -> 0 | Y4: =IF(OR(OP!$D$53=1,$B4=""),"",ROUND(($H4+$Q4)*IF(OR($C4<16,$Z4=0,$Z4=""),1,PYO),0)) -> #N/A | Z4: =IF(OR(OP!$D$53=1,$B4=""),"",ROUND(($H4+Q4)*IF(OR($C4<16,($H4+$Q4)*PY!$C$4<PY!$D$5,($H4+$Q4)*PY!$C$4*PYR<PY!$C$5),0,PYY)*PYR,0)) -> #N/A | AA4: =IF(OR(OP!$D$53=1,AND(B4>OP!$C$24)),"",OP!$C$51) -> 11326 | AB4: =IF(OR(OP!$D$53=1,$B4=""),"",N($AA4)) -> 11326 | AH4: =IF(OR(OP!$D$53=1,$B4=""),"",ROUND(VLOOKUP(OP!$C$55,HL_1,$B4+1,0)*OP!$C$28,0)) -> #N/A | AI4: =IF(OR(OP!$D$53=1,$B4=""),"",ROUND(VLOOKUP(OP!$C$55,HL_2,$B4+1,0)*OP!$C$28,0)) -> #N/A
B5: =IF(OR(C4>=OP!$F$57,C4=""),"",IF(C4+1>OP!$F$57,OP!$F$57+1-$C$4,B4+1)) -> 2 | C5: =IF(OR(OP!$D$53=1,MAX($C4:C$4)>=OP!$F$57),"",C4+(B5-B4)) -> 16 | D5: =IF(OR(OP!$D$53=1,AND($B5>OP!$C$24)),"",OP!$C$52-IF($C5<16,$K4,0)) -> 11326 | E5: =IF(OR(OP!$D$53=1,$B5=""),"",N($E4)+N($D5)) -> 22652 | F5: =IF(OR(OP!$D$53=1,$B5="",ISERROR(VLOOKUP(OP!$C$55,SRV,$B5+1,0))),"",ROUND(VLOOKUP(OP!$C$55,SRV,$B5+1,0)*OP!$C$28,0)) | G5: =IF(OR(OP!$D$53=1,$B5="",ISERROR(VLOOKUP(OP!$C$55,SRV,$B5+1,0))),"",N($G4)+N($F5)) | H5: =IF(OR(OP!$D$53=1,$B5=""),"",ROUND(VLOOKUP(OP!$C$55,DIE,$B5+1,0)*OP!$C$28,0)) -> #N/A | I5: =IF(OR(OP!$D$53=1,$B5=""),"",ROUND(VLOOKUP(OP!$C$55,CV,$B5+1,0)*OP!$C$28,0)) -> #N/A | J5: =IF(OR(OP!$D$53=1,$B5=""),"",ROUND(VLOOKUP(OP!$C$55,PA,$B5+1,0)*OP!$C$28,0)) -> #N/A | S5: =IF(OR(OP!$D$53=1,$B5=""),"",N($F5)+N($O5)) -> 0 | T5: =IF(OR(OP!$D$53=1,$B5=""),0,N($T4)+N($S5)) -> 0 | U5: =IF(OR(OP!$D$53=1,$B5=""),"",ROUND($S5/12,0)) -> 0 | V5: =IF(OR(OP!$D$53=1,$B5=""),0,N($V4)+(N($U5)*12)) -> 0 | Y5: =IF(OR(OP!$D$53=1,$B5=""),"",ROUND(($H5+$Q5)*IF(OR($C5<16,$Z5=0,$Z5=""),1,PYO),0)) -> #N/A | Z5: =IF(OR(OP!$D$53=1,$B5=""),"",ROUND(($H5+Q5)*IF(OR($C5<16,($H5+$Q5)*PY!$C$4<PY!$D$5,($H5+$Q5)*PY!$C$4*PYR<PY!$C$5),0,PYY)*PYR,0)) -> #N/A | AA5: =IF(OR(OP!$D$53=1,AND(B5>OP!$C$24)),"",OP!$C$52) -> 11326 | AB5: =IF(OR(OP!$D$53=1,$B5=""),"",N($AB4)+N($AA5)) -> 22652 | AH5: =IF(OR(OP!$D$53=1,$B5=""),"",ROUND(VLOOKUP(OP!$C$55,HL_1,$B5+1,0)*OP!$C$28,0)) -> #N/A | AI5: =IF(OR(OP!$D$53=1,$B5=""),"",ROUND(VLOOKUP(OP!$C$55,HL_2,$B5+1,0)*OP!$C$28,0)) -> #N/A
B6: =IF(OR(C5>=OP!$F$57,C5=""),"",IF(C5+1>OP!$F$57,OP!$F$57+1-$C$4,B5+1)) -> 3 | C6: =IF(OR(OP!$D$53=1,MAX($C$4:C5)>=OP!$F$57),"",C5+(B6-B5)) -> 17 | D6: =IF(OR(OP!$D$53=1,AND($B6>OP!$C$24)),"",OP!$C$52-IF($C6<16,$K5,0)) -> 11326 | E6: =IF(OR(OP!$D$53=1,$B6=""),"",N($E5)+N($D6)) -> 33978 | F6: =IF(OR(OP!$D$53=1,$B6="",ISERROR(VLOOKUP(OP!$C$55,SRV,$B6+1,0))),"",ROUND(VLOOKUP(OP!$C$55,SRV,$B6+1,0)*OP!$C$28,0)) | G6: =IF(OR(OP!$D$53=1,$B6="",ISERROR(VLOOKUP(OP!$C$55,SRV,$B6+1,0))),"",N($G5)+N($F6)) | H6: =IF(OR(OP!$D$53=1,$B6=""),"",ROUND(VLOOKUP(OP!$C$55,DIE,$B6+1,0)*OP!$C$28,0)) -> #N/A | I6: =IF(OR(OP!$D$53=1,$B6=""),"",ROUND(VLOOKUP(OP!$C$55,CV,$B6+1,0)*OP!$C$28,0)) -> #N/A | J6: =IF(OR(OP!$D$53=1,$B6=""),"",ROUND(VLOOKUP(OP!$C$55,PA,$B6+1,0)*OP!$C$28,0)) -> #N/A | S6: =IF(OR(OP!$D$53=1,$B6=""),"",N($F6)+N($O6)) -> 0 | T6: =IF(OR(OP!$D$53=1,$B6=""),0,N($T5)+N($S6)) -> 0 | U6: =IF(OR(OP!$D$53=1,$B6=""),"",ROUND($S6/12,0)) -> 0 | V6: =IF(OR(OP!$D$53=1,$B6=""),0,N($V5)+(N($U6)*12)) -> 0 | Y6: =IF(OR(OP!$D$53=1,$B6=""),"",ROUND(($H6+$Q6)*IF(OR($C6<16,$Z6=0,$Z6=""),1,PYO),0)) -> #N/A | Z6: =IF(OR(OP!$D$53=1,$B6=""),"",ROUND(($H6+Q6)*IF(OR($C6<16,($H6+$Q6)*PY!$C$4<PY!$D$5,($H6+$Q6)*PY!$C$4*PYR<PY!$C$5),0,PYY)*PYR,0)) -> #N/A | AA6: =IF(OR(OP!$D$53=1,AND(B6>OP!$C$24)),"",OP!$C$52) -> 11326 | AB6: =IF(OR(OP!$D$53=1,$B6=""),"",N($AB5)+N($AA6)) -> 33978 | AH6: =IF(OR(OP!$D$53=1,$B6=""),"",ROUND(VLOOKUP(OP!$C$55,HL_1,$B6+1,0)*OP!$C$28,0)) -> #N/A | AI6: =IF(OR(OP!$D$53=1,$B6=""),"",ROUND(VLOOKUP(OP!$C$55,HL_2,$B6+1,0)*OP!$C$28,0)) -> #N/A
B7: =IF(OR(C6>=OP!$F$57,C6=""),"",IF(C6+1>OP!$F$57,OP!$F$57+1-$C$4,B6+1)) -> 4 | C7: =IF(OR(OP!$D$53=1,MAX($C$4:C6)>=OP!$F$57),"",C6+(B7-B6)) -> 18 | D7: =IF(OR(OP!$D$53=1,AND($B7>OP!$C$24)),"",OP!$C$52-IF($C7<16,$K6,0)) -> 11326 | E7: =IF(OR(OP!$D$53=1,$B7=""),"",N($E6)+N($D7)) -> 45304 | F7: =IF(OR(OP!$D$53=1,$B7="",ISERROR(VLOOKUP(OP!$C$55,SRV,$B7+1,0))),"",ROUND(VLOOKUP(OP!$C$55,SRV,$B7+1,0)*OP!$C$28,0)) | G7: =IF(OR(OP!$D$53=1,$B7="",ISERROR(VLOOKUP(OP!$C$55,SRV,$B7+1,0))),"",N($G6)+N($F7)) | H7: =IF(OR(OP!$D$53=1,$B7=""),"",ROUND(VLOOKUP(OP!$C$55,DIE,$B7+1,0)*OP!$C$28,0)) -> #N/A | I7: =IF(OR(OP!$D$53=1,$B7=""),"",ROUND(VLOOKUP(OP!$C$55,CV,$B7+1,0)*OP!$C$28,0)) -> #N/A | J7: =IF(OR(OP!$D$53=1,$B7=""),"",ROUND(VLOOKUP(OP!$C$55,PA,$B7+1,0)*OP!$C$28,0)) -> #N/A | S7: =IF(OR(OP!$D$53=1,$B7=""),"",N($F7)+N($O7)) -> 0 | T7: =IF(OR(OP!$D$53=1,$B7=""),0,N($T6)+N($S7)) -> 0 | U7: =IF(OR(OP!$D$53=1,$B7=""),"",ROUND($S7/12,0)) -> 0 | V7: =IF(OR(OP!$D$53=1,$B7=""),0,N($V6)+(N($U7)*12)) -> 0 | Y7: =IF(OR(OP!$D$53=1,$B7=""),"",ROUND(($H7+$Q7)*IF(OR($C7<16,$Z7=0,$Z7=""),1,PYO),0)) -> #N/A | Z7: =IF(OR(OP!$D$53=1,$B7=""),"",ROUND(($H7+Q7)*IF(OR($C7<16,($H7+$Q7)*PY!$C$4<PY!$D$5,($H7+$Q7)*PY!$C$4*PYR<PY!$C$5),0,PYY)*PYR,0)) -> #N/A | AA7: =IF(OR(OP!$D$53=1,AND(B7>OP!$C$24)),"",OP!$C$52) -> 11326 | AB7: =IF(OR(OP!$D$53=1,$B7=""),"",N($AB6)+N($AA7)) -> 45304 | AH7: =IF(OR(OP!$D$53=1,$B7=""),"",ROUND(VLOOKUP(OP!$C$55,HL_1,$B7+1,0)*OP!$C$28,0)) -> #N/A | AI7: =IF(OR(OP!$D$53=1,$B7=""),"",ROUND(VLOOKUP(OP!$C$55,HL_2,$B7+1,0)*OP!$C$28,0)) -> #N/A
B8: =IF(OR(C7>=OP!$F$57,C7=""),"",IF(C7+1>OP!$F$57,OP!$F$57+1-$C$4,B7+1)) -> 5 | C8: =IF(OR(OP!$D$53=1,MAX($C$4:C7)>=OP!$F$57),"",C7+(B8-B7)) -> 19 | D8: =IF(OR(OP!$D$53=1,AND($B8>OP!$C$24)),"",OP!$C$52-IF($C8<16,$K7,0)) -> 11326 | E8: =IF(OR(OP!$D$53=1,$B8=""),"",N($E7)+N($D8)) -> 56630 | F8: =IF(OR(OP!$D$53=1,$B8="",ISERROR(VLOOKUP(OP!$C$55,SRV,$B8+1,0))),"",ROUND(VLOOKUP(OP!$C$55,SRV,$B8+1,0)*OP!$C$28,0)) | G8: =IF(OR(OP!$D$53=1,$B8="",ISERROR(VLOOKUP(OP!$C$55,SRV,$B8+1,0))),"",N($G7)+N($F8)) | H8: =IF(OR(OP!$D$53=1,$B8=""),"",ROUND(VLOOKUP(OP!$C$55,DIE,$B8+1,0)*OP!$C$28,0)) -> #N/A | I8: =IF(OR(OP!$D$53=1,$B8=""),"",ROUND(VLOOKUP(OP!$C$55,CV,$B8+1,0)*OP!$C$28,0)) -> #N/A | J8: =IF(OR(OP!$D$53=1,$B8=""),"",ROUND(VLOOKUP(OP!$C$55,PA,$B8+1,0)*OP!$C$28,0)) -> #N/A | S8: =IF(OR(OP!$D$53=1,$B8=""),"",N($F8)+N($O8)) -> 0 | T8: =IF(OR(OP!$D$53=1,$B8=""),0,N($T7)+N($S8)) -> 0 | U8: =IF(OR(OP!$D$53=1,$B8=""),"",ROUND($S8/12,0)) -> 0 | V8: =IF(OR(OP!$D$53=1,$B8=""),0,N($V7)+(N($U8)*12)) -> 0 | Y8: =IF(OR(OP!$D$53=1,$B8=""),"",ROUND(($H8+$Q8)*IF(OR($C8<16,$Z8=0,$Z8=""),1,PYO),0)) -> #N/A | Z8: =IF(OR(OP!$D$53=1,$B8=""),"",ROUND(($H8+Q8)*IF(OR($C8<16,($H8+$Q8)*PY!$C$4<PY!$D$5,($H8+$Q8)*PY!$C$4*PYR<PY!$C$5),0,PYY)*PYR,0)) -> #N/A | AA8: =IF(OR(OP!$D$53=1,AND(B8>OP!$C$24)),"",OP!$C$52) -> 11326 | AB8: =IF(OR(OP!$D$53=1,$B8=""),"",N($AB7)+N($AA8)) -> 56630 | AH8: =IF(OR(OP!$D$53=1,$B8=""),"",ROUND(VLOOKUP(OP!$C$55,HL_1,$B8+1,0)*OP!$C$28,0)) -> #N/A | AI8: =IF(OR(OP!$D$53=1,$B8=""),"",ROUND(VLOOKUP(OP!$C$55,HL_2,$B8+1,0)*OP!$C$28,0)) -> #N/A
B9: =IF(OR(C8>=OP!$F$57,C8=""),"",IF(C8+1>OP!$F$57,OP!$F$57+1-$C$4,B8+1)) -> 6 | C9: =IF(OR(OP!$D$53=1,MAX($C$4:C8)>=OP!$F$57),"",C8+(B9-B8)) -> 20 | D9: =IF(OR(OP!$D$53=1,AND($B9>OP!$C$24)),"",OP!$C$52-IF($C9<16,$K8,0)) -> 11326 | E9: =IF(OR(OP!$D$53=1,$B9=""),"",N($E8)+N($D9)) -> 67956 | F9: =IF(OR(OP!$D$53=1,$B9="",ISERROR(VLOOKUP(OP!$C$55,SRV,$B9+1,0))),"",ROUND(VLOOKUP(OP!$C$55,SRV,$B9+1,0)*OP!$C$28,0)) | G9: =IF(OR(OP!$D$53=1,$B9="",ISERROR(VLOOKUP(OP!$C$55,SRV,$B9+1,0))),"",N($G8)+N($F9)) | H9: =IF(OR(OP!$D$53=1,$B9=""),"",ROUND(VLOOKUP(OP!$C$55,DIE,$B9+1,0)*OP!$C$28,0)) -> #N/A | I9: =IF(OR(OP!$D$53=1,$B9=""),"",ROUND(VLOOKUP(OP!$C$55,CV,$B9+1,0)*OP!$C$28,0)) -> #N/A | J9: =IF(OR(OP!$D$53=1,$B9=""),"",ROUND(VLOOKUP(OP!$C$55,PA,$B9+1,0)*OP!$C$28,0)) -> #N/A | S9: =IF(OR(OP!$D$53=1,$B9=""),"",N($F9)+N($O9)) -> 0 | T9: =IF(OR(OP!$D$53=1,$B9=""),0,N($T8)+N($S9)) -> 0 | U9: =IF(OR(OP!$D$53=1,$B9=""),"",ROUND($S9/12,0)) -> 0 | V9: =IF(OR(OP!$D$53=1,$B9=""),0,N($V8)+(N($U9)*12)) -> 0 | Y9: =IF(OR(OP!$D$53=1,$B9=""),"",ROUND(($H9+$Q9)*IF(OR($C9<16,$Z9=0,$Z9=""),1,PYO),0)) -> #N/A | Z9: =IF(OR(OP!$D$53=1,$B9=""),"",ROUND(($H9+Q9)*IF(OR($C9<16,($H9+$Q9)*PY!$C$4<PY!$D$5,($H9+$Q9)*PY!$C$4*PYR<PY!$C$5),0,PYY)*PYR,0)) -> #N/A | AA9: =IF(OR(OP!$D$53=1,AND(B9>OP!$C$24)),"",OP!$C$52) -> 11326 | AB9: =IF(OR(OP!$D$53=1,$B9=""),"",N($AB8)+N($AA9)) -> 67956 | AH9: =IF(OR(OP!$D$53=1,$B9=""),"",ROUND(VLOOKUP(OP!$C$55,HL_1,$B9+1,0)*OP!$C$28,0)) -> #N/A | AI9: =IF(OR(OP!$D$53=1,$B9=""),"",ROUND(VLOOKUP(OP!$C$55,HL_2,$B9+1,0)*OP!$C$28,0)) -> #N/A
B10: =IF(OR(C9>=OP!$F$57,C9=""),"",IF(C9+1>OP!$F$57,OP!$F$57+1-$C$4,B9+1)) -> 7 | C10: =IF(OR(OP!$D$53=1,MAX($C$4:C9)>=OP!$F$57),"",C9+(B10-B9)) -> 21 | D10: =IF(OR(OP!$D$53=1,AND($B10>OP!$C$24)),"",OP!$C$52-IF($C10<16,$K9,0)) -> 11326 | E10: =IF(OR(OP!$D$53=1,$B10=""),"",N($E9)+N($D10)) -> 79282 | F10: =IF(OR(OP!$D$53=1,$B10="",ISERROR(VLOOKUP(OP!$C$55,SRV,$B10+1,0))),"",ROUND(VLOOKUP(OP!$C$55,SRV,$B10+1,0)*OP!$C$28,0)) | G10: =IF(OR(OP!$D$53=1,$B10="",ISERROR(VLOOKUP(OP!$C$55,SRV,$B10+1,0))),"",N($G9)+N($F10)) | H10: =IF(OR(OP!$D$53=1,$B10=""),"",ROUND(VLOOKUP(OP!$C$55,DIE,$B10+1,0)*OP!$C$28,0)) -> #N/A | I10: =IF(OR(OP!$D$53=1,$B10=""),"",ROUND(VLOOKUP(OP!$C$55,CV,$B10+1,0)*OP!$C$28,0)) -> #N/A | J10: =IF(OR(OP!$D$53=1,$B10=""),"",ROUND(VLOOKUP(OP!$C$55,PA,$B10+1,0)*OP!$C$28,0)) -> #N/A | S10: =IF(OR(OP!$D$53=1,$B10=""),"",N($F10)+N($O10)) -> 0 | T10: =IF(OR(OP!$D$53=1,$B10=""),0,N($T9)+N($S10)) -> 0 | U10: =IF(OR(OP!$D$53=1,$B10=""),"",ROUND($S10/12,0)) -> 0 | V10: =IF(OR(OP!$D$53=1,$B10=""),0,N($V9)+(N($U10)*12)) -> 0 | Y10: =IF(OR(OP!$D$53=1,$B10=""),"",ROUND(($H10+$Q10)*IF(OR($C10<16,$Z10=0,$Z10=""),1,PYO),0)) -> #N/A | Z10: =IF(OR(OP!$D$53=1,$B10=""),"",ROUND(($H10+Q10)*IF(OR($C10<16,($H10+$Q10)*PY!$C$4<PY!$D$5,($H10+$Q10)*PY!$C$4*PYR<PY!$C$5),0,PYY)*PYR,0)) -> #N/A | AA10: =IF(OR(OP!$D$53=1,AND(B10>OP!$C$24)),"",OP!$C$52) -> 11326 | AB10: =IF(OR(OP!$D$53=1,$B10=""),"",N($AB9)+N($AA10)) -> 79282 | AH10: =IF(OR(OP!$D$53=1,$B10=""),"",ROUND(VLOOKUP(OP!$C$55,HL_1,$B10+1,0)*OP!$C$28,0)) -> #N/A | AI10: =IF(OR(OP!$D$53=1,$B10=""),"",ROUND(VLOOKUP(OP!$C$55,HL_2,$B10+1,0)*OP!$C$28,0)) -> #N/A
B11: =IF(OR(C10>=OP!$F$57,C10=""),"",IF(C10+1>OP!$F$57,OP!$F$57+1-$C$4,B10+1)) -> 8 | C11: =IF(OR(OP!$D$53=1,MAX($C$4:C10)>=OP!$F$57),"",C10+(B11-B10)) -> 22 | D11: =IF(OR(OP!$D$53=1,AND($B11>OP!$C$24)),"",OP!$C$52-IF($C11<16,$K10,0)) -> 11326 | E11: =IF(OR(OP!$D$53=1,$B11=""),"",N($E10)+N($D11)) -> 90608 | F11: =IF(OR(OP!$D$53=1,$B11="",ISERROR(VLOOKUP(OP!$C$55,SRV,$B11+1,0))),"",ROUND(VLOOKUP(OP!$C$55,SRV,$B11+1,0)*OP!$C$28,0)) | G11: =IF(OR(OP!$D$53=1,$B11="",ISERROR(VLOOKUP(OP!$C$55,SRV,$B11+1,0))),"",N($G10)+N($F11)) | H11: =IF(OR(OP!$D$53=1,$B11=""),"",ROUND(VLOOKUP(OP!$C$55,DIE,$B11+1,0)*OP!$C$28,0)) -> #N/A | I11: =IF(OR(OP!$D$53=1,$B11=""),"",ROUND(VLOOKUP(OP!$C$55,CV,$B11+1,0)*OP!$C$28,0)) -> #N/A | J11: =IF(OR(OP!$D$53=1,$B11=""),"",ROUND(VLOOKUP(OP!$C$55,PA,$B11+1,0)*OP!$C$28,0)) -> #N/A | S11: =IF(OR(OP!$D$53=1,$B11=""),"",N($F11)+N($O11)) -> 0 | T11: =IF(OR(OP!$D$53=1,$B11=""),0,N($T10)+N($S11)) -> 0 | U11: =IF(OR(OP!$D$53=1,$B11=""),"",ROUND($S11/12,0)) -> 0 | V11: =IF(OR(OP!$D$53=1,$B11=""),0,N($V10)+(N($U11)*12)) -> 0 | Y11: =IF(OR(OP!$D$53=1,$B11=""),"",ROUND(($H11+$Q11)*IF(OR($C11<16,$Z11=0,$Z11=""),1,PYO),0)) -> #N/A | Z11: =IF(OR(OP!$D$53=1,$B11=""),"",ROUND(($H11+Q11)*IF(OR($C11<16,($H11+$Q11)*PY!$C$4<PY!$D$5,($H11+$Q11)*PY!$C$4*PYR<PY!$C$5),0,PYY)*PYR,0)) -> #N/A | AA11: =IF(OR(OP!$D$53=1,AND(B11>OP!$C$24)),"",OP!$C$52) -> 11326 | AB11: =IF(OR(OP!$D$53=1,$B11=""),"",N($AB10)+N($AA11)) -> 90608 | AH11: =IF(OR(OP!$D$53=1,$B11=""),"",ROUND(VLOOKUP(OP!$C$55,HL_1,$B11+1,0)*OP!$C$28,0)) -> #N/A | AI11: =IF(OR(OP!$D$53=1,$B11=""),"",ROUND(VLOOKUP(OP!$C$55,HL_2,$B11+1,0)*OP!$C$28,0)) -> #N/A
B12: =IF(OR(C11>=OP!$F$57,C11=""),"",IF(C11+1>OP!$F$57,OP!$F$57+1-$C$4,B11+1)) -> 9 | C12: =IF(OR(OP!$D$53=1,MAX($C$4:C11)>=OP!$F$57),"",C11+(B12-B11)) -> 23 | D12: =IF(OR(OP!$D$53=1,AND($B12>OP!$C$24)),"",OP!$C$52-IF($C12<16,$K11,0)) -> 11326 | E12: =IF(OR(OP!$D$53=1,$B12=""),"",N($E11)+N($D12)) -> 101934 | F12: =IF(OR(OP!$D$53=1,$B12="",ISERROR(VLOOKUP(OP!$C$55,SRV,$B12+1,0))),"",ROUND(VLOOKUP(OP!$C$55,SRV,$B12+1,0)*OP!$C$28,0)) | G12: =IF(OR(OP!$D$53=1,$B12="",ISERROR(VLOOKUP(OP!$C$55,SRV,$B12+1,0))),"",N($G11)+N($F12)) | H12: =IF(OR(OP!$D$53=1,$B12=""),"",ROUND(VLOOKUP(OP!$C$55,DIE,$B12+1,0)*OP!$C$28,0)) -> #N/A | I12: =IF(OR(OP!$D$53=1,$B12=""),"",ROUND(VLOOKUP(OP!$C$55,CV,$B12+1,0)*OP!$C$28,0)) -> #N/A | J12: =IF(OR(OP!$D$53=1,$B12=""),"",ROUND(VLOOKUP(OP!$C$55,PA,$B12+1,0)*OP!$C$28,0)) -> #N/A | S12: =IF(OR(OP!$D$53=1,$B12=""),"",N($F12)+N($O12)) -> 0 | T12: =IF(OR(OP!$D$53=1,$B12=""),0,N($T11)+N($S12)) -> 0 | U12: =IF(OR(OP!$D$53=1,$B12=""),"",ROUND($S12/12,0)) -> 0 | V12: =IF(OR(OP!$D$53=1,$B12=""),0,N($V11)+(N($U12)*12)) -> 0 | Y12: =IF(OR(OP!$D$53=1,$B12=""),"",ROUND(($H12+$Q12)*IF(OR($C12<16,$Z12=0,$Z12=""),1,PYO),0)) -> #N/A | Z12: =IF(OR(OP!$D$53=1,$B12=""),"",ROUND(($H12+Q12)*IF(OR($C12<16,($H12+$Q12)*PY!$C$4<PY!$D$5,($H12+$Q12)*PY!$C$4*PYR<PY!$C$5),0,PYY)*PYR,0)) -> #N/A | AA12: =IF(OR(OP!$D$53=1,AND(B12>OP!$C$24)),"",OP!$C$52) -> 11326 | AB12: =IF(OR(OP!$D$53=1,$B12=""),"",N($AB11)+N($AA12)) -> 101934 | AH12: =IF(OR(OP!$D$53=1,$B12=""),"",ROUND(VLOOKUP(OP!$C$55,HL_1,$B12+1,0)*OP!$C$28,0)) -> #N/A | AI12: =IF(OR(OP!$D$53=1,$B12=""),"",ROUND(VLOOKUP(OP!$C$55,HL_2,$B12+1,0)*OP!$C$28,0)) -> #N/A
B13: =IF(OR(C12>=OP!$F$57,C12=""),"",IF(C12+1>OP!$F$57,OP!$F$57+1-$C$4,B12+1)) -> 10 | C13: =IF(OR(OP!$D$53=1,MAX($C$4:C12)>=OP!$F$57),"",C12+(B13-B12)) -> 24 | D13: =IF(OR(OP!$D$53=1,AND($B13>OP!$C$24)),"",OP!$C$52-IF($C13<16,$K12,0)) -> 11326 | E13: =IF(OR(OP!$D$53=1,$B13=""),"",N($E12)+N($D13)) -> 113260 | F13: =IF(OR(OP!$D$53=1,$B13="",ISERROR(VLOOKUP(OP!$C$55,SRV,$B13+1,0))),"",ROUND(VLOOKUP(OP!$C$55,SRV,$B13+1,0)*OP!$C$28,0)) | G13: =IF(OR(OP!$D$53=1,$B13="",ISERROR(VLOOKUP(OP!$C$55,SRV,$B13+1,0))),"",N($G12)+N($F13)) | H13: =IF(OR(OP!$D$53=1,$B13=""),"",ROUND(VLOOKUP(OP!$C$55,DIE,$B13+1,0)*OP!$C$28,0)) -> #N/A | I13: =IF(OR(OP!$D$53=1,$B13=""),"",ROUND(VLOOKUP(OP!$C$55,CV,$B13+1,0)*OP!$C$28,0)) -> #N/A | J13: =IF(OR(OP!$D$53=1,$B13=""),"",ROUND(VLOOKUP(OP!$C$55,PA,$B13+1,0)*OP!$C$28,0)) -> #N/A | S13: =IF(OR(OP!$D$53=1,$B13=""),"",N($F13)+N($O13)) -> 0 | T13: =IF(OR(OP!$D$53=1,$B13=""),0,N($T12)+N($S13)) -> 0 | U13: =IF(OR(OP!$D$53=1,$B13=""),"",ROUND($S13/12,0)) -> 0 | V13: =IF(OR(OP!$D$53=1,$B13=""),0,N($V12)+(N($U13)*12)) -> 0 | Y13: =IF(OR(OP!$D$53=1,$B13=""),"",ROUND(($H13+$Q13)*IF(OR($C13<16,$Z13=0,$Z13=""),1,PYO),0)) -> #N/A | Z13: =IF(OR(OP!$D$53=1,$B13=""),"",ROUND(($H13+Q13)*IF(OR($C13<16,($H13+$Q13)*PY!$C$4<PY!$D$5,($H13+$Q13)*PY!$C$4*PYR<PY!$C$5),0,PYY)*PYR,0)) -> #N/A | AA13: =IF(OR(OP!$D$53=1,AND(B13>OP!$C$24)),"",OP!$C$52) -> 11326 | AB13: =IF(OR(OP!$D$53=1,$B13=""),"",N($AB12)+N($AA13)) -> 113260 | AH13: =IF(OR(OP!$D$53=1,$B13=""),"",ROUND(VLOOKUP(OP!$C$55,HL_1,$B13+1,0)*OP!$C$28,0)) -> #N/A | AI13: =IF(OR(OP!$D$53=1,$B13=""),"",ROUND(VLOOKUP(OP!$C$55,HL_2,$B13+1,0)*OP!$C$28,0)) -> #N/A
B14: =IF(OR(C13>=OP!$F$57,C13=""),"",IF(C13+1>OP!$F$57,OP!$F$57+1-$C$4,B13+1)) -> 11 | C14: =IF(OR(OP!$D$53=1,MAX($C$4:C13)>=OP!$F$57),"",C13+(B14-B13)) -> 25 | D14: =IF(OR(OP!$D$53=1,AND($B14>OP!$C$24)),"",OP!$C$52-IF($C14<16,$K13,0)) -> 11326 | E14: =IF(OR(OP!$D$53=1,$B14=""),"",N($E13)+N($D14)) -> 124586 | F14: =IF(OR(OP!$D$53=1,$B14="",ISERROR(VLOOKUP(OP!$C$55,SRV,$B14+1,0))),"",ROUND(VLOOKUP(OP!$C$55,SRV,$B14+1,0)*OP!$C$28,0)) | G14: =IF(OR(OP!$D$53=1,$B14="",ISERROR(VLOOKUP(OP!$C$55,SRV,$B14+1,0))),"",N($G13)+N($F14)) | H14: =IF(OR(OP!$D$53=1,$B14=""),"",ROUND(VLOOKUP(OP!$C$55,DIE,$B14+1,0)*OP!$C$28,0)) -> #N/A | I14: =IF(OR(OP!$D$53=1,$B14=""),"",ROUND(VLOOKUP(OP!$C$55,CV,$B14+1,0)*OP!$C$28,0)) -> #N/A | J14: =IF(OR(OP!$D$53=1,$B14=""),"",ROUND(VLOOKUP(OP!$C$55,PA,$B14+1,0)*OP!$C$28,0)) -> #N/A | S14: =IF(OR(OP!$D$53=1,$B14=""),"",N($F14)+N($O14)) -> 0 | T14: =IF(OR(OP!$D$53=1,$B14=""),0,N($T13)+N($S14)) -> 0 | U14: =IF(OR(OP!$D$53=1,$B14=""),"",ROUND($S14/12,0)) -> 0 | V14: =IF(OR(OP!$D$53=1,$B14=""),0,N($V13)+(N($U14)*12)) -> 0 | Y14: =IF(OR(OP!$D$53=1,$B14=""),"",ROUND(($H14+$Q14)*IF(OR($C14<16,$Z14=0,$Z14=""),1,PYO),0)) -> #N/A | Z14: =IF(OR(OP!$D$53=1,$B14=""),"",ROUND(($H14+Q14)*IF(OR($C14<16,($H14+$Q14)*PY!$C$4<PY!$D$5,($H14+$Q14)*PY!$C$4*PYR<PY!$C$5),0,PYY)*PYR,0)) -> #N/A | AA14: =IF(OR(OP!$D$53=1,AND(B14>OP!$C$24)),"",OP!$C$52) -> 11326 | AB14: =IF(OR(OP!$D$53=1,$B14=""),"",N($AB13)+N($AA14)) -> 124586 | AH14: =IF(OR(OP!$D$53=1,$B14=""),"",ROUND(VLOOKUP(OP!$C$55,HL_1,$B14+1,0)*OP!$C$28,0)) -> #N/A | AI14: =IF(OR(OP!$D$53=1,$B14=""),"",ROUND(VLOOKUP(OP!$C$55,HL_2,$B14+1,0)*OP!$C$28,0)) -> #N/A
B15: =IF(OR(C14>=OP!$F$57,C14=""),"",IF(C14+1>OP!$F$57,OP!$F$57+1-$C$4,B14+1)) -> 12 | C15: =IF(OR(OP!$D$53=1,MAX($C$4:C14)>=OP!$F$57),"",C14+(B15-B14)) -> 26 | D15: =IF(OR(OP!$D$53=1,AND($B15>OP!$C$24)),"",OP!$C$52-IF($C15<16,$K14,0)) -> 11326 | E15: =IF(OR(OP!$D$53=1,$B15=""),"",N($E14)+N($D15)) -> 135912 | F15: =IF(OR(OP!$D$53=1,$B15="",ISERROR(VLOOKUP(OP!$C$55,SRV,$B15+1,0))),"",ROUND(VLOOKUP(OP!$C$55,SRV,$B15+1,0)*OP!$C$28,0)) | G15: =IF(OR(OP!$D$53=1,$B15="",ISERROR(VLOOKUP(OP!$C$55,SRV,$B15+1,0))),"",N($G14)+N($F15)) | H15: =IF(OR(OP!$D$53=1,$B15=""),"",ROUND(VLOOKUP(OP!$C$55,DIE,$B15+1,0)*OP!$C$28,0)) -> #N/A | I15: =IF(OR(OP!$D$53=1,$B15=""),"",ROUND(VLOOKUP(OP!$C$55,CV,$B15+1,0)*OP!$C$28,0)) -> #N/A | J15: =IF(OR(OP!$D$53=1,$B15=""),"",ROUND(VLOOKUP(OP!$C$55,PA,$B15+1,0)*OP!$C$28,0)) -> #N/A | S15: =IF(OR(OP!$D$53=1,$B15=""),"",N($F15)+N($O15)) -> 0 | T15: =IF(OR(OP!$D$53=1,$B15=""),0,N($T14)+N($S15)) -> 0 | U15: =IF(OR(OP!$D$53=1,$B15=""),"",ROUND($S15/12,0)) -> 0 | V15: =IF(OR(OP!$D$53=1,$B15=""),0,N($V14)+(N($U15)*12)) -> 0 | Y15: =IF(OR(OP!$D$53=1,$B15=""),"",ROUND(($H15+$Q15)*IF(OR($C15<16,$Z15=0,$Z15=""),1,PYO),0)) -> #N/A | Z15: =IF(OR(OP!$D$53=1,$B15=""),"",ROUND(($H15+Q15)*IF(OR($C15<16,($H15+$Q15)*PY!$C$4<PY!$D$5,($H15+$Q15)*PY!$C$4*PYR<PY!$C$5),0,PYY)*PYR,0)) -> #N/A | AA15: =IF(OR(OP!$D$53=1,AND(B15>OP!$C$24)),"",OP!$C$52) -> 11326 | AB15: =IF(OR(OP!$D$53=1,$B15=""),"",N($AB14)+N($AA15)) -> 135912 | AH15: =IF(OR(OP!$D$53=1,$B15=""),"",ROUND(VLOOKUP(OP!$C$55,HL_1,$B15+1,0)*OP!$C$28,0)) -> #N/A | AI15: =IF(OR(OP!$D$53=1,$B15=""),"",ROUND(VLOOKUP(OP!$C$55,HL_2,$B15+1,0)*OP!$C$28,0)) -> #N/A
B16: =IF(OR(C15>=OP!$F$57,C15=""),"",IF(C15+1>OP!$F$57,OP!$F$57+1-$C$4,B15+1)) -> 13 | C16: =IF(OR(OP!$D$53=1,MAX($C$4:C15)>=OP!$F$57),"",C15+(B16-B15)) -> 27 | D16: =IF(OR(OP!$D$53=1,AND($B16>OP!$C$24)),"",OP!$C$52-IF($C16<16,$K15,0)) -> 11326 | E16: =IF(OR(OP!$D$53=1,$B16=""),"",N($E15)+N($D16)) -> 147238 | F16: =IF(OR(OP!$D$53=1,$B16="",ISERROR(VLOOKUP(OP!$C$55,SRV,$B16+1,0))),"",ROUND(VLOOKUP(OP!$C$55,SRV,$B16+1,0)*OP!$C$28,0)) | G16: =IF(OR(OP!$D$53=1,$B16="",ISERROR(VLOOKUP(OP!$C$55,SRV,$B16+1,0))),"",N($G15)+N($F16)) | H16: =IF(OR(OP!$D$53=1,$B16=""),"",ROUND(VLOOKUP(OP!$C$55,DIE,$B16+1,0)*OP!$C$28,0)) -> #N/A | I16: =IF(OR(OP!$D$53=1,$B16=""),"",ROUND(VLOOKUP(OP!$C$55,CV,$B16+1,0)*OP!$C$28,0)) -> #N/A | J16: =IF(OR(OP!$D$53=1,$B16=""),"",ROUND(VLOOKUP(OP!$C$55,PA,$B16+1,0)*OP!$C$28,0)) -> #N/A | S16: =IF(OR(OP!$D$53=1,$B16=""),"",N($F16)+N($O16)) -> 0 | T16: =IF(OR(OP!$D$53=1,$B16=""),0,N($T15)+N($S16)) -> 0 | U16: =IF(OR(OP!$D$53=1,$B16=""),"",ROUND($S16/12,0)) -> 0 | V16: =IF(OR(OP!$D$53=1,$B16=""),0,N($V15)+(N($U16)*12)) -> 0 | Y16: =IF(OR(OP!$D$53=1,$B16=""),"",ROUND(($H16+$Q16)*IF(OR($C16<16,$Z16=0,$Z16=""),1,PYO),0)) -> #N/A | Z16: =IF(OR(OP!$D$53=1,$B16=""),"",ROUND(($H16+Q16)*IF(OR($C16<16,($H16+$Q16)*PY!$C$4<PY!$D$5,($H16+$Q16)*PY!$C$4*PYR<PY!$C$5),0,PYY)*PYR,0)) -> #N/A | AA16: =IF(OR(OP!$D$53=1,AND(B16>OP!$C$24)),"",OP!$C$52) -> 11326 | AB16: =IF(OR(OP!$D$53=1,$B16=""),"",N($AB15)+N($AA16)) -> 147238 | AH16: =IF(OR(OP!$D$53=1,$B16=""),"",ROUND(VLOOKUP(OP!$C$55,HL_1,$B16+1,0)*OP!$C$28,0)) -> #N/A | AI16: =IF(OR(OP!$D$53=1,$B16=""),"",ROUND(VLOOKUP(OP!$C$55,HL_2,$B16+1,0)*OP!$C$28,0)) -> #N/A
B17: =IF(OR(C16>=OP!$F$57,C16=""),"",IF(C16+1>OP!$F$57,OP!$F$57+1-$C$4,B16+1)) -> 14 | C17: =IF(OR(OP!$D$53=1,MAX($C$4:C16)>=OP!$F$57),"",C16+(B17-B16)) -> 28 | D17: =IF(OR(OP!$D$53=1,AND($B17>OP!$C$24)),"",OP!$C$52-IF($C17<16,$K16,0)) -> 11326 | E17: =IF(OR(OP!$D$53=1,$B17=""),"",N($E16)+N($D17)) -> 158564 | F17: =IF(OR(OP!$D$53=1,$B17="",ISERROR(VLOOKUP(OP!$C$55,SRV,$B17+1,0))),"",ROUND(VLOOKUP(OP!$C$55,SRV,$B17+1,0)*OP!$C$28,0)) | G17: =IF(OR(OP!$D$53=1,$B17="",ISERROR(VLOOKUP(OP!$C$55,SRV,$B17+1,0))),"",N($G16)+N($F17)) | H17: =IF(OR(OP!$D$53=1,$B17=""),"",ROUND(VLOOKUP(OP!$C$55,DIE,$B17+1,0)*OP!$C$28,0)) -> #N/A | I17: =IF(OR(OP!$D$53=1,$B17=""),"",ROUND(VLOOKUP(OP!$C$55,CV,$B17+1,0)*OP!$C$28,0)) -> #N/A | J17: =IF(OR(OP!$D$53=1,$B17=""),"",ROUND(VLOOKUP(OP!$C$55,PA,$B17+1,0)*OP!$C$28,0)) -> #N/A | S17: =IF(OR(OP!$D$53=1,$B17=""),"",N($F17)+N($O17)) -> 0 | T17: =IF(OR(OP!$D$53=1,$B17=""),0,N($T16)+N($S17)) -> 0 | U17: =IF(OR(OP!$D$53=1,$B17=""),"",ROUND($S17/12,0)) -> 0 | V17: =IF(OR(OP!$D$53=1,$B17=""),0,N($V16)+(N($U17)*12)) -> 0 | Y17: =IF(OR(OP!$D$53=1,$B17=""),"",ROUND(($H17+$Q17)*IF(OR($C17<16,$Z17=0,$Z17=""),1,PYO),0)) -> #N/A | Z17: =IF(OR(OP!$D$53=1,$B17=""),"",ROUND(($H17+Q17)*IF(OR($C17<16,($H17+$Q17)*PY!$C$4<PY!$D$5,($H17+$Q17)*PY!$C$4*PYR<PY!$C$5),0,PYY)*PYR,0)) -> #N/A | AA17: =IF(OR(OP!$D$53=1,AND(B17>OP!$C$24)),"",OP!$C$52) -> 11326 | AB17: =IF(OR(OP!$D$53=1,$B17=""),"",N($AB16)+N($AA17)) -> 158564 | AH17: =IF(OR(OP!$D$53=1,$B17=""),"",ROUND(VLOOKUP(OP!$C$55,HL_1,$B17+1,0)*OP!$C$28,0)) -> #N/A | AI17: =IF(OR(OP!$D$53=1,$B17=""),"",ROUND(VLOOKUP(OP!$C$55,HL_2,$B17+1,0)*OP!$C$28,0)) -> #N/A
... B113: =IF(OR(C112>=OP!$F$57,C112=""),"",IF(C112+1>OP!$F$57,OP!$F$57+1-$C$4,B112+1)) | C113: =IF(OR(OP!$D$53=1,MAX($C$4:C112)>=OP!$F$57),"",C112+(B113-B112)) | D113: =IF(OR(OP!$D$53=1,AND($B113>OP!$C$24)),"",OP!$C$52-IF($C113<16,$K112,0)) | E113: =IF(OR(OP!$D$53=1,$B113=""),"",N($E112)+N($D113)) | F113: =IF(OR(OP!$D$53=1,$B113="",ISERROR(VLOOKUP(OP!$C$55,SRV,$B113+1,0))),"",ROUND(VLOOKUP(OP!$C$55,SRV,$B113+1,0)*OP!$C$28,0)) | G113: =IF(OR(OP!$D$53=1,$B113="",ISERROR(VLOOKUP(OP!$C$55,SRV,$B113+1,0))),"",N($G112)+N($F113)) | H113: =IF(OR(OP!$D$53=1,$B113=""),"",ROUND(VLOOKUP(OP!$C$55,DIE,$B113+1,0)*OP!$C$28,0)) | I113: =IF(OR(OP!$D$53=1,$B113=""),"",ROUND(VLOOKUP(OP!$C$55,CV,$B113+1,0)*OP!$C$28,0)) | J113: =IF(OR(OP!$D$53=1,$B113=""),"",ROUND(VLOOKUP(OP!$C$55,PA,$B113+1,0)*OP!$C$28,0)) | S113: =IF(OR(OP!$D$53=1,$B113=""),"",N($F113)+N($O113)) | T113: =IF(OR(OP!$D$53=1,$B113=""),0,N($T112)+N($S113)) -> 0 | U113: =IF(OR(OP!$D$53=1,$B113=""),"",ROUND($S113/12,0)) | V113: =IF(OR(OP!$D$53=1,$B113=""),0,N($V112)+(N($U113)*12)) -> 0 | Y113: =IF(OR(OP!$D$53=1,$B113=""),"",ROUND(($H113+$Q113)*IF(OR($C113<16,$Z113=0,$Z113=""),1,PYO),0)) | Z113: =IF(OR(OP!$D$53=1,$B113=""),"",ROUND(($H113+Q113)*IF(OR($C113<16,($H113+$Q113)*PY!$C$4<PY!$D$5,($H113+$Q113)*PY!$C$4*PYR<PY!$C$5),0,PYY)*PYR,0)) | AA113: =IF(OR(OP!$D$53=1,AND(B113>OP!$C$24)),"",OP!$C$52) | AB113: =IF(OR(OP!$D$53=1,$B113=""),"",N($AB112)+N($AA113)) | AH113: =IF(OR(OP!$D$53=1,$B113=""),"",ROUND(VLOOKUP(OP!$C$55,HL_1,$B113+1,0)*OP!$C$28,0)) | AI113: =IF(OR(OP!$D$53=1,$B113=""),"",ROUND(VLOOKUP(OP!$C$55,HL_2,$B113+1,0)*OP!$C$28,0))
B114: =IF(OR(C113>=OP!$F$57,C113=""),"",IF(C113+1>OP!$F$57,OP!$F$57+1-$C$4,B113+1)) | C114: =IF(OR(OP!$D$53=1,MAX($C$4:C113)>=OP!$F$57),"",C113+(B114-B113)) | D114: =IF(OR(OP!$D$53=1,AND($B114>OP!$C$24)),"",OP!$C$52-IF($C114<16,$K113,0)) | E114: =IF(OR(OP!$D$53=1,$B114=""),"",N($E113)+N($D114)) | F114: =IF(OR(OP!$D$53=1,$B114="",ISERROR(VLOOKUP(OP!$C$55,SRV,$B114+1,0))),"",ROUND(VLOOKUP(OP!$C$55,SRV,$B114+1,0)*OP!$C$28,0)) | G114: =IF(OR(OP!$D$53=1,$B114="",ISERROR(VLOOKUP(OP!$C$55,SRV,$B114+1,0))),"",N($G113)+N($F114)) | H114: =IF(OR(OP!$D$53=1,$B114=""),"",ROUND(VLOOKUP(OP!$C$55,DIE,$B114+1,0)*OP!$C$28,0)) | I114: =IF(OR(OP!$D$53=1,$B114=""),"",ROUND(VLOOKUP(OP!$C$55,CV,$B114+1,0)*OP!$C$28,0)) | J114: =IF(OR(OP!$D$53=1,$B114=""),"",ROUND(VLOOKUP(OP!$C$55,PA,$B114+1,0)*OP!$C$28,0)) | K114: =IF(OR(OP!$D$53=1,B114=""),"",VLOOKUP($B114,more1,7,0)) | S114: =IF(OR(OP!$D$53=1,$B114=""),"",N($F114)+N($O114)) | T114: =IF(OR(OP!$D$53=1,$B114=""),0,N($T113)+N($S114)) -> 0 | U114: =IF(OR(OP!$D$53=1,$B114=""),"",ROUND($S114/12,0)) | V114: =IF(OR(OP!$D$53=1,$B114=""),0,N($V113)+(N($U114)*12)) -> 0 | Y114: =IF(OR(OP!$D$53=1,$B114=""),"",ROUND(($H114+$Q114)*IF(OR($C114<16,$Z114=0,$Z114=""),1,PYO),0)) | Z114: =IF(OR(OP!$D$53=1,$B114=""),"",ROUND(($H114+Q114)*IF(OR($C114<16,($H114+$Q114)*PY!$C$4<PY!$D$5,($H114+$Q114)*PY!$C$4*PYR<PY!$C$5),0,PYY)*PYR,0)) | AA114: =IF(OR(OP!$D$53=1,AND(B114>OP!$C$24)),"",OP!$C$52) | AB114: =IF(OR(OP!$D$53=1,$B114=""),"",N($AB113)+N($AA114)) | AH114: =IF(OR(OP!$D$53=1,$B114=""),"",ROUND(VLOOKUP(OP!$C$55,HL_1,$B114+1,0)*OP!$C$28,0)) | AI114: =IF(OR(OP!$D$53=1,$B114=""),"",ROUND(VLOOKUP(OP!$C$55,HL_2,$B114+1,0)*OP!$C$28,0))
B115: 祝壽保險金 | G115: =IF(OR(OP!$D$53=1,$B115="",ISERROR(VLOOKUP(OP!$C$55,SRV,$B115+1,0))),"",N($G114)+N($F115)) | H115: =IF(OR(OP!$D$53=1),"",ROUND(VLOOKUP(OP!$C$55,EXP,OP!$D$57+1,0)*OP!$C$28,0)) -> #N/A | P115: EXP
C130: 2 | D130: 7 | E130: 8 | F130: 18 | G130: 13 | H130: 16 | I130: 17 | J130: 0 | K130: 0 | L130: 0 | M130: 0 | N130: 0 | O130: 0 | P130: 0 | Q130: 0 | R130: 0 | S130: 0 | T130: 0
B131: 年度 | C131: =VLOOKUP($B131,TOV,C$130,0) -> #N/A | D131: =IF(ISERROR(VLOOKUP($B131,TOV,D$130,0)),"",VLOOKUP($B131,TOV,D$130,0)) | E131: =IF(ISERROR(VLOOKUP($B131,TOV,E$130,0)),"",VLOOKUP($B131,TOV,E$130,0)) | F131: =IF(ISERROR(VLOOKUP($B131,TOV,F$130,0)),"",VLOOKUP($B131,TOV,F$130,0)) | G131: =IF(ISERROR(VLOOKUP($B131,TOV,G$130,0)),"",VLOOKUP($B131,TOV,G$130,0)) | H131: =IF(ISERROR(VLOOKUP($B131,TOV,H$130,0)),"",VLOOKUP($B131,TOV,H$130,0)) | I131: =IF(ISERROR(VLOOKUP($B131,TOV,I$130,0)),"",VLOOKUP($B131,TOV,I$130,0)) | J131: =IF(ISERROR(VLOOKUP($B131,TOV,J$130,0)),"",VLOOKUP($B131,TOV,J$130,0)) | K131: =IF(ISERROR(VLOOKUP($B131,TOV,K$130,0)),"",VLOOKUP($B131,TOV,K$130,0)) | ... T131: =IF(ISERROR(VLOOKUP($B131,TOV,T$130,0)),"",VLOOKUP($B131,TOV,T$130,0))
B132: 1 | C132: =VLOOKUP($B132,TOV,C$130,0) -> 15 | D132: =IF(ISERROR(VLOOKUP($B132,TOV,D$130,0)),"",VLOOKUP($B132,TOV,D$130,0)) | E132: =IF(ISERROR(VLOOKUP($B132,TOV,E$130,0)),"",VLOOKUP($B132,TOV,E$130,0)) | F132: =IF(ISERROR(VLOOKUP($B132,TOV,F$130,0)),"",VLOOKUP($B132,TOV,F$130,0)) -> 0 | G132: =IF(ISERROR(VLOOKUP($B132,TOV,G$130,0)),"",VLOOKUP($B132,TOV,G$130,0)) -> 0 | H132: =IF(ISERROR(VLOOKUP($B132,TOV,H$130,0)),"",VLOOKUP($B132,TOV,H$130,0)) -> 0 | I132: =IF(ISERROR(VLOOKUP($B132,TOV,I$130,0)),"",VLOOKUP($B132,TOV,I$130,0)) -> 0 | J132: =IF(ISERROR(VLOOKUP($B132,TOV,J$130,0)),"",VLOOKUP($B132,TOV,J$130,0)) | K132: =IF(ISERROR(VLOOKUP($B132,TOV,K$130,0)),"",VLOOKUP($B132,TOV,K$130,0)) | ... T132: =IF(ISERROR(VLOOKUP($B132,TOV,T$130,0)),"",VLOOKUP($B132,TOV,T$130,0))
B133: 2 | C133: =VLOOKUP($B133,TOV,C$130,0) -> 16 | D133: =IF(ISERROR(VLOOKUP($B133,TOV,D$130,0)),"",VLOOKUP($B133,TOV,D$130,0)) | E133: =IF(ISERROR(VLOOKUP($B133,TOV,E$130,0)),"",VLOOKUP($B133,TOV,E$130,0)) | F133: =IF(ISERROR(VLOOKUP($B133,TOV,F$130,0)),"",VLOOKUP($B133,TOV,F$130,0)) -> 0 | G133: =IF(ISERROR(VLOOKUP($B133,TOV,G$130,0)),"",VLOOKUP($B133,TOV,G$130,0)) -> 0 | H133: =IF(ISERROR(VLOOKUP($B133,TOV,H$130,0)),"",VLOOKUP($B133,TOV,H$130,0)) -> 0 | I133: =IF(ISERROR(VLOOKUP($B133,TOV,I$130,0)),"",VLOOKUP($B133,TOV,I$130,0)) -> 0 | J133: =IF(ISERROR(VLOOKUP($B133,TOV,J$130,0)),"",VLOOKUP($B133,TOV,J$130,0)) | K133: =IF(ISERROR(VLOOKUP($B133,TOV,K$130,0)),"",VLOOKUP($B133,TOV,K$130,0)) | ... T133: =IF(ISERROR(VLOOKUP($B133,TOV,T$130,0)),"",VLOOKUP($B133,TOV,T$130,0))
B134: 3 | C134: =VLOOKUP($B134,TOV,C$130,0) -> 17 | D134: =IF(ISERROR(VLOOKUP($B134,TOV,D$130,0)),"",VLOOKUP($B134,TOV,D$130,0)) | E134: =IF(ISERROR(VLOOKUP($B134,TOV,E$130,0)),"",VLOOKUP($B134,TOV,E$130,0)) | F134: =IF(ISERROR(VLOOKUP($B134,TOV,F$130,0)),"",VLOOKUP($B134,TOV,F$130,0)) -> 0 | G134: =IF(ISERROR(VLOOKUP($B134,TOV,G$130,0)),"",VLOOKUP($B134,TOV,G$130,0)) -> 0 | H134: =IF(ISERROR(VLOOKUP($B134,TOV,H$130,0)),"",VLOOKUP($B134,TOV,H$130,0)) -> 0 | I134: =IF(ISERROR(VLOOKUP($B134,TOV,I$130,0)),"",VLOOKUP($B134,TOV,I$130,0)) -> 0 | J134: =IF(ISERROR(VLOOKUP($B134,TOV,J$130,0)),"",VLOOKUP($B134,TOV,J$130,0)) | K134: =IF(ISERROR(VLOOKUP($B134,TOV,K$130,0)),"",VLOOKUP($B134,TOV,K$130,0)) | ... T134: =IF(ISERROR(VLOOKUP($B134,TOV,T$130,0)),"",VLOOKUP($B134,TOV,T$130,0))
B135: 4 | C135: =VLOOKUP($B135,TOV,C$130,0) -> 18 | D135: =IF(ISERROR(VLOOKUP($B135,TOV,D$130,0)),"",VLOOKUP($B135,TOV,D$130,0)) | E135: =IF(ISERROR(VLOOKUP($B135,TOV,E$130,0)),"",VLOOKUP($B135,TOV,E$130,0)) | F135: =IF(ISERROR(VLOOKUP($B135,TOV,F$130,0)),"",VLOOKUP($B135,TOV,F$130,0)) -> 0 | G135: =IF(ISERROR(VLOOKUP($B135,TOV,G$130,0)),"",VLOOKUP($B135,TOV,G$130,0)) -> 0 | H135: =IF(ISERROR(VLOOKUP($B135,TOV,H$130,0)),"",VLOOKUP($B135,TOV,H$130,0)) -> 0 | I135: =IF(ISERROR(VLOOKUP($B135,TOV,I$130,0)),"",VLOOKUP($B135,TOV,I$130,0)) -> 0 | J135: =IF(ISERROR(VLOOKUP($B135,TOV,J$130,0)),"",VLOOKUP($B135,TOV,J$130,0)) | K135: =IF(ISERROR(VLOOKUP($B135,TOV,K$130,0)),"",VLOOKUP($B135,TOV,K$130,0)) | ... T135: =IF(ISERROR(VLOOKUP($B135,TOV,T$130,0)),"",VLOOKUP($B135,TOV,T$130,0))
B136: 5 | C136: =VLOOKUP($B136,TOV,C$130,0) -> 19 | D136: =IF(ISERROR(VLOOKUP($B136,TOV,D$130,0)),"",VLOOKUP($B136,TOV,D$130,0)) | E136: =IF(ISERROR(VLOOKUP($B136,TOV,E$130,0)),"",VLOOKUP($B136,TOV,E$130,0)) | F136: =IF(ISERROR(VLOOKUP($B136,TOV,F$130,0)),"",VLOOKUP($B136,TOV,F$130,0)) -> 0 | G136: =IF(ISERROR(VLOOKUP($B136,TOV,G$130,0)),"",VLOOKUP($B136,TOV,G$130,0)) -> 0 | H136: =IF(ISERROR(VLOOKUP($B136,TOV,H$130,0)),"",VLOOKUP($B136,TOV,H$130,0)) -> 0 | I136: =IF(ISERROR(VLOOKUP($B136,TOV,I$130,0)),"",VLOOKUP($B136,TOV,I$130,0)) -> 0 | J136: =IF(ISERROR(VLOOKUP($B136,TOV,J$130,0)),"",VLOOKUP($B136,TOV,J$130,0)) | K136: =IF(ISERROR(VLOOKUP($B136,TOV,K$130,0)),"",VLOOKUP($B136,TOV,K$130,0)) | ... T136: =IF(ISERROR(VLOOKUP($B136,TOV,T$130,0)),"",VLOOKUP($B136,TOV,T$130,0))
B137: 6 | C137: =VLOOKUP($B137,TOV,C$130,0) -> 20 | D137: =IF(ISERROR(VLOOKUP($B137,TOV,D$130,0)),"",VLOOKUP($B137,TOV,D$130,0)) | E137: =IF(ISERROR(VLOOKUP($B137,TOV,E$130,0)),"",VLOOKUP($B137,TOV,E$130,0)) | F137: =IF(ISERROR(VLOOKUP($B137,TOV,F$130,0)),"",VLOOKUP($B137,TOV,F$130,0)) -> 0 | G137: =IF(ISERROR(VLOOKUP($B137,TOV,G$130,0)),"",VLOOKUP($B137,TOV,G$130,0)) -> 0 | H137: =IF(ISERROR(VLOOKUP($B137,TOV,H$130,0)),"",VLOOKUP($B137,TOV,H$130,0)) -> 0 | I137: =IF(ISERROR(VLOOKUP($B137,TOV,I$130,0)),"",VLOOKUP($B137,TOV,I$130,0)) -> 0 | J137: =IF(ISERROR(VLOOKUP($B137,TOV,J$130,0)),"",VLOOKUP($B137,TOV,J$130,0)) | K137: =IF(ISERROR(VLOOKUP($B137,TOV,K$130,0)),"",VLOOKUP($B137,TOV,K$130,0)) | ... T137: =IF(ISERROR(VLOOKUP($B137,TOV,T$130,0)),"",VLOOKUP($B137,TOV,T$130,0))
B138: 7 | C138: =VLOOKUP($B138,TOV,C$130,0) -> 21 | D138: =IF(ISERROR(VLOOKUP($B138,TOV,D$130,0)),"",VLOOKUP($B138,TOV,D$130,0)) | E138: =IF(ISERROR(VLOOKUP($B138,TOV,E$130,0)),"",VLOOKUP($B138,TOV,E$130,0)) | F138: =IF(ISERROR(VLOOKUP($B138,TOV,F$130,0)),"",VLOOKUP($B138,TOV,F$130,0)) -> 0 | G138: =IF(ISERROR(VLOOKUP($B138,TOV,G$130,0)),"",VLOOKUP($B138,TOV,G$130,0)) -> 0 | H138: =IF(ISERROR(VLOOKUP($B138,TOV,H$130,0)),"",VLOOKUP($B138,TOV,H$130,0)) -> 0 | I138: =IF(ISERROR(VLOOKUP($B138,TOV,I$130,0)),"",VLOOKUP($B138,TOV,I$130,0)) -> 0 | J138: =IF(ISERROR(VLOOKUP($B138,TOV,J$130,0)),"",VLOOKUP($B138,TOV,J$130,0)) | K138: =IF(ISERROR(VLOOKUP($B138,TOV,K$130,0)),"",VLOOKUP($B138,TOV,K$130,0)) | ... T138: =IF(ISERROR(VLOOKUP($B138,TOV,T$130,0)),"",VLOOKUP($B138,TOV,T$130,0))
B139: 8 | C139: =VLOOKUP($B139,TOV,C$130,0) -> 22 | D139: =IF(ISERROR(VLOOKUP($B139,TOV,D$130,0)),"",VLOOKUP($B139,TOV,D$130,0)) | E139: =IF(ISERROR(VLOOKUP($B139,TOV,E$130,0)),"",VLOOKUP($B139,TOV,E$130,0)) | F139: =IF(ISERROR(VLOOKUP($B139,TOV,F$130,0)),"",VLOOKUP($B139,TOV,F$130,0)) -> 0 | G139: =IF(ISERROR(VLOOKUP($B139,TOV,G$130,0)),"",VLOOKUP($B139,TOV,G$130,0)) -> 0 | H139: =IF(ISERROR(VLOOKUP($B139,TOV,H$130,0)),"",VLOOKUP($B139,TOV,H$130,0)) -> 0 | I139: =IF(ISERROR(VLOOKUP($B139,TOV,I$130,0)),"",VLOOKUP($B139,TOV,I$130,0)) -> 0 | J139: =IF(ISERROR(VLOOKUP($B139,TOV,J$130,0)),"",VLOOKUP($B139,TOV,J$130,0)) | K139: =IF(ISERROR(VLOOKUP($B139,TOV,K$130,0)),"",VLOOKUP($B139,TOV,K$130,0)) | ... T139: =IF(ISERROR(VLOOKUP($B139,TOV,T$130,0)),"",VLOOKUP($B139,TOV,T$130,0))
B140: 9 | C140: =VLOOKUP($B140,TOV,C$130,0) -> 23 | D140: =IF(ISERROR(VLOOKUP($B140,TOV,D$130,0)),"",VLOOKUP($B140,TOV,D$130,0)) | E140: =IF(ISERROR(VLOOKUP($B140,TOV,E$130,0)),"",VLOOKUP($B140,TOV,E$130,0)) | F140: =IF(ISERROR(VLOOKUP($B140,TOV,F$130,0)),"",VLOOKUP($B140,TOV,F$130,0)) -> 0 | G140: =IF(ISERROR(VLOOKUP($B140,TOV,G$130,0)),"",VLOOKUP($B140,TOV,G$130,0)) -> 0 | H140: =IF(ISERROR(VLOOKUP($B140,TOV,H$130,0)),"",VLOOKUP($B140,TOV,H$130,0)) -> 0 | I140: =IF(ISERROR(VLOOKUP($B140,TOV,I$130,0)),"",VLOOKUP($B140,TOV,I$130,0)) -> 0 | J140: =IF(ISERROR(VLOOKUP($B140,TOV,J$130,0)),"",VLOOKUP($B140,TOV,J$130,0)) | K140: =IF(ISERROR(VLOOKUP($B140,TOV,K$130,0)),"",VLOOKUP($B140,TOV,K$130,0)) | ... T140: =IF(ISERROR(VLOOKUP($B140,TOV,T$130,0)),"",VLOOKUP($B140,TOV,T$130,0))
B141: 10 | C141: =VLOOKUP($B141,TOV,C$130,0) -> 24 | D141: =IF(ISERROR(VLOOKUP($B141,TOV,D$130,0)),"",VLOOKUP($B141,TOV,D$130,0)) | E141: =IF(ISERROR(VLOOKUP($B141,TOV,E$130,0)),"",VLOOKUP($B141,TOV,E$130,0)) | F141: =IF(ISERROR(VLOOKUP($B141,TOV,F$130,0)),"",VLOOKUP($B141,TOV,F$130,0)) -> 0 | G141: =IF(ISERROR(VLOOKUP($B141,TOV,G$130,0)),"",VLOOKUP($B141,TOV,G$130,0)) -> 0 | H141: =IF(ISERROR(VLOOKUP($B141,TOV,H$130,0)),"",VLOOKUP($B141,TOV,H$130,0)) -> 0 | I141: =IF(ISERROR(VLOOKUP($B141,TOV,I$130,0)),"",VLOOKUP($B141,TOV,I$130,0)) -> 0 | J141: =IF(ISERROR(VLOOKUP($B141,TOV,J$130,0)),"",VLOOKUP($B141,TOV,J$130,0)) | K141: =IF(ISERROR(VLOOKUP($B141,TOV,K$130,0)),"",VLOOKUP($B141,TOV,K$130,0)) | ... T141: =IF(ISERROR(VLOOKUP($B141,TOV,T$130,0)),"",VLOOKUP($B141,TOV,T$130,0))
B142: 20 | C142: =VLOOKUP($B142,TOV,C$130,0) -> 34 | D142: =IF(ISERROR(VLOOKUP($B142,TOV,D$130,0)),"",VLOOKUP($B142,TOV,D$130,0)) | E142: =IF(ISERROR(VLOOKUP($B142,TOV,E$130,0)),"",VLOOKUP($B142,TOV,E$130,0)) | F142: =IF(ISERROR(VLOOKUP($B142,TOV,F$130,0)),"",VLOOKUP($B142,TOV,F$130,0)) -> 0 | G142: =IF(ISERROR(VLOOKUP($B142,TOV,G$130,0)),"",VLOOKUP($B142,TOV,G$130,0)) -> 0 | H142: =IF(ISERROR(VLOOKUP($B142,TOV,H$130,0)),"",VLOOKUP($B142,TOV,H$130,0)) -> 0 | I142: =IF(ISERROR(VLOOKUP($B142,TOV,I$130,0)),"",VLOOKUP($B142,TOV,I$130,0)) -> 0 | J142: =IF(ISERROR(VLOOKUP($B142,TOV,J$130,0)),"",VLOOKUP($B142,TOV,J$130,0)) | K142: =IF(ISERROR(VLOOKUP($B142,TOV,K$130,0)),"",VLOOKUP($B142,TOV,K$130,0)) | ... T142: =IF(ISERROR(VLOOKUP($B142,TOV,T$130,0)),"",VLOOKUP($B142,TOV,T$130,0))
B143: 30 | C143: =VLOOKUP($B143,TOV,C$130,0) -> 44 | D143: =IF(ISERROR(VLOOKUP($B143,TOV,D$130,0)),"",VLOOKUP($B143,TOV,D$130,0)) | E143: =IF(ISERROR(VLOOKUP($B143,TOV,E$130,0)),"",VLOOKUP($B143,TOV,E$130,0)) | F143: =IF(ISERROR(VLOOKUP($B143,TOV,F$130,0)),"",VLOOKUP($B143,TOV,F$130,0)) -> 0 | G143: =IF(ISERROR(VLOOKUP($B143,TOV,G$130,0)),"",VLOOKUP($B143,TOV,G$130,0)) -> 0 | H143: =IF(ISERROR(VLOOKUP($B143,TOV,H$130,0)),"",VLOOKUP($B143,TOV,H$130,0)) -> 0 | I143: =IF(ISERROR(VLOOKUP($B143,TOV,I$130,0)),"",VLOOKUP($B143,TOV,I$130,0)) -> 0 | J143: =IF(ISERROR(VLOOKUP($B143,TOV,J$130,0)),"",VLOOKUP($B143,TOV,J$130,0)) | K143: =IF(ISERROR(VLOOKUP($B143,TOV,K$130,0)),"",VLOOKUP($B143,TOV,K$130,0)) | ... T143: =IF(ISERROR(VLOOKUP($B143,TOV,T$130,0)),"",VLOOKUP($B143,TOV,T$130,0))
... B148: 76 | C148: =VLOOKUP($B148,TOV,C$130,0) -> #N/A | D148: =IF(ISERROR(VLOOKUP($B148,TOV,D$130,0)),"",VLOOKUP($B148,TOV,D$130,0)) | E148: =IF(ISERROR(VLOOKUP($B148,TOV,E$130,0)),"",VLOOKUP($B148,TOV,E$130,0)) | F148: =IF(ISERROR(VLOOKUP($B148,TOV,F$130,0)),"",VLOOKUP($B148,TOV,F$130,0)) | G148: =IF(ISERROR(VLOOKUP($B148,TOV,G$130,0)),"",VLOOKUP($B148,TOV,G$130,0)) | H148: =IF(ISERROR(VLOOKUP($B148,TOV,H$130,0)),"",VLOOKUP($B148,TOV,H$130,0)) | I148: =IF(ISERROR(VLOOKUP($B148,TOV,I$130,0)),"",VLOOKUP($B148,TOV,I$130,0)) | J148: =IF(ISERROR(VLOOKUP($B148,TOV,J$130,0)),"",VLOOKUP($B148,TOV,J$130,0)) | K148: =IF(ISERROR(VLOOKUP($B148,TOV,K$130,0)),"",VLOOKUP($B148,TOV,K$130,0)) | ... T148: =IF(ISERROR(VLOOKUP($B148,TOV,T$130,0)),"",VLOOKUP($B148,TOV,T$130,0))

Sheet OP
B1: 非連生：1、連生：2 | S1: 控制項目 | AA1: 被保險人2 | AB1: 姓名 | AC1: =輸入頁!$E$8 -> 客戶 | BA1: 一銀 | BH1: 上銀
B2: 1 | C2: 試算日 | D2: 生日 | E2: 驗證 | H2: 彈性繳 | I2: 1 | J2: 1 | K2: 1 | S2: 性別：En_Sex | T2: 繳別：En_PayT | U2: 繳費方式-首期：En_PayMF | V2: 繳費方式-續期：En_PayMR | W2: 給付方式：En_BFM | AB2: fubon | AC2: 試算日 | AD2: 生日 | AE2: 驗證 | AL2: =$C$69 -> 銀保 | BA2: 險種 | BB2: 最低年齡 | BC2: 最高年齡 | BD2: 最長年期 | BE2: 通算保額係數 | BF2: 通算保額係數欄位判定 | BH2: 商品別： | BI2: =$C$21 -> 1
B3: =IF(C4=0,0,VALUE(MID(C4,IF(LEN(C4)=7,4,3),2))) -> 1 | C3: =IF(input_s!H8=1,TODAY(),IF(TODAY()<DATE(2026,7,20),DATE(2026,7,20),TODAY())) -> 46259 | D3: =IF(C4=0,0,DATE(LEFT(C4,IF(LEN(C4)=7,3,2))+1911,MID(C4,IF(LEN(C4)=7,4,3),2),RIGHT(C4,2))) -> 40909 | E3: =IF(E4=1,0,IF(OR(B3=1,B3=3,B3=5,B3=7,B3=8,B3=10,B3=12),31,IF(OR(B3=4,B3=6,B3=9,B3=11),30,IF(OR(AND(B3=2,YEAR(D3)=2000),AND(B3=2,YEAR(D3)/4=INT(YEAR(D3)/4),YEAR(D3)/400<>INT(YEAR(D3)/400))),29,28)))) -> 31 | F3: =YEAR(TODAY())-1911 -> 115 | H3: 躉繳 | I3: 1 | J3: 1 | K3: 1 | S3: 男 | T3: 彈性繳 | U3: =IF($C$21=1,"匯款","外幣匯款") -> 匯款 | V3: 金融機構轉帳 | W3: 購買增額繳清保險金額 | AB3: =IF(AC4=0,0,VALUE(MID(AC4,IF(LEN(AC4)=7,4,3),2))) -> 11 | AD3: =IF(AC4=0,0,DATE(LEFT(AC4,IF(LEN(AC4)=7,3,2))+1911,MID(AC4,IF(LEN(AC4)=7,4,3),2),RIGHT(AC4,2))) -> 40118 | AE3: =IF(AE4=1,0,IF(OR(AB3=1,AB3=3,AB3=5,AB3=7,AB3=8,AB3=10,AB3=12),31,IF(OR(AB3=4,AB3=6,AB3=9,AB3=11),30,IF(OR(AND(AB3=2,YEAR(AD3)=2000),AND(AB3=2,YEAR(AD3)/4=INT(YEAR(AD3)/4),YEAR(AD3)/400<>INT(YEAR(AD3)/400))),29,28)))) -> 30 | AL3: 業務、服展、北富銀 | AM3: 業務、服展 | AN3: 北富銀 | AO3: 整銷 | AP3: 多元 | BA3: =PDSN1_1 -> LTT | BB3: =C16 -> 15 | BC3: =C15 -> 45 | BD3: =D57 -> 71 | BE3: =VLOOKUP($D$5,$H$75:$O$161,$BF$3,0) -> 100 | BF3: =IF($C$18=1,6,7) -> 7 | BH3: 保險年齡： | BI3: =$D$5 -> 15
B4: 生日 | C4: =C10 -> 1010101 | D4: =DATE(YEAR(C3)-$C$15,MONTH(C3)-6,DAY(C3)) -> 29642 | E4: =IF(C4="",1,IF(OR(B3<1,B3>12),1,"")) | F4: =YEAR(D4)-1911 -> 70 | H4: 年繳 | I4: 1 | J4: 1 | K4: 1 | S4: 女 | T4: 躉繳 | U4: 金融機構轉帳 | V4: 自行繳費 | W4: 儲存生息 | AB4: 生日 | AC4: =AC10 -> 981101 | AE4: =IF(AC4="",1,IF(OR(AB3<1,AB3>12),1,"")) | AK4: =IF(OR($AL4="",COUNTIF($AL$3:$AR$3,$AL$2)=0),"",MAX($AK$3:AK3)+1) | AL4: 富邦人壽保險股份有限公司履行個人資料保護法告知說明書 | BA4: 免體減額度 | BB4: =VLOOKUP($D$5,$H$72:$N$161,5,0) -> 1000 | BC4: 匯率 | BD4: =C58 -> 1 | BH4: 保費： | BI4: =$C$31 -> 11440
B5: 最高承保 | C5: 保險 | D5: =IF(SUM(E6,D10:D13)>=1,"生日格式錯誤",IF(D3>C3,"被保險人未出生",IF(MONTH(C3)<B3,IF(OR(MONTH(C3)+12-B3>6,AND(MONTH(C3)+12-B3=6,DAY(C3)>DAY(D3))),YEAR(C3)-1-YEAR(D3)+1,IF(OR(MONTH(C3)+12-B3<6,AND(MONTH(C3)+12-B3=6,DAY(C3)<=DAY(D3))),YEAR(C3)-1-YEAR(D3))),IF(OR(MONTH(C3)-B3>6,AND(MONTH(C3)-B3=6,DAY(C3)>DAY(D3))),YEAR(C3)-YEAR(D3)+1,IF(OR(MONTH(C3)-B3<=6,AND(MONTH(C3)-B3=6,DAY(C3)<=DAY(D3))),YEAR(C3)-YEAR(D3),))))) -> 15 | E5: =IF(C4="",1,IF(OR(VALUE(RIGHT(C4,2))<1,VALUE(RIGHT(C4,2))>E3),1,"")) | F5: =MONTH(D4) -> 2 | H5: 半年繳 | I5: 0.52 | J5: 0.5 | K5: 2 | T5: 年繳 | U5: 富邦信用卡 | V5: 富邦信用卡 | W5: 現金給付 | AB5: 最高承保 | AC5: 保險 | AD5: =IF(SUM(AE6,AD10:AD13)>=1,"生日格式錯誤",IF(AD3>C3,"被保險人未出生",IF(MONTH(C3)<AB3,IF(OR(MONTH(C3)+12-AB3>6,AND(MONTH(C3)+12-AB3=6,DAY(C3)>DAY(AD3))),YEAR(C3)-1-YEAR(AD3)+1,IF(OR(MONTH(C3)+12-AB3<6,AND(MONTH(C3)+12-AB3=6,DAY(C3)<=DAY(AD3))),YEAR(C3)-1-YEAR(AD3))),IF(OR(MONTH(C3)-AB3>6,AND(MONTH(C3)-AB3=6,DAY(C3)>DAY(AD3))),YEAR(C3)-YEAR(AD3)+1,IF(OR(MONTH(C3)-AB3<=6,AND(MONTH(C3)-AB3=6,DAY(C3)<=DAY(AD3))),YEAR(C3)-YEAR(AD3),))))) -> 17 | AE5: =IF(AC4="",1,IF(OR(VALUE(RIGHT(AC4,2))<1,VALUE(RIGHT(AC4,2))>AE3),1,"")) | AK5: =IF(OR($AL5="",COUNTIF($AL$3:$AR$3,$AL$2)=0),"",MAX($AK$3:AK4)+1) | BA5: =IF($BA$8=1,IF($D$5>70,"本保件可能需要體檢。",IF($BB$5>$BB$4,"免體檢額度:新臺幣："&TEXT($BB$4,"#,##0萬")&"，本保件體檢保額:【投保金額*匯率*通算保額係數】=新臺幣："&TEXT($BB$5,IF(OP!$E$28=0,"#,##0","#,##0.0"))&"萬，本保件投保保額超過免體檢額度，可能需要體檢。","")),"") | BB5: =$C$28*$BE$3*BD4 -> 100 | BH5: 換算匯率： | BI5: =IF($BI$2=2,$C$58,1) -> 1
C6: 足歲 | D6: =IF(SUM(E6,D10:D13)>=1,"生日格式錯誤",IF(D3>C3,"被保險人未出生", YEAR($C$3)-YEAR($D$3)-1+IF(OR(MONTH($D$3)<MONTH($C$3),AND(MONTH($D$3)=MONTH($C$3),DAY($D$3)<=DAY($C$3))),1,0))) -> 14 | E6: =IF(OR(E4=1,E5=1),1,"") | F6: =DAY(D4) -> 25 | H6: 季繳 | I6: 0.262 | J6: 0.25 | K6: 4 | T6: 半年繳 | U6: 一般信用卡 | V6: 一般信用卡 | W6: 繳清保險金額 | AC6: 足歲 | AD6: =IF(SUM(AE6,AD10:AD13)>=1,"生日格式錯誤",IF(AD3>C3,"被保險人未出生",ROUNDDOWN(YEARFRAC(AD3,C3,1),0))) -> 16 | AE6: =IF(OR(AE4=1,AE5=1),1,"") | AK6: =IF(OR($AL6="",COUNTIF($AL$3:$AR$3,$AL$2)=0),"",MAX($AK$3:AK5)+1) | AL6: 富邦人壽保險股份有限公司（下稱本公司）依據個人資料保護法（以下稱個資法） | BH6: 繳別： | BI6: =IF($C$32="躉繳",1,2) -> 2 | BJ6: =$C$32 -> 年繳
B7: 1MAX | C7: =(F4&TEXT(F5,"00")&TEXT(F6,"00"))*1 -> 700225 | D7: 1MIN | E7: =(YEAR(TODAY())-1911&TEXT(MONTH(TODAY()),"00")&TEXT(DAY(TODAY()),"00"))*1 -> 1150825 | H7: 月繳 | I7: 0.088 | J7: 0.08333333 | K7: 12 | T7: 季繳 | AK7: =IF(OR($AL7="",COUNTIF($AL$3:$AR$3,$AL$2)=0),"",MAX($AK$3:AK6)+1) | AL7: 規定，向 台端告知下列事項，請 台端詳閱： | BA7: 顯示體檢(1：顯示，空：不顯示) | BH7: 發單後是否需要電訪： | BI7: =IF($BI$8="","否","是") -> 否
K8: 第一頁說明↓ | L8: 102警語↓ | M8: =COUNTA(L11:L12) -> 2 | T8: 月繳 | AK8: =IF(OR($AL8="",COUNTIF($AL$3:$AR$3,$AL$2)=0),"",MAX($AK$3:AK7)+1) | AL8: 一、蒐集之目的： | BH8: 電訪原因： | BI8: =IF(ISERROR(VLOOKUP(1,$BH$11:$BI$13,2,0)),"",VLOOKUP(1,$BH$11:$BI$13,2,0))
B9: 輸入格式選項 | C9: 1 | D9: 檢核欄位 | H9: 折扣使用 | I9: 首期 | J9: 續期 | K9: =K10&M10&K11&M11&K12&M12&K13&M13&D47 -> 繳費方式 1.0%折扣。 | L9: ="保費折扣" -> 保費折扣 | M9: =L10&M10&L11&M11&L12&M12&L13&"折扣" -> 繳費方式。折扣 | AD9: 檢核欄位 | AK9: =IF(OR($AL9="",COUNTIF($AL$3:$AR$3,$AL$2)=0),"",MAX($AK$3:AK8)+1) | AL9: （一）人身保險（００一） | BH9: ※請注意！上述的電訪提醒僅針對本試算表所輸入的資料進行初步判斷，實際發單後是否須要電訪本公司將會另行通知。
B10: 1.輸入格式1-6或7位數字輸入 | C10: =input_s!H24 -> 1010101 | D10: =IF(AND($C$9=1,OR(C10="",C10=0,LEN(C10)<6,LEN(C10)>IF(YEAR(TODAY())>2010,7,6))),1,"") | H10: 繳費方式 | I10: =$C$42 -> 0.01 | J10: =$C$44 -> 0.01 | K10: =IF(AND(I10>0,J10>0),""&H10&TEXT(I10," 0.0%")&"折扣",IF(AND(I10>0,J10=0),"首期"&H10&TEXT(I10," 0.0%")&"折扣",IF(AND(I10=0,J10>0),"續期"&H10&TEXT(J10," 0.0%")&"折扣",""))) -> 繳費方式 1.0%折扣 | L10: =IF(SUM(I10:J10)>0,H10,"") -> 繳費方式 | M10: =IF(L10="","",IF(SUM(N11:N13)>=2,"、",IF(SUM(N11:N13)=1,"及","。"))) -> 。 | N10: =IF(L10<>"",1,0) -> 1 | AB10: 1.輸入格式1-6或7位數字輸入 | AC10: =輸入頁!$N$8 -> 981101 | AD10: =IF(AND($C$9=1,OR(AC10="",AC10=0,LEN(AC10)<6,LEN(AC10)>IF(YEAR(TODAY())>2010,7,6))),1,"") | AK10: =IF(OR($AL10="",COUNTIF($AL$3:$AR$3,$AL$2)=0),"",MAX($AK$3:AK9)+1) | AL10: （二）其他經營合於營業登記項目或組織章程所定之業務（一八一）
B11: 2.輸入格式2-年月日 | H11: 高保額 | I11: =$C$37 -> 0 | J11: =$C$37 -> 0 | K11: =IF(AND(I11>0,J11>0),""&H11&TEXT(I11," 0.0%")&"折扣",IF(AND(I11>0,J11=0),"首期"&H11&TEXT(I11," 0.0%")&"折扣",IF(AND(I11=0,J11>0),"續期"&H11&TEXT(J11," 0.0%")&"折扣",""))) | L11: =IF(SUM(I11:J11)>0,H11,"") | M11: =IF(L11="","",IF(SUM(N12:N14)>=2,"、",IF(SUM(N12:N14)=1,"及","。"))) | N11: =IF(L11<>"",1,0) -> 0 | AB11: 2.輸入格式2-年月日 | AK11: =IF(OR($AL11="",COUNTIF($AL$3:$AR$3,$AL$2)=0),"",MAX($AK$3:AK10)+1) | AL11: 二、蒐集之個人資料類別： | BH11: =IF(AND($BI$2=1,$BI$3>=70,$BI$6<>1,$BI$4>=100000),1,"") | BI11: 被保險人達70歲(含)以上且年繳保險費達10萬元(含)以上
H12: 集體彙繳件 | I12: =$C$38 -> 0 | J12: =$C$39 -> 0 | K12: =IF(AND(I12>0,J12>0),""&H12&TEXT(I12," 0.0%")&"折扣",IF(AND(I12>0,J12=0),"首期"&H12&TEXT(I12," 0.0%")&"折扣",IF(AND(I12=0,J12>0),"續期"&H12&TEXT(J12," 0.0%")&"折扣",""))) | L12: =IF(SUM(I12:J12)>0,H12,"") | M12: =IF(L12="","",IF(SUM(N13:N15)>=2,"、",IF(SUM(N13:N15)=1,"及","。"))) | N12: =IF(L12<>"",1,0) -> 0 | AK12: =IF(OR($AL12="",COUNTIF($AL$3:$AR$3,$AL$2)=0),"",MAX($AK$3:AK11)+1) | AL12: （一）姓名。 | BH12: =IF(AND($BI$2=1,$BI$3>=70,$BI$6=1,$BI$4>=1000000),1,"") | BI12: 被保險人達70歲(含)以上且躉繳保險費達100萬(含)以上
H13: 員工轉帳件 | I13: =$C$40 -> 0 | J13: =$C$40 -> 0 | K13: =IF(AND(I13>0,J13>0),""&H13&TEXT(I13," 0.0%")&"折扣",IF(AND(I13>0,J13=0),"首期"&H13&TEXT(I13," 0.0%")&"折扣",IF(AND(I13=0,J13>0),"續期"&H13&TEXT(J13," 0.0%")&"折扣",IF(J27=1,"繳費方式不符合員工折扣保費規定","")))) | L13: =IF(SUM(I13:J13)>0,H13,"") | M13: =IF(L13="","",IF(SUM(N14:N16)>=2,"、",IF(SUM(N14:N16)=1,"及","。"))) | N13: =IF(L13<>"",1,0) -> 0 | AK13: =IF(OR($AL13="",COUNTIF($AL$3:$AR$3,$AL$2)=0),"",MAX($AK$3:AK12)+1) | AL13: （二）身分證統一編號。 | BH13: =IF(AND($BI$13<>""),1,"") | BI13: =IF(AND($BJ$13="",$BK$13=""),"","外幣非投資型商品"&$BJ$13&$BK$13) | BJ13: =IF(ISERROR(VLOOKUP(1,$BH$14:$BJ$16,2,0)),"",VLOOKUP(1,$BH$14:$BJ$16,2,0)&VLOOKUP(1,$BH$14:$BJ$16,3,0)) | BK13: =IF(ISERROR(VLOOKUP(2,$BB$24:$BZ$26,2,0)),"",VLOOKUP(2,$BH$14:$BJ$16,2,0)&VLOOKUP(2,$BH$14:$BJ$16,3,0))
B14: 生日檢核 | D14: =IF(SUM(E6,D10:D13)>=1,"*日期空白或格式錯誤*","") | AB14: 生日檢核 | AD14: =IF(SUM(AE6,AD10:AD13)>=1,"*日期空白或格式錯誤*","") | AK14: =IF(OR($AL14="",COUNTIF($AL$3:$AR$3,$AL$2)=0),"",MAX($AK$3:AK13)+1) | AL14: （三）地址。 | BH14: =IF(AND($BI$2=2,$BI$3>=70),1,"") | BI14: 被保險人年齡達70歲(含)以上 | BJ14: =IF(BH14="","",IF(MAX($BH$14:$BH$16)=1,"。","，"))
B15: 最高承保(保險年齡) | C15: =IF(OR($C$22="",$C$24=""),"",$M$42) -> 45 | D15: =IF(D5>C15,1,"") | E15: =IF(E16=1,"足歲","歲") -> 歲 | K15: 繳費方式、高保額及集體彙繳件折扣 | AB15: 最高承保(保險年齡) | AD15: =IF(AD5>C15,1,"") | AK15: =IF(OR($AL15="",COUNTIF($AL$3:$AR$3,$AL$2)=0),"",MAX($AK$3:AK14)+1) | AL15: （四）病歷、醫療、健康檢查 。 | BH15: =IF(AND($BI$2=2,$BI$6<>1,$BI$4*$BI$5>=300000),MAX($BH$14:$BH$14)+1,"") | BI15: 年繳保險費達新台幣30萬(含)以上 | BJ15: =IF(BH15="","",IF(MAX($BH$14:$BH$15)>=1,"。",""))
B16: ="最低承保"&IF(E16=1,"(足歲)","(保險年齡)") -> 最低承保(保險年齡) | C16: =IF(OR($C$22="",$C$24=""),"",$L$42) -> 15 | D16: =IF(IF(E16=1,D6,IF(E16=2,D5,0))<C16,1,"") | E16: 2 | N16: =IF(O16="","",MAX($N$2:N15)+1) | AB16: ="最低承保"&IF(E16=1,"(足歲)","(保險年齡)") -> 最低承保(保險年齡) | AD16: =IF(IF(E16=1,AD6,IF(E16=2,AD5,0))<C16,1,"") | AK16: =IF(OR($AL16="",COUNTIF($AL$3:$AR$3,$AL$2)=0),"",MAX($AK$3:AK15)+1) | AL16: （五）要保書、要保文件等其他基於保險契約所提供之個人資料。 | BH16: =IF(AND($BI$2=2,$BI$6=1,$BI$4*$BI$5>=1000000),MAX($BH$14:$BH$15)+1,"") | BI16: 躉繳保險費達新台幣100萬(含)以上 | BJ16: =IF(BH16="","",IF(MAX($BH$14:$BH$16)>=1,"。",""))
B17: 年齡檢核 | D17: =IF(SUM(D15:D16)>=1,"*年齡不符專案投保區間*","") | N17: =IF(O17="","",MAX($N$2:N16)+1) | AB17: 年齡檢核 | AD17: =IF(SUM(AD15:AD16)>=1,"*年齡不符專案投保區間*","") | AK17: =IF(OR($AL17="",COUNTIF($AL$3:$AR$3,$AL$2)=0),"",MAX($AK$3:AK16)+1) | AL17: 三、個人資料利用之期間、地區、對象、方式：
B18: 性別 (1.男 2.女) | C18: =IF($E$18="男",1,IF($E$18="女",2,0)) -> 2 | D18: =IF(COUNTIF(En_Sex,$E$18)<>1,1,"") | E18: =input_s!$H$22 -> 女 | N18: =IF(O18="","",MAX($N$2:N17)+1) | AB18: 性別 (1.男 2.女) | AC18: =IF($AE$18="男",1,IF($AE$18="女",2,0)) -> 1 | AD18: =IF(COUNTIF(En_Sex,$AE$18)<>1,1,"") | AE18: =輸入頁!$K$8 -> 男 | AK18: =IF(OR($AL18="",COUNTIF($AL$3:$AR$3,$AL$2)=0),"",MAX($AK$3:AK17)+1) | AL18: （一）期間：因執行業務所必須及依法令規定應為保存之期間。
B19: 性別檢核 | D19: =IF(D18=1,"*性別輸入錯誤*","") | H19: 繳費方式 | I19: 折扣率 | AB19: 性別檢核 | AD19: =IF(AD18=1,"*性別輸入錯誤*","") | AK19: =IF(OR($AL19="",COUNTIF($AL$3:$AR$3,$AL$2)=0),"",MAX($AK$3:AK18)+1) | AL19: （二）對象：本公司、中華民國人壽保險商業同業公會、財團法人保險事業發展
B20: 基本資料欄位檢核結果 | D20: =IF(SUM(E6,D10:D13,D15,D16,D18)>=1,1,"") | H20: =IF($C$21=1,"匯款","外幣匯款") -> 匯款 | I20: =IF($C$21=1,IF($C$24=1,0%,1%),IF($C$24=1,0%,IF($C$43=$H$21,1%,0%))) -> 0.01 | J20: ↓首期 | AB20: 基本資料欄位檢核結果 | AD20: =IF(SUM(AE6,AD10,AD15,AD16,AD18)>=1,1,"") | AK20: =IF(OR($AL20="",COUNTIF($AL$3:$AR$3,$AL$2)=0),"",MAX($AK$3:AK19)+1) | AL20: 中心、財團法人金融消費評議中心、業務委外機構、臺灣網路認證(股)公司、
B21: 計價幣別(1.台幣 2.外幣) | C21: 1 | D21: =IF(OR(C21="",C21<=0,C21>=3),1,"") | E21: 新臺幣 | H21: 金融機構轉帳 | I21: =IF($C$24=1,0%,1%) -> 0.01 | J21: 續期↓ | AB21: MAX-Y | AC21: =$F$57-AD5+1 -> 69 | AK21: =IF(OR($AL21="",COUNTIF($AL$3:$AR$3,$AL$2)=0),"",MAX($AK$3:AK20)+1) | AL21: 與本公司有再保業務往來之公司、依法有調查權機關或金融監理機關。
B22: 險種代號 | C22: =input_s!$H$34 -> LTT | D22: =IF(OR($C$22="",$C$22=0,ISERROR(VLOOKUP($C$22,$H$43:$H$62,1,0))),1,"") | H22: 富邦信用卡 | I22: =IF($C$21=1,IF($C$24=1,0%,1%),0%) -> 0.01 | AK22: =IF(OR($AL22="",COUNTIF($AL$3:$AR$3,$AL$2)=0),"",MAX($AK$3:AK21)+1)
B23: 商品中文名稱 | C23: 富邦人壽順馨久久長期照顧定期健康保險 | E23: =OP!$C$23&"建議書" -> 富邦人壽順馨久久長期照顧定期健康保險建議書 | H23: 一般信用卡 | I23: 0 | J23: ↑首期 | AK23: =IF(OR($AL23="",COUNTIF($AL$3:$AR$3,$AL$2)=0),"",MAX($AK$3:AK22)+1) | AL23: （三）地區：上述對象所在之地區。
B24: 年期 | C24: =IF(ISERROR(VLOOKUP(input_s!$H$35&$C22,$J$43:$J$62,1,0)),"",input_s!$H$35) -> 30 | D24: =IF(OR($C$24="",$C$24=0,COUNTIF($J$43:$J$62,$C$24&$C$22)<>1),1,"") | E24: =IF(OP!$C$24=1,"躉繳",IF(OP!$C$24>40,OP!$C$24&" 歲滿期",OP!$C$24&" 年期")) -> 30 年期 | H24: 自行繳費 | I24: =IF($C$21=1,IF($C$24=1,0%,1%),0%) -> 0.01 | AK24: =IF(OR($AL24="",COUNTIF($AL$3:$AR$3,$AL$2)=0),"",MAX($AK$3:AK23)+1) | AL24: （四）方式：合於法令規定之利用方式。
B25: 年期檢核 | D25: =IF(SUM(D24)>=1,"*年期選擇錯誤*","") | H25: 支票 | I25: 0 | J25: 續期↑ | AB25: 跳歲計算 | AC25: =DATE(YEAR($AD$3)+$AD$6,MONTH($AD$3)+6,MIN(DAY($AD$3),$AE$25)+1) -> 46144 | AD25: =MONTH($AD$3)+IF(MONTH($AD$3)<=6,6,-6) -> 5 | AE25: =IF(OR($AD$25=1,$AD$25=3,$AD$25=5,$AD$25=7,$AD$25=8,$AD$25=10,$AD$25=12),31,IF(OR($AD$25=4,$AD$25=6,$AD$25=9,$AD$25=11),30,IF(AND($AD$25=2,YEAR($C$3)/4=INT(YEAR($C$3)/4),YEAR($C$3)/400<>INT(YEAR($C$3)/400)),29,28))) -> 31 | AK25: =IF(OR($AL25="",COUNTIF($AL$3:$AR$3,$AL$2)=0),"",MAX($AK$3:AK24)+1) | AL25: 四、依據個資法第三條規定，台端就本公司保有 台端之個人資料得行使之權利及
B26: 最低保額 | C26: =IF(OR($C$22="",$C$24=""),"",$N$42) -> 0.5 | K26: 有折扣：1、2；無折扣：0 | AC26: =IF(AC25<$C$3,"",AC25-$C$3) | AD26: =IF(C85=0,"",IF(OR($D$53=1,AC26=""),"",IF(AND(AC26>=1,AC26<=30),"提醒您：被保險人"&$AC$1&"將於 "&MONTH(AC25)&" 月 "&DAY(AC25)&" 日 ( "&AC26&"天後 ) 保險年齡增加一歲"&IF(D85=0,"。","，"&$C$22&$C$32&"保險費"&IF($C$32="躉繳","","每期")&IF(AE27>=0,"增加 ","減少 ")&TEXT(AE27,"#,##0 元")&"。"),""))) | AK26: =IF(OR($AL26="",COUNTIF($AL$3:$AR$3,$AL$2)=0),"",MAX($AK$3:AK25)+1) | AL26: 方式：
B27: 最高保額 | C27: =IF(OR($C$22="",$C$24="",D20=1),,$O$42) -> 2 | D27: =IF(C28*10<>ROUNDUP(C28,$E$28)*10,1,"") | E27: 保額小數位數 | H27: 折扣選項 | I27: =輸入頁!$E$21 -> 無 | J27: =IF(ISNA(VLOOKUP($I$27,$H$28:$I$30,2,0)),0,VLOOKUP($I$27,$H$28:$I$30,2,0)) -> 0 | K27: =IF(AND($J$27=1,$C$40>0),1,IF(AND($J$27=2,OR($C$38>0,$C$39>0)),2,0)) -> 0 | AB27: 新年齡/保費/差異 | AC27: =C88 -> LTT300216 | AD27: =IF(ISNA(VLOOKUP(AC27,GP,2,0)),0,IF($C$21=1,ROUND(VLOOKUP(AC27,GP,2,0)*$C$28*$C$34,0),IF($C$21=2,ROUNDDOWN(VLOOKUP(AC27,GP,2,0)*$C$28*$C$34,0),""))) -> 11660 | AE27: =AD27-$C$35 -> 220 | AK27: =IF(OR($AL27="",COUNTIF($AL$3:$AR$3,$AL$2)=0),"",MAX($AK$3:AK26)+1) | AL27: （一）得向本公司行使之權利：
B28: 保額 | C28: =ROUND(input_s!$H$61,$E$28) -> 1 | D28: =IF(OR(C28="",C28=0,C28<C26,C28>C27,D27<>""),1,"") | E28: 1 | H28: 無 | I28: 0 | AK28: =IF(OR($AL28="",COUNTIF($AL$3:$AR$3,$AL$2)=0),"",MAX($AK$3:AK27)+1) | AL28: 1.向本公司查詢、請求閱覽或請求製給複製本。
B29: 保額檢核 | D29: =IF(SUM(D28)>=1,"*保額錯誤*","") | H29: 員工轉帳件 | I29: 1 | AK29: =IF(OR($AL29="",COUNTIF($AL$3:$AR$3,$AL$2)=0),"",MAX($AK$3:AK28)+1) | AL29: 2.向本公司請求補充或更正。
B30: 每萬保費 | C30: =IF(OR(C18=0,C22=0,D28=1),0,IF(ISNA(VLOOKUP($C$55,GP,2,0)),0,VLOOKUP($C$55,GP,2,0))) -> 11440 | H30: 集體彙繳件 | I30: 2 | AK30: =IF(OR($AL30="",COUNTIF($AL$3:$AR$3,$AL$2)=0),"",MAX($AK$3:AK29)+1) | AL30: 3.向本公司請求停止蒐集、處理或利用及請求刪除。
B31: 原始應繳保費 | C31: =IF($C$21=1,ROUND(C28*C30,1),IF(C21=2,ROUND(C28*C30,1),"")) -> 11440 | AK31: =IF(OR($AL31="",COUNTIF($AL$3:$AR$3,$AL$2)=0),"",MAX($AK$3:AK30)+1) | AL31: （二）行使權利之方式：
B32: 繳別 | C32: =IF(input_s!$H$40="","",input_s!$H$40) -> 年繳 | D32: =IF(OR(AND($C$24<>1,$C$32="躉繳"),COUNTIF(En_PayT,$C$32)<>1),1,"") | AK32: =IF(OR($AL32="",COUNTIF($AL$3:$AR$3,$AL$2)=0),"",MAX($AK$3:AK31)+1) | AL32: 您可以透過書面（包含電子郵件、傳真、電子文件）方式行使權利。
B33: 換算格式1.傳統 2.直接除 | C33: 1 | D33: =IF(OR(C33="",C33=0),1,"") | AK33: =IF(OR($AL33="",COUNTIF($AL$3:$AR$3,$AL$2)=0),"",MAX($AK$3:AK32)+1)
B34: 繳別換算率 | C34: =IF(D32=1,,VLOOKUP(C32,H2:K7,1+C33,FALSE)) -> 1 | AK34: =IF(OR($AL34="",COUNTIF($AL$3:$AR$3,$AL$2)=0),"",MAX($AK$3:AK33)+1) | AL34: 五、台端不提供個人資料所致權益之影響
B35: 應繳保費 | C35: =IF($C$21=1,ROUND(C31*C34,0),IF($C$21=2,ROUNDDOWN(C31*C34,0),"")) -> 11440 | D35: =IF($C$50=12,$C$35*2,$C$35*1) -> 11440 | E35: 月繳*2 ←1130126新增月繳倍數(紀錄單用) | AK35: =IF(OR($AL35="",COUNTIF($AL$3:$AR$3,$AL$2)=0),"",MAX($AK$3:AK34)+1) | AL35: 台端若未能提供相關個人資料時，本公司將可能延後或無法進行必要之審核
B36: 高保費折扣 | D36: 低<=保費<高 | AK36: =IF(OR($AL36="",COUNTIF($AL$3:$AR$3,$AL$2)=0),"",MAX($AK$3:AK35)+1) | AL36: 及處理作業，因此可能婉謝承保、遲延或無法承保。
B37: 高保額折扣 | C37: =IF(D64=1,,IF(AND($C$28>=50,$C$28<100),0%,IF(AND($C$28>=100),0%,0%))) -> 0 | D37: =IF(C37>0,"本保件享有 "&TEXT(C37,"0.0%")&" 高保額折扣","") | AK37: =IF(OR($AL37="",COUNTIF($AL$3:$AR$3,$AL$2)=0),"",MAX($AK$3:AK36)+1)
B38: 集彙折扣-首期 | D38: =IF(C38>0,"本主約首期保費享有 "&TEXT(C38,"0%")&" 集體彙繳折扣","") | H38: 預定利率 | I38: 儲存生息-1% | J38: 儲存生息 | AK38: =IF(OR($AL38="",COUNTIF($AL$3:$AR$3,$AL$2)=0),"",MAX($AK$3:AK37)+1)
B39: 集彙折扣-續期 | D39: =IF(C39>0,"本主約續期保費享有 "&TEXT(C39,"0%")&" 集體彙繳折扣","") | H39: =$K$42 -> 0 | I39: =TEXT(RDATA!$I$2-1%,"0.00%") -> 0.75% | J39: =TEXT(RDATA!$I$2,"0.00%") -> 1.75% | AK39: =IF(OR($AL39="",COUNTIF($AL$3:$AR$3,$AL$2)=0),"",MAX($AK$3:AK38)+1)
B40: 員工折扣 | C40: =IF(AND($J$27=1,C41=H21,OR(C43=H21,C43=H24)),IF($C$24=10,6%,IF($C$24=20,5%,IF($C$24=30,4%,0%))),0%) -> 0 | D40: =IF(C40>0,"本主約保費享有 "&TEXT(C40,"0.0%")&H29&"折扣","") | AK40: =IF(OR($AL40="",COUNTIF($AL$3:$AR$3,$AL$2)=0),"",MAX($AK$3:AK39)+1)
B41: 首期繳別 | C41: =input_s!$H$45 -> 匯款 | D41: =IF(COUNTIF(En_PayMF,$C$41)<>1,1,"") | H41: 險種代號 | I41: 年期 | J41: 險種代號+年期 | K41: 預定利率-2 | L41: 最低年齡-3 | M41: 最高年齡-4 | N41: 最低保額-5 | O41: 最高保額-6 | AK41: =IF(OR($AL41="",COUNTIF($AL$3:$AR$3,$AL$2)=0),"",MAX($AK$3:AK40)+1)
B42: 自繳折扣-首期 | C42: =IF(OR($K$27<>0,ISNA(VLOOKUP(C41,$H$19:$I$25,2,0))),0,VLOOKUP(C41,$H$19:$I$25,2,0)) -> 0.01 | D42: =IF(C42>0,"-首期享有1%繳別折扣-","") -> -首期享有1%繳別折扣- | H42: =$C$22 -> LTT | I42: =$C$24 -> 30 | J42: =$I42&$H42 -> 30LTT | K42: =VLOOKUP($J$42,$J$43:$O$62,2,0) -> 0 | L42: =VLOOKUP($J$42,$J$43:$O$62,3,0) -> 15 | M42: =VLOOKUP($J$42,$J$43:$O$62,4,0) -> 45 | N42: =VLOOKUP($J$42,$J$43:$O$62,5,0) -> 0.5 | O42: =VLOOKUP($J$42,$J$43:$O$62,6,0) -> 2 | AK42: =IF(OR($AL42="",COUNTIF($AL$3:$AR$3,$AL$2)=0),"",MAX($AK$3:AK41)+1)
B43: 續期繳別 | C43: =input_s!H53 -> 金融機構轉帳 | D43: =IF(AND($C$24<>1,COUNTIF(En_PayMR,$C$43)<>1),1,"") | H43: LTT | I43: 10 | J43: =$I43&$H43 -> 10LTT | K43: 0 | L43: 15 | M43: 65 | N43: 0.5 | O43: =VLOOKUP($F$55,$H$81:$I$161,2,0) -> 2 | AK43: =IF(OR($AL43="",COUNTIF($AL$3:$AR$3,$AL$2)=0),"",MAX($AK$3:AK42)+1)
B44: 自繳折扣-續期 | C44: =IF(OR($K$27<>0,ISNA(VLOOKUP(C43,$H$21:$I$25,2,FALSE))),0,VLOOKUP(C43,$H$21:$I$25,2,FALSE)) -> 0.01 | D44: =IF(C44>0,"-續期享有1%繳別折扣-","") -> -續期享有1%繳別折扣- | H44: LTT | I44: 20 | J44: =$I44&$H44 -> 20LTT | K44: 0 | L44: 15 | M44: 55 | N44: 0.5 | O44: =VLOOKUP($F$55,$H$81:$I$161,2,0) -> 2 | AK44: =IF(OR($AL44="",COUNTIF($AL$3:$AR$3,$AL$2)=0),"",MAX($AK$3:AK43)+1)
B45: 折扣率上限 | C45: =IF($K$27=1,IF($C$24=10,6%,IF($C$24=20,5%,IF($C$24=30,4%,1%))),1%) -> 0.01 | D45: =IF(OR(C45="",),1,"") | H45: LTT | I45: 30 | J45: =$I45&$H45 -> 30LTT | K45: 0 | L45: 15 | M45: 45 | N45: 0.5 | O45: =VLOOKUP($F$55,$H$81:$I$161,2,0) -> 2 | AK45: =IF(OR($AL45="",COUNTIF($AL$3:$AR$3,$AL$2)=0),"",MAX($AK$3:AK44)+1)
B46: 首期總折扣率 | C46: =MIN(SUM(C36:C40,C42),C45) -> 0.01 | J46: =$I46&$H46 | AL46: 保經代 | AM46: 錠嵂保經 | AN46: 銀保
B47: 續期總折扣率 | C47: =MIN(SUM(C36:C40,C44),C45) -> 0.01 | J47: =$I47&$H47 | AK47: =IF(OR($AL47="",COUNTIF($AL$46:$AR$46,$AL$2)=0),"",MAX($AK$3:AK46)+1) -> 1 | AL47: 富邦人壽保險股份有限公司履行個人資料保護法告知說明書
B48: 首期實繳保費 | C48: =ROUND(C35*(1-C46),0) -> 11326 | J48: =$I48&$H48 | AK48: =IF(OR($AL48="",COUNTIF($AL$46:$AR$46,$AL$2)=0),"",MAX($AK$3:AK47)+1) -> 2
B49: 續期實繳保費 | C49: =ROUND(C35*(1-C47),0) -> 11326 | D49: =IF($C$50=12,"-月繳首期須繳2個月"&TEXT($C$48*2,"#,##0元"),"") | J49: =$I49&$H49 | AK49: =IF(OR($AL49="",COUNTIF($AL$46:$AR$46,$AL$2)=0),"",MAX($AK$3:AK48)+1) -> 3 | AL49: 富邦人壽保險股份有限公司（下稱本公司）依據個人資料保護法（以下稱個資法）
B50: 繳別回乘倍數 | C50: =IF(D32=1,,VLOOKUP(C32,H2:K7,4,FALSE)) -> 1 | E50: ←首期保費規則 | J50: =$I50&$H50 | AK50: =IF(OR($AL50="",COUNTIF($AL$46:$AR$46,$AL$2)=0),"",MAX($AK$3:AK49)+1) -> 4 | AL50: 規定，向 台端告知下列事項，請 台端詳閱：
B51: 首年實繳保費 | C51: =IF(C50=12,C48*2+C49*10,C48*1+C49*(C50-1)) -> 11326 | D51: =IF($C$96=0,1,"") | J51: =$I51&$H51 | AK51: =IF(OR($AL51="",COUNTIF($AL$46:$AR$46,$AL$2)=0),"",MAX($AK$3:AK50)+1) -> 5 | AL51: 一、蒐集之目的：
B52: 續年實繳保費 | C52: =C49*C50 -> 11326 | J52: =$I52&$H52 | AK52: =IF(OR($AL52="",COUNTIF($AL$46:$AR$46,$AL$2)=0),"",MAX($AK$3:AK51)+1) -> 6 | AL52: （一）人身保險（００一）
B53: 主約1欄位檢核結果 | C53: =IF(SUM(D15:D16,D18,D28,D32:D33,D40:D41,D43,D45,D50,D51,D64,E96)>=1,1,"") | D53: =IF($B$2=1,$C$53,IF(SUM(C53,AD20)>=1,1,"")) | J53: =$I53&$H53 | AK53: =IF(OR($AL53="",COUNTIF($AL$46:$AR$46,$AL$2)=0),"",MAX($AK$3:AK52)+1) -> 7 | AL53: （二）其他經營合於營業登記項目或組織章程所定之業務（一八一）
B54: 版次 | C54: V1.0-1150720 | F54: 開始承保保險年齡 | J54: =$I54&$H54 | AK54: =IF(OR($AL54="",COUNTIF($AL$46:$AR$46,$AL$2)=0),"",MAX($AK$3:AK53)+1) -> 8 | AL54: 二、蒐集之個人資料類別：
B55: KEY | C55: =C22&IF($C$24=1,"",TEXT($C$24,"00"))&IF($B$2=1,TEXT($C$18,"00")&TEXT($D$5,"00"),$D$55) -> LTT300215 | D55: =IF($B$2=2,IF($D$5>$AD$5,TEXT($AC$18,"00")&TEXT($AD$5,"00")&TEXT($C$18,"00")&TEXT($D$5,"00"),TEXT($C$18,"00")&TEXT($D$5,"00")&TEXT($AC$18,"00")&TEXT($AD$5,"00")),"") | E55: A險種+年期(2位)+性別(1位)+年齡(2位) | F55: =IF($B$2=1,$D$5,MIN($D$5,$AD$5)) -> 15 | J55: =$I55&$H55 | AK55: =IF(OR($AL55="",COUNTIF($AL$46:$AR$46,$AL$2)=0),"",MAX($AK$3:AK54)+1) -> 9 | AL55: （一）姓名。
B56: SUMKEY | C56: =C22&IF($C$24=1,"",TEXT($C$24,"00")) -> LTT30 | D56: F險種+年期(2位) | J56: =$I56&$H56 | AK56: =IF(OR($AL56="",COUNTIF($AL$46:$AR$46,$AL$2)=0),"",MAX($AK$3:AK55)+1) -> 10 | AL56: （二）身分證統一編號。
B57: MAX-Y | C57: =$F$57-D5+1 -> 71 | D57: =IF($B$2=1,$C$57,MAX($C$57,$AC$21)) -> 71 | E57: 保障至幾歲 | F57: 85 | J57: =$I57&$H57 | AK57: =IF(OR($AL57="",COUNTIF($AL$46:$AR$46,$AL$2)=0),"",MAX($AK$3:AK56)+1) -> 11 | AL57: （三）地址。
B58: 換算匯率 | C58: 1 | J58: =$I58&$H58 | AK58: =IF(OR($AL58="",COUNTIF($AL$46:$AR$46,$AL$2)=0),"",MAX($AK$3:AK57)+1) -> 12 | AL58: （四）病歷、醫療、健康檢查 。
B59: 保額上限 | J59: =$I59&$H59 | AK59: =IF(OR($AL59="",COUNTIF($AL$46:$AR$46,$AL$2)=0),"",MAX($AK$3:AK58)+1) -> 13 | AL59: （五）要保書、要保文件等其他基於保險契約所提供之個人資料。
B60: 累積總保額上限 | J60: =$I60&$H60 | AK60: =IF(OR($AL60="",COUNTIF($AL$46:$AR$46,$AL$2)=0),"",MAX($AK$3:AK59)+1) -> 14 | AL60: 三、個人資料利用之期間、地區、對象、方式：
B61: 保費 | C61: =輸入頁!$E$53 -> 100000 | J61: =$I61&$H61 | AK61: =IF(OR($AL61="",COUNTIF($AL$46:$AR$46,$AL$2)=0),"",MAX($AK$3:AK60)+1) -> 15 | AL61: （一）期間：因執行業務所必須及依法令規定應為保存之期間。
B62: 換算1 | C62: =ROUNDDOWN(C61/C30,$E$28) -> 8.7 | J62: =$I62&$H62 | AK62: =IF(OR($AL62="",COUNTIF($AL$46:$AR$46,$AL$2)=0),"",MAX($AK$3:AK61)+1) -> 16 | AL62: （二）對象：本公司、中華民國人壽保險商業同業公會、財團法人保險事業發展
B63: 換算2加計折扣 | C63: =ROUNDDOWN((C61*(1+C46))/C30,$E$28) -> 8.8 | AK63: =IF(OR($AL63="",COUNTIF($AL$46:$AR$46,$AL$2)=0),"",MAX($AK$3:AK62)+1) -> 17 | AL63: 中心、財團法人金融消費評議中心、業務委外機構、臺灣網路認證(股)公司、
B64: 保額輸入檢核 | C64: =input_s!$H$61 -> 1 | D64: =IF(ROUND($C$64,$E$28)<>$C$64,1,"") | E64: =IF(D64=1,"保額輸入"&C64&"不符投保規則，請重新輸入","") | AK64: =IF(OR($AL64="",COUNTIF($AL$46:$AR$46,$AL$2)=0),"",MAX($AK$3:AK63)+1) -> 18 | AL64: 與本公司有再保業務往來之公司、依法有調查權機關或金融監理機關。
AK65: =IF(OR($AL65="",COUNTIF($AL$46:$AR$46,$AL$2)=0),"",MAX($AK$3:AK64)+1) -> 19 | AL65: （三）地區：上述對象所在之地區。
AK66: =IF(OR($AL66="",COUNTIF($AL$46:$AR$46,$AL$2)=0),"",MAX($AK$3:AK65)+1) -> 20 | AL66: （四）方式：合於法令規定之利用方式。
AK67: =IF(OR($AL67="",COUNTIF($AL$46:$AR$46,$AL$2)=0),"",MAX($AK$3:AK66)+1) -> 21 | AL67: 四、依據個資法第三條規定，台端就本公司保有 台端之個人資料得行使之權利及
AK68: =IF(OR($AL68="",COUNTIF($AL$46:$AR$46,$AL$2)=0),"",MAX($AK$3:AK67)+1) -> 22 | AL68: 方式：
B69: 適用通路： | C69: 銀保 | D69: PB | F69: ←銀保通路判別使用 | H69: 健康管理保險費折扣項目 | I69: =$C$22&"折扣率" -> LTT折扣率 | J69: =$C$22&"續年度折扣後實繳保費"&IF($C$47>0,"(含"&IF($K$27=1,"員工轉帳","續期繳費方式")&"折扣"&TEXT($C$47,"0.0%")&")","") -> LTT續年度折扣後實繳保費(含續期繳費方式折扣1.0%) | AK69: =IF(OR($AL69="",COUNTIF($AL$46:$AR$46,$AL$2)=0),"",MAX($AK$3:AK68)+1) -> 23 | AL69: （一）得向本公司行使之權利：
H70: 指定疫苗接種或健康檢查 | I70: 0.01 | J70: =ROUND($C$35*(1-($C$47+$I$70)),0) -> 11211 | AK70: =IF(OR($AL70="",COUNTIF($AL$46:$AR$46,$AL$2)=0),"",MAX($AK$3:AK69)+1) -> 24 | AL70: 1.向本公司查詢、請求閱覽或請求製給複製本。
B71: 姓名遮蔽用：中/英/數混合：前6碼"*"，中文：倒數第2碼"○" | AK71: =IF(OR($AL71="",COUNTIF($AL$46:$AR$46,$AL$2)=0),"",MAX($AK$3:AK70)+1) -> 25 | AL71: 2.向本公司請求補充或更正。
B72: 姓名： | C72: =input_s!$H$21 -> 客戶 | D72: ←輸入頁資料 | E72: 0 | AK72: =IF(OR($AL72="",COUNTIF($AL$46:$AR$46,$AL$2)=0),"",MAX($AK$3:AK71)+1) -> 26 | AL72: 3.向本公司請求停止蒐集、處理或利用及請求刪除。
B73: 帶入資料 | C73: =IF(E72=0,C72,IF(OR(E73=1,C72="",C72=0)," ",IF(AND(E82=0),C74&MID(C72,7,50),IF(LEN(C72)=1,C72,LEFT(C72,LEN(C72)-2)&"○"&RIGHT(C72,1))))) -> 客戶 | D73: 判別不顯示(不判別) | AK73: =IF(OR($AL73="",COUNTIF($AL$46:$AR$46,$AL$2)=0),"",MAX($AK$3:AK72)+1) -> 27 | AL73: （二）行使權利之方式：
B74: =IF(OR(E73=1,C72="",C72=0),"",IF(AND(E82=0),LEN(C72),"")) | C74: =IF(OR(B74=""),"",IF(ISERROR(VLOOKUP(B74,B75:C80,2,0)),C80,VLOOKUP(B74,B75:C80,2,0))) | D74: ID-11碼數字 | E74: =IF(AND(ISNUMBER(C72),LEN(C72)=11),1,0) -> 0 | AK74: =IF(OR($AL74="",COUNTIF($AL$46:$AR$46,$AL$2)=0),"",MAX($AK$3:AK73)+1) -> 28 | AL74: 您可以透過書面（包含電子郵件、傳真、電子文件）方式行使權利。
B75: 1 | C75: * | D75: ID-10碼 | E75: =IF(AND(LEN(C72)=10,ISTEXT(LEFT(C72,1)),ISNUMBER(RIGHT(C72,1)*1)),1,0) -> 0 | AK75: =IF(OR($AL75="",COUNTIF($AL$46:$AR$46,$AL$2)=0),"",MAX($AK$3:AK74)+1)
B76: 2 | C76: ** | D76: 護照-9碼 | E76: =IF(AND(ISNUMBER(C72),LEN(C72)=9),1,0) -> 0 | AK76: =IF(OR($AL76="",COUNTIF($AL$46:$AR$46,$AL$2)=0),"",MAX($AK$3:AK75)+1) -> 29 | AL76: 五、台端不提供個人資料所致權益之影響
B77: 3 | C77: *** | AK77: =IF(OR($AL77="",COUNTIF($AL$46:$AR$46,$AL$2)=0),"",MAX($AK$3:AK76)+1) -> 30 | AL77: 台端若未能提供相關個人資料時，本公司將可能延後或無法進行必要之審核
B78: 4 | C78: **** | AK78: =IF(OR($AL78="",COUNTIF($AL$46:$AR$46,$AL$2)=0),"",MAX($AK$3:AK77)+1) -> 31 | AL78: 及處理作業，因此可能婉謝承保、遲延或無法承保。
B79: 5 | C79: ***** | AK79: =IF(OR($AL79="",COUNTIF($AL$46:$AR$46,$AL$2)=0),"",MAX($AK$3:AK78)+1)
B80: 6 | C80: ****** | H80: 年齡-1 | I80: 最高保額-2 | J80: 保留-3 | K80: 保留-4 | L80: 免體檢額度-5 | M80: 通算係數-6-男 | N80: 通算系數-7-女 | AK80: =IF(OR($AL80="",COUNTIF($AL$46:$AR$46,$AL$2)=0),"",MAX($AK$3:AK79)+1)
B81: 空格位置 | C81: =IF(OR(ISERROR(SEARCH(" ",C72)),CODE(C72)>255),"",SEARCH(" ",C72)) | H81: 0 | L81: 1000 | M81: 100 | N81: 100 | AK81: =IF(OR($AL81="",COUNTIF($AL$46:$AR$46,$AL$2)=0),"",MAX($AK$3:AK80)+1)
B82: 簡寫 | C82: =IF(OR(ISERROR(SEARCH(" ",C72)),CODE(C72)>255),"",UPPER(LEFT(C72,1)&"."&MID(C72,C81+1,1))) | D82: 1-中文-0-混合 | E82: =IF(OR(LEN(C72)*2=LENB(C72),$E$83=1),1,0) -> 1 | H82: 1 | L82: 1000 | M82: 100 | N82: 100 | AK82: =IF(OR($AL82="",COUNTIF($AL$46:$AR$46,$AL$2)=0),"",MAX($AK$3:AK81)+1)
B83: 富邦人壽 | C83: FBLI | E83: =IF(LENB($B$83)=LEN($C$83),1,0) -> 0 | H83: 2 | L83: 1000 | M83: 100 | N83: 100 | AK83: =IF(OR($AL83="",COUNTIF($AL$46:$AR$46,$AL$2)=0),"",MAX($AK$3:AK82)+1)
H84: 3 | L84: 1000 | M84: 100 | N84: 100 | AK84: =IF(OR($AL84="",COUNTIF($AL$46:$AR$46,$AL$2)=0),"",MAX($AK$3:AK83)+1)
B85: 提醒設定 | C85: 1 | D85: 0 | H85: 4 | L85: 1000 | M85: 100 | N85: 100 | AK85: =IF(OR($AL85="",COUNTIF($AL$46:$AR$46,$AL$2)=0),"",MAX($AK$3:AK84)+1)
B86: 跳歲計算 | C86: =DATE(YEAR($D$3)+$D$6,MONTH($D$3)+6,MIN(DAY($D$3),$E$86)+1) -> 46205 | D86: =MONTH($D$3)+IF(MONTH($D$3)<=6,6,-6) -> 7 | E86: =IF(OR($D$86=1,$D$86=3,$D$86=5,$D$86=7,$D$86=8,$D$86=10,$D$86=12),31,IF(OR($D$86=4,$D$86=6,$D$86=9,$D$86=11),30,IF(AND($D$86=2,YEAR($C$3)/4=INT(YEAR($C$3)/4),YEAR($C$3)/400<>INT(YEAR($C$3)/400)),29,28))) -> 31 | H86: 5 | L86: 1000 | M86: 100 | N86: 100 | AK86: =IF(OR($AL86="",COUNTIF($AL$46:$AR$46,$AL$2)=0),"",MAX($AK$3:AK85)+1)
C87: =IF(C86<$C$3,"",C86-$C$3) | D87: =IF(C85=0,"",IF(OR($D$53=1,C87=""),"",IF(AND(C87>=1,C87<=30),"提醒您：被保險人"&$C$73&"將於 "&MONTH(C86)&" 月 "&DAY(C86)&" 日 ( "&C87&"天後 ) 保險年齡增加一歲"&IF(D85=0,"。","，"&$C$22&$C$32&"保險費"&IF($C$32="躉繳","","每期")&IF(E88>=0,"增加 ","減少 ")&TEXT(E88,"#,##0 元")&"。"),""))) | H87: 6 | L87: 1000 | M87: 100 | N87: 100 | AK87: =IF(OR($AL87="",COUNTIF($AL$46:$AR$46,$AL$2)=0),"",MAX($AK$3:AK86)+1)
B88: 新年齡/保費/差異 | C88: =C22&IF($C$24=1,"",TEXT($C$24,"00"))&TEXT($C$18,"00")&TEXT($D$5+1,"00") -> LTT300216 | D88: =IF(ISNA(VLOOKUP(C88,GP,2,0)),0,IF($C$21=1,ROUND(VLOOKUP(C88,GP,2,0)*$C$28*$C$34,0),IF($C$21=2,ROUNDDOWN(VLOOKUP(C88,GP,2,0)*$C$28*C34,0),""))) -> 11660 | E88: =D88-$C$35 -> 220 | H88: 7 | L88: 1000 | M88: 100 | N88: 100 | AK88: =IF(OR($AL88="",COUNTIF($AL$46:$AR$46,$AL$2)=0),"",MAX($AK$3:AK87)+1)
H89: 8 | L89: 1000 | M89: 100 | N89: 100 | AK89: =IF(OR($AL89="",COUNTIF($AL$46:$AR$46,$AL$2)=0),"",MAX($AK$3:AK88)+1)
B90: 全列印頁面使用 | C90: 更新區域 | D90: 帶入內容區域 | E90: OLD/說明/檢核 | H90: 9 | L90: 1000 | M90: 100 | N90: 100 | AK90: =IF(OR($AL90="",COUNTIF($AL$46:$AR$46,$AL$2)=0),"",MAX($AK$3:AK89)+1)
B91: 折扣率： | D91: =IF(OR(OP!$D$53=1,AND(OP!C46=0,OP!C47=0)),"","本保件符合保費折扣條件："&OP!$K$9&OP!$D$46) -> 本保件符合保費折扣條件：繳費方式 1.0%折扣。 | H91: 10 | L91: 1000 | M91: 100 | N91: 100
B92: 保費/折扣後保費： | D92: =IF(OR(OP!$D$53=1),"",$C$32&"總保費"&TEXT($C$35,"#,##0元")&IF(AND($C$46=0,$C$47=0),"","，"&IF($C$24=1,IF(OP!$C$46>0,"躉繳折扣後保費"&TEXT($C$48,"#,##0元"),""),IF($C$46>0,"首期折扣後保費"&TEXT($C$48,"#,##0元"),"首期保費"&TEXT($C$48,"#,##0元"))&"，"&IF($C$47>0,"續期折扣後保費"&TEXT($C$49,"#,##0元"),"續期保費"&TEXT($C$49,"#,##0元"))))&$D$49) -> 年繳總保費11,440元，首期折扣後保費11,326元，續期折扣後保費11,326元 | H92: 11 | L92: 1000 | M92: 100 | N92: 100
B93: 表格保險種類 | D93: =IF(OP!$D$53=1,"",OP!$C$23&IF(OP!C24=1,"(躉繳)",IF(OP!$C$24>=40,"(繳費至"&OP!$C$24&"歲滿期)","(繳費"&OP!$C$24&"年)"))) -> 富邦人壽順馨久久長期照顧定期健康保險(繳費30年) | H93: 12 | L93: 1000 | M93: 100 | N93: 100
B94: 本保單計價幣別： | C94: =$E$21 -> 新臺幣 | D94: =$B$94&$C$94 -> 本保單計價幣別：新臺幣 | H94: 13 | L94: 1000 | M94: 100 | N94: 100
B95: 假設儲存生息利率 | C95: =TEXT(RDATA!$I$2,"0.00%") -> 1.75% | D95: =$B$95&$C$95 -> 假設儲存生息利率1.75% | H95: 14 | L95: 1000 | M95: 100 | N95: 100
B96: 年度保單紅利給付方式： | C96: =input_s!$H$71 -> 現金給付 | D96: =IF($C$96="儲存生息",$B$96&$C$96&"",$B$96&$C$96) -> 年度保單紅利給付方式：現金給付 | E96: =IF(AND(input_s!$I$8<>3,COUNTIF(En_BFM,$C$96)<>1),1,"") | H96: 15 | I96: =IF($D$6<15,2,5) -> 2 | L96: 1000 | M96: 100 | N96: 100
B97: 有紅利頁首： | D97: =$D$96 -> 年度保單紅利給付方式：現金給付 | E97: 其他頁面用 | H97: 16 | I97: 3 | L97: 1000 | M97: 100 | N97: 100
B98: 有紅利頁首： | C98: ="本險種預定利率："&TEXT($K$42,"0.00%") -> 本險種預定利率：0.00% | D98: =$C$98&"，"&$D$95 -> 本險種預定利率：0.00%，假設儲存生息利率1.75% | E98: 彙總版用 | H98: 17 | I98: 3 | L98: 1000 | M98: 100 | N98: 100
H99: 18 | I99: 3 | L99: 1000 | M99: 100 | N99: 100
B100: 商品文號： | C100: 109.07.01富壽商精字第1090002113號函備查、109.09.01依109.07.08金管保壽字第1090423012號函修正 | D100: =$B$100&$C$100 -> 商品文號：109.07.01富壽商精字第1090002113號函備查、109.09.01依109.07.08金管保壽字第1090423012號函修正 | H100: 19 | I100: 3 | L100: 1000 | M100: 100 | N100: 100
...

Sheet 輸入頁
A2: =OP!$D$53 | B2: =OP!$E$23 -> 富邦人壽順馨久久長期照顧定期健康保險建議書
B3: 請注意：如使用非微軟OFFICE-PC版開啟本建議書，本建議書內容可能會因硬體系統升級或軟體更新問題導致數值誤差，業務同仁使用時請確實確認。
C4: 被保險人基本資料： | M4: 投保年齡區間： | N4: =OP!$C$16&OP!$E$15&" ~ "&OP!$C$15&"歲 "&"("&IF(OP!$C$9=1,OP!$C$7,OP!F4&" / "&OP!F5&" / "&OP!F6)&")" -> 15歲 ~ 45歲 (700225) | R4: =IF(OP!$C$105="停售","本商品已停售","")
A5: =OP!$E$6 | D5: 姓名： | E5: 客戶 | J5: 性別： | K5: 女 | M5: 生日(民國)： | N5: 1010101 | O5: 保險年齡： | P5: =OP!$D$5 -> 15 | Q5: 實際年齡： | R5: =OP!$D$6 -> 14 | S5: =IF(OR(K5="",E7="",E17="",Q17="",Q19="",E39="",J39="",OR(J39<J40,J39>K40),A2=1),1,"") -> 1
E6: =IF(OP!$E$6=1,"生日日期錯誤",IF($A$2=1,"部分內容空白或錯誤",OP!$D$17))&OP!$B$194&" "&OP!$D$87
A8: =OP!$AE$6 | C8: 被保險人2 | D8: 姓名： | E8: 客戶 | J8: 性別： | K8: 男 | M8: 生日(民國)： | N8: 981101 | O8: 保險年齡： | P8: =OP!$AD$5 -> 17 | Q8: 實際年齡： | R8: =OP!$AD$6 -> 16
E9: =IF(OP!$AE$6=1,"生日日期錯誤",IF($A$2=1,"部分內容空白或錯誤",OP!$AD$17))&OP!$B$194&" "&OP!$AD$26
E10: =IF(OP!$C$9=1,OP!$C$7,OP!$F$4) -> 700225 | F10: =IF(OP!$C$9=1,OP!$E$7,OP!$F$3) -> 1150825 | J10: =OP!E3 -> 31
D12: 要保人/繳款人： | E12: 同被保險人 | I12: =IF(OP!$C$181<10,"",OP!$C$181) | K12: ="請確認右方內容："&IF(OP!$C$181=1,"要保人、被保險人、繳款人皆為 "&OP!$D$182,"要保人："&IF(OR(OP!$C$181=1,OP!$C$181=2),OP!$D$182,OP!$D$181)&" "&"被保險人："&OP!$D$182&" "&"繳款人："&IF(OR(OP!$C$181=1,OP!$C$181=3),OP!$D$182,IF(OR(OP!$C$181=4),OP!$D$181,OP!$D$183))) -> 請確認右方內容：要保人、被保險人、繳款人皆為 客戶
D13: =IF(OR(OP!$C$181=1,OP!$C$181=2),"","要保人姓名：") | N13: =IF(OR(OP!$C$181=1,OP!$C$181=3,OP!$C$181=4),"","繳款人姓名：")
D14: =IF(OR($D$13=""),"","要保人生日(民國)：") | I14: =IF(OR($D$13=""),"","保險年齡："&OP!$D$193&"歲") | N14: =IF(OR($N$13=""),"","繳款人生日(民國)：")
E15: =IF(AND($E$14<>"",OP!$E$194=1),"要保人生日日期錯誤","")&OP!$B$194 | O15: =IF(AND($O$14<>"",OP!$D$198=1),"本件需進行錄音","")
B17: 繳別： | E17: 年繳 | H17: =OP!D49 | O17: 繳費方式： | P17: =IF(OP!$C$24=1,"","首期") -> 首期 | Q17: 匯款
D19: 年度保單紅利給付方式： | E19: 現金給付 | P19: =IF(OP!$C$24=1,"","續期") -> 續期 | Q19: 金融機構轉帳
A21: =IF(AND(OP!I13<=0,OP!J13<=0,OP!J27=1),1,"") | D21: 身份別保費折扣： | E21: 無 | R21: =IF($S$5=1,"",IF(OR(OP!$C$42>0,OP!$C$44>0),"本保件如符合本公司繳費方式折扣條件，","")&IF(AND(OP!$C$42>0,OP!$C$44>0),"首、續期享有1%繳費方式折扣",IF(AND(OP!$C$42=0,OP!$C$44>0),"續期享有1%繳費方式折扣",IF(AND(OP!$C$42>0,OP!$C$44=0),"首期享有1%繳費方式折扣",""))))
E22: =IF($A$2=1,"",OP!K12&OP!K13)
F24: 主約身故保障給付設定：
F26: =PY!$B$4 -> 指定保險金比例： | G26: 0 | J26: % | K26: ="0% ~ 100%"&" 約定分期給付換算比例："&TEXT(PY!$C$4,"0%") -> 0% ~ 100% 約定分期給付換算比例：0%
F28: =IF(OR($G$26<=0,$G$26="",$G$26>100),"",PY!$B$7) | G28: =IF(OR($G$26<=0,$G$26="",$G$26>100),"",PY!$C$7) | J28: =IF(OR($G$26<=0,$G$26="",$G$26>100),""," 計算分期給付金額之利率")
F30: =IF(OR($G$26<=0,$G$26="",$G$26>100),"",PY!$B$6) | G30: 10
S36: =IF(OR(E39="",J39=""),1,"")
D37: 主約繳費年期： | E37: 30 | G37: 保額(以千為單位) | M37: 保額限制： | P37: =OP!$C$32&"保費：" -> 年繳保費： | R37: =IF($A$2=1,"",OP!$C$35) -> 11440
A39: =OP!D28 | D39: 主約險種代號： | E39: LTT | G39: 保額(萬)： | J39: 1 | M39: =IF(E39="","",TEXT($J$40,IF(OP!$E$28=0,"#,##0","#,##0.0"))&" ~ "&TEXT($K$40,IF(OP!$E$28=0,"#,##0","#,##0.0"))) -> 0.5 ~ 2.0 | N39: =OP!E64&OP!$D$37
J40: =OP!$C$26 -> 0.5 | K40: =OP!$C$27 -> 2
C41: =IF(OR(O7>N4,E39="",M39="保額超過限制，請修正"),"","保障年期：") -> 保障年期： | D41: =IF(OR(O7>N4,E39="",M39="保額超過限制，請修正"),"","終身（保險年齡屆滿"&OP!$F$57&"歲）") -> 終身（保險年齡屆滿85歲） | O41: =IF(OR(AND(OP!$C$24=1,OP!$C$46<=0),A2=1),"",IF(OP!$C$46>0,"折扣後","")&OP!$C$32&IF(OP!$C$24=1,"保費：","首期保費：")) -> 折扣後年繳首期保費： | R41: =IF(OR($A$2=1,AND(OP!$C$24=1,OP!$C$46<=0)),"",OP!C48) -> 11326
O43: =IF(OR(OP!$C$24=1,A2=1),"",IF(OP!$C$47>0,"折扣後","")&OP!$C$32&"續期保費：") -> 折扣後年繳續期保費： | R43: =IF(OR($A$2=1,OP!$C$24=1),"",OP!$C$49) -> 11326
R46: =OP!$D$94 -> 本保單計價幣別：新臺幣
B50: =OP!$C$54 -> V1.0-1150720 | P50: 試算日： | Q50: =OP!$D$121 -> 1150825
B52: 預計第二年度起保單週月日 領取生存保險金/元： | G52: 50000 | J52: =TEXT(J40*10000*1.5%,"#,##0")&"~"&TEXT(K40*10000*1.5%,"#,##0") -> 75~300 | N52: 換算投保保額/萬： | O52: =MAX(J40,MIN(K40,ROUNDUP(G52/1.5%,-4)/10000)) -> 2 | P52: =IF(G52<J40*10000*1.5%,"換算保額低於最低承保保額，顯示最低承保保額。",IF(G52>K40*10000*1.5%,"換算保額高於最高承保保額，顯示最高承保保額。","")) -> 換算保額高於最高承保保額，顯示最高承保保額。
D53: 客戶計畫繳交保費(元)： | E53: 100000 | M53: 換算可購買保額(萬)： | N53: =OP!$C$62 -> 8.7 | O53: 計畫繳交保費換算保額未考慮保費折扣條件
D202: 公司名稱： | O202: 投保本商品的目的及需求： | P202: 其他(請自行填入)
D203: 招攬人： | S203: 「銷售過程紀錄錄音參考範本投保目的及需求須與業務人員報告書一致」
D204: 登錄證：
D205: 共同招攬人：
D206: 共同招攬人登錄證：

Sheet 列印頁
A2: =OP!$D$53 | B2: =OP!$E$23 -> 富邦人壽順馨久久長期照顧定期健康保險建議書
D4: 被保險人： | E4: =OP!$C$73 -> 客戶 | L4: 保險年齡： | M4: =OP!$D$5 -> 15 | P4: 性別： | Q4: =OP!$E$18 -> 女 | R4: =OP!$D$94 -> 本保單計價幣別：新臺幣
B5: 保險種類 | M5: 險種代碼 | P5: 保額 | S5: =OP!$C$32&"應繳保費/元" -> 年繳應繳保費/元
A6: 1 | B6: =OP!$D$93 -> 富邦人壽順馨久久長期照顧定期健康保險(繳費30年) | M6: =IF($A$2=1,"",OP!$C$22) -> LTT | P6: =IF($A$2=1,"",TEXT(OP!$C$28,IF(OP!$E$28=0,"#,##0 ","#,##0.0 "))&"萬") -> 1.0 萬 | S6: =IF($A$2=1,"",OP!C35) -> 11440
B7: =OP!$D$91 -> 本保件符合保費折扣條件：繳費方式 1.0%折扣。
B8: =OP!$D$92 -> 年繳總保費11,440元，首期折扣後保費11,326元，續期折扣後保費11,326元
B11: =IF($A$2=1,"",OP!$C$22&"第二保單年度起之續期健康管理保險費折扣") -> LTT第二保單年度起之續期健康管理保險費折扣
B13: =IF($A$2=1,"",OP!$H$69) -> 健康管理保險費折扣項目 | H13: =IF($A$2=1,"",OP!$I$69) -> LTT折扣率 | K13: =IF($A$2=1,"",OP!$J$69) -> LTT續年度折扣後實繳保費(含續期繳費方式折扣1.0%)
B14: =IF($A$2=1,"",OP!$H$70) -> 指定疫苗接種或健康檢查 | H14: =IF($A$2=1,"",OP!$I$70) -> 0.01 | K14: =IF($A$2=1,"",TEXT(OP!$J$70,"#,### 元")) -> 11,211 元
B15: ‧上表健康管理折扣後實繳保費，繳費期內如不符折扣條件，上表將不適用，詳細內容以投保當時保單條款規定為準。
B17: 投 保 利 益 表
V18: =IF(OP!$C$105="停售","本商品已停售","")
B20: 完全失能 關懷 保險金 | E20: =IF(OR($A$2=1),"",TEXT(OP!$C$28*10000*15,"#,##0")&"元") -> 150,000元 | I20: ‧被保險人於本契約有效期間內因保單條款約定的疾病或意外傷害事故，經醫院醫師診斷確定符合保單條款附表所列完全失能程度之一，且於完全失能診斷確定日仍生存者依保單條款約定給付。本契約有效期間內以給付一次為限。 ‧若被保險人已先行符合保單條款「長期照顧一次保險金」約定之給付條件，本公司不再負本條保險金給付之責；若被保險人同時符合本條與保單條款「長期照顧一次保險金」約定之給付條件，本公司僅就其中一條約定負給付保險金之責。
B21: 完全失能 生活扶助 保險金 | E21: 累計 給付年度 | G21: 每月 給付金額 (元) | I21: ‧被保險人於本契約有效期間內因保單條款約定的疾病或意外傷害事故，經醫院醫師診斷確定致成保單條款附表所列完全失能程度之一，且於完全失能診斷確定日仍生存者，本公司於完全失能診斷確定日起一年內之每一週月日（不論被保險人生存與否）依保單條款約定給付。 ‧被保險人於完全失能診斷確定日之週年日仍生存者，本公司於各該週年日起一年內之每一週月日（不論被保險人生存與否）依保單條款約定給付。 ‧被保險人於本契約有效期間內，不論同時或先後致成二項以上完全失能者，本公司僅給付一項。若係同項完全失能發生二次以上者，本公司僅給付一次。 ‧本公司於依保單條款約定給付「長期照顧分期保險金」期間，不另給付「完全失能生活扶助保險金」。「完全失能生活扶助保險金」與「長期照顧分期保險金」之給付，合計最高給付上限為一百八十個月。
E22: 1 | G22: =IF(OR($A$2=1,ISERROR(VLOOKUP(OP!$C$56&TEXT($E22,"00"),PVal,2,0))),"",TEXT(OP!$C$28*VLOOKUP(OP!$C$56&TEXT($E22,"00"),PVal,2,0),"#,##0")) -> 20,000
E23: =$E22+1 -> 2 | G23: =IF(OR($A$2=1,ISERROR(VLOOKUP(OP!$C$56&TEXT($E23,"00"),PVal,2,0))),"",TEXT(OP!$C$28*VLOOKUP(OP!$C$56&TEXT($E23,"00"),PVal,2,0),"#,##0")) -> 20,400
E24: =$E23+1 -> 3 | G24: =IF(OR($A$2=1,ISERROR(VLOOKUP(OP!$C$56&TEXT($E24,"00"),PVal,2,0))),"",TEXT(OP!$C$28*VLOOKUP(OP!$C$56&TEXT($E24,"00"),PVal,2,0),"#,##0")) -> 20,800
E25: =$E24+1 -> 4 | G25: =IF(OR($A$2=1,ISERROR(VLOOKUP(OP!$C$56&TEXT($E25,"00"),PVal,2,0))),"",TEXT(OP!$C$28*VLOOKUP(OP!$C$56&TEXT($E25,"00"),PVal,2,0),"#,##0")) -> 21,200
E26: =$E25+1 -> 5 | G26: =IF(OR($A$2=1,ISERROR(VLOOKUP(OP!$C$56&TEXT($E26,"00"),PVal,2,0))),"",TEXT(OP!$C$28*VLOOKUP(OP!$C$56&TEXT($E26,"00"),PVal,2,0),"#,##0")) -> 21,600
E27: =$E26+1 -> 6 | G27: =IF(OR($A$2=1,ISERROR(VLOOKUP(OP!$C$56&TEXT($E27,"00"),PVal,2,0))),"",TEXT(OP!$C$28*VLOOKUP(OP!$C$56&TEXT($E27,"00"),PVal,2,0),"#,##0")) -> 22,000
E28: =$E27+1 -> 7 | G28: =IF(OR($A$2=1,ISERROR(VLOOKUP(OP!$C$56&TEXT($E28,"00"),PVal,2,0))),"",TEXT(OP!$C$28*VLOOKUP(OP!$C$56&TEXT($E28,"00"),PVal,2,0),"#,##0")) -> 22,400
E29: =$E28+1 -> 8 | G29: =IF(OR($A$2=1,ISERROR(VLOOKUP(OP!$C$56&TEXT($E29,"00"),PVal,2,0))),"",TEXT(OP!$C$28*VLOOKUP(OP!$C$56&TEXT($E29,"00"),PVal,2,0),"#,##0")) -> 22,800
E30: =$E29+1 -> 9 | G30: =IF(OR($A$2=1,ISERROR(VLOOKUP(OP!$C$56&TEXT($E30,"00"),PVal,2,0))),"",TEXT(OP!$C$28*VLOOKUP(OP!$C$56&TEXT($E30,"00"),PVal,2,0),"#,##0")) -> 23,200
E31: =$E30+1 -> 10 | G31: =IF(OR($A$2=1,ISERROR(VLOOKUP(OP!$C$56&TEXT($E31,"00"),PVal,2,0))),"",TEXT(OP!$C$28*VLOOKUP(OP!$C$56&TEXT($E31,"00"),PVal,2,0),"#,##0")) -> 23,600
E32: =$E31+1 -> 11 | G32: =IF(OR($A$2=1,ISERROR(VLOOKUP(OP!$C$56&TEXT($E32,"00"),PVal,2,0))),"",TEXT(OP!$C$28*VLOOKUP(OP!$C$56&TEXT($E32,"00"),PVal,2,0),"#,##0")) -> 24,000
E33: =$E32+1 -> 12 | G33: =IF(OR($A$2=1,ISERROR(VLOOKUP(OP!$C$56&TEXT($E33,"00"),PVal,2,0))),"",TEXT(OP!$C$28*VLOOKUP(OP!$C$56&TEXT($E33,"00"),PVal,2,0),"#,##0")) -> 24,400
E34: =$E33+1 -> 13 | G34: =IF(OR($A$2=1,ISERROR(VLOOKUP(OP!$C$56&TEXT($E34,"00"),PVal,2,0))),"",TEXT(OP!$C$28*VLOOKUP(OP!$C$56&TEXT($E34,"00"),PVal,2,0),"#,##0")) -> 24,800
... E36: =$E35+1 -> 15 | G36: =IF(OR($A$2=1,ISERROR(VLOOKUP(OP!$C$56&TEXT($E36,"00"),PVal,2,0))),"",TEXT(OP!$C$28*VLOOKUP(OP!$C$56&TEXT($E36,"00"),PVal,2,0),"#,##0")) -> 25,600
B37: 長期照顧 一次 保險金 | E37: =IF(OR($A$2=1),"",TEXT(OP!$C$28*10000*15,"#,##0")&"元") -> 150,000元 | I37: ‧被保險人於本契約有效期間內，經醫院專科醫師診斷確定符合保單條款約定之「長期照顧狀態」，並於免責期間屆滿時仍生存且持續符合「長期照顧狀態」者，本公司按免責期間屆滿時之保險金額的十五倍給付。
E38: =IF(OR($A$2=1),"",TEXT(OP!$C$28*10000*10,"#,##0")&"元") -> 100,000元 | I38: ‧前項情形，若被保險人係於保險年齡六十五歲(不含)以前，符合首次經醫院專科醫師診斷確定屬於保單條款約定之認知功能障礙，以及於免責期間屆滿時仍生存且持續符合「長期照顧狀態」之認知功能障礙二項條件者，本公司除依前項約定之金額給付外，另加計免責期間屆滿時之保險金額的十倍給付。但被保險人於符合認知功能障礙以前，已先行經醫院專科醫師診斷確定屬於保單條款約定之生理功能障礙，而符合前項約定給付條件者，無本項約定之適用。
E39: ‧本契約有效期間內以給付一次為限。 ‧若被保險人已先行符合保單條款「完全失能關懷保險金」約定之給付條件，本公司不再負本條保險金給付之責；若被保險人同時符合本條與保單條款「完全失能關懷保險金」約定之給付條件，本公司僅就其中一條約定負給付保險金之責。
A48: 1 | B48: =OP!$D$107 -> 本建議書僅供參考，詳細商品內容及其變更，應以投保當時保單條款內容及本公司核保、保全作業規定為準
V49: =OP!$D$105 -> V1.0-1150720 試算日：1150825
V50: =IF(OP!$C$105="停售","本商品已停售","")
B52: 長期照顧 分期 保險金 | E52: 累計 給付年度 | G52: 每月 給付金額 (元) | I52: ‧被保險人於本契約有效期間內，經醫院專科醫師診斷確定符合保單條款約定之「長期照顧狀態」，並於免責期間屆滿時仍生存且持續符合「長期照顧狀態」者，本公司於免責期間屆滿翌日及一年內之每一週月日（不論被保險人生存與否）依保單條款約定給付。 ‧被保險人於免責期間屆滿翌日的週年日仍生存並持續符合「長期照顧狀態」者，本公司於各該週年日起一年內之每一週月日（不論被保險人生存與否）依保單條款約定給付。 ‧本公司於依保單條款約定給付「完全失能生活扶助保險金」期間，不另給付「長期照顧分期保險金」。「長期照顧分期保險金」與「完全失能生活扶助保險金」之給付，合計最高給付上限為一百八十個月。
E53: 1 | G53: =IF(OR($A$2=1,ISERROR(VLOOKUP(OP!$C$56&TEXT($E53,"00"),PVal,2,0))),"",TEXT(OP!$C$28*VLOOKUP(OP!$C$56&TEXT($E53,"00"),PVal,2,0),"#,##0")) -> 20,000
E54: =$E53+1 -> 2 | G54: =IF(OR($A$2=1,ISERROR(VLOOKUP(OP!$C$56&TEXT($E54,"00"),PVal,2,0))),"",TEXT(OP!$C$28*VLOOKUP(OP!$C$56&TEXT($E54,"00"),PVal,2,0),"#,##0")) -> 20,400
E55: =$E54+1 -> 3 | G55: =IF(OR($A$2=1,ISERROR(VLOOKUP(OP!$C$56&TEXT($E55,"00"),PVal,2,0))),"",TEXT(OP!$C$28*VLOOKUP(OP!$C$56&TEXT($E55,"00"),PVal,2,0),"#,##0")) -> 20,800
E56: =$E55+1 -> 4 | G56: =IF(OR($A$2=1,ISERROR(VLOOKUP(OP!$C$56&TEXT($E56,"00"),PVal,2,0))),"",TEXT(OP!$C$28*VLOOKUP(OP!$C$56&TEXT($E56,"00"),PVal,2,0),"#,##0")) -> 21,200
E57: =$E56+1 -> 5 | G57: =IF(OR($A$2=1,ISERROR(VLOOKUP(OP!$C$56&TEXT($E57,"00"),PVal,2,0))),"",TEXT(OP!$C$28*VLOOKUP(OP!$C$56&TEXT($E57,"00"),PVal,2,0),"#,##0")) -> 21,600
E58: =$E57+1 -> 6 | G58: =IF(OR($A$2=1,ISERROR(VLOOKUP(OP!$C$56&TEXT($E58,"00"),PVal,2,0))),"",TEXT(OP!$C$28*VLOOKUP(OP!$C$56&TEXT($E58,"00"),PVal,2,0),"#,##0")) -> 22,000
E59: =$E58+1 -> 7 | G59: =IF(OR($A$2=1,ISERROR(VLOOKUP(OP!$C$56&TEXT($E59,"00"),PVal,2,0))),"",TEXT(OP!$C$28*VLOOKUP(OP!$C$56&TEXT($E59,"00"),PVal,2,0),"#,##0")) -> 22,400
E60: =$E59+1 -> 8 | G60: =IF(OR($A$2=1,ISERROR(VLOOKUP(OP!$C$56&TEXT($E60,"00"),PVal,2,0))),"",TEXT(OP!$C$28*VLOOKUP(OP!$C$56&TEXT($E60,"00"),PVal,2,0),"#,##0")) -> 22,800
E61: =$E60+1 -> 9 | G61: =IF(OR($A$2=1,ISERROR(VLOOKUP(OP!$C$56&TEXT($E61,"00"),PVal,2,0))),"",TEXT(OP!$C$28*VLOOKUP(OP!$C$56&TEXT($E61,"00"),PVal,2,0),"#,##0")) -> 23,200
E62: =$E61+1 -> 10 | G62: =IF(OR($A$2=1,ISERROR(VLOOKUP(OP!$C$56&TEXT($E62,"00"),PVal,2,0))),"",TEXT(OP!$C$28*VLOOKUP(OP!$C$56&TEXT($E62,"00"),PVal,2,0),"#,##0")) -> 23,600
E63: =$E62+1 -> 11 | G63: =IF(OR($A$2=1,ISERROR(VLOOKUP(OP!$C$56&TEXT($E63,"00"),PVal,2,0))),"",TEXT(OP!$C$28*VLOOKUP(OP!$C$56&TEXT($E63,"00"),PVal,2,0),"#,##0")) -> 24,000
E64: =$E63+1 -> 12 | G64: =IF(OR($A$2=1,ISERROR(VLOOKUP(OP!$C$56&TEXT($E64,"00"),PVal,2,0))),"",TEXT(OP!$C$28*VLOOKUP(OP!$C$56&TEXT($E64,"00"),PVal,2,0),"#,##0")) -> 24,400
E65: =$E64+1 -> 13 | G65: =IF(OR($A$2=1,ISERROR(VLOOKUP(OP!$C$56&TEXT($E65,"00"),PVal,2,0))),"",TEXT(OP!$C$28*VLOOKUP(OP!$C$56&TEXT($E65,"00"),PVal,2,0),"#,##0")) -> 24,800
... E67: =$E66+1 -> 15 | G67: =IF(OR($A$2=1,ISERROR(VLOOKUP(OP!$C$56&TEXT($E67,"00"),PVal,2,0))),"",TEXT(OP!$C$28*VLOOKUP(OP!$C$56&TEXT($E67,"00"),PVal,2,0),"#,##0")) -> 25,600
B68: 豁免保險費 | E68: ‧被保險人於本契約有效且繳費期間內，經醫院醫師診斷確定致成下列情形之一者，本公司豁免診斷確定日後之本契約（不含附約）續期應繳之各期保險費，本契約繼續有效： 一、依保單條款約定之疾病或意外傷害事故致成保單條款附表所列之完全失能程度之一者。 二、被保險人經醫院專科醫師診斷確定符合保單條款約定之「長期照顧狀態」，並於免責期間屆滿後 仍生存且持續符合「長期照顧狀態」者。 ‧本契約依前項第二款約定豁免保險費期間，若被保險人因保單條款約定之被保險人「長期照顧狀態」已消滅致本公司暫停給付「長期照顧分期保險金」時，本公司自暫停給付「長期照顧分期保險金」之次一應繳日起暫停豁免保險費。要保人應於暫停給付「長期照顧分期保險金」之次一應繳日起繼續交付保險費使本契約繼續有效。
B69: ‧上表所列各項保險實際給付金額以保單條款規定為準。
A103: 1 | B103: =OP!$D$107 -> 本建議書僅供參考，詳細商品內容及其變更，應以投保當時保單條款內容及本公司核保、保全作業規定為準
V104: =OP!$D$105 -> V1.0-1150720 試算日：1150825
V105: =IF(OP!$C$105="停售","本商品已停售","")
B106: 商品摘要
A107: 1 | B107: =OP!$C$23&"("&OP!$C$22&")" -> 富邦人壽順馨久久長期照顧定期健康保險(LTT)
B108: 給付項目：完全失能關懷保險金、完全失能生活扶助保險金、長期照顧一次保險金、長期照顧分期保險金、豁免保險費
B109: 免付費申訴專線：0809-000-550
B110: ‧本保險因費率計算已考慮脫退率，故本保險無解約金。
B111: ‧本商品免責期間為九十日。
B112: ‧免責期間：係指被保險人經專科醫師診斷確定為「長期照顧狀態」之日起算，且持續符合「長期照顧狀態」達九十日之
B113: 期間。
B114: ‧疾病：係指被保險人自本契約生效日或復效日（含）起所發生之疾病。
B115: ‧傷害：係指被保險人於本契約有效期間內，遭受意外傷害事故，因而蒙受之傷害。
B116: ‧意外傷害事故：係指非由疾病引起之外來突發事故。
B117: ‧長期照顧狀態：係指被保險人經專科醫師診斷判定，符合保單條款所列之生理功能障礙或認知功能障礙二項情形之一者。
B118: ‧本商品各項保險金給付詳細內容及其限制請詳閱保單條款內容說明。
B119: ‧契約的終止：本契約有下列情形之一時，其效力即行終止：
... B158: ‧富邦人壽保險股份有限公司 / 地址：台北市信義區松高路77號8樓 / 電話：(02)8771-6699
B159: ="‧消費者於購買前，應詳閱各種銷售文件內容，本商品之預定附加費用率，"&OP!$D$101&"；如要詳細了解其他" -> ‧消費者於購買前，應詳閱各種銷售文件內容，本商品之預定附加費用率，最高33.7%，最低25.9%；如要詳細了解其他
B160: 相關資訊，請洽本公司業務員、服務據點(免費服務及申訴電話：0809-000-550)或網站(www.fubon.com/life/)，
B161: 以保障您的權益。
A162: 1 | B162: =OP!$D$107 -> 本建議書僅供參考，詳細商品內容及其變更，應以投保當時保單條款內容及本公司核保、保全作業規定為準
V163: =OP!$D$105 -> V1.0-1150720 試算日：1150825
A166: 1 | B166: =IF(ISERROR(VLOOKUP(A166,PI,2,0)),"",VLOOKUP(A166,PI,2,0)) -> 富邦人壽保險股份有限公司履行個人資料保護法告知說明書
A167: 2 | C167: =IF(ISERROR(VLOOKUP(A167,PI,2,0)),"",VLOOKUP(A167,PI,2,0))
A168: 3 | C168: =IF(ISERROR(VLOOKUP(A168,PI,2,0)),"",VLOOKUP(A168,PI,2,0)) -> 富邦人壽保險股份有限公司（下稱本公司）依據個人資料保護法（以下稱個資法）
A169: 4 | C169: =IF(ISERROR(VLOOKUP(A169,PI,2,0)),"",VLOOKUP(A169,PI,2,0)) -> 規定，向 台端告知下列事項，請 台端詳閱：
A170: 5 | C170: =IF(ISERROR(VLOOKUP(A170,PI,2,0)),"",VLOOKUP(A170,PI,2,0)) -> 一、蒐集之目的：
A171: 6 | C171: =IF(ISERROR(VLOOKUP(A171,PI,2,0)),"",VLOOKUP(A171,PI,2,0)) -> （一）人身保險（００一）
A172: 7 | C172: =IF(ISERROR(VLOOKUP(A172,PI,2,0)),"",VLOOKUP(A172,PI,2,0)) -> （二）其他經營合於營業登記項目或組織章程所定之業務（一八一）
A173: 8 | C173: =IF(ISERROR(VLOOKUP(A173,PI,2,0)),"",VLOOKUP(A173,PI,2,0)) -> 二、蒐集之個人資料類別：
A174: 9 | C174: =IF(ISERROR(VLOOKUP(A174,PI,2,0)),"",VLOOKUP(A174,PI,2,0)) -> （一）姓名。
A175: 10 | C175: =IF(ISERROR(VLOOKUP(A175,PI,2,0)),"",VLOOKUP(A175,PI,2,0)) -> （二）身分證統一編號。
A176: 11 | C176: =IF(ISERROR(VLOOKUP(A176,PI,2,0)),"",VLOOKUP(A176,PI,2,0)) -> （三）地址。
A177: 12 | C177: =IF(ISERROR(VLOOKUP(A177,PI,2,0)),"",VLOOKUP(A177,PI,2,0)) -> （四）病歷、醫療、健康檢查 。
A178: 13 | C178: =IF(ISERROR(VLOOKUP(A178,PI,2,0)),"",VLOOKUP(A178,PI,2,0)) -> （五）要保書、要保文件等其他基於保險契約所提供之個人資料。
... A205: 40 | C205: =IF(ISERROR(VLOOKUP(A205,PI,2,0)),"",VLOOKUP(A205,PI,2,0))
B210: ‧本人已將本建議書內容及注意事項向要保人親自告知 | L210: ‧本人已詳閱本建議書內容並同意提醒注意事項
C213: 業務員簽名： . | N213: 要保人簽名： .
V215: ="富邦人壽提供，"&OP!$D$105 -> 富邦人壽提供，V1.0-1150720 試算日：1150825
