Workbook
Name BD: 輸入頁!$E$7
Name BGP: OP!$C$30
Name CV: P_DATA!$Q$111:$DX$212
Name DIE: P_DATA!$ED$2:$IK$104
Name EXP: P_DATA!$Q$2:$DX$104
Name GP: P_DATA!$J:$K
Name HL_1: P_DATA!$Q$218:$DX$319
Name HL_2: P_DATA!$ED$218:$IK$319
Name HL_3: P_DATA!$Q$328:$DX$429
Name IN: 輸入頁!$E$5
Name MGP: OP!$C$35
Name PA: P_DATA!$ED$110:$IK$212
Name PI: OP!$AK$4:$AL$90
Name PM: 輸入頁!$E$17
Name PYO: PY!$D$4
Name PYR: PY!$C$11
Name PYY: PY!$C$4
Name SEX: 輸入頁!$K$5
Name WORDING: OP!$P$2:$Q$20
Name WORDINGP: OP!$AD$2:$AE$41
Name YPN: 輸入頁!$D$35
Name 主約1: OP!$H$43:$H$45
Name 保額倍數: OP!$B$87:$C$197
Name 繳: OP!$H$17:$H$21
Name 繳別首: OP!$L$31:$L$35
Name 繳別續: OP!$M$31:$M$35
Name 關係: OP!$B$143:$B$147

Sheet 揭露
B1: =OP!$C$56 -> SDJ20 | C1: ←帶OP | D1: =IF(OP!$E$16=1,"足歲",IF(OP!$E$16=2,"保險年齡","錯誤")) -> 保險年齡 | E1: ←帶OP | Q1: 6 | R1: 7 | S1: 8 | T1: 9 | U1: 10 | V1: 11 | W1: 12
L2: 以下3欄要注意最下方要和右側揭露拉齊 | O2: 以下COPY-DB | Q2: 109
C3: 代表年齡第?小→ | D3: 1 | E3: 2 | F3: 3 | G3: 1 | H3: 2 | I3: 3 | K3: 年齡代號轉換 | L3: KEY | M3: 年齡 | N3: 年度 | O3: 險種大類 | P3: 年期險種 | Q3: 性別 | R3: 年齡 | S3: 繳費方式 | T3: 宣告利率 | U3: 繳費金額 | V3: 保單年度 | W3: 揭露利率
C4: 性別男=1，女=2→ | D4: 1 | E4: 1 | F4: 1 | G4: 2 | H4: 2 | I4: 2 | K4: =IF($D$1="足歲","15足歲","") | L4: =IF(P4<>$B$1,"",P4&Q4&R4&V4) -> SDJ20151 | M4: =IF(L4="","-",IF(ISERROR($R4*1),LEFT($R4,2)*1,$R4*1)) -> 5 | N4: =IF(L4="","",V4*1) -> 1 | P4: SDJ20 | Q4: 1 | R4: 5 | S4: 0 | T4: 0 | U4: 0 | V4: 1 | W4: 0.00%
B5: 取第?欄→ | C5: 12 | D5: =IF(SMALL($M:$M,D$3)=15,$K$4,SMALL($M:$M,D$3)) -> 5 | E5: =IF(SMALL($M:$M,E$3)=15,$K$4,SMALL($M:$M,E$3)) -> 35 | F5: =IF(SMALL($M:$M,F$3)=15,$K$4,SMALL($M:$M,F$3)) -> 50 | G5: =IF(SMALL($M:$M,G$3)=15,$K$4,SMALL($M:$M,G$3)) -> 5 | H5: =IF(SMALL($M:$M,H$3)=15,$K$4,SMALL($M:$M,H$3)) -> 35 | I5: =IF(SMALL($M:$M,I$3)=15,$K$4,SMALL($M:$M,I$3)) -> 50 | L5: =IF(P5<>$B$1,"",P5&Q5&R5&V5) -> SDJ20152 | M5: =IF(OR(L5="",COUNTIF($M$4:M4,IF(ISERROR($R5*1),LEFT($R5,2)*1,$R5*1))>=1),"-",IF(ISERROR($R5*1),LEFT($R5,2)*1,$R5*1)) -> - | N5: =IF(OR(L5="",COUNTIF($N$4:N4,V5*1)>=1),"-",V5*1) -> 2 | P5: SDJ20 | Q5: 1 | R5: 5 | S5: 0 | T5: 0 | U5: 0 | V5: 2 | W5: 3.57%
B6: 第?小↓ | C6: 保單年度 | D6: =IF(OR(ISERROR($D5)),"",IF(N(D$5)=0,D$5&IF(D$4=1,"男性",IF(D$4=2,"女性","")),D$5&"歲"&IF(D$4=1,"男性",IF(D$4=2,"女性","")))) -> 5歲男性 | E6: =IF(OR(ISERROR($D5)),"",IF(N(E$5)=0,E$5&IF(E$4=1,"男性",IF(E$4=2,"女性","")),E$5&"歲"&IF(E$4=1,"男性",IF(E$4=2,"女性","")))) -> 35歲男性 | F6: =IF(OR(ISERROR($D5)),"",IF(N(F$5)=0,F$5&IF(F$4=1,"男性",IF(F$4=2,"女性","")),F$5&"歲"&IF(F$4=1,"男性",IF(F$4=2,"女性","")))) -> 50歲男性 | G6: =IF(OR(ISERROR($D5)),"",IF(N(G$5)=0,G$5&IF(G$4=1,"男性",IF(G$4=2,"女性","")),G$5&"歲"&IF(G$4=1,"男性",IF(G$4=2,"女性","")))) -> 5歲女性 | H6: =IF(OR(ISERROR($D5)),"",IF(N(H$5)=0,H$5&IF(H$4=1,"男性",IF(H$4=2,"女性","")),H$5&"歲"&IF(H$4=1,"男性",IF(H$4=2,"女性","")))) -> 35歲女性 | I6: =IF(OR(ISERROR($D5)),"",IF(N(I$5)=0,I$5&IF(I$4=1,"男性",IF(I$4=2,"女性","")),I$5&"歲"&IF(I$4=1,"男性",IF(I$4=2,"女性","")))) -> 50歲女性 | L6: =IF(P6<>$B$1,"",P6&Q6&R6&V6) -> SDJ20153 | M6: =IF(OR(L6="",COUNTIF($M$4:M5,IF(ISERROR($R6*1),LEFT($R6,2)*1,$R6*1))>=1),"-",IF(ISERROR($R6*1),LEFT($R6,2)*1,$R6*1)) -> - | N6: =IF(OR(L6="",COUNTIF($N$4:N5,V6*1)>=1),"-",V6*1) -> 3 | P6: SDJ20 | Q6: 1 | R6: 5 | S6: 0 | T6: 0 | U6: 0 | V6: 3 | W6: 4.72%
B7: 1 | C7: =IF(ISERROR(SMALL($N:$N,$B7)),"",SMALL($N:$N,$B7)) -> 1 | D7: =IF(ISERROR(VLOOKUP($B$1&D$4&D$5&$C7,$L:$W,$C$5,0)),"",VLOOKUP($B$1&D$4&D$5&$C7,$L:$W,$C$5,0)) -> 0.00% | E7: =IF(ISERROR(VLOOKUP($B$1&E$4&E$5&$C7,$L:$W,$C$5,0)),"",VLOOKUP($B$1&E$4&E$5&$C7,$L:$W,$C$5,0)) -> 0.00% | F7: =IF(ISERROR(VLOOKUP($B$1&F$4&F$5&$C7,$L:$W,$C$5,0)),"",VLOOKUP($B$1&F$4&F$5&$C7,$L:$W,$C$5,0)) -> 0.00% | G7: =IF(ISERROR(VLOOKUP($B$1&G$4&G$5&$C7,$L:$W,$C$5,0)),"",VLOOKUP($B$1&G$4&G$5&$C7,$L:$W,$C$5,0)) -> 0.00% | H7: =IF(ISERROR(VLOOKUP($B$1&H$4&H$5&$C7,$L:$W,$C$5,0)),"",VLOOKUP($B$1&H$4&H$5&$C7,$L:$W,$C$5,0)) -> 0.00% | I7: =IF(ISERROR(VLOOKUP($B$1&I$4&I$5&$C7,$L:$W,$C$5,0)),"",VLOOKUP($B$1&I$4&I$5&$C7,$L:$W,$C$5,0)) -> 0.00% | L7: =IF(P7<>$B$1,"",P7&Q7&R7&V7) -> SDJ20154 | M7: =IF(OR(L7="",COUNTIF($M$4:M6,IF(ISERROR($R7*1),LEFT($R7,2)*1,$R7*1))>=1),"-",IF(ISERROR($R7*1),LEFT($R7,2)*1,$R7*1)) -> - | N7: =IF(OR(L7="",COUNTIF($N$4:N6,V7*1)>=1),"-",V7*1) -> 4 | P7: SDJ20 | Q7: 1 | R7: 5 | S7: 0 | T7: 0 | U7: 0 | V7: 4 | W7: 5.27%
B8: 2 | C8: =IF(ISERROR(SMALL($N:$N,$B8)),"",SMALL($N:$N,$B8)) -> 2 | D8: =IF(ISERROR(VLOOKUP($B$1&D$4&D$5&$C8,$L:$W,$C$5,0)),"",VLOOKUP($B$1&D$4&D$5&$C8,$L:$W,$C$5,0)) -> 3.57% | E8: =IF(ISERROR(VLOOKUP($B$1&E$4&E$5&$C8,$L:$W,$C$5,0)),"",VLOOKUP($B$1&E$4&E$5&$C8,$L:$W,$C$5,0)) -> 3.39% | F8: =IF(ISERROR(VLOOKUP($B$1&F$4&F$5&$C8,$L:$W,$C$5,0)),"",VLOOKUP($B$1&F$4&F$5&$C8,$L:$W,$C$5,0)) -> 4.76% | G8: =IF(ISERROR(VLOOKUP($B$1&G$4&G$5&$C8,$L:$W,$C$5,0)),"",VLOOKUP($B$1&G$4&G$5&$C8,$L:$W,$C$5,0)) -> 3.26% | H8: =IF(ISERROR(VLOOKUP($B$1&H$4&H$5&$C8,$L:$W,$C$5,0)),"",VLOOKUP($B$1&H$4&H$5&$C8,$L:$W,$C$5,0)) -> 3.89% | I8: =IF(ISERROR(VLOOKUP($B$1&I$4&I$5&$C8,$L:$W,$C$5,0)),"",VLOOKUP($B$1&I$4&I$5&$C8,$L:$W,$C$5,0)) -> 6.37% | L8: =IF(P8<>$B$1,"",P8&Q8&R8&V8) -> SDJ20155 | M8: =IF(OR(L8="",COUNTIF($M$4:M7,IF(ISERROR($R8*1),LEFT($R8,2)*1,$R8*1))>=1),"-",IF(ISERROR($R8*1),LEFT($R8,2)*1,$R8*1)) -> - | N8: =IF(OR(L8="",COUNTIF($N$4:N7,V8*1)>=1),"-",V8*1) -> 5 | P8: SDJ20 | Q8: 1 | R8: 5 | S8: 0 | T8: 0 | U8: 0 | V8: 5 | W8: 6.01%
B9: 3 | C9: =IF(ISERROR(SMALL($N:$N,$B9)),"",SMALL($N:$N,$B9)) -> 3 | D9: =IF(ISERROR(VLOOKUP($B$1&D$4&D$5&$C9,$L:$W,$C$5,0)),"",VLOOKUP($B$1&D$4&D$5&$C9,$L:$W,$C$5,0)) -> 4.72% | E9: =IF(ISERROR(VLOOKUP($B$1&E$4&E$5&$C9,$L:$W,$C$5,0)),"",VLOOKUP($B$1&E$4&E$5&$C9,$L:$W,$C$5,0)) -> 4.49% | F9: =IF(ISERROR(VLOOKUP($B$1&F$4&F$5&$C9,$L:$W,$C$5,0)),"",VLOOKUP($B$1&F$4&F$5&$C9,$L:$W,$C$5,0)) -> 6.37% | G9: =IF(ISERROR(VLOOKUP($B$1&G$4&G$5&$C9,$L:$W,$C$5,0)),"",VLOOKUP($B$1&G$4&G$5&$C9,$L:$W,$C$5,0)) -> 4.44% | H9: =IF(ISERROR(VLOOKUP($B$1&H$4&H$5&$C9,$L:$W,$C$5,0)),"",VLOOKUP($B$1&H$4&H$5&$C9,$L:$W,$C$5,0)) -> 5.22% | I9: =IF(ISERROR(VLOOKUP($B$1&I$4&I$5&$C9,$L:$W,$C$5,0)),"",VLOOKUP($B$1&I$4&I$5&$C9,$L:$W,$C$5,0)) -> 8.52% | L9: =IF(P9<>$B$1,"",P9&Q9&R9&V9) -> SDJ201510 | M9: =IF(OR(L9="",COUNTIF($M$4:M8,IF(ISERROR($R9*1),LEFT($R9,2)*1,$R9*1))>=1),"-",IF(ISERROR($R9*1),LEFT($R9,2)*1,$R9*1)) -> - | N9: =IF(OR(L9="",COUNTIF($N$4:N8,V9*1)>=1),"-",V9*1) -> 10 | P9: SDJ20 | Q9: 1 | R9: 5 | S9: 0 | T9: 0 | U9: 0 | V9: 10 | W9: 8.48%
B10: 4 | C10: =IF(ISERROR(SMALL($N:$N,$B10)),"",SMALL($N:$N,$B10)) -> 4 | D10: =IF(ISERROR(VLOOKUP($B$1&D$4&D$5&$C10,$L:$W,$C$5,0)),"",VLOOKUP($B$1&D$4&D$5&$C10,$L:$W,$C$5,0)) -> 5.27% | E10: =IF(ISERROR(VLOOKUP($B$1&E$4&E$5&$C10,$L:$W,$C$5,0)),"",VLOOKUP($B$1&E$4&E$5&$C10,$L:$W,$C$5,0)) -> 5.06% | F10: =IF(ISERROR(VLOOKUP($B$1&F$4&F$5&$C10,$L:$W,$C$5,0)),"",VLOOKUP($B$1&F$4&F$5&$C10,$L:$W,$C$5,0)) -> 7.21% | G10: =IF(ISERROR(VLOOKUP($B$1&G$4&G$5&$C10,$L:$W,$C$5,0)),"",VLOOKUP($B$1&G$4&G$5&$C10,$L:$W,$C$5,0)) -> 4.99% | H10: =IF(ISERROR(VLOOKUP($B$1&H$4&H$5&$C10,$L:$W,$C$5,0)),"",VLOOKUP($B$1&H$4&H$5&$C10,$L:$W,$C$5,0)) -> 5.90% | I10: =IF(ISERROR(VLOOKUP($B$1&I$4&I$5&$C10,$L:$W,$C$5,0)),"",VLOOKUP($B$1&I$4&I$5&$C10,$L:$W,$C$5,0)) -> 9.68% | L10: =IF(P10<>$B$1,"",P10&Q10&R10&V10) -> SDJ201515 | M10: =IF(OR(L10="",COUNTIF($M$4:M9,IF(ISERROR($R10*1),LEFT($R10,2)*1,$R10*1))>=1),"-",IF(ISERROR($R10*1),LEFT($R10,2)*1,$R10*1)) -> - | N10: =IF(OR(L10="",COUNTIF($N$4:N9,V10*1)>=1),"-",V10*1) -> 15 | P10: SDJ20 | Q10: 1 | R10: 5 | S10: 0 | T10: 0 | U10: 0 | V10: 15 | W10: 8.76%
B11: 5 | C11: =IF(ISERROR(SMALL($N:$N,$B11)),"",SMALL($N:$N,$B11)) -> 5 | D11: =IF(ISERROR(VLOOKUP($B$1&D$4&D$5&$C11,$L:$W,$C$5,0)),"",VLOOKUP($B$1&D$4&D$5&$C11,$L:$W,$C$5,0)) -> 6.01% | E11: =IF(ISERROR(VLOOKUP($B$1&E$4&E$5&$C11,$L:$W,$C$5,0)),"",VLOOKUP($B$1&E$4&E$5&$C11,$L:$W,$C$5,0)) -> 5.72% | F11: =IF(ISERROR(VLOOKUP($B$1&F$4&F$5&$C11,$L:$W,$C$5,0)),"",VLOOKUP($B$1&F$4&F$5&$C11,$L:$W,$C$5,0)) -> 8.28% | G11: =IF(ISERROR(VLOOKUP($B$1&G$4&G$5&$C11,$L:$W,$C$5,0)),"",VLOOKUP($B$1&G$4&G$5&$C11,$L:$W,$C$5,0)) -> 5.75% | H11: =IF(ISERROR(VLOOKUP($B$1&H$4&H$5&$C11,$L:$W,$C$5,0)),"",VLOOKUP($B$1&H$4&H$5&$C11,$L:$W,$C$5,0)) -> 6.76% | I11: =IF(ISERROR(VLOOKUP($B$1&I$4&I$5&$C11,$L:$W,$C$5,0)),"",VLOOKUP($B$1&I$4&I$5&$C11,$L:$W,$C$5,0)) -> 11.13% | L11: =IF(P11<>$B$1,"",P11&Q11&R11&V11) -> SDJ201520 | M11: =IF(OR(L11="",COUNTIF($M$4:M10,IF(ISERROR($R11*1),LEFT($R11,2)*1,$R11*1))>=1),"-",IF(ISERROR($R11*1),LEFT($R11,2)*1,$R11*1)) -> - | N11: =IF(OR(L11="",COUNTIF($N$4:N10,V11*1)>=1),"-",V11*1) -> 20 | P11: SDJ20 | Q11: 1 | R11: 5 | S11: 0 | T11: 0 | U11: 0 | V11: 20 | W11: 8.95%
B12: 6 | C12: =IF(ISERROR(SMALL($N:$N,$B12)),"",SMALL($N:$N,$B12)) -> 10 | D12: =IF(ISERROR(VLOOKUP($B$1&D$4&D$5&$C12,$L:$W,$C$5,0)),"",VLOOKUP($B$1&D$4&D$5&$C12,$L:$W,$C$5,0)) -> 8.48% | E12: =IF(ISERROR(VLOOKUP($B$1&E$4&E$5&$C12,$L:$W,$C$5,0)),"",VLOOKUP($B$1&E$4&E$5&$C12,$L:$W,$C$5,0)) -> 8.10% | F12: =IF(ISERROR(VLOOKUP($B$1&F$4&F$5&$C12,$L:$W,$C$5,0)),"",VLOOKUP($B$1&F$4&F$5&$C12,$L:$W,$C$5,0)) -> 12.67% | G12: =IF(ISERROR(VLOOKUP($B$1&G$4&G$5&$C12,$L:$W,$C$5,0)),"",VLOOKUP($B$1&G$4&G$5&$C12,$L:$W,$C$5,0)) -> 8.11% | H12: =IF(ISERROR(VLOOKUP($B$1&H$4&H$5&$C12,$L:$W,$C$5,0)),"",VLOOKUP($B$1&H$4&H$5&$C12,$L:$W,$C$5,0)) -> 9.85% | I12: =IF(ISERROR(VLOOKUP($B$1&I$4&I$5&$C12,$L:$W,$C$5,0)),"",VLOOKUP($B$1&I$4&I$5&$C12,$L:$W,$C$5,0)) -> 16.71% | L12: =IF(P12<>$B$1,"",P12&Q12&R12&V12) -> SDJ201351 | M12: =IF(OR(L12="",COUNTIF($M$4:M11,IF(ISERROR($R12*1),LEFT($R12,2)*1,$R12*1))>=1),"-",IF(ISERROR($R12*1),LEFT($R12,2)*1,$R12*1)) -> 35 | N12: =IF(OR(L12="",COUNTIF($N$4:N11,V12*1)>=1),"-",V12*1) -> - | P12: SDJ20 | Q12: 1 | R12: 35 | S12: 0 | T12: 0 | U12: 0 | V12: 1 | W12: 0.00%
B13: 7 | C13: =IF(ISERROR(SMALL($N:$N,$B13)),"",SMALL($N:$N,$B13)) -> 15 | D13: =IF(ISERROR(VLOOKUP($B$1&D$4&D$5&$C13,$L:$W,$C$5,0)),"",VLOOKUP($B$1&D$4&D$5&$C13,$L:$W,$C$5,0)) -> 8.76% | E13: =IF(ISERROR(VLOOKUP($B$1&E$4&E$5&$C13,$L:$W,$C$5,0)),"",VLOOKUP($B$1&E$4&E$5&$C13,$L:$W,$C$5,0)) -> 8.70% | F13: =IF(ISERROR(VLOOKUP($B$1&F$4&F$5&$C13,$L:$W,$C$5,0)),"",VLOOKUP($B$1&F$4&F$5&$C13,$L:$W,$C$5,0)) -> 14.94% | G13: =IF(ISERROR(VLOOKUP($B$1&G$4&G$5&$C13,$L:$W,$C$5,0)),"",VLOOKUP($B$1&G$4&G$5&$C13,$L:$W,$C$5,0)) -> 8.50% | H13: =IF(ISERROR(VLOOKUP($B$1&H$4&H$5&$C13,$L:$W,$C$5,0)),"",VLOOKUP($B$1&H$4&H$5&$C13,$L:$W,$C$5,0)) -> 10.89% | I13: =IF(ISERROR(VLOOKUP($B$1&I$4&I$5&$C13,$L:$W,$C$5,0)),"",VLOOKUP($B$1&I$4&I$5&$C13,$L:$W,$C$5,0)) -> 19.26% | L13: =IF(P13<>$B$1,"",P13&Q13&R13&V13) -> SDJ201352 | M13: =IF(OR(L13="",COUNTIF($M$4:M12,IF(ISERROR($R13*1),LEFT($R13,2)*1,$R13*1))>=1),"-",IF(ISERROR($R13*1),LEFT($R13,2)*1,$R13*1)) -> - | N13: =IF(OR(L13="",COUNTIF($N$4:N12,V13*1)>=1),"-",V13*1) -> - | P13: SDJ20 | Q13: 1 | R13: 35 | S13: 0 | T13: 0 | U13: 0 | V13: 2 | W13: 3.39%
B14: 8 | C14: =IF(ISERROR(SMALL($N:$N,$B14)),"",SMALL($N:$N,$B14)) -> 20 | D14: =IF(ISERROR(VLOOKUP($B$1&D$4&D$5&$C14,$L:$W,$C$5,0)),"",VLOOKUP($B$1&D$4&D$5&$C14,$L:$W,$C$5,0)) -> 8.95% | E14: =IF(ISERROR(VLOOKUP($B$1&E$4&E$5&$C14,$L:$W,$C$5,0)),"",VLOOKUP($B$1&E$4&E$5&$C14,$L:$W,$C$5,0)) -> 9.50% | F14: =IF(ISERROR(VLOOKUP($B$1&F$4&F$5&$C14,$L:$W,$C$5,0)),"",VLOOKUP($B$1&F$4&F$5&$C14,$L:$W,$C$5,0)) -> 17.83% | G14: =IF(ISERROR(VLOOKUP($B$1&G$4&G$5&$C14,$L:$W,$C$5,0)),"",VLOOKUP($B$1&G$4&G$5&$C14,$L:$W,$C$5,0)) -> 8.75% | H14: =IF(ISERROR(VLOOKUP($B$1&H$4&H$5&$C14,$L:$W,$C$5,0)),"",VLOOKUP($B$1&H$4&H$5&$C14,$L:$W,$C$5,0)) -> 12.00% | I14: =IF(ISERROR(VLOOKUP($B$1&I$4&I$5&$C14,$L:$W,$C$5,0)),"",VLOOKUP($B$1&I$4&I$5&$C14,$L:$W,$C$5,0)) -> 22.47% | L14: =IF(P14<>$B$1,"",P14&Q14&R14&V14) -> SDJ201353 | M14: =IF(OR(L14="",COUNTIF($M$4:M13,IF(ISERROR($R14*1),LEFT($R14,2)*1,$R14*1))>=1),"-",IF(ISERROR($R14*1),LEFT($R14,2)*1,$R14*1)) -> - | N14: =IF(OR(L14="",COUNTIF($N$4:N13,V14*1)>=1),"-",V14*1) -> - | P14: SDJ20 | Q14: 1 | R14: 35 | S14: 0 | T14: 0 | U14: 0 | V14: 3 | W14: 4.49%
C15: 以上區域為帶入列印頁範圍 | L15: =IF(P15<>$B$1,"",P15&Q15&R15&V15) -> SDJ201354 | M15: =IF(OR(L15="",COUNTIF($M$4:M14,IF(ISERROR($R15*1),LEFT($R15,2)*1,$R15*1))>=1),"-",IF(ISERROR($R15*1),LEFT($R15,2)*1,$R15*1)) -> - | N15: =IF(OR(L15="",COUNTIF($N$4:N14,V15*1)>=1),"-",V15*1) -> - | P15: SDJ20 | Q15: 1 | R15: 35 | S15: 0 | T15: 0 | U15: 0 | V15: 4 | W15: 5.06%
L16: =IF(P16<>$B$1,"",P16&Q16&R16&V16) -> SDJ201355 | M16: =IF(OR(L16="",COUNTIF($M$4:M15,IF(ISERROR($R16*1),LEFT($R16,2)*1,$R16*1))>=1),"-",IF(ISERROR($R16*1),LEFT($R16,2)*1,$R16*1)) -> - | N16: =IF(OR(L16="",COUNTIF($N$4:N15,V16*1)>=1),"-",V16*1) -> - | P16: SDJ20 | Q16: 1 | R16: 35 | S16: 0 | T16: 0 | U16: 0 | V16: 5 | W16: 5.72%
L17: =IF(P17<>$B$1,"",P17&Q17&R17&V17) -> SDJ2013510 | M17: =IF(OR(L17="",COUNTIF($M$4:M16,IF(ISERROR($R17*1),LEFT($R17,2)*1,$R17*1))>=1),"-",IF(ISERROR($R17*1),LEFT($R17,2)*1,$R17*1)) -> - | N17: =IF(OR(L17="",COUNTIF($N$4:N16,V17*1)>=1),"-",V17*1) -> - | P17: SDJ20 | Q17: 1 | R17: 35 | S17: 0 | T17: 0 | U17: 0 | V17: 10 | W17: 8.10%
L18: =IF(P18<>$B$1,"",P18&Q18&R18&V18) -> SDJ2013515 | M18: =IF(OR(L18="",COUNTIF($M$4:M17,IF(ISERROR($R18*1),LEFT($R18,2)*1,$R18*1))>=1),"-",IF(ISERROR($R18*1),LEFT($R18,2)*1,$R18*1)) -> - | N18: =IF(OR(L18="",COUNTIF($N$4:N17,V18*1)>=1),"-",V18*1) -> - | P18: SDJ20 | Q18: 1 | R18: 35 | S18: 0 | T18: 0 | U18: 0 | V18: 15 | W18: 8.70%
L19: =IF(P19<>$B$1,"",P19&Q19&R19&V19) -> SDJ2013520 | M19: =IF(OR(L19="",COUNTIF($M$4:M18,IF(ISERROR($R19*1),LEFT($R19,2)*1,$R19*1))>=1),"-",IF(ISERROR($R19*1),LEFT($R19,2)*1,$R19*1)) -> - | N19: =IF(OR(L19="",COUNTIF($N$4:N18,V19*1)>=1),"-",V19*1) -> - | P19: SDJ20 | Q19: 1 | R19: 35 | S19: 0 | T19: 0 | U19: 0 | V19: 20 | W19: 9.50%
L20: =IF(P20<>$B$1,"",P20&Q20&R20&V20) -> SDJ201501 | M20: =IF(OR(L20="",COUNTIF($M$4:M19,IF(ISERROR($R20*1),LEFT($R20,2)*1,$R20*1))>=1),"-",IF(ISERROR($R20*1),LEFT($R20,2)*1,$R20*1)) -> 50 | N20: =IF(OR(L20="",COUNTIF($N$4:N19,V20*1)>=1),"-",V20*1) -> - | P20: SDJ20 | Q20: 1 | R20: 50 | S20: 0 | T20: 0 | U20: 0 | V20: 1 | W20: 0.00%
L21: =IF(P21<>$B$1,"",P21&Q21&R21&V21) -> SDJ201502 | M21: =IF(OR(L21="",COUNTIF($M$4:M20,IF(ISERROR($R21*1),LEFT($R21,2)*1,$R21*1))>=1),"-",IF(ISERROR($R21*1),LEFT($R21,2)*1,$R21*1)) -> - | N21: =IF(OR(L21="",COUNTIF($N$4:N20,V21*1)>=1),"-",V21*1) -> - | P21: SDJ20 | Q21: 1 | R21: 50 | S21: 0 | T21: 0 | U21: 0 | V21: 2 | W21: 4.76%
L22: =IF(P22<>$B$1,"",P22&Q22&R22&V22) -> SDJ201503 | M22: =IF(OR(L22="",COUNTIF($M$4:M21,IF(ISERROR($R22*1),LEFT($R22,2)*1,$R22*1))>=1),"-",IF(ISERROR($R22*1),LEFT($R22,2)*1,$R22*1)) -> - | N22: =IF(OR(L22="",COUNTIF($N$4:N21,V22*1)>=1),"-",V22*1) -> - | P22: SDJ20 | Q22: 1 | R22: 50 | S22: 0 | T22: 0 | U22: 0 | V22: 3 | W22: 6.37%
L23: =IF(P23<>$B$1,"",P23&Q23&R23&V23) -> SDJ201504 | M23: =IF(OR(L23="",COUNTIF($M$4:M22,IF(ISERROR($R23*1),LEFT($R23,2)*1,$R23*1))>=1),"-",IF(ISERROR($R23*1),LEFT($R23,2)*1,$R23*1)) -> - | N23: =IF(OR(L23="",COUNTIF($N$4:N22,V23*1)>=1),"-",V23*1) -> - | P23: SDJ20 | Q23: 1 | R23: 50 | S23: 0 | T23: 0 | U23: 0 | V23: 4 | W23: 7.21%
L24: =IF(P24<>$B$1,"",P24&Q24&R24&V24) -> SDJ201505 | M24: =IF(OR(L24="",COUNTIF($M$4:M23,IF(ISERROR($R24*1),LEFT($R24,2)*1,$R24*1))>=1),"-",IF(ISERROR($R24*1),LEFT($R24,2)*1,$R24*1)) -> - | N24: =IF(OR(L24="",COUNTIF($N$4:N23,V24*1)>=1),"-",V24*1) -> - | P24: SDJ20 | Q24: 1 | R24: 50 | S24: 0 | T24: 0 | U24: 0 | V24: 5 | W24: 8.28%
L25: =IF(P25<>$B$1,"",P25&Q25&R25&V25) -> SDJ2015010 | M25: =IF(OR(L25="",COUNTIF($M$4:M24,IF(ISERROR($R25*1),LEFT($R25,2)*1,$R25*1))>=1),"-",IF(ISERROR($R25*1),LEFT($R25,2)*1,$R25*1)) -> - | N25: =IF(OR(L25="",COUNTIF($N$4:N24,V25*1)>=1),"-",V25*1) -> - | P25: SDJ20 | Q25: 1 | R25: 50 | S25: 0 | T25: 0 | U25: 0 | V25: 10 | W25: 12.67%
L26: =IF(P26<>$B$1,"",P26&Q26&R26&V26) -> SDJ2015015 | M26: =IF(OR(L26="",COUNTIF($M$4:M25,IF(ISERROR($R26*1),LEFT($R26,2)*1,$R26*1))>=1),"-",IF(ISERROR($R26*1),LEFT($R26,2)*1,$R26*1)) -> - | N26: =IF(OR(L26="",COUNTIF($N$4:N25,V26*1)>=1),"-",V26*1) -> - | P26: SDJ20 | Q26: 1 | R26: 50 | S26: 0 | T26: 0 | U26: 0 | V26: 15 | W26: 14.94%
L27: =IF(P27<>$B$1,"",P27&Q27&R27&V27) -> SDJ2015020 | M27: =IF(OR(L27="",COUNTIF($M$4:M26,IF(ISERROR($R27*1),LEFT($R27,2)*1,$R27*1))>=1),"-",IF(ISERROR($R27*1),LEFT($R27,2)*1,$R27*1)) -> - | N27: =IF(OR(L27="",COUNTIF($N$4:N26,V27*1)>=1),"-",V27*1) -> - | P27: SDJ20 | Q27: 1 | R27: 50 | S27: 0 | T27: 0 | U27: 0 | V27: 20 | W27: 17.83%
... L51: =IF(P51<>$B$1,"",P51&Q51&R51&V51) -> SDJ2025020 | M51: =IF(OR(L51="",COUNTIF($M$4:M50,IF(ISERROR($R51*1),LEFT($R51,2)*1,$R51*1))>=1),"-",IF(ISERROR($R51*1),LEFT($R51,2)*1,$R51*1)) -> - | N51: =IF(OR(L51="",COUNTIF($N$4:N50,V51*1)>=1),"-",V51*1) -> - | P51: SDJ20 | Q51: 2 | R51: 50 | S51: 0 | T51: 0 | U51: 0 | V51: 20 | W51: 22.47%
L52: =IF(P52<>$B$1,"",P52&Q52&R52&V52) | M52: =IF(OR(L52="",COUNTIF($M$4:M51,IF(ISERROR($R52*1),LEFT($R52,2)*1,$R52*1))>=1),"-",IF(ISERROR($R52*1),LEFT($R52,2)*1,$R52*1)) -> - | N52: =IF(OR(L52="",COUNTIF($N$4:N51,V52*1)>=1),"-",V52*1) -> -
L53: =IF(P53<>$B$1,"",P53&Q53&R53&V53) | M53: =IF(OR(L53="",COUNTIF($M$4:M52,IF(ISERROR($R53*1),LEFT($R53,2)*1,$R53*1))>=1),"-",IF(ISERROR($R53*1),LEFT($R53,2)*1,$R53*1)) -> - | N53: =IF(OR(L53="",COUNTIF($N$4:N52,V53*1)>=1),"-",V53*1) -> -
L54: =IF(P54<>$B$1,"",P54&Q54&R54&V54) | M54: =IF(OR(L54="",COUNTIF($M$4:M53,IF(ISERROR($R54*1),LEFT($R54,2)*1,$R54*1))>=1),"-",IF(ISERROR($R54*1),LEFT($R54,2)*1,$R54*1)) -> - | N54: =IF(OR(L54="",COUNTIF($N$4:N53,V54*1)>=1),"-",V54*1) -> -
L55: =IF(P55<>$B$1,"",P55&Q55&R55&V55) | M55: =IF(OR(L55="",COUNTIF($M$4:M54,IF(ISERROR($R55*1),LEFT($R55,2)*1,$R55*1))>=1),"-",IF(ISERROR($R55*1),LEFT($R55,2)*1,$R55*1)) -> - | N55: =IF(OR(L55="",COUNTIF($N$4:N54,V55*1)>=1),"-",V55*1) -> -
L56: =IF(P56<>$B$1,"",P56&Q56&R56&V56) | M56: =IF(OR(L56="",COUNTIF($M$4:M55,IF(ISERROR($R56*1),LEFT($R56,2)*1,$R56*1))>=1),"-",IF(ISERROR($R56*1),LEFT($R56,2)*1,$R56*1)) -> - | N56: =IF(OR(L56="",COUNTIF($N$4:N55,V56*1)>=1),"-",V56*1) -> -
L57: =IF(P57<>$B$1,"",P57&Q57&R57&V57) | M57: =IF(OR(L57="",COUNTIF($M$4:M56,IF(ISERROR($R57*1),LEFT($R57,2)*1,$R57*1))>=1),"-",IF(ISERROR($R57*1),LEFT($R57,2)*1,$R57*1)) -> - | N57: =IF(OR(L57="",COUNTIF($N$4:N56,V57*1)>=1),"-",V57*1) -> -
L58: =IF(P58<>$B$1,"",P58&Q58&R58&V58) | M58: =IF(OR(L58="",COUNTIF($M$4:M57,IF(ISERROR($R58*1),LEFT($R58,2)*1,$R58*1))>=1),"-",IF(ISERROR($R58*1),LEFT($R58,2)*1,$R58*1)) -> - | N58: =IF(OR(L58="",COUNTIF($N$4:N57,V58*1)>=1),"-",V58*1) -> -
L59: =IF(P59<>$B$1,"",P59&Q59&R59&V59) | M59: =IF(OR(L59="",COUNTIF($M$4:M58,IF(ISERROR($R59*1),LEFT($R59,2)*1,$R59*1))>=1),"-",IF(ISERROR($R59*1),LEFT($R59,2)*1,$R59*1)) -> - | N59: =IF(OR(L59="",COUNTIF($N$4:N58,V59*1)>=1),"-",V59*1) -> -
L60: =IF(P60<>$B$1,"",P60&Q60&R60&V60) | M60: =IF(OR(L60="",COUNTIF($M$4:M59,IF(ISERROR($R60*1),LEFT($R60,2)*1,$R60*1))>=1),"-",IF(ISERROR($R60*1),LEFT($R60,2)*1,$R60*1)) -> - | N60: =IF(OR(L60="",COUNTIF($N$4:N59,V60*1)>=1),"-",V60*1) -> -
L61: =IF(P61<>$B$1,"",P61&Q61&R61&V61) | M61: =IF(OR(L61="",COUNTIF($M$4:M60,IF(ISERROR($R61*1),LEFT($R61,2)*1,$R61*1))>=1),"-",IF(ISERROR($R61*1),LEFT($R61,2)*1,$R61*1)) -> - | N61: =IF(OR(L61="",COUNTIF($N$4:N60,V61*1)>=1),"-",V61*1) -> -
L62: =IF(P62<>$B$1,"",P62&Q62&R62&V62) | M62: =IF(OR(L62="",COUNTIF($M$4:M61,IF(ISERROR($R62*1),LEFT($R62,2)*1,$R62*1))>=1),"-",IF(ISERROR($R62*1),LEFT($R62,2)*1,$R62*1)) -> - | N62: =IF(OR(L62="",COUNTIF($N$4:N61,V62*1)>=1),"-",V62*1) -> -
L63: =IF(P63<>$B$1,"",P63&Q63&R63&V63) | M63: =IF(OR(L63="",COUNTIF($M$4:M62,IF(ISERROR($R63*1),LEFT($R63,2)*1,$R63*1))>=1),"-",IF(ISERROR($R63*1),LEFT($R63,2)*1,$R63*1)) -> - | N63: =IF(OR(L63="",COUNTIF($N$4:N62,V63*1)>=1),"-",V63*1) -> -
... L339: =IF(P339<>$B$1,"",P339&Q339&R339&V339) | M339: =IF(OR(L339="",COUNTIF($M$4:M338,IF(ISERROR($R339*1),LEFT($R339,2)*1,$R339*1))>=1),"-",IF(ISERROR($R339*1),LEFT($R339,2)*1,$R339*1)) -> - | N339: =IF(OR(L339="",COUNTIF($N$4:N338,V339*1)>=1),"-",V339*1) -> -

Sheet P_DATA
A1: GP | B1: SDJ | J1: =B1&TEXT(F1,"00")&TEXT(H1,"00") -> SDJ0000 | M1: EXP | Q1: =N1&TEXT(O1,"00")&TEXT(P1,"00") -> 0000 | DZ1: DIE | ED1: =EA1&TEXT(EB1,"00")&TEXT(EC1,"00") -> 0000
A2: 版次 | B2: 商品代號 | C2: 職業等級 | D2: 年期 | E2: 保額代碼 | F2: 性別 | G2: 投保金額 | H2: 年齡 | I2: 繳費年度 | J2: =B2&TEXT(F2,"00")&TEXT(H2,"00") -> 商品代號性別年齡 | K2: 保費 | M2: 版次 | N2: 商品代號 | O2: 性別 | P2: 年齡 | Q2: =N2&TEXT(O2,"00")&TEXT(P2,"00") -> 商品代號性別年齡 | R2: 第1年滿期保險金 | S2: 第2年滿期保險金 | T2: 第3年滿期保險金 | U2: 第4年滿期保險金 | V2: 第5年滿期保險金 | W2: 第6年滿期保險金 | X2: 第7年滿期保險金 | Y2: 第8年滿期保險金 | Z2: 第9年滿期保險金 | AA2: 第10年滿期保險金 | AB2: 第11年滿期保險金 | AC2: 第12年滿期保險金 | AD2: 第13年滿期保險金 | AE2: 第14年滿期保險金 | AF2: 第15年滿期保險金 | AG2: 第16年滿期保險金 | AH2: 第17年滿期保險金 | AI2: 第18年滿期保險金 | AJ2: 第19年滿期保險金 | AK2: 第20年滿期保險金 | AL2: 第21年滿期保險金 | AM2: 第22年滿期保險金 | AN2: 第23年滿期保險金 | AO2: 第24年滿期保險金 | AP2: 第25年滿期保險金 | AQ2: 第26年滿期保險金 | AR2: 第27年滿期保險金 | AS2: 第28年滿期保險金 | AT2: 第29年滿期保險金 | AU2: 第30年滿期保險金 | AV2: 第31年滿期保險金 | AW2: 第32年滿期保險金 | AX2: 第33年滿期保險金 | AY2: 第34年滿期保險金 | AZ2: 第35年滿期保險金 | BA2: 第36年滿期保險金 | BB2: 第37年滿期保險金 | BC2: 第38年滿期保險金 | BD2: 第39年滿期保險金 | BE2: 第40年滿期保險金 | BF2: 第41年滿期保險金 | BG2: 第42年滿期保險金 | BH2: 第43年滿期保險金 | BI2: 第44年滿期保險金 | BJ2: 第45年滿期保險金 | BK2: 第46年滿期保險金 | BL2: 第47年滿期保險金 | BM2: 第48年滿期保險金 | BN2: 第49年滿期保險金 | BO2: 第50年滿期保險金 | BP2: 第51年滿期保險金 | BQ2: 第52年滿期保險金 | BR2: 第53年滿期保險金 | BS2: 第54年滿期保險金 | BT2: 第55年滿期保險金 | BU2: 第56年滿期保險金 | BV2: 第57年滿期保險金 | BW2: 第58年滿期保險金 | BX2: 第59年滿期保險金 | BY2: 第60年滿期保險金 | BZ2: 第61年滿期保險金 | CA2: 第62年滿期保險金 | CB2: 第63年滿期保險金 | CC2: 第64年滿期保險金 | CD2: 第65年滿期保險金 | CE2: 第66年滿期保險金 | CF2: 第67年滿期保險金 | CG2: 第68年滿期保險金 | CH2: 第69年滿期保險金 | CI2: 第70年滿期保險金 | CJ2: 第71年滿期保險金 | CK2: 第72年滿期保險金 | CL2: 第73年滿期保險金 | CM2: 第74年滿期保險金 | CN2: 第75年滿期保險金 | CO2: 第76年滿期保險金 | CP2: 第77年滿期保險金 | CQ2: 第78年滿期保險金 | CR2: 第79年滿期保險金 | CS2: 第80年滿期保險金 | CT2: 第81年滿期保險金 | CU2: 第82年滿期保險金 | CV2: 第83年滿期保險金 | CW2: 第84年滿期保險金 | CX2: 第85年滿期保險金 | CY2: 第86年滿期保險金 | CZ2: 第87年滿期保險金 | DA2: 第88年滿期保險金 | DB2: 第89年滿期保險金 | DC2: 第90年滿期保險金 | DD2: 第91年滿期保險金 | DE2: 第92年滿期保險金 | DF2: 第93年滿期保險金 | DG2: 第94年滿期保險金 | DH2: 第95年滿期保險金 | DI2: 第96年滿期保險金 | DJ2: 第97年滿期保險金 | DK2: 第98年滿期保險金 | DL2: 第99年滿期保險金 | DM2: 第100年滿期保險金 | DN2: 第101年滿期保險金 | DO2: 第102年滿期保險金 | DP2: 第103年滿期保險金 | DQ2: 第104年滿期保險金 | DR2: 第105年滿期保險金 | DS2: 第106年滿期保險金 | DT2: 第107年滿期保險金 | DU2: 第108年滿期保險金 | DV2: 第109年滿期保險金 | DW2: 第110年滿期保險金 | DX2: 第111年滿期保險金 | DZ2: 版次 | EA2: 商品代號 | EB2: 性別 | EC2: 年齡 | ED2: =EA2&TEXT(EB2,"00")&TEXT(EC2,"00") -> 商品代號性別年齡 | EE2: 第1年身故保險金 | EF2: 第2年身故保險金 | EG2: 第3年身故保險金 | EH2: 第4年身故保險金 | EI2: 第5年身故保險金 | EJ2: 第6年身故保險金 | EK2: 第7年身故保險金 | EL2: 第8年身故保險金 | EM2: 第9年身故保險金 | EN2: 第10年身故保險金 | EO2: 第11年身故保險金 | EP2: 第12年身故保險金 | EQ2: 第13年身故保險金 | ER2: 第14年身故保險金 | ES2: 第15年身故保險金 | ET2: 第16年身故保險金 | EU2: 第17年身故保險金 | EV2: 第18年身故保險金 | EW2: 第19年身故保險金 | EX2: 第20年身故保險金 | EY2: 第21年身故保險金 | EZ2: 第22年身故保險金 | FA2: 第23年身故保險金 | FB2: 第24年身故保險金 | FC2: 第25年身故保險金 | FD2: 第26年身故保險金 | FE2: 第27年身故保險金 | FF2: 第28年身故保險金 | FG2: 第29年身故保險金 | FH2: 第30年身故保險金 | FI2: 第31年身故保險金 | FJ2: 第32年身故保險金 | FK2: 第33年身故保險金 | FL2: 第34年身故保險金 | FM2: 第35年身故保險金 | FN2: 第36年身故保險金 | FO2: 第37年身故保險金 | FP2: 第38年身故保險金 | FQ2: 第39年身故保險金 | FR2: 第40年身故保險金 | FS2: 第41年身故保險金 | FT2: 第42年身故保險金 | FU2: 第43年身故保險金 | FV2: 第44年身故保險金 | FW2: 第45年身故保險金 | FX2: 第46年身故保險金 | FY2: 第47年身故保險金 | FZ2: 第48年身故保險金 | GA2: 第49年身故保險金 | GB2: 第50年身故保險金 | GC2: 第51年身故保險金 | GD2: 第52年身故保險金 | GE2: 第53年身故保險金 | GF2: 第54年身故保險金 | GG2: 第55年身故保險金 | GH2: 第56年身故保險金 | GI2: 第57年身故保險金 | GJ2: 第58年身故保險金 | GK2: 第59年身故保險金 | GL2: 第60年身故保險金 | GM2: 第61年身故保險金 | GN2: 第62年身故保險金 | GO2: 第63年身故保險金 | GP2: 第64年身故保險金 | GQ2: 第65年身故保險金 | GR2: 第66年身故保險金 | GS2: 第67年身故保險金 | GT2: 第68年身故保險金 | GU2: 第69年身故保險金 | GV2: 第70年身故保險金 | GW2: 第71年身故保險金 | GX2: 第72年身故保險金 | GY2: 第73年身故保險金 | GZ2: 第74年身故保險金額 | HA2: 第75年身故保險金 | HB2: 第76年身故保險金 | HC2: 第77年身故保險金 | HD2: 第78年身故保險金 | HE2: 第79年身故保險金 | HF2: 第80年身故保險金 | HG2: 第81年身故保險金 | HH2: 第82年身故保險金 | HI2: 第83年身故保險金 | HJ2: 第84年身故保險金 | HK2: 第85年身故保險金 | HL2: 第86年身故保險金 | HM2: 第87年身故保險金 | HN2: 第88年身故保險金 | HO2: 第89年身故保險金 | HP2: 第90年身故保險金 | HQ2: 第91年身故保險金 | HR2: 第92年身故保險金 | HS2: 第93年身故保險金 | HT2: 第94年身故保險金 | HU2: 第95年身故保險金 | HV2: 第96年身故保險金 | HW2: 第97年身故保險金 | HX2: 第98年身故保險金 | HY2: 第99年身故保險金 | HZ2: 第100年身故保險金 | IA2: 第101年身故保險金 | IB2: 第102年身故保險金 | IC2: 第103年身故保險金 | ID2: 第104年身故保險金 | IE2: 第105年身故保險金 | IF2: 第106年身故保險金 | IG2: 第107年身故保險金 | IH2: 第108年身故保險金 | II2: 第109年身故保險金 | IJ2: 第110年身故保險金 | IK2: 第111年身故保險金
A3: 56 | B3: SDJ20 | F3: 1 | H3: 0 | J3: =B3&TEXT(F3,"00")&TEXT(H3,"00") -> SDJ200100 | K3: 239 | M3: 56 | N3: SDJ20 | O3: 1 | P3: 0 | Q3: =N3&TEXT(O3,"00")&TEXT(P3,"00") -> SDJ200100 | R3: 0 | S3: 0 | T3: 0 | U3: 0 | V3: 0 | W3: 0 | X3: 0 | Y3: 0 | Z3: 0 | AA3: 0 | AB3: 0 | AC3: 0 | AD3: 0 | AE3: 0 | AF3: 0 | AG3: 0 | AH3: 0 | AI3: 0 | AJ3: 0 | AK3: 0 | AL3: 0 | AM3: 0 | AN3: 0 | AO3: 0 | AP3: 0 | AQ3: 0 | AR3: 0 | AS3: 0 | AT3: 0 | AU3: 0 | AV3: 0 | AW3: 0 | AX3: 0 | AY3: 0 | AZ3: 0 | BA3: 0 | BB3: 0 | BC3: 0 | BD3: 0 | BE3: 0 | BF3: 0 | BG3: 0 | BH3: 0 | BI3: 0 | BJ3: 0 | BK3: 0 | BL3: 0 | BM3: 0 | BN3: 0 | BO3: 0 | BP3: 0 | BQ3: 0 | BR3: 0 | BS3: 0 | BT3: 0 | BU3: 0 | BV3: 0 | BW3: 0 | BX3: 0 | BY3: 0 | BZ3: 0 | CA3: 0 | CB3: 0 | CC3: 0 | CD3: 0 | CE3: 0 | CF3: 0 | CG3: 0 | CH3: 0 | CI3: 0 | CJ3: 0 | CK3: 0 | CL3: 0 | CM3: 0 | CN3: 0 | CO3: 0 | CP3: 0 | CQ3: 0 | CR3: 0 | CS3: 0 | CT3: 0 | CU3: 0 | CV3: 0 | CW3: 0 | CX3: 10000 | CY3: 0 | CZ3: 0 | DA3: 0 | DB3: 0 | DC3: 0 | DD3: 0 | DE3: 0 | DF3: 0 | DG3: 0 | DH3: 0 | DI3: 0 | DJ3: 0 | DK3: 0 | DL3: 0 | DM3: 0 | DN3: 0 | DO3: 0 | DP3: 0 | DQ3: 0 | DR3: 0 | DS3: 0 | DT3: 0 | DU3: 0 | DV3: 0 | DW3: 0 | DX3: 0 | DZ3: 56 | EA3: SDJ20 | EB3: 1 | EC3: 0 | ED3: =EA3&TEXT(EB3,"00")&TEXT(EC3,"00") -> SDJ200100 | EE3: 10000 | EF3: 10000 | EG3: 10000 | EH3: 10000 | EI3: 10000 | EJ3: 10000 | EK3: 10000 | EL3: 10000 | EM3: 10000 | EN3: 10000 | EO3: 10000 | EP3: 10000 | EQ3: 10000 | ER3: 10000 | ES3: 10000 | ET3: 10000 | EU3: 10000 | EV3: 10000 | EW3: 10000 | EX3: 10000 | EY3: 10000 | EZ3: 10000 | FA3: 10000 | FB3: 10000 | FC3: 10000 | FD3: 10000 | FE3: 10000 | FF3: 10000 | FG3: 10000 | FH3: 10000 | FI3: 10000 | FJ3: 10000 | FK3: 10000 | FL3: 10000 | FM3: 10000 | FN3: 10000 | FO3: 10000 | FP3: 10000 | FQ3: 10000 | FR3: 10000 | FS3: 10000 | FT3: 10000 | FU3: 10000 | FV3: 10000 | FW3: 10000 | FX3: 10000 | FY3: 10000 | FZ3: 10000 | GA3: 10000 | GB3: 10000 | GC3: 10000 | GD3: 10000 | GE3: 10000 | GF3: 10000 | GG3: 10000 | GH3: 10000 | GI3: 10000 | GJ3: 10000 | GK3: 10000 | GL3: 10000 | GM3: 10000 | GN3: 10000 | GO3: 10000 | GP3: 10000 | GQ3: 10000 | GR3: 10000 | GS3: 10000 | GT3: 10000 | GU3: 10000 | GV3: 10000 | GW3: 10000 | GX3: 10000 | GY3: 10000 | GZ3: 10000 | HA3: 10000 | HB3: 10000 | HC3: 10000 | HD3: 10000 | HE3: 10000 | HF3: 10000 | HG3: 10000 | HH3: 10000 | HI3: 10000 | HJ3: 10000 | HK3: 10000 | HL3: 0 | HM3: 0 | HN3: 0 | HO3: 0 | HP3: 0 | HQ3: 0 | HR3: 0 | HS3: 0 | HT3: 0 | HU3: 0 | HV3: 0 | HW3: 0 | HX3: 0 | HY3: 0 | HZ3: 0 | IA3: 0 | IB3: 0 | IC3: 0 | ID3: 0 | IE3: 0 | IF3: 0 | IG3: 0 | IH3: 0 | II3: 0 | IJ3: 0 | IK3: 0
A4: 56 | B4: SDJ20 | F4: 1 | H4: 1 | J4: =B4&TEXT(F4,"00")&TEXT(H4,"00") -> SDJ200101 | K4: 243 | M4: 56 | N4: SDJ20 | O4: 1 | P4: 1 | Q4: =N4&TEXT(O4,"00")&TEXT(P4,"00") -> SDJ200101 | R4: 0 | S4: 0 | T4: 0 | U4: 0 | V4: 0 | W4: 0 | X4: 0 | Y4: 0 | Z4: 0 | AA4: 0 | AB4: 0 | AC4: 0 | AD4: 0 | AE4: 0 | AF4: 0 | AG4: 0 | AH4: 0 | AI4: 0 | AJ4: 0 | AK4: 0 | AL4: 0 | AM4: 0 | AN4: 0 | AO4: 0 | AP4: 0 | AQ4: 0 | AR4: 0 | AS4: 0 | AT4: 0 | AU4: 0 | AV4: 0 | AW4: 0 | AX4: 0 | AY4: 0 | AZ4: 0 | BA4: 0 | BB4: 0 | BC4: 0 | BD4: 0 | BE4: 0 | BF4: 0 | BG4: 0 | BH4: 0 | BI4: 0 | BJ4: 0 | BK4: 0 | BL4: 0 | BM4: 0 | BN4: 0 | BO4: 0 | BP4: 0 | BQ4: 0 | BR4: 0 | BS4: 0 | BT4: 0 | BU4: 0 | BV4: 0 | BW4: 0 | BX4: 0 | BY4: 0 | BZ4: 0 | CA4: 0 | CB4: 0 | CC4: 0 | CD4: 0 | CE4: 0 | CF4: 0 | CG4: 0 | CH4: 0 | CI4: 0 | CJ4: 0 | CK4: 0 | CL4: 0 | CM4: 0 | CN4: 0 | CO4: 0 | CP4: 0 | CQ4: 0 | CR4: 0 | CS4: 0 | CT4: 0 | CU4: 0 | CV4: 0 | CW4: 10000 | CX4: 0 | CY4: 0 | CZ4: 0 | DA4: 0 | DB4: 0 | DC4: 0 | DD4: 0 | DE4: 0 | DF4: 0 | DG4: 0 | DH4: 0 | DI4: 0 | DJ4: 0 | DK4: 0 | DL4: 0 | DM4: 0 | DN4: 0 | DO4: 0 | DP4: 0 | DQ4: 0 | DR4: 0 | DS4: 0 | DT4: 0 | DU4: 0 | DV4: 0 | DW4: 0 | DX4: 0 | DZ4: 56 | EA4: SDJ20 | EB4: 1 | EC4: 1 | ED4: =EA4&TEXT(EB4,"00")&TEXT(EC4,"00") -> SDJ200101 | EE4: 10000 | EF4: 10000 | EG4: 10000 | EH4: 10000 | EI4: 10000 | EJ4: 10000 | EK4: 10000 | EL4: 10000 | EM4: 10000 | EN4: 10000 | EO4: 10000 | EP4: 10000 | EQ4: 10000 | ER4: 10000 | ES4: 10000 | ET4: 10000 | EU4: 10000 | EV4: 10000 | EW4: 10000 | EX4: 10000 | EY4: 10000 | EZ4: 10000 | FA4: 10000 | FB4: 10000 | FC4: 10000 | FD4: 10000 | FE4: 10000 | FF4: 10000 | FG4: 10000 | FH4: 10000 | FI4: 10000 | FJ4: 10000 | FK4: 10000 | FL4: 10000 | FM4: 10000 | FN4: 10000 | FO4: 10000 | FP4: 10000 | FQ4: 10000 | FR4: 10000 | FS4: 10000 | FT4: 10000 | FU4: 10000 | FV4: 10000 | FW4: 10000 | FX4: 10000 | FY4: 10000 | FZ4: 10000 | GA4: 10000 | GB4: 10000 | GC4: 10000 | GD4: 10000 | GE4: 10000 | GF4: 10000 | GG4: 10000 | GH4: 10000 | GI4: 10000 | GJ4: 10000 | GK4: 10000 | GL4: 10000 | GM4: 10000 | GN4: 10000 | GO4: 10000 | GP4: 10000 | GQ4: 10000 | GR4: 10000 | GS4: 10000 | GT4: 10000 | GU4: 10000 | GV4: 10000 | GW4: 10000 | GX4: 10000 | GY4: 10000 | GZ4: 10000 | HA4: 10000 | HB4: 10000 | HC4: 10000 | HD4: 10000 | HE4: 10000 | HF4: 10000 | HG4: 10000 | HH4: 10000 | HI4: 10000 | HJ4: 10000 | HK4: 0 | HL4: 0 | HM4: 0 | HN4: 0 | HO4: 0 | HP4: 0 | HQ4: 0 | HR4: 0 | HS4: 0 | HT4: 0 | HU4: 0 | HV4: 0 | HW4: 0 | HX4: 0 | HY4: 0 | HZ4: 0 | IA4: 0 | IB4: 0 | IC4: 0 | ID4: 0 | IE4: 0 | IF4: 0 | IG4: 0 | IH4: 0 | II4: 0 | IJ4: 0 | IK4: 0
A5: 56 | B5: SDJ20 | F5: 1 | H5: 2 | J5: =B5&TEXT(F5,"00")&TEXT(H5,"00") -> SDJ200102 | K5: 247 | M5: 56 | N5: SDJ20 | O5: 1 | P5: 2 | Q5: =N5&TEXT(O5,"00")&TEXT(P5,"00") -> SDJ200102 | R5: 0 | S5: 0 | T5: 0 | U5: 0 | V5: 0 | W5: 0 | X5: 0 | Y5: 0 | Z5: 0 | AA5: 0 | AB5: 0 | AC5: 0 | AD5: 0 | AE5: 0 | AF5: 0 | AG5: 0 | AH5: 0 | AI5: 0 | AJ5: 0 | AK5: 0 | AL5: 0 | AM5: 0 | AN5: 0 | AO5: 0 | AP5: 0 | AQ5: 0 | AR5: 0 | AS5: 0 | AT5: 0 | AU5: 0 | AV5: 0 | AW5: 0 | AX5: 0 | AY5: 0 | AZ5: 0 | BA5: 0 | BB5: 0 | BC5: 0 | BD5: 0 | BE5: 0 | BF5: 0 | BG5: 0 | BH5: 0 | BI5: 0 | BJ5: 0 | BK5: 0 | BL5: 0 | BM5: 0 | BN5: 0 | BO5: 0 | BP5: 0 | BQ5: 0 | BR5: 0 | BS5: 0 | BT5: 0 | BU5: 0 | BV5: 0 | BW5: 0 | BX5: 0 | BY5: 0 | BZ5: 0 | CA5: 0 | CB5: 0 | CC5: 0 | CD5: 0 | CE5: 0 | CF5: 0 | CG5: 0 | CH5: 0 | CI5: 0 | CJ5: 0 | CK5: 0 | CL5: 0 | CM5: 0 | CN5: 0 | CO5: 0 | CP5: 0 | CQ5: 0 | CR5: 0 | CS5: 0 | CT5: 0 | CU5: 0 | CV5: 10000 | CW5: 0 | CX5: 0 | CY5: 0 | CZ5: 0 | DA5: 0 | DB5: 0 | DC5: 0 | DD5: 0 | DE5: 0 | DF5: 0 | DG5: 0 | DH5: 0 | DI5: 0 | DJ5: 0 | DK5: 0 | DL5: 0 | DM5: 0 | DN5: 0 | DO5: 0 | DP5: 0 | DQ5: 0 | DR5: 0 | DS5: 0 | DT5: 0 | DU5: 0 | DV5: 0 | DW5: 0 | DX5: 0 | DZ5: 56 | EA5: SDJ20 | EB5: 1 | EC5: 2 | ED5: =EA5&TEXT(EB5,"00")&TEXT(EC5,"00") -> SDJ200102 | EE5: 10000 | EF5: 10000 | EG5: 10000 | EH5: 10000 | EI5: 10000 | EJ5: 10000 | EK5: 10000 | EL5: 10000 | EM5: 10000 | EN5: 10000 | EO5: 10000 | EP5: 10000 | EQ5: 10000 | ER5: 10000 | ES5: 10000 | ET5: 10000 | EU5: 10000 | EV5: 10000 | EW5: 10000 | EX5: 10000 | EY5: 10000 | EZ5: 10000 | FA5: 10000 | FB5: 10000 | FC5: 10000 | FD5: 10000 | FE5: 10000 | FF5: 10000 | FG5: 10000 | FH5: 10000 | FI5: 10000 | FJ5: 10000 | FK5: 10000 | FL5: 10000 | FM5: 10000 | FN5: 10000 | FO5: 10000 | FP5: 10000 | FQ5: 10000 | FR5: 10000 | FS5: 10000 | FT5: 10000 | FU5: 10000 | FV5: 10000 | FW5: 10000 | FX5: 10000 | FY5: 10000 | FZ5: 10000 | GA5: 10000 | GB5: 10000 | GC5: 10000 | GD5: 10000 | GE5: 10000 | GF5: 10000 | GG5: 10000 | GH5: 10000 | GI5: 10000 | GJ5: 10000 | GK5: 10000 | GL5: 10000 | GM5: 10000 | GN5: 10000 | GO5: 10000 | GP5: 10000 | GQ5: 10000 | GR5: 10000 | GS5: 10000 | GT5: 10000 | GU5: 10000 | GV5: 10000 | GW5: 10000 | GX5: 10000 | GY5: 10000 | GZ5: 10000 | HA5: 10000 | HB5: 10000 | HC5: 10000 | HD5: 10000 | HE5: 10000 | HF5: 10000 | HG5: 10000 | HH5: 10000 | HI5: 10000 | HJ5: 0 | HK5: 0 | HL5: 0 | HM5: 0 | HN5: 0 | HO5: 0 | HP5: 0 | HQ5: 0 | HR5: 0 | HS5: 0 | HT5: 0 | HU5: 0 | HV5: 0 | HW5: 0 | HX5: 0 | HY5: 0 | HZ5: 0 | IA5: 0 | IB5: 0 | IC5: 0 | ID5: 0 | IE5: 0 | IF5: 0 | IG5: 0 | IH5: 0 | II5: 0 | IJ5: 0 | IK5: 0
A6: 56 | B6: SDJ20 | F6: 1 | H6: 3 | J6: =B6&TEXT(F6,"00")&TEXT(H6,"00") -> SDJ200103 | K6: 251 | M6: 56 | N6: SDJ20 | O6: 1 | P6: 3 | Q6: =N6&TEXT(O6,"00")&TEXT(P6,"00") -> SDJ200103 | R6: 0 | S6: 0 | T6: 0 | U6: 0 | V6: 0 | W6: 0 | X6: 0 | Y6: 0 | Z6: 0 | AA6: 0 | AB6: 0 | AC6: 0 | AD6: 0 | AE6: 0 | AF6: 0 | AG6: 0 | AH6: 0 | AI6: 0 | AJ6: 0 | AK6: 0 | AL6: 0 | AM6: 0 | AN6: 0 | AO6: 0 | AP6: 0 | AQ6: 0 | AR6: 0 | AS6: 0 | AT6: 0 | AU6: 0 | AV6: 0 | AW6: 0 | AX6: 0 | AY6: 0 | AZ6: 0 | BA6: 0 | BB6: 0 | BC6: 0 | BD6: 0 | BE6: 0 | BF6: 0 | BG6: 0 | BH6: 0 | BI6: 0 | BJ6: 0 | BK6: 0 | BL6: 0 | BM6: 0 | BN6: 0 | BO6: 0 | BP6: 0 | BQ6: 0 | BR6: 0 | BS6: 0 | BT6: 0 | BU6: 0 | BV6: 0 | BW6: 0 | BX6: 0 | BY6: 0 | BZ6: 0 | CA6: 0 | CB6: 0 | CC6: 0 | CD6: 0 | CE6: 0 | CF6: 0 | CG6: 0 | CH6: 0 | CI6: 0 | CJ6: 0 | CK6: 0 | CL6: 0 | CM6: 0 | CN6: 0 | CO6: 0 | CP6: 0 | CQ6: 0 | CR6: 0 | CS6: 0 | CT6: 0 | CU6: 10000 | CV6: 0 | CW6: 0 | CX6: 0 | CY6: 0 | CZ6: 0 | DA6: 0 | DB6: 0 | DC6: 0 | DD6: 0 | DE6: 0 | DF6: 0 | DG6: 0 | DH6: 0 | DI6: 0 | DJ6: 0 | DK6: 0 | DL6: 0 | DM6: 0 | DN6: 0 | DO6: 0 | DP6: 0 | DQ6: 0 | DR6: 0 | DS6: 0 | DT6: 0 | DU6: 0 | DV6: 0 | DW6: 0 | DX6: 0 | DZ6: 56 | EA6: SDJ20 | EB6: 1 | EC6: 3 | ED6: =EA6&TEXT(EB6,"00")&TEXT(EC6,"00") -> SDJ200103 | EE6: 10000 | EF6: 10000 | EG6: 10000 | EH6: 10000 | EI6: 10000 | EJ6: 10000 | EK6: 10000 | EL6: 10000 | EM6: 10000 | EN6: 10000 | EO6: 10000 | EP6: 10000 | EQ6: 10000 | ER6: 10000 | ES6: 10000 | ET6: 10000 | EU6: 10000 | EV6: 10000 | EW6: 10000 | EX6: 10000 | EY6: 10000 | EZ6: 10000 | FA6: 10000 | FB6: 10000 | FC6: 10000 | FD6: 10000 | FE6: 10000 | FF6: 10000 | FG6: 10000 | FH6: 10000 | FI6: 10000 | FJ6: 10000 | FK6: 10000 | FL6: 10000 | FM6: 10000 | FN6: 10000 | FO6: 10000 | FP6: 10000 | FQ6: 10000 | FR6: 10000 | FS6: 10000 | FT6: 10000 | FU6: 10000 | FV6: 10000 | FW6: 10000 | FX6: 10000 | FY6: 10000 | FZ6: 10000 | GA6: 10000 | GB6: 10000 | GC6: 10000 | GD6: 10000 | GE6: 10000 | GF6: 10000 | GG6: 10000 | GH6: 10000 | GI6: 10000 | GJ6: 10000 | GK6: 10000 | GL6: 10000 | GM6: 10000 | GN6: 10000 | GO6: 10000 | GP6: 10000 | GQ6: 10000 | GR6: 10000 | GS6: 10000 | GT6: 10000 | GU6: 10000 | GV6: 10000 | GW6: 10000 | GX6: 10000 | GY6: 10000 | GZ6: 10000 | HA6: 10000 | HB6: 10000 | HC6: 10000 | HD6: 10000 | HE6: 10000 | HF6: 10000 | HG6: 10000 | HH6: 10000 | HI6: 0 | HJ6: 0 | HK6: 0 | HL6: 0 | HM6: 0 | HN6: 0 | HO6: 0 | HP6: 0 | HQ6: 0 | HR6: 0 | HS6: 0 | HT6: 0 | HU6: 0 | HV6: 0 | HW6: 0 | HX6: 0 | HY6: 0 | HZ6: 0 | IA6: 0 | IB6: 0 | IC6: 0 | ID6: 0 | IE6: 0 | IF6: 0 | IG6: 0 | IH6: 0 | II6: 0 | IJ6: 0 | IK6: 0
A7: 56 | B7: SDJ20 | F7: 1 | H7: 4 | J7: =B7&TEXT(F7,"00")&TEXT(H7,"00") -> SDJ200104 | K7: 255 | M7: 56 | N7: SDJ20 | O7: 1 | P7: 4 | Q7: =N7&TEXT(O7,"00")&TEXT(P7,"00") -> SDJ200104 | R7: 0 | S7: 0 | T7: 0 | U7: 0 | V7: 0 | W7: 0 | X7: 0 | Y7: 0 | Z7: 0 | AA7: 0 | AB7: 0 | AC7: 0 | AD7: 0 | AE7: 0 | AF7: 0 | AG7: 0 | AH7: 0 | AI7: 0 | AJ7: 0 | AK7: 0 | AL7: 0 | AM7: 0 | AN7: 0 | AO7: 0 | AP7: 0 | AQ7: 0 | AR7: 0 | AS7: 0 | AT7: 0 | AU7: 0 | AV7: 0 | AW7: 0 | AX7: 0 | AY7: 0 | AZ7: 0 | BA7: 0 | BB7: 0 | BC7: 0 | BD7: 0 | BE7: 0 | BF7: 0 | BG7: 0 | BH7: 0 | BI7: 0 | BJ7: 0 | BK7: 0 | BL7: 0 | BM7: 0 | BN7: 0 | BO7: 0 | BP7: 0 | BQ7: 0 | BR7: 0 | BS7: 0 | BT7: 0 | BU7: 0 | BV7: 0 | BW7: 0 | BX7: 0 | BY7: 0 | BZ7: 0 | CA7: 0 | CB7: 0 | CC7: 0 | CD7: 0 | CE7: 0 | CF7: 0 | CG7: 0 | CH7: 0 | CI7: 0 | CJ7: 0 | CK7: 0 | CL7: 0 | CM7: 0 | CN7: 0 | CO7: 0 | CP7: 0 | CQ7: 0 | CR7: 0 | CS7: 0 | CT7: 10000 | CU7: 0 | CV7: 0 | CW7: 0 | CX7: 0 | CY7: 0 | CZ7: 0 | DA7: 0 | DB7: 0 | DC7: 0 | DD7: 0 | DE7: 0 | DF7: 0 | DG7: 0 | DH7: 0 | DI7: 0 | DJ7: 0 | DK7: 0 | DL7: 0 | DM7: 0 | DN7: 0 | DO7: 0 | DP7: 0 | DQ7: 0 | DR7: 0 | DS7: 0 | DT7: 0 | DU7: 0 | DV7: 0 | DW7: 0 | DX7: 0 | DZ7: 56 | EA7: SDJ20 | EB7: 1 | EC7: 4 | ED7: =EA7&TEXT(EB7,"00")&TEXT(EC7,"00") -> SDJ200104 | EE7: 10000 | EF7: 10000 | EG7: 10000 | EH7: 10000 | EI7: 10000 | EJ7: 10000 | EK7: 10000 | EL7: 10000 | EM7: 10000 | EN7: 10000 | EO7: 10000 | EP7: 10000 | EQ7: 10000 | ER7: 10000 | ES7: 10000 | ET7: 10000 | EU7: 10000 | EV7: 10000 | EW7: 10000 | EX7: 10000 | EY7: 10000 | EZ7: 10000 | FA7: 10000 | FB7: 10000 | FC7: 10000 | FD7: 10000 | FE7: 10000 | FF7: 10000 | FG7: 10000 | FH7: 10000 | FI7: 10000 | FJ7: 10000 | FK7: 10000 | FL7: 10000 | FM7: 10000 | FN7: 10000 | FO7: 10000 | FP7: 10000 | FQ7: 10000 | FR7: 10000 | FS7: 10000 | FT7: 10000 | FU7: 10000 | FV7: 10000 | FW7: 10000 | FX7: 10000 | FY7: 10000 | FZ7: 10000 | GA7: 10000 | GB7: 10000 | GC7: 10000 | GD7: 10000 | GE7: 10000 | GF7: 10000 | GG7: 10000 | GH7: 10000 | GI7: 10000 | GJ7: 10000 | GK7: 10000 | GL7: 10000 | GM7: 10000 | GN7: 10000 | GO7: 10000 | GP7: 10000 | GQ7: 10000 | GR7: 10000 | GS7: 10000 | GT7: 10000 | GU7: 10000 | GV7: 10000 | GW7: 10000 | GX7: 10000 | GY7: 10000 | GZ7: 10000 | HA7: 10000 | HB7: 10000 | HC7: 10000 | HD7: 10000 | HE7: 10000 | HF7: 10000 | HG7: 10000 | HH7: 0 | HI7: 0 | HJ7: 0 | HK7: 0 | HL7: 0 | HM7: 0 | HN7: 0 | HO7: 0 | HP7: 0 | HQ7: 0 | HR7: 0 | HS7: 0 | HT7: 0 | HU7: 0 | HV7: 0 | HW7: 0 | HX7: 0 | HY7: 0 | HZ7: 0 | IA7: 0 | IB7: 0 | IC7: 0 | ID7: 0 | IE7: 0 | IF7: 0 | IG7: 0 | IH7: 0 | II7: 0 | IJ7: 0 | IK7: 0
A8: 56 | B8: SDJ20 | F8: 1 | H8: 5 | J8: =B8&TEXT(F8,"00")&TEXT(H8,"00") -> SDJ200105 | K8: 259 | M8: 56 | N8: SDJ20 | O8: 1 | P8: 5 | Q8: =N8&TEXT(O8,"00")&TEXT(P8,"00") -> SDJ200105 | R8: 0 | S8: 0 | T8: 0 | U8: 0 | V8: 0 | W8: 0 | X8: 0 | Y8: 0 | Z8: 0 | AA8: 0 | AB8: 0 | AC8: 0 | AD8: 0 | AE8: 0 | AF8: 0 | AG8: 0 | AH8: 0 | AI8: 0 | AJ8: 0 | AK8: 0 | AL8: 0 | AM8: 0 | AN8: 0 | AO8: 0 | AP8: 0 | AQ8: 0 | AR8: 0 | AS8: 0 | AT8: 0 | AU8: 0 | AV8: 0 | AW8: 0 | AX8: 0 | AY8: 0 | AZ8: 0 | BA8: 0 | BB8: 0 | BC8: 0 | BD8: 0 | BE8: 0 | BF8: 0 | BG8: 0 | BH8: 0 | BI8: 0 | BJ8: 0 | BK8: 0 | BL8: 0 | BM8: 0 | BN8: 0 | BO8: 0 | BP8: 0 | BQ8: 0 | BR8: 0 | BS8: 0 | BT8: 0 | BU8: 0 | BV8: 0 | BW8: 0 | BX8: 0 | BY8: 0 | BZ8: 0 | CA8: 0 | CB8: 0 | CC8: 0 | CD8: 0 | CE8: 0 | CF8: 0 | CG8: 0 | CH8: 0 | CI8: 0 | CJ8: 0 | CK8: 0 | CL8: 0 | CM8: 0 | CN8: 0 | CO8: 0 | CP8: 0 | CQ8: 0 | CR8: 0 | CS8: 10000 | CT8: 0 | CU8: 0 | CV8: 0 | CW8: 0 | CX8: 0 | CY8: 0 | CZ8: 0 | DA8: 0 | DB8: 0 | DC8: 0 | DD8: 0 | DE8: 0 | DF8: 0 | DG8: 0 | DH8: 0 | DI8: 0 | DJ8: 0 | DK8: 0 | DL8: 0 | DM8: 0 | DN8: 0 | DO8: 0 | DP8: 0 | DQ8: 0 | DR8: 0 | DS8: 0 | DT8: 0 | DU8: 0 | DV8: 0 | DW8: 0 | DX8: 0 | DZ8: 56 | EA8: SDJ20 | EB8: 1 | EC8: 5 | ED8: =EA8&TEXT(EB8,"00")&TEXT(EC8,"00") -> SDJ200105 | EE8: 10000 | EF8: 10000 | EG8: 10000 | EH8: 10000 | EI8: 10000 | EJ8: 10000 | EK8: 10000 | EL8: 10000 | EM8: 10000 | EN8: 10000 | EO8: 10000 | EP8: 10000 | EQ8: 10000 | ER8: 10000 | ES8: 10000 | ET8: 10000 | EU8: 10000 | EV8: 10000 | EW8: 10000 | EX8: 10000 | EY8: 10000 | EZ8: 10000 | FA8: 10000 | FB8: 10000 | FC8: 10000 | FD8: 10000 | FE8: 10000 | FF8: 10000 | FG8: 10000 | FH8: 10000 | FI8: 10000 | FJ8: 10000 | FK8: 10000 | FL8: 10000 | FM8: 10000 | FN8: 10000 | FO8: 10000 | FP8: 10000 | FQ8: 10000 | FR8: 10000 | FS8: 10000 | FT8: 10000 | FU8: 10000 | FV8: 10000 | FW8: 10000 | FX8: 10000 | FY8: 10000 | FZ8: 10000 | GA8: 10000 | GB8: 10000 | GC8: 10000 | GD8: 10000 | GE8: 10000 | GF8: 10000 | GG8: 10000 | GH8: 10000 | GI8: 10000 | GJ8: 10000 | GK8: 10000 | GL8: 10000 | GM8: 10000 | GN8: 10000 | GO8: 10000 | GP8: 10000 | GQ8: 10000 | GR8: 10000 | GS8: 10000 | GT8: 10000 | GU8: 10000 | GV8: 10000 | GW8: 10000 | GX8: 10000 | GY8: 10000 | GZ8: 10000 | HA8: 10000 | HB8: 10000 | HC8: 10000 | HD8: 10000 | HE8: 10000 | HF8: 10000 | HG8: 0 | HH8: 0 | HI8: 0 | HJ8: 0 | HK8: 0 | HL8: 0 | HM8: 0 | HN8: 0 | HO8: 0 | HP8: 0 | HQ8: 0 | HR8: 0 | HS8: 0 | HT8: 0 | HU8: 0 | HV8: 0 | HW8: 0 | HX8: 0 | HY8: 0 | HZ8: 0 | IA8: 0 | IB8: 0 | IC8: 0 | ID8: 0 | IE8: 0 | IF8: 0 | IG8: 0 | IH8: 0 | II8: 0 | IJ8: 0 | IK8: 0
A9: 56 | B9: SDJ20 | F9: 1 | H9: 6 | J9: =B9&TEXT(F9,"00")&TEXT(H9,"00") -> SDJ200106 | K9: 263 | M9: 56 | N9: SDJ20 | O9: 1 | P9: 6 | Q9: =N9&TEXT(O9,"00")&TEXT(P9,"00") -> SDJ200106 | R9: 0 | S9: 0 | T9: 0 | U9: 0 | V9: 0 | W9: 0 | X9: 0 | Y9: 0 | Z9: 0 | AA9: 0 | AB9: 0 | AC9: 0 | AD9: 0 | AE9: 0 | AF9: 0 | AG9: 0 | AH9: 0 | AI9: 0 | AJ9: 0 | AK9: 0 | AL9: 0 | AM9: 0 | AN9: 0 | AO9: 0 | AP9: 0 | AQ9: 0 | AR9: 0 | AS9: 0 | AT9: 0 | AU9: 0 | AV9: 0 | AW9: 0 | AX9: 0 | AY9: 0 | AZ9: 0 | BA9: 0 | BB9: 0 | BC9: 0 | BD9: 0 | BE9: 0 | BF9: 0 | BG9: 0 | BH9: 0 | BI9: 0 | BJ9: 0 | BK9: 0 | BL9: 0 | BM9: 0 | BN9: 0 | BO9: 0 | BP9: 0 | BQ9: 0 | BR9: 0 | BS9: 0 | BT9: 0 | BU9: 0 | BV9: 0 | BW9: 0 | BX9: 0 | BY9: 0 | BZ9: 0 | CA9: 0 | CB9: 0 | CC9: 0 | CD9: 0 | CE9: 0 | CF9: 0 | CG9: 0 | CH9: 0 | CI9: 0 | CJ9: 0 | CK9: 0 | CL9: 0 | CM9: 0 | CN9: 0 | CO9: 0 | CP9: 0 | CQ9: 0 | CR9: 10000 | CS9: 0 | CT9: 0 | CU9: 0 | CV9: 0 | CW9: 0 | CX9: 0 | CY9: 0 | CZ9: 0 | DA9: 0 | DB9: 0 | DC9: 0 | DD9: 0 | DE9: 0 | DF9: 0 | DG9: 0 | DH9: 0 | DI9: 0 | DJ9: 0 | DK9: 0 | DL9: 0 | DM9: 0 | DN9: 0 | DO9: 0 | DP9: 0 | DQ9: 0 | DR9: 0 | DS9: 0 | DT9: 0 | DU9: 0 | DV9: 0 | DW9: 0 | DX9: 0 | DZ9: 56 | EA9: SDJ20 | EB9: 1 | EC9: 6 | ED9: =EA9&TEXT(EB9,"00")&TEXT(EC9,"00") -> SDJ200106 | EE9: 10000 | EF9: 10000 | EG9: 10000 | EH9: 10000 | EI9: 10000 | EJ9: 10000 | EK9: 10000 | EL9: 10000 | EM9: 10000 | EN9: 10000 | EO9: 10000 | EP9: 10000 | EQ9: 10000 | ER9: 10000 | ES9: 10000 | ET9: 10000 | EU9: 10000 | EV9: 10000 | EW9: 10000 | EX9: 10000 | EY9: 10000 | EZ9: 10000 | FA9: 10000 | FB9: 10000 | FC9: 10000 | FD9: 10000 | FE9: 10000 | FF9: 10000 | FG9: 10000 | FH9: 10000 | FI9: 10000 | FJ9: 10000 | FK9: 10000 | FL9: 10000 | FM9: 10000 | FN9: 10000 | FO9: 10000 | FP9: 10000 | FQ9: 10000 | FR9: 10000 | FS9: 10000 | FT9: 10000 | FU9: 10000 | FV9: 10000 | FW9: 10000 | FX9: 10000 | FY9: 10000 | FZ9: 10000 | GA9: 10000 | GB9: 10000 | GC9: 10000 | GD9: 10000 | GE9: 10000 | GF9: 10000 | GG9: 10000 | GH9: 10000 | GI9: 10000 | GJ9: 10000 | GK9: 10000 | GL9: 10000 | GM9: 10000 | GN9: 10000 | GO9: 10000 | GP9: 10000 | GQ9: 10000 | GR9: 10000 | GS9: 10000 | GT9: 10000 | GU9: 10000 | GV9: 10000 | GW9: 10000 | GX9: 10000 | GY9: 10000 | GZ9: 10000 | HA9: 10000 | HB9: 10000 | HC9: 10000 | HD9: 10000 | HE9: 10000 | HF9: 0 | HG9: 0 | HH9: 0 | HI9: 0 | HJ9: 0 | HK9: 0 | HL9: 0 | HM9: 0 | HN9: 0 | HO9: 0 | HP9: 0 | HQ9: 0 | HR9: 0 | HS9: 0 | HT9: 0 | HU9: 0 | HV9: 0 | HW9: 0 | HX9: 0 | HY9: 0 | HZ9: 0 | IA9: 0 | IB9: 0 | IC9: 0 | ID9: 0 | IE9: 0 | IF9: 0 | IG9: 0 | IH9: 0 | II9: 0 | IJ9: 0 | IK9: 0
A10: 56 | B10: SDJ20 | F10: 1 | H10: 7 | J10: =B10&TEXT(F10,"00")&TEXT(H10,"00") -> SDJ200107 | K10: 268 | M10: 56 | N10: SDJ20 | O10: 1 | P10: 7 | Q10: =N10&TEXT(O10,"00")&TEXT(P10,"00") -> SDJ200107 | R10: 0 | S10: 0 | T10: 0 | U10: 0 | V10: 0 | W10: 0 | X10: 0 | Y10: 0 | Z10: 0 | AA10: 0 | AB10: 0 | AC10: 0 | AD10: 0 | AE10: 0 | AF10: 0 | AG10: 0 | AH10: 0 | AI10: 0 | AJ10: 0 | AK10: 0 | AL10: 0 | AM10: 0 | AN10: 0 | AO10: 0 | AP10: 0 | AQ10: 0 | AR10: 0 | AS10: 0 | AT10: 0 | AU10: 0 | AV10: 0 | AW10: 0 | AX10: 0 | AY10: 0 | AZ10: 0 | BA10: 0 | BB10: 0 | BC10: 0 | BD10: 0 | BE10: 0 | BF10: 0 | BG10: 0 | BH10: 0 | BI10: 0 | BJ10: 0 | BK10: 0 | BL10: 0 | BM10: 0 | BN10: 0 | BO10: 0 | BP10: 0 | BQ10: 0 | BR10: 0 | BS10: 0 | BT10: 0 | BU10: 0 | BV10: 0 | BW10: 0 | BX10: 0 | BY10: 0 | BZ10: 0 | CA10: 0 | CB10: 0 | CC10: 0 | CD10: 0 | CE10: 0 | CF10: 0 | CG10: 0 | CH10: 0 | CI10: 0 | CJ10: 0 | CK10: 0 | CL10: 0 | CM10: 0 | CN10: 0 | CO10: 0 | CP10: 0 | CQ10: 10000 | CR10: 0 | CS10: 0 | CT10: 0 | CU10: 0 | CV10: 0 | CW10: 0 | CX10: 0 | CY10: 0 | CZ10: 0 | DA10: 0 | DB10: 0 | DC10: 0 | DD10: 0 | DE10: 0 | DF10: 0 | DG10: 0 | DH10: 0 | DI10: 0 | DJ10: 0 | DK10: 0 | DL10: 0 | DM10: 0 | DN10: 0 | DO10: 0 | DP10: 0 | DQ10: 0 | DR10: 0 | DS10: 0 | DT10: 0 | DU10: 0 | DV10: 0 | DW10: 0 | DX10: 0 | DZ10: 56 | EA10: SDJ20 | EB10: 1 | EC10: 7 | ED10: =EA10&TEXT(EB10,"00")&TEXT(EC10,"00") -> SDJ200107 | EE10: 10000 | EF10: 10000 | EG10: 10000 | EH10: 10000 | EI10: 10000 | EJ10: 10000 | EK10: 10000 | EL10: 10000 | EM10: 10000 | EN10: 10000 | EO10: 10000 | EP10: 10000 | EQ10: 10000 | ER10: 10000 | ES10: 10000 | ET10: 10000 | EU10: 10000 | EV10: 10000 | EW10: 10000 | EX10: 10000 | EY10: 10000 | EZ10: 10000 | FA10: 10000 | FB10: 10000 | FC10: 10000 | FD10: 10000 | FE10: 10000 | FF10: 10000 | FG10: 10000 | FH10: 10000 | FI10: 10000 | FJ10: 10000 | FK10: 10000 | FL10: 10000 | FM10: 10000 | FN10: 10000 | FO10: 10000 | FP10: 10000 | FQ10: 10000 | FR10: 10000 | FS10: 10000 | FT10: 10000 | FU10: 10000 | FV10: 10000 | FW10: 10000 | FX10: 10000 | FY10: 10000 | FZ10: 10000 | GA10: 10000 | GB10: 10000 | GC10: 10000 | GD10: 10000 | GE10: 10000 | GF10: 10000 | GG10: 10000 | GH10: 10000 | GI10: 10000 | GJ10: 10000 | GK10: 10000 | GL10: 10000 | GM10: 10000 | GN10: 10000 | GO10: 10000 | GP10: 10000 | GQ10: 10000 | GR10: 10000 | GS10: 10000 | GT10: 10000 | GU10: 10000 | GV10: 10000 | GW10: 10000 | GX10: 10000 | GY10: 10000 | GZ10: 10000 | HA10: 10000 | HB10: 10000 | HC10: 10000 | HD10: 10000 | HE10: 0 | HF10: 0 | HG10: 0 | HH10: 0 | HI10: 0 | HJ10: 0 | HK10: 0 | HL10: 0 | HM10: 0 | HN10: 0 | HO10: 0 | HP10: 0 | HQ10: 0 | HR10: 0 | HS10: 0 | HT10: 0 | HU10: 0 | HV10: 0 | HW10: 0 | HX10: 0 | HY10: 0 | HZ10: 0 | IA10: 0 | IB10: 0 | IC10: 0 | ID10: 0 | IE10: 0 | IF10: 0 | IG10: 0 | IH10: 0 | II10: 0 | IJ10: 0 | IK10: 0
A11: 56 | B11: SDJ20 | F11: 1 | H11: 8 | J11: =B11&TEXT(F11,"00")&TEXT(H11,"00") -> SDJ200108 | K11: 273 | M11: 56 | N11: SDJ20 | O11: 1 | P11: 8 | Q11: =N11&TEXT(O11,"00")&TEXT(P11,"00") -> SDJ200108 | R11: 0 | S11: 0 | T11: 0 | U11: 0 | V11: 0 | W11: 0 | X11: 0 | Y11: 0 | Z11: 0 | AA11: 0 | AB11: 0 | AC11: 0 | AD11: 0 | AE11: 0 | AF11: 0 | AG11: 0 | AH11: 0 | AI11: 0 | AJ11: 0 | AK11: 0 | AL11: 0 | AM11: 0 | AN11: 0 | AO11: 0 | AP11: 0 | AQ11: 0 | AR11: 0 | AS11: 0 | AT11: 0 | AU11: 0 | AV11: 0 | AW11: 0 | AX11: 0 | AY11: 0 | AZ11: 0 | BA11: 0 | BB11: 0 | BC11: 0 | BD11: 0 | BE11: 0 | BF11: 0 | BG11: 0 | BH11: 0 | BI11: 0 | BJ11: 0 | BK11: 0 | BL11: 0 | BM11: 0 | BN11: 0 | BO11: 0 | BP11: 0 | BQ11: 0 | BR11: 0 | BS11: 0 | BT11: 0 | BU11: 0 | BV11: 0 | BW11: 0 | BX11: 0 | BY11: 0 | BZ11: 0 | CA11: 0 | CB11: 0 | CC11: 0 | CD11: 0 | CE11: 0 | CF11: 0 | CG11: 0 | CH11: 0 | CI11: 0 | CJ11: 0 | CK11: 0 | CL11: 0 | CM11: 0 | CN11: 0 | CO11: 0 | CP11: 10000 | CQ11: 0 | CR11: 0 | CS11: 0 | CT11: 0 | CU11: 0 | CV11: 0 | CW11: 0 | CX11: 0 | CY11: 0 | CZ11: 0 | DA11: 0 | DB11: 0 | DC11: 0 | DD11: 0 | DE11: 0 | DF11: 0 | DG11: 0 | DH11: 0 | DI11: 0 | DJ11: 0 | DK11: 0 | DL11: 0 | DM11: 0 | DN11: 0 | DO11: 0 | DP11: 0 | DQ11: 0 | DR11: 0 | DS11: 0 | DT11: 0 | DU11: 0 | DV11: 0 | DW11: 0 | DX11: 0 | DZ11: 56 | EA11: SDJ20 | EB11: 1 | EC11: 8 | ED11: =EA11&TEXT(EB11,"00")&TEXT(EC11,"00") -> SDJ200108 | EE11: 10000 | EF11: 10000 | EG11: 10000 | EH11: 10000 | EI11: 10000 | EJ11: 10000 | EK11: 10000 | EL11: 10000 | EM11: 10000 | EN11: 10000 | EO11: 10000 | EP11: 10000 | EQ11: 10000 | ER11: 10000 | ES11: 10000 | ET11: 10000 | EU11: 10000 | EV11: 10000 | EW11: 10000 | EX11: 10000 | EY11: 10000 | EZ11: 10000 | FA11: 10000 | FB11: 10000 | FC11: 10000 | FD11: 10000 | FE11: 10000 | FF11: 10000 | FG11: 10000 | FH11: 10000 | FI11: 10000 | FJ11: 10000 | FK11: 10000 | FL11: 10000 | FM11: 10000 | FN11: 10000 | FO11: 10000 | FP11: 10000 | FQ11: 10000 | FR11: 10000 | FS11: 10000 | FT11: 10000 | FU11: 10000 | FV11: 10000 | FW11: 10000 | FX11: 10000 | FY11: 10000 | FZ11: 10000 | GA11: 10000 | GB11: 10000 | GC11: 10000 | GD11: 10000 | GE11: 10000 | GF11: 10000 | GG11: 10000 | GH11: 10000 | GI11: 10000 | GJ11: 10000 | GK11: 10000 | GL11: 10000 | GM11: 10000 | GN11: 10000 | GO11: 10000 | GP11: 10000 | GQ11: 10000 | GR11: 10000 | GS11: 10000 | GT11: 10000 | GU11: 10000 | GV11: 10000 | GW11: 10000 | GX11: 10000 | GY11: 10000 | GZ11: 10000 | HA11: 10000 | HB11: 10000 | HC11: 10000 | HD11: 0 | HE11: 0 | HF11: 0 | HG11: 0 | HH11: 0 | HI11: 0 | HJ11: 0 | HK11: 0 | HL11: 0 | HM11: 0 | HN11: 0 | HO11: 0 | HP11: 0 | HQ11: 0 | HR11: 0 | HS11: 0 | HT11: 0 | HU11: 0 | HV11: 0 | HW11: 0 | HX11: 0 | HY11: 0 | HZ11: 0 | IA11: 0 | IB11: 0 | IC11: 0 | ID11: 0 | IE11: 0 | IF11: 0 | IG11: 0 | IH11: 0 | II11: 0 | IJ11: 0 | IK11: 0
A12: 56 | B12: SDJ20 | F12: 1 | H12: 9 | J12: =B12&TEXT(F12,"00")&TEXT(H12,"00") -> SDJ200109 | K12: 278 | M12: 56 | N12: SDJ20 | O12: 1 | P12: 9 | Q12: =N12&TEXT(O12,"00")&TEXT(P12,"00") -> SDJ200109 | R12: 0 | S12: 0 | T12: 0 | U12: 0 | V12: 0 | W12: 0 | X12: 0 | Y12: 0 | Z12: 0 | AA12: 0 | AB12: 0 | AC12: 0 | AD12: 0 | AE12: 0 | AF12: 0 | AG12: 0 | AH12: 0 | AI12: 0 | AJ12: 0 | AK12: 0 | AL12: 0 | AM12: 0 | AN12: 0 | AO12: 0 | AP12: 0 | AQ12: 0 | AR12: 0 | AS12: 0 | AT12: 0 | AU12: 0 | AV12: 0 | AW12: 0 | AX12: 0 | AY12: 0 | AZ12: 0 | BA12: 0 | BB12: 0 | BC12: 0 | BD12: 0 | BE12: 0 | BF12: 0 | BG12: 0 | BH12: 0 | BI12: 0 | BJ12: 0 | BK12: 0 | BL12: 0 | BM12: 0 | BN12: 0 | BO12: 0 | BP12: 0 | BQ12: 0 | BR12: 0 | BS12: 0 | BT12: 0 | BU12: 0 | BV12: 0 | BW12: 0 | BX12: 0 | BY12: 0 | BZ12: 0 | CA12: 0 | CB12: 0 | CC12: 0 | CD12: 0 | CE12: 0 | CF12: 0 | CG12: 0 | CH12: 0 | CI12: 0 | CJ12: 0 | CK12: 0 | CL12: 0 | CM12: 0 | CN12: 0 | CO12: 10000 | CP12: 0 | CQ12: 0 | CR12: 0 | CS12: 0 | CT12: 0 | CU12: 0 | CV12: 0 | CW12: 0 | CX12: 0 | CY12: 0 | CZ12: 0 | DA12: 0 | DB12: 0 | DC12: 0 | DD12: 0 | DE12: 0 | DF12: 0 | DG12: 0 | DH12: 0 | DI12: 0 | DJ12: 0 | DK12: 0 | DL12: 0 | DM12: 0 | DN12: 0 | DO12: 0 | DP12: 0 | DQ12: 0 | DR12: 0 | DS12: 0 | DT12: 0 | DU12: 0 | DV12: 0 | DW12: 0 | DX12: 0 | DZ12: 56 | EA12: SDJ20 | EB12: 1 | EC12: 9 | ED12: =EA12&TEXT(EB12,"00")&TEXT(EC12,"00") -> SDJ200109 | EE12: 10000 | EF12: 10000 | EG12: 10000 | EH12: 10000 | EI12: 10000 | EJ12: 10000 | EK12: 10000 | EL12: 10000 | EM12: 10000 | EN12: 10000 | EO12: 10000 | EP12: 10000 | EQ12: 10000 | ER12: 10000 | ES12: 10000 | ET12: 10000 | EU12: 10000 | EV12: 10000 | EW12: 10000 | EX12: 10000 | EY12: 10000 | EZ12: 10000 | FA12: 10000 | FB12: 10000 | FC12: 10000 | FD12: 10000 | FE12: 10000 | FF12: 10000 | FG12: 10000 | FH12: 10000 | FI12: 10000 | FJ12: 10000 | FK12: 10000 | FL12: 10000 | FM12: 10000 | FN12: 10000 | FO12: 10000 | FP12: 10000 | FQ12: 10000 | FR12: 10000 | FS12: 10000 | FT12: 10000 | FU12: 10000 | FV12: 10000 | FW12: 10000 | FX12: 10000 | FY12: 10000 | FZ12: 10000 | GA12: 10000 | GB12: 10000 | GC12: 10000 | GD12: 10000 | GE12: 10000 | GF12: 10000 | GG12: 10000 | GH12: 10000 | GI12: 10000 | GJ12: 10000 | GK12: 10000 | GL12: 10000 | GM12: 10000 | GN12: 10000 | GO12: 10000 | GP12: 10000 | GQ12: 10000 | GR12: 10000 | GS12: 10000 | GT12: 10000 | GU12: 10000 | GV12: 10000 | GW12: 10000 | GX12: 10000 | GY12: 10000 | GZ12: 10000 | HA12: 10000 | HB12: 10000 | HC12: 0 | HD12: 0 | HE12: 0 | HF12: 0 | HG12: 0 | HH12: 0 | HI12: 0 | HJ12: 0 | HK12: 0 | HL12: 0 | HM12: 0 | HN12: 0 | HO12: 0 | HP12: 0 | HQ12: 0 | HR12: 0 | HS12: 0 | HT12: 0 | HU12: 0 | HV12: 0 | HW12: 0 | HX12: 0 | HY12: 0 | HZ12: 0 | IA12: 0 | IB12: 0 | IC12: 0 | ID12: 0 | IE12: 0 | IF12: 0 | IG12: 0 | IH12: 0 | II12: 0 | IJ12: 0 | IK12: 0
A13: 56 | B13: SDJ20 | F13: 1 | H13: 10 | J13: =B13&TEXT(F13,"00")&TEXT(H13,"00") -> SDJ200110 | K13: 283 | M13: 56 | N13: SDJ20 | O13: 1 | P13: 10 | Q13: =N13&TEXT(O13,"00")&TEXT(P13,"00") -> SDJ200110 | R13: 0 | S13: 0 | T13: 0 | U13: 0 | V13: 0 | W13: 0 | X13: 0 | Y13: 0 | Z13: 0 | AA13: 0 | AB13: 0 | AC13: 0 | AD13: 0 | AE13: 0 | AF13: 0 | AG13: 0 | AH13: 0 | AI13: 0 | AJ13: 0 | AK13: 0 | AL13: 0 | AM13: 0 | AN13: 0 | AO13: 0 | AP13: 0 | AQ13: 0 | AR13: 0 | AS13: 0 | AT13: 0 | AU13: 0 | AV13: 0 | AW13: 0 | AX13: 0 | AY13: 0 | AZ13: 0 | BA13: 0 | BB13: 0 | BC13: 0 | BD13: 0 | BE13: 0 | BF13: 0 | BG13: 0 | BH13: 0 | BI13: 0 | BJ13: 0 | BK13: 0 | BL13: 0 | BM13: 0 | BN13: 0 | BO13: 0 | BP13: 0 | BQ13: 0 | BR13: 0 | BS13: 0 | BT13: 0 | BU13: 0 | BV13: 0 | BW13: 0 | BX13: 0 | BY13: 0 | BZ13: 0 | CA13: 0 | CB13: 0 | CC13: 0 | CD13: 0 | CE13: 0 | CF13: 0 | CG13: 0 | CH13: 0 | CI13: 0 | CJ13: 0 | CK13: 0 | CL13: 0 | CM13: 0 | CN13: 10000 | CO13: 0 | CP13: 0 | CQ13: 0 | CR13: 0 | CS13: 0 | CT13: 0 | CU13: 0 | CV13: 0 | CW13: 0 | CX13: 0 | CY13: 0 | CZ13: 0 | DA13: 0 | DB13: 0 | DC13: 0 | DD13: 0 | DE13: 0 | DF13: 0 | DG13: 0 | DH13: 0 | DI13: 0 | DJ13: 0 | DK13: 0 | DL13: 0 | DM13: 0 | DN13: 0 | DO13: 0 | DP13: 0 | DQ13: 0 | DR13: 0 | DS13: 0 | DT13: 0 | DU13: 0 | DV13: 0 | DW13: 0 | DX13: 0 | DZ13: 56 | EA13: SDJ20 | EB13: 1 | EC13: 10 | ED13: =EA13&TEXT(EB13,"00")&TEXT(EC13,"00") -> SDJ200110 | EE13: 10000 | EF13: 10000 | EG13: 10000 | EH13: 10000 | EI13: 10000 | EJ13: 10000 | EK13: 10000 | EL13: 10000 | EM13: 10000 | EN13: 10000 | EO13: 10000 | EP13: 10000 | EQ13: 10000 | ER13: 10000 | ES13: 10000 | ET13: 10000 | EU13: 10000 | EV13: 10000 | EW13: 10000 | EX13: 10000 | EY13: 10000 | EZ13: 10000 | FA13: 10000 | FB13: 10000 | FC13: 10000 | FD13: 10000 | FE13: 10000 | FF13: 10000 | FG13: 10000 | FH13: 10000 | FI13: 10000 | FJ13: 10000 | FK13: 10000 | FL13: 10000 | FM13: 10000 | FN13: 10000 | FO13: 10000 | FP13: 10000 | FQ13: 10000 | FR13: 10000 | FS13: 10000 | FT13: 10000 | FU13: 10000 | FV13: 10000 | FW13: 10000 | FX13: 10000 | FY13: 10000 | FZ13: 10000 | GA13: 10000 | GB13: 10000 | GC13: 10000 | GD13: 10000 | GE13: 10000 | GF13: 10000 | GG13: 10000 | GH13: 10000 | GI13: 10000 | GJ13: 10000 | GK13: 10000 | GL13: 10000 | GM13: 10000 | GN13: 10000 | GO13: 10000 | GP13: 10000 | GQ13: 10000 | GR13: 10000 | GS13: 10000 | GT13: 10000 | GU13: 10000 | GV13: 10000 | GW13: 10000 | GX13: 10000 | GY13: 10000 | GZ13: 10000 | HA13: 10000 | HB13: 0 | HC13: 0 | HD13: 0 | HE13: 0 | HF13: 0 | HG13: 0 | HH13: 0 | HI13: 0 | HJ13: 0 | HK13: 0 | HL13: 0 | HM13: 0 | HN13: 0 | HO13: 0 | HP13: 0 | HQ13: 0 | HR13: 0 | HS13: 0 | HT13: 0 | HU13: 0 | HV13: 0 | HW13: 0 | HX13: 0 | HY13: 0 | HZ13: 0 | IA13: 0 | IB13: 0 | IC13: 0 | ID13: 0 | IE13: 0 | IF13: 0 | IG13: 0 | IH13: 0 | II13: 0 | IJ13: 0 | IK13: 0
A14: 56 | B14: SDJ20 | F14: 1 | H14: 11 | J14: =B14&TEXT(F14,"00")&TEXT(H14,"00") -> SDJ200111 | K14: 289 | M14: 56 | N14: SDJ20 | O14: 1 | P14: 11 | Q14: =N14&TEXT(O14,"00")&TEXT(P14,"00") -> SDJ200111 | R14: 0 | S14: 0 | T14: 0 | U14: 0 | V14: 0 | W14: 0 | X14: 0 | Y14: 0 | Z14: 0 | AA14: 0 | AB14: 0 | AC14: 0 | AD14: 0 | AE14: 0 | AF14: 0 | AG14: 0 | AH14: 0 | AI14: 0 | AJ14: 0 | AK14: 0 | AL14: 0 | AM14: 0 | AN14: 0 | AO14: 0 | AP14: 0 | AQ14: 0 | AR14: 0 | AS14: 0 | AT14: 0 | AU14: 0 | AV14: 0 | AW14: 0 | AX14: 0 | AY14: 0 | AZ14: 0 | BA14: 0 | BB14: 0 | BC14: 0 | BD14: 0 | BE14: 0 | BF14: 0 | BG14: 0 | BH14: 0 | BI14: 0 | BJ14: 0 | BK14: 0 | BL14: 0 | BM14: 0 | BN14: 0 | BO14: 0 | BP14: 0 | BQ14: 0 | BR14: 0 | BS14: 0 | BT14: 0 | BU14: 0 | BV14: 0 | BW14: 0 | BX14: 0 | BY14: 0 | BZ14: 0 | CA14: 0 | CB14: 0 | CC14: 0 | CD14: 0 | CE14: 0 | CF14: 0 | CG14: 0 | CH14: 0 | CI14: 0 | CJ14: 0 | CK14: 0 | CL14: 0 | CM14: 10000 | CN14: 0 | CO14: 0 | CP14: 0 | CQ14: 0 | CR14: 0 | CS14: 0 | CT14: 0 | CU14: 0 | CV14: 0 | CW14: 0 | CX14: 0 | CY14: 0 | CZ14: 0 | DA14: 0 | DB14: 0 | DC14: 0 | DD14: 0 | DE14: 0 | DF14: 0 | DG14: 0 | DH14: 0 | DI14: 0 | DJ14: 0 | DK14: 0 | DL14: 0 | DM14: 0 | DN14: 0 | DO14: 0 | DP14: 0 | DQ14: 0 | DR14: 0 | DS14: 0 | DT14: 0 | DU14: 0 | DV14: 0 | DW14: 0 | DX14: 0 | DZ14: 56 | EA14: SDJ20 | EB14: 1 | EC14: 11 | ED14: =EA14&TEXT(EB14,"00")&TEXT(EC14,"00") -> SDJ200111 | EE14: 10000 | EF14: 10000 | EG14: 10000 | EH14: 10000 | EI14: 10000 | EJ14: 10000 | EK14: 10000 | EL14: 10000 | EM14: 10000 | EN14: 10000 | EO14: 10000 | EP14: 10000 | EQ14: 10000 | ER14: 10000 | ES14: 10000 | ET14: 10000 | EU14: 10000 | EV14: 10000 | EW14: 10000 | EX14: 10000 | EY14: 10000 | EZ14: 10000 | FA14: 10000 | FB14: 10000 | FC14: 10000 | FD14: 10000 | FE14: 10000 | FF14: 10000 | FG14: 10000 | FH14: 10000 | FI14: 10000 | FJ14: 10000 | FK14: 10000 | FL14: 10000 | FM14: 10000 | FN14: 10000 | FO14: 10000 | FP14: 10000 | FQ14: 10000 | FR14: 10000 | FS14: 10000 | FT14: 10000 | FU14: 10000 | FV14: 10000 | FW14: 10000 | FX14: 10000 | FY14: 10000 | FZ14: 10000 | GA14: 10000 | GB14: 10000 | GC14: 10000 | GD14: 10000 | GE14: 10000 | GF14: 10000 | GG14: 10000 | GH14: 10000 | GI14: 10000 | GJ14: 10000 | GK14: 10000 | GL14: 10000 | GM14: 10000 | GN14: 10000 | GO14: 10000 | GP14: 10000 | GQ14: 10000 | GR14: 10000 | GS14: 10000 | GT14: 10000 | GU14: 10000 | GV14: 10000 | GW14: 10000 | GX14: 10000 | GY14: 10000 | GZ14: 10000 | HA14: 0 | HB14: 0 | HC14: 0 | HD14: 0 | HE14: 0 | HF14: 0 | HG14: 0 | HH14: 0 | HI14: 0 | HJ14: 0 | HK14: 0 | HL14: 0 | HM14: 0 | HN14: 0 | HO14: 0 | HP14: 0 | HQ14: 0 | HR14: 0 | HS14: 0 | HT14: 0 | HU14: 0 | HV14: 0 | HW14: 0 | HX14: 0 | HY14: 0 | HZ14: 0 | IA14: 0 | IB14: 0 | IC14: 0 | ID14: 0 | IE14: 0 | IF14: 0 | IG14: 0 | IH14: 0 | II14: 0 | IJ14: 0 | IK14: 0
... A104: 56 | B104: SDJ20 | F104: 2 | H104: 50 | J104: =B104&TEXT(F104,"00")&TEXT(H104,"00") -> SDJ200250 | K104: 665 | M104: 56 | N104: SDJ20 | O104: 2 | P104: 50 | Q104: =N104&TEXT(O104,"00")&TEXT(P104,"00") -> SDJ200250 | R104: 0 | S104: 0 | T104: 0 | U104: 0 | V104: 0 | W104: 0 | X104: 0 | Y104: 0 | Z104: 0 | AA104: 0 | AB104: 0 | AC104: 0 | AD104: 0 | AE104: 0 | AF104: 0 | AG104: 0 | AH104: 0 | AI104: 0 | AJ104: 0 | AK104: 0 | AL104: 0 | AM104: 0 | AN104: 0 | AO104: 0 | AP104: 0 | AQ104: 0 | AR104: 0 | AS104: 0 | AT104: 0 | AU104: 0 | AV104: 0 | AW104: 0 | AX104: 0 | AY104: 0 | AZ104: 14098 | BA104: 0 | BB104: 0 | BC104: 0 | BD104: 0 | BE104: 0 | BF104: 0 | BG104: 0 | BH104: 0 | BI104: 0 | BJ104: 0 | BK104: 0 | BL104: 0 | BM104: 0 | BN104: 0 | BO104: 0 | BP104: 0 | BQ104: 0 | BR104: 0 | BS104: 0 | BT104: 0 | BU104: 0 | BV104: 0 | BW104: 0 | BX104: 0 | BY104: 0 | BZ104: 0 | CA104: 0 | CB104: 0 | CC104: 0 | CD104: 0 | CE104: 0 | CF104: 0 | CG104: 0 | CH104: 0 | CI104: 0 | CJ104: 0 | CK104: 0 | CL104: 0 | CM104: 0 | CN104: 0 | CO104: 0 | CP104: 0 | CQ104: 0 | CR104: 0 | CS104: 0 | CT104: 0 | CU104: 0 | CV104: 0 | CW104: 0 | CX104: 0 | CY104: 0 | CZ104: 0 | DA104: 0 | DB104: 0 | DC104: 0 | DD104: 0 | DE104: 0 | DF104: 0 | DG104: 0 | DH104: 0 | DI104: 0 | DJ104: 0 | DK104: 0 | DL104: 0 | DM104: 0 | DN104: 0 | DO104: 0 | DP104: 0 | DQ104: 0 | DR104: 0 | DS104: 0 | DT104: 0 | DU104: 0 | DV104: 0 | DW104: 0 | DX104: 0 | DZ104: 56 | EA104: SDJ20 | EB104: 2 | EC104: 50 | ED104: =EA104&TEXT(EB104,"00")&TEXT(EC104,"00") -> SDJ200250 | EE104: 10000 | EF104: 10000 | EG104: 10000 | EH104: 10000 | EI104: 10000 | EJ104: 10000 | EK104: 10000 | EL104: 10000 | EM104: 10000 | EN104: 10000 | EO104: 10000 | EP104: 10000 | EQ104: 10000 | ER104: 10000 | ES104: 10573.5 | ET104: 11278.4 | EU104: 11983.3 | EV104: 12688.2 | EW104: 13393.1 | EX104: 14098 | EY104: 14098 | EZ104: 14098 | FA104: 14098 | FB104: 14098 | FC104: 14098 | FD104: 14098 | FE104: 14098 | FF104: 14098 | FG104: 14098 | FH104: 14098 | FI104: 14098 | FJ104: 14098 | FK104: 14098 | FL104: 14098 | FM104: 14098 | FN104: 0 | FO104: 0 | FP104: 0 | FQ104: 0 | FR104: 0 | FS104: 0 | FT104: 0 | FU104: 0 | FV104: 0 | FW104: 0 | FX104: 0 | FY104: 0 | FZ104: 0 | GA104: 0 | GB104: 0 | GC104: 0 | GD104: 0 | GE104: 0 | GF104: 0 | GG104: 0 | GH104: 0 | GI104: 0 | GJ104: 0 | GK104: 0 | GL104: 0 | GM104: 0 | GN104: 0 | GO104: 0 | GP104: 0 | GQ104: 0 | GR104: 0 | GS104: 0 | GT104: 0 | GU104: 0 | GV104: 0 | GW104: 0 | GX104: 0 | GY104: 0 | GZ104: 0 | HA104: 0 | HB104: 0 | HC104: 0 | HD104: 0 | HE104: 0 | HF104: 0 | HG104: 0 | HH104: 0 | HI104: 0 | HJ104: 0 | HK104: 0 | HL104: 0 | HM104: 0 | HN104: 0 | HO104: 0 | HP104: 0 | HQ104: 0 | HR104: 0 | HS104: 0 | HT104: 0 | HU104: 0 | HV104: 0 | HW104: 0 | HX104: 0 | HY104: 0 | HZ104: 0 | IA104: 0 | IB104: 0 | IC104: 0 | ID104: 0 | IE104: 0 | IF104: 0 | IG104: 0 | IH104: 0 | II104: 0 | IJ104: 0 | IK104: 0
M109: CV | Q109: =N109&TEXT(O109,"00")&TEXT(P109,"00") -> 0000 | DZ109: PA | ED109: =EA109&TEXT(EB109,"00")&TEXT(EC109,"00") -> 0000
M110: 版次 | N110: 商品代號 | O110: 性別 | P110: 年齡 | Q110: =N110&TEXT(O110,"00")&TEXT(P110,"00") -> 商品代號性別年齡 | R110: 第1年解約金 | S110: 第2年解約金 | T110: 第3年解約金 | U110: 第4年解約金 | V110: 第5年解約金 | W110: 第6年解約金 | X110: 第7年解約金 | Y110: 第8年解約金 | Z110: 第9年解約金 | AA110: 第10年解約金 | AB110: 第11年解約金 | AC110: 第12年解約金 | AD110: 第13年解約金 | AE110: 第14年解約金 | AF110: 第15年解約金 | AG110: 第16年解約金 | AH110: 第17年解約金 | AI110: 第18年解約金 | AJ110: 第19年解約金 | AK110: 第20年解約金 | AL110: 第21年解約金 | AM110: 第22年解約金 | AN110: 第23年解約金 | AO110: 第24年解約金 | AP110: 第25年解約金 | AQ110: 第26年解約金 | AR110: 第27年解約金 | AS110: 第28年解約金 | AT110: 第29年解約金 | AU110: 第30年解約金 | AV110: 第31年解約金 | AW110: 第32年解約金 | AX110: 第33年解約金 | AY110: 第34年解約金 | AZ110: 第35年解約金 | BA110: 第36年解約金 | BB110: 第37年解約金 | BC110: 第38年解約金 | BD110: 第39年解約金 | BE110: 第40年解約金 | BF110: 第41年解約金 | BG110: 第42年解約金 | BH110: 第43年解約金 | BI110: 第44年解約金 | BJ110: 第45年解約金 | BK110: 第46年解約金 | BL110: 第47年解約金 | BM110: 第48年解約金 | BN110: 第49年解約金 | BO110: 第50年解約金 | BP110: 第51年解約金 | BQ110: 第52年解約金 | BR110: 第53年解約金 | BS110: 第54年解約金 | BT110: 第55年解約金 | BU110: 第56年解約金 | BV110: 第57年解約金 | BW110: 第58年解約金 | BX110: 第59年解約金 | BY110: 第60年解約金 | BZ110: 第61年解約金 | CA110: 第62年解約金 | CB110: 第63年解約金 | CC110: 第64年解約金 | CD110: 第65年解約金 | CE110: 第66年解約金 | CF110: 第67年解約金 | CG110: 第68年解約金 | CH110: 第69年解約金 | CI110: 第70年解約金 | CJ110: 第71年解約金 | CK110: 第72年解約金 | CL110: 第73年解約金 | CM110: 第74年解約金 | CN110: 第75年解約金 | CO110: 第76年解約金 | CP110: 第77年解約金 | CQ110: 第78年解約金 | CR110: 第79年解約金 | CS110: 第80年解約金 | CT110: 第81年解約金 | CU110: 第82年解約金 | CV110: 第83年解約金 | CW110: 第84年解約金 | CX110: 第85年解約金 | CY110: 第86年解約金 | CZ110: 第87年解約金 | DA110: 第88年解約金 | DB110: 第89年解約金 | DC110: 第90年解約金 | DD110: 第91年解約金 | DE110: 第92年解約金 | DF110: 第93年解約金 | DG110: 第94年解約金 | DH110: 第95年解約金 | DI110: 第96年解約金 | DJ110: 第97年解約金 | DK110: 第98年解約金 | DL110: 第99年解約金 | DM110: 第100年解約金 | DN110: 第101年解約金 | DO110: 第102年解約金 | DP110: 第103年解約金 | DQ110: 第104年解約金 | DR110: 第105年解約金 | DS110: 第106年解約金 | DT110: 第107年解約金 | DU110: 第108年解約金 | DV110: 第109年解約金 | DW110: 第110年解約金 | DX110: 第111年解約金 | DZ110: 版次 | EA110: 商品代號 | EB110: 性別 | EC110: 年齡 | ED110: =EA110&TEXT(EB110,"00")&TEXT(EC110,"00") -> 商品代號性別年齡 | EE110: 第1年減額繳清保額 | EF110: 第2年減額繳清保額 | EG110: 第3年減額繳清保額 | EH110: 第4年減額繳清保額 | EI110: 第5年減額繳清保額 | EJ110: 第6年減額繳清保額 | EK110: 第7年減額繳清保額 | EL110: 第8年減額繳清保額 | EM110: 第9年減額繳清保額 | EN110: 第10年減額繳清保額 | EO110: 第11年減額繳清保額 | EP110: 第12年減額繳清保額 | EQ110: 第13年減額繳清保額 | ER110: 第14年減額繳清保額 | ES110: 第15年減額繳清保額 | ET110: 第16年減額繳清保額 | EU110: 第17年減額繳清保額 | EV110: 第18年減額繳清保額 | EW110: 第19年減額繳清保額B | EX110: 第20年減額繳清保額 | EY110: 第21年減額繳清保額B | EZ110: 第22年減額繳清保額 | FA110: 第23年減額繳清保額 | FB110: 第24年減額繳清保額 | FC110: 第25年減額繳清保額 | FD110: 第26年減額繳清保額B | FE110: 第27年減額繳清保額 | FF110: 第28年減額繳清保額B | FG110: 第29年減額繳清保額 | FH110: 第30年減額繳清保額B | FI110: 第31年減額繳清保額 | FJ110: 第32年減額繳清保額 | FK110: 第33年減額繳清保額 | FL110: 第34年減額繳清保額 | FM110: 第35年減額繳清保額 | FN110: 第36年減額繳清保額 | FO110: 第37年減額繳清保額 | FP110: 第38年減額繳清保額 | FQ110: 第39年減額繳清保額 | FR110: 第40年減額繳清保額 | FS110: 第41年減額繳清保額 | FT110: 第42年減額繳清保額 | FU110: 第43年減額繳清保額 | FV110: 第44年減額繳清保額 | FW110: 第45年減額繳清保額 | FX110: 第46年減額繳清保額 | FY110: 第47年減額繳清保額 | FZ110: 第48年減額繳清保額 | GA110: 第49年減額繳清保額 | GB110: 第50年減額繳清保額 | GC110: 第51年減額繳清保額 | GD110: 第52年減額繳清保額 | GE110: 第53年減額繳清保額 | GF110: 第54年減額繳清保額 | GG110: 第55年減額繳清保額 | GH110: 第56年減額繳清保額 | GI110: 第57年減額繳清保額 | GJ110: 第58年減額繳清保額 | GK110: 第59年減額繳清保額 | GL110: 第60年減額繳清保額 | GM110: 第61年減額繳清保額 | GN110: 第62年減額繳清保額 | GO110: 第63年減額繳清保額 | GP110: 第64年減額繳清保額 | GQ110: 第65年減額繳清保額 | GR110: 第66年減額繳清保額 | GS110: 第67年減額繳清保額 | GT110: 第68年減額繳清保額 | GU110: 第69年減額繳清保額 | GV110: 第70年減額繳清保額 | GW110: 第71年減額繳清保額 | GX110: 第72年減額繳清保額 | GY110: 第73年減額繳清保額 | GZ110: 第74年減額繳清保額 | HA110: 第75年減額繳清保額 | HB110: 第76年減額繳清保額 | HC110: 第77年減額繳清保額 | HD110: 第78年減額繳清保額 | HE110: 第79年減額繳清保額 | HF110: 第80年減額繳清保額 | HG110: 第81年減額繳清保額 | HH110: 第82年契遾B繳清保額 | HI110: 第83年減額繳清保額 | HJ110: 第84年減額繳清保額 | HK110: 第85年減額繳清保額 | HL110: 第86年減額繳清保額 | HM110: 第87年減額繳清保額 | HN110: 第88年減額繳清保額 | HO110: 第89年減額繳清保額 | HP110: 第90年減額繳清保額 | HQ110: 第91年減額繳清保額 | HR110: 第92年減額繳清保額 | HS110: 第93年減額繳清保額 | HT110: 第94年減額繳清保額 | HU110: 第95年減額繳清保額 | HV110: 第96年減額繳清保額 | HW110: 第97年減額繳清保額 | HX110: 第98年減額繳清保額 | HY110: 第99年減額繳清保額 | HZ110: 第100年減額繳清保額 | IA110: 第101年減額繳清保額 | IB110: 第102年減額繳清保額 | IC110: 第103年減額繳清保額 | ID110: 第104年減額繳清保額 | IE110: 第105年減額繳清保額 | IF110: 第106年減額繳清保額 | IG110: 第107年減額繳清保額 | IH110: 第108年減額繳清保額 | II110: 第109年減額繳清保額 | IJ110: 第110年減額繳清保額 | IK110: 第111年減額繳清保額
M111: 56 | N111: SDJ20 | O111: 1 | P111: 0 | Q111: =N111&TEXT(O111,"00")&TEXT(P111,"00") -> SDJ200100 | R111: 0 | S111: 17 | T111: 34 | U111: 52 | V111: 75 | W111: 94 | X111: 129 | Y111: 152 | Z111: 176 | AA111: 221 | AB111: 249 | AC111: 276 | AD111: 304 | AE111: 333 | AF111: 362 | AG111: 391 | AH111: 420 | AI111: 450 | AJ111: 481 | AK111: 513 | AL111: 522 | AM111: 531 | AN111: 540 | AO111: 549 | AP111: 559 | AQ111: 568 | AR111: 578 | AS111: 588 | AT111: 599 | AU111: 609 | AV111: 620 | AW111: 630 | AX111: 641 | AY111: 652 | AZ111: 663 | BA111: 674 | BB111: 686 | BC111: 697 | BD111: 709 | BE111: 721 | BF111: 734 | BG111: 748 | BH111: 762 | BI111: 776 | BJ111: 791 | BK111: 807 | BL111: 825 | BM111: 843 | BN111: 862 | BO111: 883 | BP111: 907 | BQ111: 932 | BR111: 959 | BS111: 988 | BT111: 1019 | BU111: 1054 | BV111: 1090 | BW111: 1129 | BX111: 1173 | BY111: 1220 | BZ111: 1272 | CA111: 1328 | CB111: 1388 | CC111: 1455 | CD111: 1527 | CE111: 1610 | CF111: 1701 | CG111: 1801 | CH111: 1908 | CI111: 2028 | CJ111: 2169 | CK111: 2324 | CL111: 2499 | CM111: 2696 | CN111: 2920 | CO111: 3209 | CP111: 3547 | CQ111: 3933 | CR111: 4392 | CS111: 4919 | CT111: 5577 | CU111: 6376 | CV111: 7342 | CW111: 8535 | CX111: 0 | CY111: 0 | CZ111: 0 | DA111: 0 | DB111: 0 | DC111: 0 | DD111: 0 | DE111: 0 | DF111: 0 | DG111: 0 | DH111: 0 | DI111: 0 | DJ111: 0 | DK111: 0 | DL111: 0 | DM111: 0 | DN111: 0 | DO111: 0 | DP111: 0 | DQ111: 0 | DR111: 0 | DS111: 0 | DT111: 0 | DU111: 0 | DV111: 0 | DW111: 0 | DX111: 0 | DZ111: 56 | EA111: SDJ20 | EB111: 1 | EC111: 0 | ED111: =EA111&TEXT(EB111,"00")&TEXT(EC111,"00") -> SDJ200100 | EE111: 0 | EF111: 65 | EG111: 125 | EH111: 184 | EI111: 256 | EJ111: 310 | EK111: 413 | EL111: 474 | EM111: 534 | EN111: 652 | EO111: 714 | EP111: 770 | EQ111: 825 | ER111: 879 | ES111: 929 | ET111: 977 | EU111: 1022 | EV111: 1067 | EW111: 1112 | EX111: 0 | EY111: 0 | EZ111: 0 | FA111: 0 | FB111: 0 | FC111: 0 | FD111: 0 | FE111: 0 | FF111: 0 | FG111: 0 | FH111: 0 | FI111: 0 | FJ111: 0 | FK111: 0 | FL111: 0 | FM111: 0 | FN111: 0 | FO111: 0 | FP111: 0 | FQ111: 0 | FR111: 0 | FS111: 0 | FT111: 0 | FU111: 0 | FV111: 0 | FW111: 0 | FX111: 0 | FY111: 0 | FZ111: 0 | GA111: 0 | GB111: 0 | GC111: 0 | GD111: 0 | GE111: 0 | GF111: 0 | GG111: 0 | GH111: 0 | GI111: 0 | GJ111: 0 | GK111: 0 | GL111: 0 | GM111: 0 | GN111: 0 | GO111: 0 | GP111: 0 | GQ111: 0 | GR111: 0 | GS111: 0 | GT111: 0 | GU111: 0 | GV111: 0 | GW111: 0 | GX111: 0 | GY111: 0 | GZ111: 0 | HA111: 0 | HB111: 0 | HC111: 0 | HD111: 0 | HE111: 0 | HF111: 0 | HG111: 0 | HH111: 0 | HI111: 0 | HJ111: 0 | HK111: 0 | HL111: 0 | HM111: 0 | HN111: 0 | HO111: 0 | HP111: 0 | HQ111: 0 | HR111: 0 | HS111: 0 | HT111: 0 | HU111: 0 | HV111: 0 | HW111: 0 | HX111: 0 | HY111: 0 | HZ111: 0 | IA111: 0 | IB111: 0 | IC111: 0 | ID111: 0 | IE111: 0 | IF111: 0 | IG111: 0 | IH111: 0 | II111: 0 | IJ111: 0 | IK111: 0
M112: 56 | N112: SDJ20 | O112: 1 | P112: 1 | Q112: =N112&TEXT(O112,"00")&TEXT(P112,"00") -> SDJ200101 | R112: 0 | S112: 17 | T112: 35 | U112: 53 | V112: 77 | W112: 97 | X112: 131 | Y112: 155 | Z112: 179 | AA112: 226 | AB112: 254 | AC112: 282 | AD112: 310 | AE112: 339 | AF112: 368 | AG112: 397 | AH112: 427 | AI112: 458 | AJ112: 489 | AK112: 522 | AL112: 531 | AM112: 540 | AN112: 549 | AO112: 559 | AP112: 568 | AQ112: 578 | AR112: 588 | AS112: 599 | AT112: 609 | AU112: 620 | AV112: 630 | AW112: 641 | AX112: 652 | AY112: 663 | AZ112: 674 | BA112: 686 | BB112: 697 | BC112: 709 | BD112: 721 | BE112: 734 | BF112: 748 | BG112: 762 | BH112: 776 | BI112: 791 | BJ112: 807 | BK112: 825 | BL112: 843 | BM112: 862 | BN112: 883 | BO112: 907 | BP112: 932 | BQ112: 959 | BR112: 988 | BS112: 1019 | BT112: 1054 | BU112: 1090 | BV112: 1129 | BW112: 1173 | BX112: 1220 | BY112: 1272 | BZ112: 1328 | CA112: 1388 | CB112: 1455 | CC112: 1527 | CD112: 1610 | CE112: 1701 | CF112: 1801 | CG112: 1908 | CH112: 2028 | CI112: 2169 | CJ112: 2324 | CK112: 2499 | CL112: 2696 | CM112: 2920 | CN112: 3209 | CO112: 3547 | CP112: 3933 | CQ112: 4392 | CR112: 4919 | CS112: 5577 | CT112: 6376 | CU112: 7342 | CV112: 8535 | CW112: 0 | CX112: 0 | CY112: 0 | CZ112: 0 | DA112: 0 | DB112: 0 | DC112: 0 | DD112: 0 | DE112: 0 | DF112: 0 | DG112: 0 | DH112: 0 | DI112: 0 | DJ112: 0 | DK112: 0 | DL112: 0 | DM112: 0 | DN112: 0 | DO112: 0 | DP112: 0 | DQ112: 0 | DR112: 0 | DS112: 0 | DT112: 0 | DU112: 0 | DV112: 0 | DW112: 0 | DX112: 0 | DZ112: 56 | EA112: SDJ20 | EB112: 1 | EC112: 1 | ED112: =EA112&TEXT(EB112,"00")&TEXT(EC112,"00") -> SDJ200101 | EE112: 0 | EF112: 64 | EG112: 127 | EH112: 184 | EI112: 259 | EJ112: 315 | EK112: 412 | EL112: 474 | EM112: 532 | EN112: 653 | EO112: 714 | EP112: 771 | EQ112: 825 | ER112: 877 | ES112: 927 | ET112: 974 | EU112: 1021 | EV112: 1068 | EW112: 1112 | EX112: 0 | EY112: 0 | EZ112: 0 | FA112: 0 | FB112: 0 | FC112: 0 | FD112: 0 | FE112: 0 | FF112: 0 | FG112: 0 | FH112: 0 | FI112: 0 | FJ112: 0 | FK112: 0 | FL112: 0 | FM112: 0 | FN112: 0 | FO112: 0 | FP112: 0 | FQ112: 0 | FR112: 0 | FS112: 0 | FT112: 0 | FU112: 0 | FV112: 0 | FW112: 0 | FX112: 0 | FY112: 0 | FZ112: 0 | GA112: 0 | GB112: 0 | GC112: 0 | GD112: 0 | GE112: 0 | GF112: 0 | GG112: 0 | GH112: 0 | GI112: 0 | GJ112: 0 | GK112: 0 | GL112: 0 | GM112: 0 | GN112: 0 | GO112: 0 | GP112: 0 | GQ112: 0 | GR112: 0 | GS112: 0 | GT112: 0 | GU112: 0 | GV112: 0 | GW112: 0 | GX112: 0 | GY112: 0 | GZ112: 0 | HA112: 0 | HB112: 0 | HC112: 0 | HD112: 0 | HE112: 0 | HF112: 0 | HG112: 0 | HH112: 0 | HI112: 0 | HJ112: 0 | HK112: 0 | HL112: 0 | HM112: 0 | HN112: 0 | HO112: 0 | HP112: 0 | HQ112: 0 | HR112: 0 | HS112: 0 | HT112: 0 | HU112: 0 | HV112: 0 | HW112: 0 | HX112: 0 | HY112: 0 | HZ112: 0 | IA112: 0 | IB112: 0 | IC112: 0 | ID112: 0 | IE112: 0 | IF112: 0 | IG112: 0 | IH112: 0 | II112: 0 | IJ112: 0 | IK112: 0
M113: 56 | N113: SDJ20 | O113: 1 | P113: 2 | Q113: =N113&TEXT(O113,"00")&TEXT(P113,"00") -> SDJ200102 | R113: 0 | S113: 18 | T113: 36 | U113: 55 | V113: 78 | W113: 98 | X113: 134 | Y113: 158 | Z113: 183 | AA113: 230 | AB113: 258 | AC113: 287 | AD113: 315 | AE113: 344 | AF113: 374 | AG113: 404 | AH113: 434 | AI113: 466 | AJ113: 498 | AK113: 531 | AL113: 540 | AM113: 549 | AN113: 559 | AO113: 568 | AP113: 578 | AQ113: 588 | AR113: 599 | AS113: 609 | AT113: 620 | AU113: 630 | AV113: 641 | AW113: 652 | AX113: 663 | AY113: 674 | AZ113: 686 | BA113: 697 | BB113: 709 | BC113: 721 | BD113: 734 | BE113: 748 | BF113: 762 | BG113: 776 | BH113: 791 | BI113: 807 | BJ113: 825 | BK113: 843 | BL113: 862 | BM113: 883 | BN113: 907 | BO113: 932 | BP113: 959 | BQ113: 988 | BR113: 1019 | BS113: 1054 | BT113: 1090 | BU113: 1129 | BV113: 1173 | BW113: 1220 | BX113: 1272 | BY113: 1328 | BZ113: 1388 | CA113: 1455 | CB113: 1527 | CC113: 1610 | CD113: 1701 | CE113: 1801 | CF113: 1908 | CG113: 2028 | CH113: 2169 | CI113: 2324 | CJ113: 2499 | CK113: 2696 | CL113: 2920 | CM113: 3209 | CN113: 3547 | CO113: 3933 | CP113: 4392 | CQ113: 4919 | CR113: 5577 | CS113: 6376 | CT113: 7342 | CU113: 8535 | CV113: 0 | CW113: 0 | CX113: 0 | CY113: 0 | CZ113: 0 | DA113: 0 | DB113: 0 | DC113: 0 | DD113: 0 | DE113: 0 | DF113: 0 | DG113: 0 | DH113: 0 | DI113: 0 | DJ113: 0 | DK113: 0 | DL113: 0 | DM113: 0 | DN113: 0 | DO113: 0 | DP113: 0 | DQ113: 0 | DR113: 0 | DS113: 0 | DT113: 0 | DU113: 0 | DV113: 0 | DW113: 0 | DX113: 0 | DZ113: 56 | EA113: SDJ20 | EB113: 1 | EC113: 2 | ED113: =EA113&TEXT(EB113,"00")&TEXT(EC113,"00") -> SDJ200102 | EE113: 0 | EF113: 67 | EG113: 128 | EH113: 188 | EI113: 257 | EJ113: 312 | EK113: 413 | EL113: 473 | EM113: 533 | EN113: 652 | EO113: 711 | EP113: 770 | EQ113: 822 | ER113: 874 | ES113: 925 | ET113: 974 | EU113: 1020 | EV113: 1069 | EW113: 1114 | EX113: 0 | EY113: 0 | EZ113: 0 | FA113: 0 | FB113: 0 | FC113: 0 | FD113: 0 | FE113: 0 | FF113: 0 | FG113: 0 | FH113: 0 | FI113: 0 | FJ113: 0 | FK113: 0 | FL113: 0 | FM113: 0 | FN113: 0 | FO113: 0 | FP113: 0 | FQ113: 0 | FR113: 0 | FS113: 0 | FT113: 0 | FU113: 0 | FV113: 0 | FW113: 0 | FX113: 0 | FY113: 0 | FZ113: 0 | GA113: 0 | GB113: 0 | GC113: 0 | GD113: 0 | GE113: 0 | GF113: 0 | GG113: 0 | GH113: 0 | GI113: 0 | GJ113: 0 | GK113: 0 | GL113: 0 | GM113: 0 | GN113: 0 | GO113: 0 | GP113: 0 | GQ113: 0 | GR113: 0 | GS113: 0 | GT113: 0 | GU113: 0 | GV113: 0 | GW113: 0 | GX113: 0 | GY113: 0 | GZ113: 0 | HA113: 0 | HB113: 0 | HC113: 0 | HD113: 0 | HE113: 0 | HF113: 0 | HG113: 0 | HH113: 0 | HI113: 0 | HJ113: 0 | HK113: 0 | HL113: 0 | HM113: 0 | HN113: 0 | HO113: 0 | HP113: 0 | HQ113: 0 | HR113: 0 | HS113: 0 | HT113: 0 | HU113: 0 | HV113: 0 | HW113: 0 | HX113: 0 | HY113: 0 | HZ113: 0 | IA113: 0 | IB113: 0 | IC113: 0 | ID113: 0 | IE113: 0 | IF113: 0 | IG113: 0 | IH113: 0 | II113: 0 | IJ113: 0 | IK113: 0
M114: 56 | N114: SDJ20 | O114: 1 | P114: 3 | Q114: =N114&TEXT(O114,"00")&TEXT(P114,"00") -> SDJ200103 | R114: 0 | S114: 18 | T114: 37 | U114: 56 | V114: 79 | W114: 100 | X114: 137 | Y114: 161 | Z114: 185 | AA114: 234 | AB114: 263 | AC114: 291 | AD114: 320 | AE114: 350 | AF114: 380 | AG114: 410 | AH114: 442 | AI114: 474 | AJ114: 507 | AK114: 540 | AL114: 549 | AM114: 559 | AN114: 568 | AO114: 578 | AP114: 588 | AQ114: 599 | AR114: 609 | AS114: 620 | AT114: 630 | AU114: 641 | AV114: 652 | AW114: 663 | AX114: 674 | AY114: 686 | AZ114: 697 | BA114: 709 | BB114: 721 | BC114: 734 | BD114: 748 | BE114: 762 | BF114: 776 | BG114: 791 | BH114: 807 | BI114: 825 | BJ114: 843 | BK114: 862 | BL114: 883 | BM114: 907 | BN114: 932 | BO114: 959 | BP114: 988 | BQ114: 1019 | BR114: 1054 | BS114: 1090 | BT114: 1129 | BU114: 1173 | BV114: 1220 | BW114: 1272 | BX114: 1328 | BY114: 1388 | BZ114: 1455 | CA114: 1527 | CB114: 1610 | CC114: 1701 | CD114: 1801 | CE114: 1908 | CF114: 2028 | CG114: 2169 | CH114: 2324 | CI114: 2499 | CJ114: 2696 | CK114: 2920 | CL114: 3209 | CM114: 3547 | CN114: 3933 | CO114: 4392 | CP114: 4919 | CQ114: 5577 | CR114: 6376 | CS114: 7342 | CT114: 8535 | CU114: 0 | CV114: 0 | CW114: 0 | CX114: 0 | CY114: 0 | CZ114: 0 | DA114: 0 | DB114: 0 | DC114: 0 | DD114: 0 | DE114: 0 | DF114: 0 | DG114: 0 | DH114: 0 | DI114: 0 | DJ114: 0 | DK114: 0 | DL114: 0 | DM114: 0 | DN114: 0 | DO114: 0 | DP114: 0 | DQ114: 0 | DR114: 0 | DS114: 0 | DT114: 0 | DU114: 0 | DV114: 0 | DW114: 0 | DX114: 0 | DZ114: 56 | EA114: SDJ20 | EB114: 1 | EC114: 3 | ED114: =EA114&TEXT(EB114,"00")&TEXT(EC114,"00") -> SDJ200103 | EE114: 0 | EF114: 66 | EG114: 130 | EH114: 188 | EI114: 256 | EJ114: 312 | EK114: 414 | EL114: 473 | EM114: 529 | EN114: 650 | EO114: 711 | EP114: 765 | EQ114: 819 | ER114: 873 | ES114: 924 | ET114: 972 | EU114: 1022 | EV114: 1069 | EW114: 1115 | EX114: 0 | EY114: 0 | EZ114: 0 | FA114: 0 | FB114: 0 | FC114: 0 | FD114: 0 | FE114: 0 | FF114: 0 | FG114: 0 | FH114: 0 | FI114: 0 | FJ114: 0 | FK114: 0 | FL114: 0 | FM114: 0 | FN114: 0 | FO114: 0 | FP114: 0 | FQ114: 0 | FR114: 0 | FS114: 0 | FT114: 0 | FU114: 0 | FV114: 0 | FW114: 0 | FX114: 0 | FY114: 0 | FZ114: 0 | GA114: 0 | GB114: 0 | GC114: 0 | GD114: 0 | GE114: 0 | GF114: 0 | GG114: 0 | GH114: 0 | GI114: 0 | GJ114: 0 | GK114: 0 | GL114: 0 | GM114: 0 | GN114: 0 | GO114: 0 | GP114: 0 | GQ114: 0 | GR114: 0 | GS114: 0 | GT114: 0 | GU114: 0 | GV114: 0 | GW114: 0 | GX114: 0 | GY114: 0 | GZ114: 0 | HA114: 0 | HB114: 0 | HC114: 0 | HD114: 0 | HE114: 0 | HF114: 0 | HG114: 0 | HH114: 0 | HI114: 0 | HJ114: 0 | HK114: 0 | HL114: 0 | HM114: 0 | HN114: 0 | HO114: 0 | HP114: 0 | HQ114: 0 | HR114: 0 | HS114: 0 | HT114: 0 | HU114: 0 | HV114: 0 | HW114: 0 | HX114: 0 | HY114: 0 | HZ114: 0 | IA114: 0 | IB114: 0 | IC114: 0 | ID114: 0 | IE114: 0 | IF114: 0 | IG114: 0 | IH114: 0 | II114: 0 | IJ114: 0 | IK114: 0
M115: 56 | N115: SDJ20 | O115: 1 | P115: 4 | Q115: =N115&TEXT(O115,"00")&TEXT(P115,"00") -> SDJ200104 | R115: 0 | S115: 18 | T115: 37 | U115: 56 | V115: 81 | W115: 102 | X115: 139 | Y115: 164 | Z115: 189 | AA115: 238 | AB115: 267 | AC115: 296 | AD115: 325 | AE115: 355 | AF115: 386 | AG115: 417 | AH115: 449 | AI115: 482 | AJ115: 515 | AK115: 549 | AL115: 559 | AM115: 568 | AN115: 578 | AO115: 588 | AP115: 599 | AQ115: 609 | AR115: 620 | AS115: 630 | AT115: 641 | AU115: 652 | AV115: 663 | AW115: 674 | AX115: 686 | AY115: 697 | AZ115: 709 | BA115: 721 | BB115: 734 | BC115: 748 | BD115: 762 | BE115: 776 | BF115: 791 | BG115: 807 | BH115: 825 | BI115: 843 | BJ115: 862 | BK115: 883 | BL115: 907 | BM115: 932 | BN115: 959 | BO115: 988 | BP115: 1019 | BQ115: 1054 | BR115: 1090 | BS115: 1129 | BT115: 1173 | BU115: 1220 | BV115: 1272 | BW115: 1328 | BX115: 1388 | BY115: 1455 | BZ115: 1527 | CA115: 1610 | CB115: 1701 | CC115: 1801 | CD115: 1908 | CE115: 2028 | CF115: 2169 | CG115: 2324 | CH115: 2499 | CI115: 2696 | CJ115: 2920 | CK115: 3209 | CL115: 3547 | CM115: 3933 | CN115: 4392 | CO115: 4919 | CP115: 5577 | CQ115: 6376 | CR115: 7342 | CS115: 8535 | CT115: 0 | CU115: 0 | CV115: 0 | CW115: 0 | CX115: 0 | CY115: 0 | CZ115: 0 | DA115: 0 | DB115: 0 | DC115: 0 | DD115: 0 | DE115: 0 | DF115: 0 | DG115: 0 | DH115: 0 | DI115: 0 | DJ115: 0 | DK115: 0 | DL115: 0 | DM115: 0 | DN115: 0 | DO115: 0 | DP115: 0 | DQ115: 0 | DR115: 0 | DS115: 0 | DT115: 0 | DU115: 0 | DV115: 0 | DW115: 0 | DX115: 0 | DZ115: 56 | EA115: SDJ20 | EB115: 1 | EC115: 4 | ED115: =EA115&TEXT(EB115,"00")&TEXT(EC115,"00") -> SDJ200104 | EE115: 0 | EF115: 65 | EG115: 127 | EH115: 184 | EI115: 257 | EJ115: 312 | EK115: 412 | EL115: 472 | EM115: 529 | EN115: 649 | EO115: 708 | EP115: 764 | EQ115: 817 | ER115: 870 | ES115: 923 | ET115: 972 | EU115: 1021 | EV115: 1068 | EW115: 1113 | EX115: 0 | EY115: 0 | EZ115: 0 | FA115: 0 | FB115: 0 | FC115: 0 | FD115: 0 | FE115: 0 | FF115: 0 | FG115: 0 | FH115: 0 | FI115: 0 | FJ115: 0 | FK115: 0 | FL115: 0 | FM115: 0 | FN115: 0 | FO115: 0 | FP115: 0 | FQ115: 0 | FR115: 0 | FS115: 0 | FT115: 0 | FU115: 0 | FV115: 0 | FW115: 0 | FX115: 0 | FY115: 0 | FZ115: 0 | GA115: 0 | GB115: 0 | GC115: 0 | GD115: 0 | GE115: 0 | GF115: 0 | GG115: 0 | GH115: 0 | GI115: 0 | GJ115: 0 | GK115: 0 | GL115: 0 | GM115: 0 | GN115: 0 | GO115: 0 | GP115: 0 | GQ115: 0 | GR115: 0 | GS115: 0 | GT115: 0 | GU115: 0 | GV115: 0 | GW115: 0 | GX115: 0 | GY115: 0 | GZ115: 0 | HA115: 0 | HB115: 0 | HC115: 0 | HD115: 0 | HE115: 0 | HF115: 0 | HG115: 0 | HH115: 0 | HI115: 0 | HJ115: 0 | HK115: 0 | HL115: 0 | HM115: 0 | HN115: 0 | HO115: 0 | HP115: 0 | HQ115: 0 | HR115: 0 | HS115: 0 | HT115: 0 | HU115: 0 | HV115: 0 | HW115: 0 | HX115: 0 | HY115: 0 | HZ115: 0 | IA115: 0 | IB115: 0 | IC115: 0 | ID115: 0 | IE115: 0 | IF115: 0 | IG115: 0 | IH115: 0 | II115: 0 | IJ115: 0 | IK115: 0
M116: 56 | N116: SDJ20 | O116: 1 | P116: 5 | Q116: =N116&TEXT(O116,"00")&TEXT(P116,"00") -> SDJ200105 | R116: 0 | S116: 19 | T116: 38 | U116: 57 | V116: 82 | W116: 104 | X116: 141 | Y116: 167 | Z116: 193 | AA116: 242 | AB116: 271 | AC116: 301 | AD116: 330 | AE116: 361 | AF116: 392 | AG116: 424 | AH116: 457 | AI116: 490 | AJ116: 524 | AK116: 559 | AL116: 568 | AM116: 578 | AN116: 588 | AO116: 599 | AP116: 609 | AQ116: 620 | AR116: 630 | AS116: 641 | AT116: 652 | AU116: 663 | AV116: 674 | AW116: 686 | AX116: 697 | AY116: 709 | AZ116: 721 | BA116: 734 | BB116: 748 | BC116: 762 | BD116: 776 | BE116: 791 | BF116: 807 | BG116: 825 | BH116: 843 | BI116: 862 | BJ116: 883 | BK116: 907 | BL116: 932 | BM116: 959 | BN116: 988 | BO116: 1019 | BP116: 1054 | BQ116: 1090 | BR116: 1129 | BS116: 1173 | BT116: 1220 | BU116: 1272 | BV116: 1328 | BW116: 1388 | BX116: 1455 | BY116: 1527 | BZ116: 1610 | CA116: 1701 | CB116: 1801 | CC116: 1908 | CD116: 2028 | CE116: 2169 | CF116: 2324 | CG116: 2499 | CH116: 2696 | CI116: 2920 | CJ116: 3209 | CK116: 3547 | CL116: 3933 | CM116: 4392 | CN116: 4919 | CO116: 5577 | CP116: 6376 | CQ116: 7342 | CR116: 8535 | CS116: 0 | CT116: 0 | CU116: 0 | CV116: 0 | CW116: 0 | CX116: 0 | CY116: 0 | CZ116: 0 | DA116: 0 | DB116: 0 | DC116: 0 | DD116: 0 | DE116: 0 | DF116: 0 | DG116: 0 | DH116: 0 | DI116: 0 | DJ116: 0 | DK116: 0 | DL116: 0 | DM116: 0 | DN116: 0 | DO116: 0 | DP116: 0 | DQ116: 0 | DR116: 0 | DS116: 0 | DT116: 0 | DU116: 0 | DV116: 0 | DW116: 0 | DX116: 0 | DZ116: 56 | EA116: SDJ20 | EB116: 1 | EC116: 5 | ED116: =EA116&TEXT(EB116,"00")&TEXT(EC116,"00") -> SDJ200105 | EE116: 0 | EF116: 67 | EG116: 128 | EH116: 184 | EI116: 255 | EJ116: 312 | EK116: 409 | EL116: 472 | EM116: 530 | EN116: 647 | EO116: 705 | EP116: 763 | EQ116: 815 | ER116: 870 | ES116: 921 | ET116: 972 | EU116: 1021 | EV116: 1068 | EW116: 1113 | EX116: 0 | EY116: 0 | EZ116: 0 | FA116: 0 | FB116: 0 | FC116: 0 | FD116: 0 | FE116: 0 | FF116: 0 | FG116: 0 | FH116: 0 | FI116: 0 | FJ116: 0 | FK116: 0 | FL116: 0 | FM116: 0 | FN116: 0 | FO116: 0 | FP116: 0 | FQ116: 0 | FR116: 0 | FS116: 0 | FT116: 0 | FU116: 0 | FV116: 0 | FW116: 0 | FX116: 0 | FY116: 0 | FZ116: 0 | GA116: 0 | GB116: 0 | GC116: 0 | GD116: 0 | GE116: 0 | GF116: 0 | GG116: 0 | GH116: 0 | GI116: 0 | GJ116: 0 | GK116: 0 | GL116: 0 | GM116: 0 | GN116: 0 | GO116: 0 | GP116: 0 | GQ116: 0 | GR116: 0 | GS116: 0 | GT116: 0 | GU116: 0 | GV116: 0 | GW116: 0 | GX116: 0 | GY116: 0 | GZ116: 0 | HA116: 0 | HB116: 0 | HC116: 0 | HD116: 0 | HE116: 0 | HF116: 0 | HG116: 0 | HH116: 0 | HI116: 0 | HJ116: 0 | HK116: 0 | HL116: 0 | HM116: 0 | HN116: 0 | HO116: 0 | HP116: 0 | HQ116: 0 | HR116: 0 | HS116: 0 | HT116: 0 | HU116: 0 | HV116: 0 | HW116: 0 | HX116: 0 | HY116: 0 | HZ116: 0 | IA116: 0 | IB116: 0 | IC116: 0 | ID116: 0 | IE116: 0 | IF116: 0 | IG116: 0 | IH116: 0 | II116: 0 | IJ116: 0 | IK116: 0
M117: 56 | N117: SDJ20 | O117: 1 | P117: 6 | Q117: =N117&TEXT(O117,"00")&TEXT(P117,"00") -> SDJ200106 | R117: 0 | S117: 19 | T117: 38 | U117: 59 | V117: 84 | W117: 106 | X117: 144 | Y117: 170 | Z117: 195 | AA117: 246 | AB117: 275 | AC117: 305 | AD117: 335 | AE117: 367 | AF117: 399 | AG117: 431 | AH117: 464 | AI117: 498 | AJ117: 533 | AK117: 568 | AL117: 578 | AM117: 588 | AN117: 599 | AO117: 609 | AP117: 620 | AQ117: 630 | AR117: 641 | AS117: 652 | AT117: 663 | AU117: 674 | AV117: 686 | AW117: 697 | AX117: 709 | AY117: 721 | AZ117: 734 | BA117: 748 | BB117: 762 | BC117: 776 | BD117: 791 | BE117: 807 | BF117: 825 | BG117: 843 | BH117: 862 | BI117: 883 | BJ117: 907 | BK117: 932 | BL117: 959 | BM117: 988 | BN117: 1019 | BO117: 1054 | BP117: 1090 | BQ117: 1129 | BR117: 1173 | BS117: 1220 | BT117: 1272 | BU117: 1328 | BV117: 1388 | BW117: 1455 | BX117: 1527 | BY117: 1610 | BZ117: 1701 | CA117: 1801 | CB117: 1908 | CC117: 2028 | CD117: 2169 | CE117: 2324 | CF117: 2499 | CG117: 2696 | CH117: 2920 | CI117: 3209 | CJ117: 3547 | CK117: 3933 | CL117: 4392 | CM117: 4919 | CN117: 5577 | CO117: 6376 | CP117: 7342 | CQ117: 8535 | CR117: 0 | CS117: 0 | CT117: 0 | CU117: 0 | CV117: 0 | CW117: 0 | CX117: 0 | CY117: 0 | CZ117: 0 | DA117: 0 | DB117: 0 | DC117: 0 | DD117: 0 | DE117: 0 | DF117: 0 | DG117: 0 | DH117: 0 | DI117: 0 | DJ117: 0 | DK117: 0 | DL117: 0 | DM117: 0 | DN117: 0 | DO117: 0 | DP117: 0 | DQ117: 0 | DR117: 0 | DS117: 0 | DT117: 0 | DU117: 0 | DV117: 0 | DW117: 0 | DX117: 0 | DZ117: 56 | EA117: SDJ20 | EB117: 1 | EC117: 6 | ED117: =EA117&TEXT(EB117,"00")&TEXT(EC117,"00") -> SDJ200106 | EE117: 0 | EF117: 66 | EG117: 126 | EH117: 187 | EI117: 256 | EJ117: 312 | EK117: 410 | EL117: 471 | EM117: 525 | EN117: 645 | EO117: 703 | EP117: 759 | EQ117: 814 | ER117: 870 | ES117: 922 | ET117: 971 | EU117: 1020 | EV117: 1067 | EW117: 1113 | EX117: 0 | EY117: 0 | EZ117: 0 | FA117: 0 | FB117: 0 | FC117: 0 | FD117: 0 | FE117: 0 | FF117: 0 | FG117: 0 | FH117: 0 | FI117: 0 | FJ117: 0 | FK117: 0 | FL117: 0 | FM117: 0 | FN117: 0 | FO117: 0 | FP117: 0 | FQ117: 0 | FR117: 0 | FS117: 0 | FT117: 0 | FU117: 0 | FV117: 0 | FW117: 0 | FX117: 0 | FY117: 0 | FZ117: 0 | GA117: 0 | GB117: 0 | GC117: 0 | GD117: 0 | GE117: 0 | GF117: 0 | GG117: 0 | GH117: 0 | GI117: 0 | GJ117: 0 | GK117: 0 | GL117: 0 | GM117: 0 | GN117: 0 | GO117: 0 | GP117: 0 | GQ117: 0 | GR117: 0 | GS117: 0 | GT117: 0 | GU117: 0 | GV117: 0 | GW117: 0 | GX117: 0 | GY117: 0 | GZ117: 0 | HA117: 0 | HB117: 0 | HC117: 0 | HD117: 0 | HE117: 0 | HF117: 0 | HG117: 0 | HH117: 0 | HI117: 0 | HJ117: 0 | HK117: 0 | HL117: 0 | HM117: 0 | HN117: 0 | HO117: 0 | HP117: 0 | HQ117: 0 | HR117: 0 | HS117: 0 | HT117: 0 | HU117: 0 | HV117: 0 | HW117: 0 | HX117: 0 | HY117: 0 | HZ117: 0 | IA117: 0 | IB117: 0 | IC117: 0 | ID117: 0 | IE117: 0 | IF117: 0 | IG117: 0 | IH117: 0 | II117: 0 | IJ117: 0 | IK117: 0
M118: 56 | N118: SDJ20 | O118: 1 | P118: 7 | Q118: =N118&TEXT(O118,"00")&TEXT(P118,"00") -> SDJ200107 | R118: 0 | S118: 20 | T118: 39 | U118: 59 | V118: 86 | W118: 108 | X118: 147 | Y118: 173 | Z118: 199 | AA118: 250 | AB118: 279 | AC118: 310 | AD118: 341 | AE118: 373 | AF118: 405 | AG118: 438 | AH118: 472 | AI118: 507 | AJ118: 542 | AK118: 578 | AL118: 588 | AM118: 599 | AN118: 609 | AO118: 620 | AP118: 630 | AQ118: 641 | AR118: 652 | AS118: 663 | AT118: 674 | AU118: 686 | AV118: 697 | AW118: 709 | AX118: 721 | AY118: 734 | AZ118: 748 | BA118: 762 | BB118: 776 | BC118: 791 | BD118: 807 | BE118: 825 | BF118: 843 | BG118: 862 | BH118: 883 | BI118: 907 | BJ118: 932 | BK118: 959 | BL118: 988 | BM118: 1019 | BN118: 1054 | BO118: 1090 | BP118: 1129 | BQ118: 1173 | BR118: 1220 | BS118: 1272 | BT118: 1328 | BU118: 1388 | BV118: 1455 | BW118: 1527 | BX118: 1610 | BY118: 1701 | BZ118: 1801 | CA118: 1908 | CB118: 2028 | CC118: 2169 | CD118: 2324 | CE118: 2499 | CF118: 2696 | CG118: 2920 | CH118: 3209 | CI118: 3547 | CJ118: 3933 | CK118: 4392 | CL118: 4919 | CM118: 5577 | CN118: 6376 | CO118: 7342 | CP118: 8535 | CQ118: 0 | CR118: 0 | CS118: 0 | CT118: 0 | CU118: 0 | CV118: 0 | CW118: 0 | CX118: 0 | CY118: 0 | CZ118: 0 | DA118: 0 | DB118: 0 | DC118: 0 | DD118: 0 | DE118: 0 | DF118: 0 | DG118: 0 | DH118: 0 | DI118: 0 | DJ118: 0 | DK118: 0 | DL118: 0 | DM118: 0 | DN118: 0 | DO118: 0 | DP118: 0 | DQ118: 0 | DR118: 0 | DS118: 0 | DT118: 0 | DU118: 0 | DV118: 0 | DW118: 0 | DX118: 0 | DZ118: 56 | EA118: SDJ20 | EB118: 1 | EC118: 7 | ED118: =EA118&TEXT(EB118,"00")&TEXT(EC118,"00") -> SDJ200107 | EE118: 0 | EF118: 68 | EG118: 127 | EH118: 183 | EI118: 257 | EJ118: 311 | EK118: 410 | EL118: 470 | EM118: 526 | EN118: 644 | EO118: 700 | EP118: 759 | EQ118: 814 | ER118: 869 | ES118: 920 | ET118: 970 | EU118: 1019 | EV118: 1067 | EW118: 1112 | EX118: 0 | EY118: 0 | EZ118: 0 | FA118: 0 | FB118: 0 | FC118: 0 | FD118: 0 | FE118: 0 | FF118: 0 | FG118: 0 | FH118: 0 | FI118: 0 | FJ118: 0 | FK118: 0 | FL118: 0 | FM118: 0 | FN118: 0 | FO118: 0 | FP118: 0 | FQ118: 0 | FR118: 0 | FS118: 0 | FT118: 0 | FU118: 0 | FV118: 0 | FW118: 0 | FX118: 0 | FY118: 0 | FZ118: 0 | GA118: 0 | GB118: 0 | GC118: 0 | GD118: 0 | GE118: 0 | GF118: 0 | GG118: 0 | GH118: 0 | GI118: 0 | GJ118: 0 | GK118: 0 | GL118: 0 | GM118: 0 | GN118: 0 | GO118: 0 | GP118: 0 | GQ118: 0 | GR118: 0 | GS118: 0 | GT118: 0 | GU118: 0 | GV118: 0 | GW118: 0 | GX118: 0 | GY118: 0 | GZ118: 0 | HA118: 0 | HB118: 0 | HC118: 0 | HD118: 0 | HE118: 0 | HF118: 0 | HG118: 0 | HH118: 0 | HI118: 0 | HJ118: 0 | HK118: 0 | HL118: 0 | HM118: 0 | HN118: 0 | HO118: 0 | HP118: 0 | HQ118: 0 | HR118: 0 | HS118: 0 | HT118: 0 | HU118: 0 | HV118: 0 | HW118: 0 | HX118: 0 | HY118: 0 | HZ118: 0 | IA118: 0 | IB118: 0 | IC118: 0 | ID118: 0 | IE118: 0 | IF118: 0 | IG118: 0 | IH118: 0 | II118: 0 | IJ118: 0 | IK118: 0
M119: 56 | N119: SDJ20 | O119: 1 | P119: 8 | Q119: =N119&TEXT(O119,"00")&TEXT(P119,"00") -> SDJ200108 | R119: 0 | S119: 20 | T119: 40 | U119: 61 | V119: 87 | W119: 110 | X119: 149 | Y119: 176 | Z119: 202 | AA119: 253 | AB119: 283 | AC119: 314 | AD119: 346 | AE119: 379 | AF119: 412 | AG119: 445 | AH119: 480 | AI119: 515 | AJ119: 551 | AK119: 588 | AL119: 599 | AM119: 609 | AN119: 620 | AO119: 630 | AP119: 641 | AQ119: 652 | AR119: 663 | AS119: 674 | AT119: 686 | AU119: 697 | AV119: 709 | AW119: 721 | AX119: 734 | AY119: 748 | AZ119: 762 | BA119: 776 | BB119: 791 | BC119: 807 | BD119: 825 | BE119: 843 | BF119: 862 | BG119: 883 | BH119: 907 | BI119: 932 | BJ119: 959 | BK119: 988 | BL119: 1019 | BM119: 1054 | BN119: 1090 | BO119: 1129 | BP119: 1173 | BQ119: 1220 | BR119: 1272 | BS119: 1328 | BT119: 1388 | BU119: 1455 | BV119: 1527 | BW119: 1610 | BX119: 1701 | BY119: 1801 | BZ119: 1908 | CA119: 2028 | CB119: 2169 | CC119: 2324 | CD119: 2499 | CE119: 2696 | CF119: 2920 | CG119: 3209 | CH119: 3547 | CI119: 3933 | CJ119: 4392 | CK119: 4919 | CL119: 5577 | CM119: 6376 | CN119: 7342 | CO119: 8535 | CP119: 0 | CQ119: 0 | CR119: 0 | CS119: 0 | CT119: 0 | CU119: 0 | CV119: 0 | CW119: 0 | CX119: 0 | CY119: 0 | CZ119: 0 | DA119: 0 | DB119: 0 | DC119: 0 | DD119: 0 | DE119: 0 | DF119: 0 | DG119: 0 | DH119: 0 | DI119: 0 | DJ119: 0 | DK119: 0 | DL119: 0 | DM119: 0 | DN119: 0 | DO119: 0 | DP119: 0 | DQ119: 0 | DR119: 0 | DS119: 0 | DT119: 0 | DU119: 0 | DV119: 0 | DW119: 0 | DX119: 0 | DZ119: 56 | EA119: SDJ20 | EB119: 1 | EC119: 8 | ED119: =EA119&TEXT(EB119,"00")&TEXT(EC119,"00") -> SDJ200108 | EE119: 0 | EF119: 67 | EG119: 127 | EH119: 185 | EI119: 255 | EJ119: 311 | EK119: 408 | EL119: 469 | EM119: 524 | EN119: 640 | EO119: 698 | EP119: 756 | EQ119: 813 | ER119: 868 | ES119: 920 | ET119: 969 | EU119: 1018 | EV119: 1065 | EW119: 1110 | EX119: 0 | EY119: 0 | EZ119: 0 | FA119: 0 | FB119: 0 | FC119: 0 | FD119: 0 | FE119: 0 | FF119: 0 | FG119: 0 | FH119: 0 | FI119: 0 | FJ119: 0 | FK119: 0 | FL119: 0 | FM119: 0 | FN119: 0 | FO119: 0 | FP119: 0 | FQ119: 0 | FR119: 0 | FS119: 0 | FT119: 0 | FU119: 0 | FV119: 0 | FW119: 0 | FX119: 0 | FY119: 0 | FZ119: 0 | GA119: 0 | GB119: 0 | GC119: 0 | GD119: 0 | GE119: 0 | GF119: 0 | GG119: 0 | GH119: 0 | GI119: 0 | GJ119: 0 | GK119: 0 | GL119: 0 | GM119: 0 | GN119: 0 | GO119: 0 | GP119: 0 | GQ119: 0 | GR119: 0 | GS119: 0 | GT119: 0 | GU119: 0 | GV119: 0 | GW119: 0 | GX119: 0 | GY119: 0 | GZ119: 0 | HA119: 0 | HB119: 0 | HC119: 0 | HD119: 0 | HE119: 0 | HF119: 0 | HG119: 0 | HH119: 0 | HI119: 0 | HJ119: 0 | HK119: 0 | HL119: 0 | HM119: 0 | HN119: 0 | HO119: 0 | HP119: 0 | HQ119: 0 | HR119: 0 | HS119: 0 | HT119: 0 | HU119: 0 | HV119: 0 | HW119: 0 | HX119: 0 | HY119: 0 | HZ119: 0 | IA119: 0 | IB119: 0 | IC119: 0 | ID119: 0 | IE119: 0 | IF119: 0 | IG119: 0 | IH119: 0 | II119: 0 | IJ119: 0 | IK119: 0
M120: 56 | N120: SDJ20 | O120: 1 | P120: 9 | Q120: =N120&TEXT(O120,"00")&TEXT(P120,"00") -> SDJ200109 | R120: 0 | S120: 20 | T120: 41 | U120: 62 | V120: 89 | W120: 111 | X120: 151 | Y120: 177 | Z120: 204 | AA120: 257 | AB120: 288 | AC120: 319 | AD120: 352 | AE120: 385 | AF120: 418 | AG120: 453 | AH120: 488 | AI120: 524 | AJ120: 561 | AK120: 599 | AL120: 609 | AM120: 620 | AN120: 630 | AO120: 641 | AP120: 652 | AQ120: 663 | AR120: 674 | AS120: 686 | AT120: 697 | AU120: 709 | AV120: 721 | AW120: 734 | AX120: 748 | AY120: 762 | AZ120: 776 | BA120: 791 | BB120: 807 | BC120: 825 | BD120: 843 | BE120: 862 | BF120: 883 | BG120: 907 | BH120: 932 | BI120: 959 | BJ120: 988 | BK120: 1019 | BL120: 1054 | BM120: 1090 | BN120: 1129 | BO120: 1173 | BP120: 1220 | BQ120: 1272 | BR120: 1328 | BS120: 1388 | BT120: 1455 | BU120: 1527 | BV120: 1610 | BW120: 1701 | BX120: 1801 | BY120: 1908 | BZ120: 2028 | CA120: 2169 | CB120: 2324 | CC120: 2499 | CD120: 2696 | CE120: 2920 | CF120: 3209 | CG120: 3547 | CH120: 3933 | CI120: 4392 | CJ120: 4919 | CK120: 5577 | CL120: 6376 | CM120: 7342 | CN120: 8535 | CO120: 0 | CP120: 0 | CQ120: 0 | CR120: 0 | CS120: 0 | CT120: 0 | CU120: 0 | CV120: 0 | CW120: 0 | CX120: 0 | CY120: 0 | CZ120: 0 | DA120: 0 | DB120: 0 | DC120: 0 | DD120: 0 | DE120: 0 | DF120: 0 | DG120: 0 | DH120: 0 | DI120: 0 | DJ120: 0 | DK120: 0 | DL120: 0 | DM120: 0 | DN120: 0 | DO120: 0 | DP120: 0 | DQ120: 0 | DR120: 0 | DS120: 0 | DT120: 0 | DU120: 0 | DV120: 0 | DW120: 0 | DX120: 0 | DZ120: 56 | EA120: SDJ20 | EB120: 1 | EC120: 9 | ED120: =EA120&TEXT(EB120,"00")&TEXT(EC120,"00") -> SDJ200109 | EE120: 0 | EF120: 65 | EG120: 128 | EH120: 185 | EI120: 256 | EJ120: 308 | EK120: 405 | EL120: 463 | EM120: 520 | EN120: 639 | EO120: 699 | EP120: 755 | EQ120: 813 | ER120: 867 | ES120: 917 | ET120: 969 | EU120: 1018 | EV120: 1065 | EW120: 1110 | EX120: 0 | EY120: 0 | EZ120: 0 | FA120: 0 | FB120: 0 | FC120: 0 | FD120: 0 | FE120: 0 | FF120: 0 | FG120: 0 | FH120: 0 | FI120: 0 | FJ120: 0 | FK120: 0 | FL120: 0 | FM120: 0 | FN120: 0 | FO120: 0 | FP120: 0 | FQ120: 0 | FR120: 0 | FS120: 0 | FT120: 0 | FU120: 0 | FV120: 0 | FW120: 0 | FX120: 0 | FY120: 0 | FZ120: 0 | GA120: 0 | GB120: 0 | GC120: 0 | GD120: 0 | GE120: 0 | GF120: 0 | GG120: 0 | GH120: 0 | GI120: 0 | GJ120: 0 | GK120: 0 | GL120: 0 | GM120: 0 | GN120: 0 | GO120: 0 | GP120: 0 | GQ120: 0 | GR120: 0 | GS120: 0 | GT120: 0 | GU120: 0 | GV120: 0 | GW120: 0 | GX120: 0 | GY120: 0 | GZ120: 0 | HA120: 0 | HB120: 0 | HC120: 0 | HD120: 0 | HE120: 0 | HF120: 0 | HG120: 0 | HH120: 0 | HI120: 0 | HJ120: 0 | HK120: 0 | HL120: 0 | HM120: 0 | HN120: 0 | HO120: 0 | HP120: 0 | HQ120: 0 | HR120: 0 | HS120: 0 | HT120: 0 | HU120: 0 | HV120: 0 | HW120: 0 | HX120: 0 | HY120: 0 | HZ120: 0 | IA120: 0 | IB120: 0 | IC120: 0 | ID120: 0 | IE120: 0 | IF120: 0 | IG120: 0 | IH120: 0 | II120: 0 | IJ120: 0 | IK120: 0
M121: 56 | N121: SDJ20 | O121: 1 | P121: 10 | Q121: =N121&TEXT(O121,"00")&TEXT(P121,"00") -> SDJ200110 | R121: 0 | S121: 20 | T121: 41 | U121: 63 | V121: 90 | W121: 113 | X121: 153 | Y121: 179 | Z121: 207 | AA121: 260 | AB121: 292 | AC121: 324 | AD121: 357 | AE121: 391 | AF121: 425 | AG121: 460 | AH121: 496 | AI121: 533 | AJ121: 571 | AK121: 609 | AL121: 620 | AM121: 630 | AN121: 641 | AO121: 652 | AP121: 663 | AQ121: 674 | AR121: 686 | AS121: 697 | AT121: 709 | AU121: 721 | AV121: 734 | AW121: 748 | AX121: 762 | AY121: 776 | AZ121: 791 | BA121: 807 | BB121: 825 | BC121: 843 | BD121: 862 | BE121: 883 | BF121: 907 | BG121: 932 | BH121: 959 | BI121: 988 | BJ121: 1019 | BK121: 1054 | BL121: 1090 | BM121: 1129 | BN121: 1173 | BO121: 1220 | BP121: 1272 | BQ121: 1328 | BR121: 1388 | BS121: 1455 | BT121: 1527 | BU121: 1610 | BV121: 1701 | BW121: 1801 | BX121: 1908 | BY121: 2028 | BZ121: 2169 | CA121: 2324 | CB121: 2499 | CC121: 2696 | CD121: 2920 | CE121: 3209 | CF121: 3547 | CG121: 3933 | CH121: 4392 | CI121: 4919 | CJ121: 5577 | CK121: 6376 | CL121: 7342 | CM121: 8535 | CN121: 0 | CO121: 0 | CP121: 0 | CQ121: 0 | CR121: 0 | CS121: 0 | CT121: 0 | CU121: 0 | CV121: 0 | CW121: 0 | CX121: 0 | CY121: 0 | CZ121: 0 | DA121: 0 | DB121: 0 | DC121: 0 | DD121: 0 | DE121: 0 | DF121: 0 | DG121: 0 | DH121: 0 | DI121: 0 | DJ121: 0 | DK121: 0 | DL121: 0 | DM121: 0 | DN121: 0 | DO121: 0 | DP121: 0 | DQ121: 0 | DR121: 0 | DS121: 0 | DT121: 0 | DU121: 0 | DV121: 0 | DW121: 0 | DX121: 0 | DZ121: 56 | EA121: SDJ20 | EB121: 1 | EC121: 10 | ED121: =EA121&TEXT(EB121,"00")&TEXT(EC121,"00") -> SDJ200110 | EE121: 0 | EF121: 64 | EG121: 125 | EH121: 184 | EI121: 254 | EJ121: 307 | EK121: 403 | EL121: 460 | EM121: 519 | EN121: 636 | EO121: 697 | EP121: 754 | EQ121: 810 | ER121: 865 | ES121: 917 | ET121: 967 | EU121: 1016 | EV121: 1064 | EW121: 1110 | EX121: 0 | EY121: 0 | EZ121: 0 | FA121: 0 | FB121: 0 | FC121: 0 | FD121: 0 | FE121: 0 | FF121: 0 | FG121: 0 | FH121: 0 | FI121: 0 | FJ121: 0 | FK121: 0 | FL121: 0 | FM121: 0 | FN121: 0 | FO121: 0 | FP121: 0 | FQ121: 0 | FR121: 0 | FS121: 0 | FT121: 0 | FU121: 0 | FV121: 0 | FW121: 0 | FX121: 0 | FY121: 0 | FZ121: 0 | GA121: 0 | GB121: 0 | GC121: 0 | GD121: 0 | GE121: 0 | GF121: 0 | GG121: 0 | GH121: 0 | GI121: 0 | GJ121: 0 | GK121: 0 | GL121: 0 | GM121: 0 | GN121: 0 | GO121: 0 | GP121: 0 | GQ121: 0 | GR121: 0 | GS121: 0 | GT121: 0 | GU121: 0 | GV121: 0 | GW121: 0 | GX121: 0 | GY121: 0 | GZ121: 0 | HA121: 0 | HB121: 0 | HC121: 0 | HD121: 0 | HE121: 0 | HF121: 0 | HG121: 0 | HH121: 0 | HI121: 0 | HJ121: 0 | HK121: 0 | HL121: 0 | HM121: 0 | HN121: 0 | HO121: 0 | HP121: 0 | HQ121: 0 | HR121: 0 | HS121: 0 | HT121: 0 | HU121: 0 | HV121: 0 | HW121: 0 | HX121: 0 | HY121: 0 | HZ121: 0 | IA121: 0 | IB121: 0 | IC121: 0 | ID121: 0 | IE121: 0 | IF121: 0 | IG121: 0 | IH121: 0 | II121: 0 | IJ121: 0 | IK121: 0
M122: 56 | N122: SDJ20 | O122: 1 | P122: 11 | Q122: =N122&TEXT(O122,"00")&TEXT(P122,"00") -> SDJ200111 | R122: 0 | S122: 21 | T122: 42 | U122: 64 | V122: 90 | W122: 114 | X122: 155 | Y122: 182 | Z122: 210 | AA122: 264 | AB122: 296 | AC122: 329 | AD122: 363 | AE122: 397 | AF122: 432 | AG122: 468 | AH122: 505 | AI122: 542 | AJ122: 581 | AK122: 620 | AL122: 630 | AM122: 641 | AN122: 652 | AO122: 663 | AP122: 674 | AQ122: 686 | AR122: 697 | AS122: 709 | AT122: 721 | AU122: 734 | AV122: 748 | AW122: 762 | AX122: 776 | AY122: 791 | AZ122: 807 | BA122: 825 | BB122: 843 | BC122: 862 | BD122: 883 | BE122: 907 | BF122: 932 | BG122: 959 | BH122: 988 | BI122: 1019 | BJ122: 1054 | BK122: 1090 | BL122: 1129 | BM122: 1173 | BN122: 1220 | BO122: 1272 | BP122: 1328 | BQ122: 1388 | BR122: 1455 | BS122: 1527 | BT122: 1610 | BU122: 1701 | BV122: 1801 | BW122: 1908 | BX122: 2028 | BY122: 2169 | BZ122: 2324 | CA122: 2499 | CB122: 2696 | CC122: 2920 | CD122: 3209 | CE122: 3547 | CF122: 3933 | CG122: 4392 | CH122: 4919 | CI122: 5577 | CJ122: 6376 | CK122: 7342 | CL122: 8535 | CM122: 0 | CN122: 0 | CO122: 0 | CP122: 0 | CQ122: 0 | CR122: 0 | CS122: 0 | CT122: 0 | CU122: 0 | CV122: 0 | CW122: 0 | CX122: 0 | CY122: 0 | CZ122: 0 | DA122: 0 | DB122: 0 | DC122: 0 | DD122: 0 | DE122: 0 | DF122: 0 | DG122: 0 | DH122: 0 | DI122: 0 | DJ122: 0 | DK122: 0 | DL122: 0 | DM122: 0 | DN122: 0 | DO122: 0 | DP122: 0 | DQ122: 0 | DR122: 0 | DS122: 0 | DT122: 0 | DU122: 0 | DV122: 0 | DW122: 0 | DX122: 0 | DZ122: 56 | EA122: SDJ20 | EB122: 1 | EC122: 11 | ED122: =EA122&TEXT(EB122,"00")&TEXT(EC122,"00") -> SDJ200111 | EE122: 0 | EF122: 66 | EG122: 126 | EH122: 183 | EI122: 249 | EJ122: 304 | EK122: 401 | EL122: 460 | EM122: 518 | EN122: 635 | EO122: 694 | EP122: 753 | EQ122: 810 | ER122: 863 | ES122: 915 | ET122: 966 | EU122: 1016 | EV122: 1062 | EW122: 1110 | EX122: 0 | EY122: 0 | EZ122: 0 | FA122: 0 | FB122: 0 | FC122: 0 | FD122: 0 | FE122: 0 | FF122: 0 | FG122: 0 | FH122: 0 | FI122: 0 | FJ122: 0 | FK122: 0 | FL122: 0 | FM122: 0 | FN122: 0 | FO122: 0 | FP122: 0 | FQ122: 0 | FR122: 0 | FS122: 0 | FT122: 0 | FU122: 0 | FV122: 0 | FW122: 0 | FX122: 0 | FY122: 0 | FZ122: 0 | GA122: 0 | GB122: 0 | GC122: 0 | GD122: 0 | GE122: 0 | GF122: 0 | GG122: 0 | GH122: 0 | GI122: 0 | GJ122: 0 | GK122: 0 | GL122: 0 | GM122: 0 | GN122: 0 | GO122: 0 | GP122: 0 | GQ122: 0 | GR122: 0 | GS122: 0 | GT122: 0 | GU122: 0 | GV122: 0 | GW122: 0 | GX122: 0 | GY122: 0 | GZ122: 0 | HA122: 0 | HB122: 0 | HC122: 0 | HD122: 0 | HE122: 0 | HF122: 0 | HG122: 0 | HH122: 0 | HI122: 0 | HJ122: 0 | HK122: 0 | HL122: 0 | HM122: 0 | HN122: 0 | HO122: 0 | HP122: 0 | HQ122: 0 | HR122: 0 | HS122: 0 | HT122: 0 | HU122: 0 | HV122: 0 | HW122: 0 | HX122: 0 | HY122: 0 | HZ122: 0 | IA122: 0 | IB122: 0 | IC122: 0 | ID122: 0 | IE122: 0 | IF122: 0 | IG122: 0 | IH122: 0 | II122: 0 | IJ122: 0 | IK122: 0
... M212: 56 | N212: SDJ20 | O212: 2 | P212: 50 | Q212: =N212&TEXT(O212,"00")&TEXT(P212,"00") -> SDJ200250 | R212: 0 | S212: 87 | T212: 176 | U212: 269 | V212: 390 | W212: 497 | X212: 685 | Y212: 817 | Z212: 956 | AA212: 1224 | AB212: 1397 | AC212: 1582 | AD212: 1779 | AE212: 1989 | AF212: 2213 | AG212: 2456 | AH212: 2716 | AI212: 2991 | AJ212: 3287 | AK212: 3604 | AL212: 3836 | AM212: 4090 | AN212: 4365 | AO212: 4673 | AP212: 5017 | AQ212: 5437 | AR212: 5908 | AS212: 6444 | AT212: 7073 | AU212: 7792 | AV212: 8656 | AW212: 9664 | AX212: 10887 | AY212: 12350 | AZ212: 0 | BA212: 0 | BB212: 0 | BC212: 0 | BD212: 0 | BE212: 0 | BF212: 0 | BG212: 0 | BH212: 0 | BI212: 0 | BJ212: 0 | BK212: 0 | BL212: 0 | BM212: 0 | BN212: 0 | BO212: 0 | BP212: 0 | BQ212: 0 | BR212: 0 | BS212: 0 | BT212: 0 | BU212: 0 | BV212: 0 | BW212: 0 | BX212: 0 | BY212: 0 | BZ212: 0 | CA212: 0 | CB212: 0 | CC212: 0 | CD212: 0 | CE212: 0 | CF212: 0 | CG212: 0 | CH212: 0 | CI212: 0 | CJ212: 0 | CK212: 0 | CL212: 0 | CM212: 0 | CN212: 0 | CO212: 0 | CP212: 0 | CQ212: 0 | CR212: 0 | CS212: 0 | CT212: 0 | CU212: 0 | CV212: 0 | CW212: 0 | CX212: 0 | CY212: 0 | CZ212: 0 | DA212: 0 | DB212: 0 | DC212: 0 | DD212: 0 | DE212: 0 | DF212: 0 | DG212: 0 | DH212: 0 | DI212: 0 | DJ212: 0 | DK212: 0 | DL212: 0 | DM212: 0 | DN212: 0 | DO212: 0 | DP212: 0 | DQ212: 0 | DR212: 0 | DS212: 0 | DT212: 0 | DU212: 0 | DV212: 0 | DW212: 0 | DX212: 0 | DZ212: 56 | EA212: SDJ20 | EB212: 2 | EC212: 50 | ED212: =EA212&TEXT(EB212,"00")&TEXT(EC212,"00") -> SDJ200250 | EE212: 0 | EF212: 120 | EG212: 233 | EH212: 343 | EI212: 481 | EJ212: 622 | EK212: 794 | EL212: 924 | EM212: 1060 | EN212: 1314 | EO212: 1460 | EP212: 1609 | EQ212: 1759 | ER212: 1910 | ES212: 2066 | ET212: 2234 | EU212: 2412 | EV212: 2598 | EW212: 2799 | EX212: 0 | EY212: 0 | EZ212: 0 | FA212: 0 | FB212: 0 | FC212: 0 | FD212: 0 | FE212: 0 | FF212: 0 | FG212: 0 | FH212: 0 | FI212: 0 | FJ212: 0 | FK212: 0 | FL212: 0 | FM212: 0 | FN212: 0 | FO212: 0 | FP212: 0 | FQ212: 0 | FR212: 0 | FS212: 0 | FT212: 0 | FU212: 0 | FV212: 0 | FW212: 0 | FX212: 0 | FY212: 0 | FZ212: 0 | GA212: 0 | GB212: 0 | GC212: 0 | GD212: 0 | GE212: 0 | GF212: 0 | GG212: 0 | GH212: 0 | GI212: 0 | GJ212: 0 | GK212: 0 | GL212: 0 | GM212: 0 | GN212: 0 | GO212: 0 | GP212: 0 | GQ212: 0 | GR212: 0 | GS212: 0 | GT212: 0 | GU212: 0 | GV212: 0 | GW212: 0 | GX212: 0 | GY212: 0 | GZ212: 0 | HA212: 0 | HB212: 0 | HC212: 0 | HD212: 0 | HE212: 0 | HF212: 0 | HG212: 0 | HH212: 0 | HI212: 0 | HJ212: 0 | HK212: 0 | HL212: 0 | HM212: 0 | HN212: 0 | HO212: 0 | HP212: 0 | HQ212: 0 | HR212: 0 | HS212: 0 | HT212: 0 | HU212: 0 | HV212: 0 | HW212: 0 | HX212: 0 | HY212: 0 | HZ212: 0 | IA212: 0 | IB212: 0 | IC212: 0 | ID212: 0 | IE212: 0 | IF212: 0 | IG212: 0 | IH212: 0 | II212: 0 | IJ212: 0 | IK212: 0
M216: HEALTH1(重大傷病給付-慢性精神病) | Q216: =N216&TEXT(O216,"00")&TEXT(P216,"00") -> 0000 | DZ216: tbHEALTH2(重大傷病給付-非慢性病) | ED216: =EA216&TEXT(EB216,"00")&TEXT(EC216,"00") -> 0000
M217: 版次 | N217: 商品代號 | O217: 性別 | P217: 年齡 | Q217: =N217&TEXT(O217,"00")&TEXT(P217,"00") -> 商品代號性別年齡 | R217: 第1年重疾保險金 | S217: 第2年重疾保險金 | T217: 第3年重疾保險金 | U217: 第4年重疾保險金 | V217: 第5年重疾保險金 | W217: 第6年重疾保險金 | X217: 第7年重疾保險金 | Y217: 第8年重疾保險金 | Z217: 第9年重疾保險金 | AA217: 第10年重疾保險金 | AB217: 第11年重疾保險金 | AC217: 第12年重疾保險金 | AD217: 第13年重疾保險金 | AE217: 第14年重疾保險金 | AF217: 第15年重疾保險金 | AG217: 第16年重疾保險金 | AH217: 第17年重疾保險金 | AI217: 第18年重疾保險金 | AJ217: 第19年重疾保險金 | AK217: 第20年重疾保險金 | AL217: 第21年重疾保險金 | AM217: 第22年重疾保險金 | AN217: 第23年重疾保險金 | AO217: 第24年重疾保險金 | AP217: 第25年重疾保險金 | AQ217: 第26年重疾保險金 | AR217: 第27年重疾保險金 | AS217: 第28年重疾保險金 | AT217: 第29年重疾保險金 | AU217: 第30年重疾保險金 | AV217: 第31年重疾保險金 | AW217: 第32年重疾保險金 | AX217: 第33年重疾保險金 | AY217: 第34年重疾保險金 | AZ217: 第35年重疾保險金 | BA217: 第36年重疾保險金 | BB217: 第37年重疾保險金 | BC217: 第38年重疾保險金 | BD217: 第39年重疾保險金 | BE217: 第40年重疾保險金 | BF217: 第41年重疾保險金 | BG217: 第42年重疾保險金 | BH217: 第43年重疾保險金 | BI217: 第44年重疾保險金 | BJ217: 第45年重疾保險金 | BK217: 第46年重疾保險金 | BL217: 第47年重疾保險金 | BM217: 第48年重疾保險金 | BN217: 第49年重疾保險金 | BO217: 第50年重疾保險金 | BP217: 第51年重疾保險金 | BQ217: 第52年重疾保險金 | BR217: 第53年重疾保險金 | BS217: 第54年重疾保險金 | BT217: 第55年重疾保險金 | BU217: 第56年重疾保險金 | BV217: 第57年重疾保險金 | BW217: 第58年重疾保險金 | BX217: 第59年重疾保險金 | BY217: 第60年重疾保險金 | BZ217: 第61年重疾保險金 | CA217: 第62年重疾保險金 | CB217: 第63年重疾保險金 | CC217: 第64年重疾保險金 | CD217: 第65年重疾保險金 | CE217: 第66年重疾保險金 | CF217: 第67年重疾保險金 | CG217: 第68年重疾保險金 | CH217: 第69年重疾保險金 | CI217: 第70年重疾保險金 | CJ217: 第71年重疾保險金 | CK217: 第72年重疾保險金 | CL217: 第73年重疾保險金 | CM217: 第74年重疾保險金額 | CN217: 第75年重疾保險金 | CO217: 第76年重疾保險金 | CP217: 第77年重疾保險金 | CQ217: 第78年重疾保險金 | CR217: 第79年重疾保險金 | CS217: 第80年重疾保險金 | CT217: 第81年重疾保險金 | CU217: 第82年重疾保險金 | CV217: 第83年重疾保險金 | CW217: 第84年重疾保險金 | CX217: 第85年重疾保險金 | CY217: 第86年重疾保險金 | CZ217: 第87年重疾保險金 | DA217: 第88年重疾保險金 | DB217: 第89年重疾保險金 | DC217: 第90年重疾保險金 | DD217: 第91年重疾保險金 | DE217: 第92年重疾保險金 | DF217: 第93年重疾保險金 | DG217: 第94年重疾保險金 | DH217: 第95年重疾保險金 | DI217: 第96年重疾保險金 | DJ217: 第97年重疾保險金 | DK217: 第98年重疾保險金 | DL217: 第99年重疾保險金 | DM217: 第100年重疾保險金 | DN217: 第101年重疾保險金 | DO217: 第102年重疾保險金 | DP217: 第103年重疾保險金 | DQ217: 第104年重疾保險金 | DR217: 第105年重疾保險金 | DS217: 第106年重疾保險金 | DT217: 第107年重疾保險金 | DU217: 第108年重疾保險金 | DV217: 第109年重疾保險金 | DW217: 第110年重疾保險金 | DX217: 第111年重疾保險金 | DZ217: 版次 | EA217: 商品代號 | EB217: 性別 | EC217: 年齡 | ED217: =EA217&TEXT(EB217,"00")&TEXT(EC217,"00") -> 商品代號性別年齡 | EE217: 第1年重疾保險金 | EF217: 第2年重疾保險金 | EG217: 第3年重疾保險金 | EH217: 第4年重疾保險金 | EI217: 第5年重疾保險金 | EJ217: 第6年重疾保險金 | EK217: 第7年重疾保險金 | EL217: 第8年重疾保險金 | EM217: 第9年重疾保險金 | EN217: 第10年重疾保險金 | EO217: 第11年重疾保險金 | EP217: 第12年重疾保險金 | EQ217: 第13年重疾保險金 | ER217: 第14年重疾保險金 | ES217: 第15年重疾保險金 | ET217: 第16年重疾保險金 | EU217: 第17年重疾保險金 | EV217: 第18年重疾保險金 | EW217: 第19年重疾保險金 | EX217: 第20年重疾保險金 | EY217: 第21年重疾保險金 | EZ217: 第22年重疾保險金 | FA217: 第23年重疾保險金 | FB217: 第24年重疾保險金 | FC217: 第25年重疾保險金 | FD217: 第26年重疾保險金 | FE217: 第27年重疾保險金 | FF217: 第28年重疾保險金 | FG217: 第29年重疾保險金 | FH217: 第30年重疾保險金 | FI217: 第31年重疾保險金 | FJ217: 第32年重疾保險金 | FK217: 第33年重疾保險金 | FL217: 第34年重疾保險金 | FM217: 第35年重疾保險金 | FN217: 第36年重疾保險金 | FO217: 第37年重疾保險金 | FP217: 第38年重疾保險金 | FQ217: 第39年重疾保險金 | FR217: 第40年重疾保險金 | FS217: 第41年重疾保險金 | FT217: 第42年重疾保險金 | FU217: 第43年重疾保險金 | FV217: 第44年重疾保險金 | FW217: 第45年重疾保險金 | FX217: 第46年重疾保險金 | FY217: 第47年重疾保險金 | FZ217: 第48年重疾保險金 | GA217: 第49年重疾保險金 | GB217: 第50年重疾保險金 | GC217: 第51年重疾保險金 | GD217: 第52年重疾保險金 | GE217: 第53年重疾保險金 | GF217: 第54年重疾保險金 | GG217: 第55年重疾保險金 | GH217: 第56年重疾保險金 | GI217: 第57年重疾保險金 | GJ217: 第58年重疾保險金 | GK217: 第59年重疾保險金 | GL217: 第60年重疾保險金 | GM217: 第61年重疾保險金 | GN217: 第62年重疾保險金 | GO217: 第63年重疾保險金 | GP217: 第64年重疾保險金 | GQ217: 第65年重疾保險金 | GR217: 第66年重疾保險金 | GS217: 第67年重疾保險金 | GT217: 第68年重疾保險金 | GU217: 第69年重疾保險金 | GV217: 第70年重疾保險金 | GW217: 第71年重疾保險金 | GX217: 第72年重疾保險金 | GY217: 第73年重疾保險金 | GZ217: 第74年重疾保險金額 | HA217: 第75年重疾保險金 | HB217: 第76年重疾保險金 | HC217: 第77年重疾保險金 | HD217: 第78年重疾保險金 | HE217: 第79年重疾保險金 | HF217: 第80年重疾保險金 | HG217: 第81年重疾保險金 | HH217: 第82年重疾保險金 | HI217: 第83年重疾保險金 | HJ217: 第84年重疾保險金 | HK217: 第85年重疾保險金 | HL217: 第86年重疾保險金 | HM217: 第87年重疾保險金 | HN217: 第88年重疾保險金 | HO217: 第89年重疾保險金 | HP217: 第90年重疾保險金 | HQ217: 第91年重疾保險金 | HR217: 第92年重疾保險金 | HS217: 第93年重疾保險金 | HT217: 第94年重疾保險金 | HU217: 第95年重疾保險金 | HV217: 第96年重疾保險金 | HW217: 第97年重疾保險金 | HX217: 第98年重疾保險金 | HY217: 第99年重疾保險金 | HZ217: 第100年重疾保險金 | IA217: 第101年重疾保險金 | IB217: 第102年重疾保險金 | IC217: 第103年重疾保險金 | ID217: 第104年重疾保險金 | IE217: 第105年重疾保險金 | IF217: 第106年重疾保險金 | IG217: 第107年重疾保險金 | IH217: 第108年重疾保險金 | II217: 第109年重疾保險金 | IJ217: 第110年重疾保險金 | IK217: 第111年重疾保險金
M218: 56 | N218: SDJ20 | O218: 1 | P218: 0 | Q218: =N218&TEXT(O218,"00")&TEXT(P218,"00") -> SDJ200100 | R218: 253.3 | S218: 2000 | T218: 2000 | U218: 2000 | V218: 2000 | W218: 2000 | X218: 2000 | Y218: 2026.7 | Z218: 2280.1 | AA218: 2533.4 | AB218: 2786.7 | AC218: 3040.1 | AD218: 3293.4 | AE218: 3546.8 | AF218: 3800.1 | AG218: 4053.4 | AH218: 4306.8 | AI218: 4560.1 | AJ218: 4813.5 | AK218: 5066.8 | AL218: 5066.8 | AM218: 5066.8 | AN218: 5066.8 | AO218: 5066.8 | AP218: 5066.8 | AQ218: 5066.8 | AR218: 5066.8 | AS218: 5066.8 | AT218: 5066.8 | AU218: 5066.8 | AV218: 5066.8 | AW218: 5066.8 | AX218: 5066.8 | AY218: 5066.8 | AZ218: 5066.8 | BA218: 5066.8 | BB218: 5066.8 | BC218: 5066.8 | BD218: 5066.8 | BE218: 5066.8 | BF218: 5066.8 | BG218: 5066.8 | BH218: 5066.8 | BI218: 5066.8 | BJ218: 5066.8 | BK218: 5066.8 | BL218: 5066.8 | BM218: 5066.8 | BN218: 5066.8 | BO218: 5066.8 | BP218: 5066.8 | BQ218: 5066.8 | BR218: 5066.8 | BS218: 5066.8 | BT218: 5066.8 | BU218: 5066.8 | BV218: 5066.8 | BW218: 5066.8 | BX218: 5066.8 | BY218: 5066.8 | BZ218: 5066.8 | CA218: 5066.8 | CB218: 5066.8 | CC218: 5066.8 | CD218: 5066.8 | CE218: 5066.8 | CF218: 5066.8 | CG218: 5066.8 | CH218: 5066.8 | CI218: 5066.8 | CJ218: 5066.8 | CK218: 5066.8 | CL218: 5066.8 | CM218: 5066.8 | CN218: 5066.8 | CO218: 5066.8 | CP218: 5066.8 | CQ218: 5066.8 | CR218: 5066.8 | CS218: 5066.8 | CT218: 5066.8 | CU218: 5066.8 | CV218: 5066.8 | CW218: 5066.8 | CX218: 5066.8 | CY218: 0 | CZ218: 0 | DA218: 0 | DB218: 0 | DC218: 0 | DD218: 0 | DE218: 0 | DF218: 0 | DG218: 0 | DH218: 0 | DI218: 0 | DJ218: 0 | DK218: 0 | DL218: 0 | DM218: 0 | DN218: 0 | DO218: 0 | DP218: 0 | DQ218: 0 | DR218: 0 | DS218: 0 | DT218: 0 | DU218: 0 | DV218: 0 | DW218: 0 | DX218: 0 | DZ218: 56 | EA218: SDJ20 | EB218: 1 | EC218: 0 | ED218: =EA218&TEXT(EB218,"00")&TEXT(EC218,"00") -> SDJ200100 | EE218: 253.3 | EF218: 10000 | EG218: 10000 | EH218: 10000 | EI218: 10000 | EJ218: 10000 | EK218: 10000 | EL218: 10000 | EM218: 10000 | EN218: 10000 | EO218: 10000 | EP218: 10000 | EQ218: 10000 | ER218: 10000 | ES218: 10000 | ET218: 10000 | EU218: 10000 | EV218: 10000 | EW218: 10000 | EX218: 10000 | EY218: 10000 | EZ218: 10000 | FA218: 10000 | FB218: 10000 | FC218: 10000 | FD218: 10000 | FE218: 10000 | FF218: 10000 | FG218: 10000 | FH218: 10000 | FI218: 10000 | FJ218: 10000 | FK218: 10000 | FL218: 10000 | FM218: 10000 | FN218: 10000 | FO218: 10000 | FP218: 10000 | FQ218: 10000 | FR218: 10000 | FS218: 10000 | FT218: 10000 | FU218: 10000 | FV218: 10000 | FW218: 10000 | FX218: 10000 | FY218: 10000 | FZ218: 10000 | GA218: 10000 | GB218: 10000 | GC218: 10000 | GD218: 10000 | GE218: 10000 | GF218: 10000 | GG218: 10000 | GH218: 10000 | GI218: 10000 | GJ218: 10000 | GK218: 10000 | GL218: 10000 | GM218: 10000 | GN218: 10000 | GO218: 10000 | GP218: 10000 | GQ218: 10000 | GR218: 10000 | GS218: 10000 | GT218: 10000 | GU218: 10000 | GV218: 10000 | GW218: 10000 | GX218: 10000 | GY218: 10000 | GZ218: 10000 | HA218: 10000 | HB218: 10000 | HC218: 10000 | HD218: 10000 | HE218: 10000 | HF218: 10000 | HG218: 10000 | HH218: 10000 | HI218: 10000 | HJ218: 10000 | HK218: 10000 | HL218: 0 | HM218: 0 | HN218: 0 | HO218: 0 | HP218: 0 | HQ218: 0 | HR218: 0 | HS218: 0 | HT218: 0 | HU218: 0 | HV218: 0 | HW218: 0 | HX218: 0 | HY218: 0 | HZ218: 0 | IA218: 0 | IB218: 0 | IC218: 0 | ID218: 0 | IE218: 0 | IF218: 0 | IG218: 0 | IH218: 0 | II218: 0 | IJ218: 0 | IK218: 0
M219: 56 | N219: SDJ20 | O219: 1 | P219: 1 | Q219: =N219&TEXT(O219,"00")&TEXT(P219,"00") -> SDJ200101 | R219: 257.6 | S219: 2000 | T219: 2000 | U219: 2000 | V219: 2000 | W219: 2000 | X219: 2000 | Y219: 2060.6 | Z219: 2318.2 | AA219: 2575.8 | AB219: 2833.4 | AC219: 3091 | AD219: 3348.5 | AE219: 3606.1 | AF219: 3863.7 | AG219: 4121.3 | AH219: 4378.9 | AI219: 4636.4 | AJ219: 4894 | AK219: 5151.6 | AL219: 5151.6 | AM219: 5151.6 | AN219: 5151.6 | AO219: 5151.6 | AP219: 5151.6 | AQ219: 5151.6 | AR219: 5151.6 | AS219: 5151.6 | AT219: 5151.6 | AU219: 5151.6 | AV219: 5151.6 | AW219: 5151.6 | AX219: 5151.6 | AY219: 5151.6 | AZ219: 5151.6 | BA219: 5151.6 | BB219: 5151.6 | BC219: 5151.6 | BD219: 5151.6 | BE219: 5151.6 | BF219: 5151.6 | BG219: 5151.6 | BH219: 5151.6 | BI219: 5151.6 | BJ219: 5151.6 | BK219: 5151.6 | BL219: 5151.6 | BM219: 5151.6 | BN219: 5151.6 | BO219: 5151.6 | BP219: 5151.6 | BQ219: 5151.6 | BR219: 5151.6 | BS219: 5151.6 | BT219: 5151.6 | BU219: 5151.6 | BV219: 5151.6 | BW219: 5151.6 | BX219: 5151.6 | BY219: 5151.6 | BZ219: 5151.6 | CA219: 5151.6 | CB219: 5151.6 | CC219: 5151.6 | CD219: 5151.6 | CE219: 5151.6 | CF219: 5151.6 | CG219: 5151.6 | CH219: 5151.6 | CI219: 5151.6 | CJ219: 5151.6 | CK219: 5151.6 | CL219: 5151.6 | CM219: 5151.6 | CN219: 5151.6 | CO219: 5151.6 | CP219: 5151.6 | CQ219: 5151.6 | CR219: 5151.6 | CS219: 5151.6 | CT219: 5151.6 | CU219: 5151.6 | CV219: 5151.6 | CW219: 5151.6 | CX219: 0 | CY219: 0 | CZ219: 0 | DA219: 0 | DB219: 0 | DC219: 0 | DD219: 0 | DE219: 0 | DF219: 0 | DG219: 0 | DH219: 0 | DI219: 0 | DJ219: 0 | DK219: 0 | DL219: 0 | DM219: 0 | DN219: 0 | DO219: 0 | DP219: 0 | DQ219: 0 | DR219: 0 | DS219: 0 | DT219: 0 | DU219: 0 | DV219: 0 | DW219: 0 | DX219: 0 | DZ219: 56 | EA219: SDJ20 | EB219: 1 | EC219: 1 | ED219: =EA219&TEXT(EB219,"00")&TEXT(EC219,"00") -> SDJ200101 | EE219: 257.6 | EF219: 10000 | EG219: 10000 | EH219: 10000 | EI219: 10000 | EJ219: 10000 | EK219: 10000 | EL219: 10000 | EM219: 10000 | EN219: 10000 | EO219: 10000 | EP219: 10000 | EQ219: 10000 | ER219: 10000 | ES219: 10000 | ET219: 10000 | EU219: 10000 | EV219: 10000 | EW219: 10000 | EX219: 10000 | EY219: 10000 | EZ219: 10000 | FA219: 10000 | FB219: 10000 | FC219: 10000 | FD219: 10000 | FE219: 10000 | FF219: 10000 | FG219: 10000 | FH219: 10000 | FI219: 10000 | FJ219: 10000 | FK219: 10000 | FL219: 10000 | FM219: 10000 | FN219: 10000 | FO219: 10000 | FP219: 10000 | FQ219: 10000 | FR219: 10000 | FS219: 10000 | FT219: 10000 | FU219: 10000 | FV219: 10000 | FW219: 10000 | FX219: 10000 | FY219: 10000 | FZ219: 10000 | GA219: 10000 | GB219: 10000 | GC219: 10000 | GD219: 10000 | GE219: 10000 | GF219: 10000 | GG219: 10000 | GH219: 10000 | GI219: 10000 | GJ219: 10000 | GK219: 10000 | GL219: 10000 | GM219: 10000 | GN219: 10000 | GO219: 10000 | GP219: 10000 | GQ219: 10000 | GR219: 10000 | GS219: 10000 | GT219: 10000 | GU219: 10000 | GV219: 10000 | GW219: 10000 | GX219: 10000 | GY219: 10000 | GZ219: 10000 | HA219: 10000 | HB219: 10000 | HC219: 10000 | HD219: 10000 | HE219: 10000 | HF219: 10000 | HG219: 10000 | HH219: 10000 | HI219: 10000 | HJ219: 10000 | HK219: 0 | HL219: 0 | HM219: 0 | HN219: 0 | HO219: 0 | HP219: 0 | HQ219: 0 | HR219: 0 | HS219: 0 | HT219: 0 | HU219: 0 | HV219: 0 | HW219: 0 | HX219: 0 | HY219: 0 | HZ219: 0 | IA219: 0 | IB219: 0 | IC219: 0 | ID219: 0 | IE219: 0 | IF219: 0 | IG219: 0 | IH219: 0 | II219: 0 | IJ219: 0 | IK219: 0
M220: 56 | N220: SDJ20 | O220: 1 | P220: 2 | Q220: =N220&TEXT(O220,"00")&TEXT(P220,"00") -> SDJ200102 | R220: 261.8 | S220: 2000 | T220: 2000 | U220: 2000 | V220: 2000 | W220: 2000 | X220: 2000 | Y220: 2094.6 | Z220: 2356.4 | AA220: 2618.2 | AB220: 2880 | AC220: 3141.8 | AD220: 3403.7 | AE220: 3665.5 | AF220: 3927.3 | AG220: 4189.1 | AH220: 4450.9 | AI220: 4712.8 | AJ220: 4974.6 | AK220: 5236.4 | AL220: 5236.4 | AM220: 5236.4 | AN220: 5236.4 | AO220: 5236.4 | AP220: 5236.4 | AQ220: 5236.4 | AR220: 5236.4 | AS220: 5236.4 | AT220: 5236.4 | AU220: 5236.4 | AV220: 5236.4 | AW220: 5236.4 | AX220: 5236.4 | AY220: 5236.4 | AZ220: 5236.4 | BA220: 5236.4 | BB220: 5236.4 | BC220: 5236.4 | BD220: 5236.4 | BE220: 5236.4 | BF220: 5236.4 | BG220: 5236.4 | BH220: 5236.4 | BI220: 5236.4 | BJ220: 5236.4 | BK220: 5236.4 | BL220: 5236.4 | BM220: 5236.4 | BN220: 5236.4 | BO220: 5236.4 | BP220: 5236.4 | BQ220: 5236.4 | BR220: 5236.4 | BS220: 5236.4 | BT220: 5236.4 | BU220: 5236.4 | BV220: 5236.4 | BW220: 5236.4 | BX220: 5236.4 | BY220: 5236.4 | BZ220: 5236.4 | CA220: 5236.4 | CB220: 5236.4 | CC220: 5236.4 | CD220: 5236.4 | CE220: 5236.4 | CF220: 5236.4 | CG220: 5236.4 | CH220: 5236.4 | CI220: 5236.4 | CJ220: 5236.4 | CK220: 5236.4 | CL220: 5236.4 | CM220: 5236.4 | CN220: 5236.4 | CO220: 5236.4 | CP220: 5236.4 | CQ220: 5236.4 | CR220: 5236.4 | CS220: 5236.4 | CT220: 5236.4 | CU220: 5236.4 | CV220: 5236.4 | CW220: 0 | CX220: 0 | CY220: 0 | CZ220: 0 | DA220: 0 | DB220: 0 | DC220: 0 | DD220: 0 | DE220: 0 | DF220: 0 | DG220: 0 | DH220: 0 | DI220: 0 | DJ220: 0 | DK220: 0 | DL220: 0 | DM220: 0 | DN220: 0 | DO220: 0 | DP220: 0 | DQ220: 0 | DR220: 0 | DS220: 0 | DT220: 0 | DU220: 0 | DV220: 0 | DW220: 0 | DX220: 0 | DZ220: 56 | EA220: SDJ20 | EB220: 1 | EC220: 2 | ED220: =EA220&TEXT(EB220,"00")&TEXT(EC220,"00") -> SDJ200102 | EE220: 261.8 | EF220: 10000 | EG220: 10000 | EH220: 10000 | EI220: 10000 | EJ220: 10000 | EK220: 10000 | EL220: 10000 | EM220: 10000 | EN220: 10000 | EO220: 10000 | EP220: 10000 | EQ220: 10000 | ER220: 10000 | ES220: 10000 | ET220: 10000 | EU220: 10000 | EV220: 10000 | EW220: 10000 | EX220: 10000 | EY220: 10000 | EZ220: 10000 | FA220: 10000 | FB220: 10000 | FC220: 10000 | FD220: 10000 | FE220: 10000 | FF220: 10000 | FG220: 10000 | FH220: 10000 | FI220: 10000 | FJ220: 10000 | FK220: 10000 | FL220: 10000 | FM220: 10000 | FN220: 10000 | FO220: 10000 | FP220: 10000 | FQ220: 10000 | FR220: 10000 | FS220: 10000 | FT220: 10000 | FU220: 10000 | FV220: 10000 | FW220: 10000 | FX220: 10000 | FY220: 10000 | FZ220: 10000 | GA220: 10000 | GB220: 10000 | GC220: 10000 | GD220: 10000 | GE220: 10000 | GF220: 10000 | GG220: 10000 | GH220: 10000 | GI220: 10000 | GJ220: 10000 | GK220: 10000 | GL220: 10000 | GM220: 10000 | GN220: 10000 | GO220: 10000 | GP220: 10000 | GQ220: 10000 | GR220: 10000 | GS220: 10000 | GT220: 10000 | GU220: 10000 | GV220: 10000 | GW220: 10000 | GX220: 10000 | GY220: 10000 | GZ220: 10000 | HA220: 10000 | HB220: 10000 | HC220: 10000 | HD220: 10000 | HE220: 10000 | HF220: 10000 | HG220: 10000 | HH220: 10000 | HI220: 10000 | HJ220: 0 | HK220: 0 | HL220: 0 | HM220: 0 | HN220: 0 | HO220: 0 | HP220: 0 | HQ220: 0 | HR220: 0 | HS220: 0 | HT220: 0 | HU220: 0 | HV220: 0 | HW220: 0 | HX220: 0 | HY220: 0 | HZ220: 0 | IA220: 0 | IB220: 0 | IC220: 0 | ID220: 0 | IE220: 0 | IF220: 0 | IG220: 0 | IH220: 0 | II220: 0 | IJ220: 0 | IK220: 0
M221: 56 | N221: SDJ20 | O221: 1 | P221: 3 | Q221: =N221&TEXT(O221,"00")&TEXT(P221,"00") -> SDJ200103 | R221: 266.1 | S221: 2000 | T221: 2000 | U221: 2000 | V221: 2000 | W221: 2000 | X221: 2000 | Y221: 2128.5 | Z221: 2394.5 | AA221: 2660.6 | AB221: 2926.7 | AC221: 3192.7 | AD221: 3458.8 | AE221: 3724.8 | AF221: 3990.9 | AG221: 4257 | AH221: 4523 | AI221: 4789.1 | AJ221: 5055.1 | AK221: 5321.2 | AL221: 5321.2 | AM221: 5321.2 | AN221: 5321.2 | AO221: 5321.2 | AP221: 5321.2 | AQ221: 5321.2 | AR221: 5321.2 | AS221: 5321.2 | AT221: 5321.2 | AU221: 5321.2 | AV221: 5321.2 | AW221: 5321.2 | AX221: 5321.2 | AY221: 5321.2 | AZ221: 5321.2 | BA221: 5321.2 | BB221: 5321.2 | BC221: 5321.2 | BD221: 5321.2 | BE221: 5321.2 | BF221: 5321.2 | BG221: 5321.2 | BH221: 5321.2 | BI221: 5321.2 | BJ221: 5321.2 | BK221: 5321.2 | BL221: 5321.2 | BM221: 5321.2 | BN221: 5321.2 | BO221: 5321.2 | BP221: 5321.2 | BQ221: 5321.2 | BR221: 5321.2 | BS221: 5321.2 | BT221: 5321.2 | BU221: 5321.2 | BV221: 5321.2 | BW221: 5321.2 | BX221: 5321.2 | BY221: 5321.2 | BZ221: 5321.2 | CA221: 5321.2 | CB221: 5321.2 | CC221: 5321.2 | CD221: 5321.2 | CE221: 5321.2 | CF221: 5321.2 | CG221: 5321.2 | CH221: 5321.2 | CI221: 5321.2 | CJ221: 5321.2 | CK221: 5321.2 | CL221: 5321.2 | CM221: 5321.2 | CN221: 5321.2 | CO221: 5321.2 | CP221: 5321.2 | CQ221: 5321.2 | CR221: 5321.2 | CS221: 5321.2 | CT221: 5321.2 | CU221: 5321.2 | CV221: 0 | CW221: 0 | CX221: 0 | CY221: 0 | CZ221: 0 | DA221: 0 | DB221: 0 | DC221: 0 | DD221: 0 | DE221: 0 | DF221: 0 | DG221: 0 | DH221: 0 | DI221: 0 | DJ221: 0 | DK221: 0 | DL221: 0 | DM221: 0 | DN221: 0 | DO221: 0 | DP221: 0 | DQ221: 0 | DR221: 0 | DS221: 0 | DT221: 0 | DU221: 0 | DV221: 0 | DW221: 0 | DX221: 0 | DZ221: 56 | EA221: SDJ20 | EB221: 1 | EC221: 3 | ED221: =EA221&TEXT(EB221,"00")&TEXT(EC221,"00") -> SDJ200103 | EE221: 266.1 | EF221: 10000 | EG221: 10000 | EH221: 10000 | EI221: 10000 | EJ221: 10000 | EK221: 10000 | EL221: 10000 | EM221: 10000 | EN221: 10000 | EO221: 10000 | EP221: 10000 | EQ221: 10000 | ER221: 10000 | ES221: 10000 | ET221: 10000 | EU221: 10000 | EV221: 10000 | EW221: 10000 | EX221: 10000 | EY221: 10000 | EZ221: 10000 | FA221: 10000 | FB221: 10000 | FC221: 10000 | FD221: 10000 | FE221: 10000 | FF221: 10000 | FG221: 10000 | FH221: 10000 | FI221: 10000 | FJ221: 10000 | FK221: 10000 | FL221: 10000 | FM221: 10000 | FN221: 10000 | FO221: 10000 | FP221: 10000 | FQ221: 10000 | FR221: 10000 | FS221: 10000 | FT221: 10000 | FU221: 10000 | FV221: 10000 | FW221: 10000 | FX221: 10000 | FY221: 10000 | FZ221: 10000 | GA221: 10000 | GB221: 10000 | GC221: 10000 | GD221: 10000 | GE221: 10000 | GF221: 10000 | GG221: 10000 | GH221: 10000 | GI221: 10000 | GJ221: 10000 | GK221: 10000 | GL221: 10000 | GM221: 10000 | GN221: 10000 | GO221: 10000 | GP221: 10000 | GQ221: 10000 | GR221: 10000 | GS221: 10000 | GT221: 10000 | GU221: 10000 | GV221: 10000 | GW221: 10000 | GX221: 10000 | GY221: 10000 | GZ221: 10000 | HA221: 10000 | HB221: 10000 | HC221: 10000 | HD221: 10000 | HE221: 10000 | HF221: 10000 | HG221: 10000 | HH221: 10000 | HI221: 0 | HJ221: 0 | HK221: 0 | HL221: 0 | HM221: 0 | HN221: 0 | HO221: 0 | HP221: 0 | HQ221: 0 | HR221: 0 | HS221: 0 | HT221: 0 | HU221: 0 | HV221: 0 | HW221: 0 | HX221: 0 | HY221: 0 | HZ221: 0 | IA221: 0 | IB221: 0 | IC221: 0 | ID221: 0 | IE221: 0 | IF221: 0 | IG221: 0 | IH221: 0 | II221: 0 | IJ221: 0 | IK221: 0
M222: 56 | N222: SDJ20 | O222: 1 | P222: 4 | Q222: =N222&TEXT(O222,"00")&TEXT(P222,"00") -> SDJ200104 | R222: 270.3 | S222: 2000 | T222: 2000 | U222: 2000 | V222: 2000 | W222: 2000 | X222: 2000 | Y222: 2162.4 | Z222: 2432.7 | AA222: 2703 | AB222: 2973.3 | AC222: 3243.6 | AD222: 3513.9 | AE222: 3784.2 | AF222: 4054.5 | AG222: 4324.8 | AH222: 4595.1 | AI222: 4865.4 | AJ222: 5135.7 | AK222: 5406 | AL222: 5406 | AM222: 5406 | AN222: 5406 | AO222: 5406 | AP222: 5406 | AQ222: 5406 | AR222: 5406 | AS222: 5406 | AT222: 5406 | AU222: 5406 | AV222: 5406 | AW222: 5406 | AX222: 5406 | AY222: 5406 | AZ222: 5406 | BA222: 5406 | BB222: 5406 | BC222: 5406 | BD222: 5406 | BE222: 5406 | BF222: 5406 | BG222: 5406 | BH222: 5406 | BI222: 5406 | BJ222: 5406 | BK222: 5406 | BL222: 5406 | BM222: 5406 | BN222: 5406 | BO222: 5406 | BP222: 5406 | BQ222: 5406 | BR222: 5406 | BS222: 5406 | BT222: 5406 | BU222: 5406 | BV222: 5406 | BW222: 5406 | BX222: 5406 | BY222: 5406 | BZ222: 5406 | CA222: 5406 | CB222: 5406 | CC222: 5406 | CD222: 5406 | CE222: 5406 | CF222: 5406 | CG222: 5406 | CH222: 5406 | CI222: 5406 | CJ222: 5406 | CK222: 5406 | CL222: 5406 | CM222: 5406 | CN222: 5406 | CO222: 5406 | CP222: 5406 | CQ222: 5406 | CR222: 5406 | CS222: 5406 | CT222: 5406 | CU222: 0 | CV222: 0 | CW222: 0 | CX222: 0 | CY222: 0 | CZ222: 0 | DA222: 0 | DB222: 0 | DC222: 0 | DD222: 0 | DE222: 0 | DF222: 0 | DG222: 0 | DH222: 0 | DI222: 0 | DJ222: 0 | DK222: 0 | DL222: 0 | DM222: 0 | DN222: 0 | DO222: 0 | DP222: 0 | DQ222: 0 | DR222: 0 | DS222: 0 | DT222: 0 | DU222: 0 | DV222: 0 | DW222: 0 | DX222: 0 | DZ222: 56 | EA222: SDJ20 | EB222: 1 | EC222: 4 | ED222: =EA222&TEXT(EB222,"00")&TEXT(EC222,"00") -> SDJ200104 | EE222: 270.3 | EF222: 10000 | EG222: 10000 | EH222: 10000 | EI222: 10000 | EJ222: 10000 | EK222: 10000 | EL222: 10000 | EM222: 10000 | EN222: 10000 | EO222: 10000 | EP222: 10000 | EQ222: 10000 | ER222: 10000 | ES222: 10000 | ET222: 10000 | EU222: 10000 | EV222: 10000 | EW222: 10000 | EX222: 10000 | EY222: 10000 | EZ222: 10000 | FA222: 10000 | FB222: 10000 | FC222: 10000 | FD222: 10000 | FE222: 10000 | FF222: 10000 | FG222: 10000 | FH222: 10000 | FI222: 10000 | FJ222: 10000 | FK222: 10000 | FL222: 10000 | FM222: 10000 | FN222: 10000 | FO222: 10000 | FP222: 10000 | FQ222: 10000 | FR222: 10000 | FS222: 10000 | FT222: 10000 | FU222: 10000 | FV222: 10000 | FW222: 10000 | FX222: 10000 | FY222: 10000 | FZ222: 10000 | GA222: 10000 | GB222: 10000 | GC222: 10000 | GD222: 10000 | GE222: 10000 | GF222: 10000 | GG222: 10000 | GH222: 10000 | GI222: 10000 | GJ222: 10000 | GK222: 10000 | GL222: 10000 | GM222: 10000 | GN222: 10000 | GO222: 10000 | GP222: 10000 | GQ222: 10000 | GR222: 10000 | GS222: 10000 | GT222: 10000 | GU222: 10000 | GV222: 10000 | GW222: 10000 | GX222: 10000 | GY222: 10000 | GZ222: 10000 | HA222: 10000 | HB222: 10000 | HC222: 10000 | HD222: 10000 | HE222: 10000 | HF222: 10000 | HG222: 10000 | HH222: 0 | HI222: 0 | HJ222: 0 | HK222: 0 | HL222: 0 | HM222: 0 | HN222: 0 | HO222: 0 | HP222: 0 | HQ222: 0 | HR222: 0 | HS222: 0 | HT222: 0 | HU222: 0 | HV222: 0 | HW222: 0 | HX222: 0 | HY222: 0 | HZ222: 0 | IA222: 0 | IB222: 0 | IC222: 0 | ID222: 0 | IE222: 0 | IF222: 0 | IG222: 0 | IH222: 0 | II222: 0 | IJ222: 0 | IK222: 0
M223: 56 | N223: SDJ20 | O223: 1 | P223: 5 | Q223: =N223&TEXT(O223,"00")&TEXT(P223,"00") -> SDJ200105 | R223: 274.5 | S223: 2000 | T223: 2000 | U223: 2000 | V223: 2000 | W223: 2000 | X223: 2000 | Y223: 2196.3 | Z223: 2470.9 | AA223: 2745.4 | AB223: 3019.9 | AC223: 3294.5 | AD223: 3569 | AE223: 3843.6 | AF223: 4118.1 | AG223: 4392.6 | AH223: 4667.2 | AI223: 4941.7 | AJ223: 5216.3 | AK223: 5490.8 | AL223: 5490.8 | AM223: 5490.8 | AN223: 5490.8 | AO223: 5490.8 | AP223: 5490.8 | AQ223: 5490.8 | AR223: 5490.8 | AS223: 5490.8 | AT223: 5490.8 | AU223: 5490.8 | AV223: 5490.8 | AW223: 5490.8 | AX223: 5490.8 | AY223: 5490.8 | AZ223: 5490.8 | BA223: 5490.8 | BB223: 5490.8 | BC223: 5490.8 | BD223: 5490.8 | BE223: 5490.8 | BF223: 5490.8 | BG223: 5490.8 | BH223: 5490.8 | BI223: 5490.8 | BJ223: 5490.8 | BK223: 5490.8 | BL223: 5490.8 | BM223: 5490.8 | BN223: 5490.8 | BO223: 5490.8 | BP223: 5490.8 | BQ223: 5490.8 | BR223: 5490.8 | BS223: 5490.8 | BT223: 5490.8 | BU223: 5490.8 | BV223: 5490.8 | BW223: 5490.8 | BX223: 5490.8 | BY223: 5490.8 | BZ223: 5490.8 | CA223: 5490.8 | CB223: 5490.8 | CC223: 5490.8 | CD223: 5490.8 | CE223: 5490.8 | CF223: 5490.8 | CG223: 5490.8 | CH223: 5490.8 | CI223: 5490.8 | CJ223: 5490.8 | CK223: 5490.8 | CL223: 5490.8 | CM223: 5490.8 | CN223: 5490.8 | CO223: 5490.8 | CP223: 5490.8 | CQ223: 5490.8 | CR223: 5490.8 | CS223: 5490.8 | CT223: 0 | CU223: 0 | CV223: 0 | CW223: 0 | CX223: 0 | CY223: 0 | CZ223: 0 | DA223: 0 | DB223: 0 | DC223: 0 | DD223: 0 | DE223: 0 | DF223: 0 | DG223: 0 | DH223: 0 | DI223: 0 | DJ223: 0 | DK223: 0 | DL223: 0 | DM223: 0 | DN223: 0 | DO223: 0 | DP223: 0 | DQ223: 0 | DR223: 0 | DS223: 0 | DT223: 0 | DU223: 0 | DV223: 0 | DW223: 0 | DX223: 0 | DZ223: 56 | EA223: SDJ20 | EB223: 1 | EC223: 5 | ED223: =EA223&TEXT(EB223,"00")&TEXT(EC223,"00") -> SDJ200105 | EE223: 274.5 | EF223: 10000 | EG223: 10000 | EH223: 10000 | EI223: 10000 | EJ223: 10000 | EK223: 10000 | EL223: 10000 | EM223: 10000 | EN223: 10000 | EO223: 10000 | EP223: 10000 | EQ223: 10000 | ER223: 10000 | ES223: 10000 | ET223: 10000 | EU223: 10000 | EV223: 10000 | EW223: 10000 | EX223: 10000 | EY223: 10000 | EZ223: 10000 | FA223: 10000 | FB223: 10000 | FC223: 10000 | FD223: 10000 | FE223: 10000 | FF223: 10000 | FG223: 10000 | FH223: 10000 | FI223: 10000 | FJ223: 10000 | FK223: 10000 | FL223: 10000 | FM223: 10000 | FN223: 10000 | FO223: 10000 | FP223: 10000 | FQ223: 10000 | FR223: 10000 | FS223: 10000 | FT223: 10000 | FU223: 10000 | FV223: 10000 | FW223: 10000 | FX223: 10000 | FY223: 10000 | FZ223: 10000 | GA223: 10000 | GB223: 10000 | GC223: 10000 | GD223: 10000 | GE223: 10000 | GF223: 10000 | GG223: 10000 | GH223: 10000 | GI223: 10000 | GJ223: 10000 | GK223: 10000 | GL223: 10000 | GM223: 10000 | GN223: 10000 | GO223: 10000 | GP223: 10000 | GQ223: 10000 | GR223: 10000 | GS223: 10000 | GT223: 10000 | GU223: 10000 | GV223: 10000 | GW223: 10000 | GX223: 10000 | GY223: 10000 | GZ223: 10000 | HA223: 10000 | HB223: 10000 | HC223: 10000 | HD223: 10000 | HE223: 10000 | HF223: 10000 | HG223: 0 | HH223: 0 | HI223: 0 | HJ223: 0 | HK223: 0 | HL223: 0 | HM223: 0 | HN223: 0 | HO223: 0 | HP223: 0 | HQ223: 0 | HR223: 0 | HS223: 0 | HT223: 0 | HU223: 0 | HV223: 0 | HW223: 0 | HX223: 0 | HY223: 0 | HZ223: 0 | IA223: 0 | IB223: 0 | IC223: 0 | ID223: 0 | IE223: 0 | IF223: 0 | IG223: 0 | IH223: 0 | II223: 0 | IJ223: 0 | IK223: 0
M224: 56 | N224: SDJ20 | O224: 1 | P224: 6 | Q224: =N224&TEXT(O224,"00")&TEXT(P224,"00") -> SDJ200106 | R224: 278.8 | S224: 2000 | T224: 2000 | U224: 2000 | V224: 2000 | W224: 2000 | X224: 2000 | Y224: 2230.2 | Z224: 2509 | AA224: 2787.8 | AB224: 3066.6 | AC224: 3345.4 | AD224: 3624.1 | AE224: 3902.9 | AF224: 4181.7 | AG224: 4460.5 | AH224: 4739.3 | AI224: 5018 | AJ224: 5296.8 | AK224: 5575.6 | AL224: 5575.6 | AM224: 5575.6 | AN224: 5575.6 | AO224: 5575.6 | AP224: 5575.6 | AQ224: 5575.6 | AR224: 5575.6 | AS224: 5575.6 | AT224: 5575.6 | AU224: 5575.6 | AV224: 5575.6 | AW224: 5575.6 | AX224: 5575.6 | AY224: 5575.6 | AZ224: 5575.6 | BA224: 5575.6 | BB224: 5575.6 | BC224: 5575.6 | BD224: 5575.6 | BE224: 5575.6 | BF224: 5575.6 | BG224: 5575.6 | BH224: 5575.6 | BI224: 5575.6 | BJ224: 5575.6 | BK224: 5575.6 | BL224: 5575.6 | BM224: 5575.6 | BN224: 5575.6 | BO224: 5575.6 | BP224: 5575.6 | BQ224: 5575.6 | BR224: 5575.6 | BS224: 5575.6 | BT224: 5575.6 | BU224: 5575.6 | BV224: 5575.6 | BW224: 5575.6 | BX224: 5575.6 | BY224: 5575.6 | BZ224: 5575.6 | CA224: 5575.6 | CB224: 5575.6 | CC224: 5575.6 | CD224: 5575.6 | CE224: 5575.6 | CF224: 5575.6 | CG224: 5575.6 | CH224: 5575.6 | CI224: 5575.6 | CJ224: 5575.6 | CK224: 5575.6 | CL224: 5575.6 | CM224: 5575.6 | CN224: 5575.6 | CO224: 5575.6 | CP224: 5575.6 | CQ224: 5575.6 | CR224: 5575.6 | CS224: 0 | CT224: 0 | CU224: 0 | CV224: 0 | CW224: 0 | CX224: 0 | CY224: 0 | CZ224: 0 | DA224: 0 | DB224: 0 | DC224: 0 | DD224: 0 | DE224: 0 | DF224: 0 | DG224: 0 | DH224: 0 | DI224: 0 | DJ224: 0 | DK224: 0 | DL224: 0 | DM224: 0 | DN224: 0 | DO224: 0 | DP224: 0 | DQ224: 0 | DR224: 0 | DS224: 0 | DT224: 0 | DU224: 0 | DV224: 0 | DW224: 0 | DX224: 0 | DZ224: 56 | EA224: SDJ20 | EB224: 1 | EC224: 6 | ED224: =EA224&TEXT(EB224,"00")&TEXT(EC224,"00") -> SDJ200106 | EE224: 278.8 | EF224: 10000 | EG224: 10000 | EH224: 10000 | EI224: 10000 | EJ224: 10000 | EK224: 10000 | EL224: 10000 | EM224: 10000 | EN224: 10000 | EO224: 10000 | EP224: 10000 | EQ224: 10000 | ER224: 10000 | ES224: 10000 | ET224: 10000 | EU224: 10000 | EV224: 10000 | EW224: 10000 | EX224: 10000 | EY224: 10000 | EZ224: 10000 | FA224: 10000 | FB224: 10000 | FC224: 10000 | FD224: 10000 | FE224: 10000 | FF224: 10000 | FG224: 10000 | FH224: 10000 | FI224: 10000 | FJ224: 10000 | FK224: 10000 | FL224: 10000 | FM224: 10000 | FN224: 10000 | FO224: 10000 | FP224: 10000 | FQ224: 10000 | FR224: 10000 | FS224: 10000 | FT224: 10000 | FU224: 10000 | FV224: 10000 | FW224: 10000 | FX224: 10000 | FY224: 10000 | FZ224: 10000 | GA224: 10000 | GB224: 10000 | GC224: 10000 | GD224: 10000 | GE224: 10000 | GF224: 10000 | GG224: 10000 | GH224: 10000 | GI224: 10000 | GJ224: 10000 | GK224: 10000 | GL224: 10000 | GM224: 10000 | GN224: 10000 | GO224: 10000 | GP224: 10000 | GQ224: 10000 | GR224: 10000 | GS224: 10000 | GT224: 10000 | GU224: 10000 | GV224: 10000 | GW224: 10000 | GX224: 10000 | GY224: 10000 | GZ224: 10000 | HA224: 10000 | HB224: 10000 | HC224: 10000 | HD224: 10000 | HE224: 10000 | HF224: 0 | HG224: 0 | HH224: 0 | HI224: 0 | HJ224: 0 | HK224: 0 | HL224: 0 | HM224: 0 | HN224: 0 | HO224: 0 | HP224: 0 | HQ224: 0 | HR224: 0 | HS224: 0 | HT224: 0 | HU224: 0 | HV224: 0 | HW224: 0 | HX224: 0 | HY224: 0 | HZ224: 0 | IA224: 0 | IB224: 0 | IC224: 0 | ID224: 0 | IE224: 0 | IF224: 0 | IG224: 0 | IH224: 0 | II224: 0 | IJ224: 0 | IK224: 0
M225: 56 | N225: SDJ20 | O225: 1 | P225: 7 | Q225: =N225&TEXT(O225,"00")&TEXT(P225,"00") -> SDJ200107 | R225: 284.1 | S225: 2000 | T225: 2000 | U225: 2000 | V225: 2000 | W225: 2000 | X225: 2000 | Y225: 2272.6 | Z225: 2556.7 | AA225: 2840.8 | AB225: 3124.9 | AC225: 3409 | AD225: 3693 | AE225: 3977.1 | AF225: 4261.2 | AG225: 4545.3 | AH225: 4829.4 | AI225: 5113.4 | AJ225: 5397.5 | AK225: 5681.6 | AL225: 5681.6 | AM225: 5681.6 | AN225: 5681.6 | AO225: 5681.6 | AP225: 5681.6 | AQ225: 5681.6 | AR225: 5681.6 | AS225: 5681.6 | AT225: 5681.6 | AU225: 5681.6 | AV225: 5681.6 | AW225: 5681.6 | AX225: 5681.6 | AY225: 5681.6 | AZ225: 5681.6 | BA225: 5681.6 | BB225: 5681.6 | BC225: 5681.6 | BD225: 5681.6 | BE225: 5681.6 | BF225: 5681.6 | BG225: 5681.6 | BH225: 5681.6 | BI225: 5681.6 | BJ225: 5681.6 | BK225: 5681.6 | BL225: 5681.6 | BM225: 5681.6 | BN225: 5681.6 | BO225: 5681.6 | BP225: 5681.6 | BQ225: 5681.6 | BR225: 5681.6 | BS225: 5681.6 | BT225: 5681.6 | BU225: 5681.6 | BV225: 5681.6 | BW225: 5681.6 | BX225: 5681.6 | BY225: 5681.6 | BZ225: 5681.6 | CA225: 5681.6 | CB225: 5681.6 | CC225: 5681.6 | CD225: 5681.6 | CE225: 5681.6 | CF225: 5681.6 | CG225: 5681.6 | CH225: 5681.6 | CI225: 5681.6 | CJ225: 5681.6 | CK225: 5681.6 | CL225: 5681.6 | CM225: 5681.6 | CN225: 5681.6 | CO225: 5681.6 | CP225: 5681.6 | CQ225: 5681.6 | CR225: 0 | CS225: 0 | CT225: 0 | CU225: 0 | CV225: 0 | CW225: 0 | CX225: 0 | CY225: 0 | CZ225: 0 | DA225: 0 | DB225: 0 | DC225: 0 | DD225: 0 | DE225: 0 | DF225: 0 | DG225: 0 | DH225: 0 | DI225: 0 | DJ225: 0 | DK225: 0 | DL225: 0 | DM225: 0 | DN225: 0 | DO225: 0 | DP225: 0 | DQ225: 0 | DR225: 0 | DS225: 0 | DT225: 0 | DU225: 0 | DV225: 0 | DW225: 0 | DX225: 0 | DZ225: 56 | EA225: SDJ20 | EB225: 1 | EC225: 7 | ED225: =EA225&TEXT(EB225,"00")&TEXT(EC225,"00") -> SDJ200107 | EE225: 284.1 | EF225: 10000 | EG225: 10000 | EH225: 10000 | EI225: 10000 | EJ225: 10000 | EK225: 10000 | EL225: 10000 | EM225: 10000 | EN225: 10000 | EO225: 10000 | EP225: 10000 | EQ225: 10000 | ER225: 10000 | ES225: 10000 | ET225: 10000 | EU225: 10000 | EV225: 10000 | EW225: 10000 | EX225: 10000 | EY225: 10000 | EZ225: 10000 | FA225: 10000 | FB225: 10000 | FC225: 10000 | FD225: 10000 | FE225: 10000 | FF225: 10000 | FG225: 10000 | FH225: 10000 | FI225: 10000 | FJ225: 10000 | FK225: 10000 | FL225: 10000 | FM225: 10000 | FN225: 10000 | FO225: 10000 | FP225: 10000 | FQ225: 10000 | FR225: 10000 | FS225: 10000 | FT225: 10000 | FU225: 10000 | FV225: 10000 | FW225: 10000 | FX225: 10000 | FY225: 10000 | FZ225: 10000 | GA225: 10000 | GB225: 10000 | GC225: 10000 | GD225: 10000 | GE225: 10000 | GF225: 10000 | GG225: 10000 | GH225: 10000 | GI225: 10000 | GJ225: 10000 | GK225: 10000 | GL225: 10000 | GM225: 10000 | GN225: 10000 | GO225: 10000 | GP225: 10000 | GQ225: 10000 | GR225: 10000 | GS225: 10000 | GT225: 10000 | GU225: 10000 | GV225: 10000 | GW225: 10000 | GX225: 10000 | GY225: 10000 | GZ225: 10000 | HA225: 10000 | HB225: 10000 | HC225: 10000 | HD225: 10000 | HE225: 0 | HF225: 0 | HG225: 0 | HH225: 0 | HI225: 0 | HJ225: 0 | HK225: 0 | HL225: 0 | HM225: 0 | HN225: 0 | HO225: 0 | HP225: 0 | HQ225: 0 | HR225: 0 | HS225: 0 | HT225: 0 | HU225: 0 | HV225: 0 | HW225: 0 | HX225: 0 | HY225: 0 | HZ225: 0 | IA225: 0 | IB225: 0 | IC225: 0 | ID225: 0 | IE225: 0 | IF225: 0 | IG225: 0 | IH225: 0 | II225: 0 | IJ225: 0 | IK225: 0
M226: 56 | N226: SDJ20 | O226: 1 | P226: 8 | Q226: =N226&TEXT(O226,"00")&TEXT(P226,"00") -> SDJ200108 | R226: 289.4 | S226: 2000 | T226: 2000 | U226: 2000 | V226: 2000 | W226: 2000 | X226: 2025.7 | Y226: 2315 | Z226: 2604.4 | AA226: 2893.8 | AB226: 3183.2 | AC226: 3472.6 | AD226: 3761.9 | AE226: 4051.3 | AF226: 4340.7 | AG226: 4630.1 | AH226: 4919.5 | AI226: 5208.8 | AJ226: 5498.2 | AK226: 5787.6 | AL226: 5787.6 | AM226: 5787.6 | AN226: 5787.6 | AO226: 5787.6 | AP226: 5787.6 | AQ226: 5787.6 | AR226: 5787.6 | AS226: 5787.6 | AT226: 5787.6 | AU226: 5787.6 | AV226: 5787.6 | AW226: 5787.6 | AX226: 5787.6 | AY226: 5787.6 | AZ226: 5787.6 | BA226: 5787.6 | BB226: 5787.6 | BC226: 5787.6 | BD226: 5787.6 | BE226: 5787.6 | BF226: 5787.6 | BG226: 5787.6 | BH226: 5787.6 | BI226: 5787.6 | BJ226: 5787.6 | BK226: 5787.6 | BL226: 5787.6 | BM226: 5787.6 | BN226: 5787.6 | BO226: 5787.6 | BP226: 5787.6 | BQ226: 5787.6 | BR226: 5787.6 | BS226: 5787.6 | BT226: 5787.6 | BU226: 5787.6 | BV226: 5787.6 | BW226: 5787.6 | BX226: 5787.6 | BY226: 5787.6 | BZ226: 5787.6 | CA226: 5787.6 | CB226: 5787.6 | CC226: 5787.6 | CD226: 5787.6 | CE226: 5787.6 | CF226: 5787.6 | CG226: 5787.6 | CH226: 5787.6 | CI226: 5787.6 | CJ226: 5787.6 | CK226: 5787.6 | CL226: 5787.6 | CM226: 5787.6 | CN226: 5787.6 | CO226: 5787.6 | CP226: 5787.6 | CQ226: 0 | CR226: 0 | CS226: 0 | CT226: 0 | CU226: 0 | CV226: 0 | CW226: 0 | CX226: 0 | CY226: 0 | CZ226: 0 | DA226: 0 | DB226: 0 | DC226: 0 | DD226: 0 | DE226: 0 | DF226: 0 | DG226: 0 | DH226: 0 | DI226: 0 | DJ226: 0 | DK226: 0 | DL226: 0 | DM226: 0 | DN226: 0 | DO226: 0 | DP226: 0 | DQ226: 0 | DR226: 0 | DS226: 0 | DT226: 0 | DU226: 0 | DV226: 0 | DW226: 0 | DX226: 0 | DZ226: 56 | EA226: SDJ20 | EB226: 1 | EC226: 8 | ED226: =EA226&TEXT(EB226,"00")&TEXT(EC226,"00") -> SDJ200108 | EE226: 289.4 | EF226: 10000 | EG226: 10000 | EH226: 10000 | EI226: 10000 | EJ226: 10000 | EK226: 10000 | EL226: 10000 | EM226: 10000 | EN226: 10000 | EO226: 10000 | EP226: 10000 | EQ226: 10000 | ER226: 10000 | ES226: 10000 | ET226: 10000 | EU226: 10000 | EV226: 10000 | EW226: 10000 | EX226: 10000 | EY226: 10000 | EZ226: 10000 | FA226: 10000 | FB226: 10000 | FC226: 10000 | FD226: 10000 | FE226: 10000 | FF226: 10000 | FG226: 10000 | FH226: 10000 | FI226: 10000 | FJ226: 10000 | FK226: 10000 | FL226: 10000 | FM226: 10000 | FN226: 10000 | FO226: 10000 | FP226: 10000 | FQ226: 10000 | FR226: 10000 | FS226: 10000 | FT226: 10000 | FU226: 10000 | FV226: 10000 | FW226: 10000 | FX226: 10000 | FY226: 10000 | FZ226: 10000 | GA226: 10000 | GB226: 10000 | GC226: 10000 | GD226: 10000 | GE226: 10000 | GF226: 10000 | GG226: 10000 | GH226: 10000 | GI226: 10000 | GJ226: 10000 | GK226: 10000 | GL226: 10000 | GM226: 10000 | GN226: 10000 | GO226: 10000 | GP226: 10000 | GQ226: 10000 | GR226: 10000 | GS226: 10000 | GT226: 10000 | GU226: 10000 | GV226: 10000 | GW226: 10000 | GX226: 10000 | GY226: 10000 | GZ226: 10000 | HA226: 10000 | HB226: 10000 | HC226: 10000 | HD226: 0 | HE226: 0 | HF226: 0 | HG226: 0 | HH226: 0 | HI226: 0 | HJ226: 0 | HK226: 0 | HL226: 0 | HM226: 0 | HN226: 0 | HO226: 0 | HP226: 0 | HQ226: 0 | HR226: 0 | HS226: 0 | HT226: 0 | HU226: 0 | HV226: 0 | HW226: 0 | HX226: 0 | HY226: 0 | HZ226: 0 | IA226: 0 | IB226: 0 | IC226: 0 | ID226: 0 | IE226: 0 | IF226: 0 | IG226: 0 | IH226: 0 | II226: 0 | IJ226: 0 | IK226: 0
M227: 56 | N227: SDJ20 | O227: 1 | P227: 9 | Q227: =N227&TEXT(O227,"00")&TEXT(P227,"00") -> SDJ200109 | R227: 294.7 | S227: 2000 | T227: 2000 | U227: 2000 | V227: 2000 | W227: 2000 | X227: 2062.8 | Y227: 2357.4 | Z227: 2652.1 | AA227: 2946.8 | AB227: 3241.5 | AC227: 3536.2 | AD227: 3830.8 | AE227: 4125.5 | AF227: 4420.2 | AG227: 4714.9 | AH227: 5009.6 | AI227: 5304.2 | AJ227: 5598.9 | AK227: 5893.6 | AL227: 5893.6 | AM227: 5893.6 | AN227: 5893.6 | AO227: 5893.6 | AP227: 5893.6 | AQ227: 5893.6 | AR227: 5893.6 | AS227: 5893.6 | AT227: 5893.6 | AU227: 5893.6 | AV227: 5893.6 | AW227: 5893.6 | AX227: 5893.6 | AY227: 5893.6 | AZ227: 5893.6 | BA227: 5893.6 | BB227: 5893.6 | BC227: 5893.6 | BD227: 5893.6 | BE227: 5893.6 | BF227: 5893.6 | BG227: 5893.6 | BH227: 5893.6 | BI227: 5893.6 | BJ227: 5893.6 | BK227: 5893.6 | BL227: 5893.6 | BM227: 5893.6 | BN227: 5893.6 | BO227: 5893.6 | BP227: 5893.6 | BQ227: 5893.6 | BR227: 5893.6 | BS227: 5893.6 | BT227: 5893.6 | BU227: 5893.6 | BV227: 5893.6 | BW227: 5893.6 | BX227: 5893.6 | BY227: 5893.6 | BZ227: 5893.6 | CA227: 5893.6 | CB227: 5893.6 | CC227: 5893.6 | CD227: 5893.6 | CE227: 5893.6 | CF227: 5893.6 | CG227: 5893.6 | CH227: 5893.6 | CI227: 5893.6 | CJ227: 5893.6 | CK227: 5893.6 | CL227: 5893.6 | CM227: 5893.6 | CN227: 5893.6 | CO227: 5893.6 | CP227: 0 | CQ227: 0 | CR227: 0 | CS227: 0 | CT227: 0 | CU227: 0 | CV227: 0 | CW227: 0 | CX227: 0 | CY227: 0 | CZ227: 0 | DA227: 0 | DB227: 0 | DC227: 0 | DD227: 0 | DE227: 0 | DF227: 0 | DG227: 0 | DH227: 0 | DI227: 0 | DJ227: 0 | DK227: 0 | DL227: 0 | DM227: 0 | DN227: 0 | DO227: 0 | DP227: 0 | DQ227: 0 | DR227: 0 | DS227: 0 | DT227: 0 | DU227: 0 | DV227: 0 | DW227: 0 | DX227: 0 | DZ227: 56 | EA227: SDJ20 | EB227: 1 | EC227: 9 | ED227: =EA227&TEXT(EB227,"00")&TEXT(EC227,"00") -> SDJ200109 | EE227: 294.7 | EF227: 10000 | EG227: 10000 | EH227: 10000 | EI227: 10000 | EJ227: 10000 | EK227: 10000 | EL227: 10000 | EM227: 10000 | EN227: 10000 | EO227: 10000 | EP227: 10000 | EQ227: 10000 | ER227: 10000 | ES227: 10000 | ET227: 10000 | EU227: 10000 | EV227: 10000 | EW227: 10000 | EX227: 10000 | EY227: 10000 | EZ227: 10000 | FA227: 10000 | FB227: 10000 | FC227: 10000 | FD227: 10000 | FE227: 10000 | FF227: 10000 | FG227: 10000 | FH227: 10000 | FI227: 10000 | FJ227: 10000 | FK227: 10000 | FL227: 10000 | FM227: 10000 | FN227: 10000 | FO227: 10000 | FP227: 10000 | FQ227: 10000 | FR227: 10000 | FS227: 10000 | FT227: 10000 | FU227: 10000 | FV227: 10000 | FW227: 10000 | FX227: 10000 | FY227: 10000 | FZ227: 10000 | GA227: 10000 | GB227: 10000 | GC227: 10000 | GD227: 10000 | GE227: 10000 | GF227: 10000 | GG227: 10000 | GH227: 10000 | GI227: 10000 | GJ227: 10000 | GK227: 10000 | GL227: 10000 | GM227: 10000 | GN227: 10000 | GO227: 10000 | GP227: 10000 | GQ227: 10000 | GR227: 10000 | GS227: 10000 | GT227: 10000 | GU227: 10000 | GV227: 10000 | GW227: 10000 | GX227: 10000 | GY227: 10000 | GZ227: 10000 | HA227: 10000 | HB227: 10000 | HC227: 0 | HD227: 0 | HE227: 0 | HF227: 0 | HG227: 0 | HH227: 0 | HI227: 0 | HJ227: 0 | HK227: 0 | HL227: 0 | HM227: 0 | HN227: 0 | HO227: 0 | HP227: 0 | HQ227: 0 | HR227: 0 | HS227: 0 | HT227: 0 | HU227: 0 | HV227: 0 | HW227: 0 | HX227: 0 | HY227: 0 | HZ227: 0 | IA227: 0 | IB227: 0 | IC227: 0 | ID227: 0 | IE227: 0 | IF227: 0 | IG227: 0 | IH227: 0 | II227: 0 | IJ227: 0 | IK227: 0
M228: 56 | N228: SDJ20 | O228: 1 | P228: 10 | Q228: =N228&TEXT(O228,"00")&TEXT(P228,"00") -> SDJ200110 | R228: 300 | S228: 2000 | T228: 2000 | U228: 2000 | V228: 2000 | W228: 2000 | X228: 2099.9 | Y228: 2399.8 | Z228: 2699.8 | AA228: 2999.8 | AB228: 3299.8 | AC228: 3599.8 | AD228: 3899.7 | AE228: 4199.7 | AF228: 4499.7 | AG228: 4799.7 | AH228: 5099.7 | AI228: 5399.6 | AJ228: 5699.6 | AK228: 5999.6 | AL228: 5999.6 | AM228: 5999.6 | AN228: 5999.6 | AO228: 5999.6 | AP228: 5999.6 | AQ228: 5999.6 | AR228: 5999.6 | AS228: 5999.6 | AT228: 5999.6 | AU228: 5999.6 | AV228: 5999.6 | AW228: 5999.6 | AX228: 5999.6 | AY228: 5999.6 | AZ228: 5999.6 | BA228: 5999.6 | BB228: 5999.6 | BC228: 5999.6 | BD228: 5999.6 | BE228: 5999.6 | BF228: 5999.6 | BG228: 5999.6 | BH228: 5999.6 | BI228: 5999.6 | BJ228: 5999.6 | BK228: 5999.6 | BL228: 5999.6 | BM228: 5999.6 | BN228: 5999.6 | BO228: 5999.6 | BP228: 5999.6 | BQ228: 5999.6 | BR228: 5999.6 | BS228: 5999.6 | BT228: 5999.6 | BU228: 5999.6 | BV228: 5999.6 | BW228: 5999.6 | BX228: 5999.6 | BY228: 5999.6 | BZ228: 5999.6 | CA228: 5999.6 | CB228: 5999.6 | CC228: 5999.6 | CD228: 5999.6 | CE228: 5999.6 | CF228: 5999.6 | CG228: 5999.6 | CH228: 5999.6 | CI228: 5999.6 | CJ228: 5999.6 | CK228: 5999.6 | CL228: 5999.6 | CM228: 5999.6 | CN228: 5999.6 | CO228: 0 | CP228: 0 | CQ228: 0 | CR228: 0 | CS228: 0 | CT228: 0 | CU228: 0 | CV228: 0 | CW228: 0 | CX228: 0 | CY228: 0 | CZ228: 0 | DA228: 0 | DB228: 0 | DC228: 0 | DD228: 0 | DE228: 0 | DF228: 0 | DG228: 0 | DH228: 0 | DI228: 0 | DJ228: 0 | DK228: 0 | DL228: 0 | DM228: 0 | DN228: 0 | DO228: 0 | DP228: 0 | DQ228: 0 | DR228: 0 | DS228: 0 | DT228: 0 | DU228: 0 | DV228: 0 | DW228: 0 | DX228: 0 | DZ228: 56 | EA228: SDJ20 | EB228: 1 | EC228: 10 | ED228: =EA228&TEXT(EB228,"00")&TEXT(EC228,"00") -> SDJ200110 | EE228: 300 | EF228: 10000 | EG228: 10000 | EH228: 10000 | EI228: 10000 | EJ228: 10000 | EK228: 10000 | EL228: 10000 | EM228: 10000 | EN228: 10000 | EO228: 10000 | EP228: 10000 | EQ228: 10000 | ER228: 10000 | ES228: 10000 | ET228: 10000 | EU228: 10000 | EV228: 10000 | EW228: 10000 | EX228: 10000 | EY228: 10000 | EZ228: 10000 | FA228: 10000 | FB228: 10000 | FC228: 10000 | FD228: 10000 | FE228: 10000 | FF228: 10000 | FG228: 10000 | FH228: 10000 | FI228: 10000 | FJ228: 10000 | FK228: 10000 | FL228: 10000 | FM228: 10000 | FN228: 10000 | FO228: 10000 | FP228: 10000 | FQ228: 10000 | FR228: 10000 | FS228: 10000 | FT228: 10000 | FU228: 10000 | FV228: 10000 | FW228: 10000 | FX228: 10000 | FY228: 10000 | FZ228: 10000 | GA228: 10000 | GB228: 10000 | GC228: 10000 | GD228: 10000 | GE228: 10000 | GF228: 10000 | GG228: 10000 | GH228: 10000 | GI228: 10000 | GJ228: 10000 | GK228: 10000 | GL228: 10000 | GM228: 10000 | GN228: 10000 | GO228: 10000 | GP228: 10000 | GQ228: 10000 | GR228: 10000 | GS228: 10000 | GT228: 10000 | GU228: 10000 | GV228: 10000 | GW228: 10000 | GX228: 10000 | GY228: 10000 | GZ228: 10000 | HA228: 10000 | HB228: 0 | HC228: 0 | HD228: 0 | HE228: 0 | HF228: 0 | HG228: 0 | HH228: 0 | HI228: 0 | HJ228: 0 | HK228: 0 | HL228: 0 | HM228: 0 | HN228: 0 | HO228: 0 | HP228: 0 | HQ228: 0 | HR228: 0 | HS228: 0 | HT228: 0 | HU228: 0 | HV228: 0 | HW228: 0 | HX228: 0 | HY228: 0 | HZ228: 0 | IA228: 0 | IB228: 0 | IC228: 0 | ID228: 0 | IE228: 0 | IF228: 0 | IG228: 0 | IH228: 0 | II228: 0 | IJ228: 0 | IK228: 0
M229: 56 | N229: SDJ20 | O229: 1 | P229: 11 | Q229: =N229&TEXT(O229,"00")&TEXT(P229,"00") -> SDJ200111 | R229: 306.3 | S229: 2000 | T229: 2000 | U229: 2000 | V229: 2000 | W229: 2000 | X229: 2144.4 | Y229: 2450.7 | Z229: 2757.1 | AA229: 3063.4 | AB229: 3369.7 | AC229: 3676.1 | AD229: 3982.4 | AE229: 4288.8 | AF229: 4595.1 | AG229: 4901.4 | AH229: 5207.8 | AI229: 5514.1 | AJ229: 5820.5 | AK229: 6126.8 | AL229: 6126.8 | AM229: 6126.8 | AN229: 6126.8 | AO229: 6126.8 | AP229: 6126.8 | AQ229: 6126.8 | AR229: 6126.8 | AS229: 6126.8 | AT229: 6126.8 | AU229: 6126.8 | AV229: 6126.8 | AW229: 6126.8 | AX229: 6126.8 | AY229: 6126.8 | AZ229: 6126.8 | BA229: 6126.8 | BB229: 6126.8 | BC229: 6126.8 | BD229: 6126.8 | BE229: 6126.8 | BF229: 6126.8 | BG229: 6126.8 | BH229: 6126.8 | BI229: 6126.8 | BJ229: 6126.8 | BK229: 6126.8 | BL229: 6126.8 | BM229: 6126.8 | BN229: 6126.8 | BO229: 6126.8 | BP229: 6126.8 | BQ229: 6126.8 | BR229: 6126.8 | BS229: 6126.8 | BT229: 6126.8 | BU229: 6126.8 | BV229: 6126.8 | BW229: 6126.8 | BX229: 6126.8 | BY229: 6126.8 | BZ229: 6126.8 | CA229: 6126.8 | CB229: 6126.8 | CC229: 6126.8 | CD229: 6126.8 | CE229: 6126.8 | CF229: 6126.8 | CG229: 6126.8 | CH229: 6126.8 | CI229: 6126.8 | CJ229: 6126.8 | CK229: 6126.8 | CL229: 6126.8 | CM229: 6126.8 | CN229: 0 | CO229: 0 | CP229: 0 | CQ229: 0 | CR229: 0 | CS229: 0 | CT229: 0 | CU229: 0 | CV229: 0 | CW229: 0 | CX229: 0 | CY229: 0 | CZ229: 0 | DA229: 0 | DB229: 0 | DC229: 0 | DD229: 0 | DE229: 0 | DF229: 0 | DG229: 0 | DH229: 0 | DI229: 0 | DJ229: 0 | DK229: 0 | DL229: 0 | DM229: 0 | DN229: 0 | DO229: 0 | DP229: 0 | DQ229: 0 | DR229: 0 | DS229: 0 | DT229: 0 | DU229: 0 | DV229: 0 | DW229: 0 | DX229: 0 | DZ229: 56 | EA229: SDJ20 | EB229: 1 | EC229: 11 | ED229: =EA229&TEXT(EB229,"00")&TEXT(EC229,"00") -> SDJ200111 | EE229: 306.3 | EF229: 10000 | EG229: 10000 | EH229: 10000 | EI229: 10000 | EJ229: 10000 | EK229: 10000 | EL229: 10000 | EM229: 10000 | EN229: 10000 | EO229: 10000 | EP229: 10000 | EQ229: 10000 | ER229: 10000 | ES229: 10000 | ET229: 10000 | EU229: 10000 | EV229: 10000 | EW229: 10000 | EX229: 10000 | EY229: 10000 | EZ229: 10000 | FA229: 10000 | FB229: 10000 | FC229: 10000 | FD229: 10000 | FE229: 10000 | FF229: 10000 | FG229: 10000 | FH229: 10000 | FI229: 10000 | FJ229: 10000 | FK229: 10000 | FL229: 10000 | FM229: 10000 | FN229: 10000 | FO229: 10000 | FP229: 10000 | FQ229: 10000 | FR229: 10000 | FS229: 10000 | FT229: 10000 | FU229: 10000 | FV229: 10000 | FW229: 10000 | FX229: 10000 | FY229: 10000 | FZ229: 10000 | GA229: 10000 | GB229: 10000 | GC229: 10000 | GD229: 10000 | GE229: 10000 | GF229: 10000 | GG229: 10000 | GH229: 10000 | GI229: 10000 | GJ229: 10000 | GK229: 10000 | GL229: 10000 | GM229: 10000 | GN229: 10000 | GO229: 10000 | GP229: 10000 | GQ229: 10000 | GR229: 10000 | GS229: 10000 | GT229: 10000 | GU229: 10000 | GV229: 10000 | GW229: 10000 | GX229: 10000 | GY229: 10000 | GZ229: 10000 | HA229: 0 | HB229: 0 | HC229: 0 | HD229: 0 | HE229: 0 | HF229: 0 | HG229: 0 | HH229: 0 | HI229: 0 | HJ229: 0 | HK229: 0 | HL229: 0 | HM229: 0 | HN229: 0 | HO229: 0 | HP229: 0 | HQ229: 0 | HR229: 0 | HS229: 0 | HT229: 0 | HU229: 0 | HV229: 0 | HW229: 0 | HX229: 0 | HY229: 0 | HZ229: 0 | IA229: 0 | IB229: 0 | IC229: 0 | ID229: 0 | IE229: 0 | IF229: 0 | IG229: 0 | IH229: 0 | II229: 0 | IJ229: 0 | IK229: 0
... M319: 56 | N319: SDJ20 | O319: 2 | P319: 50 | Q319: =N319&TEXT(O319,"00")&TEXT(P319,"00") -> SDJ200250 | R319: 704.9 | S319: 2000 | T319: 2114.7 | U319: 2819.6 | V319: 3524.5 | W319: 4229.4 | X319: 4934.3 | Y319: 5639.2 | Z319: 6344.1 | AA319: 7049 | AB319: 7753.9 | AC319: 8458.8 | AD319: 9163.7 | AE319: 9868.6 | AF319: 10573.5 | AG319: 11278.4 | AH319: 11983.3 | AI319: 12688.2 | AJ319: 13393.1 | AK319: 14098 | AL319: 14098 | AM319: 14098 | AN319: 14098 | AO319: 14098 | AP319: 14098 | AQ319: 14098 | AR319: 14098 | AS319: 14098 | AT319: 14098 | AU319: 14098 | AV319: 14098 | AW319: 14098 | AX319: 14098 | AY319: 14098 | AZ319: 14098 | BA319: 0 | BB319: 0 | BC319: 0 | BD319: 0 | BE319: 0 | BF319: 0 | BG319: 0 | BH319: 0 | BI319: 0 | BJ319: 0 | BK319: 0 | BL319: 0 | BM319: 0 | BN319: 0 | BO319: 0 | BP319: 0 | BQ319: 0 | BR319: 0 | BS319: 0 | BT319: 0 | BU319: 0 | BV319: 0 | BW319: 0 | BX319: 0 | BY319: 0 | BZ319: 0 | CA319: 0 | CB319: 0 | CC319: 0 | CD319: 0 | CE319: 0 | CF319: 0 | CG319: 0 | CH319: 0 | CI319: 0 | CJ319: 0 | CK319: 0 | CL319: 0 | CM319: 0 | CN319: 0 | CO319: 0 | CP319: 0 | CQ319: 0 | CR319: 0 | CS319: 0 | CT319: 0 | CU319: 0 | CV319: 0 | CW319: 0 | CX319: 0 | CY319: 0 | CZ319: 0 | DA319: 0 | DB319: 0 | DC319: 0 | DD319: 0 | DE319: 0 | DF319: 0 | DG319: 0 | DH319: 0 | DI319: 0 | DJ319: 0 | DK319: 0 | DL319: 0 | DM319: 0 | DN319: 0 | DO319: 0 | DP319: 0 | DQ319: 0 | DR319: 0 | DS319: 0 | DT319: 0 | DU319: 0 | DV319: 0 | DW319: 0 | DX319: 0 | DZ319: 56 | EA319: SDJ20 | EB319: 2 | EC319: 50 | ED319: =EA319&TEXT(EB319,"00")&TEXT(EC319,"00") -> SDJ200250 | EE319: 704.9 | EF319: 10000 | EG319: 10000 | EH319: 10000 | EI319: 10000 | EJ319: 10000 | EK319: 10000 | EL319: 10000 | EM319: 10000 | EN319: 10000 | EO319: 10000 | EP319: 10000 | EQ319: 10000 | ER319: 10000 | ES319: 10573.5 | ET319: 11278.4 | EU319: 11983.3 | EV319: 12688.2 | EW319: 13393.1 | EX319: 14098 | EY319: 14098 | EZ319: 14098 | FA319: 14098 | FB319: 14098 | FC319: 14098 | FD319: 14098 | FE319: 14098 | FF319: 14098 | FG319: 14098 | FH319: 14098 | FI319: 14098 | FJ319: 14098 | FK319: 14098 | FL319: 14098 | FM319: 14098 | FN319: 0 | FO319: 0 | FP319: 0 | FQ319: 0 | FR319: 0 | FS319: 0 | FT319: 0 | FU319: 0 | FV319: 0 | FW319: 0 | FX319: 0 | FY319: 0 | FZ319: 0 | GA319: 0 | GB319: 0 | GC319: 0 | GD319: 0 | GE319: 0 | GF319: 0 | GG319: 0 | GH319: 0 | GI319: 0 | GJ319: 0 | GK319: 0 | GL319: 0 | GM319: 0 | GN319: 0 | GO319: 0 | GP319: 0 | GQ319: 0 | GR319: 0 | GS319: 0 | GT319: 0 | GU319: 0 | GV319: 0 | GW319: 0 | GX319: 0 | GY319: 0 | GZ319: 0 | HA319: 0 | HB319: 0 | HC319: 0 | HD319: 0 | HE319: 0 | HF319: 0 | HG319: 0 | HH319: 0 | HI319: 0 | HJ319: 0 | HK319: 0 | HL319: 0 | HM319: 0 | HN319: 0 | HO319: 0 | HP319: 0 | HQ319: 0 | HR319: 0 | HS319: 0 | HT319: 0 | HU319: 0 | HV319: 0 | HW319: 0 | HX319: 0 | HY319: 0 | HZ319: 0 | IA319: 0 | IB319: 0 | IC319: 0 | ID319: 0 | IE319: 0 | IF319: 0 | IG319: 0 | IH319: 0 | II319: 0 | IJ319: 0 | IK319: 0
M326: tbHEALTH3(重大疾病給付) | Q326: =N326&TEXT(O326,"00")&TEXT(P326,"00") -> 0000
M327: 版次 | N327: 商品代號 | O327: 性別 | P327: 年齡 | Q327: =N327&TEXT(O327,"00")&TEXT(P327,"00") -> 商品代號性別年齡 | R327: 第1年重疾保險金 | S327: 第2年重疾保險金 | T327: 第3年重疾保險金 | U327: 第4年重疾保險金 | V327: 第5年重疾保險金 | W327: 第6年重疾保險金 | X327: 第7年重疾保險金 | Y327: 第8年重疾保險金 | Z327: 第9年重疾保險金 | AA327: 第10年重疾保險金 | AB327: 第11年重疾保險金 | AC327: 第12年重疾保險金 | AD327: 第13年重疾保險金 | AE327: 第14年重疾保險金 | AF327: 第15年重疾保險金 | AG327: 第16年重疾保險金 | AH327: 第17年重疾保險金 | AI327: 第18年重疾保險金 | AJ327: 第19年重疾保險金 | AK327: 第20年重疾保險金 | AL327: 第21年重疾保險金 | AM327: 第22年重疾保險金 | AN327: 第23年重疾保險金 | AO327: 第24年重疾保險金 | AP327: 第25年重疾保險金 | AQ327: 第26年重疾保險金 | AR327: 第27年重疾保險金 | AS327: 第28年重疾保險金 | AT327: 第29年重疾保險金 | AU327: 第30年重疾保險金 | AV327: 第31年重疾保險金 | AW327: 第32年重疾保險金 | AX327: 第33年重疾保險金 | AY327: 第34年重疾保險金 | AZ327: 第35年重疾保險金 | BA327: 第36年重疾保險金 | BB327: 第37年重疾保險金 | BC327: 第38年重疾保險金 | BD327: 第39年重疾保險金 | BE327: 第40年重疾保險金 | BF327: 第41年重疾保險金 | BG327: 第42年重疾保險金 | BH327: 第43年重疾保險金 | BI327: 第44年重疾保險金 | BJ327: 第45年重疾保險金 | BK327: 第46年重疾保險金 | BL327: 第47年重疾保險金 | BM327: 第48年重疾保險金 | BN327: 第49年重疾保險金 | BO327: 第50年重疾保險金 | BP327: 第51年重疾保險金 | BQ327: 第52年重疾保險金 | BR327: 第53年重疾保險金 | BS327: 第54年重疾保險金 | BT327: 第55年重疾保險金 | BU327: 第56年重疾保險金 | BV327: 第57年重疾保險金 | BW327: 第58年重疾保險金 | BX327: 第59年重疾保險金 | BY327: 第60年重疾保險金 | BZ327: 第61年重疾保險金 | CA327: 第62年重疾保險金 | CB327: 第63年重疾保險金 | CC327: 第64年重疾保險金 | CD327: 第65年重疾保險金 | CE327: 第66年重疾保險金 | CF327: 第67年重疾保險金 | CG327: 第68年重疾保險金 | CH327: 第69年重疾保險金 | CI327: 第70年重疾保險金 | CJ327: 第71年重疾保險金 | CK327: 第72年重疾保險金 | CL327: 第73年重疾保險金 | CM327: 第74年重疾保險金額 | CN327: 第75年重疾保險金 | CO327: 第76年重疾保險金 | CP327: 第77年重疾保險金 | CQ327: 第78年重疾保險金 | CR327: 第79年重疾保險金 | CS327: 第80年重疾保險金 | CT327: 第81年重疾保險金 | CU327: 第82年重疾保險金 | CV327: 第83年重疾保險金 | CW327: 第84年重疾保險金 | CX327: 第85年重疾保險金 | CY327: 第86年重疾保險金 | CZ327: 第87年重疾保險金 | DA327: 第88年重疾保險金 | DB327: 第89年重疾保險金 | DC327: 第90年重疾保險金 | DD327: 第91年重疾保險金 | DE327: 第92年重疾保險金 | DF327: 第93年重疾保險金 | DG327: 第94年重疾保險金 | DH327: 第95年重疾保險金 | DI327: 第96年重疾保險金 | DJ327: 第97年重疾保險金 | DK327: 第98年重疾保險金 | DL327: 第99年重疾保險金 | DM327: 第100年重疾保險金 | DN327: 第101年重疾保險金 | DO327: 第102年重疾保險金 | DP327: 第103年重疾保險金 | DQ327: 第104年重疾保險金 | DR327: 第105年重疾保險金 | DS327: 第106年重疾保險金 | DT327: 第107年重疾保險金 | DU327: 第108年重疾保險金 | DV327: 第109年重疾保險金 | DW327: 第110年重疾保險金 | DX327: 第111年重疾保險金
M328: 56 | N328: SDJ20 | O328: 1 | P328: 0 | Q328: =N328&TEXT(O328,"00")&TEXT(P328,"00") -> SDJ200100 | R328: 10000 | S328: 10000 | T328: 10000 | U328: 10000 | V328: 10000 | W328: 10000 | X328: 10000 | Y328: 10000 | Z328: 10000 | AA328: 10000 | AB328: 10000 | AC328: 10000 | AD328: 10000 | AE328: 10000 | AF328: 10000 | AG328: 10000 | AH328: 10000 | AI328: 10000 | AJ328: 10000 | AK328: 10000 | AL328: 10000 | AM328: 10000 | AN328: 10000 | AO328: 10000 | AP328: 10000 | AQ328: 10000 | AR328: 10000 | AS328: 10000 | AT328: 10000 | AU328: 10000 | AV328: 10000 | AW328: 10000 | AX328: 10000 | AY328: 10000 | AZ328: 10000 | BA328: 10000 | BB328: 10000 | BC328: 10000 | BD328: 10000 | BE328: 10000 | BF328: 10000 | BG328: 10000 | BH328: 10000 | BI328: 10000 | BJ328: 10000 | BK328: 10000 | BL328: 10000 | BM328: 10000 | BN328: 10000 | BO328: 10000 | BP328: 10000 | BQ328: 10000 | BR328: 10000 | BS328: 10000 | BT328: 10000 | BU328: 10000 | BV328: 10000 | BW328: 10000 | BX328: 10000 | BY328: 10000 | BZ328: 10000 | CA328: 10000 | CB328: 10000 | CC328: 10000 | CD328: 10000 | CE328: 10000 | CF328: 10000 | CG328: 10000 | CH328: 10000 | CI328: 10000 | CJ328: 10000 | CK328: 10000 | CL328: 10000 | CM328: 10000 | CN328: 10000 | CO328: 10000 | CP328: 10000 | CQ328: 10000 | CR328: 10000 | CS328: 10000 | CT328: 10000 | CU328: 10000 | CV328: 10000 | CW328: 10000 | CX328: 10000 | CY328: 0 | CZ328: 0 | DA328: 0 | DB328: 0 | DC328: 0 | DD328: 0 | DE328: 0 | DF328: 0 | DG328: 0 | DH328: 0 | DI328: 0 | DJ328: 0 | DK328: 0 | DL328: 0 | DM328: 0 | DN328: 0 | DO328: 0 | DP328: 0 | DQ328: 0 | DR328: 0 | DS328: 0 | DT328: 0 | DU328: 0 | DV328: 0 | DW328: 0 | DX328: 0
M329: 56 | N329: SDJ20 | O329: 1 | P329: 1 | Q329: =N329&TEXT(O329,"00")&TEXT(P329,"00") -> SDJ200101 | R329: 10000 | S329: 10000 | T329: 10000 | U329: 10000 | V329: 10000 | W329: 10000 | X329: 10000 | Y329: 10000 | Z329: 10000 | AA329: 10000 | AB329: 10000 | AC329: 10000 | AD329: 10000 | AE329: 10000 | AF329: 10000 | AG329: 10000 | AH329: 10000 | AI329: 10000 | AJ329: 10000 | AK329: 10000 | AL329: 10000 | AM329: 10000 | AN329: 10000 | AO329: 10000 | AP329: 10000 | AQ329: 10000 | AR329: 10000 | AS329: 10000 | AT329: 10000 | AU329: 10000 | AV329: 10000 | AW329: 10000 | AX329: 10000 | AY329: 10000 | AZ329: 10000 | BA329: 10000 | BB329: 10000 | BC329: 10000 | BD329: 10000 | BE329: 10000 | BF329: 10000 | BG329: 10000 | BH329: 10000 | BI329: 10000 | BJ329: 10000 | BK329: 10000 | BL329: 10000 | BM329: 10000 | BN329: 10000 | BO329: 10000 | BP329: 10000 | BQ329: 10000 | BR329: 10000 | BS329: 10000 | BT329: 10000 | BU329: 10000 | BV329: 10000 | BW329: 10000 | BX329: 10000 | BY329: 10000 | BZ329: 10000 | CA329: 10000 | CB329: 10000 | CC329: 10000 | CD329: 10000 | CE329: 10000 | CF329: 10000 | CG329: 10000 | CH329: 10000 | CI329: 10000 | CJ329: 10000 | CK329: 10000 | CL329: 10000 | CM329: 10000 | CN329: 10000 | CO329: 10000 | CP329: 10000 | CQ329: 10000 | CR329: 10000 | CS329: 10000 | CT329: 10000 | CU329: 10000 | CV329: 10000 | CW329: 10000 | CX329: 0 | CY329: 0 | CZ329: 0 | DA329: 0 | DB329: 0 | DC329: 0 | DD329: 0 | DE329: 0 | DF329: 0 | DG329: 0 | DH329: 0 | DI329: 0 | DJ329: 0 | DK329: 0 | DL329: 0 | DM329: 0 | DN329: 0 | DO329: 0 | DP329: 0 | DQ329: 0 | DR329: 0 | DS329: 0 | DT329: 0 | DU329: 0 | DV329: 0 | DW329: 0 | DX329: 0
M330: 56 | N330: SDJ20 | O330: 1 | P330: 2 | Q330: =N330&TEXT(O330,"00")&TEXT(P330,"00") -> SDJ200102 | R330: 10000 | S330: 10000 | T330: 10000 | U330: 10000 | V330: 10000 | W330: 10000 | X330: 10000 | Y330: 10000 | Z330: 10000 | AA330: 10000 | AB330: 10000 | AC330: 10000 | AD330: 10000 | AE330: 10000 | AF330: 10000 | AG330: 10000 | AH330: 10000 | AI330: 10000 | AJ330: 10000 | AK330: 10000 | AL330: 10000 | AM330: 10000 | AN330: 10000 | AO330: 10000 | AP330: 10000 | AQ330: 10000 | AR330: 10000 | AS330: 10000 | AT330: 10000 | AU330: 10000 | AV330: 10000 | AW330: 10000 | AX330: 10000 | AY330: 10000 | AZ330: 10000 | BA330: 10000 | BB330: 10000 | BC330: 10000 | BD330: 10000 | BE330: 10000 | BF330: 10000 | BG330: 10000 | BH330: 10000 | BI330: 10000 | BJ330: 10000 | BK330: 10000 | BL330: 10000 | BM330: 10000 | BN330: 10000 | BO330: 10000 | BP330: 10000 | BQ330: 10000 | BR330: 10000 | BS330: 10000 | BT330: 10000 | BU330: 10000 | BV330: 10000 | BW330: 10000 | BX330: 10000 | BY330: 10000 | BZ330: 10000 | CA330: 10000 | CB330: 10000 | CC330: 10000 | CD330: 10000 | CE330: 10000 | CF330: 10000 | CG330: 10000 | CH330: 10000 | CI330: 10000 | CJ330: 10000 | CK330: 10000 | CL330: 10000 | CM330: 10000 | CN330: 10000 | CO330: 10000 | CP330: 10000 | CQ330: 10000 | CR330: 10000 | CS330: 10000 | CT330: 10000 | CU330: 10000 | CV330: 10000 | CW330: 0 | CX330: 0 | CY330: 0 | CZ330: 0 | DA330: 0 | DB330: 0 | DC330: 0 | DD330: 0 | DE330: 0 | DF330: 0 | DG330: 0 | DH330: 0 | DI330: 0 | DJ330: 0 | DK330: 0 | DL330: 0 | DM330: 0 | DN330: 0 | DO330: 0 | DP330: 0 | DQ330: 0 | DR330: 0 | DS330: 0 | DT330: 0 | DU330: 0 | DV330: 0 | DW330: 0 | DX330: 0
M331: 56 | N331: SDJ20 | O331: 1 | P331: 3 | Q331: =N331&TEXT(O331,"00")&TEXT(P331,"00") -> SDJ200103 | R331: 10000 | S331: 10000 | T331: 10000 | U331: 10000 | V331: 10000 | W331: 10000 | X331: 10000 | Y331: 10000 | Z331: 10000 | AA331: 10000 | AB331: 10000 | AC331: 10000 | AD331: 10000 | AE331: 10000 | AF331: 10000 | AG331: 10000 | AH331: 10000 | AI331: 10000 | AJ331: 10000 | AK331: 10000 | AL331: 10000 | AM331: 10000 | AN331: 10000 | AO331: 10000 | AP331: 10000 | AQ331: 10000 | AR331: 10000 | AS331: 10000 | AT331: 10000 | AU331: 10000 | AV331: 10000 | AW331: 10000 | AX331: 10000 | AY331: 10000 | AZ331: 10000 | BA331: 10000 | BB331: 10000 | BC331: 10000 | BD331: 10000 | BE331: 10000 | BF331: 10000 | BG331: 10000 | BH331: 10000 | BI331: 10000 | BJ331: 10000 | BK331: 10000 | BL331: 10000 | BM331: 10000 | BN331: 10000 | BO331: 10000 | BP331: 10000 | BQ331: 10000 | BR331: 10000 | BS331: 10000 | BT331: 10000 | BU331: 10000 | BV331: 10000 | BW331: 10000 | BX331: 10000 | BY331: 10000 | BZ331: 10000 | CA331: 10000 | CB331: 10000 | CC331: 10000 | CD331: 10000 | CE331: 10000 | CF331: 10000 | CG331: 10000 | CH331: 10000 | CI331: 10000 | CJ331: 10000 | CK331: 10000 | CL331: 10000 | CM331: 10000 | CN331: 10000 | CO331: 10000 | CP331: 10000 | CQ331: 10000 | CR331: 10000 | CS331: 10000 | CT331: 10000 | CU331: 10000 | CV331: 0 | CW331: 0 | CX331: 0 | CY331: 0 | CZ331: 0 | DA331: 0 | DB331: 0 | DC331: 0 | DD331: 0 | DE331: 0 | DF331: 0 | DG331: 0 | DH331: 0 | DI331: 0 | DJ331: 0 | DK331: 0 | DL331: 0 | DM331: 0 | DN331: 0 | DO331: 0 | DP331: 0 | DQ331: 0 | DR331: 0 | DS331: 0 | DT331: 0 | DU331: 0 | DV331: 0 | DW331: 0 | DX331: 0
M332: 56 | N332: SDJ20 | O332: 1 | P332: 4 | Q332: =N332&TEXT(O332,"00")&TEXT(P332,"00") -> SDJ200104 | R332: 10000 | S332: 10000 | T332: 10000 | U332: 10000 | V332: 10000 | W332: 10000 | X332: 10000 | Y332: 10000 | Z332: 10000 | AA332: 10000 | AB332: 10000 | AC332: 10000 | AD332: 10000 | AE332: 10000 | AF332: 10000 | AG332: 10000 | AH332: 10000 | AI332: 10000 | AJ332: 10000 | AK332: 10000 | AL332: 10000 | AM332: 10000 | AN332: 10000 | AO332: 10000 | AP332: 10000 | AQ332: 10000 | AR332: 10000 | AS332: 10000 | AT332: 10000 | AU332: 10000 | AV332: 10000 | AW332: 10000 | AX332: 10000 | AY332: 10000 | AZ332: 10000 | BA332: 10000 | BB332: 10000 | BC332: 10000 | BD332: 10000 | BE332: 10000 | BF332: 10000 | BG332: 10000 | BH332: 10000 | BI332: 10000 | BJ332: 10000 | BK332: 10000 | BL332: 10000 | BM332: 10000 | BN332: 10000 | BO332: 10000 | BP332: 10000 | BQ332: 10000 | BR332: 10000 | BS332: 10000 | BT332: 10000 | BU332: 10000 | BV332: 10000 | BW332: 10000 | BX332: 10000 | BY332: 10000 | BZ332: 10000 | CA332: 10000 | CB332: 10000 | CC332: 10000 | CD332: 10000 | CE332: 10000 | CF332: 10000 | CG332: 10000 | CH332: 10000 | CI332: 10000 | CJ332: 10000 | CK332: 10000 | CL332: 10000 | CM332: 10000 | CN332: 10000 | CO332: 10000 | CP332: 10000 | CQ332: 10000 | CR332: 10000 | CS332: 10000 | CT332: 10000 | CU332: 0 | CV332: 0 | CW332: 0 | CX332: 0 | CY332: 0 | CZ332: 0 | DA332: 0 | DB332: 0 | DC332: 0 | DD332: 0 | DE332: 0 | DF332: 0 | DG332: 0 | DH332: 0 | DI332: 0 | DJ332: 0 | DK332: 0 | DL332: 0 | DM332: 0 | DN332: 0 | DO332: 0 | DP332: 0 | DQ332: 0 | DR332: 0 | DS332: 0 | DT332: 0 | DU332: 0 | DV332: 0 | DW332: 0 | DX332: 0
M333: 56 | N333: SDJ20 | O333: 1 | P333: 5 | Q333: =N333&TEXT(O333,"00")&TEXT(P333,"00") -> SDJ200105 | R333: 10000 | S333: 10000 | T333: 10000 | U333: 10000 | V333: 10000 | W333: 10000 | X333: 10000 | Y333: 10000 | Z333: 10000 | AA333: 10000 | AB333: 10000 | AC333: 10000 | AD333: 10000 | AE333: 10000 | AF333: 10000 | AG333: 10000 | AH333: 10000 | AI333: 10000 | AJ333: 10000 | AK333: 10000 | AL333: 10000 | AM333: 10000 | AN333: 10000 | AO333: 10000 | AP333: 10000 | AQ333: 10000 | AR333: 10000 | AS333: 10000 | AT333: 10000 | AU333: 10000 | AV333: 10000 | AW333: 10000 | AX333: 10000 | AY333: 10000 | AZ333: 10000 | BA333: 10000 | BB333: 10000 | BC333: 10000 | BD333: 10000 | BE333: 10000 | BF333: 10000 | BG333: 10000 | BH333: 10000 | BI333: 10000 | BJ333: 10000 | BK333: 10000 | BL333: 10000 | BM333: 10000 | BN333: 10000 | BO333: 10000 | BP333: 10000 | BQ333: 10000 | BR333: 10000 | BS333: 10000 | BT333: 10000 | BU333: 10000 | BV333: 10000 | BW333: 10000 | BX333: 10000 | BY333: 10000 | BZ333: 10000 | CA333: 10000 | CB333: 10000 | CC333: 10000 | CD333: 10000 | CE333: 10000 | CF333: 10000 | CG333: 10000 | CH333: 10000 | CI333: 10000 | CJ333: 10000 | CK333: 10000 | CL333: 10000 | CM333: 10000 | CN333: 10000 | CO333: 10000 | CP333: 10000 | CQ333: 10000 | CR333: 10000 | CS333: 10000 | CT333: 0 | CU333: 0 | CV333: 0 | CW333: 0 | CX333: 0 | CY333: 0 | CZ333: 0 | DA333: 0 | DB333: 0 | DC333: 0 | DD333: 0 | DE333: 0 | DF333: 0 | DG333: 0 | DH333: 0 | DI333: 0 | DJ333: 0 | DK333: 0 | DL333: 0 | DM333: 0 | DN333: 0 | DO333: 0 | DP333: 0 | DQ333: 0 | DR333: 0 | DS333: 0 | DT333: 0 | DU333: 0 | DV333: 0 | DW333: 0 | DX333: 0
M334: 56 | N334: SDJ20 | O334: 1 | P334: 6 | Q334: =N334&TEXT(O334,"00")&TEXT(P334,"00") -> SDJ200106 | R334: 10000 | S334: 10000 | T334: 10000 | U334: 10000 | V334: 10000 | W334: 10000 | X334: 10000 | Y334: 10000 | Z334: 10000 | AA334: 10000 | AB334: 10000 | AC334: 10000 | AD334: 10000 | AE334: 10000 | AF334: 10000 | AG334: 10000 | AH334: 10000 | AI334: 10000 | AJ334: 10000 | AK334: 10000 | AL334: 10000 | AM334: 10000 | AN334: 10000 | AO334: 10000 | AP334: 10000 | AQ334: 10000 | AR334: 10000 | AS334: 10000 | AT334: 10000 | AU334: 10000 | AV334: 10000 | AW334: 10000 | AX334: 10000 | AY334: 10000 | AZ334: 10000 | BA334: 10000 | BB334: 10000 | BC334: 10000 | BD334: 10000 | BE334: 10000 | BF334: 10000 | BG334: 10000 | BH334: 10000 | BI334: 10000 | BJ334: 10000 | BK334: 10000 | BL334: 10000 | BM334: 10000 | BN334: 10000 | BO334: 10000 | BP334: 10000 | BQ334: 10000 | BR334: 10000 | BS334: 10000 | BT334: 10000 | BU334: 10000 | BV334: 10000 | BW334: 10000 | BX334: 10000 | BY334: 10000 | BZ334: 10000 | CA334: 10000 | CB334: 10000 | CC334: 10000 | CD334: 10000 | CE334: 10000 | CF334: 10000 | CG334: 10000 | CH334: 10000 | CI334: 10000 | CJ334: 10000 | CK334: 10000 | CL334: 10000 | CM334: 10000 | CN334: 10000 | CO334: 10000 | CP334: 10000 | CQ334: 10000 | CR334: 10000 | CS334: 0 | CT334: 0 | CU334: 0 | CV334: 0 | CW334: 0 | CX334: 0 | CY334: 0 | CZ334: 0 | DA334: 0 | DB334: 0 | DC334: 0 | DD334: 0 | DE334: 0 | DF334: 0 | DG334: 0 | DH334: 0 | DI334: 0 | DJ334: 0 | DK334: 0 | DL334: 0 | DM334: 0 | DN334: 0 | DO334: 0 | DP334: 0 | DQ334: 0 | DR334: 0 | DS334: 0 | DT334: 0 | DU334: 0 | DV334: 0 | DW334: 0 | DX334: 0
M335: 56 | N335: SDJ20 | O335: 1 | P335: 7 | Q335: =N335&TEXT(O335,"00")&TEXT(P335,"00") -> SDJ200107 | R335: 10000 | S335: 10000 | T335: 10000 | U335: 10000 | V335: 10000 | W335: 10000 | X335: 10000 | Y335: 10000 | Z335: 10000 | AA335: 10000 | AB335: 10000 | AC335: 10000 | AD335: 10000 | AE335: 10000 | AF335: 10000 | AG335: 10000 | AH335: 10000 | AI335: 10000 | AJ335: 10000 | AK335: 10000 | AL335: 10000 | AM335: 10000 | AN335: 10000 | AO335: 10000 | AP335: 10000 | AQ335: 10000 | AR335: 10000 | AS335: 10000 | AT335: 10000 | AU335: 10000 | AV335: 10000 | AW335: 10000 | AX335: 10000 | AY335: 10000 | AZ335: 10000 | BA335: 10000 | BB335: 10000 | BC335: 10000 | BD335: 10000 | BE335: 10000 | BF335: 10000 | BG335: 10000 | BH335: 10000 | BI335: 10000 | BJ335: 10000 | BK335: 10000 | BL335: 10000 | BM335: 10000 | BN335: 10000 | BO335: 10000 | BP335: 10000 | BQ335: 10000 | BR335: 10000 | BS335: 10000 | BT335: 10000 | BU335: 10000 | BV335: 10000 | BW335: 10000 | BX335: 10000 | BY335: 10000 | BZ335: 10000 | CA335: 10000 | CB335: 10000 | CC335: 10000 | CD335: 10000 | CE335: 10000 | CF335: 10000 | CG335: 10000 | CH335: 10000 | CI335: 10000 | CJ335: 10000 | CK335: 10000 | CL335: 10000 | CM335: 10000 | CN335: 10000 | CO335: 10000 | CP335: 10000 | CQ335: 10000 | CR335: 0 | CS335: 0 | CT335: 0 | CU335: 0 | CV335: 0 | CW335: 0 | CX335: 0 | CY335: 0 | CZ335: 0 | DA335: 0 | DB335: 0 | DC335: 0 | DD335: 0 | DE335: 0 | DF335: 0 | DG335: 0 | DH335: 0 | DI335: 0 | DJ335: 0 | DK335: 0 | DL335: 0 | DM335: 0 | DN335: 0 | DO335: 0 | DP335: 0 | DQ335: 0 | DR335: 0 | DS335: 0 | DT335: 0 | DU335: 0 | DV335: 0 | DW335: 0 | DX335: 0
M336: 56 | N336: SDJ20 | O336: 1 | P336: 8 | Q336: =N336&TEXT(O336,"00")&TEXT(P336,"00") -> SDJ200108 | R336: 10000 | S336: 10000 | T336: 10000 | U336: 10000 | V336: 10000 | W336: 10000 | X336: 10000 | Y336: 10000 | Z336: 10000 | AA336: 10000 | AB336: 10000 | AC336: 10000 | AD336: 10000 | AE336: 10000 | AF336: 10000 | AG336: 10000 | AH336: 10000 | AI336: 10000 | AJ336: 10000 | AK336: 10000 | AL336: 10000 | AM336: 10000 | AN336: 10000 | AO336: 10000 | AP336: 10000 | AQ336: 10000 | AR336: 10000 | AS336: 10000 | AT336: 10000 | AU336: 10000 | AV336: 10000 | AW336: 10000 | AX336: 10000 | AY336: 10000 | AZ336: 10000 | BA336: 10000 | BB336: 10000 | BC336: 10000 | BD336: 10000 | BE336: 10000 | BF336: 10000 | BG336: 10000 | BH336: 10000 | BI336: 10000 | BJ336: 10000 | BK336: 10000 | BL336: 10000 | BM336: 10000 | BN336: 10000 | BO336: 10000 | BP336: 10000 | BQ336: 10000 | BR336: 10000 | BS336: 10000 | BT336: 10000 | BU336: 10000 | BV336: 10000 | BW336: 10000 | BX336: 10000 | BY336: 10000 | BZ336: 10000 | CA336: 10000 | CB336: 10000 | CC336: 10000 | CD336: 10000 | CE336: 10000 | CF336: 10000 | CG336: 10000 | CH336: 10000 | CI336: 10000 | CJ336: 10000 | CK336: 10000 | CL336: 10000 | CM336: 10000 | CN336: 10000 | CO336: 10000 | CP336: 10000 | CQ336: 0 | CR336: 0 | CS336: 0 | CT336: 0 | CU336: 0 | CV336: 0 | CW336: 0 | CX336: 0 | CY336: 0 | CZ336: 0 | DA336: 0 | DB336: 0 | DC336: 0 | DD336: 0 | DE336: 0 | DF336: 0 | DG336: 0 | DH336: 0 | DI336: 0 | DJ336: 0 | DK336: 0 | DL336: 0 | DM336: 0 | DN336: 0 | DO336: 0 | DP336: 0 | DQ336: 0 | DR336: 0 | DS336: 0 | DT336: 0 | DU336: 0 | DV336: 0 | DW336: 0 | DX336: 0
M337: 56 | N337: SDJ20 | O337: 1 | P337: 9 | Q337: =N337&TEXT(O337,"00")&TEXT(P337,"00") -> SDJ200109 | R337: 10000 | S337: 10000 | T337: 10000 | U337: 10000 | V337: 10000 | W337: 10000 | X337: 10000 | Y337: 10000 | Z337: 10000 | AA337: 10000 | AB337: 10000 | AC337: 10000 | AD337: 10000 | AE337: 10000 | AF337: 10000 | AG337: 10000 | AH337: 10000 | AI337: 10000 | AJ337: 10000 | AK337: 10000 | AL337: 10000 | AM337: 10000 | AN337: 10000 | AO337: 10000 | AP337: 10000 | AQ337: 10000 | AR337: 10000 | AS337: 10000 | AT337: 10000 | AU337: 10000 | AV337: 10000 | AW337: 10000 | AX337: 10000 | AY337: 10000 | AZ337: 10000 | BA337: 10000 | BB337: 10000 | BC337: 10000 | BD337: 10000 | BE337: 10000 | BF337: 10000 | BG337: 10000 | BH337: 10000 | BI337: 10000 | BJ337: 10000 | BK337: 10000 | BL337: 10000 | BM337: 10000 | BN337: 10000 | BO337: 10000 | BP337: 10000 | BQ337: 10000 | BR337: 10000 | BS337: 10000 | BT337: 10000 | BU337: 10000 | BV337: 10000 | BW337: 10000 | BX337: 10000 | BY337: 10000 | BZ337: 10000 | CA337: 10000 | CB337: 10000 | CC337: 10000 | CD337: 10000 | CE337: 10000 | CF337: 10000 | CG337: 10000 | CH337: 10000 | CI337: 10000 | CJ337: 10000 | CK337: 10000 | CL337: 10000 | CM337: 10000 | CN337: 10000 | CO337: 10000 | CP337: 0 | CQ337: 0 | CR337: 0 | CS337: 0 | CT337: 0 | CU337: 0 | CV337: 0 | CW337: 0 | CX337: 0 | CY337: 0 | CZ337: 0 | DA337: 0 | DB337: 0 | DC337: 0 | DD337: 0 | DE337: 0 | DF337: 0 | DG337: 0 | DH337: 0 | DI337: 0 | DJ337: 0 | DK337: 0 | DL337: 0 | DM337: 0 | DN337: 0 | DO337: 0 | DP337: 0 | DQ337: 0 | DR337: 0 | DS337: 0 | DT337: 0 | DU337: 0 | DV337: 0 | DW337: 0 | DX337: 0
M338: 56 | N338: SDJ20 | O338: 1 | P338: 10 | Q338: =N338&TEXT(O338,"00")&TEXT(P338,"00") -> SDJ200110 | R338: 10000 | S338: 10000 | T338: 10000 | U338: 10000 | V338: 10000 | W338: 10000 | X338: 10000 | Y338: 10000 | Z338: 10000 | AA338: 10000 | AB338: 10000 | AC338: 10000 | AD338: 10000 | AE338: 10000 | AF338: 10000 | AG338: 10000 | AH338: 10000 | AI338: 10000 | AJ338: 10000 | AK338: 10000 | AL338: 10000 | AM338: 10000 | AN338: 10000 | AO338: 10000 | AP338: 10000 | AQ338: 10000 | AR338: 10000 | AS338: 10000 | AT338: 10000 | AU338: 10000 | AV338: 10000 | AW338: 10000 | AX338: 10000 | AY338: 10000 | AZ338: 10000 | BA338: 10000 | BB338: 10000 | BC338: 10000 | BD338: 10000 | BE338: 10000 | BF338: 10000 | BG338: 10000 | BH338: 10000 | BI338: 10000 | BJ338: 10000 | BK338: 10000 | BL338: 10000 | BM338: 10000 | BN338: 10000 | BO338: 10000 | BP338: 10000 | BQ338: 10000 | BR338: 10000 | BS338: 10000 | BT338: 10000 | BU338: 10000 | BV338: 10000 | BW338: 10000 | BX338: 10000 | BY338: 10000 | BZ338: 10000 | CA338: 10000 | CB338: 10000 | CC338: 10000 | CD338: 10000 | CE338: 10000 | CF338: 10000 | CG338: 10000 | CH338: 10000 | CI338: 10000 | CJ338: 10000 | CK338: 10000 | CL338: 10000 | CM338: 10000 | CN338: 10000 | CO338: 0 | CP338: 0 | CQ338: 0 | CR338: 0 | CS338: 0 | CT338: 0 | CU338: 0 | CV338: 0 | CW338: 0 | CX338: 0 | CY338: 0 | CZ338: 0 | DA338: 0 | DB338: 0 | DC338: 0 | DD338: 0 | DE338: 0 | DF338: 0 | DG338: 0 | DH338: 0 | DI338: 0 | DJ338: 0 | DK338: 0 | DL338: 0 | DM338: 0 | DN338: 0 | DO338: 0 | DP338: 0 | DQ338: 0 | DR338: 0 | DS338: 0 | DT338: 0 | DU338: 0 | DV338: 0 | DW338: 0 | DX338: 0
M339: 56 | N339: SDJ20 | O339: 1 | P339: 11 | Q339: =N339&TEXT(O339,"00")&TEXT(P339,"00") -> SDJ200111 | R339: 10000 | S339: 10000 | T339: 10000 | U339: 10000 | V339: 10000 | W339: 10000 | X339: 10000 | Y339: 10000 | Z339: 10000 | AA339: 10000 | AB339: 10000 | AC339: 10000 | AD339: 10000 | AE339: 10000 | AF339: 10000 | AG339: 10000 | AH339: 10000 | AI339: 10000 | AJ339: 10000 | AK339: 10000 | AL339: 10000 | AM339: 10000 | AN339: 10000 | AO339: 10000 | AP339: 10000 | AQ339: 10000 | AR339: 10000 | AS339: 10000 | AT339: 10000 | AU339: 10000 | AV339: 10000 | AW339: 10000 | AX339: 10000 | AY339: 10000 | AZ339: 10000 | BA339: 10000 | BB339: 10000 | BC339: 10000 | BD339: 10000 | BE339: 10000 | BF339: 10000 | BG339: 10000 | BH339: 10000 | BI339: 10000 | BJ339: 10000 | BK339: 10000 | BL339: 10000 | BM339: 10000 | BN339: 10000 | BO339: 10000 | BP339: 10000 | BQ339: 10000 | BR339: 10000 | BS339: 10000 | BT339: 10000 | BU339: 10000 | BV339: 10000 | BW339: 10000 | BX339: 10000 | BY339: 10000 | BZ339: 10000 | CA339: 10000 | CB339: 10000 | CC339: 10000 | CD339: 10000 | CE339: 10000 | CF339: 10000 | CG339: 10000 | CH339: 10000 | CI339: 10000 | CJ339: 10000 | CK339: 10000 | CL339: 10000 | CM339: 10000 | CN339: 0 | CO339: 0 | CP339: 0 | CQ339: 0 | CR339: 0 | CS339: 0 | CT339: 0 | CU339: 0 | CV339: 0 | CW339: 0 | CX339: 0 | CY339: 0 | CZ339: 0 | DA339: 0 | DB339: 0 | DC339: 0 | DD339: 0 | DE339: 0 | DF339: 0 | DG339: 0 | DH339: 0 | DI339: 0 | DJ339: 0 | DK339: 0 | DL339: 0 | DM339: 0 | DN339: 0 | DO339: 0 | DP339: 0 | DQ339: 0 | DR339: 0 | DS339: 0 | DT339: 0 | DU339: 0 | DV339: 0 | DW339: 0 | DX339: 0
... M429: 56 | N429: SDJ20 | O429: 2 | P429: 50 | Q429: =N429&TEXT(O429,"00")&TEXT(P429,"00") -> SDJ200250 | R429: 10000 | S429: 10000 | T429: 10000 | U429: 10000 | V429: 10000 | W429: 10000 | X429: 10000 | Y429: 10000 | Z429: 10000 | AA429: 10000 | AB429: 10000 | AC429: 10000 | AD429: 10000 | AE429: 10000 | AF429: 10573.5 | AG429: 11278.4 | AH429: 11983.3 | AI429: 12688.2 | AJ429: 13393.1 | AK429: 14098 | AL429: 14098 | AM429: 14098 | AN429: 14098 | AO429: 14098 | AP429: 14098 | AQ429: 14098 | AR429: 14098 | AS429: 14098 | AT429: 14098 | AU429: 14098 | AV429: 14098 | AW429: 14098 | AX429: 14098 | AY429: 14098 | AZ429: 14098 | BA429: 0 | BB429: 0 | BC429: 0 | BD429: 0 | BE429: 0 | BF429: 0 | BG429: 0 | BH429: 0 | BI429: 0 | BJ429: 0 | BK429: 0 | BL429: 0 | BM429: 0 | BN429: 0 | BO429: 0 | BP429: 0 | BQ429: 0 | BR429: 0 | BS429: 0 | BT429: 0 | BU429: 0 | BV429: 0 | BW429: 0 | BX429: 0 | BY429: 0 | BZ429: 0 | CA429: 0 | CB429: 0 | CC429: 0 | CD429: 0 | CE429: 0 | CF429: 0 | CG429: 0 | CH429: 0 | CI429: 0 | CJ429: 0 | CK429: 0 | CL429: 0 | CM429: 0 | CN429: 0 | CO429: 0 | CP429: 0 | CQ429: 0 | CR429: 0 | CS429: 0 | CT429: 0 | CU429: 0 | CV429: 0 | CW429: 0 | CX429: 0 | CY429: 0 | CZ429: 0 | DA429: 0 | DB429: 0 | DC429: 0 | DD429: 0 | DE429: 0 | DF429: 0 | DG429: 0 | DH429: 0 | DI429: 0 | DJ429: 0 | DK429: 0 | DL429: 0 | DM429: 0 | DN429: 0 | DO429: 0 | DP429: 0 | DQ429: 0 | DR429: 0 | DS429: 0 | DT429: 0 | DU429: 0 | DV429: 0 | DW429: 0 | DX429: 0

Sheet PY
B2: 轉換金額 | C2: 10000
C3: 分期 | D3: ㄧ次
B4: 比例 | C4: =MIN(1,ROUND(輸入頁!$G$26,2)) -> 0 | D4: =1-C4 -> 1 | F4: 年 | G4: 1
B5: 分期最低金額 | C5: =$C$38 -> 20000 | D5: =$D$38 -> 200000 | F5: 半年 | G5: 2
B6: 分期期數 | C6: =輸入頁!$G$30 -> 24 | F6: 季 | G6: 4
B7: 利率 | C7: =$B$30 -> 0.02 | F7: 月 | G7: 12
B8: 期別 | C8: 月 | D8: =VLOOKUP($C$8,$F$4:$G$7,2,0) -> 12
B10: 精算公式→ | C10: =IF(C6=0,,C2*(1-(1+$C$7)^-(1/12))/(1-(1+$C$7)^-($C$6/12))) -> 424.62177 | D10: ←精算換算比例(每萬元)
C11: =(1-(1+$C$7)^-(1/12))/(1-(1+$C$7)^-($C$6/12)) -> 0.042462177 | D11: ←帶入換算比例(每元)
B15: 定期定額-本利攤還
B16: 給付金額/每期 | C16: =ROUND(PMT($C$7/$D$8,$C$6*$D$8,-$C$2*$C$4,,1),0) -> 0
B17: 給付總額 | C17: =C16*C6*D8 -> 0
B18: 給付比例 | C18: =PMT($C$7/$D$8,$C$6*$D$8,-$C$2,,1)/C2 -> 0.0043675263 | D18: ←自行計算換算比例
B20: 定額不定期
B21: 給付金額/每期 | C21: 550 | D21: ←帶入期付金額
B22: 給付總額 | C22: =C21*(($C$26*$D$8)+$C$27) -> 9900
B23: 給付比例 | C23: =$C$21/($C$2/$C$4) -> #DIV/0!
B24: 給付次數 | C24: =NPER($C$7/$D$8,$C$21,-$C$2,0,1) -> 18.447154
B25: 剩餘金額 | C25: =ROUND(C21*($C$24-ROUNDDOWN($C$24,0)),0) -> 246
B26: 給付年次 | C26: =ROUNDDOWN(ROUNDDOWN($C$24,0)/$D$8,0) -> 1 | D26: ←自行計算給付年月數
B27: ="給付"&C8&"次" -> 給付月次 | C27: =ROUNDDOWN($C$24,0)-($C$26*$D$8) -> 6 | D27: ="EX："&$C$26&" 年 "&IF($C$27=0,"",C27&" "&$C$8) -> EX：1 年 6 月
B29: 台幣=1，美元=2，澳幣=3 | C29: =OP!$C$21 -> 1 | D29: 新臺幣 | E29: ←設定幣別
B30: =IF($C$29=1,$C$31,IF($C$29=2,$D$31,$E$31)) -> 0.02 | C30: 台幣 | D30: 美元 | E30: 澳幣
C31: 0.02 | D31: 0.025 | E31: 0.0275
B37: 分期低額 | C37: 每期 | D37: 指定
B38: =OP!$C$21 -> 1 | C38: =VLOOKUP(B38,$B$39:$D$40,2,0) -> 20000 | D38: =VLOOKUP(B38,$B$39:$D$40,3,0) -> 200000
B39: 2 | C39: 3000 | D39: 30000 | E39: =NUMBERSTRING(IF(C39/10000<1,C39/1000,C39/10000),3)&RIGHT(NUMBERSTRING(C39,2),1) -> 三仟 | F39: =NUMBERSTRING(IF(D39/10000<1,D39/1000,D39/10000),1)&RIGHT(NUMBERSTRING(D39,2),1) -> 三萬
B40: 1 | C40: 20000 | D40: 200000 | E40: =NUMBERSTRING(IF(C40/10000<1,C40/1000,C40/10000),3)&RIGHT(NUMBERSTRING(C40,2),1) -> 二萬 | F40: =NUMBERSTRING(IF(D40/10000<1,D40/1000,D40/10000),1)&RIGHT(NUMBERSTRING(D40,2),1) -> 二十萬
B41: 3 | E41: =NUMBERSTRING(IF(C41/10000<1,C41/1000,C41/10000),3)&RIGHT(NUMBERSTRING(C41,2),1) -> ○零 | F41: =NUMBERSTRING(IF(D41/10000<1,D41/1000,D41/10000),1)&RIGHT(NUMBERSTRING(D41,2),1) -> ○零
B42: 4 | E42: =NUMBERSTRING(IF(C42/10000<1,C42/1000,C42/10000),3)&RIGHT(NUMBERSTRING(C42,2),1) -> ○零 | F42: =NUMBERSTRING(IF(D42/10000<1,D42/1000,D42/10000),1)&RIGHT(NUMBERSTRING(D42,2),1) -> ○零
B43: =IF(OR(AND($D$29=$B$45,$C$29<>1),ISERROR(VLOOKUP($D$29,$B$45:$D$48,3,0))),"商品幣別設定錯誤",VLOOKUP($D$29,$B$45:$D$48,3,0)) -> 二十萬元或每月給付之分期定期保險金低於二萬元者， | C43: =IF(OR(AND($D$29=$B$45,$C$29<>1),ISERROR(VLOOKUP($D$29,$B$45:$D$48,3,0))),1,0) -> 0
B45: 新臺幣 | C45: 1 | D45: =VLOOKUP($C$45,$B$39:$F$42,5,0)&"元"&"或每月給付之分期定期保險金低於"&VLOOKUP($C$45,$B$39:$F$42,4,0)&"元"&"者，" -> 二十萬元或每月給付之分期定期保險金低於二萬元者，
B46: 美元 | C46: 2 | D46: =VLOOKUP($C$46,$B$39:$F$42,5,0)&$B$46&"或每月給付之分期定期保險金低於"&VLOOKUP($C$46,$B$39:$F$42,4,0)&$B$46&"者，" -> 三萬美元或每月給付之分期定期保險金低於三仟美元者，
B47: 澳幣 | C47: 3 | D47: =VLOOKUP($C$47,$B$39:$F$42,5,0)&$B$47&"或每月給付之分期定期保險金低於"&VLOOKUP($C$47,$B$39:$F$42,4,0)&$B$47&"者，" -> ○零澳幣或每月給付之分期定期保險金低於○零澳幣者，
B48: 人民幣 | C48: 4 | D48: =VLOOKUP($C$48,$B$39:$F$42,5,0)&$B$48&"或每月給付之分期定期保險金低於"&VLOOKUP($C$48,$B$39:$F$42,4,0)&$B$48&"者，" -> ○零人民幣或每月給付之分期定期保險金低於○零人民幣者，

Sheet OP
P1: 文字區域
B2: fubon | C2: 試算日 | D2: 生日 | E2: 驗證 | H2: 彈性繳 | I2: 1 | J2: 1 | K2: 1 | P2: 0 | Q2: 註： | AD2: =IF(AE2="","",MAX($AD$1:AD1)+1) | AL2: =$C$69 -> 業務、服展、北富銀
B3: =IF(C4=0,0,VALUE(MID(C4,IF(LEN(C4)=7,4,3),2))) -> 7 | C3: =IF(TODAY()<DATE(2026,1,1),DATE(2026,1,1),TODAY()) -> 46023 | D3: =IF(C4=0,0,DATE(LEFT(C4,IF(LEN(C4)=7,3,2))+1911,MID(C4,IF(LEN(C4)=7,4,3),2),RIGHT(C4,2))) -> 45839 | E3: =N(DAY(DATE(LEFT(C4,IF(LEN(C4)=7,3,2))+1911,MID(C4,IF(LEN(C4)=7,4,3),2)+1,0))) -> 31 | H3: 躉繳 | I3: 1 | J3: 1 | K3: 1 | P3: =IF(Q3="","",MAX($P$2:P2)+1) -> 1 | Q3: =IF(AND(C46=0,C47=0),"","‧上表年度實繳保費已扣除保費折扣，繳費期內如不符保費折扣條件，上表將不適用。") -> ‧上表年度實繳保費已扣除保費折扣，繳費期內如不符保費折扣條件，上表將不適用。 | AD3: =IF(AE3="","",MAX($AD$1:AD2)+1) | AL3: 業務、服展、北富銀 | AM3: 業務、服展 | AN3: 北富銀 | AO3: 整銷 | AP3: 多元
B4: 生日 | C4: =IF(C9=1,C10,IF(C9=2,VALUE(C11&TEXT(C12,"00")&TEXT(C13,"00")),"")) -> 1140701 | D4: =DATE(YEAR(C3)-$C$15,MONTH(C3)-6,DAY(C3)) -> 27576 | E4: =IF(OR(B3<1,B3>12),1,"") | F4: =YEAR($D$4)-1911 -> 64 | H4: 年繳 | I4: 1 | J4: 1 | K4: 1 | P4: =IF(Q4="","",MAX($P$2:P3)+1) -> 2 | Q4: ‧上表所列之各項數值，係指各保單年度末之數值。本保險契約若辦理減額繳清保險時，上表將不適用。 | AD4: =IF(AE4="","",MAX($AD$1:AD3)+1) | AK4: =IF(OR($AL4="",COUNTIF($AL$3:$AR$3,$AL$2)=0),"",MAX($AK$3:AK3)+1) -> 1 | AL4: 富邦人壽保險股份有限公司履行個人資料保護法告知說明書
B5: 最高承保 | C5: 保險 | D5: =IF(SUM(E6,D10:D13)>=1,"生日格式錯誤",IF(D3>C3,"被保險人未出生",IF(MONTH(C3)<B3,IF(OR(MONTH(C3)+12-B3>6,AND(MONTH(C3)+12-B3=6,DAY(C3)>DAY(D3))),YEAR(C3)-1-YEAR(D3)+1,IF(OR(MONTH(C3)+12-B3<6,AND(MONTH(C3)+12-B3=6,DAY(C3)<=DAY(D3))),YEAR(C3)-1-YEAR(D3))),IF(OR(MONTH(C3)-B3>6,AND(MONTH(C3)-B3=6,DAY(C3)>DAY(D3))),YEAR(C3)-YEAR(D3)+1,IF(OR(MONTH(C3)-B3<=6,AND(MONTH(C3)-B3=6,DAY(C3)<=DAY(D3))),YEAR(C3)-YEAR(D3),))))) -> 0 | E5: =IF(OR(VALUE(RIGHT(C4,2))<1,VALUE(RIGHT(C4,2))>E3),1,"") | F5: =MONTH($D$4) -> 7 | H5: 半年繳 | I5: 0.52 | J5: 0.5 | K5: 2 | P5: =IF(Q5="","",MAX($P$2:P4)+1) -> 3 | Q5: ‧上表數值為從未申領老年住院醫療提前給付保險金之數值，如有申領過老年住院醫療提前給付保險金者上表將不適 | AD5: =IF(AE5="","",MAX($AD$1:AD4)+1) | AK5: =IF(OR($AL5="",COUNTIF($AL$3:$AR$3,$AL$2)=0),"",MAX($AK$3:AK4)+1) -> 2
C6: 足歲 | D6: =IF(SUM(E6,D10:D13)>=1,"生日格式錯誤",IF(D3>C3,"被保險人未出生",DATEDIF(D3,C3,"y"))) -> 0 | E6: =IF(OR(E4=1,E5=1),1,"") | F6: =DAY($D$4) -> 1 | H6: 季繳 | I6: 0.262 | J6: 0.25 | K6: 4 | P6: =IF(Q6="","",MAX($P$2:P5)+1) -> 4 | Q6: 用，老年住院醫療提前給付保險金申領之條件及限制請詳閱保單條款說明。 | AD6: =IF(AE6="","",MAX($AD$1:AD5)+1) | AK6: =IF(OR($AL6="",COUNTIF($AL$3:$AR$3,$AL$2)=0),"",MAX($AK$3:AK5)+1) -> 3 | AL6: 富邦人壽保險股份有限公司（下稱本公司）依據個人資料保護法（以下稱個資法）
F7: =F4&TEXT(F5,"00")&TEXT(F6,"00") -> 640701 | H7: 月繳 | I7: 0.088 | J7: 0.08333333 | K7: 12 | P7: =IF(Q7="","",MAX($P$2:P6)+1) -> 5 | Q7: ‧身故保險金若被保險人未滿十五足歲前身故者，將以「所繳保險費加計利息」退還予要保人。 | AD7: =IF(AE7="","",MAX($AD$1:AD6)+1) | AK7: =IF(OR($AL7="",COUNTIF($AL$3:$AR$3,$AL$2)=0),"",MAX($AK$3:AK6)+1) -> 4 | AL7: 規定，向 台端告知下列事項，請 台端詳閱：
K8: 第一頁說明↓ | L8: 警語↓ | M8: =COUNTA(L11:L12) -> 2 | P8: =IF(Q8="","",MAX($P$2:P7)+1) -> 6 | Q8: ‧上表保險年齡15歲以下(含15歲)之身故/完全失能保障數值，為按年繳計算之所繳保險費總和，不含加計利息的部分， | AD8: =IF(AE8="","",MAX($AD$1:AD7)+1) | AK8: =IF(OR($AL8="",COUNTIF($AL$3:$AR$3,$AL$2)=0),"",MAX($AK$3:AK7)+1) -> 5 | AL8: 一、蒐集之目的：
B9: 輸入格式選項 | C9: 1 | D9: 檢核欄位 | H9: 折扣使用 | I9: 首期 | J9: 續期 | K9: =K10&M10&K11&M11&K12&M12&K13&M13&"。"&D47 -> 首、續期繳費方式 1%折扣。 | L9: =L10&M10&L11&M11&L12&M12&L13&"折扣" -> 繳費方式折扣 | P9: =IF(Q9="","",MAX($P$2:P8)+1) -> 7 | Q9: 若有加計利息，則實際理賠金額依條款約定辦理。 | AD9: =IF(AE9="","",MAX($AD$1:AD8)+1) | AK9: =IF(OR($AL9="",COUNTIF($AL$3:$AR$3,$AL$2)=0),"",MAX($AK$3:AK8)+1) -> 6 | AL9: （一）人身保險（００一）
B10: 1.輸入格式1-6或7位數字輸入 | C10: =BD -> 1140701 | D10: =IF(AND($C$9=1,OR(C10="",C10=0)),1,"") | G10: 1 | H10: 繳費方式 | I10: =$C$42 -> 0.01 | J10: =$C$44 -> 0.01 | K10: =IF(AND(I10>0,J10>0),"首、續期"&H10&TEXT(I10," 0%")&"折扣",IF(AND(I10>0,J10=0),"首期"&H10&TEXT(I10," 0%")&"折扣",IF(AND(I10=0,J10>0),"續期"&H10&TEXT(J10," 0%")&"折扣",""))) -> 首、續期繳費方式 1%折扣 | L10: =IF(SUM(I10:J10)>0,H10,"") -> 繳費方式 | M10: =IF(L10="","",IF(SUM(N11:N13)>=2,"、",IF(SUM(N11:N13)=1,"及",""))) | N10: =IF(L10<>"",1,0) -> 1 | P10: =IF(Q10="","",MAX($P$2:P9)+1) | AD10: =IF(AE10="","",MAX($AD$1:AD9)+1) | AK10: =IF(OR($AL10="",COUNTIF($AL$3:$AR$3,$AL$2)=0),"",MAX($AK$3:AK9)+1) -> 7 | AL10: （二）其他經營合於營業登記項目或組織章程所定之業務（一八一）
B11: 2.輸入格式2-年月日 | D11: =IF(AND($C$9=2,OR(C11="",C11=0)),1,"") | G11: 2 | H11: 高保額 | I11: =$C$37 -> 0 | J11: =$C$37 -> 0 | K11: =IF(AND(I11>0,J11>0),"首、續期"&H11&TEXT(I11," 0%")&"折扣",IF(AND(I11>0,J11=0),"首期"&H11&TEXT(I11," 0%")&"折扣",IF(AND(I11=0,J11>0),"續期"&H11&TEXT(J11," 0%")&"折扣",""))) | L11: =IF(SUM(I11:J11)>0,H11,"") | M11: =IF(L11="","",IF(SUM(N12:N14)>=2,"、",IF(SUM(N12:N14)=1,"及",""))) | N11: =IF(L11<>"",1,0) -> 0 | P11: =IF(Q11="","",MAX($P$2:P10)+1) | AD11: =IF(AE11="","",MAX($AD$1:AD10)+1) | AK11: =IF(OR($AL11="",COUNTIF($AL$3:$AR$3,$AL$2)=0),"",MAX($AK$3:AK10)+1) -> 8 | AL11: 二、蒐集之個人資料類別：
D12: =IF(AND($C$9=2,OR(C12="",C12<1,C12>12)),1,"") | G12: 3 | H12: 集體彙繳件 | I12: =$C$38 -> 0 | J12: =$C$39 -> 0 | K12: =IF(AND(I12>0,J12>0),"首、續期"&H12&TEXT(I12," 0%")&"折扣",IF(AND(I12>0,J12=0),"首期"&H12&TEXT(I12," 0%")&"折扣",IF(AND(I12=0,J12>0),"續期"&H12&TEXT(J12," 0%")&"折扣",""))) | L12: =IF(SUM(I12:J12)>0,H12,"") | M12: =IF(L12="","",IF(SUM(N13:N15)>=2,"、",IF(SUM(N13:N15)=1,"及",""))) | N12: =IF(L12<>"",1,0) -> 0 | P12: =IF(Q12="","",MAX($P$2:P11)+1) | AD12: =IF(AE12="","",MAX($AD$1:AD11)+1) | AK12: =IF(OR($AL12="",COUNTIF($AL$3:$AR$3,$AL$2)=0),"",MAX($AK$3:AK11)+1) -> 9 | AL12: （一）姓名。
D13: =IF(AND($C$9=2,OR(C13="",C13<1,C13>E3)),1,"") | G13: 4 | H13: 員工轉帳件 | I13: =$C$40 -> 0 | J13: =$C$40 -> 0 | K13: =IF(AND(I13>0,J13>0),"首、續期"&H13&TEXT(I13," 0%")&"折扣",IF(AND(I13>0,J13=0),"首期"&H13&TEXT(I13," 0%")&"折扣",IF(AND(I13=0,J13>0),"續期"&H13&TEXT(J13," 0%")&"折扣",""))) | L13: =IF(SUM(I13:J13)>0,H13,"") | M13: =IF(L13="","",IF(SUM(N14:N16)>=2,"、",IF(SUM(N14:N16)=1,"及",""))) | N13: =IF(L13<>"",1,0) -> 0 | P13: =IF(Q13="","",MAX($P$2:P12)+1) | AD13: =IF(AE13="","",MAX($AD$1:AD12)+1) | AK13: =IF(OR($AL13="",COUNTIF($AL$3:$AR$3,$AL$2)=0),"",MAX($AK$3:AK12)+1) -> 10 | AL13: （二）身分證統一編號。
B14: 生日檢核 | D14: =IF(SUM(E6,D10:D13)>=1,"*日期空白或格式錯誤*","") | P14: =IF(Q14="","",MAX($P$2:P13)+1) | AD14: =IF(AE14="","",MAX($AD$1:AD13)+1) | AK14: =IF(OR($AL14="",COUNTIF($AL$3:$AR$3,$AL$2)=0),"",MAX($AK$3:AK13)+1) -> 11 | AL14: （三）地址。
B15: 最高承保(保險年齡) | C15: =IF($C$22="",,VLOOKUP($C$24,$H$51:$J$54,3,FALSE)) -> 50 | D15: =IF(D5>C15,1,"") | K15: 繳費方式、高保額及集體彙繳件折扣 | P15: =IF(Q15="","",MAX($P$2:P14)+1) | AD15: =IF(AE15="","",MAX($AD$1:AD14)+1) | AK15: =IF(OR($AL15="",COUNTIF($AL$3:$AR$3,$AL$2)=0),"",MAX($AK$3:AK14)+1) -> 12 | AL15: （四）病歷、醫療、健康檢查 。
B16: ="最低承保"&IF(E16=1,"(足歲)","(保險年齡)") -> 最低承保(保險年齡) | C16: =IF($C$22="",,VLOOKUP($C$24,H51:J54,2,FALSE)) -> 0 | D16: =IF(IF(E16=1,D6,IF(E16=2,D5,0))<C16,1,"") | E16: 2 | K16: 高保額及員工轉帳件折扣 | P16: =IF(Q16="","",MAX($P$2:P15)+1) | AD16: =IF(AE16="","",MAX($AD$1:AD15)+1) | AK16: =IF(OR($AL16="",COUNTIF($AL$3:$AR$3,$AL$2)=0),"",MAX($AK$3:AK15)+1) -> 13 | AL16: （五）要保書、要保文件等其他基於保險契約所提供之個人資料。
B17: 年齡檢核 | D17: =IF(SUM(D15:D16)>=1,"*年齡不符專案投保區間*","") | H17: =IF($C$24=1,"躉繳","躉繳") -> 躉繳 | K17: 繳費方式及高保額折扣 | P17: =IF(Q17="","",MAX($P$2:P16)+1) | AD17: =IF(AE17="","",MAX($AD$1:AD16)+1) | AK17: =IF(OR($AL17="",COUNTIF($AL$3:$AR$3,$AL$2)=0),"",MAX($AK$3:AK16)+1) -> 14 | AL17: 三、個人資料利用之期間、地區、對象、方式：
B18: 性別 (1.男 2.女) | C18: =IF(輸入頁!$K$5="男",1,IF(輸入頁!$K$5="女",2,0)) -> 1 | D18: =IF(OR(C18="",C18<=0,C18>=3),1,"") | H18: =IF($C$24=1,"年繳","年繳") -> 年繳 | K18: 高保額及集體彙繳件折扣 | P18: =IF(Q18="","",MAX($P$2:P17)+1) | AD18: =IF(AE18="","",MAX($AD$1:AD17)+1) | AK18: =IF(OR($AL18="",COUNTIF($AL$3:$AR$3,$AL$2)=0),"",MAX($AK$3:AK17)+1) -> 15 | AL18: （一）期間：因執行業務所必須及依法令規定應為保存之期間。
B19: 性別檢核 | D19: =IF(D18=1,"*性別輸入錯誤*","") | H19: =IF($C$24=1,"半年繳","半年繳") -> 半年繳 | K19: 繳費方式及集體彙繳件折扣 | P19: =IF(Q19="","",MAX($P$2:P18)+1) | AD19: =IF(AE19="","",MAX($AD$1:AD18)+1) | AK19: =IF(OR($AL19="",COUNTIF($AL$3:$AR$3,$AL$2)=0),"",MAX($AK$3:AK18)+1) -> 16 | AL19: （二）對象：本公司、中華民國人壽保險商業同業公會、財團法人保險事業發展
B20: 基本資料欄位檢核結果 | D20: =IF(SUM(E6,D10:D13,D18)>=1,1,"") | H20: =IF($C$24=1,"季繳","季繳") -> 季繳 | P20: =IF(Q20="","",MAX($P$2:P19)+1) | AD20: =IF(AE20="","",MAX($AD$1:AD19)+1) | AK20: =IF(OR($AL20="",COUNTIF($AL$3:$AR$3,$AL$2)=0),"",MAX($AK$3:AK19)+1) -> 17 | AL20: 中心、財團法人金融消費評議中心、業務委外機構、臺灣網路認證(股)公司、
B21: 計價幣別(1.台幣 2.外幣) | C21: 1 | D21: =IF(OR(C21="",C21<=0,C21>=3),1,"") | E21: 新臺幣 | H21: =IF($C$24=1,"月繳","月繳") -> 月繳 | P21: =IF(Q21="","",MAX($P$2:P20)+1) | AD21: =IF(AE21="","",MAX($AD$1:AD20)+1) | AK21: =IF(OR($AL21="",COUNTIF($AL$3:$AR$3,$AL$2)=0),"",MAX($AK$3:AK20)+1) -> 18 | AL21: 與本公司有再保業務往來之公司、依法有調查權機關或金融監理機關。
B22: 險種代號 | C22: =IF(YPN<>I58,"",YPN) -> SDJ | D22: =IF(OR(C22="",C22=0,AND(C22<>K39,C22<>K40)),1,"") | P22: =IF(Q22="","",MAX($P$2:P21)+1) | AD22: =IF(AE22="","",MAX($AD$1:AD21)+1) | AK22: =IF(OR($AL22="",COUNTIF($AL$3:$AR$3,$AL$2)=0),"",MAX($AK$3:AK21)+1)
B23: 商品中文名稱 | C23: 富邦人壽優卡安心重大傷病健康保險 | E23: 繳費年期 | AD23: =IF(AE23="","",MAX($AD$1:AD22)+1) | AK23: =IF(OR($AL23="",COUNTIF($AL$3:$AR$3,$AL$2)=0),"",MAX($AK$3:AK22)+1) -> 19 | AL23: （三）地區：上述對象所在之地區。
B24: 年期 | C24: =IF($C$22="",,輸入頁!$D$33) -> 20 | D24: =IF(OR(C24="",C24=0,COUNTIF(H39:J41,C24)=0),1,"") | E24: =IF($C$22="",,IF(OP!C24=1,"(躉繳)",IF(OP!$C$24>40,"繳費至"&OP!$C$24&"歲滿期","繳費"&OP!$C$24&"年"))) -> 繳費20年 | AD24: =IF(AE24="","",MAX($AD$1:AD23)+1) | AK24: =IF(OR($AL24="",COUNTIF($AL$3:$AR$3,$AL$2)=0),"",MAX($AK$3:AK23)+1) -> 20 | AL24: （四）方式：合於法令規定之利用方式。
B25: 年期檢核 | D25: =IF(SUM(D24)>=1,"*年期選擇錯誤*","") | E25: =COUNTIF(H39:J41,C24) -> 1 | H25: =輸入頁!$E$20 -> 無 | I25: =VLOOKUP(H25,H26:I28,2,0) -> 1 | AD25: =IF(AE25="","",MAX($AD$1:AD24)+1) | AK25: =IF(OR($AL25="",COUNTIF($AL$3:$AR$3,$AL$2)=0),"",MAX($AK$3:AK24)+1) -> 21 | AL25: 四、依據個資法第三條規定，台端就本公司保有 台端之個人資料得行使之權利及
B26: 最低保額 | C26: =IF($C$22="",,VLOOKUP($C$24,$H$61:$L$64,$H$58+1,FALSE)) -> 10 | H26: 無 | I26: 1 | AD26: =IF(AE26="","",MAX($AD$1:AD25)+1) | AK26: =IF(OR($AL26="",COUNTIF($AL$3:$AR$3,$AL$2)=0),"",MAX($AK$3:AK25)+1) -> 22 | AL26: 方式：
B27: 最高保額 | C27: =IF($C$22="",,VLOOKUP($C$24,$H$61:$L$64,$H$58+2,FALSE)) -> 500 | E27: 保額小數位數 | H27: 集體彙繳件 | I27: 2 | AD27: =IF(AE27="","",MAX($AD$1:AD26)+1) | AK27: =IF(OR($AL27="",COUNTIF($AL$3:$AR$3,$AL$2)=0),"",MAX($AK$3:AK26)+1) -> 23 | AL27: （一）得向本公司行使之權利：
B28: 保額 | C28: =ROUND(輸入頁!J35,1) -> 10 | D28: =IF(OR(C28="",C28=0,C28<C26,C28>C27),1,"") | E28: 1 | H28: 員工轉帳件 | I28: 3 | AD28: =IF(AE28="","",MAX($AD$1:AD27)+1) | AK28: =IF(OR($AL28="",COUNTIF($AL$3:$AR$3,$AL$2)=0),"",MAX($AK$3:AK27)+1) -> 24 | AL28: 1.向本公司查詢、請求閱覽或請求製給複製本。
B29: 保額檢核 | D29: =IF(SUM(D28)>=1,"*保額錯誤*","") | AD29: =IF(AE29="","",MAX($AD$1:AD28)+1) | AK29: =IF(OR($AL29="",COUNTIF($AL$3:$AR$3,$AL$2)=0),"",MAX($AK$3:AK28)+1) -> 25 | AL29: 2.向本公司請求補充或更正。
B30: 每萬保費 | C30: =IF(OR(C18=0,C22=0,D28=1),0,IF(ISNA(VLOOKUP($C$55,GP,2,0)),0,VLOOKUP($C$55,GP,2,0))) -> 239 | H30: 繳別 | I30: 折扣率 | L30: 首期 | M30: 續期 | AD30: =IF(AE30="","",MAX($AD$1:AD29)+1) | AK30: =IF(OR($AL30="",COUNTIF($AL$3:$AR$3,$AL$2)=0),"",MAX($AK$3:AK29)+1) -> 26 | AL30: 3.向本公司請求停止蒐集、處理或利用及請求刪除。
B31: 原始應繳保費 | C31: =IF($C$21=1,ROUND($C28*BGP,1),IF(C21=2,ROUND($C28*BGP,1),"")) -> 2390 | H31: 匯款 | I31: =IF($C$24=1,0,1%) -> 0.01 | J31: ↓首期 | L31: 匯款 | M31: =IF($C$24=1,"","金融機構轉帳") -> 金融機構轉帳 | AD31: =IF(AE31="","",MAX($AD$1:AD30)+1) | AK31: =IF(OR($AL31="",COUNTIF($AL$3:$AR$3,$AL$2)=0),"",MAX($AK$3:AK30)+1) -> 27 | AL31: （二）行使權利之方式：
B32: 繳別 | C32: =IF(PM="","",PM) -> 年繳 | D32: =IF(OR(C32="",C32=0,COUNTIF(繳,$C$32)<1),1,"") | E32: =IF($D$32=1,"繳別錯誤","") | H32: 金融機構轉帳 | I32: =IF($C$24=1,0,1%) -> 0.01 | J32: 續期↓ | L32: 金融機構轉帳 | M32: =IF($C$24=1,"","富邦信用卡") -> 富邦信用卡 | AD32: =IF(AE32="","",MAX($AD$1:AD31)+1) | AK32: =IF(OR($AL32="",COUNTIF($AL$3:$AR$3,$AL$2)=0),"",MAX($AK$3:AK31)+1) -> 28 | AL32: 您可以透過書面（包含電子郵件、傳真、電子文件）方式行使權利。
B33: 換算格式1.傳統 2.直接除 | C33: 1 | D33: =IF(OR(C33="",C33=0),1,"") | H33: 富邦信用卡 | I33: =IF($C$24=1,0,1%) -> 0.01 | L33: =IF($C$24=1,"支票","富邦信用卡") -> 富邦信用卡 | M33: =IF($C$24=1,"","一般信用卡") -> 一般信用卡 | AD33: =IF(AE33="","",MAX($AD$1:AD32)+1) | AK33: =IF(OR($AL33="",COUNTIF($AL$3:$AR$3,$AL$2)=0),"",MAX($AK$3:AK32)+1)
B34: 繳別換算率 | C34: =IF(D32=1,,VLOOKUP(C32,H2:K7,1+C33,FALSE)) -> 1 | H34: 一般信用卡 | I34: =IF($C$24=1,0,0%) -> 0 | J34: ↑首期 | L34: =IF($C$24=1,"","一般信用卡") -> 一般信用卡 | M34: =IF($C$24=1,"","收費") -> 收費 | AD34: =IF(AE34="","",MAX($AD$1:AD33)+1) | AK34: =IF(OR($AL34="",COUNTIF($AL$3:$AR$3,$AL$2)=0),"",MAX($AK$3:AK33)+1) -> 29 | AL34: 五、台端不提供個人資料所致權益之影響
B35: 應繳保費 | C35: =IF($C$21=1,ROUND(C31*C34,0),IF($C$21=2,ROUNDDOWN(C31*C34,0),"")) -> 2390 | D35: =IF($C$50=12,$C$35*2,$C$35*1) -> 2390 | E35: 月繳*2 ←1130126新增月繳倍數(紀錄單用) | H35: 支票 | I35: =IF($C$24=1,0,0%) -> 0 | L35: =IF($C$24=1,"","支票") -> 支票 | M35: =IF($C$24=1,"","自行繳費") -> 自行繳費 | AD35: =IF(AE35="","",MAX($AD$1:AD34)+1) | AK35: =IF(OR($AL35="",COUNTIF($AL$3:$AR$3,$AL$2)=0),"",MAX($AK$3:AK34)+1) -> 30 | AL35: 台端若未能提供相關個人資料時，本公司將可能延後或無法進行必要之審核
B36: 高保費折扣 | D36: 低<=保費<高 | H36: 自行繳費 | I36: =IF($C$24=1,0,1%) -> 0.01 | J36: 續期↑ | AD36: =IF(AE36="","",MAX($AD$1:AD35)+1) | AK36: =IF(OR($AL36="",COUNTIF($AL$3:$AR$3,$AL$2)=0),"",MAX($AK$3:AK35)+1) -> 31 | AL36: 及處理作業，因此可能婉謝承保、遲延或無法承保。
B37: 高保額折扣 | C37: 0 | H37: 收費 | I37: =IF($C$24=1,0,0%) -> 0 | AD37: =IF(AE37="","",MAX($AD$1:AD36)+1) | AK37: =IF(OR($AL37="",COUNTIF($AL$3:$AR$3,$AL$2)=0),"",MAX($AK$3:AK36)+1)
B38: 集彙折扣-首期 | C38: =IF(AND($C$24<>1,$I$25=2,OR(AND(OR(C41=H31,C41=H35),OR(C43=H32,C43=H33,C43=H34,C43=H36)),$C$41=$H$32,$C$41=$H$33,$C$41=$H$34)),2%,0%) -> 0 | D38: =IF(C38>0,"本主約首期保費享有 "&TEXT(C38,"0%")&" 集體彙繳折扣","") | H38: 年期 | K38: 險種 | AD38: =IF(AE38="","",MAX($AD$1:AD37)+1) | AK38: =IF(OR($AL38="",COUNTIF($AL$3:$AR$3,$AL$2)=0),"",MAX($AK$3:AK37)+1)
B39: 集彙折扣-續期 | C39: =IF(AND($C$24<>1,$I$25=2,OR($C$43=$H$32,$C$43=$H$33,$C$43=$H$34,$C$43=$H$36)),2%,0%) -> 0 | D39: =IF(C39>0,"本主約續期保費享有 "&TEXT(C39,"0%")&" 集體彙繳折扣","") | E39: =IF(C24=1,"",IF(AND(I25=3,OR(C41<>H32,AND(C43<>H32,C43<>H36))),1,"")) | F39: =IF($E$39=1,"已選定員工轉帳件資格，請確認繳費方式是否符合規定","") | H39: 20 | K39: SDJ | AD39: =IF(AE39="","",MAX($AD$1:AD38)+1) | AK39: =IF(OR($AL39="",COUNTIF($AL$3:$AR$3,$AL$2)=0),"",MAX($AK$3:AK38)+1)
B40: 員工折扣 | C40: =IF(AND($I$25=3,C41=H32,OR(C43=H32,C43=H36)),IF($C$24=10,5%,IF(OR($C$24=15,$C$24=20),5%,5%)),0%) -> 0 | D40: =IF(C40>0,"本保件享有 "&TEXT(C40,"0%")&" 員工轉帳件折扣","") | AD40: =IF(AE40="","",MAX($AD$1:AD39)+1) | AK40: =IF(OR($AL40="",COUNTIF($AL$3:$AR$3,$AL$2)=0),"",MAX($AK$3:AK39)+1)
B41: 首期繳別 | C41: =輸入頁!Q17 -> 匯款 | AD41: =IF(AE41="","",MAX($AD$1:AD40)+1) | AK41: =IF(OR($AL41="",COUNTIF($AL$3:$AR$3,$AL$2)=0),"",MAX($AK$3:AK40)+1)
B42: 自繳折扣-首期 | C42: =IF(OR(ISNA(VLOOKUP(C41,$H$30:$I$37,2,FALSE)),$C$40>0),0,VLOOKUP(C41,$H$30:$I$37,2,FALSE)) -> 0.01 | D42: =IF(C42>0,"-首期享有1%繳別折扣-","") -> -首期享有1%繳別折扣- | H42: 繳費年期 | I42: 保險期間 | AD42: =IF(AE42="","",MAX($AD$1:AD41)+1) | AK42: =IF(OR($AL42="",COUNTIF($AL$3:$AR$3,$AL$2)=0),"",MAX($AK$3:AK41)+1)
B43: 續期繳別 | C43: =輸入頁!Q19 -> 金融機構轉帳 | H43: 20 | L43: 健康管理保險費折扣項目 | M43: SDJ折扣率 | N43: ="SDJ續年度折扣後實繳保費"&IF($C$47>0,"(含續期繳費方式折扣"&TEXT($C$47,"0%")&")","") -> SDJ續年度折扣後實繳保費(含續期繳費方式折扣1%) | AD43: =IF(AE43="","",MAX($AD$1:AD42)+1) | AK43: =IF(OR($AL43="",COUNTIF($AL$3:$AR$3,$AL$2)=0),"",MAX($AK$3:AK42)+1)
B44: 自繳折扣-續期 | C44: =IF(OR(ISNA(VLOOKUP(C43,$H$30:$I$37,2,FALSE)),$C$40>0),0,VLOOKUP(C43,$H$30:$I$37,2,FALSE)) -> 0.01 | D44: =IF(C44>0,"-續期享有1%繳別折扣-","") -> -續期享有1%繳別折扣- | L44: 指定疫苗接種或健康檢查 | M44: 0.01 | N44: =ROUND($C$35*(1-($C$47+$M$44)),0) -> 2342 | AD44: =IF(AE44="","",MAX($AD$1:AD43)+1) | AK44: =IF(OR($AL44="",COUNTIF($AL$3:$AR$3,$AL$2)=0),"",MAX($AK$3:AK43)+1)
B45: 折扣率上限 | C45: =IF($I$25=3,IF($C$24=10,5%,IF(OR($C$24=15,$C$24=20),5%,5%)),1%) -> 0.01 | D45: =IF(OR(C45="",),1,"") | AD45: =IF(AE45="","",MAX($AD$1:AD44)+1) | AK45: =IF(OR($AL45="",COUNTIF($AL$3:$AR$3,$AL$2)=0),"",MAX($AK$3:AK44)+1)
B46: 首期總折扣率 | C46: =MIN(SUM(C36:C37,C38,C40,C42),C45) -> 0.01 | D46: =IF(OR(C42>0,C44>0),"繳費方式折扣‧","")&IF(C37>0,"高保額折扣‧","")&IF(OR(C38>0,C39>0),"集體彙繳件折扣‧","")&IF(OR(C40>0),"員工轉帳件折扣‧","") -> 繳費方式折扣‧ | AD46: =IF(AE46="","",MAX($AD$1:AD45)+1) | AL46: 保經代 | AM46: 錠嵂保經 | AN46: 銀保
B47: 續期總折扣率 | C47: =MIN(SUM(C37,C39,C40,C44),C45) -> 0.01 | D47: =IF(OR(C37+C38+C40+C42>C45,C37+C39+C44>C45),"本商品折扣率上限"&TEXT($C$45,"0%。"),"") | AD47: =IF(AE47="","",MAX($AD$1:AD46)+1) | AK47: =IF(OR($AL47="",COUNTIF($AL$46:$AR$46,$AL$2)=0),"",MAX($AK$3:AK46)+1) | AL47: 富邦人壽保險股份有限公司履行個人資料保護法告知說明書
B48: 首期實繳保費 | C48: =ROUND(MGP*(1-C46),0) -> 2366 | AD48: =IF(AE48="","",MAX($AD$1:AD47)+1) | AK48: =IF(OR($AL48="",COUNTIF($AL$46:$AR$46,$AL$2)=0),"",MAX($AK$3:AK47)+1)
B49: 續期實繳保費 | C49: =ROUND(MGP*(1-C47),0) -> 2366 | D49: =IF($C$50=12,"-月繳首期須繳 2個月 "&TEXT($C$48*2,"#,##0 元-"),"") | AD49: =IF(AE49="","",MAX($AD$1:AD48)+1) | AK49: =IF(OR($AL49="",COUNTIF($AL$46:$AR$46,$AL$2)=0),"",MAX($AK$3:AK48)+1) | AL49: 富邦人壽保險股份有限公司（下稱本公司）依據個人資料保護法（以下稱個資法）
B50: 繳別回乘倍數 | C50: =IF(D32=1,,VLOOKUP(C32,H2:K7,4,FALSE)) -> 1 | E50: ←首期保費規則 | H50: 繳費年期 | I50: 最低年齡 | J50: 最高年齡 | AD50: =IF(AE50="","",MAX($AD$1:AD49)+1) | AK50: =IF(OR($AL50="",COUNTIF($AL$46:$AR$46,$AL$2)=0),"",MAX($AK$3:AK49)+1) | AL50: 規定，向 台端告知下列事項，請 台端詳閱：
B51: 首年實繳保費 | C51: =IF(C50=12,C48*2+C49*10,C48*1+C49*(C50-1)) -> 2366 | D51: 40831 | H51: 20 | I51: 0 | J51: 50 | AD51: =IF(AE51="","",MAX($AD$1:AD50)+1) | AK51: =IF(OR($AL51="",COUNTIF($AL$46:$AR$46,$AL$2)=0),"",MAX($AK$3:AK50)+1) | AL51: 一、蒐集之目的：
B52: 續年實繳保費 | C52: =C49*C50 -> 2366 | AD52: =IF(AE52="","",MAX($AD$1:AD51)+1) | AK52: =IF(OR($AL52="",COUNTIF($AL$46:$AR$46,$AL$2)=0),"",MAX($AK$3:AK51)+1) | AL52: （一）人身保險（００一）
B53: 主約1欄位檢核結果 | D53: =IF(SUM(D15:D16,D28,D32:D33,D40:D41,D43,D45,D50,D24,D64,E39)>=1,1,"") | AD53: =IF(AE53="","",MAX($AD$1:AD52)+1) | AK53: =IF(OR($AL53="",COUNTIF($AL$46:$AR$46,$AL$2)=0),"",MAX($AK$3:AK52)+1) | AL53: （二）其他經營合於營業登記項目或組織章程所定之業務（一八一）
B54: 版次 | C54: V1.2-1150101 | AD54: =IF(AE54="","",MAX($AD$1:AD53)+1) | AK54: =IF(OR($AL54="",COUNTIF($AL$46:$AR$46,$AL$2)=0),"",MAX($AK$3:AK53)+1) | AL54: 二、蒐集之個人資料類別：
B55: KEY | C55: =$C$22&$C$24&TEXT($C$18,"00")&TEXT($D$5,"00") -> SDJ200100 | D55: A險種+年期(2位)+性別(1位)+年齡(2位) | AD55: =IF(AE55="","",MAX($AD$1:AD54)+1) | AK55: =IF(OR($AL55="",COUNTIF($AL$46:$AR$46,$AL$2)=0),"",MAX($AK$3:AK54)+1) | AL55: （一）姓名。
B56: SUMKEY | C56: =IF($C$24=1,$C$22,C22&TEXT($C$24,"00")) -> SDJ20 | D56: F險種+年期(2位)+年齡(2位) | AD56: =IF(AE56="","",MAX($AD$1:AD55)+1) | AK56: =IF(OR($AL56="",COUNTIF($AL$46:$AR$46,$AL$2)=0),"",MAX($AK$3:AK55)+1) | AL56: （二）身分證統一編號。
B57: MAX-Y | C57: =$F$57+1-D5 -> 85 | E57: 保障至幾歲 | F57: 84 | AD57: =IF(AE57="","",MAX($AD$1:AD56)+1) | AK57: =IF(OR($AL57="",COUNTIF($AL$46:$AR$46,$AL$2)=0),"",MAX($AK$3:AK56)+1) | AL57: （三）地址。
H58: =IF(C22=I58,1,3) -> 1 | I58: SDJ | AD58: =IF(AE58="","",MAX($AD$1:AD57)+1) | AK58: =IF(OR($AL58="",COUNTIF($AL$46:$AR$46,$AL$2)=0),"",MAX($AK$3:AK57)+1) | AL58: （四）病歷、醫療、健康檢查 。
AD59: =IF(AE59="","",MAX($AD$1:AD58)+1) | AK59: =IF(OR($AL59="",COUNTIF($AL$46:$AR$46,$AL$2)=0),"",MAX($AK$3:AK58)+1) | AL59: （五）要保書、要保文件等其他基於保險契約所提供之個人資料。
H60: 繳費年期 | I60: 最低保額 | J60: 最高保額 | AD60: =IF(AE60="","",MAX($AD$1:AD59)+1) | AK60: =IF(OR($AL60="",COUNTIF($AL$46:$AR$46,$AL$2)=0),"",MAX($AK$3:AK59)+1) | AL60: 三、個人資料利用之期間、地區、對象、方式：
B61: 保費 | C61: =輸入頁!$E$48 -> 50000 | H61: 20 | I61: 10 | J61: =IF($D$16=1,0,VLOOKUP($D$5,$H$72:$I$146,2,0)) -> 500 | AD61: =IF(AE61="","",MAX($AD$1:AD60)+1) | AK61: =IF(OR($AL61="",COUNTIF($AL$46:$AR$46,$AL$2)=0),"",MAX($AK$3:AK60)+1) | AL61: （一）期間：因執行業務所必須及依法令規定應為保存之期間。
B62: 換算1 | C62: =ROUNDDOWN(C61/C30,$E$28) -> 209.2 | AD62: =IF(AE62="","",MAX($AD$1:AD61)+1) | AK62: =IF(OR($AL62="",COUNTIF($AL$46:$AR$46,$AL$2)=0),"",MAX($AK$3:AK61)+1) | AL62: （二）對象：本公司、中華民國人壽保險商業同業公會、財團法人保險事業發展
B63: 換算2加計折扣 | C63: =ROUNDDOWN((C61*(1+C46))/C30,$E$28) -> 211.2 | AD63: =IF(AE63="","",MAX($AD$1:AD62)+1) | AK63: =IF(OR($AL63="",COUNTIF($AL$46:$AR$46,$AL$2)=0),"",MAX($AK$3:AK62)+1) | AL63: 中心、財團法人金融消費評議中心、業務委外機構、臺灣網路認證(股)公司、
B64: 保額輸入檢核 | C64: =輸入頁!$J$35 -> 10 | D64: =IF(ROUND($C$64,$E$28)<>$C$64,1,"") | E64: =IF(D64=1,"保額輸入"&C64&"不符投保規則，請重新輸入","") | AD64: =IF(AE64="","",MAX($AD$1:AD63)+1) | AK64: =IF(OR($AL64="",COUNTIF($AL$46:$AR$46,$AL$2)=0),"",MAX($AK$3:AK63)+1) | AL64: 與本公司有再保業務往來之公司、依法有調查權機關或金融監理機關。
AD65: =IF(AE65="","",MAX($AD$1:AD64)+1) | AK65: =IF(OR($AL65="",COUNTIF($AL$46:$AR$46,$AL$2)=0),"",MAX($AK$3:AK64)+1) | AL65: （三）地區：上述對象所在之地區。
AD66: =IF(AE66="","",MAX($AD$1:AD65)+1) | AK66: =IF(OR($AL66="",COUNTIF($AL$46:$AR$46,$AL$2)=0),"",MAX($AK$3:AK65)+1) | AL66: （四）方式：合於法令規定之利用方式。
AD67: =IF(AE67="","",MAX($AD$1:AD66)+1) | AK67: =IF(OR($AL67="",COUNTIF($AL$46:$AR$46,$AL$2)=0),"",MAX($AK$3:AK66)+1) | AL67: 四、依據個資法第三條規定，台端就本公司保有 台端之個人資料得行使之權利及
AD68: =IF(AE68="","",MAX($AD$1:AD67)+1) | AK68: =IF(OR($AL68="",COUNTIF($AL$46:$AR$46,$AL$2)=0),"",MAX($AK$3:AK67)+1) | AL68: 方式：
B69: 適用通路： | C69: 業務、服展、北富銀 | D69: PB | F69: ←銀保通路判別使用 | AD69: =IF(AE69="","",MAX($AD$1:AD68)+1) | AK69: =IF(OR($AL69="",COUNTIF($AL$46:$AR$46,$AL$2)=0),"",MAX($AK$3:AK68)+1) | AL69: （一）得向本公司行使之權利：
AK70: =IF(OR($AL70="",COUNTIF($AL$46:$AR$46,$AL$2)=0),"",MAX($AK$3:AK69)+1) | AL70: 1.向本公司查詢、請求閱覽或請求製給複製本。
B71: 姓名遮蔽用：中/英/數混合：前6碼"*"，中文：倒數第2碼"○" | H71: 年齡-1 | I71: 最高保額-2 | AK71: =IF(OR($AL71="",COUNTIF($AL$46:$AR$46,$AL$2)=0),"",MAX($AK$3:AK70)+1) | AL71: 2.向本公司請求補充或更正。
B72: 姓名： | C72: =IN -> 客戶 | D72: ←輸入頁資料 | E72: 0 | H72: 0 | I72: 500 | AK72: =IF(OR($AL72="",COUNTIF($AL$46:$AR$46,$AL$2)=0),"",MAX($AK$3:AK71)+1) | AL72: 3.向本公司請求停止蒐集、處理或利用及請求刪除。
B73: 帶入資料 | C73: =IF(E72=0,C72,IF(OR(E73=1,C72="",C72=0)," ",IF(AND(E82=0),C74&MID(C72,7,50),IF(LEN(C72)=1,C72,LEFT(C72,LEN(C72)-2)&"○"&RIGHT(C72,1))))) -> 客戶 | D73: 判別不顯示(不判別) | H73: 1 | I73: 500 | AK73: =IF(OR($AL73="",COUNTIF($AL$46:$AR$46,$AL$2)=0),"",MAX($AK$3:AK72)+1) | AL73: （二）行使權利之方式：
B74: =IF(OR(E73=1,C72="",C72=0),"",IF(AND(E82=0),LEN(C72),"")) | C74: =IF(OR(B74=""),"",IF(ISERROR(VLOOKUP(B74,B75:C80,2,0)),C80,VLOOKUP(B74,B75:C80,2,0))) | D74: ID-11碼數字 | E74: =IF(AND(ISNUMBER(C72),LEN(C72)=11),1,0) -> 0 | H74: 2 | I74: 500 | AK74: =IF(OR($AL74="",COUNTIF($AL$46:$AR$46,$AL$2)=0),"",MAX($AK$3:AK73)+1) | AL74: 您可以透過書面（包含電子郵件、傳真、電子文件）方式行使權利。
B75: 1 | C75: * | D75: ID-10碼 | E75: =IF(AND(LEN(C72)=10,ISTEXT(LEFT(C72,1)),ISNUMBER(RIGHT(C72,1)*1)),1,0) -> 0 | H75: 3 | I75: 500 | AK75: =IF(OR($AL75="",COUNTIF($AL$46:$AR$46,$AL$2)=0),"",MAX($AK$3:AK74)+1)
B76: 2 | C76: ** | D76: 護照-9碼 | E76: =IF(AND(ISNUMBER(C72),LEN(C72)=9),1,0) -> 0 | H76: 4 | I76: 500 | AK76: =IF(OR($AL76="",COUNTIF($AL$46:$AR$46,$AL$2)=0),"",MAX($AK$3:AK75)+1) | AL76: 五、台端不提供個人資料所致權益之影響
B77: 3 | C77: *** | H77: 5 | I77: 500 | AK77: =IF(OR($AL77="",COUNTIF($AL$46:$AR$46,$AL$2)=0),"",MAX($AK$3:AK76)+1) | AL77: 台端若未能提供相關個人資料時，本公司將可能延後或無法進行必要之審核
B78: 4 | C78: **** | H78: 6 | I78: 500 | AK78: =IF(OR($AL78="",COUNTIF($AL$46:$AR$46,$AL$2)=0),"",MAX($AK$3:AK77)+1) | AL78: 及處理作業，因此可能婉謝承保、遲延或無法承保。
B79: 5 | C79: ***** | H79: 7 | I79: 500 | AK79: =IF(OR($AL79="",COUNTIF($AL$46:$AR$46,$AL$2)=0),"",MAX($AK$3:AK78)+1)
B80: 6 | C80: ****** | H80: 8 | I80: 500 | AK80: =IF(OR($AL80="",COUNTIF($AL$46:$AR$46,$AL$2)=0),"",MAX($AK$3:AK79)+1)
B81: 空格位置 | C81: =IF(OR(ISERROR(SEARCH(" ",C72)),CODE(C72)>255),"",SEARCH(" ",C72)) | H81: 9 | I81: 500 | AK81: =IF(OR($AL81="",COUNTIF($AL$46:$AR$46,$AL$2)=0),"",MAX($AK$3:AK80)+1)
B82: 簡寫 | C82: =IF(OR(ISERROR(SEARCH(" ",C72)),CODE(C72)>255),"",UPPER(LEFT(C72,1)&"."&MID(C72,C81+1,1))) | D82: 1-中文-0-混合 | E82: =IF(LEN(C72)*2=LENB(C72),1,0) -> 1 | H82: 10 | I82: 500 | AK82: =IF(OR($AL82="",COUNTIF($AL$46:$AR$46,$AL$2)=0),"",MAX($AK$3:AK81)+1)
H83: 11 | I83: 500 | AK83: =IF(OR($AL83="",COUNTIF($AL$46:$AR$46,$AL$2)=0),"",MAX($AK$3:AK82)+1)
H84: 12 | I84: 500 | AK84: =IF(OR($AL84="",COUNTIF($AL$46:$AR$46,$AL$2)=0),"",MAX($AK$3:AK83)+1)
B85: 提醒設定 | C85: 1 | D85: 0 | H85: 13 | I85: 500 | AK85: =IF(OR($AL85="",COUNTIF($AL$46:$AR$46,$AL$2)=0),"",MAX($AK$3:AK84)+1)
B86: 跳歲計算 | C86: =IF($D$53=1,"",DATE(YEAR($D$3)+$D$6,MONTH($D$3)+6,MIN(DAY($D$3),$E$86)+1)) -> 46024 | D86: =MONTH($D$3)+IF(MONTH($D$3)<=6,6,-6) -> 1 | E86: =IF(OR($D$86=1,$D$86=3,$D$86=5,$D$86=7,$D$86=8,$D$86=10,$D$86=12),31,IF(OR($D$86=4,$D$86=6,$D$86=9,$D$86=11),30,IF(AND($D$86=2,YEAR($C$3)/4=INT(YEAR($C$3)/4),YEAR($C$3)/400<>INT(YEAR($C$3)/400)),29,28))) -> 31 | H86: 14 | I86: 500 | AK86: =IF(OR($AL86="",COUNTIF($AL$46:$AR$46,$AL$2)=0),"",MAX($AK$3:AK85)+1)
C87: =IF($D$53=1,"",IF(C86<$C$3,"",C86-$C$3)) -> 1 | D87: =IF(C85=0,"",IF(OR($D$53=1,C87=""),"",IF(AND(C87>=1,C87<=30),"提醒您：被保險人將於 "&MONTH(C86)&" 月 "&DAY(C86)&" 日 ( "&C87&"天後 ) 保險年齡增加一歲"&IF(D85=0,"。","，"&$C$22&$C$32&"保險費"&IF($C$32="躉繳","","每期")&IF(E88>=0,"增加 ","減少 ")&TEXT(E88,"#,##0 元")&"。"),""))) -> 提醒您：被保險人將於 1 月 2 日 ( 1天後 ) 保險年齡增加一歲。 | H87: 15 | I87: 500 | AK87: =IF(OR($AL87="",COUNTIF($AL$46:$AR$46,$AL$2)=0),"",MAX($AK$3:AK86)+1)
B88: 新年齡/保費/差異 | C88: =C22&TEXT($C$24,"00")&TEXT($C$18,"00")&TEXT($D$5,"00") -> SDJ200100 | D88: =IF(ISNA(VLOOKUP(C88,GP,2,0)),0,ROUND((VLOOKUP(C88,GP,2,0)*$C$28)*$C$34,0)) -> 2390 | E88: =D88-$C$35 -> 0 | H88: 16 | I88: 500 | AK88: =IF(OR($AL88="",COUNTIF($AL$46:$AR$46,$AL$2)=0),"",MAX($AK$3:AK87)+1)
H89: 17 | I89: 500 | AK89: =IF(OR($AL89="",COUNTIF($AL$46:$AR$46,$AL$2)=0),"",MAX($AK$3:AK88)+1)
B90: 全列印頁面使用 | C90: 更新區域 | D90: 帶入內容區域 | E90: OLD/說明 | H90: 18 | I90: 500 | AK90: =IF(OR($AL90="",COUNTIF($AL$46:$AR$46,$AL$2)=0),"",MAX($AK$3:AK89)+1)
