Workbook
Name BD: 輸入頁!$E$7
Name BGP: OP!$C$30
Name CV: P_DATA!$Q$427:$DX$844
Name DIE: P_DATA!$ED$2:$IK$420
Name EXP: P_DATA!$Q$2:$DX$420
Name GP: P_DATA!$J:$K
Name GP_PY: 年度保費_階梯!$B$3:$H$114
Name HL_1: P_DATA!$Q$850:$DX$1267
Name HL_2: P_DATA!$ED$850:$IK$1267
Name HL_3: P_DATA!$Q$1276:$DX$1693
Name IN: 輸入頁!$E$5
Name MGP: OP!$C$35
Name PA: P_DATA!$ED$426:$IK$844
Name PI: OP!$AK$4:$AL$90
Name PM: 輸入頁!$E$17
Name PYO: PY!$D$4
Name PYR: PY!$C$11
Name PYY: PY!$C$4
Name SEX: 輸入頁!$K$5
Name WORDING: OP!$P$2:$Q$20
Name WORDINGP: OP!$AD$2:$AE$41
Name YPN: 輸入頁!$D$35
Name 主約1: OP!$H$43:$H$45
Name 保額倍數: OP!$B$87:$C$197
Name 繳: OP!$H$17:$H$21
Name 繳別首: OP!$L$31:$L$35
Name 繳別續: OP!$M$31:$M$35
Name 關係: OP!$B$143:$B$147

Sheet 揭露
B1: =OP!$C$56 -> SDN30 | C1: ←帶OP | D1: =IF(OP!$E$16=1,"足歲",IF(OP!$E$16=2,"保險年齡","錯誤")) -> 保險年齡 | E1: ←帶OP | K1: 1141125 | Q1: 6 | R1: 7 | S1: 8 | T1: 9 | U1: 10 | V1: 11 | W1: 12
L2: 以下3欄要注意最下方要和右側揭露拉齊 | O2: 以下COPY-DB | Q2: 109
C3: 代表年齡第?小→ | D3: 1 | E3: 2 | F3: 3 | G3: 1 | H3: 2 | I3: 3 | K3: 年齡代號轉換 | L3: KEY | M3: 年齡 | N3: 年度 | O3: 險種大類 | P3: 年期險種 | Q3: 性別 | R3: 年齡 | S3: 繳費方式 | T3: 宣告利率 | U3: 繳費金額 | V3: 保單年度 | W3: 揭露利率
C4: 性別男=1，女=2→ | D4: 1 | E4: 1 | F4: 1 | G4: 2 | H4: 2 | I4: 2 | K4: =IF($D$1="足歲","15足歲","") | L4: =IF(P4<>$B$1,"",P4&Q4&R4&V4) | M4: =IF(L4="","-",IF(ISERROR($R4*1),LEFT($R4,2)*1,$R4*1)) -> - | N4: =IF(L4="","",V4*1) | P4: SDN10 | Q4: 1 | R4: 5 | S4: 0 | T4: 0 | U4: 0 | V4: 1 | W4: 43.92%
B5: 取第?欄→ | C5: 12 | D5: =IF(SMALL($M:$M,D$3)=15,$K$4,SMALL($M:$M,D$3)) -> 5 | E5: =IF(SMALL($M:$M,E$3)=15,$K$4,SMALL($M:$M,E$3)) -> 35 | F5: =IF(SMALL($M:$M,F$3)=15,$K$4,SMALL($M:$M,F$3)) -> 40 | G5: =IF(SMALL($M:$M,G$3)=15,$K$4,SMALL($M:$M,G$3)) -> 5 | H5: =IF(SMALL($M:$M,H$3)=15,$K$4,SMALL($M:$M,H$3)) -> 35 | I5: =IF(SMALL($M:$M,I$3)=15,$K$4,SMALL($M:$M,I$3)) -> 40 | L5: =IF(P5<>$B$1,"",P5&Q5&R5&V5) | M5: =IF(OR(L5="",COUNTIF($M$4:M4,IF(ISERROR($R5*1),LEFT($R5,2)*1,$R5*1))>=1),"-",IF(ISERROR($R5*1),LEFT($R5,2)*1,$R5*1)) -> - | N5: =IF(OR(L5="",COUNTIF($N$4:N4,V5*1)>=1),"-",V5*1) -> - | P5: SDN10 | Q5: 1 | R5: 5 | S5: 0 | T5: 0 | U5: 0 | V5: 2 | W5: 49.73%
B6: 第?小↓ | C6: 保單年度 | D6: =IF(OR(ISERROR($D5)),"",IF(N(D$5)=0,D$5&IF(D$4=1,"男性",IF(D$4=2,"女性","")),D$5&"歲"&IF(D$4=1,"男性",IF(D$4=2,"女性","")))) -> 5歲男性 | E6: =IF(OR(ISERROR($D5)),"",IF(N(E$5)=0,E$5&IF(E$4=1,"男性",IF(E$4=2,"女性","")),E$5&"歲"&IF(E$4=1,"男性",IF(E$4=2,"女性","")))) -> 35歲男性 | F6: =IF(OR(ISERROR($D5)),"",IF(N(F$5)=0,F$5&IF(F$4=1,"男性",IF(F$4=2,"女性","")),F$5&"歲"&IF(F$4=1,"男性",IF(F$4=2,"女性","")))) -> 40歲男性 | G6: =IF(OR(ISERROR($D5)),"",IF(N(G$5)=0,G$5&IF(G$4=1,"男性",IF(G$4=2,"女性","")),G$5&"歲"&IF(G$4=1,"男性",IF(G$4=2,"女性","")))) -> 5歲女性 | H6: =IF(OR(ISERROR($D5)),"",IF(N(H$5)=0,H$5&IF(H$4=1,"男性",IF(H$4=2,"女性","")),H$5&"歲"&IF(H$4=1,"男性",IF(H$4=2,"女性","")))) -> 35歲女性 | I6: =IF(OR(ISERROR($D5)),"",IF(N(I$5)=0,I$5&IF(I$4=1,"男性",IF(I$4=2,"女性","")),I$5&"歲"&IF(I$4=1,"男性",IF(I$4=2,"女性","")))) -> 40歲女性 | L6: =IF(P6<>$B$1,"",P6&Q6&R6&V6) | M6: =IF(OR(L6="",COUNTIF($M$4:M5,IF(ISERROR($R6*1),LEFT($R6,2)*1,$R6*1))>=1),"-",IF(ISERROR($R6*1),LEFT($R6,2)*1,$R6*1)) -> - | N6: =IF(OR(L6="",COUNTIF($N$4:N5,V6*1)>=1),"-",V6*1) -> - | P6: SDN10 | Q6: 1 | R6: 5 | S6: 0 | T6: 0 | U6: 0 | V6: 3 | W6: 51.78%
B7: 1 | C7: =IF(ISERROR(SMALL($N:$N,$B7)),"",SMALL($N:$N,$B7)) -> 1 | D7: =IF(ISERROR(VLOOKUP($B$1&D$4&D$5&$C7,$L:$W,$C$5,0)),"",VLOOKUP($B$1&D$4&D$5&$C7,$L:$W,$C$5,0)) -> 7.15% | E7: =IF(ISERROR(VLOOKUP($B$1&E$4&E$5&$C7,$L:$W,$C$5,0)),"",VLOOKUP($B$1&E$4&E$5&$C7,$L:$W,$C$5,0)) -> 0.00% | F7: =IF(ISERROR(VLOOKUP($B$1&F$4&F$5&$C7,$L:$W,$C$5,0)),"",VLOOKUP($B$1&F$4&F$5&$C7,$L:$W,$C$5,0)) -> 0.00% | G7: =IF(ISERROR(VLOOKUP($B$1&G$4&G$5&$C7,$L:$W,$C$5,0)),"",VLOOKUP($B$1&G$4&G$5&$C7,$L:$W,$C$5,0)) -> 8.58% | H7: =IF(ISERROR(VLOOKUP($B$1&H$4&H$5&$C7,$L:$W,$C$5,0)),"",VLOOKUP($B$1&H$4&H$5&$C7,$L:$W,$C$5,0)) -> 0.00% | I7: =IF(ISERROR(VLOOKUP($B$1&I$4&I$5&$C7,$L:$W,$C$5,0)),"",VLOOKUP($B$1&I$4&I$5&$C7,$L:$W,$C$5,0)) -> 0.00% | L7: =IF(P7<>$B$1,"",P7&Q7&R7&V7) | M7: =IF(OR(L7="",COUNTIF($M$4:M6,IF(ISERROR($R7*1),LEFT($R7,2)*1,$R7*1))>=1),"-",IF(ISERROR($R7*1),LEFT($R7,2)*1,$R7*1)) -> - | N7: =IF(OR(L7="",COUNTIF($N$4:N6,V7*1)>=1),"-",V7*1) -> - | P7: SDN10 | Q7: 1 | R7: 5 | S7: 0 | T7: 0 | U7: 0 | V7: 4 | W7: 52.83%
B8: 2 | C8: =IF(ISERROR(SMALL($N:$N,$B8)),"",SMALL($N:$N,$B8)) -> 2 | D8: =IF(ISERROR(VLOOKUP($B$1&D$4&D$5&$C8,$L:$W,$C$5,0)),"",VLOOKUP($B$1&D$4&D$5&$C8,$L:$W,$C$5,0)) -> 25.86% | E8: =IF(ISERROR(VLOOKUP($B$1&E$4&E$5&$C8,$L:$W,$C$5,0)),"",VLOOKUP($B$1&E$4&E$5&$C8,$L:$W,$C$5,0)) -> 4.81% | F8: =IF(ISERROR(VLOOKUP($B$1&F$4&F$5&$C8,$L:$W,$C$5,0)),"",VLOOKUP($B$1&F$4&F$5&$C8,$L:$W,$C$5,0)) -> 3.98% | G8: =IF(ISERROR(VLOOKUP($B$1&G$4&G$5&$C8,$L:$W,$C$5,0)),"",VLOOKUP($B$1&G$4&G$5&$C8,$L:$W,$C$5,0)) -> 25.33% | H8: =IF(ISERROR(VLOOKUP($B$1&H$4&H$5&$C8,$L:$W,$C$5,0)),"",VLOOKUP($B$1&H$4&H$5&$C8,$L:$W,$C$5,0)) -> 6.45% | I8: =IF(ISERROR(VLOOKUP($B$1&I$4&I$5&$C8,$L:$W,$C$5,0)),"",VLOOKUP($B$1&I$4&I$5&$C8,$L:$W,$C$5,0)) -> 4.99% | L8: =IF(P8<>$B$1,"",P8&Q8&R8&V8) | M8: =IF(OR(L8="",COUNTIF($M$4:M7,IF(ISERROR($R8*1),LEFT($R8,2)*1,$R8*1))>=1),"-",IF(ISERROR($R8*1),LEFT($R8,2)*1,$R8*1)) -> - | N8: =IF(OR(L8="",COUNTIF($N$4:N7,V8*1)>=1),"-",V8*1) -> - | P8: SDN10 | Q8: 1 | R8: 5 | S8: 0 | T8: 0 | U8: 0 | V8: 5 | W8: 53.50%
B9: 3 | C9: =IF(ISERROR(SMALL($N:$N,$B9)),"",SMALL($N:$N,$B9)) -> 3 | D9: =IF(ISERROR(VLOOKUP($B$1&D$4&D$5&$C9,$L:$W,$C$5,0)),"",VLOOKUP($B$1&D$4&D$5&$C9,$L:$W,$C$5,0)) -> 32.19% | E9: =IF(ISERROR(VLOOKUP($B$1&E$4&E$5&$C9,$L:$W,$C$5,0)),"",VLOOKUP($B$1&E$4&E$5&$C9,$L:$W,$C$5,0)) -> 6.36% | F9: =IF(ISERROR(VLOOKUP($B$1&F$4&F$5&$C9,$L:$W,$C$5,0)),"",VLOOKUP($B$1&F$4&F$5&$C9,$L:$W,$C$5,0)) -> 5.19% | G9: =IF(ISERROR(VLOOKUP($B$1&G$4&G$5&$C9,$L:$W,$C$5,0)),"",VLOOKUP($B$1&G$4&G$5&$C9,$L:$W,$C$5,0)) -> 30.79% | H9: =IF(ISERROR(VLOOKUP($B$1&H$4&H$5&$C9,$L:$W,$C$5,0)),"",VLOOKUP($B$1&H$4&H$5&$C9,$L:$W,$C$5,0)) -> 8.62% | I9: =IF(ISERROR(VLOOKUP($B$1&I$4&I$5&$C9,$L:$W,$C$5,0)),"",VLOOKUP($B$1&I$4&I$5&$C9,$L:$W,$C$5,0)) -> 6.67% | L9: =IF(P9<>$B$1,"",P9&Q9&R9&V9) | M9: =IF(OR(L9="",COUNTIF($M$4:M8,IF(ISERROR($R9*1),LEFT($R9,2)*1,$R9*1))>=1),"-",IF(ISERROR($R9*1),LEFT($R9,2)*1,$R9*1)) -> - | N9: =IF(OR(L9="",COUNTIF($N$4:N8,V9*1)>=1),"-",V9*1) -> - | P9: SDN10 | Q9: 1 | R9: 5 | S9: 0 | T9: 0 | U9: 0 | V9: 10 | W9: 73.73%
B10: 4 | C10: =IF(ISERROR(SMALL($N:$N,$B10)),"",SMALL($N:$N,$B10)) -> 4 | D10: =IF(ISERROR(VLOOKUP($B$1&D$4&D$5&$C10,$L:$W,$C$5,0)),"",VLOOKUP($B$1&D$4&D$5&$C10,$L:$W,$C$5,0)) -> 35.42% | E10: =IF(ISERROR(VLOOKUP($B$1&E$4&E$5&$C10,$L:$W,$C$5,0)),"",VLOOKUP($B$1&E$4&E$5&$C10,$L:$W,$C$5,0)) -> 7.21% | F10: =IF(ISERROR(VLOOKUP($B$1&F$4&F$5&$C10,$L:$W,$C$5,0)),"",VLOOKUP($B$1&F$4&F$5&$C10,$L:$W,$C$5,0)) -> 5.87% | G10: =IF(ISERROR(VLOOKUP($B$1&G$4&G$5&$C10,$L:$W,$C$5,0)),"",VLOOKUP($B$1&G$4&G$5&$C10,$L:$W,$C$5,0)) -> 33.68% | H10: =IF(ISERROR(VLOOKUP($B$1&H$4&H$5&$C10,$L:$W,$C$5,0)),"",VLOOKUP($B$1&H$4&H$5&$C10,$L:$W,$C$5,0)) -> 9.64% | I10: =IF(ISERROR(VLOOKUP($B$1&I$4&I$5&$C10,$L:$W,$C$5,0)),"",VLOOKUP($B$1&I$4&I$5&$C10,$L:$W,$C$5,0)) -> 7.58% | L10: =IF(P10<>$B$1,"",P10&Q10&R10&V10) | M10: =IF(OR(L10="",COUNTIF($M$4:M9,IF(ISERROR($R10*1),LEFT($R10,2)*1,$R10*1))>=1),"-",IF(ISERROR($R10*1),LEFT($R10,2)*1,$R10*1)) -> - | N10: =IF(OR(L10="",COUNTIF($N$4:N9,V10*1)>=1),"-",V10*1) -> - | P10: SDN10 | Q10: 1 | R10: 5 | S10: 0 | T10: 0 | U10: 0 | V10: 15 | W10: 75.72%
B11: 5 | C11: =IF(ISERROR(SMALL($N:$N,$B11)),"",SMALL($N:$N,$B11)) -> 5 | D11: =IF(ISERROR(VLOOKUP($B$1&D$4&D$5&$C11,$L:$W,$C$5,0)),"",VLOOKUP($B$1&D$4&D$5&$C11,$L:$W,$C$5,0)) -> 37.41% | E11: =IF(ISERROR(VLOOKUP($B$1&E$4&E$5&$C11,$L:$W,$C$5,0)),"",VLOOKUP($B$1&E$4&E$5&$C11,$L:$W,$C$5,0)) -> 7.64% | F11: =IF(ISERROR(VLOOKUP($B$1&F$4&F$5&$C11,$L:$W,$C$5,0)),"",VLOOKUP($B$1&F$4&F$5&$C11,$L:$W,$C$5,0)) -> 6.25% | G11: =IF(ISERROR(VLOOKUP($B$1&G$4&G$5&$C11,$L:$W,$C$5,0)),"",VLOOKUP($B$1&G$4&G$5&$C11,$L:$W,$C$5,0)) -> 35.41% | H11: =IF(ISERROR(VLOOKUP($B$1&H$4&H$5&$C11,$L:$W,$C$5,0)),"",VLOOKUP($B$1&H$4&H$5&$C11,$L:$W,$C$5,0)) -> 10.37% | I11: =IF(ISERROR(VLOOKUP($B$1&I$4&I$5&$C11,$L:$W,$C$5,0)),"",VLOOKUP($B$1&I$4&I$5&$C11,$L:$W,$C$5,0)) -> 8.09% | L11: =IF(P11<>$B$1,"",P11&Q11&R11&V11) | M11: =IF(OR(L11="",COUNTIF($M$4:M10,IF(ISERROR($R11*1),LEFT($R11,2)*1,$R11*1))>=1),"-",IF(ISERROR($R11*1),LEFT($R11,2)*1,$R11*1)) -> - | N11: =IF(OR(L11="",COUNTIF($N$4:N10,V11*1)>=1),"-",V11*1) -> - | P11: SDN10 | Q11: 1 | R11: 5 | S11: 0 | T11: 0 | U11: 0 | V11: 20 | W11: 78.09%
B12: 6 | C12: =IF(ISERROR(SMALL($N:$N,$B12)),"",SMALL($N:$N,$B12)) -> 10 | D12: =IF(ISERROR(VLOOKUP($B$1&D$4&D$5&$C12,$L:$W,$C$5,0)),"",VLOOKUP($B$1&D$4&D$5&$C12,$L:$W,$C$5,0)) -> 55.46% | E12: =IF(ISERROR(VLOOKUP($B$1&E$4&E$5&$C12,$L:$W,$C$5,0)),"",VLOOKUP($B$1&E$4&E$5&$C12,$L:$W,$C$5,0)) -> 11.61% | F12: =IF(ISERROR(VLOOKUP($B$1&F$4&F$5&$C12,$L:$W,$C$5,0)),"",VLOOKUP($B$1&F$4&F$5&$C12,$L:$W,$C$5,0)) -> 9.57% | G12: =IF(ISERROR(VLOOKUP($B$1&G$4&G$5&$C12,$L:$W,$C$5,0)),"",VLOOKUP($B$1&G$4&G$5&$C12,$L:$W,$C$5,0)) -> 52.26% | H12: =IF(ISERROR(VLOOKUP($B$1&H$4&H$5&$C12,$L:$W,$C$5,0)),"",VLOOKUP($B$1&H$4&H$5&$C12,$L:$W,$C$5,0)) -> 16.03% | I12: =IF(ISERROR(VLOOKUP($B$1&I$4&I$5&$C12,$L:$W,$C$5,0)),"",VLOOKUP($B$1&I$4&I$5&$C12,$L:$W,$C$5,0)) -> 12.62% | L12: =IF(P12<>$B$1,"",P12&Q12&R12&V12) | M12: =IF(OR(L12="",COUNTIF($M$4:M11,IF(ISERROR($R12*1),LEFT($R12,2)*1,$R12*1))>=1),"-",IF(ISERROR($R12*1),LEFT($R12,2)*1,$R12*1)) -> - | N12: =IF(OR(L12="",COUNTIF($N$4:N11,V12*1)>=1),"-",V12*1) -> - | P12: SDN10 | Q12: 1 | R12: 35 | S12: 0 | T12: 0 | U12: 0 | V12: 1 | W12: 19.46%
B13: 7 | C13: =IF(ISERROR(SMALL($N:$N,$B13)),"",SMALL($N:$N,$B13)) -> 15 | D13: =IF(ISERROR(VLOOKUP($B$1&D$4&D$5&$C13,$L:$W,$C$5,0)),"",VLOOKUP($B$1&D$4&D$5&$C13,$L:$W,$C$5,0)) -> 57.99% | E13: =IF(ISERROR(VLOOKUP($B$1&E$4&E$5&$C13,$L:$W,$C$5,0)),"",VLOOKUP($B$1&E$4&E$5&$C13,$L:$W,$C$5,0)) -> 12.45% | F13: =IF(ISERROR(VLOOKUP($B$1&F$4&F$5&$C13,$L:$W,$C$5,0)),"",VLOOKUP($B$1&F$4&F$5&$C13,$L:$W,$C$5,0)) -> 10.45% | G13: =IF(ISERROR(VLOOKUP($B$1&G$4&G$5&$C13,$L:$W,$C$5,0)),"",VLOOKUP($B$1&G$4&G$5&$C13,$L:$W,$C$5,0)) -> 54.58% | H13: =IF(ISERROR(VLOOKUP($B$1&H$4&H$5&$C13,$L:$W,$C$5,0)),"",VLOOKUP($B$1&H$4&H$5&$C13,$L:$W,$C$5,0)) -> 17.51% | I13: =IF(ISERROR(VLOOKUP($B$1&I$4&I$5&$C13,$L:$W,$C$5,0)),"",VLOOKUP($B$1&I$4&I$5&$C13,$L:$W,$C$5,0)) -> 13.89% | L13: =IF(P13<>$B$1,"",P13&Q13&R13&V13) | M13: =IF(OR(L13="",COUNTIF($M$4:M12,IF(ISERROR($R13*1),LEFT($R13,2)*1,$R13*1))>=1),"-",IF(ISERROR($R13*1),LEFT($R13,2)*1,$R13*1)) -> - | N13: =IF(OR(L13="",COUNTIF($N$4:N12,V13*1)>=1),"-",V13*1) -> - | P13: SDN10 | Q13: 1 | R13: 35 | S13: 0 | T13: 0 | U13: 0 | V13: 2 | W13: 29.52%
B14: 8 | C14: =IF(ISERROR(SMALL($N:$N,$B14)),"",SMALL($N:$N,$B14)) -> 20 | D14: =IF(ISERROR(VLOOKUP($B$1&D$4&D$5&$C14,$L:$W,$C$5,0)),"",VLOOKUP($B$1&D$4&D$5&$C14,$L:$W,$C$5,0)) -> 60.03% | E14: =IF(ISERROR(VLOOKUP($B$1&E$4&E$5&$C14,$L:$W,$C$5,0)),"",VLOOKUP($B$1&E$4&E$5&$C14,$L:$W,$C$5,0)) -> 13.51% | F14: =IF(ISERROR(VLOOKUP($B$1&F$4&F$5&$C14,$L:$W,$C$5,0)),"",VLOOKUP($B$1&F$4&F$5&$C14,$L:$W,$C$5,0)) -> 11.54% | G14: =IF(ISERROR(VLOOKUP($B$1&G$4&G$5&$C14,$L:$W,$C$5,0)),"",VLOOKUP($B$1&G$4&G$5&$C14,$L:$W,$C$5,0)) -> 56.43% | H14: =IF(ISERROR(VLOOKUP($B$1&H$4&H$5&$C14,$L:$W,$C$5,0)),"",VLOOKUP($B$1&H$4&H$5&$C14,$L:$W,$C$5,0)) -> 19.20% | I14: =IF(ISERROR(VLOOKUP($B$1&I$4&I$5&$C14,$L:$W,$C$5,0)),"",VLOOKUP($B$1&I$4&I$5&$C14,$L:$W,$C$5,0)) -> 15.28% | L14: =IF(P14<>$B$1,"",P14&Q14&R14&V14) | M14: =IF(OR(L14="",COUNTIF($M$4:M13,IF(ISERROR($R14*1),LEFT($R14,2)*1,$R14*1))>=1),"-",IF(ISERROR($R14*1),LEFT($R14,2)*1,$R14*1)) -> - | N14: =IF(OR(L14="",COUNTIF($N$4:N13,V14*1)>=1),"-",V14*1) -> - | P14: SDN10 | Q14: 1 | R14: 35 | S14: 0 | T14: 0 | U14: 0 | V14: 3 | W14: 32.97%
C15: 以上區域為帶入列印頁範圍 | L15: =IF(P15<>$B$1,"",P15&Q15&R15&V15) | M15: =IF(OR(L15="",COUNTIF($M$4:M14,IF(ISERROR($R15*1),LEFT($R15,2)*1,$R15*1))>=1),"-",IF(ISERROR($R15*1),LEFT($R15,2)*1,$R15*1)) -> - | N15: =IF(OR(L15="",COUNTIF($N$4:N14,V15*1)>=1),"-",V15*1) -> - | P15: SDN10 | Q15: 1 | R15: 35 | S15: 0 | T15: 0 | U15: 0 | V15: 4 | W15: 34.83%
L16: =IF(P16<>$B$1,"",P16&Q16&R16&V16) | M16: =IF(OR(L16="",COUNTIF($M$4:M15,IF(ISERROR($R16*1),LEFT($R16,2)*1,$R16*1))>=1),"-",IF(ISERROR($R16*1),LEFT($R16,2)*1,$R16*1)) -> - | N16: =IF(OR(L16="",COUNTIF($N$4:N15,V16*1)>=1),"-",V16*1) -> - | P16: SDN10 | Q16: 1 | R16: 35 | S16: 0 | T16: 0 | U16: 0 | V16: 5 | W16: 36.01%
L17: =IF(P17<>$B$1,"",P17&Q17&R17&V17) | M17: =IF(OR(L17="",COUNTIF($M$4:M16,IF(ISERROR($R17*1),LEFT($R17,2)*1,$R17*1))>=1),"-",IF(ISERROR($R17*1),LEFT($R17,2)*1,$R17*1)) -> - | N17: =IF(OR(L17="",COUNTIF($N$4:N16,V17*1)>=1),"-",V17*1) -> - | P17: SDN10 | Q17: 1 | R17: 35 | S17: 0 | T17: 0 | U17: 0 | V17: 10 | W17: 52.56%
L18: =IF(P18<>$B$1,"",P18&Q18&R18&V18) | M18: =IF(OR(L18="",COUNTIF($M$4:M17,IF(ISERROR($R18*1),LEFT($R18,2)*1,$R18*1))>=1),"-",IF(ISERROR($R18*1),LEFT($R18,2)*1,$R18*1)) -> - | N18: =IF(OR(L18="",COUNTIF($N$4:N17,V18*1)>=1),"-",V18*1) -> - | P18: SDN10 | Q18: 1 | R18: 35 | S18: 0 | T18: 0 | U18: 0 | V18: 15 | W18: 56.89%
L19: =IF(P19<>$B$1,"",P19&Q19&R19&V19) | M19: =IF(OR(L19="",COUNTIF($M$4:M18,IF(ISERROR($R19*1),LEFT($R19,2)*1,$R19*1))>=1),"-",IF(ISERROR($R19*1),LEFT($R19,2)*1,$R19*1)) -> - | N19: =IF(OR(L19="",COUNTIF($N$4:N18,V19*1)>=1),"-",V19*1) -> - | P19: SDN10 | Q19: 1 | R19: 35 | S19: 0 | T19: 0 | U19: 0 | V19: 20 | W19: 64.40%
L20: =IF(P20<>$B$1,"",P20&Q20&R20&V20) | M20: =IF(OR(L20="",COUNTIF($M$4:M19,IF(ISERROR($R20*1),LEFT($R20,2)*1,$R20*1))>=1),"-",IF(ISERROR($R20*1),LEFT($R20,2)*1,$R20*1)) -> - | N20: =IF(OR(L20="",COUNTIF($N$4:N19,V20*1)>=1),"-",V20*1) -> - | P20: SDN10 | Q20: 1 | R20: 60 | S20: 0 | T20: 0 | U20: 0 | V20: 1 | W20: 0.00%
L21: =IF(P21<>$B$1,"",P21&Q21&R21&V21) | M21: =IF(OR(L21="",COUNTIF($M$4:M20,IF(ISERROR($R21*1),LEFT($R21,2)*1,$R21*1))>=1),"-",IF(ISERROR($R21*1),LEFT($R21,2)*1,$R21*1)) -> - | N21: =IF(OR(L21="",COUNTIF($N$4:N20,V21*1)>=1),"-",V21*1) -> - | P21: SDN10 | Q21: 1 | R21: 60 | S21: 0 | T21: 0 | U21: 0 | V21: 2 | W21: 7.66%
L22: =IF(P22<>$B$1,"",P22&Q22&R22&V22) | M22: =IF(OR(L22="",COUNTIF($M$4:M21,IF(ISERROR($R22*1),LEFT($R22,2)*1,$R22*1))>=1),"-",IF(ISERROR($R22*1),LEFT($R22,2)*1,$R22*1)) -> - | N22: =IF(OR(L22="",COUNTIF($N$4:N21,V22*1)>=1),"-",V22*1) -> - | P22: SDN10 | Q22: 1 | R22: 60 | S22: 0 | T22: 0 | U22: 0 | V22: 3 | W22: 10.41%
L23: =IF(P23<>$B$1,"",P23&Q23&R23&V23) | M23: =IF(OR(L23="",COUNTIF($M$4:M22,IF(ISERROR($R23*1),LEFT($R23,2)*1,$R23*1))>=1),"-",IF(ISERROR($R23*1),LEFT($R23,2)*1,$R23*1)) -> - | N23: =IF(OR(L23="",COUNTIF($N$4:N22,V23*1)>=1),"-",V23*1) -> - | P23: SDN10 | Q23: 1 | R23: 60 | S23: 0 | T23: 0 | U23: 0 | V23: 4 | W23: 11.93%
L24: =IF(P24<>$B$1,"",P24&Q24&R24&V24) | M24: =IF(OR(L24="",COUNTIF($M$4:M23,IF(ISERROR($R24*1),LEFT($R24,2)*1,$R24*1))>=1),"-",IF(ISERROR($R24*1),LEFT($R24,2)*1,$R24*1)) -> - | N24: =IF(OR(L24="",COUNTIF($N$4:N23,V24*1)>=1),"-",V24*1) -> - | P24: SDN10 | Q24: 1 | R24: 60 | S24: 0 | T24: 0 | U24: 0 | V24: 5 | W24: 12.94%
L25: =IF(P25<>$B$1,"",P25&Q25&R25&V25) | M25: =IF(OR(L25="",COUNTIF($M$4:M24,IF(ISERROR($R25*1),LEFT($R25,2)*1,$R25*1))>=1),"-",IF(ISERROR($R25*1),LEFT($R25,2)*1,$R25*1)) -> - | N25: =IF(OR(L25="",COUNTIF($N$4:N24,V25*1)>=1),"-",V25*1) -> - | P25: SDN10 | Q25: 1 | R25: 60 | S25: 0 | T25: 0 | U25: 0 | V25: 10 | W25: 21.65%
L26: =IF(P26<>$B$1,"",P26&Q26&R26&V26) | M26: =IF(OR(L26="",COUNTIF($M$4:M25,IF(ISERROR($R26*1),LEFT($R26,2)*1,$R26*1))>=1),"-",IF(ISERROR($R26*1),LEFT($R26,2)*1,$R26*1)) -> - | N26: =IF(OR(L26="",COUNTIF($N$4:N25,V26*1)>=1),"-",V26*1) -> - | P26: SDN10 | Q26: 1 | R26: 60 | S26: 0 | T26: 0 | U26: 0 | V26: 15 | W26: 27.23%
L27: =IF(P27<>$B$1,"",P27&Q27&R27&V27) | M27: =IF(OR(L27="",COUNTIF($M$4:M26,IF(ISERROR($R27*1),LEFT($R27,2)*1,$R27*1))>=1),"-",IF(ISERROR($R27*1),LEFT($R27,2)*1,$R27*1)) -> - | N27: =IF(OR(L27="",COUNTIF($N$4:N26,V27*1)>=1),"-",V27*1) -> - | P27: SDN10 | Q27: 1 | R27: 60 | S27: 0 | T27: 0 | U27: 0 | V27: 20 | W27: 40.26%
... L195: =IF(P195<>$B$1,"",P195&Q195&R195&V195) -> SDN3024020 | M195: =IF(OR(L195="",COUNTIF($M$4:M194,IF(ISERROR($R195*1),LEFT($R195,2)*1,$R195*1))>=1),"-",IF(ISERROR($R195*1),LEFT($R195,2)*1,$R195*1)) -> - | N195: =IF(OR(L195="",COUNTIF($N$4:N194,V195*1)>=1),"-",V195*1) -> - | P195: SDN30 | Q195: 2 | R195: 40 | S195: 0 | T195: 0 | U195: 0 | V195: 20 | W195: 15.28%

Sheet P_DATA
A1: GP | B1: SDN | J1: =B1&TEXT(F1,"00")&TEXT(H1,"00") -> SDN0000 | M1: EXP | Q1: =N1&TEXT(O1,"00")&TEXT(P1,"00") -> 0000 | U1: 1141009 | DZ1: DIE | ED1: =EA1&TEXT(EB1,"00")&TEXT(EC1,"00") -> 0000
A2: 版次 | B2: 商品代號 | C2: 職業等級 | D2: 年期 | E2: 保額代碼 | F2: 性別 | G2: 投保金額 | H2: 年齡 | I2: 繳費年度 | J2: =B2&TEXT(F2,"00")&TEXT(H2,"00") -> 商品代號性別年齡 | K2: 保費 | M2: 版次 | N2: 商品代號 | O2: 性別 | P2: 年齡 | Q2: =N2&TEXT(O2,"00")&TEXT(P2,"00") -> 商品代號性別年齡 | R2: 第1年滿期保險金 | S2: 第2年滿期保險金 | T2: 第3年滿期保險金 | U2: 第4年滿期保險金 | V2: 第5年滿期保險金 | W2: 第6年滿期保險金 | X2: 第7年滿期保險金 | Y2: 第8年滿期保險金 | Z2: 第9年滿期保險金 | AA2: 第10年滿期保險金 | AB2: 第11年滿期保險金 | AC2: 第12年滿期保險金 | AD2: 第13年滿期保險金 | AE2: 第14年滿期保險金 | AF2: 第15年滿期保險金 | AG2: 第16年滿期保險金 | AH2: 第17年滿期保險金 | AI2: 第18年滿期保險金 | AJ2: 第19年滿期保險金 | AK2: 第20年滿期保險金 | AL2: 第21年滿期保險金 | AM2: 第22年滿期保險金 | AN2: 第23年滿期保險金 | AO2: 第24年滿期保險金 | AP2: 第25年滿期保險金 | AQ2: 第26年滿期保險金 | AR2: 第27年滿期保險金 | AS2: 第28年滿期保險金 | AT2: 第29年滿期保險金 | AU2: 第30年滿期保險金 | AV2: 第31年滿期保險金 | AW2: 第32年滿期保險金 | AX2: 第33年滿期保險金 | AY2: 第34年滿期保險金 | AZ2: 第35年滿期保險金 | BA2: 第36年滿期保險金 | BB2: 第37年滿期保險金 | BC2: 第38年滿期保險金 | BD2: 第39年滿期保險金 | BE2: 第40年滿期保險金 | BF2: 第41年滿期保險金 | BG2: 第42年滿期保險金 | BH2: 第43年滿期保險金 | BI2: 第44年滿期保險金 | BJ2: 第45年滿期保險金 | BK2: 第46年滿期保險金 | BL2: 第47年滿期保險金 | BM2: 第48年滿期保險金 | BN2: 第49年滿期保險金 | BO2: 第50年滿期保險金 | BP2: 第51年滿期保險金 | BQ2: 第52年滿期保險金 | BR2: 第53年滿期保險金 | BS2: 第54年滿期保險金 | BT2: 第55年滿期保險金 | BU2: 第56年滿期保險金 | BV2: 第57年滿期保險金 | BW2: 第58年滿期保險金 | BX2: 第59年滿期保險金 | BY2: 第60年滿期保險金 | BZ2: 第61年滿期保險金 | CA2: 第62年滿期保險金 | CB2: 第63年滿期保險金 | CC2: 第64年滿期保險金 | CD2: 第65年滿期保險金 | CE2: 第66年滿期保險金 | CF2: 第67年滿期保險金 | CG2: 第68年滿期保險金 | CH2: 第69年滿期保險金 | CI2: 第70年滿期保險金 | CJ2: 第71年滿期保險金 | CK2: 第72年滿期保險金 | CL2: 第73年滿期保險金 | CM2: 第74年滿期保險金 | CN2: 第75年滿期保險金 | CO2: 第76年滿期保險金 | CP2: 第77年滿期保險金 | CQ2: 第78年滿期保險金 | CR2: 第79年滿期保險金 | CS2: 第80年滿期保險金 | CT2: 第81年滿期保險金 | CU2: 第82年滿期保險金 | CV2: 第83年滿期保險金 | CW2: 第84年滿期保險金 | CX2: 第85年滿期保險金 | CY2: 第86年滿期保險金 | CZ2: 第87年滿期保險金 | DA2: 第88年滿期保險金 | DB2: 第89年滿期保險金 | DC2: 第90年滿期保險金 | DD2: 第91年滿期保險金 | DE2: 第92年滿期保險金 | DF2: 第93年滿期保險金 | DG2: 第94年滿期保險金 | DH2: 第95年滿期保險金 | DI2: 第96年滿期保險金 | DJ2: 第97年滿期保險金 | DK2: 第98年滿期保險金 | DL2: 第99年滿期保險金 | DM2: 第100年滿期保險金 | DN2: 第101年滿期保險金 | DO2: 第102年滿期保險金 | DP2: 第103年滿期保險金 | DQ2: 第104年滿期保險金 | DR2: 第105年滿期保險金 | DS2: 第106年滿期保險金 | DT2: 第107年滿期保險金 | DU2: 第108年滿期保險金 | DV2: 第109年滿期保險金 | DW2: 第110年滿期保險金 | DX2: 第111年滿期保險金 | DZ2: 版次 | EA2: 商品代號 | EB2: 性別 | EC2: 年齡 | ED2: =EA2&TEXT(EB2,"00")&TEXT(EC2,"00") -> 商品代號性別年齡 | EE2: 第1年身故保險金 | EF2: 第2年身故保險金 | EG2: 第3年身故保險金 | EH2: 第4年身故保險金 | EI2: 第5年身故保險金 | EJ2: 第6年身故保險金 | EK2: 第7年身故保險金 | EL2: 第8年身故保險金 | EM2: 第9年身故保險金 | EN2: 第10年身故保險金 | EO2: 第11年身故保險金 | EP2: 第12年身故保險金 | EQ2: 第13年身故保險金 | ER2: 第14年身故保險金 | ES2: 第15年身故保險金 | ET2: 第16年身故保險金 | EU2: 第17年身故保險金 | EV2: 第18年身故保險金 | EW2: 第19年身故保險金 | EX2: 第20年身故保險金 | EY2: 第21年身故保險金 | EZ2: 第22年身故保險金 | FA2: 第23年身故保險金 | FB2: 第24年身故保險金 | FC2: 第25年身故保險金 | FD2: 第26年身故保險金 | FE2: 第27年身故保險金 | FF2: 第28年身故保險金 | FG2: 第29年身故保險金 | FH2: 第30年身故保險金 | FI2: 第31年身故保險金 | FJ2: 第32年身故保險金 | FK2: 第33年身故保險金 | FL2: 第34年身故保險金 | FM2: 第35年身故保險金 | FN2: 第36年身故保險金 | FO2: 第37年身故保險金 | FP2: 第38年身故保險金 | FQ2: 第39年身故保險金 | FR2: 第40年身故保險金 | FS2: 第41年身故保險金 | FT2: 第42年身故保險金 | FU2: 第43年身故保險金 | FV2: 第44年身故保險金 | FW2: 第45年身故保險金 | FX2: 第46年身故保險金 | FY2: 第47年身故保險金 | FZ2: 第48年身故保險金 | GA2: 第49年身故保險金 | GB2: 第50年身故保險金 | GC2: 第51年身故保險金 | GD2: 第52年身故保險金 | GE2: 第53年身故保險金 | GF2: 第54年身故保險金 | GG2: 第55年身故保險金 | GH2: 第56年身故保險金 | GI2: 第57年身故保險金 | GJ2: 第58年身故保險金 | GK2: 第59年身故保險金 | GL2: 第60年身故保險金 | GM2: 第61年身故保險金 | GN2: 第62年身故保險金 | GO2: 第63年身故保險金 | GP2: 第64年身故保險金 | GQ2: 第65年身故保險金 | GR2: 第66年身故保險金 | GS2: 第67年身故保險金 | GT2: 第68年身故保險金 | GU2: 第69年身故保險金 | GV2: 第70年身故保險金 | GW2: 第71年身故保險金 | GX2: 第72年身故保險金 | GY2: 第73年身故保險金 | GZ2: 第74年身故保險金額 | HA2: 第75年身故保險金 | HB2: 第76年身故保險金 | HC2: 第77年身故保險金 | HD2: 第78年身故保險金 | HE2: 第79年身故保險金 | HF2: 第80年身故保險金 | HG2: 第81年身故保險金 | HH2: 第82年身故保險金 | HI2: 第83年身故保險金 | HJ2: 第84年身故保險金 | HK2: 第85年身故保險金 | HL2: 第86年身故保險金 | HM2: 第87年身故保險金 | HN2: 第88年身故保險金 | HO2: 第89年身故保險金 | HP2: 第90年身故保險金 | HQ2: 第91年身故保險金 | HR2: 第92年身故保險金 | HS2: 第93年身故保險金 | HT2: 第94年身故保險金 | HU2: 第95年身故保險金 | HV2: 第96年身故保險金 | HW2: 第97年身故保險金 | HX2: 第98年身故保險金 | HY2: 第99年身故保險金 | HZ2: 第100年身故保險金 | IA2: 第101年身故保險金 | IB2: 第102年身故保險金 | IC2: 第103年身故保險金 | ID2: 第104年身故保險金 | IE2: 第105年身故保險金 | IF2: 第106年身故保險金 | IG2: 第107年身故保險金 | IH2: 第108年身故保險金 | II2: 第109年身故保險金 | IJ2: 第110年身故保險金 | IK2: 第111年身故保險金
A3: 56 | B3: SDN10 | F3: 1 | H3: 0 | I3: 1 | J3: =B3&TEXT(F3,"00")&TEXT(H3,"00")&TEXT(I3,"00") -> SDN10010001 | K3: 960 | M3: 56 | N3: SDN10 | O3: 1 | P3: 0 | Q3: =N3&TEXT(O3,"00")&TEXT(P3,"00") -> SDN100100 | R3: 0 | S3: 0 | T3: 0 | U3: 0 | V3: 0 | W3: 0 | X3: 0 | Y3: 0 | Z3: 0 | AA3: 0 | AB3: 0 | AC3: 0 | AD3: 0 | AE3: 0 | AF3: 0 | AG3: 0 | AH3: 0 | AI3: 0 | AJ3: 0 | AK3: 0 | AL3: 0 | AM3: 0 | AN3: 0 | AO3: 0 | AP3: 10000 | AQ3: 0 | AR3: 0 | AS3: 0 | AT3: 0 | AU3: 0 | AV3: 0 | AW3: 0 | AX3: 0 | AY3: 0 | AZ3: 0 | BA3: 0 | BB3: 0 | BC3: 0 | BD3: 0 | BE3: 0 | BF3: 0 | BG3: 0 | BH3: 0 | BI3: 0 | BJ3: 0 | BK3: 0 | BL3: 0 | BM3: 0 | BN3: 0 | BO3: 0 | BP3: 0 | BQ3: 0 | BR3: 0 | BS3: 0 | BT3: 0 | BU3: 0 | BV3: 0 | BW3: 0 | BX3: 0 | BY3: 0 | BZ3: 0 | CA3: 0 | CB3: 0 | CC3: 0 | CD3: 0 | CE3: 0 | CF3: 0 | CG3: 0 | CH3: 0 | CI3: 0 | CJ3: 0 | CK3: 0 | CL3: 0 | CM3: 0 | CN3: 0 | CO3: 0 | CP3: 0 | CQ3: 0 | CR3: 0 | CS3: 0 | CT3: 0 | CU3: 0 | CV3: 0 | CW3: 0 | CX3: 0 | CY3: 0 | CZ3: 0 | DA3: 0 | DB3: 0 | DC3: 0 | DD3: 0 | DE3: 0 | DF3: 0 | DG3: 0 | DH3: 0 | DI3: 0 | DJ3: 0 | DK3: 0 | DL3: 0 | DM3: 0 | DN3: 0 | DO3: 0 | DP3: 0 | DQ3: 0 | DR3: 0 | DS3: 0 | DT3: 0 | DU3: 0 | DV3: 0 | DW3: 0 | DX3: 0 | DZ3: 56 | EA3: SDN10 | EB3: 1 | EC3: 0 | ED3: =EA3&TEXT(EB3,"00")&TEXT(EC3,"00") -> SDN100100 | EE3: 10000 | EF3: 10000 | EG3: 10000 | EH3: 10000 | EI3: 10000 | EJ3: 10000 | EK3: 10000 | EL3: 10000 | EM3: 10000 | EN3: 10000 | EO3: 10000 | EP3: 10000 | EQ3: 10000 | ER3: 10000 | ES3: 10000 | ET3: 10000 | EU3: 10000 | EV3: 10000 | EW3: 10000 | EX3: 10000 | EY3: 10000 | EZ3: 10000 | FA3: 10000 | FB3: 10000 | FC3: 10000 | FD3: 0 | FE3: 0 | FF3: 0 | FG3: 0 | FH3: 0 | FI3: 0 | FJ3: 0 | FK3: 0 | FL3: 0 | FM3: 0 | FN3: 0 | FO3: 0 | FP3: 0 | FQ3: 0 | FR3: 0 | FS3: 0 | FT3: 0 | FU3: 0 | FV3: 0 | FW3: 0 | FX3: 0 | FY3: 0 | FZ3: 0 | GA3: 0 | GB3: 0 | GC3: 0 | GD3: 0 | GE3: 0 | GF3: 0 | GG3: 0 | GH3: 0 | GI3: 0 | GJ3: 0 | GK3: 0 | GL3: 0 | GM3: 0 | GN3: 0 | GO3: 0 | GP3: 0 | GQ3: 0 | GR3: 0 | GS3: 0 | GT3: 0 | GU3: 0 | GV3: 0 | GW3: 0 | GX3: 0 | GY3: 0 | GZ3: 0 | HA3: 0 | HB3: 0 | HC3: 0 | HD3: 0 | HE3: 0 | HF3: 0 | HG3: 0 | HH3: 0 | HI3: 0 | HJ3: 0 | HK3: 0 | HL3: 0 | HM3: 0 | HN3: 0 | HO3: 0 | HP3: 0 | HQ3: 0 | HR3: 0 | HS3: 0 | HT3: 0 | HU3: 0 | HV3: 0 | HW3: 0 | HX3: 0 | HY3: 0 | HZ3: 0 | IA3: 0 | IB3: 0 | IC3: 0 | ID3: 0 | IE3: 0 | IF3: 0 | IG3: 0 | IH3: 0 | II3: 0 | IJ3: 0 | IK3: 0
A4: 56 | B4: SDN10 | F4: 1 | H4: 0 | I4: 2 | J4: =B4&TEXT(F4,"00")&TEXT(H4,"00")&TEXT(I4,"00") -> SDN10010002 | K4: 960 | M4: 56 | N4: SDN10 | O4: 1 | P4: 1 | Q4: =N4&TEXT(O4,"00")&TEXT(P4,"00") -> SDN100101 | R4: 0 | S4: 0 | T4: 0 | U4: 0 | V4: 0 | W4: 0 | X4: 0 | Y4: 0 | Z4: 0 | AA4: 0 | AB4: 0 | AC4: 0 | AD4: 0 | AE4: 0 | AF4: 0 | AG4: 0 | AH4: 0 | AI4: 0 | AJ4: 0 | AK4: 0 | AL4: 0 | AM4: 0 | AN4: 0 | AO4: 0 | AP4: 10000 | AQ4: 0 | AR4: 0 | AS4: 0 | AT4: 0 | AU4: 0 | AV4: 0 | AW4: 0 | AX4: 0 | AY4: 0 | AZ4: 0 | BA4: 0 | BB4: 0 | BC4: 0 | BD4: 0 | BE4: 0 | BF4: 0 | BG4: 0 | BH4: 0 | BI4: 0 | BJ4: 0 | BK4: 0 | BL4: 0 | BM4: 0 | BN4: 0 | BO4: 0 | BP4: 0 | BQ4: 0 | BR4: 0 | BS4: 0 | BT4: 0 | BU4: 0 | BV4: 0 | BW4: 0 | BX4: 0 | BY4: 0 | BZ4: 0 | CA4: 0 | CB4: 0 | CC4: 0 | CD4: 0 | CE4: 0 | CF4: 0 | CG4: 0 | CH4: 0 | CI4: 0 | CJ4: 0 | CK4: 0 | CL4: 0 | CM4: 0 | CN4: 0 | CO4: 0 | CP4: 0 | CQ4: 0 | CR4: 0 | CS4: 0 | CT4: 0 | CU4: 0 | CV4: 0 | CW4: 0 | CX4: 0 | CY4: 0 | CZ4: 0 | DA4: 0 | DB4: 0 | DC4: 0 | DD4: 0 | DE4: 0 | DF4: 0 | DG4: 0 | DH4: 0 | DI4: 0 | DJ4: 0 | DK4: 0 | DL4: 0 | DM4: 0 | DN4: 0 | DO4: 0 | DP4: 0 | DQ4: 0 | DR4: 0 | DS4: 0 | DT4: 0 | DU4: 0 | DV4: 0 | DW4: 0 | DX4: 0 | DZ4: 56 | EA4: SDN10 | EB4: 1 | EC4: 1 | ED4: =EA4&TEXT(EB4,"00")&TEXT(EC4,"00") -> SDN100101 | EE4: 10000 | EF4: 10000 | EG4: 10000 | EH4: 10000 | EI4: 10000 | EJ4: 10000 | EK4: 10000 | EL4: 10000 | EM4: 10000 | EN4: 10000 | EO4: 10000 | EP4: 10000 | EQ4: 10000 | ER4: 10000 | ES4: 10000 | ET4: 10000 | EU4: 10000 | EV4: 10000 | EW4: 10000 | EX4: 10000 | EY4: 10000 | EZ4: 10000 | FA4: 10000 | FB4: 10000 | FC4: 10000 | FD4: 0 | FE4: 0 | FF4: 0 | FG4: 0 | FH4: 0 | FI4: 0 | FJ4: 0 | FK4: 0 | FL4: 0 | FM4: 0 | FN4: 0 | FO4: 0 | FP4: 0 | FQ4: 0 | FR4: 0 | FS4: 0 | FT4: 0 | FU4: 0 | FV4: 0 | FW4: 0 | FX4: 0 | FY4: 0 | FZ4: 0 | GA4: 0 | GB4: 0 | GC4: 0 | GD4: 0 | GE4: 0 | GF4: 0 | GG4: 0 | GH4: 0 | GI4: 0 | GJ4: 0 | GK4: 0 | GL4: 0 | GM4: 0 | GN4: 0 | GO4: 0 | GP4: 0 | GQ4: 0 | GR4: 0 | GS4: 0 | GT4: 0 | GU4: 0 | GV4: 0 | GW4: 0 | GX4: 0 | GY4: 0 | GZ4: 0 | HA4: 0 | HB4: 0 | HC4: 0 | HD4: 0 | HE4: 0 | HF4: 0 | HG4: 0 | HH4: 0 | HI4: 0 | HJ4: 0 | HK4: 0 | HL4: 0 | HM4: 0 | HN4: 0 | HO4: 0 | HP4: 0 | HQ4: 0 | HR4: 0 | HS4: 0 | HT4: 0 | HU4: 0 | HV4: 0 | HW4: 0 | HX4: 0 | HY4: 0 | HZ4: 0 | IA4: 0 | IB4: 0 | IC4: 0 | ID4: 0 | IE4: 0 | IF4: 0 | IG4: 0 | IH4: 0 | II4: 0 | IJ4: 0 | IK4: 0
A5: 56 | B5: SDN10 | F5: 1 | H5: 0 | I5: 3 | J5: =B5&TEXT(F5,"00")&TEXT(H5,"00")&TEXT(I5,"00") -> SDN10010003 | K5: 960 | M5: 56 | N5: SDN10 | O5: 1 | P5: 2 | Q5: =N5&TEXT(O5,"00")&TEXT(P5,"00") -> SDN100102 | R5: 0 | S5: 0 | T5: 0 | U5: 0 | V5: 0 | W5: 0 | X5: 0 | Y5: 0 | Z5: 0 | AA5: 0 | AB5: 0 | AC5: 0 | AD5: 0 | AE5: 0 | AF5: 0 | AG5: 0 | AH5: 0 | AI5: 0 | AJ5: 0 | AK5: 0 | AL5: 0 | AM5: 0 | AN5: 0 | AO5: 0 | AP5: 10000 | AQ5: 0 | AR5: 0 | AS5: 0 | AT5: 0 | AU5: 0 | AV5: 0 | AW5: 0 | AX5: 0 | AY5: 0 | AZ5: 0 | BA5: 0 | BB5: 0 | BC5: 0 | BD5: 0 | BE5: 0 | BF5: 0 | BG5: 0 | BH5: 0 | BI5: 0 | BJ5: 0 | BK5: 0 | BL5: 0 | BM5: 0 | BN5: 0 | BO5: 0 | BP5: 0 | BQ5: 0 | BR5: 0 | BS5: 0 | BT5: 0 | BU5: 0 | BV5: 0 | BW5: 0 | BX5: 0 | BY5: 0 | BZ5: 0 | CA5: 0 | CB5: 0 | CC5: 0 | CD5: 0 | CE5: 0 | CF5: 0 | CG5: 0 | CH5: 0 | CI5: 0 | CJ5: 0 | CK5: 0 | CL5: 0 | CM5: 0 | CN5: 0 | CO5: 0 | CP5: 0 | CQ5: 0 | CR5: 0 | CS5: 0 | CT5: 0 | CU5: 0 | CV5: 0 | CW5: 0 | CX5: 0 | CY5: 0 | CZ5: 0 | DA5: 0 | DB5: 0 | DC5: 0 | DD5: 0 | DE5: 0 | DF5: 0 | DG5: 0 | DH5: 0 | DI5: 0 | DJ5: 0 | DK5: 0 | DL5: 0 | DM5: 0 | DN5: 0 | DO5: 0 | DP5: 0 | DQ5: 0 | DR5: 0 | DS5: 0 | DT5: 0 | DU5: 0 | DV5: 0 | DW5: 0 | DX5: 0 | DZ5: 56 | EA5: SDN10 | EB5: 1 | EC5: 2 | ED5: =EA5&TEXT(EB5,"00")&TEXT(EC5,"00") -> SDN100102 | EE5: 10000 | EF5: 10000 | EG5: 10000 | EH5: 10000 | EI5: 10000 | EJ5: 10000 | EK5: 10000 | EL5: 10000 | EM5: 10000 | EN5: 10000 | EO5: 10000 | EP5: 10000 | EQ5: 10000 | ER5: 10000 | ES5: 10000 | ET5: 10000 | EU5: 10000 | EV5: 10000 | EW5: 10000 | EX5: 10000 | EY5: 10000 | EZ5: 10000 | FA5: 10000 | FB5: 10000 | FC5: 10000 | FD5: 0 | FE5: 0 | FF5: 0 | FG5: 0 | FH5: 0 | FI5: 0 | FJ5: 0 | FK5: 0 | FL5: 0 | FM5: 0 | FN5: 0 | FO5: 0 | FP5: 0 | FQ5: 0 | FR5: 0 | FS5: 0 | FT5: 0 | FU5: 0 | FV5: 0 | FW5: 0 | FX5: 0 | FY5: 0 | FZ5: 0 | GA5: 0 | GB5: 0 | GC5: 0 | GD5: 0 | GE5: 0 | GF5: 0 | GG5: 0 | GH5: 0 | GI5: 0 | GJ5: 0 | GK5: 0 | GL5: 0 | GM5: 0 | GN5: 0 | GO5: 0 | GP5: 0 | GQ5: 0 | GR5: 0 | GS5: 0 | GT5: 0 | GU5: 0 | GV5: 0 | GW5: 0 | GX5: 0 | GY5: 0 | GZ5: 0 | HA5: 0 | HB5: 0 | HC5: 0 | HD5: 0 | HE5: 0 | HF5: 0 | HG5: 0 | HH5: 0 | HI5: 0 | HJ5: 0 | HK5: 0 | HL5: 0 | HM5: 0 | HN5: 0 | HO5: 0 | HP5: 0 | HQ5: 0 | HR5: 0 | HS5: 0 | HT5: 0 | HU5: 0 | HV5: 0 | HW5: 0 | HX5: 0 | HY5: 0 | HZ5: 0 | IA5: 0 | IB5: 0 | IC5: 0 | ID5: 0 | IE5: 0 | IF5: 0 | IG5: 0 | IH5: 0 | II5: 0 | IJ5: 0 | IK5: 0
A6: 56 | B6: SDN10 | F6: 1 | H6: 0 | I6: 4 | J6: =B6&TEXT(F6,"00")&TEXT(H6,"00")&TEXT(I6,"00") -> SDN10010004 | K6: 960 | M6: 56 | N6: SDN10 | O6: 1 | P6: 3 | Q6: =N6&TEXT(O6,"00")&TEXT(P6,"00") -> SDN100103 | R6: 0 | S6: 0 | T6: 0 | U6: 0 | V6: 0 | W6: 0 | X6: 0 | Y6: 0 | Z6: 0 | AA6: 0 | AB6: 0 | AC6: 0 | AD6: 0 | AE6: 0 | AF6: 0 | AG6: 0 | AH6: 0 | AI6: 0 | AJ6: 0 | AK6: 0 | AL6: 0 | AM6: 0 | AN6: 0 | AO6: 0 | AP6: 10000 | AQ6: 0 | AR6: 0 | AS6: 0 | AT6: 0 | AU6: 0 | AV6: 0 | AW6: 0 | AX6: 0 | AY6: 0 | AZ6: 0 | BA6: 0 | BB6: 0 | BC6: 0 | BD6: 0 | BE6: 0 | BF6: 0 | BG6: 0 | BH6: 0 | BI6: 0 | BJ6: 0 | BK6: 0 | BL6: 0 | BM6: 0 | BN6: 0 | BO6: 0 | BP6: 0 | BQ6: 0 | BR6: 0 | BS6: 0 | BT6: 0 | BU6: 0 | BV6: 0 | BW6: 0 | BX6: 0 | BY6: 0 | BZ6: 0 | CA6: 0 | CB6: 0 | CC6: 0 | CD6: 0 | CE6: 0 | CF6: 0 | CG6: 0 | CH6: 0 | CI6: 0 | CJ6: 0 | CK6: 0 | CL6: 0 | CM6: 0 | CN6: 0 | CO6: 0 | CP6: 0 | CQ6: 0 | CR6: 0 | CS6: 0 | CT6: 0 | CU6: 0 | CV6: 0 | CW6: 0 | CX6: 0 | CY6: 0 | CZ6: 0 | DA6: 0 | DB6: 0 | DC6: 0 | DD6: 0 | DE6: 0 | DF6: 0 | DG6: 0 | DH6: 0 | DI6: 0 | DJ6: 0 | DK6: 0 | DL6: 0 | DM6: 0 | DN6: 0 | DO6: 0 | DP6: 0 | DQ6: 0 | DR6: 0 | DS6: 0 | DT6: 0 | DU6: 0 | DV6: 0 | DW6: 0 | DX6: 0 | DZ6: 56 | EA6: SDN10 | EB6: 1 | EC6: 3 | ED6: =EA6&TEXT(EB6,"00")&TEXT(EC6,"00") -> SDN100103 | EE6: 10000 | EF6: 10000 | EG6: 10000 | EH6: 10000 | EI6: 10000 | EJ6: 10000 | EK6: 10000 | EL6: 10000 | EM6: 10000 | EN6: 10000 | EO6: 10000 | EP6: 10000 | EQ6: 10000 | ER6: 10000 | ES6: 10000 | ET6: 10000 | EU6: 10000 | EV6: 10000 | EW6: 10000 | EX6: 10000 | EY6: 10000 | EZ6: 10000 | FA6: 10000 | FB6: 10000 | FC6: 10000 | FD6: 0 | FE6: 0 | FF6: 0 | FG6: 0 | FH6: 0 | FI6: 0 | FJ6: 0 | FK6: 0 | FL6: 0 | FM6: 0 | FN6: 0 | FO6: 0 | FP6: 0 | FQ6: 0 | FR6: 0 | FS6: 0 | FT6: 0 | FU6: 0 | FV6: 0 | FW6: 0 | FX6: 0 | FY6: 0 | FZ6: 0 | GA6: 0 | GB6: 0 | GC6: 0 | GD6: 0 | GE6: 0 | GF6: 0 | GG6: 0 | GH6: 0 | GI6: 0 | GJ6: 0 | GK6: 0 | GL6: 0 | GM6: 0 | GN6: 0 | GO6: 0 | GP6: 0 | GQ6: 0 | GR6: 0 | GS6: 0 | GT6: 0 | GU6: 0 | GV6: 0 | GW6: 0 | GX6: 0 | GY6: 0 | GZ6: 0 | HA6: 0 | HB6: 0 | HC6: 0 | HD6: 0 | HE6: 0 | HF6: 0 | HG6: 0 | HH6: 0 | HI6: 0 | HJ6: 0 | HK6: 0 | HL6: 0 | HM6: 0 | HN6: 0 | HO6: 0 | HP6: 0 | HQ6: 0 | HR6: 0 | HS6: 0 | HT6: 0 | HU6: 0 | HV6: 0 | HW6: 0 | HX6: 0 | HY6: 0 | HZ6: 0 | IA6: 0 | IB6: 0 | IC6: 0 | ID6: 0 | IE6: 0 | IF6: 0 | IG6: 0 | IH6: 0 | II6: 0 | IJ6: 0 | IK6: 0
A7: 56 | B7: SDN10 | F7: 1 | H7: 0 | I7: 5 | J7: =B7&TEXT(F7,"00")&TEXT(H7,"00")&TEXT(I7,"00") -> SDN10010005 | K7: 960 | M7: 56 | N7: SDN10 | O7: 1 | P7: 4 | Q7: =N7&TEXT(O7,"00")&TEXT(P7,"00") -> SDN100104 | R7: 0 | S7: 0 | T7: 0 | U7: 0 | V7: 0 | W7: 0 | X7: 0 | Y7: 0 | Z7: 0 | AA7: 0 | AB7: 0 | AC7: 0 | AD7: 0 | AE7: 0 | AF7: 0 | AG7: 0 | AH7: 0 | AI7: 0 | AJ7: 0 | AK7: 0 | AL7: 0 | AM7: 0 | AN7: 0 | AO7: 0 | AP7: 10000 | AQ7: 0 | AR7: 0 | AS7: 0 | AT7: 0 | AU7: 0 | AV7: 0 | AW7: 0 | AX7: 0 | AY7: 0 | AZ7: 0 | BA7: 0 | BB7: 0 | BC7: 0 | BD7: 0 | BE7: 0 | BF7: 0 | BG7: 0 | BH7: 0 | BI7: 0 | BJ7: 0 | BK7: 0 | BL7: 0 | BM7: 0 | BN7: 0 | BO7: 0 | BP7: 0 | BQ7: 0 | BR7: 0 | BS7: 0 | BT7: 0 | BU7: 0 | BV7: 0 | BW7: 0 | BX7: 0 | BY7: 0 | BZ7: 0 | CA7: 0 | CB7: 0 | CC7: 0 | CD7: 0 | CE7: 0 | CF7: 0 | CG7: 0 | CH7: 0 | CI7: 0 | CJ7: 0 | CK7: 0 | CL7: 0 | CM7: 0 | CN7: 0 | CO7: 0 | CP7: 0 | CQ7: 0 | CR7: 0 | CS7: 0 | CT7: 0 | CU7: 0 | CV7: 0 | CW7: 0 | CX7: 0 | CY7: 0 | CZ7: 0 | DA7: 0 | DB7: 0 | DC7: 0 | DD7: 0 | DE7: 0 | DF7: 0 | DG7: 0 | DH7: 0 | DI7: 0 | DJ7: 0 | DK7: 0 | DL7: 0 | DM7: 0 | DN7: 0 | DO7: 0 | DP7: 0 | DQ7: 0 | DR7: 0 | DS7: 0 | DT7: 0 | DU7: 0 | DV7: 0 | DW7: 0 | DX7: 0 | DZ7: 56 | EA7: SDN10 | EB7: 1 | EC7: 4 | ED7: =EA7&TEXT(EB7,"00")&TEXT(EC7,"00") -> SDN100104 | EE7: 10000 | EF7: 10000 | EG7: 10000 | EH7: 10000 | EI7: 10000 | EJ7: 10000 | EK7: 10000 | EL7: 10000 | EM7: 10000 | EN7: 10000 | EO7: 10000 | EP7: 10000 | EQ7: 10000 | ER7: 10000 | ES7: 10000 | ET7: 10000 | EU7: 10000 | EV7: 10000 | EW7: 10000 | EX7: 10000 | EY7: 10000 | EZ7: 10000 | FA7: 10000 | FB7: 10000 | FC7: 10000 | FD7: 0 | FE7: 0 | FF7: 0 | FG7: 0 | FH7: 0 | FI7: 0 | FJ7: 0 | FK7: 0 | FL7: 0 | FM7: 0 | FN7: 0 | FO7: 0 | FP7: 0 | FQ7: 0 | FR7: 0 | FS7: 0 | FT7: 0 | FU7: 0 | FV7: 0 | FW7: 0 | FX7: 0 | FY7: 0 | FZ7: 0 | GA7: 0 | GB7: 0 | GC7: 0 | GD7: 0 | GE7: 0 | GF7: 0 | GG7: 0 | GH7: 0 | GI7: 0 | GJ7: 0 | GK7: 0 | GL7: 0 | GM7: 0 | GN7: 0 | GO7: 0 | GP7: 0 | GQ7: 0 | GR7: 0 | GS7: 0 | GT7: 0 | GU7: 0 | GV7: 0 | GW7: 0 | GX7: 0 | GY7: 0 | GZ7: 0 | HA7: 0 | HB7: 0 | HC7: 0 | HD7: 0 | HE7: 0 | HF7: 0 | HG7: 0 | HH7: 0 | HI7: 0 | HJ7: 0 | HK7: 0 | HL7: 0 | HM7: 0 | HN7: 0 | HO7: 0 | HP7: 0 | HQ7: 0 | HR7: 0 | HS7: 0 | HT7: 0 | HU7: 0 | HV7: 0 | HW7: 0 | HX7: 0 | HY7: 0 | HZ7: 0 | IA7: 0 | IB7: 0 | IC7: 0 | ID7: 0 | IE7: 0 | IF7: 0 | IG7: 0 | IH7: 0 | II7: 0 | IJ7: 0 | IK7: 0
A8: 56 | B8: SDN10 | F8: 1 | H8: 0 | I8: 6 | J8: =B8&TEXT(F8,"00")&TEXT(H8,"00")&TEXT(I8,"00") -> SDN10010006 | K8: 768 | M8: 56 | N8: SDN10 | O8: 1 | P8: 5 | Q8: =N8&TEXT(O8,"00")&TEXT(P8,"00") -> SDN100105 | R8: 0 | S8: 0 | T8: 0 | U8: 0 | V8: 0 | W8: 0 | X8: 0 | Y8: 0 | Z8: 0 | AA8: 0 | AB8: 0 | AC8: 0 | AD8: 0 | AE8: 0 | AF8: 0 | AG8: 0 | AH8: 0 | AI8: 0 | AJ8: 0 | AK8: 0 | AL8: 0 | AM8: 0 | AN8: 0 | AO8: 0 | AP8: 10000 | AQ8: 0 | AR8: 0 | AS8: 0 | AT8: 0 | AU8: 0 | AV8: 0 | AW8: 0 | AX8: 0 | AY8: 0 | AZ8: 0 | BA8: 0 | BB8: 0 | BC8: 0 | BD8: 0 | BE8: 0 | BF8: 0 | BG8: 0 | BH8: 0 | BI8: 0 | BJ8: 0 | BK8: 0 | BL8: 0 | BM8: 0 | BN8: 0 | BO8: 0 | BP8: 0 | BQ8: 0 | BR8: 0 | BS8: 0 | BT8: 0 | BU8: 0 | BV8: 0 | BW8: 0 | BX8: 0 | BY8: 0 | BZ8: 0 | CA8: 0 | CB8: 0 | CC8: 0 | CD8: 0 | CE8: 0 | CF8: 0 | CG8: 0 | CH8: 0 | CI8: 0 | CJ8: 0 | CK8: 0 | CL8: 0 | CM8: 0 | CN8: 0 | CO8: 0 | CP8: 0 | CQ8: 0 | CR8: 0 | CS8: 0 | CT8: 0 | CU8: 0 | CV8: 0 | CW8: 0 | CX8: 0 | CY8: 0 | CZ8: 0 | DA8: 0 | DB8: 0 | DC8: 0 | DD8: 0 | DE8: 0 | DF8: 0 | DG8: 0 | DH8: 0 | DI8: 0 | DJ8: 0 | DK8: 0 | DL8: 0 | DM8: 0 | DN8: 0 | DO8: 0 | DP8: 0 | DQ8: 0 | DR8: 0 | DS8: 0 | DT8: 0 | DU8: 0 | DV8: 0 | DW8: 0 | DX8: 0 | DZ8: 56 | EA8: SDN10 | EB8: 1 | EC8: 5 | ED8: =EA8&TEXT(EB8,"00")&TEXT(EC8,"00") -> SDN100105 | EE8: 10000 | EF8: 10000 | EG8: 10000 | EH8: 10000 | EI8: 10000 | EJ8: 10000 | EK8: 10000 | EL8: 10000 | EM8: 10000 | EN8: 10000 | EO8: 10000 | EP8: 10000 | EQ8: 10000 | ER8: 10000 | ES8: 10000 | ET8: 10000 | EU8: 10000 | EV8: 10000 | EW8: 10000 | EX8: 10000 | EY8: 10000 | EZ8: 10000 | FA8: 10000 | FB8: 10000 | FC8: 10000 | FD8: 0 | FE8: 0 | FF8: 0 | FG8: 0 | FH8: 0 | FI8: 0 | FJ8: 0 | FK8: 0 | FL8: 0 | FM8: 0 | FN8: 0 | FO8: 0 | FP8: 0 | FQ8: 0 | FR8: 0 | FS8: 0 | FT8: 0 | FU8: 0 | FV8: 0 | FW8: 0 | FX8: 0 | FY8: 0 | FZ8: 0 | GA8: 0 | GB8: 0 | GC8: 0 | GD8: 0 | GE8: 0 | GF8: 0 | GG8: 0 | GH8: 0 | GI8: 0 | GJ8: 0 | GK8: 0 | GL8: 0 | GM8: 0 | GN8: 0 | GO8: 0 | GP8: 0 | GQ8: 0 | GR8: 0 | GS8: 0 | GT8: 0 | GU8: 0 | GV8: 0 | GW8: 0 | GX8: 0 | GY8: 0 | GZ8: 0 | HA8: 0 | HB8: 0 | HC8: 0 | HD8: 0 | HE8: 0 | HF8: 0 | HG8: 0 | HH8: 0 | HI8: 0 | HJ8: 0 | HK8: 0 | HL8: 0 | HM8: 0 | HN8: 0 | HO8: 0 | HP8: 0 | HQ8: 0 | HR8: 0 | HS8: 0 | HT8: 0 | HU8: 0 | HV8: 0 | HW8: 0 | HX8: 0 | HY8: 0 | HZ8: 0 | IA8: 0 | IB8: 0 | IC8: 0 | ID8: 0 | IE8: 0 | IF8: 0 | IG8: 0 | IH8: 0 | II8: 0 | IJ8: 0 | IK8: 0
A9: 56 | B9: SDN10 | F9: 1 | H9: 0 | I9: 7 | J9: =B9&TEXT(F9,"00")&TEXT(H9,"00")&TEXT(I9,"00") -> SDN10010007 | K9: 768 | M9: 56 | N9: SDN10 | O9: 1 | P9: 6 | Q9: =N9&TEXT(O9,"00")&TEXT(P9,"00") -> SDN100106 | R9: 0 | S9: 0 | T9: 0 | U9: 0 | V9: 0 | W9: 0 | X9: 0 | Y9: 0 | Z9: 0 | AA9: 0 | AB9: 0 | AC9: 0 | AD9: 0 | AE9: 0 | AF9: 0 | AG9: 0 | AH9: 0 | AI9: 0 | AJ9: 0 | AK9: 0 | AL9: 0 | AM9: 0 | AN9: 0 | AO9: 0 | AP9: 10000 | AQ9: 0 | AR9: 0 | AS9: 0 | AT9: 0 | AU9: 0 | AV9: 0 | AW9: 0 | AX9: 0 | AY9: 0 | AZ9: 0 | BA9: 0 | BB9: 0 | BC9: 0 | BD9: 0 | BE9: 0 | BF9: 0 | BG9: 0 | BH9: 0 | BI9: 0 | BJ9: 0 | BK9: 0 | BL9: 0 | BM9: 0 | BN9: 0 | BO9: 0 | BP9: 0 | BQ9: 0 | BR9: 0 | BS9: 0 | BT9: 0 | BU9: 0 | BV9: 0 | BW9: 0 | BX9: 0 | BY9: 0 | BZ9: 0 | CA9: 0 | CB9: 0 | CC9: 0 | CD9: 0 | CE9: 0 | CF9: 0 | CG9: 0 | CH9: 0 | CI9: 0 | CJ9: 0 | CK9: 0 | CL9: 0 | CM9: 0 | CN9: 0 | CO9: 0 | CP9: 0 | CQ9: 0 | CR9: 0 | CS9: 0 | CT9: 0 | CU9: 0 | CV9: 0 | CW9: 0 | CX9: 0 | CY9: 0 | CZ9: 0 | DA9: 0 | DB9: 0 | DC9: 0 | DD9: 0 | DE9: 0 | DF9: 0 | DG9: 0 | DH9: 0 | DI9: 0 | DJ9: 0 | DK9: 0 | DL9: 0 | DM9: 0 | DN9: 0 | DO9: 0 | DP9: 0 | DQ9: 0 | DR9: 0 | DS9: 0 | DT9: 0 | DU9: 0 | DV9: 0 | DW9: 0 | DX9: 0 | DZ9: 56 | EA9: SDN10 | EB9: 1 | EC9: 6 | ED9: =EA9&TEXT(EB9,"00")&TEXT(EC9,"00") -> SDN100106 | EE9: 10000 | EF9: 10000 | EG9: 10000 | EH9: 10000 | EI9: 10000 | EJ9: 10000 | EK9: 10000 | EL9: 10000 | EM9: 10000 | EN9: 10000 | EO9: 10000 | EP9: 10000 | EQ9: 10000 | ER9: 10000 | ES9: 10000 | ET9: 10000 | EU9: 10000 | EV9: 10000 | EW9: 10000 | EX9: 10000 | EY9: 10000 | EZ9: 10000 | FA9: 10000 | FB9: 10000 | FC9: 10000 | FD9: 0 | FE9: 0 | FF9: 0 | FG9: 0 | FH9: 0 | FI9: 0 | FJ9: 0 | FK9: 0 | FL9: 0 | FM9: 0 | FN9: 0 | FO9: 0 | FP9: 0 | FQ9: 0 | FR9: 0 | FS9: 0 | FT9: 0 | FU9: 0 | FV9: 0 | FW9: 0 | FX9: 0 | FY9: 0 | FZ9: 0 | GA9: 0 | GB9: 0 | GC9: 0 | GD9: 0 | GE9: 0 | GF9: 0 | GG9: 0 | GH9: 0 | GI9: 0 | GJ9: 0 | GK9: 0 | GL9: 0 | GM9: 0 | GN9: 0 | GO9: 0 | GP9: 0 | GQ9: 0 | GR9: 0 | GS9: 0 | GT9: 0 | GU9: 0 | GV9: 0 | GW9: 0 | GX9: 0 | GY9: 0 | GZ9: 0 | HA9: 0 | HB9: 0 | HC9: 0 | HD9: 0 | HE9: 0 | HF9: 0 | HG9: 0 | HH9: 0 | HI9: 0 | HJ9: 0 | HK9: 0 | HL9: 0 | HM9: 0 | HN9: 0 | HO9: 0 | HP9: 0 | HQ9: 0 | HR9: 0 | HS9: 0 | HT9: 0 | HU9: 0 | HV9: 0 | HW9: 0 | HX9: 0 | HY9: 0 | HZ9: 0 | IA9: 0 | IB9: 0 | IC9: 0 | ID9: 0 | IE9: 0 | IF9: 0 | IG9: 0 | IH9: 0 | II9: 0 | IJ9: 0 | IK9: 0
A10: 56 | B10: SDN10 | F10: 1 | H10: 0 | I10: 8 | J10: =B10&TEXT(F10,"00")&TEXT(H10,"00")&TEXT(I10,"00") -> SDN10010008 | K10: 768 | M10: 56 | N10: SDN10 | O10: 1 | P10: 7 | Q10: =N10&TEXT(O10,"00")&TEXT(P10,"00") -> SDN100107 | R10: 0 | S10: 0 | T10: 0 | U10: 0 | V10: 0 | W10: 0 | X10: 0 | Y10: 0 | Z10: 0 | AA10: 0 | AB10: 0 | AC10: 0 | AD10: 0 | AE10: 0 | AF10: 0 | AG10: 0 | AH10: 0 | AI10: 0 | AJ10: 0 | AK10: 0 | AL10: 0 | AM10: 0 | AN10: 0 | AO10: 0 | AP10: 10000 | AQ10: 0 | AR10: 0 | AS10: 0 | AT10: 0 | AU10: 0 | AV10: 0 | AW10: 0 | AX10: 0 | AY10: 0 | AZ10: 0 | BA10: 0 | BB10: 0 | BC10: 0 | BD10: 0 | BE10: 0 | BF10: 0 | BG10: 0 | BH10: 0 | BI10: 0 | BJ10: 0 | BK10: 0 | BL10: 0 | BM10: 0 | BN10: 0 | BO10: 0 | BP10: 0 | BQ10: 0 | BR10: 0 | BS10: 0 | BT10: 0 | BU10: 0 | BV10: 0 | BW10: 0 | BX10: 0 | BY10: 0 | BZ10: 0 | CA10: 0 | CB10: 0 | CC10: 0 | CD10: 0 | CE10: 0 | CF10: 0 | CG10: 0 | CH10: 0 | CI10: 0 | CJ10: 0 | CK10: 0 | CL10: 0 | CM10: 0 | CN10: 0 | CO10: 0 | CP10: 0 | CQ10: 0 | CR10: 0 | CS10: 0 | CT10: 0 | CU10: 0 | CV10: 0 | CW10: 0 | CX10: 0 | CY10: 0 | CZ10: 0 | DA10: 0 | DB10: 0 | DC10: 0 | DD10: 0 | DE10: 0 | DF10: 0 | DG10: 0 | DH10: 0 | DI10: 0 | DJ10: 0 | DK10: 0 | DL10: 0 | DM10: 0 | DN10: 0 | DO10: 0 | DP10: 0 | DQ10: 0 | DR10: 0 | DS10: 0 | DT10: 0 | DU10: 0 | DV10: 0 | DW10: 0 | DX10: 0 | DZ10: 56 | EA10: SDN10 | EB10: 1 | EC10: 7 | ED10: =EA10&TEXT(EB10,"00")&TEXT(EC10,"00") -> SDN100107 | EE10: 10000 | EF10: 10000 | EG10: 10000 | EH10: 10000 | EI10: 10000 | EJ10: 10000 | EK10: 10000 | EL10: 10000 | EM10: 10000 | EN10: 10000 | EO10: 10000 | EP10: 10000 | EQ10: 10000 | ER10: 10000 | ES10: 10000 | ET10: 10000 | EU10: 10000 | EV10: 10000 | EW10: 10000 | EX10: 10000 | EY10: 10000 | EZ10: 10000 | FA10: 10000 | FB10: 10000 | FC10: 10000 | FD10: 0 | FE10: 0 | FF10: 0 | FG10: 0 | FH10: 0 | FI10: 0 | FJ10: 0 | FK10: 0 | FL10: 0 | FM10: 0 | FN10: 0 | FO10: 0 | FP10: 0 | FQ10: 0 | FR10: 0 | FS10: 0 | FT10: 0 | FU10: 0 | FV10: 0 | FW10: 0 | FX10: 0 | FY10: 0 | FZ10: 0 | GA10: 0 | GB10: 0 | GC10: 0 | GD10: 0 | GE10: 0 | GF10: 0 | GG10: 0 | GH10: 0 | GI10: 0 | GJ10: 0 | GK10: 0 | GL10: 0 | GM10: 0 | GN10: 0 | GO10: 0 | GP10: 0 | GQ10: 0 | GR10: 0 | GS10: 0 | GT10: 0 | GU10: 0 | GV10: 0 | GW10: 0 | GX10: 0 | GY10: 0 | GZ10: 0 | HA10: 0 | HB10: 0 | HC10: 0 | HD10: 0 | HE10: 0 | HF10: 0 | HG10: 0 | HH10: 0 | HI10: 0 | HJ10: 0 | HK10: 0 | HL10: 0 | HM10: 0 | HN10: 0 | HO10: 0 | HP10: 0 | HQ10: 0 | HR10: 0 | HS10: 0 | HT10: 0 | HU10: 0 | HV10: 0 | HW10: 0 | HX10: 0 | HY10: 0 | HZ10: 0 | IA10: 0 | IB10: 0 | IC10: 0 | ID10: 0 | IE10: 0 | IF10: 0 | IG10: 0 | IH10: 0 | II10: 0 | IJ10: 0 | IK10: 0
A11: 56 | B11: SDN10 | F11: 1 | H11: 0 | I11: 9 | J11: =B11&TEXT(F11,"00")&TEXT(H11,"00")&TEXT(I11,"00") -> SDN10010009 | K11: 768 | M11: 56 | N11: SDN10 | O11: 1 | P11: 8 | Q11: =N11&TEXT(O11,"00")&TEXT(P11,"00") -> SDN100108 | R11: 0 | S11: 0 | T11: 0 | U11: 0 | V11: 0 | W11: 0 | X11: 0 | Y11: 0 | Z11: 0 | AA11: 0 | AB11: 0 | AC11: 0 | AD11: 0 | AE11: 0 | AF11: 0 | AG11: 0 | AH11: 0 | AI11: 0 | AJ11: 0 | AK11: 0 | AL11: 0 | AM11: 0 | AN11: 0 | AO11: 0 | AP11: 10000 | AQ11: 0 | AR11: 0 | AS11: 0 | AT11: 0 | AU11: 0 | AV11: 0 | AW11: 0 | AX11: 0 | AY11: 0 | AZ11: 0 | BA11: 0 | BB11: 0 | BC11: 0 | BD11: 0 | BE11: 0 | BF11: 0 | BG11: 0 | BH11: 0 | BI11: 0 | BJ11: 0 | BK11: 0 | BL11: 0 | BM11: 0 | BN11: 0 | BO11: 0 | BP11: 0 | BQ11: 0 | BR11: 0 | BS11: 0 | BT11: 0 | BU11: 0 | BV11: 0 | BW11: 0 | BX11: 0 | BY11: 0 | BZ11: 0 | CA11: 0 | CB11: 0 | CC11: 0 | CD11: 0 | CE11: 0 | CF11: 0 | CG11: 0 | CH11: 0 | CI11: 0 | CJ11: 0 | CK11: 0 | CL11: 0 | CM11: 0 | CN11: 0 | CO11: 0 | CP11: 0 | CQ11: 0 | CR11: 0 | CS11: 0 | CT11: 0 | CU11: 0 | CV11: 0 | CW11: 0 | CX11: 0 | CY11: 0 | CZ11: 0 | DA11: 0 | DB11: 0 | DC11: 0 | DD11: 0 | DE11: 0 | DF11: 0 | DG11: 0 | DH11: 0 | DI11: 0 | DJ11: 0 | DK11: 0 | DL11: 0 | DM11: 0 | DN11: 0 | DO11: 0 | DP11: 0 | DQ11: 0 | DR11: 0 | DS11: 0 | DT11: 0 | DU11: 0 | DV11: 0 | DW11: 0 | DX11: 0 | DZ11: 56 | EA11: SDN10 | EB11: 1 | EC11: 8 | ED11: =EA11&TEXT(EB11,"00")&TEXT(EC11,"00") -> SDN100108 | EE11: 10000 | EF11: 10000 | EG11: 10000 | EH11: 10000 | EI11: 10000 | EJ11: 10000 | EK11: 10000 | EL11: 10000 | EM11: 10000 | EN11: 10000 | EO11: 10000 | EP11: 10000 | EQ11: 10000 | ER11: 10000 | ES11: 10000 | ET11: 10000 | EU11: 10000 | EV11: 10000 | EW11: 10000 | EX11: 10000 | EY11: 10000 | EZ11: 10000 | FA11: 10000 | FB11: 10000 | FC11: 10000 | FD11: 0 | FE11: 0 | FF11: 0 | FG11: 0 | FH11: 0 | FI11: 0 | FJ11: 0 | FK11: 0 | FL11: 0 | FM11: 0 | FN11: 0 | FO11: 0 | FP11: 0 | FQ11: 0 | FR11: 0 | FS11: 0 | FT11: 0 | FU11: 0 | FV11: 0 | FW11: 0 | FX11: 0 | FY11: 0 | FZ11: 0 | GA11: 0 | GB11: 0 | GC11: 0 | GD11: 0 | GE11: 0 | GF11: 0 | GG11: 0 | GH11: 0 | GI11: 0 | GJ11: 0 | GK11: 0 | GL11: 0 | GM11: 0 | GN11: 0 | GO11: 0 | GP11: 0 | GQ11: 0 | GR11: 0 | GS11: 0 | GT11: 0 | GU11: 0 | GV11: 0 | GW11: 0 | GX11: 0 | GY11: 0 | GZ11: 0 | HA11: 0 | HB11: 0 | HC11: 0 | HD11: 0 | HE11: 0 | HF11: 0 | HG11: 0 | HH11: 0 | HI11: 0 | HJ11: 0 | HK11: 0 | HL11: 0 | HM11: 0 | HN11: 0 | HO11: 0 | HP11: 0 | HQ11: 0 | HR11: 0 | HS11: 0 | HT11: 0 | HU11: 0 | HV11: 0 | HW11: 0 | HX11: 0 | HY11: 0 | HZ11: 0 | IA11: 0 | IB11: 0 | IC11: 0 | ID11: 0 | IE11: 0 | IF11: 0 | IG11: 0 | IH11: 0 | II11: 0 | IJ11: 0 | IK11: 0
A12: 56 | B12: SDN10 | F12: 1 | H12: 0 | I12: 10 | J12: =B12&TEXT(F12,"00")&TEXT(H12,"00")&TEXT(I12,"00") -> SDN10010010 | K12: 768 | M12: 56 | N12: SDN10 | O12: 1 | P12: 9 | Q12: =N12&TEXT(O12,"00")&TEXT(P12,"00") -> SDN100109 | R12: 0 | S12: 0 | T12: 0 | U12: 0 | V12: 0 | W12: 0 | X12: 0 | Y12: 0 | Z12: 0 | AA12: 0 | AB12: 0 | AC12: 0 | AD12: 0 | AE12: 0 | AF12: 0 | AG12: 0 | AH12: 0 | AI12: 0 | AJ12: 0 | AK12: 0 | AL12: 0 | AM12: 0 | AN12: 0 | AO12: 0 | AP12: 10000 | AQ12: 0 | AR12: 0 | AS12: 0 | AT12: 0 | AU12: 0 | AV12: 0 | AW12: 0 | AX12: 0 | AY12: 0 | AZ12: 0 | BA12: 0 | BB12: 0 | BC12: 0 | BD12: 0 | BE12: 0 | BF12: 0 | BG12: 0 | BH12: 0 | BI12: 0 | BJ12: 0 | BK12: 0 | BL12: 0 | BM12: 0 | BN12: 0 | BO12: 0 | BP12: 0 | BQ12: 0 | BR12: 0 | BS12: 0 | BT12: 0 | BU12: 0 | BV12: 0 | BW12: 0 | BX12: 0 | BY12: 0 | BZ12: 0 | CA12: 0 | CB12: 0 | CC12: 0 | CD12: 0 | CE12: 0 | CF12: 0 | CG12: 0 | CH12: 0 | CI12: 0 | CJ12: 0 | CK12: 0 | CL12: 0 | CM12: 0 | CN12: 0 | CO12: 0 | CP12: 0 | CQ12: 0 | CR12: 0 | CS12: 0 | CT12: 0 | CU12: 0 | CV12: 0 | CW12: 0 | CX12: 0 | CY12: 0 | CZ12: 0 | DA12: 0 | DB12: 0 | DC12: 0 | DD12: 0 | DE12: 0 | DF12: 0 | DG12: 0 | DH12: 0 | DI12: 0 | DJ12: 0 | DK12: 0 | DL12: 0 | DM12: 0 | DN12: 0 | DO12: 0 | DP12: 0 | DQ12: 0 | DR12: 0 | DS12: 0 | DT12: 0 | DU12: 0 | DV12: 0 | DW12: 0 | DX12: 0 | DZ12: 56 | EA12: SDN10 | EB12: 1 | EC12: 9 | ED12: =EA12&TEXT(EB12,"00")&TEXT(EC12,"00") -> SDN100109 | EE12: 10000 | EF12: 10000 | EG12: 10000 | EH12: 10000 | EI12: 10000 | EJ12: 10000 | EK12: 10000 | EL12: 10000 | EM12: 10000 | EN12: 10000 | EO12: 10000 | EP12: 10000 | EQ12: 10000 | ER12: 10000 | ES12: 10000 | ET12: 10000 | EU12: 10000 | EV12: 10000 | EW12: 10000 | EX12: 10000 | EY12: 10000 | EZ12: 10000 | FA12: 10000 | FB12: 10000 | FC12: 10000 | FD12: 0 | FE12: 0 | FF12: 0 | FG12: 0 | FH12: 0 | FI12: 0 | FJ12: 0 | FK12: 0 | FL12: 0 | FM12: 0 | FN12: 0 | FO12: 0 | FP12: 0 | FQ12: 0 | FR12: 0 | FS12: 0 | FT12: 0 | FU12: 0 | FV12: 0 | FW12: 0 | FX12: 0 | FY12: 0 | FZ12: 0 | GA12: 0 | GB12: 0 | GC12: 0 | GD12: 0 | GE12: 0 | GF12: 0 | GG12: 0 | GH12: 0 | GI12: 0 | GJ12: 0 | GK12: 0 | GL12: 0 | GM12: 0 | GN12: 0 | GO12: 0 | GP12: 0 | GQ12: 0 | GR12: 0 | GS12: 0 | GT12: 0 | GU12: 0 | GV12: 0 | GW12: 0 | GX12: 0 | GY12: 0 | GZ12: 0 | HA12: 0 | HB12: 0 | HC12: 0 | HD12: 0 | HE12: 0 | HF12: 0 | HG12: 0 | HH12: 0 | HI12: 0 | HJ12: 0 | HK12: 0 | HL12: 0 | HM12: 0 | HN12: 0 | HO12: 0 | HP12: 0 | HQ12: 0 | HR12: 0 | HS12: 0 | HT12: 0 | HU12: 0 | HV12: 0 | HW12: 0 | HX12: 0 | HY12: 0 | HZ12: 0 | IA12: 0 | IB12: 0 | IC12: 0 | ID12: 0 | IE12: 0 | IF12: 0 | IG12: 0 | IH12: 0 | II12: 0 | IJ12: 0 | IK12: 0
A13: 56 | B13: SDN10 | F13: 1 | H13: 1 | I13: 1 | J13: =B13&TEXT(F13,"00")&TEXT(H13,"00")&TEXT(I13,"00") -> SDN10010101 | K13: 960 | M13: 56 | N13: SDN10 | O13: 1 | P13: 10 | Q13: =N13&TEXT(O13,"00")&TEXT(P13,"00") -> SDN100110 | R13: 0 | S13: 0 | T13: 0 | U13: 0 | V13: 0 | W13: 0 | X13: 0 | Y13: 0 | Z13: 0 | AA13: 0 | AB13: 0 | AC13: 0 | AD13: 0 | AE13: 0 | AF13: 0 | AG13: 0 | AH13: 0 | AI13: 0 | AJ13: 0 | AK13: 0 | AL13: 0 | AM13: 0 | AN13: 0 | AO13: 0 | AP13: 10000 | AQ13: 0 | AR13: 0 | AS13: 0 | AT13: 0 | AU13: 0 | AV13: 0 | AW13: 0 | AX13: 0 | AY13: 0 | AZ13: 0 | BA13: 0 | BB13: 0 | BC13: 0 | BD13: 0 | BE13: 0 | BF13: 0 | BG13: 0 | BH13: 0 | BI13: 0 | BJ13: 0 | BK13: 0 | BL13: 0 | BM13: 0 | BN13: 0 | BO13: 0 | BP13: 0 | BQ13: 0 | BR13: 0 | BS13: 0 | BT13: 0 | BU13: 0 | BV13: 0 | BW13: 0 | BX13: 0 | BY13: 0 | BZ13: 0 | CA13: 0 | CB13: 0 | CC13: 0 | CD13: 0 | CE13: 0 | CF13: 0 | CG13: 0 | CH13: 0 | CI13: 0 | CJ13: 0 | CK13: 0 | CL13: 0 | CM13: 0 | CN13: 0 | CO13: 0 | CP13: 0 | CQ13: 0 | CR13: 0 | CS13: 0 | CT13: 0 | CU13: 0 | CV13: 0 | CW13: 0 | CX13: 0 | CY13: 0 | CZ13: 0 | DA13: 0 | DB13: 0 | DC13: 0 | DD13: 0 | DE13: 0 | DF13: 0 | DG13: 0 | DH13: 0 | DI13: 0 | DJ13: 0 | DK13: 0 | DL13: 0 | DM13: 0 | DN13: 0 | DO13: 0 | DP13: 0 | DQ13: 0 | DR13: 0 | DS13: 0 | DT13: 0 | DU13: 0 | DV13: 0 | DW13: 0 | DX13: 0 | DZ13: 56 | EA13: SDN10 | EB13: 1 | EC13: 10 | ED13: =EA13&TEXT(EB13,"00")&TEXT(EC13,"00") -> SDN100110 | EE13: 10000 | EF13: 10000 | EG13: 10000 | EH13: 10000 | EI13: 10000 | EJ13: 10000 | EK13: 10000 | EL13: 10000 | EM13: 10000 | EN13: 10000 | EO13: 10000 | EP13: 10000 | EQ13: 10000 | ER13: 10000 | ES13: 10000 | ET13: 10000 | EU13: 10000 | EV13: 10000 | EW13: 10000 | EX13: 10000 | EY13: 10000 | EZ13: 10000 | FA13: 10000 | FB13: 10000 | FC13: 10000 | FD13: 0 | FE13: 0 | FF13: 0 | FG13: 0 | FH13: 0 | FI13: 0 | FJ13: 0 | FK13: 0 | FL13: 0 | FM13: 0 | FN13: 0 | FO13: 0 | FP13: 0 | FQ13: 0 | FR13: 0 | FS13: 0 | FT13: 0 | FU13: 0 | FV13: 0 | FW13: 0 | FX13: 0 | FY13: 0 | FZ13: 0 | GA13: 0 | GB13: 0 | GC13: 0 | GD13: 0 | GE13: 0 | GF13: 0 | GG13: 0 | GH13: 0 | GI13: 0 | GJ13: 0 | GK13: 0 | GL13: 0 | GM13: 0 | GN13: 0 | GO13: 0 | GP13: 0 | GQ13: 0 | GR13: 0 | GS13: 0 | GT13: 0 | GU13: 0 | GV13: 0 | GW13: 0 | GX13: 0 | GY13: 0 | GZ13: 0 | HA13: 0 | HB13: 0 | HC13: 0 | HD13: 0 | HE13: 0 | HF13: 0 | HG13: 0 | HH13: 0 | HI13: 0 | HJ13: 0 | HK13: 0 | HL13: 0 | HM13: 0 | HN13: 0 | HO13: 0 | HP13: 0 | HQ13: 0 | HR13: 0 | HS13: 0 | HT13: 0 | HU13: 0 | HV13: 0 | HW13: 0 | HX13: 0 | HY13: 0 | HZ13: 0 | IA13: 0 | IB13: 0 | IC13: 0 | ID13: 0 | IE13: 0 | IF13: 0 | IG13: 0 | IH13: 0 | II13: 0 | IJ13: 0 | IK13: 0
A14: 56 | B14: SDN10 | F14: 1 | H14: 1 | I14: 2 | J14: =B14&TEXT(F14,"00")&TEXT(H14,"00")&TEXT(I14,"00") -> SDN10010102 | K14: 960 | M14: 56 | N14: SDN10 | O14: 1 | P14: 11 | Q14: =N14&TEXT(O14,"00")&TEXT(P14,"00") -> SDN100111 | R14: 0 | S14: 0 | T14: 0 | U14: 0 | V14: 0 | W14: 0 | X14: 0 | Y14: 0 | Z14: 0 | AA14: 0 | AB14: 0 | AC14: 0 | AD14: 0 | AE14: 0 | AF14: 0 | AG14: 0 | AH14: 0 | AI14: 0 | AJ14: 0 | AK14: 0 | AL14: 0 | AM14: 0 | AN14: 0 | AO14: 0 | AP14: 10000 | AQ14: 0 | AR14: 0 | AS14: 0 | AT14: 0 | AU14: 0 | AV14: 0 | AW14: 0 | AX14: 0 | AY14: 0 | AZ14: 0 | BA14: 0 | BB14: 0 | BC14: 0 | BD14: 0 | BE14: 0 | BF14: 0 | BG14: 0 | BH14: 0 | BI14: 0 | BJ14: 0 | BK14: 0 | BL14: 0 | BM14: 0 | BN14: 0 | BO14: 0 | BP14: 0 | BQ14: 0 | BR14: 0 | BS14: 0 | BT14: 0 | BU14: 0 | BV14: 0 | BW14: 0 | BX14: 0 | BY14: 0 | BZ14: 0 | CA14: 0 | CB14: 0 | CC14: 0 | CD14: 0 | CE14: 0 | CF14: 0 | CG14: 0 | CH14: 0 | CI14: 0 | CJ14: 0 | CK14: 0 | CL14: 0 | CM14: 0 | CN14: 0 | CO14: 0 | CP14: 0 | CQ14: 0 | CR14: 0 | CS14: 0 | CT14: 0 | CU14: 0 | CV14: 0 | CW14: 0 | CX14: 0 | CY14: 0 | CZ14: 0 | DA14: 0 | DB14: 0 | DC14: 0 | DD14: 0 | DE14: 0 | DF14: 0 | DG14: 0 | DH14: 0 | DI14: 0 | DJ14: 0 | DK14: 0 | DL14: 0 | DM14: 0 | DN14: 0 | DO14: 0 | DP14: 0 | DQ14: 0 | DR14: 0 | DS14: 0 | DT14: 0 | DU14: 0 | DV14: 0 | DW14: 0 | DX14: 0 | DZ14: 56 | EA14: SDN10 | EB14: 1 | EC14: 11 | ED14: =EA14&TEXT(EB14,"00")&TEXT(EC14,"00") -> SDN100111 | EE14: 10000 | EF14: 10000 | EG14: 10000 | EH14: 10000 | EI14: 10000 | EJ14: 10000 | EK14: 10000 | EL14: 10000 | EM14: 10000 | EN14: 10000 | EO14: 10000 | EP14: 10000 | EQ14: 10000 | ER14: 10000 | ES14: 10000 | ET14: 10000 | EU14: 10000 | EV14: 10000 | EW14: 10000 | EX14: 10000 | EY14: 10000 | EZ14: 10000 | FA14: 10000 | FB14: 10000 | FC14: 10000 | FD14: 0 | FE14: 0 | FF14: 0 | FG14: 0 | FH14: 0 | FI14: 0 | FJ14: 0 | FK14: 0 | FL14: 0 | FM14: 0 | FN14: 0 | FO14: 0 | FP14: 0 | FQ14: 0 | FR14: 0 | FS14: 0 | FT14: 0 | FU14: 0 | FV14: 0 | FW14: 0 | FX14: 0 | FY14: 0 | FZ14: 0 | GA14: 0 | GB14: 0 | GC14: 0 | GD14: 0 | GE14: 0 | GF14: 0 | GG14: 0 | GH14: 0 | GI14: 0 | GJ14: 0 | GK14: 0 | GL14: 0 | GM14: 0 | GN14: 0 | GO14: 0 | GP14: 0 | GQ14: 0 | GR14: 0 | GS14: 0 | GT14: 0 | GU14: 0 | GV14: 0 | GW14: 0 | GX14: 0 | GY14: 0 | GZ14: 0 | HA14: 0 | HB14: 0 | HC14: 0 | HD14: 0 | HE14: 0 | HF14: 0 | HG14: 0 | HH14: 0 | HI14: 0 | HJ14: 0 | HK14: 0 | HL14: 0 | HM14: 0 | HN14: 0 | HO14: 0 | HP14: 0 | HQ14: 0 | HR14: 0 | HS14: 0 | HT14: 0 | HU14: 0 | HV14: 0 | HW14: 0 | HX14: 0 | HY14: 0 | HZ14: 0 | IA14: 0 | IB14: 0 | IC14: 0 | ID14: 0 | IE14: 0 | IF14: 0 | IG14: 0 | IH14: 0 | II14: 0 | IJ14: 0 | IK14: 0
... A103: 56 | B103: SDN10 | F103: 1 | H103: 10 | I103: 1 | J103: =B103&TEXT(F103,"00")&TEXT(H103,"00")&TEXT(I103,"00") -> SDN10011001 | K103: 960 | M103: 56 | N103: SDN10 | O103: 2 | P103: 39 | Q103: =N103&TEXT(O103,"00")&TEXT(P103,"00") -> SDN100239 | R103: 0 | S103: 0 | T103: 0 | U103: 0 | V103: 0 | W103: 0 | X103: 0 | Y103: 0 | Z103: 0 | AA103: 0 | AB103: 0 | AC103: 0 | AD103: 0 | AE103: 0 | AF103: 0 | AG103: 0 | AH103: 0 | AI103: 0 | AJ103: 0 | AK103: 0 | AL103: 0 | AM103: 0 | AN103: 0 | AO103: 0 | AP103: 10000 | AQ103: 0 | AR103: 0 | AS103: 0 | AT103: 0 | AU103: 0 | AV103: 0 | AW103: 0 | AX103: 0 | AY103: 0 | AZ103: 0 | BA103: 0 | BB103: 0 | BC103: 0 | BD103: 0 | BE103: 0 | BF103: 0 | BG103: 0 | BH103: 0 | BI103: 0 | BJ103: 0 | BK103: 0 | BL103: 0 | BM103: 0 | BN103: 0 | BO103: 0 | BP103: 0 | BQ103: 0 | BR103: 0 | BS103: 0 | BT103: 0 | BU103: 0 | BV103: 0 | BW103: 0 | BX103: 0 | BY103: 0 | BZ103: 0 | CA103: 0 | CB103: 0 | CC103: 0 | CD103: 0 | CE103: 0 | CF103: 0 | CG103: 0 | CH103: 0 | CI103: 0 | CJ103: 0 | CK103: 0 | CL103: 0 | CM103: 0 | CN103: 0 | CO103: 0 | CP103: 0 | CQ103: 0 | CR103: 0 | CS103: 0 | CT103: 0 | CU103: 0 | CV103: 0 | CW103: 0 | CX103: 0 | CY103: 0 | CZ103: 0 | DA103: 0 | DB103: 0 | DC103: 0 | DD103: 0 | DE103: 0 | DF103: 0 | DG103: 0 | DH103: 0 | DI103: 0 | DJ103: 0 | DK103: 0 | DL103: 0 | DM103: 0 | DN103: 0 | DO103: 0 | DP103: 0 | DQ103: 0 | DR103: 0 | DS103: 0 | DT103: 0 | DU103: 0 | DV103: 0 | DW103: 0 | DX103: 0 | DZ103: 56 | EA103: SDN10 | EB103: 2 | EC103: 39 | ED103: =EA103&TEXT(EB103,"00")&TEXT(EC103,"00") -> SDN100239 | EE103: 10000 | EF103: 10000 | EG103: 10000 | EH103: 10000 | EI103: 10000 | EJ103: 10000 | EK103: 10000 | EL103: 10000 | EM103: 10000 | EN103: 10000 | EO103: 10000 | EP103: 10000 | EQ103: 10000 | ER103: 10000 | ES103: 10000 | ET103: 10000 | EU103: 10000 | EV103: 10000 | EW103: 10000 | EX103: 10000 | EY103: 10000 | EZ103: 10000 | FA103: 10000 | FB103: 10000 | FC103: 10000 | FD103: 0 | FE103: 0 | FF103: 0 | FG103: 0 | FH103: 0 | FI103: 0 | FJ103: 0 | FK103: 0 | FL103: 0 | FM103: 0 | FN103: 0 | FO103: 0 | FP103: 0 | FQ103: 0 | FR103: 0 | FS103: 0 | FT103: 0 | FU103: 0 | FV103: 0 | FW103: 0 | FX103: 0 | FY103: 0 | FZ103: 0 | GA103: 0 | GB103: 0 | GC103: 0 | GD103: 0 | GE103: 0 | GF103: 0 | GG103: 0 | GH103: 0 | GI103: 0 | GJ103: 0 | GK103: 0 | GL103: 0 | GM103: 0 | GN103: 0 | GO103: 0 | GP103: 0 | GQ103: 0 | GR103: 0 | GS103: 0 | GT103: 0 | GU103: 0 | GV103: 0 | GW103: 0 | GX103: 0 | GY103: 0 | GZ103: 0 | HA103: 0 | HB103: 0 | HC103: 0 | HD103: 0 | HE103: 0 | HF103: 0 | HG103: 0 | HH103: 0 | HI103: 0 | HJ103: 0 | HK103: 0 | HL103: 0 | HM103: 0 | HN103: 0 | HO103: 0 | HP103: 0 | HQ103: 0 | HR103: 0 | HS103: 0 | HT103: 0 | HU103: 0 | HV103: 0 | HW103: 0 | HX103: 0 | HY103: 0 | HZ103: 0 | IA103: 0 | IB103: 0 | IC103: 0 | ID103: 0 | IE103: 0 | IF103: 0 | IG103: 0 | IH103: 0 | II103: 0 | IJ103: 0 | IK103: 0
B104: SDN10 | F104: 1 | H104: 10 | I104: 2 | J104: =B104&TEXT(F104,"00")&TEXT(H104,"00")&TEXT(I104,"00") -> SDN10011002 | K104: 960 | N104: SDN10 | O104: 2 | P104: 40 | Q104: =N104&TEXT(O104,"00")&TEXT(P104,"00") -> SDN100240 | R104: 0 | S104: 0 | T104: 0 | U104: 0 | V104: 0 | W104: 0 | X104: 0 | Y104: 0 | Z104: 0 | AA104: 0 | AB104: 0 | AC104: 0 | AD104: 0 | AE104: 0 | AF104: 0 | AG104: 0 | AH104: 0 | AI104: 0 | AJ104: 0 | AK104: 0 | AL104: 0 | AM104: 0 | AN104: 0 | AO104: 0 | AP104: 10000 | AQ104: 0 | AR104: 0 | AS104: 0 | AT104: 0 | AU104: 0 | AV104: 0 | AW104: 0 | AX104: 0 | AY104: 0 | AZ104: 0 | BA104: 0 | BB104: 0 | BC104: 0 | BD104: 0 | BE104: 0 | BF104: 0 | BG104: 0 | BH104: 0 | BI104: 0 | BJ104: 0 | BK104: 0 | BL104: 0 | BM104: 0 | BN104: 0 | BO104: 0 | BP104: 0 | BQ104: 0 | BR104: 0 | BS104: 0 | BT104: 0 | BU104: 0 | BV104: 0 | BW104: 0 | BX104: 0 | BY104: 0 | BZ104: 0 | CA104: 0 | CB104: 0 | CC104: 0 | CD104: 0 | CE104: 0 | CF104: 0 | CG104: 0 | CH104: 0 | CI104: 0 | CJ104: 0 | CK104: 0 | CL104: 0 | CM104: 0 | CN104: 0 | CO104: 0 | CP104: 0 | CQ104: 0 | CR104: 0 | CS104: 0 | CT104: 0 | CU104: 0 | CV104: 0 | CW104: 0 | CX104: 0 | CY104: 0 | CZ104: 0 | DA104: 0 | DB104: 0 | DC104: 0 | DD104: 0 | DE104: 0 | DF104: 0 | DG104: 0 | DH104: 0 | DI104: 0 | DJ104: 0 | DK104: 0 | DL104: 0 | DM104: 0 | DN104: 0 | DO104: 0 | DP104: 0 | DQ104: 0 | DR104: 0 | DS104: 0 | DT104: 0 | DU104: 0 | DV104: 0 | DW104: 0 | DX104: 0 | EA104: SDN10 | EB104: 2 | EC104: 40 | ED104: =EA104&TEXT(EB104,"00")&TEXT(EC104,"00") -> SDN100240 | EE104: 10000 | EF104: 10000 | EG104: 10000 | EH104: 10000 | EI104: 10000 | EJ104: 10000 | EK104: 10000 | EL104: 10000 | EM104: 10000 | EN104: 10000 | EO104: 10000 | EP104: 10000 | EQ104: 10000 | ER104: 10000 | ES104: 10000 | ET104: 10000 | EU104: 10000 | EV104: 10000 | EW104: 10000 | EX104: 10000 | EY104: 10000 | EZ104: 10000 | FA104: 10000 | FB104: 10000 | FC104: 10000 | FD104: 0 | FE104: 0 | FF104: 0 | FG104: 0 | FH104: 0 | FI104: 0 | FJ104: 0 | FK104: 0 | FL104: 0 | FM104: 0 | FN104: 0 | FO104: 0 | FP104: 0 | FQ104: 0 | FR104: 0 | FS104: 0 | FT104: 0 | FU104: 0 | FV104: 0 | FW104: 0 | FX104: 0 | FY104: 0 | FZ104: 0 | GA104: 0 | GB104: 0 | GC104: 0 | GD104: 0 | GE104: 0 | GF104: 0 | GG104: 0 | GH104: 0 | GI104: 0 | GJ104: 0 | GK104: 0 | GL104: 0 | GM104: 0 | GN104: 0 | GO104: 0 | GP104: 0 | GQ104: 0 | GR104: 0 | GS104: 0 | GT104: 0 | GU104: 0 | GV104: 0 | GW104: 0 | GX104: 0 | GY104: 0 | GZ104: 0 | HA104: 0 | HB104: 0 | HC104: 0 | HD104: 0 | HE104: 0 | HF104: 0 | HG104: 0 | HH104: 0 | HI104: 0 | HJ104: 0 | HK104: 0 | HL104: 0 | HM104: 0 | HN104: 0 | HO104: 0 | HP104: 0 | HQ104: 0 | HR104: 0 | HS104: 0 | HT104: 0 | HU104: 0 | HV104: 0 | HW104: 0 | HX104: 0 | HY104: 0 | HZ104: 0 | IA104: 0 | IB104: 0 | IC104: 0 | ID104: 0 | IE104: 0 | IF104: 0 | IG104: 0 | IH104: 0 | II104: 0 | IJ104: 0 | IK104: 0
B105: SDN10 | F105: 1 | H105: 10 | I105: 3 | J105: =B105&TEXT(F105,"00")&TEXT(H105,"00")&TEXT(I105,"00") -> SDN10011003 | K105: 960 | N105: SDN10 | O105: 2 | P105: 41 | Q105: =N105&TEXT(O105,"00")&TEXT(P105,"00") -> SDN100241 | R105: 0 | S105: 0 | T105: 0 | U105: 0 | V105: 0 | W105: 0 | X105: 0 | Y105: 0 | Z105: 0 | AA105: 0 | AB105: 0 | AC105: 0 | AD105: 0 | AE105: 0 | AF105: 0 | AG105: 0 | AH105: 0 | AI105: 0 | AJ105: 0 | AK105: 0 | AL105: 0 | AM105: 0 | AN105: 0 | AO105: 0 | AP105: 10000 | AQ105: 0 | AR105: 0 | AS105: 0 | AT105: 0 | AU105: 0 | AV105: 0 | AW105: 0 | AX105: 0 | AY105: 0 | AZ105: 0 | BA105: 0 | BB105: 0 | BC105: 0 | BD105: 0 | BE105: 0 | BF105: 0 | BG105: 0 | BH105: 0 | BI105: 0 | BJ105: 0 | BK105: 0 | BL105: 0 | BM105: 0 | BN105: 0 | BO105: 0 | BP105: 0 | BQ105: 0 | BR105: 0 | BS105: 0 | BT105: 0 | BU105: 0 | BV105: 0 | BW105: 0 | BX105: 0 | BY105: 0 | BZ105: 0 | CA105: 0 | CB105: 0 | CC105: 0 | CD105: 0 | CE105: 0 | CF105: 0 | CG105: 0 | CH105: 0 | CI105: 0 | CJ105: 0 | CK105: 0 | CL105: 0 | CM105: 0 | CN105: 0 | CO105: 0 | CP105: 0 | CQ105: 0 | CR105: 0 | CS105: 0 | CT105: 0 | CU105: 0 | CV105: 0 | CW105: 0 | CX105: 0 | CY105: 0 | CZ105: 0 | DA105: 0 | DB105: 0 | DC105: 0 | DD105: 0 | DE105: 0 | DF105: 0 | DG105: 0 | DH105: 0 | DI105: 0 | DJ105: 0 | DK105: 0 | DL105: 0 | DM105: 0 | DN105: 0 | DO105: 0 | DP105: 0 | DQ105: 0 | DR105: 0 | DS105: 0 | DT105: 0 | DU105: 0 | DV105: 0 | DW105: 0 | DX105: 0 | EA105: SDN10 | EB105: 2 | EC105: 41 | ED105: =EA105&TEXT(EB105,"00")&TEXT(EC105,"00") -> SDN100241 | EE105: 10000 | EF105: 10000 | EG105: 10000 | EH105: 10000 | EI105: 10000 | EJ105: 10000 | EK105: 10000 | EL105: 10000 | EM105: 10000 | EN105: 10000 | EO105: 10000 | EP105: 10000 | EQ105: 10000 | ER105: 10000 | ES105: 10000 | ET105: 10000 | EU105: 10000 | EV105: 10000 | EW105: 10000 | EX105: 10000 | EY105: 10000 | EZ105: 10000 | FA105: 10000 | FB105: 10000 | FC105: 10000 | FD105: 0 | FE105: 0 | FF105: 0 | FG105: 0 | FH105: 0 | FI105: 0 | FJ105: 0 | FK105: 0 | FL105: 0 | FM105: 0 | FN105: 0 | FO105: 0 | FP105: 0 | FQ105: 0 | FR105: 0 | FS105: 0 | FT105: 0 | FU105: 0 | FV105: 0 | FW105: 0 | FX105: 0 | FY105: 0 | FZ105: 0 | GA105: 0 | GB105: 0 | GC105: 0 | GD105: 0 | GE105: 0 | GF105: 0 | GG105: 0 | GH105: 0 | GI105: 0 | GJ105: 0 | GK105: 0 | GL105: 0 | GM105: 0 | GN105: 0 | GO105: 0 | GP105: 0 | GQ105: 0 | GR105: 0 | GS105: 0 | GT105: 0 | GU105: 0 | GV105: 0 | GW105: 0 | GX105: 0 | GY105: 0 | GZ105: 0 | HA105: 0 | HB105: 0 | HC105: 0 | HD105: 0 | HE105: 0 | HF105: 0 | HG105: 0 | HH105: 0 | HI105: 0 | HJ105: 0 | HK105: 0 | HL105: 0 | HM105: 0 | HN105: 0 | HO105: 0 | HP105: 0 | HQ105: 0 | HR105: 0 | HS105: 0 | HT105: 0 | HU105: 0 | HV105: 0 | HW105: 0 | HX105: 0 | HY105: 0 | HZ105: 0 | IA105: 0 | IB105: 0 | IC105: 0 | ID105: 0 | IE105: 0 | IF105: 0 | IG105: 0 | IH105: 0 | II105: 0 | IJ105: 0 | IK105: 0
B106: SDN10 | F106: 1 | H106: 10 | I106: 4 | J106: =B106&TEXT(F106,"00")&TEXT(H106,"00")&TEXT(I106,"00") -> SDN10011004 | K106: 960 | N106: SDN10 | O106: 2 | P106: 42 | Q106: =N106&TEXT(O106,"00")&TEXT(P106,"00") -> SDN100242 | R106: 0 | S106: 0 | T106: 0 | U106: 0 | V106: 0 | W106: 0 | X106: 0 | Y106: 0 | Z106: 0 | AA106: 0 | AB106: 0 | AC106: 0 | AD106: 0 | AE106: 0 | AF106: 0 | AG106: 0 | AH106: 0 | AI106: 0 | AJ106: 0 | AK106: 0 | AL106: 0 | AM106: 0 | AN106: 0 | AO106: 0 | AP106: 10017 | AQ106: 0 | AR106: 0 | AS106: 0 | AT106: 0 | AU106: 0 | AV106: 0 | AW106: 0 | AX106: 0 | AY106: 0 | AZ106: 0 | BA106: 0 | BB106: 0 | BC106: 0 | BD106: 0 | BE106: 0 | BF106: 0 | BG106: 0 | BH106: 0 | BI106: 0 | BJ106: 0 | BK106: 0 | BL106: 0 | BM106: 0 | BN106: 0 | BO106: 0 | BP106: 0 | BQ106: 0 | BR106: 0 | BS106: 0 | BT106: 0 | BU106: 0 | BV106: 0 | BW106: 0 | BX106: 0 | BY106: 0 | BZ106: 0 | CA106: 0 | CB106: 0 | CC106: 0 | CD106: 0 | CE106: 0 | CF106: 0 | CG106: 0 | CH106: 0 | CI106: 0 | CJ106: 0 | CK106: 0 | CL106: 0 | CM106: 0 | CN106: 0 | CO106: 0 | CP106: 0 | CQ106: 0 | CR106: 0 | CS106: 0 | CT106: 0 | CU106: 0 | CV106: 0 | CW106: 0 | CX106: 0 | CY106: 0 | CZ106: 0 | DA106: 0 | DB106: 0 | DC106: 0 | DD106: 0 | DE106: 0 | DF106: 0 | DG106: 0 | DH106: 0 | DI106: 0 | DJ106: 0 | DK106: 0 | DL106: 0 | DM106: 0 | DN106: 0 | DO106: 0 | DP106: 0 | DQ106: 0 | DR106: 0 | DS106: 0 | DT106: 0 | DU106: 0 | DV106: 0 | DW106: 0 | DX106: 0 | EA106: SDN10 | EB106: 2 | EC106: 42 | ED106: =EA106&TEXT(EB106,"00")&TEXT(EC106,"00") -> SDN100242 | EE106: 10000 | EF106: 10000 | EG106: 10000 | EH106: 10000 | EI106: 10000 | EJ106: 10000 | EK106: 10000 | EL106: 10000 | EM106: 10000 | EN106: 10017 | EO106: 10017 | EP106: 10017 | EQ106: 10017 | ER106: 10017 | ES106: 10017 | ET106: 10017 | EU106: 10017 | EV106: 10017 | EW106: 10017 | EX106: 10017 | EY106: 10017 | EZ106: 10017 | FA106: 10017 | FB106: 10017 | FC106: 10017 | FD106: 0 | FE106: 0 | FF106: 0 | FG106: 0 | FH106: 0 | FI106: 0 | FJ106: 0 | FK106: 0 | FL106: 0 | FM106: 0 | FN106: 0 | FO106: 0 | FP106: 0 | FQ106: 0 | FR106: 0 | FS106: 0 | FT106: 0 | FU106: 0 | FV106: 0 | FW106: 0 | FX106: 0 | FY106: 0 | FZ106: 0 | GA106: 0 | GB106: 0 | GC106: 0 | GD106: 0 | GE106: 0 | GF106: 0 | GG106: 0 | GH106: 0 | GI106: 0 | GJ106: 0 | GK106: 0 | GL106: 0 | GM106: 0 | GN106: 0 | GO106: 0 | GP106: 0 | GQ106: 0 | GR106: 0 | GS106: 0 | GT106: 0 | GU106: 0 | GV106: 0 | GW106: 0 | GX106: 0 | GY106: 0 | GZ106: 0 | HA106: 0 | HB106: 0 | HC106: 0 | HD106: 0 | HE106: 0 | HF106: 0 | HG106: 0 | HH106: 0 | HI106: 0 | HJ106: 0 | HK106: 0 | HL106: 0 | HM106: 0 | HN106: 0 | HO106: 0 | HP106: 0 | HQ106: 0 | HR106: 0 | HS106: 0 | HT106: 0 | HU106: 0 | HV106: 0 | HW106: 0 | HX106: 0 | HY106: 0 | HZ106: 0 | IA106: 0 | IB106: 0 | IC106: 0 | ID106: 0 | IE106: 0 | IF106: 0 | IG106: 0 | IH106: 0 | II106: 0 | IJ106: 0 | IK106: 0
B107: SDN10 | F107: 1 | H107: 10 | I107: 5 | J107: =B107&TEXT(F107,"00")&TEXT(H107,"00")&TEXT(I107,"00") -> SDN10011005 | K107: 960 | N107: SDN10 | O107: 2 | P107: 43 | Q107: =N107&TEXT(O107,"00")&TEXT(P107,"00") -> SDN100243 | R107: 0 | S107: 0 | T107: 0 | U107: 0 | V107: 0 | W107: 0 | X107: 0 | Y107: 0 | Z107: 0 | AA107: 0 | AB107: 0 | AC107: 0 | AD107: 0 | AE107: 0 | AF107: 0 | AG107: 0 | AH107: 0 | AI107: 0 | AJ107: 0 | AK107: 0 | AL107: 0 | AM107: 0 | AN107: 0 | AO107: 0 | AP107: 10160.1 | AQ107: 0 | AR107: 0 | AS107: 0 | AT107: 0 | AU107: 0 | AV107: 0 | AW107: 0 | AX107: 0 | AY107: 0 | AZ107: 0 | BA107: 0 | BB107: 0 | BC107: 0 | BD107: 0 | BE107: 0 | BF107: 0 | BG107: 0 | BH107: 0 | BI107: 0 | BJ107: 0 | BK107: 0 | BL107: 0 | BM107: 0 | BN107: 0 | BO107: 0 | BP107: 0 | BQ107: 0 | BR107: 0 | BS107: 0 | BT107: 0 | BU107: 0 | BV107: 0 | BW107: 0 | BX107: 0 | BY107: 0 | BZ107: 0 | CA107: 0 | CB107: 0 | CC107: 0 | CD107: 0 | CE107: 0 | CF107: 0 | CG107: 0 | CH107: 0 | CI107: 0 | CJ107: 0 | CK107: 0 | CL107: 0 | CM107: 0 | CN107: 0 | CO107: 0 | CP107: 0 | CQ107: 0 | CR107: 0 | CS107: 0 | CT107: 0 | CU107: 0 | CV107: 0 | CW107: 0 | CX107: 0 | CY107: 0 | CZ107: 0 | DA107: 0 | DB107: 0 | DC107: 0 | DD107: 0 | DE107: 0 | DF107: 0 | DG107: 0 | DH107: 0 | DI107: 0 | DJ107: 0 | DK107: 0 | DL107: 0 | DM107: 0 | DN107: 0 | DO107: 0 | DP107: 0 | DQ107: 0 | DR107: 0 | DS107: 0 | DT107: 0 | DU107: 0 | DV107: 0 | DW107: 0 | DX107: 0 | EA107: SDN10 | EB107: 2 | EC107: 43 | ED107: =EA107&TEXT(EB107,"00")&TEXT(EC107,"00") -> SDN100243 | EE107: 10000 | EF107: 10000 | EG107: 10000 | EH107: 10000 | EI107: 10000 | EJ107: 10000 | EK107: 10000 | EL107: 10000 | EM107: 10000 | EN107: 10160.1 | EO107: 10160.1 | EP107: 10160.1 | EQ107: 10160.1 | ER107: 10160.1 | ES107: 10160.1 | ET107: 10160.1 | EU107: 10160.1 | EV107: 10160.1 | EW107: 10160.1 | EX107: 10160.1 | EY107: 10160.1 | EZ107: 10160.1 | FA107: 10160.1 | FB107: 10160.1 | FC107: 10160.1 | FD107: 0 | FE107: 0 | FF107: 0 | FG107: 0 | FH107: 0 | FI107: 0 | FJ107: 0 | FK107: 0 | FL107: 0 | FM107: 0 | FN107: 0 | FO107: 0 | FP107: 0 | FQ107: 0 | FR107: 0 | FS107: 0 | FT107: 0 | FU107: 0 | FV107: 0 | FW107: 0 | FX107: 0 | FY107: 0 | FZ107: 0 | GA107: 0 | GB107: 0 | GC107: 0 | GD107: 0 | GE107: 0 | GF107: 0 | GG107: 0 | GH107: 0 | GI107: 0 | GJ107: 0 | GK107: 0 | GL107: 0 | GM107: 0 | GN107: 0 | GO107: 0 | GP107: 0 | GQ107: 0 | GR107: 0 | GS107: 0 | GT107: 0 | GU107: 0 | GV107: 0 | GW107: 0 | GX107: 0 | GY107: 0 | GZ107: 0 | HA107: 0 | HB107: 0 | HC107: 0 | HD107: 0 | HE107: 0 | HF107: 0 | HG107: 0 | HH107: 0 | HI107: 0 | HJ107: 0 | HK107: 0 | HL107: 0 | HM107: 0 | HN107: 0 | HO107: 0 | HP107: 0 | HQ107: 0 | HR107: 0 | HS107: 0 | HT107: 0 | HU107: 0 | HV107: 0 | HW107: 0 | HX107: 0 | HY107: 0 | HZ107: 0 | IA107: 0 | IB107: 0 | IC107: 0 | ID107: 0 | IE107: 0 | IF107: 0 | IG107: 0 | IH107: 0 | II107: 0 | IJ107: 0 | IK107: 0
B108: SDN10 | F108: 1 | H108: 10 | I108: 6 | J108: =B108&TEXT(F108,"00")&TEXT(H108,"00")&TEXT(I108,"00") -> SDN10011006 | K108: 768 | N108: SDN10 | O108: 2 | P108: 44 | Q108: =N108&TEXT(O108,"00")&TEXT(P108,"00") -> SDN100244 | R108: 0 | S108: 0 | T108: 0 | U108: 0 | V108: 0 | W108: 0 | X108: 0 | Y108: 0 | Z108: 0 | AA108: 0 | AB108: 0 | AC108: 0 | AD108: 0 | AE108: 0 | AF108: 0 | AG108: 0 | AH108: 0 | AI108: 0 | AJ108: 0 | AK108: 0 | AL108: 0 | AM108: 0 | AN108: 0 | AO108: 0 | AP108: 10398.6 | AQ108: 0 | AR108: 0 | AS108: 0 | AT108: 0 | AU108: 0 | AV108: 0 | AW108: 0 | AX108: 0 | AY108: 0 | AZ108: 0 | BA108: 0 | BB108: 0 | BC108: 0 | BD108: 0 | BE108: 0 | BF108: 0 | BG108: 0 | BH108: 0 | BI108: 0 | BJ108: 0 | BK108: 0 | BL108: 0 | BM108: 0 | BN108: 0 | BO108: 0 | BP108: 0 | BQ108: 0 | BR108: 0 | BS108: 0 | BT108: 0 | BU108: 0 | BV108: 0 | BW108: 0 | BX108: 0 | BY108: 0 | BZ108: 0 | CA108: 0 | CB108: 0 | CC108: 0 | CD108: 0 | CE108: 0 | CF108: 0 | CG108: 0 | CH108: 0 | CI108: 0 | CJ108: 0 | CK108: 0 | CL108: 0 | CM108: 0 | CN108: 0 | CO108: 0 | CP108: 0 | CQ108: 0 | CR108: 0 | CS108: 0 | CT108: 0 | CU108: 0 | CV108: 0 | CW108: 0 | CX108: 0 | CY108: 0 | CZ108: 0 | DA108: 0 | DB108: 0 | DC108: 0 | DD108: 0 | DE108: 0 | DF108: 0 | DG108: 0 | DH108: 0 | DI108: 0 | DJ108: 0 | DK108: 0 | DL108: 0 | DM108: 0 | DN108: 0 | DO108: 0 | DP108: 0 | DQ108: 0 | DR108: 0 | DS108: 0 | DT108: 0 | DU108: 0 | DV108: 0 | DW108: 0 | DX108: 0 | EA108: SDN10 | EB108: 2 | EC108: 44 | ED108: =EA108&TEXT(EB108,"00")&TEXT(EC108,"00") -> SDN100244 | EE108: 10000 | EF108: 10000 | EG108: 10000 | EH108: 10000 | EI108: 10000 | EJ108: 10000 | EK108: 10000 | EL108: 10000 | EM108: 10000 | EN108: 10398.6 | EO108: 10398.6 | EP108: 10398.6 | EQ108: 10398.6 | ER108: 10398.6 | ES108: 10398.6 | ET108: 10398.6 | EU108: 10398.6 | EV108: 10398.6 | EW108: 10398.6 | EX108: 10398.6 | EY108: 10398.6 | EZ108: 10398.6 | FA108: 10398.6 | FB108: 10398.6 | FC108: 10398.6 | FD108: 0 | FE108: 0 | FF108: 0 | FG108: 0 | FH108: 0 | FI108: 0 | FJ108: 0 | FK108: 0 | FL108: 0 | FM108: 0 | FN108: 0 | FO108: 0 | FP108: 0 | FQ108: 0 | FR108: 0 | FS108: 0 | FT108: 0 | FU108: 0 | FV108: 0 | FW108: 0 | FX108: 0 | FY108: 0 | FZ108: 0 | GA108: 0 | GB108: 0 | GC108: 0 | GD108: 0 | GE108: 0 | GF108: 0 | GG108: 0 | GH108: 0 | GI108: 0 | GJ108: 0 | GK108: 0 | GL108: 0 | GM108: 0 | GN108: 0 | GO108: 0 | GP108: 0 | GQ108: 0 | GR108: 0 | GS108: 0 | GT108: 0 | GU108: 0 | GV108: 0 | GW108: 0 | GX108: 0 | GY108: 0 | GZ108: 0 | HA108: 0 | HB108: 0 | HC108: 0 | HD108: 0 | HE108: 0 | HF108: 0 | HG108: 0 | HH108: 0 | HI108: 0 | HJ108: 0 | HK108: 0 | HL108: 0 | HM108: 0 | HN108: 0 | HO108: 0 | HP108: 0 | HQ108: 0 | HR108: 0 | HS108: 0 | HT108: 0 | HU108: 0 | HV108: 0 | HW108: 0 | HX108: 0 | HY108: 0 | HZ108: 0 | IA108: 0 | IB108: 0 | IC108: 0 | ID108: 0 | IE108: 0 | IF108: 0 | IG108: 0 | IH108: 0 | II108: 0 | IJ108: 0 | IK108: 0
B109: SDN10 | F109: 1 | H109: 10 | I109: 7 | J109: =B109&TEXT(F109,"00")&TEXT(H109,"00")&TEXT(I109,"00") -> SDN10011007 | K109: 768 | N109: SDN10 | O109: 2 | P109: 45 | Q109: =N109&TEXT(O109,"00")&TEXT(P109,"00") -> SDN100245 | R109: 0 | S109: 0 | T109: 0 | U109: 0 | V109: 0 | W109: 0 | X109: 0 | Y109: 0 | Z109: 0 | AA109: 0 | AB109: 0 | AC109: 0 | AD109: 0 | AE109: 0 | AF109: 0 | AG109: 0 | AH109: 0 | AI109: 0 | AJ109: 0 | AK109: 0 | AL109: 0 | AM109: 0 | AN109: 0 | AO109: 0 | AP109: 10780.2 | AQ109: 0 | AR109: 0 | AS109: 0 | AT109: 0 | AU109: 0 | AV109: 0 | AW109: 0 | AX109: 0 | AY109: 0 | AZ109: 0 | BA109: 0 | BB109: 0 | BC109: 0 | BD109: 0 | BE109: 0 | BF109: 0 | BG109: 0 | BH109: 0 | BI109: 0 | BJ109: 0 | BK109: 0 | BL109: 0 | BM109: 0 | BN109: 0 | BO109: 0 | BP109: 0 | BQ109: 0 | BR109: 0 | BS109: 0 | BT109: 0 | BU109: 0 | BV109: 0 | BW109: 0 | BX109: 0 | BY109: 0 | BZ109: 0 | CA109: 0 | CB109: 0 | CC109: 0 | CD109: 0 | CE109: 0 | CF109: 0 | CG109: 0 | CH109: 0 | CI109: 0 | CJ109: 0 | CK109: 0 | CL109: 0 | CM109: 0 | CN109: 0 | CO109: 0 | CP109: 0 | CQ109: 0 | CR109: 0 | CS109: 0 | CT109: 0 | CU109: 0 | CV109: 0 | CW109: 0 | CX109: 0 | CY109: 0 | CZ109: 0 | DA109: 0 | DB109: 0 | DC109: 0 | DD109: 0 | DE109: 0 | DF109: 0 | DG109: 0 | DH109: 0 | DI109: 0 | DJ109: 0 | DK109: 0 | DL109: 0 | DM109: 0 | DN109: 0 | DO109: 0 | DP109: 0 | DQ109: 0 | DR109: 0 | DS109: 0 | DT109: 0 | DU109: 0 | DV109: 0 | DW109: 0 | DX109: 0 | EA109: SDN10 | EB109: 2 | EC109: 45 | ED109: =EA109&TEXT(EB109,"00")&TEXT(EC109,"00") -> SDN100245 | EE109: 10000 | EF109: 10000 | EG109: 10000 | EH109: 10000 | EI109: 10000 | EJ109: 10000 | EK109: 10000 | EL109: 10000 | EM109: 10000 | EN109: 10780.2 | EO109: 10780.2 | EP109: 10780.2 | EQ109: 10780.2 | ER109: 10780.2 | ES109: 10780.2 | ET109: 10780.2 | EU109: 10780.2 | EV109: 10780.2 | EW109: 10780.2 | EX109: 10780.2 | EY109: 10780.2 | EZ109: 10780.2 | FA109: 10780.2 | FB109: 10780.2 | FC109: 10780.2 | FD109: 0 | FE109: 0 | FF109: 0 | FG109: 0 | FH109: 0 | FI109: 0 | FJ109: 0 | FK109: 0 | FL109: 0 | FM109: 0 | FN109: 0 | FO109: 0 | FP109: 0 | FQ109: 0 | FR109: 0 | FS109: 0 | FT109: 0 | FU109: 0 | FV109: 0 | FW109: 0 | FX109: 0 | FY109: 0 | FZ109: 0 | GA109: 0 | GB109: 0 | GC109: 0 | GD109: 0 | GE109: 0 | GF109: 0 | GG109: 0 | GH109: 0 | GI109: 0 | GJ109: 0 | GK109: 0 | GL109: 0 | GM109: 0 | GN109: 0 | GO109: 0 | GP109: 0 | GQ109: 0 | GR109: 0 | GS109: 0 | GT109: 0 | GU109: 0 | GV109: 0 | GW109: 0 | GX109: 0 | GY109: 0 | GZ109: 0 | HA109: 0 | HB109: 0 | HC109: 0 | HD109: 0 | HE109: 0 | HF109: 0 | HG109: 0 | HH109: 0 | HI109: 0 | HJ109: 0 | HK109: 0 | HL109: 0 | HM109: 0 | HN109: 0 | HO109: 0 | HP109: 0 | HQ109: 0 | HR109: 0 | HS109: 0 | HT109: 0 | HU109: 0 | HV109: 0 | HW109: 0 | HX109: 0 | HY109: 0 | HZ109: 0 | IA109: 0 | IB109: 0 | IC109: 0 | ID109: 0 | IE109: 0 | IF109: 0 | IG109: 0 | IH109: 0 | II109: 0 | IJ109: 0 | IK109: 0
B110: SDN10 | F110: 1 | H110: 10 | I110: 8 | J110: =B110&TEXT(F110,"00")&TEXT(H110,"00")&TEXT(I110,"00") -> SDN10011008 | K110: 768 | N110: SDN10 | O110: 2 | P110: 46 | Q110: =N110&TEXT(O110,"00")&TEXT(P110,"00") -> SDN100246 | R110: 0 | S110: 0 | T110: 0 | U110: 0 | V110: 0 | W110: 0 | X110: 0 | Y110: 0 | Z110: 0 | AA110: 0 | AB110: 0 | AC110: 0 | AD110: 0 | AE110: 0 | AF110: 0 | AG110: 0 | AH110: 0 | AI110: 0 | AJ110: 0 | AK110: 0 | AL110: 0 | AM110: 0 | AN110: 0 | AO110: 0 | AP110: 11018.7 | AQ110: 0 | AR110: 0 | AS110: 0 | AT110: 0 | AU110: 0 | AV110: 0 | AW110: 0 | AX110: 0 | AY110: 0 | AZ110: 0 | BA110: 0 | BB110: 0 | BC110: 0 | BD110: 0 | BE110: 0 | BF110: 0 | BG110: 0 | BH110: 0 | BI110: 0 | BJ110: 0 | BK110: 0 | BL110: 0 | BM110: 0 | BN110: 0 | BO110: 0 | BP110: 0 | BQ110: 0 | BR110: 0 | BS110: 0 | BT110: 0 | BU110: 0 | BV110: 0 | BW110: 0 | BX110: 0 | BY110: 0 | BZ110: 0 | CA110: 0 | CB110: 0 | CC110: 0 | CD110: 0 | CE110: 0 | CF110: 0 | CG110: 0 | CH110: 0 | CI110: 0 | CJ110: 0 | CK110: 0 | CL110: 0 | CM110: 0 | CN110: 0 | CO110: 0 | CP110: 0 | CQ110: 0 | CR110: 0 | CS110: 0 | CT110: 0 | CU110: 0 | CV110: 0 | CW110: 0 | CX110: 0 | CY110: 0 | CZ110: 0 | DA110: 0 | DB110: 0 | DC110: 0 | DD110: 0 | DE110: 0 | DF110: 0 | DG110: 0 | DH110: 0 | DI110: 0 | DJ110: 0 | DK110: 0 | DL110: 0 | DM110: 0 | DN110: 0 | DO110: 0 | DP110: 0 | DQ110: 0 | DR110: 0 | DS110: 0 | DT110: 0 | DU110: 0 | DV110: 0 | DW110: 0 | DX110: 0 | EA110: SDN10 | EB110: 2 | EC110: 46 | ED110: =EA110&TEXT(EB110,"00")&TEXT(EC110,"00") -> SDN100246 | EE110: 10000 | EF110: 10000 | EG110: 10000 | EH110: 10000 | EI110: 10000 | EJ110: 10000 | EK110: 10000 | EL110: 10000 | EM110: 10039.3 | EN110: 11018.7 | EO110: 11018.7 | EP110: 11018.7 | EQ110: 11018.7 | ER110: 11018.7 | ES110: 11018.7 | ET110: 11018.7 | EU110: 11018.7 | EV110: 11018.7 | EW110: 11018.7 | EX110: 11018.7 | EY110: 11018.7 | EZ110: 11018.7 | FA110: 11018.7 | FB110: 11018.7 | FC110: 11018.7 | FD110: 0 | FE110: 0 | FF110: 0 | FG110: 0 | FH110: 0 | FI110: 0 | FJ110: 0 | FK110: 0 | FL110: 0 | FM110: 0 | FN110: 0 | FO110: 0 | FP110: 0 | FQ110: 0 | FR110: 0 | FS110: 0 | FT110: 0 | FU110: 0 | FV110: 0 | FW110: 0 | FX110: 0 | FY110: 0 | FZ110: 0 | GA110: 0 | GB110: 0 | GC110: 0 | GD110: 0 | GE110: 0 | GF110: 0 | GG110: 0 | GH110: 0 | GI110: 0 | GJ110: 0 | GK110: 0 | GL110: 0 | GM110: 0 | GN110: 0 | GO110: 0 | GP110: 0 | GQ110: 0 | GR110: 0 | GS110: 0 | GT110: 0 | GU110: 0 | GV110: 0 | GW110: 0 | GX110: 0 | GY110: 0 | GZ110: 0 | HA110: 0 | HB110: 0 | HC110: 0 | HD110: 0 | HE110: 0 | HF110: 0 | HG110: 0 | HH110: 0 | HI110: 0 | HJ110: 0 | HK110: 0 | HL110: 0 | HM110: 0 | HN110: 0 | HO110: 0 | HP110: 0 | HQ110: 0 | HR110: 0 | HS110: 0 | HT110: 0 | HU110: 0 | HV110: 0 | HW110: 0 | HX110: 0 | HY110: 0 | HZ110: 0 | IA110: 0 | IB110: 0 | IC110: 0 | ID110: 0 | IE110: 0 | IF110: 0 | IG110: 0 | IH110: 0 | II110: 0 | IJ110: 0 | IK110: 0
B111: SDN10 | F111: 1 | H111: 10 | I111: 9 | J111: =B111&TEXT(F111,"00")&TEXT(H111,"00")&TEXT(I111,"00") -> SDN10011009 | K111: 768 | N111: SDN10 | O111: 2 | P111: 47 | Q111: =N111&TEXT(O111,"00")&TEXT(P111,"00") -> SDN100247 | R111: 0 | S111: 0 | T111: 0 | U111: 0 | V111: 0 | W111: 0 | X111: 0 | Y111: 0 | Z111: 0 | AA111: 0 | AB111: 0 | AC111: 0 | AD111: 0 | AE111: 0 | AF111: 0 | AG111: 0 | AH111: 0 | AI111: 0 | AJ111: 0 | AK111: 0 | AL111: 0 | AM111: 0 | AN111: 0 | AO111: 0 | AP111: 11257.2 | AQ111: 0 | AR111: 0 | AS111: 0 | AT111: 0 | AU111: 0 | AV111: 0 | AW111: 0 | AX111: 0 | AY111: 0 | AZ111: 0 | BA111: 0 | BB111: 0 | BC111: 0 | BD111: 0 | BE111: 0 | BF111: 0 | BG111: 0 | BH111: 0 | BI111: 0 | BJ111: 0 | BK111: 0 | BL111: 0 | BM111: 0 | BN111: 0 | BO111: 0 | BP111: 0 | BQ111: 0 | BR111: 0 | BS111: 0 | BT111: 0 | BU111: 0 | BV111: 0 | BW111: 0 | BX111: 0 | BY111: 0 | BZ111: 0 | CA111: 0 | CB111: 0 | CC111: 0 | CD111: 0 | CE111: 0 | CF111: 0 | CG111: 0 | CH111: 0 | CI111: 0 | CJ111: 0 | CK111: 0 | CL111: 0 | CM111: 0 | CN111: 0 | CO111: 0 | CP111: 0 | CQ111: 0 | CR111: 0 | CS111: 0 | CT111: 0 | CU111: 0 | CV111: 0 | CW111: 0 | CX111: 0 | CY111: 0 | CZ111: 0 | DA111: 0 | DB111: 0 | DC111: 0 | DD111: 0 | DE111: 0 | DF111: 0 | DG111: 0 | DH111: 0 | DI111: 0 | DJ111: 0 | DK111: 0 | DL111: 0 | DM111: 0 | DN111: 0 | DO111: 0 | DP111: 0 | DQ111: 0 | DR111: 0 | DS111: 0 | DT111: 0 | DU111: 0 | DV111: 0 | DW111: 0 | DX111: 0 | EA111: SDN10 | EB111: 2 | EC111: 47 | ED111: =EA111&TEXT(EB111,"00")&TEXT(EC111,"00") -> SDN100247 | EE111: 10000 | EF111: 10000 | EG111: 10000 | EH111: 10000 | EI111: 10000 | EJ111: 10000 | EK111: 10000 | EL111: 10000 | EM111: 10256.6 | EN111: 11257.2 | EO111: 11257.2 | EP111: 11257.2 | EQ111: 11257.2 | ER111: 11257.2 | ES111: 11257.2 | ET111: 11257.2 | EU111: 11257.2 | EV111: 11257.2 | EW111: 11257.2 | EX111: 11257.2 | EY111: 11257.2 | EZ111: 11257.2 | FA111: 11257.2 | FB111: 11257.2 | FC111: 11257.2 | FD111: 0 | FE111: 0 | FF111: 0 | FG111: 0 | FH111: 0 | FI111: 0 | FJ111: 0 | FK111: 0 | FL111: 0 | FM111: 0 | FN111: 0 | FO111: 0 | FP111: 0 | FQ111: 0 | FR111: 0 | FS111: 0 | FT111: 0 | FU111: 0 | FV111: 0 | FW111: 0 | FX111: 0 | FY111: 0 | FZ111: 0 | GA111: 0 | GB111: 0 | GC111: 0 | GD111: 0 | GE111: 0 | GF111: 0 | GG111: 0 | GH111: 0 | GI111: 0 | GJ111: 0 | GK111: 0 | GL111: 0 | GM111: 0 | GN111: 0 | GO111: 0 | GP111: 0 | GQ111: 0 | GR111: 0 | GS111: 0 | GT111: 0 | GU111: 0 | GV111: 0 | GW111: 0 | GX111: 0 | GY111: 0 | GZ111: 0 | HA111: 0 | HB111: 0 | HC111: 0 | HD111: 0 | HE111: 0 | HF111: 0 | HG111: 0 | HH111: 0 | HI111: 0 | HJ111: 0 | HK111: 0 | HL111: 0 | HM111: 0 | HN111: 0 | HO111: 0 | HP111: 0 | HQ111: 0 | HR111: 0 | HS111: 0 | HT111: 0 | HU111: 0 | HV111: 0 | HW111: 0 | HX111: 0 | HY111: 0 | HZ111: 0 | IA111: 0 | IB111: 0 | IC111: 0 | ID111: 0 | IE111: 0 | IF111: 0 | IG111: 0 | IH111: 0 | II111: 0 | IJ111: 0 | IK111: 0
B112: SDN10 | F112: 1 | H112: 10 | I112: 10 | J112: =B112&TEXT(F112,"00")&TEXT(H112,"00")&TEXT(I112,"00") -> SDN10011010 | K112: 768 | N112: SDN10 | O112: 2 | P112: 48 | Q112: =N112&TEXT(O112,"00")&TEXT(P112,"00") -> SDN100248 | R112: 0 | S112: 0 | T112: 0 | U112: 0 | V112: 0 | W112: 0 | X112: 0 | Y112: 0 | Z112: 0 | AA112: 0 | AB112: 0 | AC112: 0 | AD112: 0 | AE112: 0 | AF112: 0 | AG112: 0 | AH112: 0 | AI112: 0 | AJ112: 0 | AK112: 0 | AL112: 0 | AM112: 0 | AN112: 0 | AO112: 0 | AP112: 11591.1 | AQ112: 0 | AR112: 0 | AS112: 0 | AT112: 0 | AU112: 0 | AV112: 0 | AW112: 0 | AX112: 0 | AY112: 0 | AZ112: 0 | BA112: 0 | BB112: 0 | BC112: 0 | BD112: 0 | BE112: 0 | BF112: 0 | BG112: 0 | BH112: 0 | BI112: 0 | BJ112: 0 | BK112: 0 | BL112: 0 | BM112: 0 | BN112: 0 | BO112: 0 | BP112: 0 | BQ112: 0 | BR112: 0 | BS112: 0 | BT112: 0 | BU112: 0 | BV112: 0 | BW112: 0 | BX112: 0 | BY112: 0 | BZ112: 0 | CA112: 0 | CB112: 0 | CC112: 0 | CD112: 0 | CE112: 0 | CF112: 0 | CG112: 0 | CH112: 0 | CI112: 0 | CJ112: 0 | CK112: 0 | CL112: 0 | CM112: 0 | CN112: 0 | CO112: 0 | CP112: 0 | CQ112: 0 | CR112: 0 | CS112: 0 | CT112: 0 | CU112: 0 | CV112: 0 | CW112: 0 | CX112: 0 | CY112: 0 | CZ112: 0 | DA112: 0 | DB112: 0 | DC112: 0 | DD112: 0 | DE112: 0 | DF112: 0 | DG112: 0 | DH112: 0 | DI112: 0 | DJ112: 0 | DK112: 0 | DL112: 0 | DM112: 0 | DN112: 0 | DO112: 0 | DP112: 0 | DQ112: 0 | DR112: 0 | DS112: 0 | DT112: 0 | DU112: 0 | DV112: 0 | DW112: 0 | DX112: 0 | EA112: SDN10 | EB112: 2 | EC112: 48 | ED112: =EA112&TEXT(EB112,"00")&TEXT(EC112,"00") -> SDN100248 | EE112: 10000 | EF112: 10000 | EG112: 10000 | EH112: 10000 | EI112: 10000 | EJ112: 10000 | EK112: 10000 | EL112: 10000 | EM112: 10560.8 | EN112: 11591.1 | EO112: 11591.1 | EP112: 11591.1 | EQ112: 11591.1 | ER112: 11591.1 | ES112: 11591.1 | ET112: 11591.1 | EU112: 11591.1 | EV112: 11591.1 | EW112: 11591.1 | EX112: 11591.1 | EY112: 11591.1 | EZ112: 11591.1 | FA112: 11591.1 | FB112: 11591.1 | FC112: 11591.1 | FD112: 0 | FE112: 0 | FF112: 0 | FG112: 0 | FH112: 0 | FI112: 0 | FJ112: 0 | FK112: 0 | FL112: 0 | FM112: 0 | FN112: 0 | FO112: 0 | FP112: 0 | FQ112: 0 | FR112: 0 | FS112: 0 | FT112: 0 | FU112: 0 | FV112: 0 | FW112: 0 | FX112: 0 | FY112: 0 | FZ112: 0 | GA112: 0 | GB112: 0 | GC112: 0 | GD112: 0 | GE112: 0 | GF112: 0 | GG112: 0 | GH112: 0 | GI112: 0 | GJ112: 0 | GK112: 0 | GL112: 0 | GM112: 0 | GN112: 0 | GO112: 0 | GP112: 0 | GQ112: 0 | GR112: 0 | GS112: 0 | GT112: 0 | GU112: 0 | GV112: 0 | GW112: 0 | GX112: 0 | GY112: 0 | GZ112: 0 | HA112: 0 | HB112: 0 | HC112: 0 | HD112: 0 | HE112: 0 | HF112: 0 | HG112: 0 | HH112: 0 | HI112: 0 | HJ112: 0 | HK112: 0 | HL112: 0 | HM112: 0 | HN112: 0 | HO112: 0 | HP112: 0 | HQ112: 0 | HR112: 0 | HS112: 0 | HT112: 0 | HU112: 0 | HV112: 0 | HW112: 0 | HX112: 0 | HY112: 0 | HZ112: 0 | IA112: 0 | IB112: 0 | IC112: 0 | ID112: 0 | IE112: 0 | IF112: 0 | IG112: 0 | IH112: 0 | II112: 0 | IJ112: 0 | IK112: 0
B113: SDN10 | F113: 1 | H113: 11 | I113: 1 | J113: =B113&TEXT(F113,"00")&TEXT(H113,"00")&TEXT(I113,"00") -> SDN10011101 | K113: 965 | N113: SDN10 | O113: 2 | P113: 49 | Q113: =N113&TEXT(O113,"00")&TEXT(P113,"00") -> SDN100249 | R113: 0 | S113: 0 | T113: 0 | U113: 0 | V113: 0 | W113: 0 | X113: 0 | Y113: 0 | Z113: 0 | AA113: 0 | AB113: 0 | AC113: 0 | AD113: 0 | AE113: 0 | AF113: 0 | AG113: 0 | AH113: 0 | AI113: 0 | AJ113: 0 | AK113: 0 | AL113: 0 | AM113: 0 | AN113: 0 | AO113: 0 | AP113: 11877.3 | AQ113: 0 | AR113: 0 | AS113: 0 | AT113: 0 | AU113: 0 | AV113: 0 | AW113: 0 | AX113: 0 | AY113: 0 | AZ113: 0 | BA113: 0 | BB113: 0 | BC113: 0 | BD113: 0 | BE113: 0 | BF113: 0 | BG113: 0 | BH113: 0 | BI113: 0 | BJ113: 0 | BK113: 0 | BL113: 0 | BM113: 0 | BN113: 0 | BO113: 0 | BP113: 0 | BQ113: 0 | BR113: 0 | BS113: 0 | BT113: 0 | BU113: 0 | BV113: 0 | BW113: 0 | BX113: 0 | BY113: 0 | BZ113: 0 | CA113: 0 | CB113: 0 | CC113: 0 | CD113: 0 | CE113: 0 | CF113: 0 | CG113: 0 | CH113: 0 | CI113: 0 | CJ113: 0 | CK113: 0 | CL113: 0 | CM113: 0 | CN113: 0 | CO113: 0 | CP113: 0 | CQ113: 0 | CR113: 0 | CS113: 0 | CT113: 0 | CU113: 0 | CV113: 0 | CW113: 0 | CX113: 0 | CY113: 0 | CZ113: 0 | DA113: 0 | DB113: 0 | DC113: 0 | DD113: 0 | DE113: 0 | DF113: 0 | DG113: 0 | DH113: 0 | DI113: 0 | DJ113: 0 | DK113: 0 | DL113: 0 | DM113: 0 | DN113: 0 | DO113: 0 | DP113: 0 | DQ113: 0 | DR113: 0 | DS113: 0 | DT113: 0 | DU113: 0 | DV113: 0 | DW113: 0 | DX113: 0 | EA113: SDN10 | EB113: 2 | EC113: 49 | ED113: =EA113&TEXT(EB113,"00")&TEXT(EC113,"00") -> SDN100249 | EE113: 10000 | EF113: 10000 | EG113: 10000 | EH113: 10000 | EI113: 10000 | EJ113: 10000 | EK113: 10000 | EL113: 10000 | EM113: 10821.5 | EN113: 11877.3 | EO113: 11877.3 | EP113: 11877.3 | EQ113: 11877.3 | ER113: 11877.3 | ES113: 11877.3 | ET113: 11877.3 | EU113: 11877.3 | EV113: 11877.3 | EW113: 11877.3 | EX113: 11877.3 | EY113: 11877.3 | EZ113: 11877.3 | FA113: 11877.3 | FB113: 11877.3 | FC113: 11877.3 | FD113: 0 | FE113: 0 | FF113: 0 | FG113: 0 | FH113: 0 | FI113: 0 | FJ113: 0 | FK113: 0 | FL113: 0 | FM113: 0 | FN113: 0 | FO113: 0 | FP113: 0 | FQ113: 0 | FR113: 0 | FS113: 0 | FT113: 0 | FU113: 0 | FV113: 0 | FW113: 0 | FX113: 0 | FY113: 0 | FZ113: 0 | GA113: 0 | GB113: 0 | GC113: 0 | GD113: 0 | GE113: 0 | GF113: 0 | GG113: 0 | GH113: 0 | GI113: 0 | GJ113: 0 | GK113: 0 | GL113: 0 | GM113: 0 | GN113: 0 | GO113: 0 | GP113: 0 | GQ113: 0 | GR113: 0 | GS113: 0 | GT113: 0 | GU113: 0 | GV113: 0 | GW113: 0 | GX113: 0 | GY113: 0 | GZ113: 0 | HA113: 0 | HB113: 0 | HC113: 0 | HD113: 0 | HE113: 0 | HF113: 0 | HG113: 0 | HH113: 0 | HI113: 0 | HJ113: 0 | HK113: 0 | HL113: 0 | HM113: 0 | HN113: 0 | HO113: 0 | HP113: 0 | HQ113: 0 | HR113: 0 | HS113: 0 | HT113: 0 | HU113: 0 | HV113: 0 | HW113: 0 | HX113: 0 | HY113: 0 | HZ113: 0 | IA113: 0 | IB113: 0 | IC113: 0 | ID113: 0 | IE113: 0 | IF113: 0 | IG113: 0 | IH113: 0 | II113: 0 | IJ113: 0 | IK113: 0
B114: SDN10 | F114: 1 | H114: 11 | I114: 2 | J114: =B114&TEXT(F114,"00")&TEXT(H114,"00")&TEXT(I114,"00") -> SDN10011102 | K114: 965 | N114: SDN10 | O114: 2 | P114: 50 | Q114: =N114&TEXT(O114,"00")&TEXT(P114,"00") -> SDN100250 | R114: 0 | S114: 0 | T114: 0 | U114: 0 | V114: 0 | W114: 0 | X114: 0 | Y114: 0 | Z114: 0 | AA114: 0 | AB114: 0 | AC114: 0 | AD114: 0 | AE114: 0 | AF114: 0 | AG114: 0 | AH114: 0 | AI114: 0 | AJ114: 0 | AK114: 0 | AL114: 0 | AM114: 0 | AN114: 0 | AO114: 0 | AP114: 12211.2 | AQ114: 0 | AR114: 0 | AS114: 0 | AT114: 0 | AU114: 0 | AV114: 0 | AW114: 0 | AX114: 0 | AY114: 0 | AZ114: 0 | BA114: 0 | BB114: 0 | BC114: 0 | BD114: 0 | BE114: 0 | BF114: 0 | BG114: 0 | BH114: 0 | BI114: 0 | BJ114: 0 | BK114: 0 | BL114: 0 | BM114: 0 | BN114: 0 | BO114: 0 | BP114: 0 | BQ114: 0 | BR114: 0 | BS114: 0 | BT114: 0 | BU114: 0 | BV114: 0 | BW114: 0 | BX114: 0 | BY114: 0 | BZ114: 0 | CA114: 0 | CB114: 0 | CC114: 0 | CD114: 0 | CE114: 0 | CF114: 0 | CG114: 0 | CH114: 0 | CI114: 0 | CJ114: 0 | CK114: 0 | CL114: 0 | CM114: 0 | CN114: 0 | CO114: 0 | CP114: 0 | CQ114: 0 | CR114: 0 | CS114: 0 | CT114: 0 | CU114: 0 | CV114: 0 | CW114: 0 | CX114: 0 | CY114: 0 | CZ114: 0 | DA114: 0 | DB114: 0 | DC114: 0 | DD114: 0 | DE114: 0 | DF114: 0 | DG114: 0 | DH114: 0 | DI114: 0 | DJ114: 0 | DK114: 0 | DL114: 0 | DM114: 0 | DN114: 0 | DO114: 0 | DP114: 0 | DQ114: 0 | DR114: 0 | DS114: 0 | DT114: 0 | DU114: 0 | DV114: 0 | DW114: 0 | DX114: 0 | EA114: SDN10 | EB114: 2 | EC114: 50 | ED114: =EA114&TEXT(EB114,"00")&TEXT(EC114,"00") -> SDN100250 | EE114: 10000 | EF114: 10000 | EG114: 10000 | EH114: 10000 | EI114: 10000 | EJ114: 10000 | EK114: 10000 | EL114: 10040.3 | EM114: 11125.8 | EN114: 12211.2 | EO114: 12211.2 | EP114: 12211.2 | EQ114: 12211.2 | ER114: 12211.2 | ES114: 12211.2 | ET114: 12211.2 | EU114: 12211.2 | EV114: 12211.2 | EW114: 12211.2 | EX114: 12211.2 | EY114: 12211.2 | EZ114: 12211.2 | FA114: 12211.2 | FB114: 12211.2 | FC114: 12211.2 | FD114: 0 | FE114: 0 | FF114: 0 | FG114: 0 | FH114: 0 | FI114: 0 | FJ114: 0 | FK114: 0 | FL114: 0 | FM114: 0 | FN114: 0 | FO114: 0 | FP114: 0 | FQ114: 0 | FR114: 0 | FS114: 0 | FT114: 0 | FU114: 0 | FV114: 0 | FW114: 0 | FX114: 0 | FY114: 0 | FZ114: 0 | GA114: 0 | GB114: 0 | GC114: 0 | GD114: 0 | GE114: 0 | GF114: 0 | GG114: 0 | GH114: 0 | GI114: 0 | GJ114: 0 | GK114: 0 | GL114: 0 | GM114: 0 | GN114: 0 | GO114: 0 | GP114: 0 | GQ114: 0 | GR114: 0 | GS114: 0 | GT114: 0 | GU114: 0 | GV114: 0 | GW114: 0 | GX114: 0 | GY114: 0 | GZ114: 0 | HA114: 0 | HB114: 0 | HC114: 0 | HD114: 0 | HE114: 0 | HF114: 0 | HG114: 0 | HH114: 0 | HI114: 0 | HJ114: 0 | HK114: 0 | HL114: 0 | HM114: 0 | HN114: 0 | HO114: 0 | HP114: 0 | HQ114: 0 | HR114: 0 | HS114: 0 | HT114: 0 | HU114: 0 | HV114: 0 | HW114: 0 | HX114: 0 | HY114: 0 | HZ114: 0 | IA114: 0 | IB114: 0 | IC114: 0 | ID114: 0 | IE114: 0 | IF114: 0 | IG114: 0 | IH114: 0 | II114: 0 | IJ114: 0 | IK114: 0
B115: SDN10 | F115: 1 | H115: 11 | I115: 3 | J115: =B115&TEXT(F115,"00")&TEXT(H115,"00")&TEXT(I115,"00") -> SDN10011103 | K115: 965 | N115: SDN10 | O115: 2 | P115: 51 | Q115: =N115&TEXT(O115,"00")&TEXT(P115,"00") -> SDN100251 | R115: 0 | S115: 0 | T115: 0 | U115: 0 | V115: 0 | W115: 0 | X115: 0 | Y115: 0 | Z115: 0 | AA115: 0 | AB115: 0 | AC115: 0 | AD115: 0 | AE115: 0 | AF115: 0 | AG115: 0 | AH115: 0 | AI115: 0 | AJ115: 0 | AK115: 0 | AL115: 0 | AM115: 0 | AN115: 0 | AO115: 0 | AP115: 12545.1 | AQ115: 0 | AR115: 0 | AS115: 0 | AT115: 0 | AU115: 0 | AV115: 0 | AW115: 0 | AX115: 0 | AY115: 0 | AZ115: 0 | BA115: 0 | BB115: 0 | BC115: 0 | BD115: 0 | BE115: 0 | BF115: 0 | BG115: 0 | BH115: 0 | BI115: 0 | BJ115: 0 | BK115: 0 | BL115: 0 | BM115: 0 | BN115: 0 | BO115: 0 | BP115: 0 | BQ115: 0 | BR115: 0 | BS115: 0 | BT115: 0 | BU115: 0 | BV115: 0 | BW115: 0 | BX115: 0 | BY115: 0 | BZ115: 0 | CA115: 0 | CB115: 0 | CC115: 0 | CD115: 0 | CE115: 0 | CF115: 0 | CG115: 0 | CH115: 0 | CI115: 0 | CJ115: 0 | CK115: 0 | CL115: 0 | CM115: 0 | CN115: 0 | CO115: 0 | CP115: 0 | CQ115: 0 | CR115: 0 | CS115: 0 | CT115: 0 | CU115: 0 | CV115: 0 | CW115: 0 | CX115: 0 | CY115: 0 | CZ115: 0 | DA115: 0 | DB115: 0 | DC115: 0 | DD115: 0 | DE115: 0 | DF115: 0 | DG115: 0 | DH115: 0 | DI115: 0 | DJ115: 0 | DK115: 0 | DL115: 0 | DM115: 0 | DN115: 0 | DO115: 0 | DP115: 0 | DQ115: 0 | DR115: 0 | DS115: 0 | DT115: 0 | DU115: 0 | DV115: 0 | DW115: 0 | DX115: 0 | EA115: SDN10 | EB115: 2 | EC115: 51 | ED115: =EA115&TEXT(EB115,"00")&TEXT(EC115,"00") -> SDN100251 | EE115: 10000 | EF115: 10000 | EG115: 10000 | EH115: 10000 | EI115: 10000 | EJ115: 10000 | EK115: 10000 | EL115: 10314.9 | EM115: 11430 | EN115: 12545.1 | EO115: 12545.1 | EP115: 12545.1 | EQ115: 12545.1 | ER115: 12545.1 | ES115: 12545.1 | ET115: 12545.1 | EU115: 12545.1 | EV115: 12545.1 | EW115: 12545.1 | EX115: 12545.1 | EY115: 12545.1 | EZ115: 12545.1 | FA115: 12545.1 | FB115: 12545.1 | FC115: 12545.1 | FD115: 0 | FE115: 0 | FF115: 0 | FG115: 0 | FH115: 0 | FI115: 0 | FJ115: 0 | FK115: 0 | FL115: 0 | FM115: 0 | FN115: 0 | FO115: 0 | FP115: 0 | FQ115: 0 | FR115: 0 | FS115: 0 | FT115: 0 | FU115: 0 | FV115: 0 | FW115: 0 | FX115: 0 | FY115: 0 | FZ115: 0 | GA115: 0 | GB115: 0 | GC115: 0 | GD115: 0 | GE115: 0 | GF115: 0 | GG115: 0 | GH115: 0 | GI115: 0 | GJ115: 0 | GK115: 0 | GL115: 0 | GM115: 0 | GN115: 0 | GO115: 0 | GP115: 0 | GQ115: 0 | GR115: 0 | GS115: 0 | GT115: 0 | GU115: 0 | GV115: 0 | GW115: 0 | GX115: 0 | GY115: 0 | GZ115: 0 | HA115: 0 | HB115: 0 | HC115: 0 | HD115: 0 | HE115: 0 | HF115: 0 | HG115: 0 | HH115: 0 | HI115: 0 | HJ115: 0 | HK115: 0 | HL115: 0 | HM115: 0 | HN115: 0 | HO115: 0 | HP115: 0 | HQ115: 0 | HR115: 0 | HS115: 0 | HT115: 0 | HU115: 0 | HV115: 0 | HW115: 0 | HX115: 0 | HY115: 0 | HZ115: 0 | IA115: 0 | IB115: 0 | IC115: 0 | ID115: 0 | IE115: 0 | IF115: 0 | IG115: 0 | IH115: 0 | II115: 0 | IJ115: 0 | IK115: 0
... B420: SDN10 | F420: 1 | H420: 41 | I420: 8 | J420: =B420&TEXT(F420,"00")&TEXT(H420,"00")&TEXT(I420,"00") -> SDN10014108 | K420: 816 | N420: SDN30 | O420: 2 | P420: 40 | Q420: =N420&TEXT(O420,"00")&TEXT(P420,"00") -> SDN300240 | R420: 0 | S420: 0 | T420: 0 | U420: 0 | V420: 0 | W420: 0 | X420: 0 | Y420: 0 | Z420: 0 | AA420: 0 | AB420: 0 | AC420: 0 | AD420: 0 | AE420: 0 | AF420: 0 | AG420: 0 | AH420: 0 | AI420: 0 | AJ420: 0 | AK420: 0 | AL420: 0 | AM420: 0 | AN420: 0 | AO420: 0 | AP420: 0 | AQ420: 0 | AR420: 0 | AS420: 0 | AT420: 0 | AU420: 0 | AV420: 0 | AW420: 0 | AX420: 0 | AY420: 0 | AZ420: 0 | BA420: 0 | BB420: 0 | BC420: 0 | BD420: 0 | BE420: 0 | BF420: 0 | BG420: 0 | BH420: 0 | BI420: 0 | BJ420: 12020.4 | BK420: 0 | BL420: 0 | BM420: 0 | BN420: 0 | BO420: 0 | BP420: 0 | BQ420: 0 | BR420: 0 | BS420: 0 | BT420: 0 | BU420: 0 | BV420: 0 | BW420: 0 | BX420: 0 | BY420: 0 | BZ420: 0 | CA420: 0 | CB420: 0 | CC420: 0 | CD420: 0 | CE420: 0 | CF420: 0 | CG420: 0 | CH420: 0 | CI420: 0 | CJ420: 0 | CK420: 0 | CL420: 0 | CM420: 0 | CN420: 0 | CO420: 0 | CP420: 0 | CQ420: 0 | CR420: 0 | CS420: 0 | CT420: 0 | CU420: 0 | CV420: 0 | CW420: 0 | CX420: 0 | CY420: 0 | CZ420: 0 | DA420: 0 | DB420: 0 | DC420: 0 | DD420: 0 | DE420: 0 | DF420: 0 | DG420: 0 | DH420: 0 | DI420: 0 | DJ420: 0 | DK420: 0 | DL420: 0 | DM420: 0 | DN420: 0 | DO420: 0 | DP420: 0 | DQ420: 0 | DR420: 0 | DS420: 0 | DT420: 0 | DU420: 0 | DV420: 0 | DW420: 0 | DX420: 0 | EA420: SDN30 | EB420: 2 | EC420: 40 | ED420: =EA420&TEXT(EB420,"00")&TEXT(EC420,"00") -> SDN300240 | EE420: 10000 | EF420: 10000 | EG420: 10000 | EH420: 10000 | EI420: 10000 | EJ420: 10000 | EK420: 10000 | EL420: 10000 | EM420: 10000 | EN420: 10000 | EO420: 10000 | EP420: 10000 | EQ420: 10000 | ER420: 10000 | ES420: 10000 | ET420: 10000 | EU420: 10000 | EV420: 10000 | EW420: 10000 | EX420: 10000 | EY420: 10000 | EZ420: 10000 | FA420: 10000 | FB420: 10000 | FC420: 10239.6 | FD420: 10595.8 | FE420: 10951.9 | FF420: 11308.1 | FG420: 11664.2 | FH420: 12020.4 | FI420: 12020.4 | FJ420: 12020.4 | FK420: 12020.4 | FL420: 12020.4 | FM420: 12020.4 | FN420: 12020.4 | FO420: 12020.4 | FP420: 12020.4 | FQ420: 12020.4 | FR420: 12020.4 | FS420: 12020.4 | FT420: 12020.4 | FU420: 12020.4 | FV420: 12020.4 | FW420: 12020.4 | FX420: 0 | FY420: 0 | FZ420: 0 | GA420: 0 | GB420: 0 | GC420: 0 | GD420: 0 | GE420: 0 | GF420: 0 | GG420: 0 | GH420: 0 | GI420: 0 | GJ420: 0 | GK420: 0 | GL420: 0 | GM420: 0 | GN420: 0 | GO420: 0 | GP420: 0 | GQ420: 0 | GR420: 0 | GS420: 0 | GT420: 0 | GU420: 0 | GV420: 0 | GW420: 0 | GX420: 0 | GY420: 0 | GZ420: 0 | HA420: 0 | HB420: 0 | HC420: 0 | HD420: 0 | HE420: 0 | HF420: 0 | HG420: 0 | HH420: 0 | HI420: 0 | HJ420: 0 | HK420: 0 | HL420: 0 | HM420: 0 | HN420: 0 | HO420: 0 | HP420: 0 | HQ420: 0 | HR420: 0 | HS420: 0 | HT420: 0 | HU420: 0 | HV420: 0 | HW420: 0 | HX420: 0 | HY420: 0 | HZ420: 0 | IA420: 0 | IB420: 0 | IC420: 0 | ID420: 0 | IE420: 0 | IF420: 0 | IG420: 0 | IH420: 0 | II420: 0 | IJ420: 0 | IK420: 0
B421: SDN10 | F421: 1 | H421: 41 | I421: 9 | J421: =B421&TEXT(F421,"00")&TEXT(H421,"00")&TEXT(I421,"00") -> SDN10014109 | K421: 816
B422: SDN10 | F422: 1 | H422: 41 | I422: 10 | J422: =B422&TEXT(F422,"00")&TEXT(H422,"00")&TEXT(I422,"00") -> SDN10014110 | K422: 816
B423: SDN10 | F423: 1 | H423: 42 | I423: 1 | J423: =B423&TEXT(F423,"00")&TEXT(H423,"00")&TEXT(I423,"00") -> SDN10014201 | K423: 1065
B424: SDN10 | F424: 1 | H424: 42 | I424: 2 | J424: =B424&TEXT(F424,"00")&TEXT(H424,"00")&TEXT(I424,"00") -> SDN10014202 | K424: 1065
B425: SDN10 | F425: 1 | H425: 42 | I425: 3 | J425: =B425&TEXT(F425,"00")&TEXT(H425,"00")&TEXT(I425,"00") -> SDN10014203 | K425: 1065 | M425: CV | Q425: =N425&TEXT(O425,"00")&TEXT(P425,"00") -> 0000 | DZ425: PA | ED425: =EA425&TEXT(EB425,"00")&TEXT(EC425,"00") -> 0000
B426: SDN10 | F426: 1 | H426: 42 | I426: 4 | J426: =B426&TEXT(F426,"00")&TEXT(H426,"00")&TEXT(I426,"00") -> SDN10014204 | K426: 1065 | M426: 版次 | N426: 商品代號 | O426: 性別 | P426: 年齡 | Q426: =N426&TEXT(O426,"00")&TEXT(P426,"00") -> 商品代號性別年齡 | R426: 第1年解約金 | S426: 第2年解約金 | T426: 第3年解約金 | U426: 第4年解約金 | V426: 第5年解約金 | W426: 第6年解約金 | X426: 第7年解約金 | Y426: 第8年解約金 | Z426: 第9年解約金 | AA426: 第10年解約金 | AB426: 第11年解約金 | AC426: 第12年解約金 | AD426: 第13年解約金 | AE426: 第14年解約金 | AF426: 第15年解約金 | AG426: 第16年解約金 | AH426: 第17年解約金 | AI426: 第18年解約金 | AJ426: 第19年解約金 | AK426: 第20年解約金 | AL426: 第21年解約金 | AM426: 第22年解約金 | AN426: 第23年解約金 | AO426: 第24年解約金 | AP426: 第25年解約金 | AQ426: 第26年解約金 | AR426: 第27年解約金 | AS426: 第28年解約金 | AT426: 第29年解約金 | AU426: 第30年解約金 | AV426: 第31年解約金 | AW426: 第32年解約金 | AX426: 第33年解約金 | AY426: 第34年解約金 | AZ426: 第35年解約金 | BA426: 第36年解約金 | BB426: 第37年解約金 | BC426: 第38年解約金 | BD426: 第39年解約金 | BE426: 第40年解約金 | BF426: 第41年解約金 | BG426: 第42年解約金 | BH426: 第43年解約金 | BI426: 第44年解約金 | BJ426: 第45年解約金 | BK426: 第46年解約金 | BL426: 第47年解約金 | BM426: 第48年解約金 | BN426: 第49年解約金 | BO426: 第50年解約金 | BP426: 第51年解約金 | BQ426: 第52年解約金 | BR426: 第53年解約金 | BS426: 第54年解約金 | BT426: 第55年解約金 | BU426: 第56年解約金 | BV426: 第57年解約金 | BW426: 第58年解約金 | BX426: 第59年解約金 | BY426: 第60年解約金 | BZ426: 第61年解約金 | CA426: 第62年解約金 | CB426: 第63年解約金 | CC426: 第64年解約金 | CD426: 第65年解約金 | CE426: 第66年解約金 | CF426: 第67年解約金 | CG426: 第68年解約金 | CH426: 第69年解約金 | CI426: 第70年解約金 | CJ426: 第71年解約金 | CK426: 第72年解約金 | CL426: 第73年解約金 | CM426: 第74年解約金 | CN426: 第75年解約金 | CO426: 第76年解約金 | CP426: 第77年解約金 | CQ426: 第78年解約金 | CR426: 第79年解約金 | CS426: 第80年解約金 | CT426: 第81年解約金 | CU426: 第82年解約金 | CV426: 第83年解約金 | CW426: 第84年解約金 | CX426: 第85年解約金 | CY426: 第86年解約金 | CZ426: 第87年解約金 | DA426: 第88年解約金 | DB426: 第89年解約金 | DC426: 第90年解約金 | DD426: 第91年解約金 | DE426: 第92年解約金 | DF426: 第93年解約金 | DG426: 第94年解約金 | DH426: 第95年解約金 | DI426: 第96年解約金 | DJ426: 第97年解約金 | DK426: 第98年解約金 | DL426: 第99年解約金 | DM426: 第100年解約金 | DN426: 第101年解約金 | DO426: 第102年解約金 | DP426: 第103年解約金 | DQ426: 第104年解約金 | DR426: 第105年解約金 | DS426: 第106年解約金 | DT426: 第107年解約金 | DU426: 第108年解約金 | DV426: 第109年解約金 | DW426: 第110年解約金 | DX426: 第111年解約金 | DZ426: 版次 | EA426: 商品代號 | EB426: 性別 | EC426: 年齡 | ED426: =EA426&TEXT(EB426,"00")&TEXT(EC426,"00") -> 商品代號性別年齡 | EE426: 第1年減額繳清保額 | EF426: 第2年減額繳清保額 | EG426: 第3年減額繳清保額 | EH426: 第4年減額繳清保額 | EI426: 第5年減額繳清保額 | EJ426: 第6年減額繳清保額 | EK426: 第7年減額繳清保額 | EL426: 第8年減額繳清保額 | EM426: 第9年減額繳清保額 | EN426: 第10年減額繳清保額 | EO426: 第11年減額繳清保額 | EP426: 第12年減額繳清保額 | EQ426: 第13年減額繳清保額 | ER426: 第14年減額繳清保額 | ES426: 第15年減額繳清保額 | ET426: 第16年減額繳清保額 | EU426: 第17年減額繳清保額 | EV426: 第18年減額繳清保額 | EW426: 第19年減額繳清保額B | EX426: 第20年減額繳清保額 | EY426: 第21年減額繳清保額B | EZ426: 第22年減額繳清保額 | FA426: 第23年減額繳清保額 | FB426: 第24年減額繳清保額 | FC426: 第25年減額繳清保額 | FD426: 第26年減額繳清保額B | FE426: 第27年減額繳清保額 | FF426: 第28年減額繳清保額B | FG426: 第29年減額繳清保額 | FH426: 第30年減額繳清保額B | FI426: 第31年減額繳清保額 | FJ426: 第32年減額繳清保額 | FK426: 第33年減額繳清保額 | FL426: 第34年減額繳清保額 | FM426: 第35年減額繳清保額 | FN426: 第36年減額繳清保額 | FO426: 第37年減額繳清保額 | FP426: 第38年減額繳清保額 | FQ426: 第39年減額繳清保額 | FR426: 第40年減額繳清保額 | FS426: 第41年減額繳清保額 | FT426: 第42年減額繳清保額 | FU426: 第43年減額繳清保額 | FV426: 第44年減額繳清保額 | FW426: 第45年減額繳清保額 | FX426: 第46年減額繳清保額 | FY426: 第47年減額繳清保額 | FZ426: 第48年減額繳清保額 | GA426: 第49年減額繳清保額 | GB426: 第50年減額繳清保額 | GC426: 第51年減額繳清保額 | GD426: 第52年減額繳清保額 | GE426: 第53年減額繳清保額 | GF426: 第54年減額繳清保額 | GG426: 第55年減額繳清保額 | GH426: 第56年減額繳清保額 | GI426: 第57年減額繳清保額 | GJ426: 第58年減額繳清保額 | GK426: 第59年減額繳清保額 | GL426: 第60年減額繳清保額 | GM426: 第61年減額繳清保額 | GN426: 第62年減額繳清保額 | GO426: 第63年減額繳清保額 | GP426: 第64年減額繳清保額 | GQ426: 第65年減額繳清保額 | GR426: 第66年減額繳清保額 | GS426: 第67年減額繳清保額 | GT426: 第68年減額繳清保額 | GU426: 第69年減額繳清保額 | GV426: 第70年減額繳清保額 | GW426: 第71年減額繳清保額 | GX426: 第72年減額繳清保額 | GY426: 第73年減額繳清保額 | GZ426: 第74年減額繳清保額 | HA426: 第75年減額繳清保額 | HB426: 第76年減額繳清保額 | HC426: 第77年減額繳清保額 | HD426: 第78年減額繳清保額 | HE426: 第79年減額繳清保額 | HF426: 第80年減額繳清保額 | HG426: 第81年減額繳清保額 | HH426: 第82年契遾B繳清保額 | HI426: 第83年減額繳清保額 | HJ426: 第84年減額繳清保額 | HK426: 第85年減額繳清保額 | HL426: 第86年減額繳清保額 | HM426: 第87年減額繳清保額 | HN426: 第88年減額繳清保額 | HO426: 第89年減額繳清保額 | HP426: 第90年減額繳清保額 | HQ426: 第91年減額繳清保額 | HR426: 第92年減額繳清保額 | HS426: 第93年減額繳清保額 | HT426: 第94年減額繳清保額 | HU426: 第95年減額繳清保額 | HV426: 第96年減額繳清保額 | HW426: 第97年減額繳清保額 | HX426: 第98年減額繳清保額 | HY426: 第99年減額繳清保額 | HZ426: 第100年減額繳清保額 | IA426: 第101年減額繳清保額 | IB426: 第102年減額繳清保額 | IC426: 第103年減額繳清保額 | ID426: 第104年減額繳清保額 | IE426: 第105年減額繳清保額 | IF426: 第106年減額繳清保額 | IG426: 第107年減額繳清保額 | IH426: 第108年減額繳清保額 | II426: 第109年減額繳清保額 | IJ426: 第110年減額繳清保額 | IK426: 第111年減額繳清保額
B427: SDN10 | F427: 1 | H427: 42 | I427: 5 | J427: =B427&TEXT(F427,"00")&TEXT(H427,"00")&TEXT(I427,"00") -> SDN10014205 | K427: 1065 | M427: 56 | N427: SDN10 | O427: 1 | P427: 0 | Q427: =N427&TEXT(O427,"00")&TEXT(P427,"00") -> SDN100100 | R427: 443 | S427: 996 | T427: 1564 | U427: 2147 | V427: 2741 | W427: 3240 | X427: 3750 | Y427: 4270 | Z427: 4799 | AA427: 7120 | AB427: 7275 | AC427: 7433 | AD427: 7594 | AE427: 7760 | AF427: 7930 | AG427: 8106 | AH427: 8289 | AI427: 8479 | AJ427: 8678 | AK427: 8885 | AL427: 9098 | AM427: 9315 | AN427: 9539 | AO427: 9766 | AP427: 0 | AQ427: 0 | AR427: 0 | AS427: 0 | AT427: 0 | AU427: 0 | AV427: 0 | AW427: 0 | AX427: 0 | AY427: 0 | AZ427: 0 | BA427: 0 | BB427: 0 | BC427: 0 | BD427: 0 | BE427: 0 | BF427: 0 | BG427: 0 | BH427: 0 | BI427: 0 | BJ427: 0 | BK427: 0 | BL427: 0 | BM427: 0 | BN427: 0 | BO427: 0 | BP427: 0 | BQ427: 0 | BR427: 0 | BS427: 0 | BT427: 0 | BU427: 0 | BV427: 0 | BW427: 0 | BX427: 0 | BY427: 0 | BZ427: 0 | CA427: 0 | CB427: 0 | CC427: 0 | CD427: 0 | CE427: 0 | CF427: 0 | CG427: 0 | CH427: 0 | CI427: 0 | CJ427: 0 | CK427: 0 | CL427: 0 | CM427: 0 | CN427: 0 | CO427: 0 | CP427: 0 | CQ427: 0 | CR427: 0 | CS427: 0 | CT427: 0 | CU427: 0 | CV427: 0 | CW427: 0 | CX427: 0 | CY427: 0 | CZ427: 0 | DA427: 0 | DB427: 0 | DC427: 0 | DD427: 0 | DE427: 0 | DF427: 0 | DG427: 0 | DH427: 0 | DI427: 0 | DJ427: 0 | DK427: 0 | DL427: 0 | DM427: 0 | DN427: 0 | DO427: 0 | DP427: 0 | DQ427: 0 | DR427: 0 | DS427: 0 | DT427: 0 | DU427: 0 | DV427: 0 | DW427: 0 | DX427: 0 | DZ427: 56 | EA427: SDN10 | EB427: 1 | EC427: 0 | ED427: =EA427&TEXT(EB427,"00")&TEXT(EC427,"00") -> SDN100100 | EE427: 801 | EF427: 1965 | EG427: 3110 | EH427: 4240 | EI427: 5344 | EJ427: 6217 | EK427: 7071 | EL427: 7906 | EM427: 8721 | EN427: 0 | EO427: 0 | EP427: 0 | EQ427: 0 | ER427: 0 | ES427: 0 | ET427: 0 | EU427: 0 | EV427: 0 | EW427: 0 | EX427: 0 | EY427: 0 | EZ427: 0 | FA427: 0 | FB427: 0 | FC427: 0 | FD427: 0 | FE427: 0 | FF427: 0 | FG427: 0 | FH427: 0 | FI427: 0 | FJ427: 0 | FK427: 0 | FL427: 0 | FM427: 0 | FN427: 0 | FO427: 0 | FP427: 0 | FQ427: 0 | FR427: 0 | FS427: 0 | FT427: 0 | FU427: 0 | FV427: 0 | FW427: 0 | FX427: 0 | FY427: 0 | FZ427: 0 | GA427: 0 | GB427: 0 | GC427: 0 | GD427: 0 | GE427: 0 | GF427: 0 | GG427: 0 | GH427: 0 | GI427: 0 | GJ427: 0 | GK427: 0 | GL427: 0 | GM427: 0 | GN427: 0 | GO427: 0 | GP427: 0 | GQ427: 0 | GR427: 0 | GS427: 0 | GT427: 0 | GU427: 0 | GV427: 0 | GW427: 0 | GX427: 0 | GY427: 0 | GZ427: 0 | HA427: 0 | HB427: 0 | HC427: 0 | HD427: 0 | HE427: 0 | HF427: 0 | HG427: 0 | HH427: 0 | HI427: 0 | HJ427: 0 | HK427: 0 | HL427: 0 | HM427: 0 | HN427: 0 | HO427: 0 | HP427: 0 | HQ427: 0 | HR427: 0 | HS427: 0 | HT427: 0 | HU427: 0 | HV427: 0 | HW427: 0 | HX427: 0 | HY427: 0 | HZ427: 0 | IA427: 0 | IB427: 0 | IC427: 0 | ID427: 0 | IE427: 0 | IF427: 0 | IG427: 0 | IH427: 0 | II427: 0 | IJ427: 0 | IK427: 0
B428: SDN10 | F428: 1 | H428: 42 | I428: 6 | J428: =B428&TEXT(F428,"00")&TEXT(H428,"00")&TEXT(I428,"00") -> SDN10014206 | K428: 852 | M428: 56 | N428: SDN10 | O428: 1 | P428: 1 | Q428: =N428&TEXT(O428,"00")&TEXT(P428,"00") -> SDN100101 | R428: 440 | S428: 994 | T428: 1562 | U428: 2143 | V428: 2735 | W428: 3234 | X428: 3742 | Y428: 4260 | Z428: 4790 | AA428: 7107 | AB428: 7261 | AC428: 7419 | AD428: 7580 | AE428: 7746 | AF428: 7919 | AG428: 8097 | AH428: 8282 | AI428: 8477 | AJ428: 8679 | AK428: 8887 | AL428: 9099 | AM428: 9316 | AN428: 9539 | AO428: 9767 | AP428: 0 | AQ428: 0 | AR428: 0 | AS428: 0 | AT428: 0 | AU428: 0 | AV428: 0 | AW428: 0 | AX428: 0 | AY428: 0 | AZ428: 0 | BA428: 0 | BB428: 0 | BC428: 0 | BD428: 0 | BE428: 0 | BF428: 0 | BG428: 0 | BH428: 0 | BI428: 0 | BJ428: 0 | BK428: 0 | BL428: 0 | BM428: 0 | BN428: 0 | BO428: 0 | BP428: 0 | BQ428: 0 | BR428: 0 | BS428: 0 | BT428: 0 | BU428: 0 | BV428: 0 | BW428: 0 | BX428: 0 | BY428: 0 | BZ428: 0 | CA428: 0 | CB428: 0 | CC428: 0 | CD428: 0 | CE428: 0 | CF428: 0 | CG428: 0 | CH428: 0 | CI428: 0 | CJ428: 0 | CK428: 0 | CL428: 0 | CM428: 0 | CN428: 0 | CO428: 0 | CP428: 0 | CQ428: 0 | CR428: 0 | CS428: 0 | CT428: 0 | CU428: 0 | CV428: 0 | CW428: 0 | CX428: 0 | CY428: 0 | CZ428: 0 | DA428: 0 | DB428: 0 | DC428: 0 | DD428: 0 | DE428: 0 | DF428: 0 | DG428: 0 | DH428: 0 | DI428: 0 | DJ428: 0 | DK428: 0 | DL428: 0 | DM428: 0 | DN428: 0 | DO428: 0 | DP428: 0 | DQ428: 0 | DR428: 0 | DS428: 0 | DT428: 0 | DU428: 0 | DV428: 0 | DW428: 0 | DX428: 0 | DZ428: 56 | EA428: SDN10 | EB428: 1 | EC428: 1 | ED428: =EA428&TEXT(EB428,"00")&TEXT(EC428,"00") -> SDN100101 | EE428: 795 | EF428: 1960 | EG428: 3109 | EH428: 4232 | EI428: 5334 | EJ428: 6202 | EK428: 7051 | EL428: 7882 | EM428: 8697 | EN428: 0 | EO428: 0 | EP428: 0 | EQ428: 0 | ER428: 0 | ES428: 0 | ET428: 0 | EU428: 0 | EV428: 0 | EW428: 0 | EX428: 0 | EY428: 0 | EZ428: 0 | FA428: 0 | FB428: 0 | FC428: 0 | FD428: 0 | FE428: 0 | FF428: 0 | FG428: 0 | FH428: 0 | FI428: 0 | FJ428: 0 | FK428: 0 | FL428: 0 | FM428: 0 | FN428: 0 | FO428: 0 | FP428: 0 | FQ428: 0 | FR428: 0 | FS428: 0 | FT428: 0 | FU428: 0 | FV428: 0 | FW428: 0 | FX428: 0 | FY428: 0 | FZ428: 0 | GA428: 0 | GB428: 0 | GC428: 0 | GD428: 0 | GE428: 0 | GF428: 0 | GG428: 0 | GH428: 0 | GI428: 0 | GJ428: 0 | GK428: 0 | GL428: 0 | GM428: 0 | GN428: 0 | GO428: 0 | GP428: 0 | GQ428: 0 | GR428: 0 | GS428: 0 | GT428: 0 | GU428: 0 | GV428: 0 | GW428: 0 | GX428: 0 | GY428: 0 | GZ428: 0 | HA428: 0 | HB428: 0 | HC428: 0 | HD428: 0 | HE428: 0 | HF428: 0 | HG428: 0 | HH428: 0 | HI428: 0 | HJ428: 0 | HK428: 0 | HL428: 0 | HM428: 0 | HN428: 0 | HO428: 0 | HP428: 0 | HQ428: 0 | HR428: 0 | HS428: 0 | HT428: 0 | HU428: 0 | HV428: 0 | HW428: 0 | HX428: 0 | HY428: 0 | HZ428: 0 | IA428: 0 | IB428: 0 | IC428: 0 | ID428: 0 | IE428: 0 | IF428: 0 | IG428: 0 | IH428: 0 | II428: 0 | IJ428: 0 | IK428: 0
B429: SDN10 | F429: 1 | H429: 42 | I429: 7 | J429: =B429&TEXT(F429,"00")&TEXT(H429,"00")&TEXT(I429,"00") -> SDN10014207 | K429: 852 | M429: 56 | N429: SDN10 | O429: 1 | P429: 2 | Q429: =N429&TEXT(O429,"00")&TEXT(P429,"00") -> SDN100102 | R429: 437 | S429: 992 | T429: 1559 | U429: 2138 | V429: 2729 | W429: 3227 | X429: 3734 | Y429: 4251 | Z429: 4780 | AA429: 7094 | AB429: 7247 | AC429: 7405 | AD429: 7567 | AE429: 7736 | AF429: 7910 | AG429: 8090 | AH429: 8280 | AI429: 8477 | AJ429: 8680 | AK429: 8887 | AL429: 9100 | AM429: 9316 | AN429: 9539 | AO429: 9766 | AP429: 0 | AQ429: 0 | AR429: 0 | AS429: 0 | AT429: 0 | AU429: 0 | AV429: 0 | AW429: 0 | AX429: 0 | AY429: 0 | AZ429: 0 | BA429: 0 | BB429: 0 | BC429: 0 | BD429: 0 | BE429: 0 | BF429: 0 | BG429: 0 | BH429: 0 | BI429: 0 | BJ429: 0 | BK429: 0 | BL429: 0 | BM429: 0 | BN429: 0 | BO429: 0 | BP429: 0 | BQ429: 0 | BR429: 0 | BS429: 0 | BT429: 0 | BU429: 0 | BV429: 0 | BW429: 0 | BX429: 0 | BY429: 0 | BZ429: 0 | CA429: 0 | CB429: 0 | CC429: 0 | CD429: 0 | CE429: 0 | CF429: 0 | CG429: 0 | CH429: 0 | CI429: 0 | CJ429: 0 | CK429: 0 | CL429: 0 | CM429: 0 | CN429: 0 | CO429: 0 | CP429: 0 | CQ429: 0 | CR429: 0 | CS429: 0 | CT429: 0 | CU429: 0 | CV429: 0 | CW429: 0 | CX429: 0 | CY429: 0 | CZ429: 0 | DA429: 0 | DB429: 0 | DC429: 0 | DD429: 0 | DE429: 0 | DF429: 0 | DG429: 0 | DH429: 0 | DI429: 0 | DJ429: 0 | DK429: 0 | DL429: 0 | DM429: 0 | DN429: 0 | DO429: 0 | DP429: 0 | DQ429: 0 | DR429: 0 | DS429: 0 | DT429: 0 | DU429: 0 | DV429: 0 | DW429: 0 | DX429: 0 | DZ429: 56 | EA429: SDN10 | EB429: 1 | EC429: 2 | ED429: =EA429&TEXT(EB429,"00")&TEXT(EC429,"00") -> SDN100102 | EE429: 790 | EF429: 1958 | EG429: 3103 | EH429: 4223 | EI429: 5319 | EJ429: 6186 | EK429: 7031 | EL429: 7860 | EM429: 8673 | EN429: 0 | EO429: 0 | EP429: 0 | EQ429: 0 | ER429: 0 | ES429: 0 | ET429: 0 | EU429: 0 | EV429: 0 | EW429: 0 | EX429: 0 | EY429: 0 | EZ429: 0 | FA429: 0 | FB429: 0 | FC429: 0 | FD429: 0 | FE429: 0 | FF429: 0 | FG429: 0 | FH429: 0 | FI429: 0 | FJ429: 0 | FK429: 0 | FL429: 0 | FM429: 0 | FN429: 0 | FO429: 0 | FP429: 0 | FQ429: 0 | FR429: 0 | FS429: 0 | FT429: 0 | FU429: 0 | FV429: 0 | FW429: 0 | FX429: 0 | FY429: 0 | FZ429: 0 | GA429: 0 | GB429: 0 | GC429: 0 | GD429: 0 | GE429: 0 | GF429: 0 | GG429: 0 | GH429: 0 | GI429: 0 | GJ429: 0 | GK429: 0 | GL429: 0 | GM429: 0 | GN429: 0 | GO429: 0 | GP429: 0 | GQ429: 0 | GR429: 0 | GS429: 0 | GT429: 0 | GU429: 0 | GV429: 0 | GW429: 0 | GX429: 0 | GY429: 0 | GZ429: 0 | HA429: 0 | HB429: 0 | HC429: 0 | HD429: 0 | HE429: 0 | HF429: 0 | HG429: 0 | HH429: 0 | HI429: 0 | HJ429: 0 | HK429: 0 | HL429: 0 | HM429: 0 | HN429: 0 | HO429: 0 | HP429: 0 | HQ429: 0 | HR429: 0 | HS429: 0 | HT429: 0 | HU429: 0 | HV429: 0 | HW429: 0 | HX429: 0 | HY429: 0 | HZ429: 0 | IA429: 0 | IB429: 0 | IC429: 0 | ID429: 0 | IE429: 0 | IF429: 0 | IG429: 0 | IH429: 0 | II429: 0 | IJ429: 0 | IK429: 0
B430: SDN10 | F430: 1 | H430: 42 | I430: 8 | J430: =B430&TEXT(F430,"00")&TEXT(H430,"00")&TEXT(I430,"00") -> SDN10014208 | K430: 852 | M430: 56 | N430: SDN10 | O430: 1 | P430: 3 | Q430: =N430&TEXT(O430,"00")&TEXT(P430,"00") -> SDN100103 | R430: 436 | S430: 989 | T430: 1555 | U430: 2132 | V430: 2722 | W430: 3218 | X430: 3724 | Y430: 4241 | Z430: 4770 | AA430: 7080 | AB430: 7234 | AC430: 7392 | AD430: 7556 | AE430: 7726 | AF430: 7903 | AG430: 8088 | AH430: 8280 | AI430: 8478 | AJ430: 8680 | AK430: 8887 | AL430: 9099 | AM430: 9315 | AN430: 9537 | AO430: 9765 | AP430: 0 | AQ430: 0 | AR430: 0 | AS430: 0 | AT430: 0 | AU430: 0 | AV430: 0 | AW430: 0 | AX430: 0 | AY430: 0 | AZ430: 0 | BA430: 0 | BB430: 0 | BC430: 0 | BD430: 0 | BE430: 0 | BF430: 0 | BG430: 0 | BH430: 0 | BI430: 0 | BJ430: 0 | BK430: 0 | BL430: 0 | BM430: 0 | BN430: 0 | BO430: 0 | BP430: 0 | BQ430: 0 | BR430: 0 | BS430: 0 | BT430: 0 | BU430: 0 | BV430: 0 | BW430: 0 | BX430: 0 | BY430: 0 | BZ430: 0 | CA430: 0 | CB430: 0 | CC430: 0 | CD430: 0 | CE430: 0 | CF430: 0 | CG430: 0 | CH430: 0 | CI430: 0 | CJ430: 0 | CK430: 0 | CL430: 0 | CM430: 0 | CN430: 0 | CO430: 0 | CP430: 0 | CQ430: 0 | CR430: 0 | CS430: 0 | CT430: 0 | CU430: 0 | CV430: 0 | CW430: 0 | CX430: 0 | CY430: 0 | CZ430: 0 | DA430: 0 | DB430: 0 | DC430: 0 | DD430: 0 | DE430: 0 | DF430: 0 | DG430: 0 | DH430: 0 | DI430: 0 | DJ430: 0 | DK430: 0 | DL430: 0 | DM430: 0 | DN430: 0 | DO430: 0 | DP430: 0 | DQ430: 0 | DR430: 0 | DS430: 0 | DT430: 0 | DU430: 0 | DV430: 0 | DW430: 0 | DX430: 0 | DZ430: 56 | EA430: SDN10 | EB430: 1 | EC430: 3 | ED430: =EA430&TEXT(EB430,"00")&TEXT(EC430,"00") -> SDN100103 | EE430: 787 | EF430: 1952 | EG430: 3093 | EH430: 4209 | EI430: 5303 | EJ430: 6163 | EK430: 7007 | EL430: 7835 | EM430: 8649 | EN430: 0 | EO430: 0 | EP430: 0 | EQ430: 0 | ER430: 0 | ES430: 0 | ET430: 0 | EU430: 0 | EV430: 0 | EW430: 0 | EX430: 0 | EY430: 0 | EZ430: 0 | FA430: 0 | FB430: 0 | FC430: 0 | FD430: 0 | FE430: 0 | FF430: 0 | FG430: 0 | FH430: 0 | FI430: 0 | FJ430: 0 | FK430: 0 | FL430: 0 | FM430: 0 | FN430: 0 | FO430: 0 | FP430: 0 | FQ430: 0 | FR430: 0 | FS430: 0 | FT430: 0 | FU430: 0 | FV430: 0 | FW430: 0 | FX430: 0 | FY430: 0 | FZ430: 0 | GA430: 0 | GB430: 0 | GC430: 0 | GD430: 0 | GE430: 0 | GF430: 0 | GG430: 0 | GH430: 0 | GI430: 0 | GJ430: 0 | GK430: 0 | GL430: 0 | GM430: 0 | GN430: 0 | GO430: 0 | GP430: 0 | GQ430: 0 | GR430: 0 | GS430: 0 | GT430: 0 | GU430: 0 | GV430: 0 | GW430: 0 | GX430: 0 | GY430: 0 | GZ430: 0 | HA430: 0 | HB430: 0 | HC430: 0 | HD430: 0 | HE430: 0 | HF430: 0 | HG430: 0 | HH430: 0 | HI430: 0 | HJ430: 0 | HK430: 0 | HL430: 0 | HM430: 0 | HN430: 0 | HO430: 0 | HP430: 0 | HQ430: 0 | HR430: 0 | HS430: 0 | HT430: 0 | HU430: 0 | HV430: 0 | HW430: 0 | HX430: 0 | HY430: 0 | HZ430: 0 | IA430: 0 | IB430: 0 | IC430: 0 | ID430: 0 | IE430: 0 | IF430: 0 | IG430: 0 | IH430: 0 | II430: 0 | IJ430: 0 | IK430: 0
B431: SDN10 | F431: 1 | H431: 42 | I431: 9 | J431: =B431&TEXT(F431,"00")&TEXT(H431,"00")&TEXT(I431,"00") -> SDN10014209 | K431: 852 | M431: 56 | N431: SDN10 | O431: 1 | P431: 4 | Q431: =N431&TEXT(O431,"00")&TEXT(P431,"00") -> SDN100104 | R431: 433 | S431: 985 | T431: 1550 | U431: 2126 | V431: 2714 | W431: 3209 | X431: 3715 | Y431: 4232 | Z431: 4760 | AA431: 7066 | AB431: 7220 | AC431: 7381 | AD431: 7546 | AE431: 7719 | AF431: 7900 | AG431: 8087 | AH431: 8280 | AI431: 8477 | AJ431: 8679 | AK431: 8885 | AL431: 9097 | AM431: 9313 | AN431: 9536 | AO431: 9764 | AP431: 0 | AQ431: 0 | AR431: 0 | AS431: 0 | AT431: 0 | AU431: 0 | AV431: 0 | AW431: 0 | AX431: 0 | AY431: 0 | AZ431: 0 | BA431: 0 | BB431: 0 | BC431: 0 | BD431: 0 | BE431: 0 | BF431: 0 | BG431: 0 | BH431: 0 | BI431: 0 | BJ431: 0 | BK431: 0 | BL431: 0 | BM431: 0 | BN431: 0 | BO431: 0 | BP431: 0 | BQ431: 0 | BR431: 0 | BS431: 0 | BT431: 0 | BU431: 0 | BV431: 0 | BW431: 0 | BX431: 0 | BY431: 0 | BZ431: 0 | CA431: 0 | CB431: 0 | CC431: 0 | CD431: 0 | CE431: 0 | CF431: 0 | CG431: 0 | CH431: 0 | CI431: 0 | CJ431: 0 | CK431: 0 | CL431: 0 | CM431: 0 | CN431: 0 | CO431: 0 | CP431: 0 | CQ431: 0 | CR431: 0 | CS431: 0 | CT431: 0 | CU431: 0 | CV431: 0 | CW431: 0 | CX431: 0 | CY431: 0 | CZ431: 0 | DA431: 0 | DB431: 0 | DC431: 0 | DD431: 0 | DE431: 0 | DF431: 0 | DG431: 0 | DH431: 0 | DI431: 0 | DJ431: 0 | DK431: 0 | DL431: 0 | DM431: 0 | DN431: 0 | DO431: 0 | DP431: 0 | DQ431: 0 | DR431: 0 | DS431: 0 | DT431: 0 | DU431: 0 | DV431: 0 | DW431: 0 | DX431: 0 | DZ431: 56 | EA431: SDN10 | EB431: 1 | EC431: 4 | ED431: =EA431&TEXT(EB431,"00")&TEXT(EC431,"00") -> SDN100104 | EE431: 781 | EF431: 1942 | EG431: 3082 | EH431: 4193 | EI431: 5284 | EJ431: 6143 | EK431: 6985 | EL431: 7811 | EM431: 8622 | EN431: 0 | EO431: 0 | EP431: 0 | EQ431: 0 | ER431: 0 | ES431: 0 | ET431: 0 | EU431: 0 | EV431: 0 | EW431: 0 | EX431: 0 | EY431: 0 | EZ431: 0 | FA431: 0 | FB431: 0 | FC431: 0 | FD431: 0 | FE431: 0 | FF431: 0 | FG431: 0 | FH431: 0 | FI431: 0 | FJ431: 0 | FK431: 0 | FL431: 0 | FM431: 0 | FN431: 0 | FO431: 0 | FP431: 0 | FQ431: 0 | FR431: 0 | FS431: 0 | FT431: 0 | FU431: 0 | FV431: 0 | FW431: 0 | FX431: 0 | FY431: 0 | FZ431: 0 | GA431: 0 | GB431: 0 | GC431: 0 | GD431: 0 | GE431: 0 | GF431: 0 | GG431: 0 | GH431: 0 | GI431: 0 | GJ431: 0 | GK431: 0 | GL431: 0 | GM431: 0 | GN431: 0 | GO431: 0 | GP431: 0 | GQ431: 0 | GR431: 0 | GS431: 0 | GT431: 0 | GU431: 0 | GV431: 0 | GW431: 0 | GX431: 0 | GY431: 0 | GZ431: 0 | HA431: 0 | HB431: 0 | HC431: 0 | HD431: 0 | HE431: 0 | HF431: 0 | HG431: 0 | HH431: 0 | HI431: 0 | HJ431: 0 | HK431: 0 | HL431: 0 | HM431: 0 | HN431: 0 | HO431: 0 | HP431: 0 | HQ431: 0 | HR431: 0 | HS431: 0 | HT431: 0 | HU431: 0 | HV431: 0 | HW431: 0 | HX431: 0 | HY431: 0 | HZ431: 0 | IA431: 0 | IB431: 0 | IC431: 0 | ID431: 0 | IE431: 0 | IF431: 0 | IG431: 0 | IH431: 0 | II431: 0 | IJ431: 0 | IK431: 0
B432: SDN10 | F432: 1 | H432: 42 | I432: 10 | J432: =B432&TEXT(F432,"00")&TEXT(H432,"00")&TEXT(I432,"00") -> SDN10014210 | K432: 852 | M432: 56 | N432: SDN10 | O432: 1 | P432: 5 | Q432: =N432&TEXT(O432,"00")&TEXT(P432,"00") -> SDN100105 | R432: 429 | S432: 980 | T432: 1544 | U432: 2119 | V432: 2706 | W432: 3200 | X432: 3705 | Y432: 4221 | Z432: 4749 | AA432: 7051 | AB432: 7208 | AC432: 7370 | AD432: 7538 | AE432: 7714 | AF432: 7897 | AG432: 8086 | AH432: 8278 | AI432: 8475 | AJ432: 8676 | AK432: 8882 | AL432: 9093 | AM432: 9310 | AN432: 9533 | AO432: 9763 | AP432: 0 | AQ432: 0 | AR432: 0 | AS432: 0 | AT432: 0 | AU432: 0 | AV432: 0 | AW432: 0 | AX432: 0 | AY432: 0 | AZ432: 0 | BA432: 0 | BB432: 0 | BC432: 0 | BD432: 0 | BE432: 0 | BF432: 0 | BG432: 0 | BH432: 0 | BI432: 0 | BJ432: 0 | BK432: 0 | BL432: 0 | BM432: 0 | BN432: 0 | BO432: 0 | BP432: 0 | BQ432: 0 | BR432: 0 | BS432: 0 | BT432: 0 | BU432: 0 | BV432: 0 | BW432: 0 | BX432: 0 | BY432: 0 | BZ432: 0 | CA432: 0 | CB432: 0 | CC432: 0 | CD432: 0 | CE432: 0 | CF432: 0 | CG432: 0 | CH432: 0 | CI432: 0 | CJ432: 0 | CK432: 0 | CL432: 0 | CM432: 0 | CN432: 0 | CO432: 0 | CP432: 0 | CQ432: 0 | CR432: 0 | CS432: 0 | CT432: 0 | CU432: 0 | CV432: 0 | CW432: 0 | CX432: 0 | CY432: 0 | CZ432: 0 | DA432: 0 | DB432: 0 | DC432: 0 | DD432: 0 | DE432: 0 | DF432: 0 | DG432: 0 | DH432: 0 | DI432: 0 | DJ432: 0 | DK432: 0 | DL432: 0 | DM432: 0 | DN432: 0 | DO432: 0 | DP432: 0 | DQ432: 0 | DR432: 0 | DS432: 0 | DT432: 0 | DU432: 0 | DV432: 0 | DW432: 0 | DX432: 0 | DZ432: 56 | EA432: SDN10 | EB432: 1 | EC432: 5 | ED432: =EA432&TEXT(EB432,"00")&TEXT(EC432,"00") -> SDN100105 | EE432: 773 | EF432: 1932 | EG432: 3068 | EH432: 4177 | EI432: 5264 | EJ432: 6120 | EK432: 6959 | EL432: 7785 | EM432: 8595 | EN432: 0 | EO432: 0 | EP432: 0 | EQ432: 0 | ER432: 0 | ES432: 0 | ET432: 0 | EU432: 0 | EV432: 0 | EW432: 0 | EX432: 0 | EY432: 0 | EZ432: 0 | FA432: 0 | FB432: 0 | FC432: 0 | FD432: 0 | FE432: 0 | FF432: 0 | FG432: 0 | FH432: 0 | FI432: 0 | FJ432: 0 | FK432: 0 | FL432: 0 | FM432: 0 | FN432: 0 | FO432: 0 | FP432: 0 | FQ432: 0 | FR432: 0 | FS432: 0 | FT432: 0 | FU432: 0 | FV432: 0 | FW432: 0 | FX432: 0 | FY432: 0 | FZ432: 0 | GA432: 0 | GB432: 0 | GC432: 0 | GD432: 0 | GE432: 0 | GF432: 0 | GG432: 0 | GH432: 0 | GI432: 0 | GJ432: 0 | GK432: 0 | GL432: 0 | GM432: 0 | GN432: 0 | GO432: 0 | GP432: 0 | GQ432: 0 | GR432: 0 | GS432: 0 | GT432: 0 | GU432: 0 | GV432: 0 | GW432: 0 | GX432: 0 | GY432: 0 | GZ432: 0 | HA432: 0 | HB432: 0 | HC432: 0 | HD432: 0 | HE432: 0 | HF432: 0 | HG432: 0 | HH432: 0 | HI432: 0 | HJ432: 0 | HK432: 0 | HL432: 0 | HM432: 0 | HN432: 0 | HO432: 0 | HP432: 0 | HQ432: 0 | HR432: 0 | HS432: 0 | HT432: 0 | HU432: 0 | HV432: 0 | HW432: 0 | HX432: 0 | HY432: 0 | HZ432: 0 | IA432: 0 | IB432: 0 | IC432: 0 | ID432: 0 | IE432: 0 | IF432: 0 | IG432: 0 | IH432: 0 | II432: 0 | IJ432: 0 | IK432: 0
B433: SDN10 | F433: 1 | H433: 43 | I433: 1 | J433: =B433&TEXT(F433,"00")&TEXT(H433,"00")&TEXT(I433,"00") -> SDN10014301 | K433: 1110 | M433: 56 | N433: SDN10 | O433: 1 | P433: 6 | Q433: =N433&TEXT(O433,"00")&TEXT(P433,"00") -> SDN100106 | R433: 426 | S433: 976 | T433: 1538 | U433: 2111 | V433: 2698 | W433: 3191 | X433: 3695 | Y433: 4211 | Z433: 4738 | AA433: 7038 | AB433: 7195 | AC433: 7360 | AD433: 7532 | AE433: 7710 | AF433: 7894 | AG433: 8081 | AH433: 8273 | AI433: 8470 | AJ433: 8671 | AK433: 8876 | AL433: 9087 | AM433: 9305 | AN433: 9529 | AO433: 9760 | AP433: 0 | AQ433: 0 | AR433: 0 | AS433: 0 | AT433: 0 | AU433: 0 | AV433: 0 | AW433: 0 | AX433: 0 | AY433: 0 | AZ433: 0 | BA433: 0 | BB433: 0 | BC433: 0 | BD433: 0 | BE433: 0 | BF433: 0 | BG433: 0 | BH433: 0 | BI433: 0 | BJ433: 0 | BK433: 0 | BL433: 0 | BM433: 0 | BN433: 0 | BO433: 0 | BP433: 0 | BQ433: 0 | BR433: 0 | BS433: 0 | BT433: 0 | BU433: 0 | BV433: 0 | BW433: 0 | BX433: 0 | BY433: 0 | BZ433: 0 | CA433: 0 | CB433: 0 | CC433: 0 | CD433: 0 | CE433: 0 | CF433: 0 | CG433: 0 | CH433: 0 | CI433: 0 | CJ433: 0 | CK433: 0 | CL433: 0 | CM433: 0 | CN433: 0 | CO433: 0 | CP433: 0 | CQ433: 0 | CR433: 0 | CS433: 0 | CT433: 0 | CU433: 0 | CV433: 0 | CW433: 0 | CX433: 0 | CY433: 0 | CZ433: 0 | DA433: 0 | DB433: 0 | DC433: 0 | DD433: 0 | DE433: 0 | DF433: 0 | DG433: 0 | DH433: 0 | DI433: 0 | DJ433: 0 | DK433: 0 | DL433: 0 | DM433: 0 | DN433: 0 | DO433: 0 | DP433: 0 | DQ433: 0 | DR433: 0 | DS433: 0 | DT433: 0 | DU433: 0 | DV433: 0 | DW433: 0 | DX433: 0 | DZ433: 56 | EA433: SDN10 | EB433: 1 | EC433: 6 | ED433: =EA433&TEXT(EB433,"00")&TEXT(EC433,"00") -> SDN100106 | EE433: 766 | EF433: 1922 | EG433: 3054 | EH433: 4159 | EI433: 5243 | EJ433: 6097 | EK433: 6934 | EL433: 7759 | EM433: 8568 | EN433: 0 | EO433: 0 | EP433: 0 | EQ433: 0 | ER433: 0 | ES433: 0 | ET433: 0 | EU433: 0 | EV433: 0 | EW433: 0 | EX433: 0 | EY433: 0 | EZ433: 0 | FA433: 0 | FB433: 0 | FC433: 0 | FD433: 0 | FE433: 0 | FF433: 0 | FG433: 0 | FH433: 0 | FI433: 0 | FJ433: 0 | FK433: 0 | FL433: 0 | FM433: 0 | FN433: 0 | FO433: 0 | FP433: 0 | FQ433: 0 | FR433: 0 | FS433: 0 | FT433: 0 | FU433: 0 | FV433: 0 | FW433: 0 | FX433: 0 | FY433: 0 | FZ433: 0 | GA433: 0 | GB433: 0 | GC433: 0 | GD433: 0 | GE433: 0 | GF433: 0 | GG433: 0 | GH433: 0 | GI433: 0 | GJ433: 0 | GK433: 0 | GL433: 0 | GM433: 0 | GN433: 0 | GO433: 0 | GP433: 0 | GQ433: 0 | GR433: 0 | GS433: 0 | GT433: 0 | GU433: 0 | GV433: 0 | GW433: 0 | GX433: 0 | GY433: 0 | GZ433: 0 | HA433: 0 | HB433: 0 | HC433: 0 | HD433: 0 | HE433: 0 | HF433: 0 | HG433: 0 | HH433: 0 | HI433: 0 | HJ433: 0 | HK433: 0 | HL433: 0 | HM433: 0 | HN433: 0 | HO433: 0 | HP433: 0 | HQ433: 0 | HR433: 0 | HS433: 0 | HT433: 0 | HU433: 0 | HV433: 0 | HW433: 0 | HX433: 0 | HY433: 0 | HZ433: 0 | IA433: 0 | IB433: 0 | IC433: 0 | ID433: 0 | IE433: 0 | IF433: 0 | IG433: 0 | IH433: 0 | II433: 0 | IJ433: 0 | IK433: 0
B434: SDN10 | F434: 1 | H434: 43 | I434: 2 | J434: =B434&TEXT(F434,"00")&TEXT(H434,"00")&TEXT(I434,"00") -> SDN10014302 | K434: 1110 | M434: 56 | N434: SDN10 | O434: 1 | P434: 7 | Q434: =N434&TEXT(O434,"00")&TEXT(P434,"00") -> SDN100107 | R434: 422 | S434: 971 | T434: 1532 | U434: 2105 | V434: 2690 | W434: 3182 | X434: 3685 | Y434: 4200 | Z434: 4727 | AA434: 7025 | AB434: 7185 | AC434: 7353 | AD434: 7526 | AE434: 7706 | AF434: 7888 | AG434: 8076 | AH434: 8267 | AI434: 8463 | AJ434: 8663 | AK434: 8869 | AL434: 9081 | AM434: 9299 | AN434: 9524 | AO434: 9758 | AP434: 0 | AQ434: 0 | AR434: 0 | AS434: 0 | AT434: 0 | AU434: 0 | AV434: 0 | AW434: 0 | AX434: 0 | AY434: 0 | AZ434: 0 | BA434: 0 | BB434: 0 | BC434: 0 | BD434: 0 | BE434: 0 | BF434: 0 | BG434: 0 | BH434: 0 | BI434: 0 | BJ434: 0 | BK434: 0 | BL434: 0 | BM434: 0 | BN434: 0 | BO434: 0 | BP434: 0 | BQ434: 0 | BR434: 0 | BS434: 0 | BT434: 0 | BU434: 0 | BV434: 0 | BW434: 0 | BX434: 0 | BY434: 0 | BZ434: 0 | CA434: 0 | CB434: 0 | CC434: 0 | CD434: 0 | CE434: 0 | CF434: 0 | CG434: 0 | CH434: 0 | CI434: 0 | CJ434: 0 | CK434: 0 | CL434: 0 | CM434: 0 | CN434: 0 | CO434: 0 | CP434: 0 | CQ434: 0 | CR434: 0 | CS434: 0 | CT434: 0 | CU434: 0 | CV434: 0 | CW434: 0 | CX434: 0 | CY434: 0 | CZ434: 0 | DA434: 0 | DB434: 0 | DC434: 0 | DD434: 0 | DE434: 0 | DF434: 0 | DG434: 0 | DH434: 0 | DI434: 0 | DJ434: 0 | DK434: 0 | DL434: 0 | DM434: 0 | DN434: 0 | DO434: 0 | DP434: 0 | DQ434: 0 | DR434: 0 | DS434: 0 | DT434: 0 | DU434: 0 | DV434: 0 | DW434: 0 | DX434: 0 | DZ434: 56 | EA434: SDN10 | EB434: 1 | EC434: 7 | ED434: =EA434&TEXT(EB434,"00")&TEXT(EC434,"00") -> SDN100107 | EE434: 758 | EF434: 1911 | EG434: 3039 | EH434: 4141 | EI434: 5222 | EJ434: 6073 | EK434: 6909 | EL434: 7732 | EM434: 8543 | EN434: 0 | EO434: 0 | EP434: 0 | EQ434: 0 | ER434: 0 | ES434: 0 | ET434: 0 | EU434: 0 | EV434: 0 | EW434: 0 | EX434: 0 | EY434: 0 | EZ434: 0 | FA434: 0 | FB434: 0 | FC434: 0 | FD434: 0 | FE434: 0 | FF434: 0 | FG434: 0 | FH434: 0 | FI434: 0 | FJ434: 0 | FK434: 0 | FL434: 0 | FM434: 0 | FN434: 0 | FO434: 0 | FP434: 0 | FQ434: 0 | FR434: 0 | FS434: 0 | FT434: 0 | FU434: 0 | FV434: 0 | FW434: 0 | FX434: 0 | FY434: 0 | FZ434: 0 | GA434: 0 | GB434: 0 | GC434: 0 | GD434: 0 | GE434: 0 | GF434: 0 | GG434: 0 | GH434: 0 | GI434: 0 | GJ434: 0 | GK434: 0 | GL434: 0 | GM434: 0 | GN434: 0 | GO434: 0 | GP434: 0 | GQ434: 0 | GR434: 0 | GS434: 0 | GT434: 0 | GU434: 0 | GV434: 0 | GW434: 0 | GX434: 0 | GY434: 0 | GZ434: 0 | HA434: 0 | HB434: 0 | HC434: 0 | HD434: 0 | HE434: 0 | HF434: 0 | HG434: 0 | HH434: 0 | HI434: 0 | HJ434: 0 | HK434: 0 | HL434: 0 | HM434: 0 | HN434: 0 | HO434: 0 | HP434: 0 | HQ434: 0 | HR434: 0 | HS434: 0 | HT434: 0 | HU434: 0 | HV434: 0 | HW434: 0 | HX434: 0 | HY434: 0 | HZ434: 0 | IA434: 0 | IB434: 0 | IC434: 0 | ID434: 0 | IE434: 0 | IF434: 0 | IG434: 0 | IH434: 0 | II434: 0 | IJ434: 0 | IK434: 0
B435: SDN10 | F435: 1 | H435: 43 | I435: 3 | J435: =B435&TEXT(F435,"00")&TEXT(H435,"00")&TEXT(I435,"00") -> SDN10014303 | K435: 1110 | M435: 56 | N435: SDN10 | O435: 1 | P435: 8 | Q435: =N435&TEXT(O435,"00")&TEXT(P435,"00") -> SDN100108 | R435: 419 | S435: 966 | T435: 1526 | U435: 2097 | V435: 2681 | W435: 3173 | X435: 3675 | Y435: 4190 | Z435: 4718 | AA435: 7013 | AB435: 7177 | AC435: 7346 | AD435: 7521 | AE435: 7699 | AF435: 7882 | AG435: 8068 | AH435: 8259 | AI435: 8454 | AJ435: 8655 | AK435: 8861 | AL435: 9074 | AM435: 9293 | AN435: 9521 | AO435: 9756 | AP435: 0 | AQ435: 0 | AR435: 0 | AS435: 0 | AT435: 0 | AU435: 0 | AV435: 0 | AW435: 0 | AX435: 0 | AY435: 0 | AZ435: 0 | BA435: 0 | BB435: 0 | BC435: 0 | BD435: 0 | BE435: 0 | BF435: 0 | BG435: 0 | BH435: 0 | BI435: 0 | BJ435: 0 | BK435: 0 | BL435: 0 | BM435: 0 | BN435: 0 | BO435: 0 | BP435: 0 | BQ435: 0 | BR435: 0 | BS435: 0 | BT435: 0 | BU435: 0 | BV435: 0 | BW435: 0 | BX435: 0 | BY435: 0 | BZ435: 0 | CA435: 0 | CB435: 0 | CC435: 0 | CD435: 0 | CE435: 0 | CF435: 0 | CG435: 0 | CH435: 0 | CI435: 0 | CJ435: 0 | CK435: 0 | CL435: 0 | CM435: 0 | CN435: 0 | CO435: 0 | CP435: 0 | CQ435: 0 | CR435: 0 | CS435: 0 | CT435: 0 | CU435: 0 | CV435: 0 | CW435: 0 | CX435: 0 | CY435: 0 | CZ435: 0 | DA435: 0 | DB435: 0 | DC435: 0 | DD435: 0 | DE435: 0 | DF435: 0 | DG435: 0 | DH435: 0 | DI435: 0 | DJ435: 0 | DK435: 0 | DL435: 0 | DM435: 0 | DN435: 0 | DO435: 0 | DP435: 0 | DQ435: 0 | DR435: 0 | DS435: 0 | DT435: 0 | DU435: 0 | DV435: 0 | DW435: 0 | DX435: 0 | DZ435: 56 | EA435: SDN10 | EB435: 1 | EC435: 8 | ED435: =EA435&TEXT(EB435,"00")&TEXT(EC435,"00") -> SDN100108 | EE435: 751 | EF435: 1899 | EG435: 3024 | EH435: 4123 | EI435: 5199 | EJ435: 6050 | EK435: 6885 | EL435: 7710 | EM435: 8520 | EN435: 0 | EO435: 0 | EP435: 0 | EQ435: 0 | ER435: 0 | ES435: 0 | ET435: 0 | EU435: 0 | EV435: 0 | EW435: 0 | EX435: 0 | EY435: 0 | EZ435: 0 | FA435: 0 | FB435: 0 | FC435: 0 | FD435: 0 | FE435: 0 | FF435: 0 | FG435: 0 | FH435: 0 | FI435: 0 | FJ435: 0 | FK435: 0 | FL435: 0 | FM435: 0 | FN435: 0 | FO435: 0 | FP435: 0 | FQ435: 0 | FR435: 0 | FS435: 0 | FT435: 0 | FU435: 0 | FV435: 0 | FW435: 0 | FX435: 0 | FY435: 0 | FZ435: 0 | GA435: 0 | GB435: 0 | GC435: 0 | GD435: 0 | GE435: 0 | GF435: 0 | GG435: 0 | GH435: 0 | GI435: 0 | GJ435: 0 | GK435: 0 | GL435: 0 | GM435: 0 | GN435: 0 | GO435: 0 | GP435: 0 | GQ435: 0 | GR435: 0 | GS435: 0 | GT435: 0 | GU435: 0 | GV435: 0 | GW435: 0 | GX435: 0 | GY435: 0 | GZ435: 0 | HA435: 0 | HB435: 0 | HC435: 0 | HD435: 0 | HE435: 0 | HF435: 0 | HG435: 0 | HH435: 0 | HI435: 0 | HJ435: 0 | HK435: 0 | HL435: 0 | HM435: 0 | HN435: 0 | HO435: 0 | HP435: 0 | HQ435: 0 | HR435: 0 | HS435: 0 | HT435: 0 | HU435: 0 | HV435: 0 | HW435: 0 | HX435: 0 | HY435: 0 | HZ435: 0 | IA435: 0 | IB435: 0 | IC435: 0 | ID435: 0 | IE435: 0 | IF435: 0 | IG435: 0 | IH435: 0 | II435: 0 | IJ435: 0 | IK435: 0
B436: SDN10 | F436: 1 | H436: 43 | I436: 4 | J436: =B436&TEXT(F436,"00")&TEXT(H436,"00")&TEXT(I436,"00") -> SDN10014304 | K436: 1110 | M436: 56 | N436: SDN10 | O436: 1 | P436: 9 | Q436: =N436&TEXT(O436,"00")&TEXT(P436,"00") -> SDN100109 | R436: 416 | S436: 962 | T436: 1520 | U436: 2090 | V436: 2672 | W436: 3163 | X436: 3665 | Y436: 4181 | Z436: 4709 | AA436: 7003 | AB436: 7168 | AC436: 7339 | AD436: 7512 | AE436: 7690 | AF436: 7872 | AG436: 8058 | AH436: 8248 | AI436: 8444 | AJ436: 8645 | AK436: 8851 | AL436: 9065 | AM436: 9287 | AN436: 9516 | AO436: 9753 | AP436: 0 | AQ436: 0 | AR436: 0 | AS436: 0 | AT436: 0 | AU436: 0 | AV436: 0 | AW436: 0 | AX436: 0 | AY436: 0 | AZ436: 0 | BA436: 0 | BB436: 0 | BC436: 0 | BD436: 0 | BE436: 0 | BF436: 0 | BG436: 0 | BH436: 0 | BI436: 0 | BJ436: 0 | BK436: 0 | BL436: 0 | BM436: 0 | BN436: 0 | BO436: 0 | BP436: 0 | BQ436: 0 | BR436: 0 | BS436: 0 | BT436: 0 | BU436: 0 | BV436: 0 | BW436: 0 | BX436: 0 | BY436: 0 | BZ436: 0 | CA436: 0 | CB436: 0 | CC436: 0 | CD436: 0 | CE436: 0 | CF436: 0 | CG436: 0 | CH436: 0 | CI436: 0 | CJ436: 0 | CK436: 0 | CL436: 0 | CM436: 0 | CN436: 0 | CO436: 0 | CP436: 0 | CQ436: 0 | CR436: 0 | CS436: 0 | CT436: 0 | CU436: 0 | CV436: 0 | CW436: 0 | CX436: 0 | CY436: 0 | CZ436: 0 | DA436: 0 | DB436: 0 | DC436: 0 | DD436: 0 | DE436: 0 | DF436: 0 | DG436: 0 | DH436: 0 | DI436: 0 | DJ436: 0 | DK436: 0 | DL436: 0 | DM436: 0 | DN436: 0 | DO436: 0 | DP436: 0 | DQ436: 0 | DR436: 0 | DS436: 0 | DT436: 0 | DU436: 0 | DV436: 0 | DW436: 0 | DX436: 0 | DZ436: 56 | EA436: SDN10 | EB436: 1 | EC436: 9 | ED436: =EA436&TEXT(EB436,"00")&TEXT(EC436,"00") -> SDN100109 | EE436: 742 | EF436: 1888 | EG436: 3009 | EH436: 4104 | EI436: 5178 | EJ436: 6025 | EK436: 6860 | EL436: 7687 | EM436: 8503 | EN436: 0 | EO436: 0 | EP436: 0 | EQ436: 0 | ER436: 0 | ES436: 0 | ET436: 0 | EU436: 0 | EV436: 0 | EW436: 0 | EX436: 0 | EY436: 0 | EZ436: 0 | FA436: 0 | FB436: 0 | FC436: 0 | FD436: 0 | FE436: 0 | FF436: 0 | FG436: 0 | FH436: 0 | FI436: 0 | FJ436: 0 | FK436: 0 | FL436: 0 | FM436: 0 | FN436: 0 | FO436: 0 | FP436: 0 | FQ436: 0 | FR436: 0 | FS436: 0 | FT436: 0 | FU436: 0 | FV436: 0 | FW436: 0 | FX436: 0 | FY436: 0 | FZ436: 0 | GA436: 0 | GB436: 0 | GC436: 0 | GD436: 0 | GE436: 0 | GF436: 0 | GG436: 0 | GH436: 0 | GI436: 0 | GJ436: 0 | GK436: 0 | GL436: 0 | GM436: 0 | GN436: 0 | GO436: 0 | GP436: 0 | GQ436: 0 | GR436: 0 | GS436: 0 | GT436: 0 | GU436: 0 | GV436: 0 | GW436: 0 | GX436: 0 | GY436: 0 | GZ436: 0 | HA436: 0 | HB436: 0 | HC436: 0 | HD436: 0 | HE436: 0 | HF436: 0 | HG436: 0 | HH436: 0 | HI436: 0 | HJ436: 0 | HK436: 0 | HL436: 0 | HM436: 0 | HN436: 0 | HO436: 0 | HP436: 0 | HQ436: 0 | HR436: 0 | HS436: 0 | HT436: 0 | HU436: 0 | HV436: 0 | HW436: 0 | HX436: 0 | HY436: 0 | HZ436: 0 | IA436: 0 | IB436: 0 | IC436: 0 | ID436: 0 | IE436: 0 | IF436: 0 | IG436: 0 | IH436: 0 | II436: 0 | IJ436: 0 | IK436: 0
B437: SDN10 | F437: 1 | H437: 43 | I437: 5 | J437: =B437&TEXT(F437,"00")&TEXT(H437,"00")&TEXT(I437,"00") -> SDN10014305 | K437: 1110 | M437: 56 | N437: SDN10 | O437: 1 | P437: 10 | Q437: =N437&TEXT(O437,"00")&TEXT(P437,"00") -> SDN100110 | R437: 412 | S437: 956 | T437: 1513 | U437: 2081 | V437: 2663 | W437: 3153 | X437: 3656 | Y437: 4171 | Z437: 4701 | AA437: 6993 | AB437: 7159 | AC437: 7328 | AD437: 7501 | AE437: 7678 | AF437: 7859 | AG437: 8045 | AH437: 8235 | AI437: 8431 | AJ437: 8632 | AK437: 8840 | AL437: 9056 | AM437: 9279 | AN437: 9510 | AO437: 9750 | AP437: 0 | AQ437: 0 | AR437: 0 | AS437: 0 | AT437: 0 | AU437: 0 | AV437: 0 | AW437: 0 | AX437: 0 | AY437: 0 | AZ437: 0 | BA437: 0 | BB437: 0 | BC437: 0 | BD437: 0 | BE437: 0 | BF437: 0 | BG437: 0 | BH437: 0 | BI437: 0 | BJ437: 0 | BK437: 0 | BL437: 0 | BM437: 0 | BN437: 0 | BO437: 0 | BP437: 0 | BQ437: 0 | BR437: 0 | BS437: 0 | BT437: 0 | BU437: 0 | BV437: 0 | BW437: 0 | BX437: 0 | BY437: 0 | BZ437: 0 | CA437: 0 | CB437: 0 | CC437: 0 | CD437: 0 | CE437: 0 | CF437: 0 | CG437: 0 | CH437: 0 | CI437: 0 | CJ437: 0 | CK437: 0 | CL437: 0 | CM437: 0 | CN437: 0 | CO437: 0 | CP437: 0 | CQ437: 0 | CR437: 0 | CS437: 0 | CT437: 0 | CU437: 0 | CV437: 0 | CW437: 0 | CX437: 0 | CY437: 0 | CZ437: 0 | DA437: 0 | DB437: 0 | DC437: 0 | DD437: 0 | DE437: 0 | DF437: 0 | DG437: 0 | DH437: 0 | DI437: 0 | DJ437: 0 | DK437: 0 | DL437: 0 | DM437: 0 | DN437: 0 | DO437: 0 | DP437: 0 | DQ437: 0 | DR437: 0 | DS437: 0 | DT437: 0 | DU437: 0 | DV437: 0 | DW437: 0 | DX437: 0 | DZ437: 56 | EA437: SDN10 | EB437: 1 | EC437: 10 | ED437: =EA437&TEXT(EB437,"00")&TEXT(EC437,"00") -> SDN100110 | EE437: 733 | EF437: 1875 | EG437: 2992 | EH437: 4083 | EI437: 5155 | EJ437: 6002 | EK437: 6839 | EL437: 7666 | EM437: 8488 | EN437: 0 | EO437: 0 | EP437: 0 | EQ437: 0 | ER437: 0 | ES437: 0 | ET437: 0 | EU437: 0 | EV437: 0 | EW437: 0 | EX437: 0 | EY437: 0 | EZ437: 0 | FA437: 0 | FB437: 0 | FC437: 0 | FD437: 0 | FE437: 0 | FF437: 0 | FG437: 0 | FH437: 0 | FI437: 0 | FJ437: 0 | FK437: 0 | FL437: 0 | FM437: 0 | FN437: 0 | FO437: 0 | FP437: 0 | FQ437: 0 | FR437: 0 | FS437: 0 | FT437: 0 | FU437: 0 | FV437: 0 | FW437: 0 | FX437: 0 | FY437: 0 | FZ437: 0 | GA437: 0 | GB437: 0 | GC437: 0 | GD437: 0 | GE437: 0 | GF437: 0 | GG437: 0 | GH437: 0 | GI437: 0 | GJ437: 0 | GK437: 0 | GL437: 0 | GM437: 0 | GN437: 0 | GO437: 0 | GP437: 0 | GQ437: 0 | GR437: 0 | GS437: 0 | GT437: 0 | GU437: 0 | GV437: 0 | GW437: 0 | GX437: 0 | GY437: 0 | GZ437: 0 | HA437: 0 | HB437: 0 | HC437: 0 | HD437: 0 | HE437: 0 | HF437: 0 | HG437: 0 | HH437: 0 | HI437: 0 | HJ437: 0 | HK437: 0 | HL437: 0 | HM437: 0 | HN437: 0 | HO437: 0 | HP437: 0 | HQ437: 0 | HR437: 0 | HS437: 0 | HT437: 0 | HU437: 0 | HV437: 0 | HW437: 0 | HX437: 0 | HY437: 0 | HZ437: 0 | IA437: 0 | IB437: 0 | IC437: 0 | ID437: 0 | IE437: 0 | IF437: 0 | IG437: 0 | IH437: 0 | II437: 0 | IJ437: 0 | IK437: 0
B438: SDN10 | F438: 1 | H438: 43 | I438: 6 | J438: =B438&TEXT(F438,"00")&TEXT(H438,"00")&TEXT(I438,"00") -> SDN10014306 | K438: 888 | M438: 56 | N438: SDN10 | O438: 1 | P438: 11 | Q438: =N438&TEXT(O438,"00")&TEXT(P438,"00") -> SDN100111 | R438: 407 | S438: 951 | T438: 1506 | U438: 2073 | V438: 2654 | W438: 3143 | X438: 3646 | Y438: 4162 | Z438: 4691 | AA438: 6980 | AB438: 7144 | AC438: 7313 | AD438: 7486 | AE438: 7662 | AF438: 7842 | AG438: 8028 | AH438: 8218 | AI438: 8414 | AJ438: 8617 | AK438: 8826 | AL438: 9043 | AM438: 9268 | AN438: 9501 | AO438: 9744 | AP438: 0 | AQ438: 0 | AR438: 0 | AS438: 0 | AT438: 0 | AU438: 0 | AV438: 0 | AW438: 0 | AX438: 0 | AY438: 0 | AZ438: 0 | BA438: 0 | BB438: 0 | BC438: 0 | BD438: 0 | BE438: 0 | BF438: 0 | BG438: 0 | BH438: 0 | BI438: 0 | BJ438: 0 | BK438: 0 | BL438: 0 | BM438: 0 | BN438: 0 | BO438: 0 | BP438: 0 | BQ438: 0 | BR438: 0 | BS438: 0 | BT438: 0 | BU438: 0 | BV438: 0 | BW438: 0 | BX438: 0 | BY438: 0 | BZ438: 0 | CA438: 0 | CB438: 0 | CC438: 0 | CD438: 0 | CE438: 0 | CF438: 0 | CG438: 0 | CH438: 0 | CI438: 0 | CJ438: 0 | CK438: 0 | CL438: 0 | CM438: 0 | CN438: 0 | CO438: 0 | CP438: 0 | CQ438: 0 | CR438: 0 | CS438: 0 | CT438: 0 | CU438: 0 | CV438: 0 | CW438: 0 | CX438: 0 | CY438: 0 | CZ438: 0 | DA438: 0 | DB438: 0 | DC438: 0 | DD438: 0 | DE438: 0 | DF438: 0 | DG438: 0 | DH438: 0 | DI438: 0 | DJ438: 0 | DK438: 0 | DL438: 0 | DM438: 0 | DN438: 0 | DO438: 0 | DP438: 0 | DQ438: 0 | DR438: 0 | DS438: 0 | DT438: 0 | DU438: 0 | DV438: 0 | DW438: 0 | DX438: 0 | DZ438: 56 | EA438: SDN10 | EB438: 1 | EC438: 11 | ED438: =EA438&TEXT(EB438,"00")&TEXT(EC438,"00") -> SDN100111 | EE438: 723 | EF438: 1863 | EG438: 2975 | EH438: 4063 | EI438: 5132 | EJ438: 5979 | EK438: 6818 | EL438: 7649 | EM438: 8471 | EN438: 0 | EO438: 0 | EP438: 0 | EQ438: 0 | ER438: 0 | ES438: 0 | ET438: 0 | EU438: 0 | EV438: 0 | EW438: 0 | EX438: 0 | EY438: 0 | EZ438: 0 | FA438: 0 | FB438: 0 | FC438: 0 | FD438: 0 | FE438: 0 | FF438: 0 | FG438: 0 | FH438: 0 | FI438: 0 | FJ438: 0 | FK438: 0 | FL438: 0 | FM438: 0 | FN438: 0 | FO438: 0 | FP438: 0 | FQ438: 0 | FR438: 0 | FS438: 0 | FT438: 0 | FU438: 0 | FV438: 0 | FW438: 0 | FX438: 0 | FY438: 0 | FZ438: 0 | GA438: 0 | GB438: 0 | GC438: 0 | GD438: 0 | GE438: 0 | GF438: 0 | GG438: 0 | GH438: 0 | GI438: 0 | GJ438: 0 | GK438: 0 | GL438: 0 | GM438: 0 | GN438: 0 | GO438: 0 | GP438: 0 | GQ438: 0 | GR438: 0 | GS438: 0 | GT438: 0 | GU438: 0 | GV438: 0 | GW438: 0 | GX438: 0 | GY438: 0 | GZ438: 0 | HA438: 0 | HB438: 0 | HC438: 0 | HD438: 0 | HE438: 0 | HF438: 0 | HG438: 0 | HH438: 0 | HI438: 0 | HJ438: 0 | HK438: 0 | HL438: 0 | HM438: 0 | HN438: 0 | HO438: 0 | HP438: 0 | HQ438: 0 | HR438: 0 | HS438: 0 | HT438: 0 | HU438: 0 | HV438: 0 | HW438: 0 | HX438: 0 | HY438: 0 | HZ438: 0 | IA438: 0 | IB438: 0 | IC438: 0 | ID438: 0 | IE438: 0 | IF438: 0 | IG438: 0 | IH438: 0 | II438: 0 | IJ438: 0 | IK438: 0
... B527: SDN10 | F527: 1 | H527: 52 | I527: 5 | J527: =B527&TEXT(F527,"00")&TEXT(H527,"00")&TEXT(I527,"00") -> SDN10015205 | K527: 1665 | M527: 56 | N527: SDN10 | O527: 2 | P527: 39 | Q527: =N527&TEXT(O527,"00")&TEXT(P527,"00") -> SDN100239 | R527: 189 | S527: 582 | T527: 987 | U527: 1404 | V527: 1836 | W527: 2210 | X527: 2597 | Y527: 3001 | Z527: 3423 | AA527: 5150 | AB527: 5337 | AC527: 5537 | AD527: 5749 | AE527: 5976 | AF527: 6217 | AG527: 6475 | AH527: 6752 | AI527: 7046 | AJ527: 7365 | AK527: 7712 | AL527: 8088 | AM527: 8503 | AN527: 8956 | AO527: 9453 | AP527: 0 | AQ527: 0 | AR527: 0 | AS527: 0 | AT527: 0 | AU527: 0 | AV527: 0 | AW527: 0 | AX527: 0 | AY527: 0 | AZ527: 0 | BA527: 0 | BB527: 0 | BC527: 0 | BD527: 0 | BE527: 0 | BF527: 0 | BG527: 0 | BH527: 0 | BI527: 0 | BJ527: 0 | BK527: 0 | BL527: 0 | BM527: 0 | BN527: 0 | BO527: 0 | BP527: 0 | BQ527: 0 | BR527: 0 | BS527: 0 | BT527: 0 | BU527: 0 | BV527: 0 | BW527: 0 | BX527: 0 | BY527: 0 | BZ527: 0 | CA527: 0 | CB527: 0 | CC527: 0 | CD527: 0 | CE527: 0 | CF527: 0 | CG527: 0 | CH527: 0 | CI527: 0 | CJ527: 0 | CK527: 0 | CL527: 0 | CM527: 0 | CN527: 0 | CO527: 0 | CP527: 0 | CQ527: 0 | CR527: 0 | CS527: 0 | CT527: 0 | CU527: 0 | CV527: 0 | CW527: 0 | CX527: 0 | CY527: 0 | CZ527: 0 | DA527: 0 | DB527: 0 | DC527: 0 | DD527: 0 | DE527: 0 | DF527: 0 | DG527: 0 | DH527: 0 | DI527: 0 | DJ527: 0 | DK527: 0 | DL527: 0 | DM527: 0 | DN527: 0 | DO527: 0 | DP527: 0 | DQ527: 0 | DR527: 0 | DS527: 0 | DT527: 0 | DU527: 0 | DV527: 0 | DW527: 0 | DX527: 0 | DZ527: 56 | EA527: SDN10 | EB527: 2 | EC527: 39 | ED527: =EA527&TEXT(EB527,"00")&TEXT(EC527,"00") -> SDN100239 | EE527: 303 | EF527: 1049 | EG527: 1836 | EH527: 2601 | EI527: 3366 | EJ527: 3984 | EK527: 4607 | EL527: 5241 | EM527: 5882 | EN527: 0 | EO527: 0 | EP527: 0 | EQ527: 0 | ER527: 0 | ES527: 0 | ET527: 0 | EU527: 0 | EV527: 0 | EW527: 0 | EX527: 0 | EY527: 0 | EZ527: 0 | FA527: 0 | FB527: 0 | FC527: 0 | FD527: 0 | FE527: 0 | FF527: 0 | FG527: 0 | FH527: 0 | FI527: 0 | FJ527: 0 | FK527: 0 | FL527: 0 | FM527: 0 | FN527: 0 | FO527: 0 | FP527: 0 | FQ527: 0 | FR527: 0 | FS527: 0 | FT527: 0 | FU527: 0 | FV527: 0 | FW527: 0 | FX527: 0 | FY527: 0 | FZ527: 0 | GA527: 0 | GB527: 0 | GC527: 0 | GD527: 0 | GE527: 0 | GF527: 0 | GG527: 0 | GH527: 0 | GI527: 0 | GJ527: 0 | GK527: 0 | GL527: 0 | GM527: 0 | GN527: 0 | GO527: 0 | GP527: 0 | GQ527: 0 | GR527: 0 | GS527: 0 | GT527: 0 | GU527: 0 | GV527: 0 | GW527: 0 | GX527: 0 | GY527: 0 | GZ527: 0 | HA527: 0 | HB527: 0 | HC527: 0 | HD527: 0 | HE527: 0 | HF527: 0 | HG527: 0 | HH527: 0 | HI527: 0 | HJ527: 0 | HK527: 0 | HL527: 0 | HM527: 0 | HN527: 0 | HO527: 0 | HP527: 0 | HQ527: 0 | HR527: 0 | HS527: 0 | HT527: 0 | HU527: 0 | HV527: 0 | HW527: 0 | HX527: 0 | HY527: 0 | HZ527: 0 | IA527: 0 | IB527: 0 | IC527: 0 | ID527: 0 | IE527: 0 | IF527: 0 | IG527: 0 | IH527: 0 | II527: 0 | IJ527: 0 | IK527: 0
B528: SDN10 | F528: 1 | H528: 52 | I528: 6 | J528: =B528&TEXT(F528,"00")&TEXT(H528,"00")&TEXT(I528,"00") -> SDN10015206 | K528: 1332 | N528: SDN10 | O528: 2 | P528: 40 | Q528: =N528&TEXT(O528,"00")&TEXT(P528,"00") -> SDN100240 | R528: 179 | S528: 565 | T528: 963 | U528: 1375 | V528: 1800 | W528: 2169 | X528: 2552 | Y528: 2952 | Z528: 3368 | AA528: 5071 | AB528: 5259 | AC528: 5459 | AD528: 5672 | AE528: 5898 | AF528: 6140 | AG528: 6399 | AH528: 6675 | AI528: 6973 | AJ528: 7297 | AK528: 7648 | AL528: 8035 | AM528: 8457 | AN528: 8920 | AO528: 9432 | AP528: 0 | AQ528: 0 | AR528: 0 | AS528: 0 | AT528: 0 | AU528: 0 | AV528: 0 | AW528: 0 | AX528: 0 | AY528: 0 | AZ528: 0 | BA528: 0 | BB528: 0 | BC528: 0 | BD528: 0 | BE528: 0 | BF528: 0 | BG528: 0 | BH528: 0 | BI528: 0 | BJ528: 0 | BK528: 0 | BL528: 0 | BM528: 0 | BN528: 0 | BO528: 0 | BP528: 0 | BQ528: 0 | BR528: 0 | BS528: 0 | BT528: 0 | BU528: 0 | BV528: 0 | BW528: 0 | BX528: 0 | BY528: 0 | BZ528: 0 | CA528: 0 | CB528: 0 | CC528: 0 | CD528: 0 | CE528: 0 | CF528: 0 | CG528: 0 | CH528: 0 | CI528: 0 | CJ528: 0 | CK528: 0 | CL528: 0 | CM528: 0 | CN528: 0 | CO528: 0 | CP528: 0 | CQ528: 0 | CR528: 0 | CS528: 0 | CT528: 0 | CU528: 0 | CV528: 0 | CW528: 0 | CX528: 0 | CY528: 0 | CZ528: 0 | DA528: 0 | DB528: 0 | DC528: 0 | DD528: 0 | DE528: 0 | DF528: 0 | DG528: 0 | DH528: 0 | DI528: 0 | DJ528: 0 | DK528: 0 | DL528: 0 | DM528: 0 | DN528: 0 | DO528: 0 | DP528: 0 | DQ528: 0 | DR528: 0 | DS528: 0 | DT528: 0 | DU528: 0 | DV528: 0 | DW528: 0 | DX528: 0 | EA528: SDN10 | EB528: 2 | EC528: 40 | ED528: =EA528&TEXT(EB528,"00")&TEXT(EC528,"00") -> SDN100240 | EE528: 286 | EF528: 1011 | EG528: 1783 | EH528: 2538 | EI528: 3289 | EJ528: 3899 | EK528: 4515 | EL528: 5142 | EM528: 5774 | EN528: 0 | EO528: 0 | EP528: 0 | EQ528: 0 | ER528: 0 | ES528: 0 | ET528: 0 | EU528: 0 | EV528: 0 | EW528: 0 | EX528: 0 | EY528: 0 | EZ528: 0 | FA528: 0 | FB528: 0 | FC528: 0 | FD528: 0 | FE528: 0 | FF528: 0 | FG528: 0 | FH528: 0 | FI528: 0 | FJ528: 0 | FK528: 0 | FL528: 0 | FM528: 0 | FN528: 0 | FO528: 0 | FP528: 0 | FQ528: 0 | FR528: 0 | FS528: 0 | FT528: 0 | FU528: 0 | FV528: 0 | FW528: 0 | FX528: 0 | FY528: 0 | FZ528: 0 | GA528: 0 | GB528: 0 | GC528: 0 | GD528: 0 | GE528: 0 | GF528: 0 | GG528: 0 | GH528: 0 | GI528: 0 | GJ528: 0 | GK528: 0 | GL528: 0 | GM528: 0 | GN528: 0 | GO528: 0 | GP528: 0 | GQ528: 0 | GR528: 0 | GS528: 0 | GT528: 0 | GU528: 0 | GV528: 0 | GW528: 0 | GX528: 0 | GY528: 0 | GZ528: 0 | HA528: 0 | HB528: 0 | HC528: 0 | HD528: 0 | HE528: 0 | HF528: 0 | HG528: 0 | HH528: 0 | HI528: 0 | HJ528: 0 | HK528: 0 | HL528: 0 | HM528: 0 | HN528: 0 | HO528: 0 | HP528: 0 | HQ528: 0 | HR528: 0 | HS528: 0 | HT528: 0 | HU528: 0 | HV528: 0 | HW528: 0 | HX528: 0 | HY528: 0 | HZ528: 0 | IA528: 0 | IB528: 0 | IC528: 0 | ID528: 0 | IE528: 0 | IF528: 0 | IG528: 0 | IH528: 0 | II528: 0 | IJ528: 0 | IK528: 0
B529: SDN10 | F529: 1 | H529: 52 | I529: 7 | J529: =B529&TEXT(F529,"00")&TEXT(H529,"00")&TEXT(I529,"00") -> SDN10015207 | K529: 1332 | N529: SDN10 | O529: 2 | P529: 41 | Q529: =N529&TEXT(O529,"00")&TEXT(P529,"00") -> SDN100241 | R529: 167 | S529: 547 | T529: 938 | U529: 1342 | V529: 1761 | W529: 2124 | X529: 2503 | Y529: 2897 | Z529: 3308 | AA529: 4983 | AB529: 5170 | AC529: 5370 | AD529: 5581 | AE529: 5807 | AF529: 6049 | AG529: 6307 | AH529: 6586 | AI529: 6887 | AJ529: 7215 | AK529: 7574 | AL529: 7967 | AM529: 8397 | AN529: 8872 | AO529: 9402 | AP529: 0 | AQ529: 0 | AR529: 0 | AS529: 0 | AT529: 0 | AU529: 0 | AV529: 0 | AW529: 0 | AX529: 0 | AY529: 0 | AZ529: 0 | BA529: 0 | BB529: 0 | BC529: 0 | BD529: 0 | BE529: 0 | BF529: 0 | BG529: 0 | BH529: 0 | BI529: 0 | BJ529: 0 | BK529: 0 | BL529: 0 | BM529: 0 | BN529: 0 | BO529: 0 | BP529: 0 | BQ529: 0 | BR529: 0 | BS529: 0 | BT529: 0 | BU529: 0 | BV529: 0 | BW529: 0 | BX529: 0 | BY529: 0 | BZ529: 0 | CA529: 0 | CB529: 0 | CC529: 0 | CD529: 0 | CE529: 0 | CF529: 0 | CG529: 0 | CH529: 0 | CI529: 0 | CJ529: 0 | CK529: 0 | CL529: 0 | CM529: 0 | CN529: 0 | CO529: 0 | CP529: 0 | CQ529: 0 | CR529: 0 | CS529: 0 | CT529: 0 | CU529: 0 | CV529: 0 | CW529: 0 | CX529: 0 | CY529: 0 | CZ529: 0 | DA529: 0 | DB529: 0 | DC529: 0 | DD529: 0 | DE529: 0 | DF529: 0 | DG529: 0 | DH529: 0 | DI529: 0 | DJ529: 0 | DK529: 0 | DL529: 0 | DM529: 0 | DN529: 0 | DO529: 0 | DP529: 0 | DQ529: 0 | DR529: 0 | DS529: 0 | DT529: 0 | DU529: 0 | DV529: 0 | DW529: 0 | DX529: 0 | EA529: SDN10 | EB529: 2 | EC529: 41 | ED529: =EA529&TEXT(EB529,"00")&TEXT(EC529,"00") -> SDN100241 | EE529: 267 | EF529: 972 | EG529: 1728 | EH529: 2467 | EI529: 3206 | EJ529: 3806 | EK529: 4414 | EL529: 5031 | EM529: 5654 | EN529: 0 | EO529: 0 | EP529: 0 | EQ529: 0 | ER529: 0 | ES529: 0 | ET529: 0 | EU529: 0 | EV529: 0 | EW529: 0 | EX529: 0 | EY529: 0 | EZ529: 0 | FA529: 0 | FB529: 0 | FC529: 0 | FD529: 0 | FE529: 0 | FF529: 0 | FG529: 0 | FH529: 0 | FI529: 0 | FJ529: 0 | FK529: 0 | FL529: 0 | FM529: 0 | FN529: 0 | FO529: 0 | FP529: 0 | FQ529: 0 | FR529: 0 | FS529: 0 | FT529: 0 | FU529: 0 | FV529: 0 | FW529: 0 | FX529: 0 | FY529: 0 | FZ529: 0 | GA529: 0 | GB529: 0 | GC529: 0 | GD529: 0 | GE529: 0 | GF529: 0 | GG529: 0 | GH529: 0 | GI529: 0 | GJ529: 0 | GK529: 0 | GL529: 0 | GM529: 0 | GN529: 0 | GO529: 0 | GP529: 0 | GQ529: 0 | GR529: 0 | GS529: 0 | GT529: 0 | GU529: 0 | GV529: 0 | GW529: 0 | GX529: 0 | GY529: 0 | GZ529: 0 | HA529: 0 | HB529: 0 | HC529: 0 | HD529: 0 | HE529: 0 | HF529: 0 | HG529: 0 | HH529: 0 | HI529: 0 | HJ529: 0 | HK529: 0 | HL529: 0 | HM529: 0 | HN529: 0 | HO529: 0 | HP529: 0 | HQ529: 0 | HR529: 0 | HS529: 0 | HT529: 0 | HU529: 0 | HV529: 0 | HW529: 0 | HX529: 0 | HY529: 0 | HZ529: 0 | IA529: 0 | IB529: 0 | IC529: 0 | ID529: 0 | IE529: 0 | IF529: 0 | IG529: 0 | IH529: 0 | II529: 0 | IJ529: 0 | IK529: 0
B530: SDN10 | F530: 1 | H530: 52 | I530: 8 | J530: =B530&TEXT(F530,"00")&TEXT(H530,"00")&TEXT(I530,"00") -> SDN10015208 | K530: 1332 | N530: SDN10 | O530: 2 | P530: 42 | Q530: =N530&TEXT(O530,"00")&TEXT(P530,"00") -> SDN100242 | R530: 156 | S530: 529 | T530: 914 | U530: 1311 | V530: 1724 | W530: 2082 | X530: 2455 | Y530: 2843 | Z530: 3250 | AA530: 4899 | AB530: 5086 | AC530: 5284 | AD530: 5495 | AE530: 5722 | AF530: 5963 | AG530: 6223 | AH530: 6504 | AI530: 6809 | AJ530: 7144 | AK530: 7509 | AL530: 7908 | AM530: 8349 | AN530: 8840 | AO530: 9398 | AP530: 0 | AQ530: 0 | AR530: 0 | AS530: 0 | AT530: 0 | AU530: 0 | AV530: 0 | AW530: 0 | AX530: 0 | AY530: 0 | AZ530: 0 | BA530: 0 | BB530: 0 | BC530: 0 | BD530: 0 | BE530: 0 | BF530: 0 | BG530: 0 | BH530: 0 | BI530: 0 | BJ530: 0 | BK530: 0 | BL530: 0 | BM530: 0 | BN530: 0 | BO530: 0 | BP530: 0 | BQ530: 0 | BR530: 0 | BS530: 0 | BT530: 0 | BU530: 0 | BV530: 0 | BW530: 0 | BX530: 0 | BY530: 0 | BZ530: 0 | CA530: 0 | CB530: 0 | CC530: 0 | CD530: 0 | CE530: 0 | CF530: 0 | CG530: 0 | CH530: 0 | CI530: 0 | CJ530: 0 | CK530: 0 | CL530: 0 | CM530: 0 | CN530: 0 | CO530: 0 | CP530: 0 | CQ530: 0 | CR530: 0 | CS530: 0 | CT530: 0 | CU530: 0 | CV530: 0 | CW530: 0 | CX530: 0 | CY530: 0 | CZ530: 0 | DA530: 0 | DB530: 0 | DC530: 0 | DD530: 0 | DE530: 0 | DF530: 0 | DG530: 0 | DH530: 0 | DI530: 0 | DJ530: 0 | DK530: 0 | DL530: 0 | DM530: 0 | DN530: 0 | DO530: 0 | DP530: 0 | DQ530: 0 | DR530: 0 | DS530: 0 | DT530: 0 | DU530: 0 | DV530: 0 | DW530: 0 | DX530: 0 | EA530: SDN10 | EB530: 2 | EC530: 42 | ED530: =EA530&TEXT(EB530,"00")&TEXT(EC530,"00") -> SDN100242 | EE530: 248 | EF530: 931 | EG530: 1672 | EH530: 2396 | EI530: 3121 | EJ530: 3710 | EK530: 4306 | EL530: 4913 | EM530: 5527 | EN530: 0 | EO530: 0 | EP530: 0 | EQ530: 0 | ER530: 0 | ES530: 0 | ET530: 0 | EU530: 0 | EV530: 0 | EW530: 0 | EX530: 0 | EY530: 0 | EZ530: 0 | FA530: 0 | FB530: 0 | FC530: 0 | FD530: 0 | FE530: 0 | FF530: 0 | FG530: 0 | FH530: 0 | FI530: 0 | FJ530: 0 | FK530: 0 | FL530: 0 | FM530: 0 | FN530: 0 | FO530: 0 | FP530: 0 | FQ530: 0 | FR530: 0 | FS530: 0 | FT530: 0 | FU530: 0 | FV530: 0 | FW530: 0 | FX530: 0 | FY530: 0 | FZ530: 0 | GA530: 0 | GB530: 0 | GC530: 0 | GD530: 0 | GE530: 0 | GF530: 0 | GG530: 0 | GH530: 0 | GI530: 0 | GJ530: 0 | GK530: 0 | GL530: 0 | GM530: 0 | GN530: 0 | GO530: 0 | GP530: 0 | GQ530: 0 | GR530: 0 | GS530: 0 | GT530: 0 | GU530: 0 | GV530: 0 | GW530: 0 | GX530: 0 | GY530: 0 | GZ530: 0 | HA530: 0 | HB530: 0 | HC530: 0 | HD530: 0 | HE530: 0 | HF530: 0 | HG530: 0 | HH530: 0 | HI530: 0 | HJ530: 0 | HK530: 0 | HL530: 0 | HM530: 0 | HN530: 0 | HO530: 0 | HP530: 0 | HQ530: 0 | HR530: 0 | HS530: 0 | HT530: 0 | HU530: 0 | HV530: 0 | HW530: 0 | HX530: 0 | HY530: 0 | HZ530: 0 | IA530: 0 | IB530: 0 | IC530: 0 | ID530: 0 | IE530: 0 | IF530: 0 | IG530: 0 | IH530: 0 | II530: 0 | IJ530: 0 | IK530: 0
B531: SDN10 | F531: 1 | H531: 52 | I531: 9 | J531: =B531&TEXT(F531,"00")&TEXT(H531,"00")&TEXT(I531,"00") -> SDN10015209 | K531: 1332 | N531: SDN10 | O531: 2 | P531: 43 | Q531: =N531&TEXT(O531,"00")&TEXT(P531,"00") -> SDN100243 | R531: 147 | S531: 518 | T531: 900 | U531: 1296 | V531: 1707 | W531: 2064 | X531: 2436 | Y531: 2825 | Z531: 3230 | AA531: 4873 | AB531: 5061 | AC531: 5261 | AD531: 5475 | AE531: 5702 | AF531: 5948 | AG531: 6213 | AH531: 6500 | AI531: 6816 | AJ531: 7159 | AK531: 7535 | AL531: 7948 | AM531: 8408 | AN531: 8931 | AO531: 9515 | AP531: 0 | AQ531: 0 | AR531: 0 | AS531: 0 | AT531: 0 | AU531: 0 | AV531: 0 | AW531: 0 | AX531: 0 | AY531: 0 | AZ531: 0 | BA531: 0 | BB531: 0 | BC531: 0 | BD531: 0 | BE531: 0 | BF531: 0 | BG531: 0 | BH531: 0 | BI531: 0 | BJ531: 0 | BK531: 0 | BL531: 0 | BM531: 0 | BN531: 0 | BO531: 0 | BP531: 0 | BQ531: 0 | BR531: 0 | BS531: 0 | BT531: 0 | BU531: 0 | BV531: 0 | BW531: 0 | BX531: 0 | BY531: 0 | BZ531: 0 | CA531: 0 | CB531: 0 | CC531: 0 | CD531: 0 | CE531: 0 | CF531: 0 | CG531: 0 | CH531: 0 | CI531: 0 | CJ531: 0 | CK531: 0 | CL531: 0 | CM531: 0 | CN531: 0 | CO531: 0 | CP531: 0 | CQ531: 0 | CR531: 0 | CS531: 0 | CT531: 0 | CU531: 0 | CV531: 0 | CW531: 0 | CX531: 0 | CY531: 0 | CZ531: 0 | DA531: 0 | DB531: 0 | DC531: 0 | DD531: 0 | DE531: 0 | DF531: 0 | DG531: 0 | DH531: 0 | DI531: 0 | DJ531: 0 | DK531: 0 | DL531: 0 | DM531: 0 | DN531: 0 | DO531: 0 | DP531: 0 | DQ531: 0 | DR531: 0 | DS531: 0 | DT531: 0 | DU531: 0 | DV531: 0 | DW531: 0 | DX531: 0 | EA531: SDN10 | EB531: 2 | EC531: 43 | ED531: =EA531&TEXT(EB531,"00")&TEXT(EC531,"00") -> SDN100243 | EE531: 230 | EF531: 895 | EG531: 1621 | EH531: 2331 | EI531: 3042 | EJ531: 3620 | EK531: 4204 | EL531: 4801 | EM531: 5403 | EN531: 0 | EO531: 0 | EP531: 0 | EQ531: 0 | ER531: 0 | ES531: 0 | ET531: 0 | EU531: 0 | EV531: 0 | EW531: 0 | EX531: 0 | EY531: 0 | EZ531: 0 | FA531: 0 | FB531: 0 | FC531: 0 | FD531: 0 | FE531: 0 | FF531: 0 | FG531: 0 | FH531: 0 | FI531: 0 | FJ531: 0 | FK531: 0 | FL531: 0 | FM531: 0 | FN531: 0 | FO531: 0 | FP531: 0 | FQ531: 0 | FR531: 0 | FS531: 0 | FT531: 0 | FU531: 0 | FV531: 0 | FW531: 0 | FX531: 0 | FY531: 0 | FZ531: 0 | GA531: 0 | GB531: 0 | GC531: 0 | GD531: 0 | GE531: 0 | GF531: 0 | GG531: 0 | GH531: 0 | GI531: 0 | GJ531: 0 | GK531: 0 | GL531: 0 | GM531: 0 | GN531: 0 | GO531: 0 | GP531: 0 | GQ531: 0 | GR531: 0 | GS531: 0 | GT531: 0 | GU531: 0 | GV531: 0 | GW531: 0 | GX531: 0 | GY531: 0 | GZ531: 0 | HA531: 0 | HB531: 0 | HC531: 0 | HD531: 0 | HE531: 0 | HF531: 0 | HG531: 0 | HH531: 0 | HI531: 0 | HJ531: 0 | HK531: 0 | HL531: 0 | HM531: 0 | HN531: 0 | HO531: 0 | HP531: 0 | HQ531: 0 | HR531: 0 | HS531: 0 | HT531: 0 | HU531: 0 | HV531: 0 | HW531: 0 | HX531: 0 | HY531: 0 | HZ531: 0 | IA531: 0 | IB531: 0 | IC531: 0 | ID531: 0 | IE531: 0 | IF531: 0 | IG531: 0 | IH531: 0 | II531: 0 | IJ531: 0 | IK531: 0
B532: SDN10 | F532: 1 | H532: 52 | I532: 10 | J532: =B532&TEXT(F532,"00")&TEXT(H532,"00")&TEXT(I532,"00") -> SDN10015210 | K532: 1332 | N532: SDN10 | O532: 2 | P532: 44 | Q532: =N532&TEXT(O532,"00")&TEXT(P532,"00") -> SDN100244 | R532: 139 | S532: 510 | T532: 893 | U532: 1291 | V532: 1703 | W532: 2061 | X532: 2436 | Y532: 2827 | Z532: 3235 | AA532: 4882 | AB532: 5072 | AC532: 5276 | AD532: 5493 | AE532: 5726 | AF532: 5978 | AG532: 6251 | AH532: 6550 | AI532: 6875 | AJ532: 7231 | AK532: 7622 | AL532: 8056 | AM532: 8550 | AN532: 9099 | AO532: 9711 | AP532: 0 | AQ532: 0 | AR532: 0 | AS532: 0 | AT532: 0 | AU532: 0 | AV532: 0 | AW532: 0 | AX532: 0 | AY532: 0 | AZ532: 0 | BA532: 0 | BB532: 0 | BC532: 0 | BD532: 0 | BE532: 0 | BF532: 0 | BG532: 0 | BH532: 0 | BI532: 0 | BJ532: 0 | BK532: 0 | BL532: 0 | BM532: 0 | BN532: 0 | BO532: 0 | BP532: 0 | BQ532: 0 | BR532: 0 | BS532: 0 | BT532: 0 | BU532: 0 | BV532: 0 | BW532: 0 | BX532: 0 | BY532: 0 | BZ532: 0 | CA532: 0 | CB532: 0 | CC532: 0 | CD532: 0 | CE532: 0 | CF532: 0 | CG532: 0 | CH532: 0 | CI532: 0 | CJ532: 0 | CK532: 0 | CL532: 0 | CM532: 0 | CN532: 0 | CO532: 0 | CP532: 0 | CQ532: 0 | CR532: 0 | CS532: 0 | CT532: 0 | CU532: 0 | CV532: 0 | CW532: 0 | CX532: 0 | CY532: 0 | CZ532: 0 | DA532: 0 | DB532: 0 | DC532: 0 | DD532: 0 | DE532: 0 | DF532: 0 | DG532: 0 | DH532: 0 | DI532: 0 | DJ532: 0 | DK532: 0 | DL532: 0 | DM532: 0 | DN532: 0 | DO532: 0 | DP532: 0 | DQ532: 0 | DR532: 0 | DS532: 0 | DT532: 0 | DU532: 0 | DV532: 0 | DW532: 0 | DX532: 0 | EA532: SDN10 | EB532: 2 | EC532: 44 | ED532: =EA532&TEXT(EB532,"00")&TEXT(EC532,"00") -> SDN100244 | EE532: 213 | EF532: 860 | EG532: 1572 | EH532: 2268 | EI532: 2963 | EJ532: 3528 | EK532: 4102 | EL532: 4685 | EM532: 5272 | EN532: 0 | EO532: 0 | EP532: 0 | EQ532: 0 | ER532: 0 | ES532: 0 | ET532: 0 | EU532: 0 | EV532: 0 | EW532: 0 | EX532: 0 | EY532: 0 | EZ532: 0 | FA532: 0 | FB532: 0 | FC532: 0 | FD532: 0 | FE532: 0 | FF532: 0 | FG532: 0 | FH532: 0 | FI532: 0 | FJ532: 0 | FK532: 0 | FL532: 0 | FM532: 0 | FN532: 0 | FO532: 0 | FP532: 0 | FQ532: 0 | FR532: 0 | FS532: 0 | FT532: 0 | FU532: 0 | FV532: 0 | FW532: 0 | FX532: 0 | FY532: 0 | FZ532: 0 | GA532: 0 | GB532: 0 | GC532: 0 | GD532: 0 | GE532: 0 | GF532: 0 | GG532: 0 | GH532: 0 | GI532: 0 | GJ532: 0 | GK532: 0 | GL532: 0 | GM532: 0 | GN532: 0 | GO532: 0 | GP532: 0 | GQ532: 0 | GR532: 0 | GS532: 0 | GT532: 0 | GU532: 0 | GV532: 0 | GW532: 0 | GX532: 0 | GY532: 0 | GZ532: 0 | HA532: 0 | HB532: 0 | HC532: 0 | HD532: 0 | HE532: 0 | HF532: 0 | HG532: 0 | HH532: 0 | HI532: 0 | HJ532: 0 | HK532: 0 | HL532: 0 | HM532: 0 | HN532: 0 | HO532: 0 | HP532: 0 | HQ532: 0 | HR532: 0 | HS532: 0 | HT532: 0 | HU532: 0 | HV532: 0 | HW532: 0 | HX532: 0 | HY532: 0 | HZ532: 0 | IA532: 0 | IB532: 0 | IC532: 0 | ID532: 0 | IE532: 0 | IF532: 0 | IG532: 0 | IH532: 0 | II532: 0 | IJ532: 0 | IK532: 0
B533: SDN10 | F533: 1 | H533: 53 | I533: 1 | J533: =B533&TEXT(F533,"00")&TEXT(H533,"00")&TEXT(I533,"00") -> SDN10015301 | K533: 1755 | N533: SDN10 | O533: 2 | P533: 45 | Q533: =N533&TEXT(O533,"00")&TEXT(P533,"00") -> SDN100245 | R533: 132 | S533: 508 | T533: 897 | U533: 1300 | V533: 1718 | W533: 2083 | X533: 2464 | Y533: 2861 | Z533: 3276 | AA533: 4947 | AB533: 5144 | AC533: 5352 | AD533: 5577 | AE533: 5819 | AF533: 6080 | AG533: 6368 | AH533: 6679 | AI533: 7019 | AJ533: 7393 | AK533: 7808 | AL533: 8279 | AM533: 8803 | AN533: 9385 | AO533: 10043 | AP533: 0 | AQ533: 0 | AR533: 0 | AS533: 0 | AT533: 0 | AU533: 0 | AV533: 0 | AW533: 0 | AX533: 0 | AY533: 0 | AZ533: 0 | BA533: 0 | BB533: 0 | BC533: 0 | BD533: 0 | BE533: 0 | BF533: 0 | BG533: 0 | BH533: 0 | BI533: 0 | BJ533: 0 | BK533: 0 | BL533: 0 | BM533: 0 | BN533: 0 | BO533: 0 | BP533: 0 | BQ533: 0 | BR533: 0 | BS533: 0 | BT533: 0 | BU533: 0 | BV533: 0 | BW533: 0 | BX533: 0 | BY533: 0 | BZ533: 0 | CA533: 0 | CB533: 0 | CC533: 0 | CD533: 0 | CE533: 0 | CF533: 0 | CG533: 0 | CH533: 0 | CI533: 0 | CJ533: 0 | CK533: 0 | CL533: 0 | CM533: 0 | CN533: 0 | CO533: 0 | CP533: 0 | CQ533: 0 | CR533: 0 | CS533: 0 | CT533: 0 | CU533: 0 | CV533: 0 | CW533: 0 | CX533: 0 | CY533: 0 | CZ533: 0 | DA533: 0 | DB533: 0 | DC533: 0 | DD533: 0 | DE533: 0 | DF533: 0 | DG533: 0 | DH533: 0 | DI533: 0 | DJ533: 0 | DK533: 0 | DL533: 0 | DM533: 0 | DN533: 0 | DO533: 0 | DP533: 0 | DQ533: 0 | DR533: 0 | DS533: 0 | DT533: 0 | DU533: 0 | DV533: 0 | DW533: 0 | DX533: 0 | EA533: SDN10 | EB533: 2 | EC533: 45 | ED533: =EA533&TEXT(EB533,"00")&TEXT(EC533,"00") -> SDN100245 | EE533: 196 | EF533: 828 | EG533: 1526 | EH533: 2207 | EI533: 2885 | EJ533: 3439 | EK533: 3998 | EL533: 4567 | EM533: 5138 | EN533: 0 | EO533: 0 | EP533: 0 | EQ533: 0 | ER533: 0 | ES533: 0 | ET533: 0 | EU533: 0 | EV533: 0 | EW533: 0 | EX533: 0 | EY533: 0 | EZ533: 0 | FA533: 0 | FB533: 0 | FC533: 0 | FD533: 0 | FE533: 0 | FF533: 0 | FG533: 0 | FH533: 0 | FI533: 0 | FJ533: 0 | FK533: 0 | FL533: 0 | FM533: 0 | FN533: 0 | FO533: 0 | FP533: 0 | FQ533: 0 | FR533: 0 | FS533: 0 | FT533: 0 | FU533: 0 | FV533: 0 | FW533: 0 | FX533: 0 | FY533: 0 | FZ533: 0 | GA533: 0 | GB533: 0 | GC533: 0 | GD533: 0 | GE533: 0 | GF533: 0 | GG533: 0 | GH533: 0 | GI533: 0 | GJ533: 0 | GK533: 0 | GL533: 0 | GM533: 0 | GN533: 0 | GO533: 0 | GP533: 0 | GQ533: 0 | GR533: 0 | GS533: 0 | GT533: 0 | GU533: 0 | GV533: 0 | GW533: 0 | GX533: 0 | GY533: 0 | GZ533: 0 | HA533: 0 | HB533: 0 | HC533: 0 | HD533: 0 | HE533: 0 | HF533: 0 | HG533: 0 | HH533: 0 | HI533: 0 | HJ533: 0 | HK533: 0 | HL533: 0 | HM533: 0 | HN533: 0 | HO533: 0 | HP533: 0 | HQ533: 0 | HR533: 0 | HS533: 0 | HT533: 0 | HU533: 0 | HV533: 0 | HW533: 0 | HX533: 0 | HY533: 0 | HZ533: 0 | IA533: 0 | IB533: 0 | IC533: 0 | ID533: 0 | IE533: 0 | IF533: 0 | IG533: 0 | IH533: 0 | II533: 0 | IJ533: 0 | IK533: 0
B534: SDN10 | F534: 1 | H534: 53 | I534: 2 | J534: =B534&TEXT(F534,"00")&TEXT(H534,"00")&TEXT(I534,"00") -> SDN10015302 | K534: 1755 | N534: SDN10 | O534: 2 | P534: 46 | Q534: =N534&TEXT(O534,"00")&TEXT(P534,"00") -> SDN100246 | R534: 122 | S534: 496 | T534: 884 | U534: 1285 | V534: 1703 | W534: 2069 | X534: 2449 | Y534: 2846 | Z534: 3262 | AA534: 4930 | AB534: 5127 | AC534: 5339 | AD534: 5568 | AE534: 5814 | AF534: 6085 | AG534: 6379 | AH534: 6698 | AI534: 7049 | AJ534: 7439 | AK534: 7880 | AL534: 8371 | AM534: 8915 | AN534: 9529 | AO534: 10222 | AP534: 0 | AQ534: 0 | AR534: 0 | AS534: 0 | AT534: 0 | AU534: 0 | AV534: 0 | AW534: 0 | AX534: 0 | AY534: 0 | AZ534: 0 | BA534: 0 | BB534: 0 | BC534: 0 | BD534: 0 | BE534: 0 | BF534: 0 | BG534: 0 | BH534: 0 | BI534: 0 | BJ534: 0 | BK534: 0 | BL534: 0 | BM534: 0 | BN534: 0 | BO534: 0 | BP534: 0 | BQ534: 0 | BR534: 0 | BS534: 0 | BT534: 0 | BU534: 0 | BV534: 0 | BW534: 0 | BX534: 0 | BY534: 0 | BZ534: 0 | CA534: 0 | CB534: 0 | CC534: 0 | CD534: 0 | CE534: 0 | CF534: 0 | CG534: 0 | CH534: 0 | CI534: 0 | CJ534: 0 | CK534: 0 | CL534: 0 | CM534: 0 | CN534: 0 | CO534: 0 | CP534: 0 | CQ534: 0 | CR534: 0 | CS534: 0 | CT534: 0 | CU534: 0 | CV534: 0 | CW534: 0 | CX534: 0 | CY534: 0 | CZ534: 0 | DA534: 0 | DB534: 0 | DC534: 0 | DD534: 0 | DE534: 0 | DF534: 0 | DG534: 0 | DH534: 0 | DI534: 0 | DJ534: 0 | DK534: 0 | DL534: 0 | DM534: 0 | DN534: 0 | DO534: 0 | DP534: 0 | DQ534: 0 | DR534: 0 | DS534: 0 | DT534: 0 | DU534: 0 | DV534: 0 | DW534: 0 | DX534: 0 | EA534: SDN10 | EB534: 2 | EC534: 46 | ED534: =EA534&TEXT(EB534,"00")&TEXT(EC534,"00") -> SDN100246 | EE534: 178 | EF534: 788 | EG534: 1469 | EH534: 2132 | EI534: 2796 | EJ534: 3335 | EK534: 3879 | EL534: 4432 | EM534: 4989 | EN534: 0 | EO534: 0 | EP534: 0 | EQ534: 0 | ER534: 0 | ES534: 0 | ET534: 0 | EU534: 0 | EV534: 0 | EW534: 0 | EX534: 0 | EY534: 0 | EZ534: 0 | FA534: 0 | FB534: 0 | FC534: 0 | FD534: 0 | FE534: 0 | FF534: 0 | FG534: 0 | FH534: 0 | FI534: 0 | FJ534: 0 | FK534: 0 | FL534: 0 | FM534: 0 | FN534: 0 | FO534: 0 | FP534: 0 | FQ534: 0 | FR534: 0 | FS534: 0 | FT534: 0 | FU534: 0 | FV534: 0 | FW534: 0 | FX534: 0 | FY534: 0 | FZ534: 0 | GA534: 0 | GB534: 0 | GC534: 0 | GD534: 0 | GE534: 0 | GF534: 0 | GG534: 0 | GH534: 0 | GI534: 0 | GJ534: 0 | GK534: 0 | GL534: 0 | GM534: 0 | GN534: 0 | GO534: 0 | GP534: 0 | GQ534: 0 | GR534: 0 | GS534: 0 | GT534: 0 | GU534: 0 | GV534: 0 | GW534: 0 | GX534: 0 | GY534: 0 | GZ534: 0 | HA534: 0 | HB534: 0 | HC534: 0 | HD534: 0 | HE534: 0 | HF534: 0 | HG534: 0 | HH534: 0 | HI534: 0 | HJ534: 0 | HK534: 0 | HL534: 0 | HM534: 0 | HN534: 0 | HO534: 0 | HP534: 0 | HQ534: 0 | HR534: 0 | HS534: 0 | HT534: 0 | HU534: 0 | HV534: 0 | HW534: 0 | HX534: 0 | HY534: 0 | HZ534: 0 | IA534: 0 | IB534: 0 | IC534: 0 | ID534: 0 | IE534: 0 | IF534: 0 | IG534: 0 | IH534: 0 | II534: 0 | IJ534: 0 | IK534: 0
B535: SDN10 | F535: 1 | H535: 53 | I535: 3 | J535: =B535&TEXT(F535,"00")&TEXT(H535,"00")&TEXT(I535,"00") -> SDN10015303 | K535: 1755 | N535: SDN10 | O535: 2 | P535: 47 | Q535: =N535&TEXT(O535,"00")&TEXT(P535,"00") -> SDN100247 | R535: 110 | S535: 482 | T535: 868 | U535: 1268 | V535: 1685 | W535: 2050 | X535: 2429 | Y535: 2826 | Z535: 3242 | AA535: 4902 | AB535: 5102 | AC535: 5317 | AD535: 5550 | AE535: 5804 | AF535: 6080 | AG535: 6380 | AH535: 6709 | AI535: 7073 | AJ535: 7487 | AK535: 7945 | AL535: 8453 | AM535: 9025 | AN535: 9669 | AO535: 10415 | AP535: 0 | AQ535: 0 | AR535: 0 | AS535: 0 | AT535: 0 | AU535: 0 | AV535: 0 | AW535: 0 | AX535: 0 | AY535: 0 | AZ535: 0 | BA535: 0 | BB535: 0 | BC535: 0 | BD535: 0 | BE535: 0 | BF535: 0 | BG535: 0 | BH535: 0 | BI535: 0 | BJ535: 0 | BK535: 0 | BL535: 0 | BM535: 0 | BN535: 0 | BO535: 0 | BP535: 0 | BQ535: 0 | BR535: 0 | BS535: 0 | BT535: 0 | BU535: 0 | BV535: 0 | BW535: 0 | BX535: 0 | BY535: 0 | BZ535: 0 | CA535: 0 | CB535: 0 | CC535: 0 | CD535: 0 | CE535: 0 | CF535: 0 | CG535: 0 | CH535: 0 | CI535: 0 | CJ535: 0 | CK535: 0 | CL535: 0 | CM535: 0 | CN535: 0 | CO535: 0 | CP535: 0 | CQ535: 0 | CR535: 0 | CS535: 0 | CT535: 0 | CU535: 0 | CV535: 0 | CW535: 0 | CX535: 0 | CY535: 0 | CZ535: 0 | DA535: 0 | DB535: 0 | DC535: 0 | DD535: 0 | DE535: 0 | DF535: 0 | DG535: 0 | DH535: 0 | DI535: 0 | DJ535: 0 | DK535: 0 | DL535: 0 | DM535: 0 | DN535: 0 | DO535: 0 | DP535: 0 | DQ535: 0 | DR535: 0 | DS535: 0 | DT535: 0 | DU535: 0 | DV535: 0 | DW535: 0 | DX535: 0 | EA535: SDN10 | EB535: 2 | EC535: 47 | ED535: =EA535&TEXT(EB535,"00")&TEXT(EC535,"00") -> SDN100247 | EE535: 157 | EF535: 747 | EG535: 1410 | EH535: 2056 | EI535: 2703 | EJ535: 3228 | EK535: 3755 | EL535: 4293 | EM535: 4837 | EN535: 0 | EO535: 0 | EP535: 0 | EQ535: 0 | ER535: 0 | ES535: 0 | ET535: 0 | EU535: 0 | EV535: 0 | EW535: 0 | EX535: 0 | EY535: 0 | EZ535: 0 | FA535: 0 | FB535: 0 | FC535: 0 | FD535: 0 | FE535: 0 | FF535: 0 | FG535: 0 | FH535: 0 | FI535: 0 | FJ535: 0 | FK535: 0 | FL535: 0 | FM535: 0 | FN535: 0 | FO535: 0 | FP535: 0 | FQ535: 0 | FR535: 0 | FS535: 0 | FT535: 0 | FU535: 0 | FV535: 0 | FW535: 0 | FX535: 0 | FY535: 0 | FZ535: 0 | GA535: 0 | GB535: 0 | GC535: 0 | GD535: 0 | GE535: 0 | GF535: 0 | GG535: 0 | GH535: 0 | GI535: 0 | GJ535: 0 | GK535: 0 | GL535: 0 | GM535: 0 | GN535: 0 | GO535: 0 | GP535: 0 | GQ535: 0 | GR535: 0 | GS535: 0 | GT535: 0 | GU535: 0 | GV535: 0 | GW535: 0 | GX535: 0 | GY535: 0 | GZ535: 0 | HA535: 0 | HB535: 0 | HC535: 0 | HD535: 0 | HE535: 0 | HF535: 0 | HG535: 0 | HH535: 0 | HI535: 0 | HJ535: 0 | HK535: 0 | HL535: 0 | HM535: 0 | HN535: 0 | HO535: 0 | HP535: 0 | HQ535: 0 | HR535: 0 | HS535: 0 | HT535: 0 | HU535: 0 | HV535: 0 | HW535: 0 | HX535: 0 | HY535: 0 | HZ535: 0 | IA535: 0 | IB535: 0 | IC535: 0 | ID535: 0 | IE535: 0 | IF535: 0 | IG535: 0 | IH535: 0 | II535: 0 | IJ535: 0 | IK535: 0
B536: SDN10 | F536: 1 | H536: 53 | I536: 4 | J536: =B536&TEXT(F536,"00")&TEXT(H536,"00")&TEXT(I536,"00") -> SDN10015304 | K536: 1755 | N536: SDN10 | O536: 2 | P536: 48 | Q536: =N536&TEXT(O536,"00")&TEXT(P536,"00") -> SDN100248 | R536: 98 | S536: 471 | T536: 859 | U536: 1261 | V536: 1679 | W536: 2044 | X536: 2426 | Y536: 2825 | Z536: 3243 | AA536: 4909 | AB536: 5113 | AC536: 5333 | AD536: 5574 | AE536: 5835 | AF536: 6119 | AG536: 6429 | AH536: 6772 | AI536: 7161 | AJ536: 7592 | AK536: 8069 | AL536: 8605 | AM536: 9208 | AN536: 9906 | AO536: 10698 | AP536: 0 | AQ536: 0 | AR536: 0 | AS536: 0 | AT536: 0 | AU536: 0 | AV536: 0 | AW536: 0 | AX536: 0 | AY536: 0 | AZ536: 0 | BA536: 0 | BB536: 0 | BC536: 0 | BD536: 0 | BE536: 0 | BF536: 0 | BG536: 0 | BH536: 0 | BI536: 0 | BJ536: 0 | BK536: 0 | BL536: 0 | BM536: 0 | BN536: 0 | BO536: 0 | BP536: 0 | BQ536: 0 | BR536: 0 | BS536: 0 | BT536: 0 | BU536: 0 | BV536: 0 | BW536: 0 | BX536: 0 | BY536: 0 | BZ536: 0 | CA536: 0 | CB536: 0 | CC536: 0 | CD536: 0 | CE536: 0 | CF536: 0 | CG536: 0 | CH536: 0 | CI536: 0 | CJ536: 0 | CK536: 0 | CL536: 0 | CM536: 0 | CN536: 0 | CO536: 0 | CP536: 0 | CQ536: 0 | CR536: 0 | CS536: 0 | CT536: 0 | CU536: 0 | CV536: 0 | CW536: 0 | CX536: 0 | CY536: 0 | CZ536: 0 | DA536: 0 | DB536: 0 | DC536: 0 | DD536: 0 | DE536: 0 | DF536: 0 | DG536: 0 | DH536: 0 | DI536: 0 | DJ536: 0 | DK536: 0 | DL536: 0 | DM536: 0 | DN536: 0 | DO536: 0 | DP536: 0 | DQ536: 0 | DR536: 0 | DS536: 0 | DT536: 0 | DU536: 0 | DV536: 0 | DW536: 0 | DX536: 0 | EA536: SDN10 | EB536: 2 | EC536: 48 | ED536: =EA536&TEXT(EB536,"00")&TEXT(EC536,"00") -> SDN100248 | EE536: 136 | EF536: 706 | EG536: 1354 | EH536: 1984 | EI536: 2611 | EJ536: 3119 | EK536: 3632 | EL536: 4154 | EM536: 4683 | EN536: 0 | EO536: 0 | EP536: 0 | EQ536: 0 | ER536: 0 | ES536: 0 | ET536: 0 | EU536: 0 | EV536: 0 | EW536: 0 | EX536: 0 | EY536: 0 | EZ536: 0 | FA536: 0 | FB536: 0 | FC536: 0 | FD536: 0 | FE536: 0 | FF536: 0 | FG536: 0 | FH536: 0 | FI536: 0 | FJ536: 0 | FK536: 0 | FL536: 0 | FM536: 0 | FN536: 0 | FO536: 0 | FP536: 0 | FQ536: 0 | FR536: 0 | FS536: 0 | FT536: 0 | FU536: 0 | FV536: 0 | FW536: 0 | FX536: 0 | FY536: 0 | FZ536: 0 | GA536: 0 | GB536: 0 | GC536: 0 | GD536: 0 | GE536: 0 | GF536: 0 | GG536: 0 | GH536: 0 | GI536: 0 | GJ536: 0 | GK536: 0 | GL536: 0 | GM536: 0 | GN536: 0 | GO536: 0 | GP536: 0 | GQ536: 0 | GR536: 0 | GS536: 0 | GT536: 0 | GU536: 0 | GV536: 0 | GW536: 0 | GX536: 0 | GY536: 0 | GZ536: 0 | HA536: 0 | HB536: 0 | HC536: 0 | HD536: 0 | HE536: 0 | HF536: 0 | HG536: 0 | HH536: 0 | HI536: 0 | HJ536: 0 | HK536: 0 | HL536: 0 | HM536: 0 | HN536: 0 | HO536: 0 | HP536: 0 | HQ536: 0 | HR536: 0 | HS536: 0 | HT536: 0 | HU536: 0 | HV536: 0 | HW536: 0 | HX536: 0 | HY536: 0 | HZ536: 0 | IA536: 0 | IB536: 0 | IC536: 0 | ID536: 0 | IE536: 0 | IF536: 0 | IG536: 0 | IH536: 0 | II536: 0 | IJ536: 0 | IK536: 0
B537: SDN10 | F537: 1 | H537: 53 | I537: 5 | J537: =B537&TEXT(F537,"00")&TEXT(H537,"00")&TEXT(I537,"00") -> SDN10015305 | K537: 1755 | N537: SDN10 | O537: 2 | P537: 49 | Q537: =N537&TEXT(O537,"00")&TEXT(P537,"00") -> SDN100249 | R537: 85 | S537: 457 | T537: 842 | U537: 1243 | V537: 1659 | W537: 2024 | X537: 2405 | Y537: 2804 | Z537: 3223 | AA537: 4883 | AB537: 5089 | AC537: 5316 | AD537: 5561 | AE537: 5827 | AF537: 6117 | AG537: 6438 | AH537: 6802 | AI537: 7204 | AJ537: 7648 | AK537: 8147 | AL537: 8706 | AM537: 9354 | AN537: 10088 | AO537: 10920 | AP537: 0 | AQ537: 0 | AR537: 0 | AS537: 0 | AT537: 0 | AU537: 0 | AV537: 0 | AW537: 0 | AX537: 0 | AY537: 0 | AZ537: 0 | BA537: 0 | BB537: 0 | BC537: 0 | BD537: 0 | BE537: 0 | BF537: 0 | BG537: 0 | BH537: 0 | BI537: 0 | BJ537: 0 | BK537: 0 | BL537: 0 | BM537: 0 | BN537: 0 | BO537: 0 | BP537: 0 | BQ537: 0 | BR537: 0 | BS537: 0 | BT537: 0 | BU537: 0 | BV537: 0 | BW537: 0 | BX537: 0 | BY537: 0 | BZ537: 0 | CA537: 0 | CB537: 0 | CC537: 0 | CD537: 0 | CE537: 0 | CF537: 0 | CG537: 0 | CH537: 0 | CI537: 0 | CJ537: 0 | CK537: 0 | CL537: 0 | CM537: 0 | CN537: 0 | CO537: 0 | CP537: 0 | CQ537: 0 | CR537: 0 | CS537: 0 | CT537: 0 | CU537: 0 | CV537: 0 | CW537: 0 | CX537: 0 | CY537: 0 | CZ537: 0 | DA537: 0 | DB537: 0 | DC537: 0 | DD537: 0 | DE537: 0 | DF537: 0 | DG537: 0 | DH537: 0 | DI537: 0 | DJ537: 0 | DK537: 0 | DL537: 0 | DM537: 0 | DN537: 0 | DO537: 0 | DP537: 0 | DQ537: 0 | DR537: 0 | DS537: 0 | DT537: 0 | DU537: 0 | DV537: 0 | DW537: 0 | DX537: 0 | EA537: SDN10 | EB537: 2 | EC537: 49 | ED537: =EA537&TEXT(EB537,"00")&TEXT(EC537,"00") -> SDN100249 | EE537: 115 | EF537: 665 | EG537: 1294 | EH537: 1905 | EI537: 2513 | EJ537: 3005 | EK537: 3503 | EL537: 4008 | EM537: 4524 | EN537: 0 | EO537: 0 | EP537: 0 | EQ537: 0 | ER537: 0 | ES537: 0 | ET537: 0 | EU537: 0 | EV537: 0 | EW537: 0 | EX537: 0 | EY537: 0 | EZ537: 0 | FA537: 0 | FB537: 0 | FC537: 0 | FD537: 0 | FE537: 0 | FF537: 0 | FG537: 0 | FH537: 0 | FI537: 0 | FJ537: 0 | FK537: 0 | FL537: 0 | FM537: 0 | FN537: 0 | FO537: 0 | FP537: 0 | FQ537: 0 | FR537: 0 | FS537: 0 | FT537: 0 | FU537: 0 | FV537: 0 | FW537: 0 | FX537: 0 | FY537: 0 | FZ537: 0 | GA537: 0 | GB537: 0 | GC537: 0 | GD537: 0 | GE537: 0 | GF537: 0 | GG537: 0 | GH537: 0 | GI537: 0 | GJ537: 0 | GK537: 0 | GL537: 0 | GM537: 0 | GN537: 0 | GO537: 0 | GP537: 0 | GQ537: 0 | GR537: 0 | GS537: 0 | GT537: 0 | GU537: 0 | GV537: 0 | GW537: 0 | GX537: 0 | GY537: 0 | GZ537: 0 | HA537: 0 | HB537: 0 | HC537: 0 | HD537: 0 | HE537: 0 | HF537: 0 | HG537: 0 | HH537: 0 | HI537: 0 | HJ537: 0 | HK537: 0 | HL537: 0 | HM537: 0 | HN537: 0 | HO537: 0 | HP537: 0 | HQ537: 0 | HR537: 0 | HS537: 0 | HT537: 0 | HU537: 0 | HV537: 0 | HW537: 0 | HX537: 0 | HY537: 0 | HZ537: 0 | IA537: 0 | IB537: 0 | IC537: 0 | ID537: 0 | IE537: 0 | IF537: 0 | IG537: 0 | IH537: 0 | II537: 0 | IJ537: 0 | IK537: 0
B538: SDN10 | F538: 1 | H538: 53 | I538: 6 | J538: =B538&TEXT(F538,"00")&TEXT(H538,"00")&TEXT(I538,"00") -> SDN10015306 | K538: 1404 | N538: SDN10 | O538: 2 | P538: 50 | Q538: =N538&TEXT(O538,"00")&TEXT(P538,"00") -> SDN100250 | R538: 71 | S538: 442 | T538: 826 | U538: 1225 | V538: 1640 | W538: 2006 | X538: 2387 | Y538: 2788 | Z538: 3207 | AA538: 4865 | AB538: 5078 | AC538: 5308 | AD538: 5557 | AE538: 5829 | AF538: 6130 | AG538: 6470 | AH538: 6846 | AI538: 7259 | AJ538: 7724 | AK538: 8243 | AL538: 8846 | AM538: 9526 | AN538: 10295 | AO538: 11185 | AP538: 0 | AQ538: 0 | AR538: 0 | AS538: 0 | AT538: 0 | AU538: 0 | AV538: 0 | AW538: 0 | AX538: 0 | AY538: 0 | AZ538: 0 | BA538: 0 | BB538: 0 | BC538: 0 | BD538: 0 | BE538: 0 | BF538: 0 | BG538: 0 | BH538: 0 | BI538: 0 | BJ538: 0 | BK538: 0 | BL538: 0 | BM538: 0 | BN538: 0 | BO538: 0 | BP538: 0 | BQ538: 0 | BR538: 0 | BS538: 0 | BT538: 0 | BU538: 0 | BV538: 0 | BW538: 0 | BX538: 0 | BY538: 0 | BZ538: 0 | CA538: 0 | CB538: 0 | CC538: 0 | CD538: 0 | CE538: 0 | CF538: 0 | CG538: 0 | CH538: 0 | CI538: 0 | CJ538: 0 | CK538: 0 | CL538: 0 | CM538: 0 | CN538: 0 | CO538: 0 | CP538: 0 | CQ538: 0 | CR538: 0 | CS538: 0 | CT538: 0 | CU538: 0 | CV538: 0 | CW538: 0 | CX538: 0 | CY538: 0 | CZ538: 0 | DA538: 0 | DB538: 0 | DC538: 0 | DD538: 0 | DE538: 0 | DF538: 0 | DG538: 0 | DH538: 0 | DI538: 0 | DJ538: 0 | DK538: 0 | DL538: 0 | DM538: 0 | DN538: 0 | DO538: 0 | DP538: 0 | DQ538: 0 | DR538: 0 | DS538: 0 | DT538: 0 | DU538: 0 | DV538: 0 | DW538: 0 | DX538: 0 | EA538: SDN10 | EB538: 2 | EC538: 50 | ED538: =EA538&TEXT(EB538,"00")&TEXT(EC538,"00") -> SDN100250 | EE538: 94 | EF538: 622 | EG538: 1231 | EH538: 1823 | EI538: 2411 | EJ538: 2890 | EK538: 3370 | EL538: 3861 | EM538: 4361 | EN538: 0 | EO538: 0 | EP538: 0 | EQ538: 0 | ER538: 0 | ES538: 0 | ET538: 0 | EU538: 0 | EV538: 0 | EW538: 0 | EX538: 0 | EY538: 0 | EZ538: 0 | FA538: 0 | FB538: 0 | FC538: 0 | FD538: 0 | FE538: 0 | FF538: 0 | FG538: 0 | FH538: 0 | FI538: 0 | FJ538: 0 | FK538: 0 | FL538: 0 | FM538: 0 | FN538: 0 | FO538: 0 | FP538: 0 | FQ538: 0 | FR538: 0 | FS538: 0 | FT538: 0 | FU538: 0 | FV538: 0 | FW538: 0 | FX538: 0 | FY538: 0 | FZ538: 0 | GA538: 0 | GB538: 0 | GC538: 0 | GD538: 0 | GE538: 0 | GF538: 0 | GG538: 0 | GH538: 0 | GI538: 0 | GJ538: 0 | GK538: 0 | GL538: 0 | GM538: 0 | GN538: 0 | GO538: 0 | GP538: 0 | GQ538: 0 | GR538: 0 | GS538: 0 | GT538: 0 | GU538: 0 | GV538: 0 | GW538: 0 | GX538: 0 | GY538: 0 | GZ538: 0 | HA538: 0 | HB538: 0 | HC538: 0 | HD538: 0 | HE538: 0 | HF538: 0 | HG538: 0 | HH538: 0 | HI538: 0 | HJ538: 0 | HK538: 0 | HL538: 0 | HM538: 0 | HN538: 0 | HO538: 0 | HP538: 0 | HQ538: 0 | HR538: 0 | HS538: 0 | HT538: 0 | HU538: 0 | HV538: 0 | HW538: 0 | HX538: 0 | HY538: 0 | HZ538: 0 | IA538: 0 | IB538: 0 | IC538: 0 | ID538: 0 | IE538: 0 | IF538: 0 | IG538: 0 | IH538: 0 | II538: 0 | IJ538: 0 | IK538: 0
B539: SDN10 | F539: 1 | H539: 53 | I539: 7 | J539: =B539&TEXT(F539,"00")&TEXT(H539,"00")&TEXT(I539,"00") -> SDN10015307 | K539: 1404 | N539: SDN10 | O539: 2 | P539: 51 | Q539: =N539&TEXT(O539,"00")&TEXT(P539,"00") -> SDN100251 | R539: 55 | S539: 423 | T539: 805 | U539: 1202 | V539: 1616 | W539: 1980 | X539: 2361 | Y539: 2761 | Z539: 3180 | AA539: 4833 | AB539: 5048 | AC539: 5281 | AD539: 5534 | AE539: 5814 | AF539: 6131 | AG539: 6480 | AH539: 6864 | AI539: 7294 | AJ539: 7774 | AK539: 8330 | AL539: 8958 | AM539: 9666 | AN539: 10483 | AO539: 11429 | AP539: 0 | AQ539: 0 | AR539: 0 | AS539: 0 | AT539: 0 | AU539: 0 | AV539: 0 | AW539: 0 | AX539: 0 | AY539: 0 | AZ539: 0 | BA539: 0 | BB539: 0 | BC539: 0 | BD539: 0 | BE539: 0 | BF539: 0 | BG539: 0 | BH539: 0 | BI539: 0 | BJ539: 0 | BK539: 0 | BL539: 0 | BM539: 0 | BN539: 0 | BO539: 0 | BP539: 0 | BQ539: 0 | BR539: 0 | BS539: 0 | BT539: 0 | BU539: 0 | BV539: 0 | BW539: 0 | BX539: 0 | BY539: 0 | BZ539: 0 | CA539: 0 | CB539: 0 | CC539: 0 | CD539: 0 | CE539: 0 | CF539: 0 | CG539: 0 | CH539: 0 | CI539: 0 | CJ539: 0 | CK539: 0 | CL539: 0 | CM539: 0 | CN539: 0 | CO539: 0 | CP539: 0 | CQ539: 0 | CR539: 0 | CS539: 0 | CT539: 0 | CU539: 0 | CV539: 0 | CW539: 0 | CX539: 0 | CY539: 0 | CZ539: 0 | DA539: 0 | DB539: 0 | DC539: 0 | DD539: 0 | DE539: 0 | DF539: 0 | DG539: 0 | DH539: 0 | DI539: 0 | DJ539: 0 | DK539: 0 | DL539: 0 | DM539: 0 | DN539: 0 | DO539: 0 | DP539: 0 | DQ539: 0 | DR539: 0 | DS539: 0 | DT539: 0 | DU539: 0 | DV539: 0 | DW539: 0 | DX539: 0 | EA539: SDN10 | EB539: 2 | EC539: 51 | ED539: =EA539&TEXT(EB539,"00")&TEXT(EC539,"00") -> SDN100251 | EE539: 71 | EF539: 575 | EG539: 1165 | EH539: 1737 | EI539: 2306 | EJ539: 2767 | EK539: 3231 | EL539: 3705 | EM539: 4191 | EN539: 0 | EO539: 0 | EP539: 0 | EQ539: 0 | ER539: 0 | ES539: 0 | ET539: 0 | EU539: 0 | EV539: 0 | EW539: 0 | EX539: 0 | EY539: 0 | EZ539: 0 | FA539: 0 | FB539: 0 | FC539: 0 | FD539: 0 | FE539: 0 | FF539: 0 | FG539: 0 | FH539: 0 | FI539: 0 | FJ539: 0 | FK539: 0 | FL539: 0 | FM539: 0 | FN539: 0 | FO539: 0 | FP539: 0 | FQ539: 0 | FR539: 0 | FS539: 0 | FT539: 0 | FU539: 0 | FV539: 0 | FW539: 0 | FX539: 0 | FY539: 0 | FZ539: 0 | GA539: 0 | GB539: 0 | GC539: 0 | GD539: 0 | GE539: 0 | GF539: 0 | GG539: 0 | GH539: 0 | GI539: 0 | GJ539: 0 | GK539: 0 | GL539: 0 | GM539: 0 | GN539: 0 | GO539: 0 | GP539: 0 | GQ539: 0 | GR539: 0 | GS539: 0 | GT539: 0 | GU539: 0 | GV539: 0 | GW539: 0 | GX539: 0 | GY539: 0 | GZ539: 0 | HA539: 0 | HB539: 0 | HC539: 0 | HD539: 0 | HE539: 0 | HF539: 0 | HG539: 0 | HH539: 0 | HI539: 0 | HJ539: 0 | HK539: 0 | HL539: 0 | HM539: 0 | HN539: 0 | HO539: 0 | HP539: 0 | HQ539: 0 | HR539: 0 | HS539: 0 | HT539: 0 | HU539: 0 | HV539: 0 | HW539: 0 | HX539: 0 | HY539: 0 | HZ539: 0 | IA539: 0 | IB539: 0 | IC539: 0 | ID539: 0 | IE539: 0 | IF539: 0 | IG539: 0 | IH539: 0 | II539: 0 | IJ539: 0 | IK539: 0
... B843: SDN10 | F843: 2 | H843: 23 | I843: 1 | J843: =B843&TEXT(F843,"00")&TEXT(H843,"00")&TEXT(I843,"00") -> SDN10022301 | K843: 965 | N843: SDN30 | O843: 2 | P843: 39 | Q843: =N843&TEXT(O843,"00")&TEXT(P843,"00") -> SDN300239 | R843: 0 | S843: 44 | T843: 89 | U843: 134 | V843: 181 | W843: 230 | X843: 280 | Y843: 332 | Z843: 386 | AA843: 589 | AB843: 666 | AC843: 748 | AD843: 833 | AE843: 922 | AF843: 1015 | AG843: 1100 | AH843: 1190 | AI843: 1284 | AJ843: 1383 | AK843: 1488 | AL843: 1600 | AM843: 1721 | AN843: 1850 | AO843: 1988 | AP843: 2137 | AQ843: 2296 | AR843: 2473 | AS843: 2662 | AT843: 2864 | AU843: 3083 | AV843: 3268 | AW843: 3483 | AX843: 3720 | AY843: 3979 | AZ843: 4269 | BA843: 4594 | BB843: 4988 | BC843: 5432 | BD843: 5941 | BE843: 6539 | BF843: 7226 | BG843: 8048 | BH843: 9012 | BI843: 10184 | BJ843: 0 | BK843: 0 | BL843: 0 | BM843: 0 | BN843: 0 | BO843: 0 | BP843: 0 | BQ843: 0 | BR843: 0 | BS843: 0 | BT843: 0 | BU843: 0 | BV843: 0 | BW843: 0 | BX843: 0 | BY843: 0 | BZ843: 0 | CA843: 0 | CB843: 0 | CC843: 0 | CD843: 0 | CE843: 0 | CF843: 0 | CG843: 0 | CH843: 0 | CI843: 0 | CJ843: 0 | CK843: 0 | CL843: 0 | CM843: 0 | CN843: 0 | CO843: 0 | CP843: 0 | CQ843: 0 | CR843: 0 | CS843: 0 | CT843: 0 | CU843: 0 | CV843: 0 | CW843: 0 | CX843: 0 | CY843: 0 | CZ843: 0 | DA843: 0 | DB843: 0 | DC843: 0 | DD843: 0 | DE843: 0 | DF843: 0 | DG843: 0 | DH843: 0 | DI843: 0 | DJ843: 0 | DK843: 0 | DL843: 0 | DM843: 0 | DN843: 0 | DO843: 0 | DP843: 0 | DQ843: 0 | DR843: 0 | DS843: 0 | DT843: 0 | DU843: 0 | DV843: 0 | DW843: 0 | DX843: 0 | EA843: SDN30 | EB843: 2 | EC843: 39 | ED843: =EA843&TEXT(EB843,"00")&TEXT(EC843,"00") -> SDN300239 | EE843: 0 | EF843: 85 | EG843: 166 | EH843: 240 | EI843: 315 | EJ843: 388 | EK843: 461 | EL843: 553 | EM843: 655 | EN843: 911 | EO843: 1010 | EP843: 1111 | EQ843: 1212 | ER843: 1314 | ES843: 1417 | ET843: 1505 | EU843: 1595 | EV843: 1685 | EW843: 1777 | EX843: 1872 | EY843: 1971 | EZ843: 2075 | FA843: 2183 | FB843: 2295 | FC843: 2412 | FD843: 2534 | FE843: 2674 | FF843: 2822 | FG843: 2981 | FH843: 0 | FI843: 0 | FJ843: 0 | FK843: 0 | FL843: 0 | FM843: 0 | FN843: 0 | FO843: 0 | FP843: 0 | FQ843: 0 | FR843: 0 | FS843: 0 | FT843: 0 | FU843: 0 | FV843: 0 | FW843: 0 | FX843: 0 | FY843: 0 | FZ843: 0 | GA843: 0 | GB843: 0 | GC843: 0 | GD843: 0 | GE843: 0 | GF843: 0 | GG843: 0 | GH843: 0 | GI843: 0 | GJ843: 0 | GK843: 0 | GL843: 0 | GM843: 0 | GN843: 0 | GO843: 0 | GP843: 0 | GQ843: 0 | GR843: 0 | GS843: 0 | GT843: 0 | GU843: 0 | GV843: 0 | GW843: 0 | GX843: 0 | GY843: 0 | GZ843: 0 | HA843: 0 | HB843: 0 | HC843: 0 | HD843: 0 | HE843: 0 | HF843: 0 | HG843: 0 | HH843: 0 | HI843: 0 | HJ843: 0 | HK843: 0 | HL843: 0 | HM843: 0 | HN843: 0 | HO843: 0 | HP843: 0 | HQ843: 0 | HR843: 0 | HS843: 0 | HT843: 0 | HU843: 0 | HV843: 0 | HW843: 0 | HX843: 0 | HY843: 0 | HZ843: 0 | IA843: 0 | IB843: 0 | IC843: 0 | ID843: 0 | IE843: 0 | IF843: 0 | IG843: 0 | IH843: 0 | II843: 0 | IJ843: 0 | IK843: 0
B844: SDN10 | F844: 2 | H844: 23 | I844: 2 | J844: =B844&TEXT(F844,"00")&TEXT(H844,"00")&TEXT(I844,"00") -> SDN10022302 | K844: 965 | M844: 56 | N844: SDN30 | O844: 2 | P844: 40 | Q844: =N844&TEXT(O844,"00")&TEXT(P844,"00") -> SDN300240 | R844: 0 | S844: 43 | T844: 87 | U844: 133 | V844: 179 | W844: 228 | X844: 278 | Y844: 329 | Z844: 383 | AA844: 584 | AB844: 663 | AC844: 744 | AD844: 829 | AE844: 917 | AF844: 1008 | AG844: 1094 | AH844: 1183 | AI844: 1276 | AJ844: 1375 | AK844: 1480 | AL844: 1594 | AM844: 1715 | AN844: 1844 | AO844: 1983 | AP844: 2132 | AQ844: 2297 | AR844: 2474 | AS844: 2662 | AT844: 2865 | AU844: 3083 | AV844: 3282 | AW844: 3498 | AX844: 3734 | AY844: 3997 | AZ844: 4290 | BA844: 4648 | BB844: 5050 | BC844: 5507 | BD844: 6043 | BE844: 6656 | BF844: 7391 | BG844: 8249 | BH844: 9290 | BI844: 10534 | BJ844: 0 | BK844: 0 | BL844: 0 | BM844: 0 | BN844: 0 | BO844: 0 | BP844: 0 | BQ844: 0 | BR844: 0 | BS844: 0 | BT844: 0 | BU844: 0 | BV844: 0 | BW844: 0 | BX844: 0 | BY844: 0 | BZ844: 0 | CA844: 0 | CB844: 0 | CC844: 0 | CD844: 0 | CE844: 0 | CF844: 0 | CG844: 0 | CH844: 0 | CI844: 0 | CJ844: 0 | CK844: 0 | CL844: 0 | CM844: 0 | CN844: 0 | CO844: 0 | CP844: 0 | CQ844: 0 | CR844: 0 | CS844: 0 | CT844: 0 | CU844: 0 | CV844: 0 | CW844: 0 | CX844: 0 | CY844: 0 | CZ844: 0 | DA844: 0 | DB844: 0 | DC844: 0 | DD844: 0 | DE844: 0 | DF844: 0 | DG844: 0 | DH844: 0 | DI844: 0 | DJ844: 0 | DK844: 0 | DL844: 0 | DM844: 0 | DN844: 0 | DO844: 0 | DP844: 0 | DQ844: 0 | DR844: 0 | DS844: 0 | DT844: 0 | DU844: 0 | DV844: 0 | DW844: 0 | DX844: 0 | DZ844: 56 | EA844: SDN30 | EB844: 2 | EC844: 40 | ED844: =EA844&TEXT(EB844,"00")&TEXT(EC844,"00") -> SDN300240 | EE844: 0 | EF844: 81 | EG844: 157 | EH844: 232 | EI844: 303 | EJ844: 374 | EK844: 445 | EL844: 531 | EM844: 631 | EN844: 878 | EO844: 976 | EP844: 1072 | EQ844: 1170 | ER844: 1267 | ES844: 1363 | ET844: 1448 | EU844: 1533 | EV844: 1618 | EW844: 1706 | EX844: 1796 | EY844: 1892 | EZ844: 1990 | FA844: 2091 | FB844: 2196 | FC844: 2307 | FD844: 2432 | FE844: 2566 | FF844: 2706 | FG844: 2860 | FH844: 0 | FI844: 0 | FJ844: 0 | FK844: 0 | FL844: 0 | FM844: 0 | FN844: 0 | FO844: 0 | FP844: 0 | FQ844: 0 | FR844: 0 | FS844: 0 | FT844: 0 | FU844: 0 | FV844: 0 | FW844: 0 | FX844: 0 | FY844: 0 | FZ844: 0 | GA844: 0 | GB844: 0 | GC844: 0 | GD844: 0 | GE844: 0 | GF844: 0 | GG844: 0 | GH844: 0 | GI844: 0 | GJ844: 0 | GK844: 0 | GL844: 0 | GM844: 0 | GN844: 0 | GO844: 0 | GP844: 0 | GQ844: 0 | GR844: 0 | GS844: 0 | GT844: 0 | GU844: 0 | GV844: 0 | GW844: 0 | GX844: 0 | GY844: 0 | GZ844: 0 | HA844: 0 | HB844: 0 | HC844: 0 | HD844: 0 | HE844: 0 | HF844: 0 | HG844: 0 | HH844: 0 | HI844: 0 | HJ844: 0 | HK844: 0 | HL844: 0 | HM844: 0 | HN844: 0 | HO844: 0 | HP844: 0 | HQ844: 0 | HR844: 0 | HS844: 0 | HT844: 0 | HU844: 0 | HV844: 0 | HW844: 0 | HX844: 0 | HY844: 0 | HZ844: 0 | IA844: 0 | IB844: 0 | IC844: 0 | ID844: 0 | IE844: 0 | IF844: 0 | IG844: 0 | IH844: 0 | II844: 0 | IJ844: 0 | IK844: 0
B845: SDN10 | F845: 2 | H845: 23 | I845: 3 | J845: =B845&TEXT(F845,"00")&TEXT(H845,"00")&TEXT(I845,"00") -> SDN10022303 | K845: 965
B846: SDN10 | F846: 2 | H846: 23 | I846: 4 | J846: =B846&TEXT(F846,"00")&TEXT(H846,"00")&TEXT(I846,"00") -> SDN10022304 | K846: 965
B847: SDN10 | F847: 2 | H847: 23 | I847: 5 | J847: =B847&TEXT(F847,"00")&TEXT(H847,"00")&TEXT(I847,"00") -> SDN10022305 | K847: 965
B848: SDN10 | F848: 2 | H848: 23 | I848: 6 | J848: =B848&TEXT(F848,"00")&TEXT(H848,"00")&TEXT(I848,"00") -> SDN10022306 | K848: 772 | M848: HEALTH1(重大傷病給付-慢性精神病) | Q848: =N848&TEXT(O848,"00")&TEXT(P848,"00") -> 0000 | DZ848: tbHEALTH2(重大傷病給付-非慢性病) | ED848: =EA848&TEXT(EB848,"00")&TEXT(EC848,"00") -> 0000
B849: SDN10 | F849: 2 | H849: 23 | I849: 7 | J849: =B849&TEXT(F849,"00")&TEXT(H849,"00")&TEXT(I849,"00") -> SDN10022307 | K849: 772 | M849: 版次 | N849: 商品代號 | O849: 性別 | P849: 年齡 | Q849: =N849&TEXT(O849,"00")&TEXT(P849,"00") -> 商品代號性別年齡 | R849: 第1年重疾保險金 | S849: 第2年重疾保險金 | T849: 第3年重疾保險金 | U849: 第4年重疾保險金 | V849: 第5年重疾保險金 | W849: 第6年重疾保險金 | X849: 第7年重疾保險金 | Y849: 第8年重疾保險金 | Z849: 第9年重疾保險金 | AA849: 第10年重疾保險金 | AB849: 第11年重疾保險金 | AC849: 第12年重疾保險金 | AD849: 第13年重疾保險金 | AE849: 第14年重疾保險金 | AF849: 第15年重疾保險金 | AG849: 第16年重疾保險金 | AH849: 第17年重疾保險金 | AI849: 第18年重疾保險金 | AJ849: 第19年重疾保險金 | AK849: 第20年重疾保險金 | AL849: 第21年重疾保險金 | AM849: 第22年重疾保險金 | AN849: 第23年重疾保險金 | AO849: 第24年重疾保險金 | AP849: 第25年重疾保險金 | AQ849: 第26年重疾保險金 | AR849: 第27年重疾保險金 | AS849: 第28年重疾保險金 | AT849: 第29年重疾保險金 | AU849: 第30年重疾保險金 | AV849: 第31年重疾保險金 | AW849: 第32年重疾保險金 | AX849: 第33年重疾保險金 | AY849: 第34年重疾保險金 | AZ849: 第35年重疾保險金 | BA849: 第36年重疾保險金 | BB849: 第37年重疾保險金 | BC849: 第38年重疾保險金 | BD849: 第39年重疾保險金 | BE849: 第40年重疾保險金 | BF849: 第41年重疾保險金 | BG849: 第42年重疾保險金 | BH849: 第43年重疾保險金 | BI849: 第44年重疾保險金 | BJ849: 第45年重疾保險金 | BK849: 第46年重疾保險金 | BL849: 第47年重疾保險金 | BM849: 第48年重疾保險金 | BN849: 第49年重疾保險金 | BO849: 第50年重疾保險金 | BP849: 第51年重疾保險金 | BQ849: 第52年重疾保險金 | BR849: 第53年重疾保險金 | BS849: 第54年重疾保險金 | BT849: 第55年重疾保險金 | BU849: 第56年重疾保險金 | BV849: 第57年重疾保險金 | BW849: 第58年重疾保險金 | BX849: 第59年重疾保險金 | BY849: 第60年重疾保險金 | BZ849: 第61年重疾保險金 | CA849: 第62年重疾保險金 | CB849: 第63年重疾保險金 | CC849: 第64年重疾保險金 | CD849: 第65年重疾保險金 | CE849: 第66年重疾保險金 | CF849: 第67年重疾保險金 | CG849: 第68年重疾保險金 | CH849: 第69年重疾保險金 | CI849: 第70年重疾保險金 | CJ849: 第71年重疾保險金 | CK849: 第72年重疾保險金 | CL849: 第73年重疾保險金 | CM849: 第74年重疾保險金額 | CN849: 第75年重疾保險金 | CO849: 第76年重疾保險金 | CP849: 第77年重疾保險金 | CQ849: 第78年重疾保險金 | CR849: 第79年重疾保險金 | CS849: 第80年重疾保險金 | CT849: 第81年重疾保險金 | CU849: 第82年重疾保險金 | CV849: 第83年重疾保險金 | CW849: 第84年重疾保險金 | CX849: 第85年重疾保險金 | CY849: 第86年重疾保險金 | CZ849: 第87年重疾保險金 | DA849: 第88年重疾保險金 | DB849: 第89年重疾保險金 | DC849: 第90年重疾保險金 | DD849: 第91年重疾保險金 | DE849: 第92年重疾保險金 | DF849: 第93年重疾保險金 | DG849: 第94年重疾保險金 | DH849: 第95年重疾保險金 | DI849: 第96年重疾保險金 | DJ849: 第97年重疾保險金 | DK849: 第98年重疾保險金 | DL849: 第99年重疾保險金 | DM849: 第100年重疾保險金 | DN849: 第101年重疾保險金 | DO849: 第102年重疾保險金 | DP849: 第103年重疾保險金 | DQ849: 第104年重疾保險金 | DR849: 第105年重疾保險金 | DS849: 第106年重疾保險金 | DT849: 第107年重疾保險金 | DU849: 第108年重疾保險金 | DV849: 第109年重疾保險金 | DW849: 第110年重疾保險金 | DX849: 第111年重疾保險金 | DZ849: 版次 | EA849: 商品代號 | EB849: 性別 | EC849: 年齡 | ED849: =EA849&TEXT(EB849,"00")&TEXT(EC849,"00") -> 商品代號性別年齡 | EE849: 第1年重疾保險金 | EF849: 第2年重疾保險金 | EG849: 第3年重疾保險金 | EH849: 第4年重疾保險金 | EI849: 第5年重疾保險金 | EJ849: 第6年重疾保險金 | EK849: 第7年重疾保險金 | EL849: 第8年重疾保險金 | EM849: 第9年重疾保險金 | EN849: 第10年重疾保險金 | EO849: 第11年重疾保險金 | EP849: 第12年重疾保險金 | EQ849: 第13年重疾保險金 | ER849: 第14年重疾保險金 | ES849: 第15年重疾保險金 | ET849: 第16年重疾保險金 | EU849: 第17年重疾保險金 | EV849: 第18年重疾保險金 | EW849: 第19年重疾保險金 | EX849: 第20年重疾保險金 | EY849: 第21年重疾保險金 | EZ849: 第22年重疾保險金 | FA849: 第23年重疾保險金 | FB849: 第24年重疾保險金 | FC849: 第25年重疾保險金 | FD849: 第26年重疾保險金 | FE849: 第27年重疾保險金 | FF849: 第28年重疾保險金 | FG849: 第29年重疾保險金 | FH849: 第30年重疾保險金 | FI849: 第31年重疾保險金 | FJ849: 第32年重疾保險金 | FK849: 第33年重疾保險金 | FL849: 第34年重疾保險金 | FM849: 第35年重疾保險金 | FN849: 第36年重疾保險金 | FO849: 第37年重疾保險金 | FP849: 第38年重疾保險金 | FQ849: 第39年重疾保險金 | FR849: 第40年重疾保險金 | FS849: 第41年重疾保險金 | FT849: 第42年重疾保險金 | FU849: 第43年重疾保險金 | FV849: 第44年重疾保險金 | FW849: 第45年重疾保險金 | FX849: 第46年重疾保險金 | FY849: 第47年重疾保險金 | FZ849: 第48年重疾保險金 | GA849: 第49年重疾保險金 | GB849: 第50年重疾保險金 | GC849: 第51年重疾保險金 | GD849: 第52年重疾保險金 | GE849: 第53年重疾保險金 | GF849: 第54年重疾保險金 | GG849: 第55年重疾保險金 | GH849: 第56年重疾保險金 | GI849: 第57年重疾保險金 | GJ849: 第58年重疾保險金 | GK849: 第59年重疾保險金 | GL849: 第60年重疾保險金 | GM849: 第61年重疾保險金 | GN849: 第62年重疾保險金 | GO849: 第63年重疾保險金 | GP849: 第64年重疾保險金 | GQ849: 第65年重疾保險金 | GR849: 第66年重疾保險金 | GS849: 第67年重疾保險金 | GT849: 第68年重疾保險金 | GU849: 第69年重疾保險金 | GV849: 第70年重疾保險金 | GW849: 第71年重疾保險金 | GX849: 第72年重疾保險金 | GY849: 第73年重疾保險金 | GZ849: 第74年重疾保險金額 | HA849: 第75年重疾保險金 | HB849: 第76年重疾保險金 | HC849: 第77年重疾保險金 | HD849: 第78年重疾保險金 | HE849: 第79年重疾保險金 | HF849: 第80年重疾保險金 | HG849: 第81年重疾保險金 | HH849: 第82年重疾保險金 | HI849: 第83年重疾保險金 | HJ849: 第84年重疾保險金 | HK849: 第85年重疾保險金 | HL849: 第86年重疾保險金 | HM849: 第87年重疾保險金 | HN849: 第88年重疾保險金 | HO849: 第89年重疾保險金 | HP849: 第90年重疾保險金 | HQ849: 第91年重疾保險金 | HR849: 第92年重疾保險金 | HS849: 第93年重疾保險金 | HT849: 第94年重疾保險金 | HU849: 第95年重疾保險金 | HV849: 第96年重疾保險金 | HW849: 第97年重疾保險金 | HX849: 第98年重疾保險金 | HY849: 第99年重疾保險金 | HZ849: 第100年重疾保險金 | IA849: 第101年重疾保險金 | IB849: 第102年重疾保險金 | IC849: 第103年重疾保險金 | ID849: 第104年重疾保險金 | IE849: 第105年重疾保險金 | IF849: 第106年重疾保險金 | IG849: 第107年重疾保險金 | IH849: 第108年重疾保險金 | II849: 第109年重疾保險金 | IJ849: 第110年重疾保險金 | IK849: 第111年重疾保險金
B850: SDN10 | F850: 2 | H850: 23 | I850: 8 | J850: =B850&TEXT(F850,"00")&TEXT(H850,"00")&TEXT(I850,"00") -> SDN10022308 | K850: 772 | M850: 56 | N850: SDN10 | O850: 1 | P850: 0 | Q850: =N850&TEXT(O850,"00")&TEXT(P850,"00") -> SDN100100 | R850: 1017.6 | S850: 2035.2 | T850: 3052.8 | U850: 4070.4 | V850: 5088 | W850: 5902.1 | X850: 6716.2 | Y850: 7530.2 | Z850: 8344.3 | AA850: 9158.4 | AB850: 9158.4 | AC850: 9158.4 | AD850: 9158.4 | AE850: 9158.4 | AF850: 9158.4 | AG850: 9158.4 | AH850: 9158.4 | AI850: 9158.4 | AJ850: 9158.4 | AK850: 9158.4 | AL850: 9158.4 | AM850: 9158.4 | AN850: 9158.4 | AO850: 9158.4 | AP850: 9158.4 | AQ850: 0 | AR850: 0 | AS850: 0 | AT850: 0 | AU850: 0 | AV850: 0 | AW850: 0 | AX850: 0 | AY850: 0 | AZ850: 0 | BA850: 0 | BB850: 0 | BC850: 0 | BD850: 0 | BE850: 0 | BF850: 0 | BG850: 0 | BH850: 0 | BI850: 0 | BJ850: 0 | BK850: 0 | BL850: 0 | BM850: 0 | BN850: 0 | BO850: 0 | BP850: 0 | BQ850: 0 | BR850: 0 | BS850: 0 | BT850: 0 | BU850: 0 | BV850: 0 | BW850: 0 | BX850: 0 | BY850: 0 | BZ850: 0 | CA850: 0 | CB850: 0 | CC850: 0 | CD850: 0 | CE850: 0 | CF850: 0 | CG850: 0 | CH850: 0 | CI850: 0 | CJ850: 0 | CK850: 0 | CL850: 0 | CM850: 0 | CN850: 0 | CO850: 0 | CP850: 0 | CQ850: 0 | CR850: 0 | CS850: 0 | CT850: 0 | CU850: 0 | CV850: 0 | CW850: 0 | CX850: 0 | CY850: 0 | CZ850: 0 | DA850: 0 | DB850: 0 | DC850: 0 | DD850: 0 | DE850: 0 | DF850: 0 | DG850: 0 | DH850: 0 | DI850: 0 | DJ850: 0 | DK850: 0 | DL850: 0 | DM850: 0 | DN850: 0 | DO850: 0 | DP850: 0 | DQ850: 0 | DR850: 0 | DS850: 0 | DT850: 0 | DU850: 0 | DV850: 0 | DW850: 0 | DX850: 0 | DZ850: 56 | EA850: SDN10 | EB850: 1 | EC850: 0 | ED850: =EA850&TEXT(EB850,"00")&TEXT(EC850,"00") -> SDN100100 | EE850: 1017.6 | EF850: 10000 | EG850: 10000 | EH850: 10000 | EI850: 10000 | EJ850: 10000 | EK850: 10000 | EL850: 10000 | EM850: 10000 | EN850: 10000 | EO850: 10000 | EP850: 10000 | EQ850: 10000 | ER850: 10000 | ES850: 10000 | ET850: 10000 | EU850: 10000 | EV850: 10000 | EW850: 10000 | EX850: 10000 | EY850: 10000 | EZ850: 10000 | FA850: 10000 | FB850: 10000 | FC850: 10000 | FD850: 0 | FE850: 0 | FF850: 0 | FG850: 0 | FH850: 0 | FI850: 0 | FJ850: 0 | FK850: 0 | FL850: 0 | FM850: 0 | FN850: 0 | FO850: 0 | FP850: 0 | FQ850: 0 | FR850: 0 | FS850: 0 | FT850: 0 | FU850: 0 | FV850: 0 | FW850: 0 | FX850: 0 | FY850: 0 | FZ850: 0 | GA850: 0 | GB850: 0 | GC850: 0 | GD850: 0 | GE850: 0 | GF850: 0 | GG850: 0 | GH850: 0 | GI850: 0 | GJ850: 0 | GK850: 0 | GL850: 0 | GM850: 0 | GN850: 0 | GO850: 0 | GP850: 0 | GQ850: 0 | GR850: 0 | GS850: 0 | GT850: 0 | GU850: 0 | GV850: 0 | GW850: 0 | GX850: 0 | GY850: 0 | GZ850: 0 | HA850: 0 | HB850: 0 | HC850: 0 | HD850: 0 | HE850: 0 | HF850: 0 | HG850: 0 | HH850: 0 | HI850: 0 | HJ850: 0 | HK850: 0 | HL850: 0 | HM850: 0 | HN850: 0 | HO850: 0 | HP850: 0 | HQ850: 0 | HR850: 0 | HS850: 0 | HT850: 0 | HU850: 0 | HV850: 0 | HW850: 0 | HX850: 0 | HY850: 0 | HZ850: 0 | IA850: 0 | IB850: 0 | IC850: 0 | ID850: 0 | IE850: 0 | IF850: 0 | IG850: 0 | IH850: 0 | II850: 0 | IJ850: 0 | IK850: 0
B851: SDN10 | F851: 2 | H851: 23 | I851: 9 | J851: =B851&TEXT(F851,"00")&TEXT(H851,"00")&TEXT(I851,"00") -> SDN10022309 | K851: 772 | M851: 56 | N851: SDN10 | O851: 1 | P851: 1 | Q851: =N851&TEXT(O851,"00")&TEXT(P851,"00") -> SDN100101 | R851: 1017.6 | S851: 2035.2 | T851: 3052.8 | U851: 4070.4 | V851: 5088 | W851: 5902.1 | X851: 6716.2 | Y851: 7530.2 | Z851: 8344.3 | AA851: 9158.4 | AB851: 9158.4 | AC851: 9158.4 | AD851: 9158.4 | AE851: 9158.4 | AF851: 9158.4 | AG851: 9158.4 | AH851: 9158.4 | AI851: 9158.4 | AJ851: 9158.4 | AK851: 9158.4 | AL851: 9158.4 | AM851: 9158.4 | AN851: 9158.4 | AO851: 9158.4 | AP851: 9158.4 | AQ851: 0 | AR851: 0 | AS851: 0 | AT851: 0 | AU851: 0 | AV851: 0 | AW851: 0 | AX851: 0 | AY851: 0 | AZ851: 0 | BA851: 0 | BB851: 0 | BC851: 0 | BD851: 0 | BE851: 0 | BF851: 0 | BG851: 0 | BH851: 0 | BI851: 0 | BJ851: 0 | BK851: 0 | BL851: 0 | BM851: 0 | BN851: 0 | BO851: 0 | BP851: 0 | BQ851: 0 | BR851: 0 | BS851: 0 | BT851: 0 | BU851: 0 | BV851: 0 | BW851: 0 | BX851: 0 | BY851: 0 | BZ851: 0 | CA851: 0 | CB851: 0 | CC851: 0 | CD851: 0 | CE851: 0 | CF851: 0 | CG851: 0 | CH851: 0 | CI851: 0 | CJ851: 0 | CK851: 0 | CL851: 0 | CM851: 0 | CN851: 0 | CO851: 0 | CP851: 0 | CQ851: 0 | CR851: 0 | CS851: 0 | CT851: 0 | CU851: 0 | CV851: 0 | CW851: 0 | CX851: 0 | CY851: 0 | CZ851: 0 | DA851: 0 | DB851: 0 | DC851: 0 | DD851: 0 | DE851: 0 | DF851: 0 | DG851: 0 | DH851: 0 | DI851: 0 | DJ851: 0 | DK851: 0 | DL851: 0 | DM851: 0 | DN851: 0 | DO851: 0 | DP851: 0 | DQ851: 0 | DR851: 0 | DS851: 0 | DT851: 0 | DU851: 0 | DV851: 0 | DW851: 0 | DX851: 0 | DZ851: 56 | EA851: SDN10 | EB851: 1 | EC851: 1 | ED851: =EA851&TEXT(EB851,"00")&TEXT(EC851,"00") -> SDN100101 | EE851: 1017.6 | EF851: 10000 | EG851: 10000 | EH851: 10000 | EI851: 10000 | EJ851: 10000 | EK851: 10000 | EL851: 10000 | EM851: 10000 | EN851: 10000 | EO851: 10000 | EP851: 10000 | EQ851: 10000 | ER851: 10000 | ES851: 10000 | ET851: 10000 | EU851: 10000 | EV851: 10000 | EW851: 10000 | EX851: 10000 | EY851: 10000 | EZ851: 10000 | FA851: 10000 | FB851: 10000 | FC851: 10000 | FD851: 0 | FE851: 0 | FF851: 0 | FG851: 0 | FH851: 0 | FI851: 0 | FJ851: 0 | FK851: 0 | FL851: 0 | FM851: 0 | FN851: 0 | FO851: 0 | FP851: 0 | FQ851: 0 | FR851: 0 | FS851: 0 | FT851: 0 | FU851: 0 | FV851: 0 | FW851: 0 | FX851: 0 | FY851: 0 | FZ851: 0 | GA851: 0 | GB851: 0 | GC851: 0 | GD851: 0 | GE851: 0 | GF851: 0 | GG851: 0 | GH851: 0 | GI851: 0 | GJ851: 0 | GK851: 0 | GL851: 0 | GM851: 0 | GN851: 0 | GO851: 0 | GP851: 0 | GQ851: 0 | GR851: 0 | GS851: 0 | GT851: 0 | GU851: 0 | GV851: 0 | GW851: 0 | GX851: 0 | GY851: 0 | GZ851: 0 | HA851: 0 | HB851: 0 | HC851: 0 | HD851: 0 | HE851: 0 | HF851: 0 | HG851: 0 | HH851: 0 | HI851: 0 | HJ851: 0 | HK851: 0 | HL851: 0 | HM851: 0 | HN851: 0 | HO851: 0 | HP851: 0 | HQ851: 0 | HR851: 0 | HS851: 0 | HT851: 0 | HU851: 0 | HV851: 0 | HW851: 0 | HX851: 0 | HY851: 0 | HZ851: 0 | IA851: 0 | IB851: 0 | IC851: 0 | ID851: 0 | IE851: 0 | IF851: 0 | IG851: 0 | IH851: 0 | II851: 0 | IJ851: 0 | IK851: 0
B852: SDN10 | F852: 2 | H852: 23 | I852: 10 | J852: =B852&TEXT(F852,"00")&TEXT(H852,"00")&TEXT(I852,"00") -> SDN10022310 | K852: 772 | M852: 56 | N852: SDN10 | O852: 1 | P852: 2 | Q852: =N852&TEXT(O852,"00")&TEXT(P852,"00") -> SDN100102 | R852: 1017.6 | S852: 2035.2 | T852: 3052.8 | U852: 4070.4 | V852: 5088 | W852: 5902.1 | X852: 6716.2 | Y852: 7530.2 | Z852: 8344.3 | AA852: 9158.4 | AB852: 9158.4 | AC852: 9158.4 | AD852: 9158.4 | AE852: 9158.4 | AF852: 9158.4 | AG852: 9158.4 | AH852: 9158.4 | AI852: 9158.4 | AJ852: 9158.4 | AK852: 9158.4 | AL852: 9158.4 | AM852: 9158.4 | AN852: 9158.4 | AO852: 9158.4 | AP852: 9158.4 | AQ852: 0 | AR852: 0 | AS852: 0 | AT852: 0 | AU852: 0 | AV852: 0 | AW852: 0 | AX852: 0 | AY852: 0 | AZ852: 0 | BA852: 0 | BB852: 0 | BC852: 0 | BD852: 0 | BE852: 0 | BF852: 0 | BG852: 0 | BH852: 0 | BI852: 0 | BJ852: 0 | BK852: 0 | BL852: 0 | BM852: 0 | BN852: 0 | BO852: 0 | BP852: 0 | BQ852: 0 | BR852: 0 | BS852: 0 | BT852: 0 | BU852: 0 | BV852: 0 | BW852: 0 | BX852: 0 | BY852: 0 | BZ852: 0 | CA852: 0 | CB852: 0 | CC852: 0 | CD852: 0 | CE852: 0 | CF852: 0 | CG852: 0 | CH852: 0 | CI852: 0 | CJ852: 0 | CK852: 0 | CL852: 0 | CM852: 0 | CN852: 0 | CO852: 0 | CP852: 0 | CQ852: 0 | CR852: 0 | CS852: 0 | CT852: 0 | CU852: 0 | CV852: 0 | CW852: 0 | CX852: 0 | CY852: 0 | CZ852: 0 | DA852: 0 | DB852: 0 | DC852: 0 | DD852: 0 | DE852: 0 | DF852: 0 | DG852: 0 | DH852: 0 | DI852: 0 | DJ852: 0 | DK852: 0 | DL852: 0 | DM852: 0 | DN852: 0 | DO852: 0 | DP852: 0 | DQ852: 0 | DR852: 0 | DS852: 0 | DT852: 0 | DU852: 0 | DV852: 0 | DW852: 0 | DX852: 0 | DZ852: 56 | EA852: SDN10 | EB852: 1 | EC852: 2 | ED852: =EA852&TEXT(EB852,"00")&TEXT(EC852,"00") -> SDN100102 | EE852: 1017.6 | EF852: 10000 | EG852: 10000 | EH852: 10000 | EI852: 10000 | EJ852: 10000 | EK852: 10000 | EL852: 10000 | EM852: 10000 | EN852: 10000 | EO852: 10000 | EP852: 10000 | EQ852: 10000 | ER852: 10000 | ES852: 10000 | ET852: 10000 | EU852: 10000 | EV852: 10000 | EW852: 10000 | EX852: 10000 | EY852: 10000 | EZ852: 10000 | FA852: 10000 | FB852: 10000 | FC852: 10000 | FD852: 0 | FE852: 0 | FF852: 0 | FG852: 0 | FH852: 0 | FI852: 0 | FJ852: 0 | FK852: 0 | FL852: 0 | FM852: 0 | FN852: 0 | FO852: 0 | FP852: 0 | FQ852: 0 | FR852: 0 | FS852: 0 | FT852: 0 | FU852: 0 | FV852: 0 | FW852: 0 | FX852: 0 | FY852: 0 | FZ852: 0 | GA852: 0 | GB852: 0 | GC852: 0 | GD852: 0 | GE852: 0 | GF852: 0 | GG852: 0 | GH852: 0 | GI852: 0 | GJ852: 0 | GK852: 0 | GL852: 0 | GM852: 0 | GN852: 0 | GO852: 0 | GP852: 0 | GQ852: 0 | GR852: 0 | GS852: 0 | GT852: 0 | GU852: 0 | GV852: 0 | GW852: 0 | GX852: 0 | GY852: 0 | GZ852: 0 | HA852: 0 | HB852: 0 | HC852: 0 | HD852: 0 | HE852: 0 | HF852: 0 | HG852: 0 | HH852: 0 | HI852: 0 | HJ852: 0 | HK852: 0 | HL852: 0 | HM852: 0 | HN852: 0 | HO852: 0 | HP852: 0 | HQ852: 0 | HR852: 0 | HS852: 0 | HT852: 0 | HU852: 0 | HV852: 0 | HW852: 0 | HX852: 0 | HY852: 0 | HZ852: 0 | IA852: 0 | IB852: 0 | IC852: 0 | ID852: 0 | IE852: 0 | IF852: 0 | IG852: 0 | IH852: 0 | II852: 0 | IJ852: 0 | IK852: 0
B853: SDN10 | F853: 2 | H853: 24 | I853: 1 | J853: =B853&TEXT(F853,"00")&TEXT(H853,"00")&TEXT(I853,"00") -> SDN10022401 | K853: 965 | M853: 56 | N853: SDN10 | O853: 1 | P853: 3 | Q853: =N853&TEXT(O853,"00")&TEXT(P853,"00") -> SDN100103 | R853: 1017.6 | S853: 2035.2 | T853: 3052.8 | U853: 4070.4 | V853: 5088 | W853: 5902.1 | X853: 6716.2 | Y853: 7530.2 | Z853: 8344.3 | AA853: 9158.4 | AB853: 9158.4 | AC853: 9158.4 | AD853: 9158.4 | AE853: 9158.4 | AF853: 9158.4 | AG853: 9158.4 | AH853: 9158.4 | AI853: 9158.4 | AJ853: 9158.4 | AK853: 9158.4 | AL853: 9158.4 | AM853: 9158.4 | AN853: 9158.4 | AO853: 9158.4 | AP853: 9158.4 | AQ853: 0 | AR853: 0 | AS853: 0 | AT853: 0 | AU853: 0 | AV853: 0 | AW853: 0 | AX853: 0 | AY853: 0 | AZ853: 0 | BA853: 0 | BB853: 0 | BC853: 0 | BD853: 0 | BE853: 0 | BF853: 0 | BG853: 0 | BH853: 0 | BI853: 0 | BJ853: 0 | BK853: 0 | BL853: 0 | BM853: 0 | BN853: 0 | BO853: 0 | BP853: 0 | BQ853: 0 | BR853: 0 | BS853: 0 | BT853: 0 | BU853: 0 | BV853: 0 | BW853: 0 | BX853: 0 | BY853: 0 | BZ853: 0 | CA853: 0 | CB853: 0 | CC853: 0 | CD853: 0 | CE853: 0 | CF853: 0 | CG853: 0 | CH853: 0 | CI853: 0 | CJ853: 0 | CK853: 0 | CL853: 0 | CM853: 0 | CN853: 0 | CO853: 0 | CP853: 0 | CQ853: 0 | CR853: 0 | CS853: 0 | CT853: 0 | CU853: 0 | CV853: 0 | CW853: 0 | CX853: 0 | CY853: 0 | CZ853: 0 | DA853: 0 | DB853: 0 | DC853: 0 | DD853: 0 | DE853: 0 | DF853: 0 | DG853: 0 | DH853: 0 | DI853: 0 | DJ853: 0 | DK853: 0 | DL853: 0 | DM853: 0 | DN853: 0 | DO853: 0 | DP853: 0 | DQ853: 0 | DR853: 0 | DS853: 0 | DT853: 0 | DU853: 0 | DV853: 0 | DW853: 0 | DX853: 0 | DZ853: 56 | EA853: SDN10 | EB853: 1 | EC853: 3 | ED853: =EA853&TEXT(EB853,"00")&TEXT(EC853,"00") -> SDN100103 | EE853: 1017.6 | EF853: 10000 | EG853: 10000 | EH853: 10000 | EI853: 10000 | EJ853: 10000 | EK853: 10000 | EL853: 10000 | EM853: 10000 | EN853: 10000 | EO853: 10000 | EP853: 10000 | EQ853: 10000 | ER853: 10000 | ES853: 10000 | ET853: 10000 | EU853: 10000 | EV853: 10000 | EW853: 10000 | EX853: 10000 | EY853: 10000 | EZ853: 10000 | FA853: 10000 | FB853: 10000 | FC853: 10000 | FD853: 0 | FE853: 0 | FF853: 0 | FG853: 0 | FH853: 0 | FI853: 0 | FJ853: 0 | FK853: 0 | FL853: 0 | FM853: 0 | FN853: 0 | FO853: 0 | FP853: 0 | FQ853: 0 | FR853: 0 | FS853: 0 | FT853: 0 | FU853: 0 | FV853: 0 | FW853: 0 | FX853: 0 | FY853: 0 | FZ853: 0 | GA853: 0 | GB853: 0 | GC853: 0 | GD853: 0 | GE853: 0 | GF853: 0 | GG853: 0 | GH853: 0 | GI853: 0 | GJ853: 0 | GK853: 0 | GL853: 0 | GM853: 0 | GN853: 0 | GO853: 0 | GP853: 0 | GQ853: 0 | GR853: 0 | GS853: 0 | GT853: 0 | GU853: 0 | GV853: 0 | GW853: 0 | GX853: 0 | GY853: 0 | GZ853: 0 | HA853: 0 | HB853: 0 | HC853: 0 | HD853: 0 | HE853: 0 | HF853: 0 | HG853: 0 | HH853: 0 | HI853: 0 | HJ853: 0 | HK853: 0 | HL853: 0 | HM853: 0 | HN853: 0 | HO853: 0 | HP853: 0 | HQ853: 0 | HR853: 0 | HS853: 0 | HT853: 0 | HU853: 0 | HV853: 0 | HW853: 0 | HX853: 0 | HY853: 0 | HZ853: 0 | IA853: 0 | IB853: 0 | IC853: 0 | ID853: 0 | IE853: 0 | IF853: 0 | IG853: 0 | IH853: 0 | II853: 0 | IJ853: 0 | IK853: 0
B854: SDN10 | F854: 2 | H854: 24 | I854: 2 | J854: =B854&TEXT(F854,"00")&TEXT(H854,"00")&TEXT(I854,"00") -> SDN10022402 | K854: 965 | M854: 56 | N854: SDN10 | O854: 1 | P854: 4 | Q854: =N854&TEXT(O854,"00")&TEXT(P854,"00") -> SDN100104 | R854: 1017.6 | S854: 2035.2 | T854: 3052.8 | U854: 4070.4 | V854: 5088 | W854: 5902.1 | X854: 6716.2 | Y854: 7530.2 | Z854: 8344.3 | AA854: 9158.4 | AB854: 9158.4 | AC854: 9158.4 | AD854: 9158.4 | AE854: 9158.4 | AF854: 9158.4 | AG854: 9158.4 | AH854: 9158.4 | AI854: 9158.4 | AJ854: 9158.4 | AK854: 9158.4 | AL854: 9158.4 | AM854: 9158.4 | AN854: 9158.4 | AO854: 9158.4 | AP854: 9158.4 | AQ854: 0 | AR854: 0 | AS854: 0 | AT854: 0 | AU854: 0 | AV854: 0 | AW854: 0 | AX854: 0 | AY854: 0 | AZ854: 0 | BA854: 0 | BB854: 0 | BC854: 0 | BD854: 0 | BE854: 0 | BF854: 0 | BG854: 0 | BH854: 0 | BI854: 0 | BJ854: 0 | BK854: 0 | BL854: 0 | BM854: 0 | BN854: 0 | BO854: 0 | BP854: 0 | BQ854: 0 | BR854: 0 | BS854: 0 | BT854: 0 | BU854: 0 | BV854: 0 | BW854: 0 | BX854: 0 | BY854: 0 | BZ854: 0 | CA854: 0 | CB854: 0 | CC854: 0 | CD854: 0 | CE854: 0 | CF854: 0 | CG854: 0 | CH854: 0 | CI854: 0 | CJ854: 0 | CK854: 0 | CL854: 0 | CM854: 0 | CN854: 0 | CO854: 0 | CP854: 0 | CQ854: 0 | CR854: 0 | CS854: 0 | CT854: 0 | CU854: 0 | CV854: 0 | CW854: 0 | CX854: 0 | CY854: 0 | CZ854: 0 | DA854: 0 | DB854: 0 | DC854: 0 | DD854: 0 | DE854: 0 | DF854: 0 | DG854: 0 | DH854: 0 | DI854: 0 | DJ854: 0 | DK854: 0 | DL854: 0 | DM854: 0 | DN854: 0 | DO854: 0 | DP854: 0 | DQ854: 0 | DR854: 0 | DS854: 0 | DT854: 0 | DU854: 0 | DV854: 0 | DW854: 0 | DX854: 0 | DZ854: 56 | EA854: SDN10 | EB854: 1 | EC854: 4 | ED854: =EA854&TEXT(EB854,"00")&TEXT(EC854,"00") -> SDN100104 | EE854: 1017.6 | EF854: 10000 | EG854: 10000 | EH854: 10000 | EI854: 10000 | EJ854: 10000 | EK854: 10000 | EL854: 10000 | EM854: 10000 | EN854: 10000 | EO854: 10000 | EP854: 10000 | EQ854: 10000 | ER854: 10000 | ES854: 10000 | ET854: 10000 | EU854: 10000 | EV854: 10000 | EW854: 10000 | EX854: 10000 | EY854: 10000 | EZ854: 10000 | FA854: 10000 | FB854: 10000 | FC854: 10000 | FD854: 0 | FE854: 0 | FF854: 0 | FG854: 0 | FH854: 0 | FI854: 0 | FJ854: 0 | FK854: 0 | FL854: 0 | FM854: 0 | FN854: 0 | FO854: 0 | FP854: 0 | FQ854: 0 | FR854: 0 | FS854: 0 | FT854: 0 | FU854: 0 | FV854: 0 | FW854: 0 | FX854: 0 | FY854: 0 | FZ854: 0 | GA854: 0 | GB854: 0 | GC854: 0 | GD854: 0 | GE854: 0 | GF854: 0 | GG854: 0 | GH854: 0 | GI854: 0 | GJ854: 0 | GK854: 0 | GL854: 0 | GM854: 0 | GN854: 0 | GO854: 0 | GP854: 0 | GQ854: 0 | GR854: 0 | GS854: 0 | GT854: 0 | GU854: 0 | GV854: 0 | GW854: 0 | GX854: 0 | GY854: 0 | GZ854: 0 | HA854: 0 | HB854: 0 | HC854: 0 | HD854: 0 | HE854: 0 | HF854: 0 | HG854: 0 | HH854: 0 | HI854: 0 | HJ854: 0 | HK854: 0 | HL854: 0 | HM854: 0 | HN854: 0 | HO854: 0 | HP854: 0 | HQ854: 0 | HR854: 0 | HS854: 0 | HT854: 0 | HU854: 0 | HV854: 0 | HW854: 0 | HX854: 0 | HY854: 0 | HZ854: 0 | IA854: 0 | IB854: 0 | IC854: 0 | ID854: 0 | IE854: 0 | IF854: 0 | IG854: 0 | IH854: 0 | II854: 0 | IJ854: 0 | IK854: 0
B855: SDN10 | F855: 2 | H855: 24 | I855: 3 | J855: =B855&TEXT(F855,"00")&TEXT(H855,"00")&TEXT(I855,"00") -> SDN10022403 | K855: 965 | M855: 56 | N855: SDN10 | O855: 1 | P855: 5 | Q855: =N855&TEXT(O855,"00")&TEXT(P855,"00") -> SDN100105 | R855: 1017.6 | S855: 2035.2 | T855: 3052.8 | U855: 4070.4 | V855: 5088 | W855: 5902.1 | X855: 6716.2 | Y855: 7530.2 | Z855: 8344.3 | AA855: 9158.4 | AB855: 9158.4 | AC855: 9158.4 | AD855: 9158.4 | AE855: 9158.4 | AF855: 9158.4 | AG855: 9158.4 | AH855: 9158.4 | AI855: 9158.4 | AJ855: 9158.4 | AK855: 9158.4 | AL855: 9158.4 | AM855: 9158.4 | AN855: 9158.4 | AO855: 9158.4 | AP855: 9158.4 | AQ855: 0 | AR855: 0 | AS855: 0 | AT855: 0 | AU855: 0 | AV855: 0 | AW855: 0 | AX855: 0 | AY855: 0 | AZ855: 0 | BA855: 0 | BB855: 0 | BC855: 0 | BD855: 0 | BE855: 0 | BF855: 0 | BG855: 0 | BH855: 0 | BI855: 0 | BJ855: 0 | BK855: 0 | BL855: 0 | BM855: 0 | BN855: 0 | BO855: 0 | BP855: 0 | BQ855: 0 | BR855: 0 | BS855: 0 | BT855: 0 | BU855: 0 | BV855: 0 | BW855: 0 | BX855: 0 | BY855: 0 | BZ855: 0 | CA855: 0 | CB855: 0 | CC855: 0 | CD855: 0 | CE855: 0 | CF855: 0 | CG855: 0 | CH855: 0 | CI855: 0 | CJ855: 0 | CK855: 0 | CL855: 0 | CM855: 0 | CN855: 0 | CO855: 0 | CP855: 0 | CQ855: 0 | CR855: 0 | CS855: 0 | CT855: 0 | CU855: 0 | CV855: 0 | CW855: 0 | CX855: 0 | CY855: 0 | CZ855: 0 | DA855: 0 | DB855: 0 | DC855: 0 | DD855: 0 | DE855: 0 | DF855: 0 | DG855: 0 | DH855: 0 | DI855: 0 | DJ855: 0 | DK855: 0 | DL855: 0 | DM855: 0 | DN855: 0 | DO855: 0 | DP855: 0 | DQ855: 0 | DR855: 0 | DS855: 0 | DT855: 0 | DU855: 0 | DV855: 0 | DW855: 0 | DX855: 0 | DZ855: 56 | EA855: SDN10 | EB855: 1 | EC855: 5 | ED855: =EA855&TEXT(EB855,"00")&TEXT(EC855,"00") -> SDN100105 | EE855: 1017.6 | EF855: 10000 | EG855: 10000 | EH855: 10000 | EI855: 10000 | EJ855: 10000 | EK855: 10000 | EL855: 10000 | EM855: 10000 | EN855: 10000 | EO855: 10000 | EP855: 10000 | EQ855: 10000 | ER855: 10000 | ES855: 10000 | ET855: 10000 | EU855: 10000 | EV855: 10000 | EW855: 10000 | EX855: 10000 | EY855: 10000 | EZ855: 10000 | FA855: 10000 | FB855: 10000 | FC855: 10000 | FD855: 0 | FE855: 0 | FF855: 0 | FG855: 0 | FH855: 0 | FI855: 0 | FJ855: 0 | FK855: 0 | FL855: 0 | FM855: 0 | FN855: 0 | FO855: 0 | FP855: 0 | FQ855: 0 | FR855: 0 | FS855: 0 | FT855: 0 | FU855: 0 | FV855: 0 | FW855: 0 | FX855: 0 | FY855: 0 | FZ855: 0 | GA855: 0 | GB855: 0 | GC855: 0 | GD855: 0 | GE855: 0 | GF855: 0 | GG855: 0 | GH855: 0 | GI855: 0 | GJ855: 0 | GK855: 0 | GL855: 0 | GM855: 0 | GN855: 0 | GO855: 0 | GP855: 0 | GQ855: 0 | GR855: 0 | GS855: 0 | GT855: 0 | GU855: 0 | GV855: 0 | GW855: 0 | GX855: 0 | GY855: 0 | GZ855: 0 | HA855: 0 | HB855: 0 | HC855: 0 | HD855: 0 | HE855: 0 | HF855: 0 | HG855: 0 | HH855: 0 | HI855: 0 | HJ855: 0 | HK855: 0 | HL855: 0 | HM855: 0 | HN855: 0 | HO855: 0 | HP855: 0 | HQ855: 0 | HR855: 0 | HS855: 0 | HT855: 0 | HU855: 0 | HV855: 0 | HW855: 0 | HX855: 0 | HY855: 0 | HZ855: 0 | IA855: 0 | IB855: 0 | IC855: 0 | ID855: 0 | IE855: 0 | IF855: 0 | IG855: 0 | IH855: 0 | II855: 0 | IJ855: 0 | IK855: 0
